{
  "type": "Feature",
  "properties": {
    "addr:full":"1395 Atwood Ave Johnston RI 02919",
    "addr:housenumber":"1395",
    "addr:postcode":"02919",
    "addr:street":"Atwood Ave",
    "iso:country":"US",
    "sg:address":"1395 Atwood Ave",
    "sg:city":"Johnston",
    "sg:classifiers":[
        {
            "category":"Restaurant",
            "type":"Food & Drink"
        }
    ],
    "sg:phone":"+1 401 275 0769",
    "sg:postcode":"02919",
    "sg:province":"RI",
    "sg:tags":[
        "shop",
        "coffee"
    ],
    "wof:name":"Brewed Awakenings Inc",
    "wof:placetype":"venue"
},
  "geometry": {"coordinates":[-71.496658,41.817181],"type":"Point"}
}