{
  "type": "Feature",
  "properties": {
    "addr:full":"56 Schoolhouse Rd Warren RI 02885",
    "addr:housenumber":"56",
    "addr:postcode":"02885",
    "addr:street":"Schoolhouse Rd",
    "iso:country":"US",
    "sg:address":"56 Schoolhouse Rd",
    "sg:city":"Warren",
    "sg:classifiers":[
        {
            "category":"Real Estate",
            "subcategory":"Real Estate Agent",
            "type":"Services"
        }
    ],
    "sg:phone":"+1 401 245 1155",
    "sg:postcode":"02885",
    "sg:province":"RI",
    "wof:name":"J & J Realty",
    "wof:placetype":"venue"
},
  "geometry": {"coordinates":[-71.262686,41.740274],"type":"Point"}
}