{
  "type": "Feature",
  "properties": {
    "addr:full":"278 Moonstone Beach Rd Wakefield RI 02879",
    "addr:housenumber":"278",
    "addr:postcode":"02879",
    "addr:street":"Moonstone Beach Rd",
    "iso:country":"US",
    "sg:address":"278 Moonstone Beach Rd",
    "sg:city":"Wakefield",
    "sg:classifiers":[
        {
            "category":"Building & Trades",
            "subcategory":"Construction",
            "type":"Services"
        }
    ],
    "sg:phone":"+1 401 782 2939",
    "sg:postcode":"02879",
    "sg:province":"RI",
    "sg:tags":[
        "house"
    ],
    "wof:name":"Eric T Little Const",
    "wof:placetype":"venue"
},
  "geometry": {"coordinates":[-71.572208,41.383448],"type":"Point"}
}