{
  "type": "Feature",
  "properties": {
    "iso:country":"US",
    "sg:address":"14 Tabor Dr",
    "sg:city":"Johnston",
    "sg:classifiers":[
        {
            "category":"Real Estate",
            "subcategory":"Real Estate Agent",
            "type":"Services"
        }
    ],
    "sg:phone":"+1 401 232 1675",
    "sg:postcode":"02919",
    "sg:province":"RI",
    "wof:name":"Hea Realty Assoc Inc",
    "wof:placetype":"venue"
},
  "geometry": {"coordinates":[-71.490664,41.851123],"type":"Point"}
}