{
  "type": "Feature",
  "properties": {
    "iso:country":"US",
    "sg:address":"231 Quaker Ln",
    "sg:city":"West Warwick",
    "sg:classifiers":[
        {
            "category":"Freight",
            "type":"Transportation"
        }
    ],
    "sg:phone":"+1 401 827 0081",
    "sg:postcode":"02893",
    "sg:province":"RI",
    "sg:tags":[
        "trucking"
    ],
    "wof:name":"CFS Logistics",
    "wof:placetype":"venue"
},
  "geometry": {"coordinates":[-71.50121,41.689042],"type":"Point"}
}