{
  "type": "Feature",
  "properties": {
    "iso:country":"US",
    "sg:address":"847 Atwells Ave",
    "sg:city":"Providence",
    "sg:classifiers":[
        {
            "category":"Real Estate",
            "subcategory":"Real Estate Agent",
            "type":"Services"
        }
    ],
    "sg:phone":"+1 401 751 2567",
    "sg:postcode":"02909",
    "sg:province":"RI",
    "sg:tags":[
        "management"
    ],
    "wof:name":"United Management Group",
    "wof:placetype":"venue"
},
  "geometry": {"coordinates":[-71.445001,41.82494],"type":"Point"}
}