{
  "type": "Feature",
  "properties": {
    "iso:country":"US",
    "sg:address":"396 Manton Ave",
    "sg:city":"Providence",
    "sg:classifiers":[
        {
            "category":"Real Estate",
            "subcategory":"Real Estate Operator",
            "type":"Services"
        }
    ],
    "sg:phone":"+1 401 351 2880",
    "sg:postcode":"02909",
    "sg:province":"RI",
    "sg:tags":[
        "apartment"
    ],
    "sg:website":"http://www.industrialwelderssupply.com",
    "wof:name":"Aec Associates Inc",
    "wof:placetype":"venue"
},
  "geometry": {"coordinates":[-71.452873,41.824662],"type":"Point"}
}