{
  "type": "Feature",
  "properties": {
    "iso:country":"US",
    "sg:address":"763 Westminster St",
    "sg:city":"Providence",
    "sg:classifiers":[
        {
            "category":"Sports & Exercise",
            "subcategory":"Golf",
            "type":"Entertainment"
        }
    ],
    "sg:phone":"+1 401 454 8100",
    "sg:postcode":"02903",
    "sg:province":"RI",
    "sg:tags":[
        "mini"
    ],
    "wof:name":"Monster Entertainment Llc",
    "wof:placetype":"venue"
},
  "geometry": {"coordinates":[-71.420798,41.818088],"type":"Point"}
}