{
  "type": "Feature",
  "properties": {
    "addr:full":"495 Phenix Ave Cranston RI 02921",
    "addr:housenumber":"495",
    "addr:postcode":"02921",
    "addr:street":"Phenix Ave",
    "iso:country":"US",
    "sg:address":"495 Phenix Ave",
    "sg:city":"Cranston",
    "sg:classifiers":[
        {
            "category":"Home & Garden",
            "subcategory":"Garden Supply",
            "type":"Retail Goods"
        }
    ],
    "sg:phone":"+1 401 942 6866",
    "sg:postcode":"02921",
    "sg:province":"RI",
    "sg:tags":[
        "nurseryman"
    ],
    "wof:name":"Fire House Nursery & Garden",
    "wof:placetype":"venue"
},
  "geometry": {"coordinates":[-71.48127599999999,41.773785],"type":"Point"}
}