{
  "type": "Feature",
  "properties": {
    "addr:full":"9 Tilley Ave Newport RI 02840",
    "addr:housenumber":"9",
    "addr:postcode":"02840",
    "addr:street":"Tilley Ave",
    "iso:country":"US",
    "sg:address":"9 Tilley Ave",
    "sg:city":"Newport",
    "sg:classifiers":[
        {
            "category":"Travel",
            "subcategory":"Travel Agent",
            "type":"Entertainment"
        }
    ],
    "sg:phone":"+1 401 847 4168",
    "sg:postcode":"02840",
    "sg:province":"RI",
    "sg:tags":[
        "tours",
        "promoter"
    ],
    "wof:name":"New England Access",
    "wof:placetype":"venue"
},
  "geometry": {"coordinates":[-71.31285800000001,41.498993],"type":"Point"}
}