{
  "type": "Feature",
  "properties": {
    "iso:country":"US",
    "sg:address":"4 Lanni Dr",
    "sg:city":"Pawtucket",
    "sg:classifiers":[
        {
            "category":"Professional",
            "subcategory":"Accounting & Tax Preparation",
            "type":"Services"
        }
    ],
    "sg:phone":"+1 401 724 1590",
    "sg:postcode":"02861",
    "sg:province":"RI",
    "wof:name":"Kathy Cote Bookkeeping",
    "wof:placetype":"venue"
},
  "geometry": {"coordinates":[-71.353528,41.874513],"type":"Point"}
}