{
  "type": "Feature",
  "properties": {
    "iso:country":"US",
    "sg:address":"7 Baldwin Rd",
    "sg:city":"Middletown",
    "sg:classifiers":[
        {
            "category":"Professional",
            "subcategory":"Management & Consulting",
            "type":"Services"
        }
    ],
    "sg:phone":"+1 401 849 1560",
    "sg:postcode":"02842",
    "sg:province":"RI",
    "sg:tags":[
        "consultant",
        "marine",
        "business"
    ],
    "wof:name":"Newport Marine Survey Assoc",
    "wof:placetype":"venue"
},
  "geometry": {"coordinates":[-71.249611,41.511557],"type":"Point"}
}