{
  "type": "Feature",
  "properties": {
    "addr:full":"350 Fair St Warwick RI 02888",
    "addr:housenumber":"350",
    "addr:postcode":"02888",
    "addr:street":"Fair St",
    "iso:country":"US",
    "sg:address":"350 Fair St",
    "sg:city":"Warwick",
    "sg:classifiers":[
        {
            "category":"Organizations",
            "subcategory":"Religious Organization",
            "type":"Services"
        }
    ],
    "sg:phone":"+1 401 467 4895",
    "sg:postcode":"02888",
    "sg:province":"RI",
    "sg:tags":[
        "church"
    ],
    "wof:name":"St Peter's Rectory",
    "wof:placetype":"venue"
},
  "geometry": {"coordinates":[-71.39391500000001,41.754375],"type":"Point"}
}