{
  "type": "Feature",
  "properties": {
    "iso:country":"US",
    "sg:address":"176 1st Ave",
    "sg:city":"East Greenwich",
    "sg:classifiers":[
        {
            "category":"Government",
            "subcategory":"Post Office",
            "type":"Public Place"
        }
    ],
    "sg:phone":"+1 401 884 3962",
    "sg:postcode":"02818",
    "sg:province":"RI",
    "sg:tags":[
        "postal",
        "us"
    ],
    "wof:name":"East Greenwich Post Office",
    "wof:placetype":"venue"
},
  "geometry": {"coordinates":[-71.45796799999999,41.6577],"type":"Point"}
}