{
  "type": "Feature",
  "properties": {
    "addr:full":"61 Vinton St Providence RI 02909",
    "addr:housenumber":"61",
    "addr:postcode":"02909",
    "addr:street":"Vinton St",
    "iso:country":"US",
    "sg:address":"61 Vinton St",
    "sg:city":"Providence",
    "sg:classifiers":[
        {
            "category":"Personal",
            "subcategory":"Beauty Salon",
            "type":"Services"
        }
    ],
    "sg:phone":"+1 401 270 7483",
    "sg:postcode":"02909",
    "sg:province":"RI",
    "wof:name":"Executive Hair Styling",
    "wof:placetype":"venue"
},
  "geometry": {"coordinates":[-71.429486,41.822288],"type":"Point"}
}