{
  "type": "Feature",
  "properties": {
    "iso:country":"US",
    "sg:address":"1942 Smith St",
    "sg:city":"North Providence",
    "sg:classifiers":[
        {
            "category":"Restaurant",
            "type":"Food & Drink"
        }
    ],
    "sg:phone":"+1 401 353 0971",
    "sg:postcode":"02911",
    "sg:province":"RI",
    "sg:tags":[
        "eating"
    ],
    "wof:name":"Carries Seafood Express",
    "wof:placetype":"venue"
},
  "geometry": {"coordinates":[-71.480904,41.856499],"type":"Point"}
}