{
  "type": "Feature",
  "properties": {
    "addr:full":"20 Mechanic St North Smithfield RI 02896",
    "addr:housenumber":"20",
    "addr:postcode":"02896",
    "addr:street":"Mechanic St",
    "iso:country":"US",
    "sg:address":"20 Mechanic St",
    "sg:city":"North Smithfield",
    "sg:classifiers":[
        {
            "category":"Building & Trades",
            "subcategory":"Construction",
            "type":"Services"
        }
    ],
    "sg:phone":"+1 401 636 1380",
    "sg:postcode":"02896",
    "sg:province":"RI",
    "sg:tags":[
        "tile",
        "dealer"
    ],
    "wof:name":"Straight Line Flooring",
    "wof:placetype":"venue"
},
  "geometry": {"coordinates":[-71.583061,42.009316],"type":"Point"}
}