{
  "type": "Feature",
  "properties": {
    "iso:country":"US",
    "sg:address":"227 Wampanoag Trl",
    "sg:city":"Riverside",
    "sg:classifiers":[
        {
            "category":"Professional",
            "subcategory":"Engineering",
            "type":"Services"
        }
    ],
    "sg:phone":"+1 401 438 7711",
    "sg:postcode":"02915",
    "sg:province":"RI",
    "sg:tags":[
        "engineer"
    ],
    "sg:website":"www.geisserengineering.com",
    "wof:name":"Geisser Engineering Corp",
    "wof:placetype":"venue"
},
  "geometry": {"coordinates":[-71.355146,41.796284],"type":"Point"}
}