{
  "type": "Feature",
  "properties": {
    "iso:country":"US",
    "sg:address":"232 Norwood Ave",
    "sg:city":"Cranston",
    "sg:classifiers":[
        {
            "category":"Health Services",
            "subcategory":"Chiropractor",
            "type":"Services"
        }
    ],
    "sg:phone":"+1 401 467 9000",
    "sg:postcode":"02905",
    "sg:province":"RI",
    "wof:name":"Lombardi Chiropractic Ctr",
    "wof:placetype":"venue"
},
  "geometry": {"coordinates":[-71.401095,41.778252],"type":"Point"}
}