{
  "type": "Feature",
  "properties": {
    "iso:country":"US",
    "sg:address":"15 Puritan Ave",
    "sg:city":"Cranston",
    "sg:classifiers":[
        {
            "category":"Professional",
            "subcategory":"Computer Services",
            "type":"Services"
        }
    ],
    "sg:phone":"+1 401 944 8404",
    "sg:postcode":"02920",
    "sg:province":"RI",
    "sg:tags":[
        "consultant",
        "designer"
    ],
    "wof:name":"Village Goldsmith Inc",
    "wof:placetype":"venue"
},
  "geometry": {"coordinates":[-71.452811,41.792911],"type":"Point"}
}