{
  "type": "Feature",
  "properties": {
    "iso:country":"US",
    "sg:address":"169 Main St",
    "sg:city":"Westerly",
    "sg:classifiers":[
        {
            "category":"Restaurant",
            "type":"Food & Drink"
        }
    ],
    "sg:phone":"+1 401 596 7180",
    "sg:postcode":"02891",
    "sg:province":"RI",
    "sg:tags":[
        "eating"
    ],
    "wof:name":"Amanda's Pantry",
    "wof:placetype":"venue"
},
  "geometry": {"coordinates":[-71.831002,41.371082],"type":"Point"}
}