{
  "type": "Feature",
  "properties": {
    "iso:country":"US",
    "sg:address":"39 Sutton St",
    "sg:city":"Providence",
    "sg:classifiers":[
        {
            "category":"Building & Trades",
            "subcategory":"Electrical",
            "type":"Services"
        }
    ],
    "sg:phone":"+1 401 274 2009",
    "sg:postcode":"02903",
    "sg:province":"RI",
    "sg:tags":[
        "electrical",
        "contractor"
    ],
    "wof:name":"Tesla Electric Inc",
    "wof:placetype":"venue"
},
  "geometry": {"coordinates":[-71.429192,41.824486],"type":"Point"}
}