{
  "type": "Feature",
  "properties": {
    "iso:country":"US",
    "sg:address":"249 Academy Ave",
    "sg:city":"Providence",
    "sg:classifiers":[
        {
            "category":"Home & Garden",
            "subcategory":"Hardware",
            "type":"Retail Goods"
        }
    ],
    "sg:phone":"+1 401 351 7207",
    "sg:postcode":"02908",
    "sg:province":"RI",
    "sg:tags":[
        "store"
    ],
    "wof:name":"Alg Window and Glass",
    "wof:placetype":"venue"
},
  "geometry": {"coordinates":[-71.444238,41.831721],"type":"Point"}
}