{
  "type": "Feature",
  "properties": {
    "addr:full":"600 Central Ave Pawtucket RI 02861",
    "addr:housenumber":"600",
    "addr:postcode":"02861",
    "addr:street":"Central Ave",
    "iso:country":"US",
    "sg:address":"600 Central Ave",
    "sg:city":"Pawtucket",
    "sg:classifiers":[
        {
            "category":"Health Services",
            "subcategory":"Chiropractor",
            "type":"Services"
        }
    ],
    "sg:phone":"+1 401 726 1311",
    "sg:postcode":"02861",
    "sg:province":"RI",
    "wof:name":"Grinsell George J Chirprctr",
    "wof:placetype":"venue"
},
  "geometry": {"coordinates":[-71.359802,41.886501],"type":"Point"}
}