{
  "type": "Feature",
  "properties": {
    "addr:full":"167 Stella St Providence RI 02909",
    "addr:housenumber":"167",
    "addr:postcode":"02909",
    "addr:street":"Stella St",
    "iso:country":"US",
    "sg:address":"167 Stella St",
    "sg:city":"Providence",
    "sg:classifiers":[
        {
            "category":"Professional",
            "type":"Services"
        }
    ],
    "sg:phone":"+1 401 270 7114",
    "sg:postcode":"02909",
    "sg:province":"RI",
    "wof:name":"Airwave Network Svc",
    "wof:placetype":"venue"
},
  "geometry": {"coordinates":[-71.46574099999999,41.821766],"type":"Point"}
}