{
  "type": "Feature",
  "properties": {
    "addr:full":"299 Blackstone St Blackstone RI 01504",
    "addr:housenumber":"299",
    "addr:postcode":"01504",
    "addr:street":"Blackstone St",
    "iso:country":"US",
    "sg:address":"299 Blackstone St",
    "sg:city":"Blackstone",
    "sg:classifiers":[
        {
            "category":"Retail",
            "subcategory":"Auto Repair",
            "type":"Services"
        }
    ],
    "sg:phone":"+1   ",
    "sg:postcode":"01504",
    "sg:province":"RI",
    "sg:tags":[
        "general"
    ],
    "wof:name":"Millettes Garage Inc",
    "wof:placetype":"venue"
},
  "geometry": {"coordinates":[-71.52755999999999,42.060565],"type":"Point"}
}