{
  "type": "Feature",
  "properties": {
    "addr:full":"400 Westminster St Providence RI 02903",
    "addr:housenumber":"400",
    "addr:postcode":"02903",
    "addr:street":"Westminster St",
    "iso:country":"US",
    "sg:address":"400 Westminster St",
    "sg:city":"Providence",
    "sg:classifiers":[
        {
            "category":"Professional",
            "subcategory":"Lawyer & Legal Services",
            "type":"Services"
        }
    ],
    "sg:phone":"+1 401 454 0700",
    "sg:postcode":"02903",
    "sg:province":"RI",
    "sg:tags":[
        "attorney"
    ],
    "wof:name":"Hagopian & Hagopian",
    "wof:placetype":"venue"
},
  "geometry": {"coordinates":[-71.41477999999999,41.821346],"type":"Point"}
}