{
  "type": "Feature",
  "properties": {
    "addr:full":"690 Oaklawn Ave Cranston RI 02920",
    "addr:housenumber":"690",
    "addr:postcode":"02920",
    "addr:street":"Oaklawn Ave",
    "iso:country":"US",
    "sg:address":"690 Oaklawn Ave",
    "sg:city":"Cranston",
    "sg:classifiers":[
        {
            "category":"Restaurant",
            "type":"Food & Drink"
        }
    ],
    "sg:menulink":"http://www.allmenus.com/ri/cranston/139895-subway/menu/",
    "sg:phone":"+1 401 275 6650",
    "sg:postcode":"02920",
    "sg:province":"RI",
    "sg:tags":[
        "american",
        "sandwich"
    ],
    "wof:name":"Subway",
    "wof:placetype":"venue"
},
  "geometry": {"coordinates":[-71.476815,41.754002],"type":"Point"}
}