{
  "type": "Feature",
  "properties": {
    "iso:country":"US",
    "sg:address":"271 Main St",
    "sg:city":"Blackstone",
    "sg:classifiers":[
        {
            "category":"Home & Garden",
            "subcategory":"Garden Supply",
            "type":"Retail Goods"
        }
    ],
    "sg:phone":"+1 508 883 7670",
    "sg:postcode":"01504",
    "sg:province":"RI",
    "sg:tags":[
        "lawn",
        "mower"
    ],
    "wof:name":"State Line Power Products",
    "wof:placetype":"venue"
},
  "geometry": {"coordinates":[-71.551728,42.017889],"type":"Point"}
}