{
  "type": "Feature",
  "properties": {
    "iso:country":"US",
    "sg:address":"20 Kenson Dr",
    "sg:city":"East Greenwich",
    "sg:classifiers":[
        {
            "category":"Building & Trades",
            "subcategory":"Construction",
            "type":"Services"
        }
    ],
    "sg:phone":"+1 401 885 8803",
    "sg:postcode":"02818",
    "sg:province":"RI",
    "sg:tags":[
        "house"
    ],
    "wof:name":"Tracy Home Improvements",
    "wof:placetype":"venue"
},
  "geometry": {"coordinates":[-71.466573,41.661855],"type":"Point"}
}