{
  "type": "Feature",
  "properties": {
    "iso:country":"US",
    "sg:address":"1515 Elmwood Ave",
    "sg:city":"Cranston",
    "sg:classifiers":[
        {
            "category":"Building & Trades",
            "subcategory":"Construction",
            "type":"Services"
        }
    ],
    "sg:phone":"+1 401 467 0075",
    "sg:postcode":"02910",
    "sg:province":"RI",
    "sg:tags":[
        "steel",
        "fabrication",
        "welding"
    ],
    "wof:name":"Northstar Steel & Aluminum Inc",
    "wof:placetype":"venue"
},
  "geometry": {"coordinates":[-71.42290199999999,41.773395],"type":"Point"}
}