{
  "type": "Feature",
  "properties": {
    "addr:full":"667 Kingstown Rd Wakefield RI 02879",
    "addr:housenumber":"667",
    "addr:postcode":"02879",
    "addr:street":"Kingstown Rd",
    "iso:country":"US",
    "sg:address":"667 Kingstown Rd",
    "sg:city":"Wakefield",
    "sg:classifiers":[
        {
            "category":"Food & Beverages",
            "subcategory":"Liquor & Beverages",
            "type":"Retail Goods"
        }
    ],
    "sg:phone":"+1 401 783 4555",
    "sg:postcode":"02879",
    "sg:province":"RI",
    "wof:name":"Wakefield Liquors Inc",
    "wof:placetype":"venue"
},
  "geometry": {"coordinates":[-71.48872299999999,41.442274],"type":"Point"}
}