{
  "type": "Feature",
  "properties": {
    "addr:full":"15 Sunset Dr Smithfield RI 02917",
    "addr:housenumber":"15",
    "addr:postcode":"02917",
    "addr:street":"Sunset Dr",
    "iso:country":"US",
    "sg:address":"15 Sunset Dr",
    "sg:city":"Smithfield",
    "sg:classifiers":[
        {
            "category":"Recreation",
            "type":"Entertainment"
        }
    ],
    "sg:phone":"+1 401 232 5325",
    "sg:postcode":"02917",
    "sg:province":"RI",
    "wof:name":"Seaworthy Yacht Charters LLC",
    "wof:placetype":"venue"
},
  "geometry": {"coordinates":[-71.50902499999999,41.900712],"type":"Point"}
}