{
  "type": "Feature",
  "properties": {
    "iso:country":"US",
    "sg:address":"150 Ferry Rd",
    "sg:city":"Bristol",
    "sg:classifiers":[
        {
            "category":"Travel",
            "subcategory":"Hotels & Motels",
            "type":"Entertainment"
        }
    ],
    "sg:phone":"+1 401 254 5056",
    "sg:postcode":"02809",
    "sg:province":"RI",
    "sg:tags":[
        "accommodation"
    ],
    "wof:name":"Swanson House",
    "wof:placetype":"venue"
},
  "geometry": {"coordinates":[-71.266098,41.657862],"type":"Point"}
}