{
  "type": "Feature",
  "properties": {
    "iso:country":"US",
    "sg:address":"71 Arbutus Trl",
    "sg:city":"Charlestown",
    "sg:classifiers":[
        {
            "category":"Shopping",
            "subcategory":"Jewelry",
            "type":"Retail Goods"
        }
    ],
    "sg:phone":"+1 401 364 8814",
    "sg:postcode":"02813",
    "sg:province":"RI",
    "wof:name":"Linda Boback Designs",
    "wof:placetype":"venue"
},
  "geometry": {"coordinates":[-71.624358,41.405281],"type":"Point"}
}