{
  "type": "Feature",
  "properties": {
    "addr:full":"8 Freebody St Newport RI 02840",
    "addr:housenumber":"8",
    "addr:postcode":"02840",
    "addr:street":"Freebody St",
    "iso:country":"US",
    "sg:address":"8 Freebody St",
    "sg:city":"Newport",
    "sg:classifiers":[
        {
            "category":"Banks & Credit Unions",
            "subcategory":"Bank",
            "type":"Services"
        }
    ],
    "sg:phone":"+1 401 619 0300",
    "sg:postcode":"02840",
    "sg:province":"RI",
    "sg:tags":[
        "loan",
        "real estate"
    ],
    "wof:name":"Harvest Mortgage",
    "wof:placetype":"venue"
},
  "geometry": {"coordinates":[-71.306056,41.481745],"type":"Point"}
}