{
  "type": "Feature",
  "properties": {
    "iso:country":"US",
    "sg:address":"100 Main St",
    "sg:city":"Westerly",
    "sg:classifiers":[
        {
            "category":"Shopping",
            "subcategory":"Florist",
            "type":"Retail Goods"
        }
    ],
    "sg:phone":"+1 401 596 1011",
    "sg:postcode":"02891",
    "sg:province":"RI",
    "wof:name":"Celebrations Flower Shop",
    "wof:placetype":"venue"
},
  "geometry": {"coordinates":[-71.8312,41.37542],"type":"Point"}
}