{
  "type": "Feature",
  "properties": {
    "iso:country":"US",
    "sg:address":"2374 Mendon Rd",
    "sg:city":"Cumberland",
    "sg:classifiers":[
        {
            "category":"Sports & Exercise",
            "subcategory":"Gym",
            "type":"Entertainment"
        }
    ],
    "sg:phone":"+1 401 405 0819",
    "sg:postcode":"02864",
    "sg:province":"RI",
    "sg:tags":[
        "trainer"
    ],
    "wof:name":"It's My Health Wellcare",
    "wof:placetype":"venue"
},
  "geometry": {"coordinates":[-71.44328400000001,41.95866],"type":"Point"}
}