{
  "type": "Feature",
  "properties": {
    "iso:country":"US",
    "sg:address":"660 Hartford Ave",
    "sg:city":"Providence",
    "sg:classifiers":[
        {
            "category":"Retail",
            "subcategory":"Animal Services",
            "type":"Services"
        }
    ],
    "sg:phone":"+1 401 338 9896",
    "sg:postcode":"02909",
    "sg:province":"RI",
    "sg:tags":[
        "pet"
    ],
    "sg:website":"Www.K-9Times.Com",
    "wof:name":"K-9 Times.Com",
    "wof:placetype":"venue"
},
  "geometry": {"coordinates":[-71.466886,41.819629],"type":"Point"}
}