{
  "type": "Feature",
  "properties": {
    "addr:full":"807 Old Smithfield Rd North Smithfield RI 02896",
    "addr:housenumber":"807",
    "addr:postcode":"02896",
    "addr:street":"Old Smithfield Rd",
    "iso:country":"US",
    "sg:address":"807 Old Smithfield Rd",
    "sg:city":"North Smithfield",
    "sg:classifiers":[
        {
            "category":"Professional",
            "subcategory":"Testing Lab",
            "type":"Services"
        }
    ],
    "sg:phone":"+1 401 765 3483",
    "sg:postcode":"02896",
    "sg:province":"RI",
    "sg:tags":[
        "laboratory"
    ],
    "wof:name":"Abbott Laboratories",
    "wof:placetype":"venue"
},
  "geometry": {"coordinates":[-71.50414000000001,41.970926],"type":"Point"}
}