{
  "type": "Feature",
  "properties": {
    "iso:country":"US",
    "sg:address":"9 Woodland Ave",
    "sg:city":"Coventry",
    "sg:classifiers":[
        {
            "category":"Professional",
            "type":"Services"
        }
    ],
    "sg:phone":"+1 401 821 9444",
    "sg:postcode":"02816",
    "sg:province":"RI",
    "sg:tags":[
        "note",
        "cards",
        "specialized",
        "artwork"
    ],
    "wof:name":"Brush and Lens",
    "wof:placetype":"venue"
},
  "geometry": {"coordinates":[-71.56631400000001,41.682662],"type":"Point"}
}