{
  "type": "Feature",
  "properties": {
    "iso:country":"US",
    "sg:address":"5 George Waterman Rd",
    "sg:city":"Johnston",
    "sg:classifiers":[
        {
            "category":"Shopping",
            "subcategory":"Florist",
            "type":"Retail Goods"
        }
    ],
    "sg:phone":"+1 401 232 5353",
    "sg:postcode":"02919",
    "sg:province":"RI",
    "wof:name":"Flowers By Semia",
    "wof:placetype":"venue"
},
  "geometry": {"coordinates":[-71.483538,41.839263],"type":"Point"}
}