{
  "type": "Feature",
  "properties": {
    "iso:country":"US",
    "sg:address":"93 Abram St",
    "sg:city":"Pawtucket",
    "sg:classifiers":[
        {
            "category":"Autos & Motor Vehicles",
            "subcategory":"Automobile Sales",
            "type":"Retail Goods"
        },
        {
            "category":"Airline",
            "type":"Transportation"
        }
    ],
    "sg:phone":"+1 800 533 0142",
    "sg:postcode":"02860",
    "sg:province":"RI",
    "sg:tags":[
        "shuttle",
        "airport",
        "limo"
    ],
    "wof:name":"Airport Express Direct",
    "wof:placetype":"venue"
},
  "geometry": {"coordinates":[-71.377639,41.891473],"type":"Point"}
}