{
  "type": "Feature",
  "properties": {
    "addr:full":"613 Cranston St Providence RI 02907",
    "addr:housenumber":"613",
    "addr:postcode":"02907",
    "addr:street":"Cranston St",
    "iso:country":"US",
    "sg:address":"613 Cranston St",
    "sg:city":"Providence",
    "sg:classifiers":[
        {
            "category":"Shopping",
            "subcategory":"Pharmacy",
            "type":"Retail Goods"
        }
    ],
    "sg:phone":"+1 401 521 9660",
    "sg:postcode":"02907",
    "sg:province":"RI",
    "wof:name":"Prime Drug",
    "wof:placetype":"venue"
},
  "geometry": {"coordinates":[-71.436295,41.806339],"type":"Point"}
}