{
  "type": "Feature",
  "properties": {
    "iso:country":"US",
    "sg:address":"70 Narragansett Park Dr",
    "sg:city":"Rumford",
    "sg:classifiers":[
        {
            "category":"Restaurant",
            "type":"Food & Drink"
        }
    ],
    "sg:phone":"+1 401 431 1470",
    "sg:postcode":"02916",
    "sg:province":"RI",
    "sg:tags":[
        "pizza"
    ],
    "wof:name":"Bertucci's Brick Oven Rstrnt",
    "wof:placetype":"venue"
},
  "geometry": {"coordinates":[-71.351748,41.858165],"type":"Point"}
}