{
  "type": "Feature",
  "properties": {
    "iso:country":"US",
    "sg:address":"1526 Louisquisset Pike",
    "sg:city":"Lincoln",
    "sg:classifiers":[
        {
            "category":"Retail",
            "subcategory":"Animal Services",
            "type":"Services"
        }
    ],
    "sg:phone":"+1 401 729 4997",
    "sg:postcode":"02865",
    "sg:province":"RI",
    "wof:name":"C and S Whiteoak Kennels",
    "wof:placetype":"venue"
},
  "geometry": {"coordinates":[-71.43976000000001,41.886056],"type":"Point"}
}