{
  "type": "Feature",
  "properties": {
    "iso:country":"US",
    "sg:address":"615 Central Ave",
    "sg:city":"Pawtucket",
    "sg:classifiers":[
        {
            "category":"Restaurant",
            "type":"Food & Drink"
        }
    ],
    "sg:phone":"+1 401 726 6179",
    "sg:postcode":"02861",
    "sg:province":"RI",
    "sg:tags":[
        "eating"
    ],
    "wof:name":"Beispring Inc",
    "wof:placetype":"venue"
},
  "geometry": {"coordinates":[-71.359787,41.886457],"type":"Point"}
}