{
  "type": "Feature",
  "properties": {
    "iso:country":"US",
    "sg:address":"1028 Tiogue Ave",
    "sg:city":"Coventry",
    "sg:classifiers":[
        {
            "category":"Restaurant",
            "type":"Food & Drink"
        }
    ],
    "sg:phone":"+1 401 828 3127",
    "sg:postcode":"02816",
    "sg:province":"RI",
    "wof:name":"China Star",
    "wof:placetype":"venue"
},
  "geometry": {"coordinates":[-71.579211,41.679236],"type":"Point"}
}