{
  "type": "Feature",
  "properties": {
    "iso:country":"US",
    "sg:address":"680 Warren Ave",
    "sg:city":"East Providence",
    "sg:classifiers":[
        {
            "category":"Professional",
            "subcategory":"Computer Services",
            "type":"Services"
        }
    ],
    "sg:phone":"+1 401 434 2762",
    "sg:postcode":"02914",
    "sg:province":"RI",
    "sg:tags":[
        "programing",
        "custom"
    ],
    "wof:name":"Data Pro",
    "wof:placetype":"venue"
},
  "geometry": {"coordinates":[-71.354395,41.810209],"type":"Point"}
}