{
  "type": "Feature",
  "properties": {
    "iso:country":"US",
    "sg:address":"101 Comstock Pkwy",
    "sg:city":"Cranston",
    "sg:classifiers":[
        {
            "category":"Building & Trades",
            "subcategory":"Construction",
            "type":"Services"
        }
    ],
    "sg:phone":"+1 401 944 0336",
    "sg:postcode":"02921",
    "sg:province":"RI",
    "sg:tags":[
        "painter"
    ],
    "wof:name":"T & T Painting Contractors",
    "wof:placetype":"venue"
},
  "geometry": {"coordinates":[-71.51538499999999,41.782412],"type":"Point"}
}