{
  "type": "Feature",
  "properties": {
    "addr:full":"517 Main St East Greenwich RI 02818",
    "addr:housenumber":"517",
    "addr:postcode":"02818",
    "addr:street":"Main St",
    "iso:country":"US",
    "sg:address":"517 Main St",
    "sg:city":"East Greenwich",
    "sg:classifiers":[
        {
            "category":"Autos & Motor Vehicles",
            "subcategory":"Boat Sales",
            "type":"Retail Goods"
        }
    ],
    "sg:phone":"+1 401 886 6790",
    "sg:postcode":"02818",
    "sg:province":"RI",
    "sg:tags":[
        "equipment",
        "marine",
        "supply"
    ],
    "sg:website":"www.boatus.com",
    "wof:name":"Boat/US Marine Ctr",
    "wof:placetype":"venue"
},
  "geometry": {"coordinates":[-71.452416,41.656859],"type":"Point"}
}