{
  "type": "Feature",
  "properties": {
    "iso:country":"US",
    "sg:address":"278 Lincoln Ave",
    "sg:city":"Warwick",
    "sg:phone":"+1 401 536 9917",
    "sg:postcode":"02888",
    "sg:province":"RI",
    "wof:name":"West Bay Martial Arts Club",
    "wof:placetype":"venue"
},
  "geometry": {"coordinates":[-71.437828,41.74297],"type":"Point"}
}