{
  "type": "Feature",
  "properties": {
    "iso:country":"US",
    "sg:address":"336 Dexter St",
    "sg:city":"Central Falls",
    "sg:classifiers":[
        {
            "category":"Wholesale",
            "subcategory":"Non-durable Goods",
            "type":"Manufacturing & Wholesale Goods"
        }
    ],
    "sg:phone":"+1 401 726 9726",
    "sg:postcode":"02863",
    "sg:province":"RI",
    "sg:tags":[
        "ice"
    ],
    "wof:name":"Hilltop Ice",
    "wof:placetype":"venue"
},
  "geometry": {"coordinates":[-71.39297500000001,41.883251],"type":"Point"}
}