{
  "type": "Feature",
  "properties": {
    "addr:full":"105 Main St Slatersville RI 02876",
    "addr:housenumber":"105",
    "addr:postcode":"02876",
    "addr:street":"Main St",
    "iso:country":"US",
    "sg:address":"105 Main St",
    "sg:city":"Slatersville",
    "sg:classifiers":[
        {
            "category":"Mining & Drilling",
            "type":"Manufacturing & Wholesale Goods"
        },
        {
            "category":"Wholesale",
            "subcategory":"Machinery & Supplies",
            "type":"Manufacturing & Wholesale Goods"
        },
        {
            "category":"Home & Garden",
            "subcategory":"Hardware",
            "type":"Retail Goods"
        },
        {
            "category":"Utilities",
            "subcategory":"Water",
            "type":"Services"
        }
    ],
    "sg:phone":"+1 401 766 2832",
    "sg:postcode":"02876",
    "sg:province":"RI",
    "sg:tags":[
        "filtration",
        "boring",
        "well",
        "contractor",
        "equipment",
        "pump",
        "purification"
    ],
    "wof:name":"A & J Well CO Inc",
    "wof:placetype":"venue"
},
  "geometry": {"coordinates":[-71.587407,41.996145],"type":"Point"}
}