{
  "type": "Feature",
  "properties": {
    "addr:full":"49 Weybosset St Providence RI 02903",
    "addr:housenumber":"49",
    "addr:postcode":"02903",
    "addr:street":"Weybosset St",
    "iso:country":"US",
    "sg:address":"49 Weybosset St",
    "sg:city":"Providence",
    "sg:classifiers":[
        {
            "category":"Professional",
            "subcategory":"Research",
            "type":"Services"
        }
    ],
    "sg:phone":"+1 401 351 5951",
    "sg:postcode":"02903",
    "sg:province":"RI",
    "sg:tags":[
        "foundation",
        "philanthropic"
    ],
    "wof:name":"Feed Thier Dreams Childrens",
    "wof:placetype":"venue"
},
  "geometry": {"coordinates":[-71.41027699999999,41.82357],"type":"Point"}
}