{
  "type": "Feature",
  "properties": {
    "iso:country":"US",
    "sg:address":"671 Broadway",
    "sg:city":"Pawtucket",
    "sg:classifiers":[
        {
            "category":"Restaurant",
            "type":"Food & Drink"
        }
    ],
    "sg:phone":"+1 401 722 3970",
    "sg:postcode":"02860",
    "sg:province":"RI",
    "sg:tags":[
        "eating"
    ],
    "wof:name":"Absolute Catering",
    "wof:placetype":"venue"
},
  "geometry": {"coordinates":[-71.372704,41.891639],"type":"Point"}
}