{
  "type": "Feature",
  "properties": {
    "iso:country":"US",
    "sg:address":"56 Stilson Rd",
    "sg:city":"Wyoming",
    "sg:classifiers":[
        {
            "category":"Manufacturing",
            "subcategory":"Tools & Machinery",
            "type":"Manufacturing & Wholesale Goods"
        }
    ],
    "sg:phone":"+1 401 539 2062",
    "sg:postcode":"02898",
    "sg:province":"RI",
    "sg:tags":[
        "machine",
        "shop"
    ],
    "wof:name":"RKH Machine",
    "wof:placetype":"venue"
},
  "geometry": {"coordinates":[-71.686278,41.514645],"type":"Point"}
}