{
  "type": "Feature",
  "properties": {
    "iso:country":"US",
    "sg:address":"1116 Cranston St",
    "sg:city":"Cranston",
    "sg:classifiers":[
        {
            "category":"Retail",
            "subcategory":"Self-service Laundry",
            "type":"Services"
        }
    ],
    "sg:phone":"+1 401 943 8081",
    "sg:postcode":"02920",
    "sg:province":"RI",
    "wof:name":"Classic Laundromat",
    "wof:placetype":"venue"
},
  "geometry": {"coordinates":[-71.44903100000001,41.79631],"type":"Point"}
}