{
  "type": "Feature",
  "properties": {
    "addr:full":"415 Station St Cranston RI 02910",
    "addr:housenumber":"415",
    "addr:postcode":"02910",
    "addr:street":"Station St",
    "iso:country":"US",
    "sg:address":"415 Station St",
    "sg:city":"Cranston",
    "sg:classifiers":[
        {
            "category":"Manufacturing",
            "subcategory":"Metals",
            "type":"Manufacturing & Wholesale Goods"
        }
    ],
    "sg:phone":"+1 401 461 8220",
    "sg:postcode":"02910",
    "sg:province":"RI",
    "sg:tags":[
        "stamping"
    ],
    "sg:website":"www.sjoberginc.com",
    "wof:name":"C Sjoberg & Son Inc",
    "wof:placetype":"venue"
},
  "geometry": {"coordinates":[-71.425707,41.774397],"type":"Point"}
}