{
  "type": "Feature",
  "properties": {
    "addr:full":"903 Warwick Ave Warwick RI 02888",
    "addr:housenumber":"903",
    "addr:postcode":"02888",
    "addr:street":"Warwick Ave",
    "iso:country":"US",
    "sg:address":"903 Warwick Ave",
    "sg:city":"Warwick",
    "sg:classifiers":[
        {
            "category":"Building & Trades",
            "subcategory":"Construction",
            "type":"Services"
        }
    ],
    "sg:phone":"+1 401 461 8570",
    "sg:postcode":"02888",
    "sg:province":"RI",
    "sg:tags":[
        "company"
    ],
    "wof:name":"D' Ambra Construction",
    "wof:placetype":"venue"
},
  "geometry": {"coordinates":[-71.404107,41.750776],"type":"Point"}
}