{
  "type": "Feature",
  "properties": {
    "iso:country":"US",
    "sg:address":"659 Diamond Hill Rd",
    "sg:city":"Woonsocket",
    "sg:phone":"+1 401 762 2895",
    "sg:postcode":"02895",
    "sg:province":"RI",
    "sg:tags":[
        "oil"
    ],
    "wof:name":"John R Bileau Oil Co Inc",
    "wof:placetype":"venue"
},
  "geometry": {"coordinates":[-71.493225,42.015448],"type":"Point"}
}