{
  "type": "Feature",
  "properties": {
    "addr:full":"68 Taunton Ave East Providence RI 02914",
    "addr:housenumber":"68",
    "addr:postcode":"02914",
    "addr:street":"Taunton Ave",
    "iso:country":"US",
    "sg:address":"68 Taunton Ave",
    "sg:city":"East Providence",
    "sg:classifiers":[
        {
            "category":"Banks & Credit Unions",
            "subcategory":"Bank",
            "type":"Services"
        }
    ],
    "sg:phone":"+1 401 383 4444",
    "sg:postcode":"02914",
    "sg:province":"RI",
    "sg:tags":[
        "mortgage",
        "loan",
        "broker",
        "real estate"
    ],
    "wof:name":"Hallmark Mortgage Inc",
    "wof:placetype":"venue"
},
  "geometry": {"coordinates":[-71.379856,41.819641],"type":"Point"}
}