{
  "type": "Feature",
  "properties": {
    "iso:country":"US",
    "sg:address":"400 Bald Hill Rd",
    "sg:city":"Warwick",
    "sg:classifiers":[
        {
            "category":"Health Services",
            "subcategory":"Doctor",
            "type":"Services"
        }
    ],
    "sg:phone":"+1 401 738 7001",
    "sg:postcode":"02886",
    "sg:province":"RI",
    "sg:tags":[
        "physician",
        "surgeon"
    ],
    "wof:name":"Glenn S Prescod MD",
    "wof:placetype":"venue"
},
  "geometry": {"coordinates":[-71.47998699999999,41.726538],"type":"Point"}
}