{
  "type": "Feature",
  "properties": {
    "iso:country":"US",
    "sg:address":"1596 Broad St",
    "sg:city":"Cranston",
    "sg:classifiers":[
        {
            "category":"Health Services",
            "subcategory":"Doctor",
            "type":"Services"
        }
    ],
    "sg:phone":"+1 401 461 5400",
    "sg:postcode":"02905",
    "sg:province":"RI",
    "sg:tags":[
        "physician",
        "surgeon"
    ],
    "wof:name":"Primary Care Med Assoc Inc",
    "wof:placetype":"venue"
},
  "geometry": {"coordinates":[-71.40109699999999,41.783267],"type":"Point"}
}