{
  "type": "Feature",
  "properties": {
    "addr:full":"505 Central Ave Pawtucket RI 02861",
    "addr:housenumber":"505",
    "addr:postcode":"02861",
    "addr:street":"Central Ave",
    "iso:country":"US",
    "sg:address":"505 Central Ave",
    "sg:city":"Pawtucket",
    "sg:classifiers":[
        {
            "category":"Manufacturing",
            "subcategory":"Chemicals & Compounds",
            "type":"Manufacturing & Wholesale Goods"
        }
    ],
    "sg:phone":"+1 401 725 8000",
    "sg:postcode":"02861",
    "sg:province":"RI",
    "sg:tags":[
        "shoe",
        "store",
        "plastic"
    ],
    "sg:website":"www.teknorapex.com",
    "wof:name":"Teknor Apex Co",
    "wof:placetype":"venue"
},
  "geometry": {"coordinates":[-71.36387999999999,41.885474],"type":"Point"}
}