{
  "type": "Feature",
  "properties": {
    "iso:country":"US",
    "sg:address":"261 S Main St",
    "sg:city":"Woonsocket",
    "sg:classifiers":[
        {
            "category":"Restaurant",
            "type":"Food & Drink"
        }
    ],
    "sg:phone":"+1 401 769 7571",
    "sg:postcode":"02895",
    "sg:province":"RI",
    "wof:name":"Perfect Pizza",
    "wof:placetype":"venue"
},
  "geometry": {"coordinates":[-71.520218,41.997695],"type":"Point"}
}