{
  "type": "Feature",
  "properties": {
    "iso:country":"US",
    "sg:address":"100 Gaspee St",
    "sg:city":"Providence",
    "sg:classifiers":[
        {
            "category":"Local Transit",
            "type":"Transportation"
        }
    ],
    "sg:phone":"+1 617 222 3200",
    "sg:postcode":"02903",
    "sg:province":"RI",
    "sg:tags":[
        "public"
    ],
    "sg:website":"www.mbta.com",
    "wof:name":"MBTA",
    "wof:placetype":"venue"
},
  "geometry": {"coordinates":[-71.413321,41.829283],"type":"Point"}
}