{
  "type": "Feature",
  "properties": {
    "addr:full":"475 Smithfield Ave Pawtucket RI 02860",
    "addr:housenumber":"475",
    "addr:postcode":"02860",
    "addr:street":"Smithfield Ave",
    "iso:country":"US",
    "sg:address":"475 Smithfield Ave",
    "sg:city":"Pawtucket",
    "sg:classifiers":[
        {
            "category":"Home & Garden",
            "subcategory":"Home Furnishings",
            "type":"Retail Goods"
        }
    ],
    "sg:phone":"+1 401 723 4400",
    "sg:postcode":"02860",
    "sg:province":"RI",
    "sg:tags":[
        "cutlery",
        "mfg"
    ],
    "wof:name":"General Services Inc",
    "wof:placetype":"venue"
},
  "geometry": {"coordinates":[-71.41432399999999,41.874056],"type":"Point"}
}