{
  "type": "Feature",
  "properties": {
    "iso:country":"US",
    "sg:address":"99 Brownlee Blvd",
    "sg:city":"Warwick",
    "sg:classifiers":[
        {
            "category":"Building & Trades",
            "subcategory":"Pest Control",
            "type":"Services"
        }
    ],
    "sg:phone":"+1 401 738 3766",
    "sg:postcode":"02886",
    "sg:province":"RI",
    "wof:name":"Paints Pro",
    "wof:placetype":"venue"
},
  "geometry": {"coordinates":[-71.452309,41.702293],"type":"Point"}
}