{
  "type": "Feature",
  "properties": {
    "iso:country":"US",
    "sg:address":"7 Mill Rd",
    "sg:city":"Foster",
    "sg:classifiers":[
        {
            "category":"Professional",
            "subcategory":"Art Services",
            "type":"Services"
        }
    ],
    "sg:phone":"+1 401 647 0684",
    "sg:postcode":"02825",
    "sg:province":"RI",
    "sg:tags":[
        "commercial",
        "design"
    ],
    "wof:name":"Michele McGrath",
    "wof:placetype":"venue"
},
  "geometry": {"coordinates":[-71.70932999999999,41.791943],"type":"Point"}
}