{
  "type": "Feature",
  "properties": {
    "addr:full":"107 Waterman Ave East Providence RI 02914",
    "addr:housenumber":"107",
    "addr:postcode":"02914",
    "addr:street":"Waterman Ave",
    "iso:country":"US",
    "sg:address":"107 Waterman Ave",
    "sg:city":"East Providence",
    "sg:classifiers":[
        {
            "category":"Education",
            "subcategory":"Music School",
            "type":"Public Place"
        }
    ],
    "sg:phone":"+1 401 434 1841",
    "sg:postcode":"02914",
    "sg:province":"RI",
    "sg:tags":[
        "instrument",
        "teacher",
        "musical"
    ],
    "wof:name":"Ye Olde Piano Shoppe",
    "wof:placetype":"venue"
},
  "geometry": {"coordinates":[-71.37491799999999,41.823894],"type":"Point"}
}