{
  "type": "Feature",
  "properties": {
    "iso:country":"US",
    "sg:address":"273 N Farm Dr",
    "sg:city":"Bristol",
    "sg:classifiers":[
        {
            "category":"Professional",
            "subcategory":"Management & Consulting",
            "type":"Services"
        }
    ],
    "sg:phone":"+1 401 254 9712",
    "sg:postcode":"02809",
    "sg:province":"RI",
    "sg:tags":[
        "business"
    ],
    "wof:name":"Danzberger & Associates",
    "wof:placetype":"venue"
},
  "geometry": {"coordinates":[-71.281285,41.707819],"type":"Point"}
}