{
  "type": "Feature",
  "properties": {
    "addr:full":"39 Putnam Pike Johnston RI 02919",
    "addr:housenumber":"39",
    "addr:postcode":"02919",
    "addr:street":"Putnam Pike",
    "iso:country":"US",
    "sg:address":"39 Putnam Pike",
    "sg:city":"Johnston",
    "sg:classifiers":[
        {
            "category":"Shopping",
            "type":"Retail Goods"
        }
    ],
    "sg:phone":"+1 401 231 5710",
    "sg:postcode":"02919",
    "sg:province":"RI",
    "sg:tags":[
        "pet",
        "shop"
    ],
    "wof:name":"Pure Paradise Pets",
    "wof:placetype":"venue"
},
  "geometry": {"coordinates":[-71.49085599999999,41.860956],"type":"Point"}
}