{
  "type": "Feature",
  "properties": {
    "iso:country":"US",
    "sg:address":"103 Sayles St",
    "sg:city":"Providence",
    "sg:classifiers":[
        {
            "category":"Retail",
            "subcategory":"Auto Repair",
            "type":"Services"
        }
    ],
    "sg:phone":"+1 401 781 5722",
    "sg:postcode":"02905",
    "sg:province":"RI",
    "sg:tags":[
        "body"
    ],
    "wof:name":"Sunset Autobody",
    "wof:placetype":"venue"
},
  "geometry": {"coordinates":[-71.404704,41.804846],"type":"Point"}
}