{
  "type": "Feature",
  "properties": {
    "iso:country":"US",
    "sg:address":"1086 Willett Ave",
    "sg:city":"Riverside",
    "sg:classifiers":[
        {
            "category":"Personal",
            "type":"Services"
        }
    ],
    "sg:phone":"+1 401 433 0015",
    "sg:postcode":"02915",
    "sg:province":"RI",
    "wof:name":"Rhonda & Company",
    "wof:placetype":"venue"
},
  "geometry": {"coordinates":[-71.342944,41.759214],"type":"Point"}
}