{
  "type": "Feature",
  "properties": {
    "iso:country":"US",
    "sg:address":"20 Commercial Way",
    "sg:city":"East Providence",
    "sg:classifiers":[
        {
            "category":"Shopping",
            "subcategory":"Jewelry",
            "type":"Retail Goods"
        }
    ],
    "sg:phone":"+1 401 438 7925",
    "sg:postcode":"02914",
    "sg:province":"RI",
    "wof:name":"Barlow Designs Inc",
    "wof:placetype":"venue"
},
  "geometry": {"coordinates":[-71.34884,41.81396],"type":"Point"}
}