{
  "type": "Feature",
  "properties": {
    "addr:full":"65 Green St Wakefield RI 02879",
    "addr:housenumber":"65",
    "addr:postcode":"02879",
    "addr:street":"Green St",
    "iso:country":"US",
    "sg:address":"65 Green St",
    "sg:city":"Wakefield",
    "sg:classifiers":[
        {
            "category":"Building & Trades",
            "subcategory":"Plumbing",
            "type":"Services"
        }
    ],
    "sg:phone":"+1 401 783 1790",
    "sg:postcode":"02879",
    "sg:province":"RI",
    "sg:tags":[
        "heating",
        "contractor"
    ],
    "wof:name":"Harris Plumbing & Heating Inc",
    "wof:placetype":"venue"
},
  "geometry": {"coordinates":[-71.49795399999999,41.45298],"type":"Point"}
}