{
  "type": "Feature",
  "properties": {
    "iso:country":"US",
    "sg:address":"110 Main St",
    "sg:city":"Wakefield",
    "sg:classifiers":[
        {
            "category":"Professional",
            "subcategory":"Lawyer & Legal Services",
            "type":"Services"
        }
    ],
    "sg:phone":"+1 401 783 9333",
    "sg:postcode":"02879",
    "sg:province":"RI",
    "sg:tags":[
        "attorney"
    ],
    "wof:name":"John V Mc Closkey",
    "wof:placetype":"venue"
},
  "geometry": {"coordinates":[-71.49209500000001,41.441047],"type":"Point"}
}