{
  "type": "Feature",
  "properties": {
    "iso:country":"US",
    "sg:address":"1 Pocasset Ave",
    "sg:city":"Providence",
    "sg:classifiers":[
        {
            "category":"Restaurant",
            "type":"Food & Drink"
        }
    ],
    "sg:phone":"+1 401 946 8970",
    "sg:postcode":"02909",
    "sg:province":"RI",
    "wof:name":"Long River",
    "wof:placetype":"venue"
},
  "geometry": {"coordinates":[-71.448364,41.813342],"type":"Point"}
}