{
  "type": "Feature",
  "properties": {
    "addr:full":"87 Abbott St Providence RI 02906",
    "addr:housenumber":"87",
    "addr:postcode":"02906",
    "addr:street":"Abbott St",
    "iso:country":"US",
    "sg:address":"87 Abbott St",
    "sg:city":"Providence",
    "sg:classifiers":[
        {
            "category":"Professional",
            "subcategory":"Computer Services",
            "type":"Services"
        }
    ],
    "sg:phone":"+1 401 421 3971",
    "sg:postcode":"02906",
    "sg:province":"RI",
    "sg:tags":[
        "programing",
        "custom"
    ],
    "wof:name":"Progressive Systems Technology",
    "wof:placetype":"venue"
},
  "geometry": {"coordinates":[-71.40667999999999,41.842611],"type":"Point"}
}