{
  "type": "Feature",
  "properties": {
    "iso:country":"US",
    "sg:address":"95 Old Boston Neck Rd",
    "sg:city":"Narragansett",
    "sg:classifiers":[
        {
            "category":"Professional",
            "subcategory":"Management & Consulting",
            "type":"Services"
        }
    ],
    "sg:phone":"+1 401 789 7662",
    "sg:postcode":"02882",
    "sg:province":"RI",
    "wof:name":"Capers Jones & Associates",
    "wof:placetype":"venue"
},
  "geometry": {"coordinates":[-71.442566,41.450039],"type":"Point"}
}