{
  "type": "Feature",
  "properties": {
    "iso:country":"US",
    "sg:address":"172 Cushing St",
    "sg:city":"Providence",
    "sg:classifiers":[
        {
            "category":"Health Services",
            "subcategory":"Health Practitioner",
            "type":"Services"
        }
    ],
    "sg:phone":"+1 401 273 7736",
    "sg:postcode":"02906",
    "sg:province":"RI",
    "sg:tags":[
        "psychologist"
    ],
    "wof:name":"Graham C Jelley",
    "wof:placetype":"venue"
},
  "geometry": {"coordinates":[-71.39877199999999,41.83025],"type":"Point"}
}