{
  "type": "Feature",
  "properties": {
    "addr:full":"200 Lavan St Warwick RI 02888",
    "addr:housenumber":"200",
    "addr:postcode":"02888",
    "addr:street":"Lavan St",
    "iso:country":"US",
    "sg:address":"200 Lavan St",
    "sg:city":"Warwick",
    "sg:classifiers":[
        {
            "category":"Manufacturing",
            "subcategory":"Tools & Machinery",
            "type":"Manufacturing & Wholesale Goods"
        }
    ],
    "sg:phone":"+1 401 781 5300",
    "sg:postcode":"02888",
    "sg:province":"RI",
    "sg:tags":[
        "design",
        "jewelry",
        "mfg"
    ],
    "wof:name":"Paroline/Wright Design Inc",
    "wof:placetype":"venue"
},
  "geometry": {"coordinates":[-71.43226799999999,41.754996],"type":"Point"}
}