{
  "type": "Feature",
  "properties": {
    "iso:country":"US",
    "sg:address":"60 Angell Rd",
    "sg:city":"Narragansett",
    "sg:classifiers":[
        {
            "category":"Real Estate",
            "subcategory":"Real Estate Agent",
            "type":"Services"
        }
    ],
    "sg:phone":"+1 401 783 5183",
    "sg:postcode":"02882",
    "sg:province":"RI",
    "sg:website":"www.jblrealty.com",
    "wof:name":"JBL Realty Inc",
    "wof:placetype":"venue"
},
  "geometry": {"coordinates":[-71.480338,41.390029],"type":"Point"}
}