{
  "type": "Feature",
  "properties": {
    "iso:country":"US",
    "sg:address":"1174 Douglas Ave",
    "sg:city":"Providence",
    "sg:classifiers":[
        {
            "category":"Professional",
            "subcategory":"Business Services",
            "type":"Services"
        }
    ],
    "sg:phone":"+1 401 231 5445",
    "sg:postcode":"02904",
    "sg:province":"RI",
    "wof:name":"Dennis Pastina",
    "wof:placetype":"venue"
},
  "geometry": {"coordinates":[-71.443579,41.856553],"type":"Point"}
}