{
  "type": "Feature",
  "properties": {
    "iso:country":"US",
    "sg:address":"50 S County Trl",
    "sg:city":"Wakefield",
    "sg:classifiers":[
        {
            "category":"Real Estate",
            "subcategory":"Real Estate Agent",
            "type":"Services"
        }
    ],
    "sg:phone":"+1 401 788 9300",
    "sg:postcode":"02822",
    "sg:province":"RI",
    "sg:website":"www.residentialproperties.com",
    "wof:name":"Residential Properties LTD",
    "wof:placetype":"venue"
},
  "geometry": {"coordinates":[-71.520717,41.555063],"type":"Point"}
}