{
  "type": "Feature",
  "properties": {
    "iso:country":"US",
    "sg:address":"6 Angell Ct",
    "sg:city":"Providence",
    "sg:classifiers":[
        {
            "category":"Professional",
            "subcategory":"Management & Consulting",
            "type":"Services"
        }
    ],
    "sg:phone":"+1 401 351 5632",
    "sg:postcode":"02906",
    "sg:province":"RI",
    "sg:tags":[
        "business"
    ],
    "wof:name":"Urban Eden",
    "wof:placetype":"venue"
},
  "geometry": {"coordinates":[-71.390348,41.829997],"type":"Point"}
}