{
  "type": "Feature",
  "properties": {
    "iso:country":"US",
    "sg:address":"362 Ives St",
    "sg:city":"Providence",
    "sg:phone":"+1 401 861 4358",
    "sg:postcode":"02906",
    "sg:province":"RI",
    "sg:website":"http://www.drsrubinsteinandducoff.com",
    "wof:name":"Ducoff, Robert J, Dds - East Side General Cosmetic",
    "wof:placetype":"venue"
},
  "geometry": {"coordinates":[-71.392884,41.827714],"type":"Point"}
}