{
  "type": "Feature",
  "properties": {
    "addr:full":"36 Branch Ave Providence RI 02904",
    "addr:housenumber":"36",
    "addr:postcode":"02904",
    "addr:street":"Branch Ave",
    "iso:country":"US",
    "sg:address":"36 Branch Ave",
    "sg:city":"Providence",
    "sg:classifiers":[
        {
            "category":"Wholesale",
            "subcategory":"Furniture",
            "type":"Manufacturing & Wholesale Goods"
        }
    ],
    "sg:phone":"+1 401 276 0000",
    "sg:postcode":"02904",
    "sg:province":"RI",
    "sg:tags":[
        "equipment"
    ],
    "sg:website":"www.seatingzone.com",
    "wof:name":"Seating Zone.Com",
    "wof:placetype":"venue"
},
  "geometry": {"coordinates":[-71.40844800000001,41.842519],"type":"Point"}
}