{
  "type": "Feature",
  "properties": {
    "iso:country":"US",
    "sg:address":"50 Washington Sq",
    "sg:city":"Newport",
    "sg:classifiers":[
        {
            "category":"Organizations",
            "subcategory":"Religious Organization",
            "type":"Services"
        }
    ],
    "sg:phone":"+1 401 846 4406",
    "sg:postcode":"02840",
    "sg:province":"RI",
    "sg:tags":[
        "monastery",
        "convent"
    ],
    "wof:name":"Big Sisters Of RI",
    "wof:placetype":"venue"
},
  "geometry": {"coordinates":[-71.31310999999999,41.49057],"type":"Point"}
}