{
  "type": "Feature",
  "properties": {
    "addr:full":"Minrl Spring Ave North Providence RI 02911",
    "addr:postcode":"02911",
    "addr:street":"Minrl Spring Ave",
    "iso:country":"US",
    "sg:address":"Minrl Spring Ave",
    "sg:city":"North Providence",
    "sg:classifiers":[
        {
            "category":"Autos & Motor Vehicles",
            "subcategory":"Automobile Sales",
            "type":"Retail Goods"
        },
        {
            "category":"Retail",
            "subcategory":"Auto Repair",
            "type":"Services"
        }
    ],
    "sg:phone":"+1 401 353 2300",
    "sg:postcode":"02911",
    "sg:province":"RI",
    "sg:tags":[
        "body",
        "shop",
        "car"
    ],
    "wof:name":"Rizzo Ford Inc",
    "wof:placetype":"venue"
},
  "geometry": {"coordinates":[-71.47640199999999,41.851799],"type":"Point"}
}