{
  "type": "Feature",
  "properties": {
    "iso:country":"US",
    "sg:address":"1130 Ten Rod Rd",
    "sg:city":"North Kingstown",
    "sg:classifiers":[
        {
            "category":"Professional",
            "subcategory":"Management & Consulting",
            "type":"Services"
        }
    ],
    "sg:phone":"+1 401 294 9888",
    "sg:postcode":"02852",
    "sg:province":"RI",
    "sg:tags":[
        "consultant",
        "business"
    ],
    "wof:name":"Nova Group Intl",
    "wof:placetype":"venue"
},
  "geometry": {"coordinates":[-71.49251099999999,41.579776],"type":"Point"}
}