{
  "type": "Feature",
  "properties": {
    "iso:country":"US",
    "sg:address":"1395 Atwood Ave",
    "sg:city":"Johnston",
    "sg:classifiers":[
        {
            "category":"Professional",
            "subcategory":"Management & Consulting",
            "type":"Services"
        }
    ],
    "sg:phone":"+1 401 942 7275",
    "sg:postcode":"02919",
    "sg:province":"RI",
    "sg:tags":[
        "consultant",
        "traffic",
        "parking"
    ],
    "wof:name":"Parkrite Management Inc",
    "wof:placetype":"venue"
},
  "geometry": {"coordinates":[-71.496658,41.817181],"type":"Point"}
}