{
  "type": "Feature",
  "properties": {
    "addr:full":"2949 Hartford Ave Johnston RI 02919",
    "addr:housenumber":"2949",
    "addr:postcode":"02919",
    "addr:street":"Hartford Ave",
    "iso:country":"US",
    "sg:address":"2949 Hartford Ave",
    "sg:city":"Johnston",
    "sg:classifiers":[
        {
            "category":"Shopping",
            "type":"Retail Goods"
        }
    ],
    "sg:phone":"+1 401 272 8994",
    "sg:postcode":"02919",
    "sg:province":"RI",
    "sg:tags":[
        "supply",
        "also",
        "billiard",
        "table",
        "pool",
        "swimming"
    ],
    "wof:name":"Johnston Pool Supply",
    "wof:placetype":"venue"
},
  "geometry": {"coordinates":[-71.56835100000001,41.835048],"type":"Point"}
}