{
  "type": "Feature",
  "properties": {
    "addr:full":"846 Broncos Hwy Mapleville RI 02839",
    "addr:housenumber":"846",
    "addr:postcode":"02839",
    "addr:street":"Broncos Hwy",
    "iso:country":"US",
    "sg:address":"846 Broncos Hwy",
    "sg:city":"Mapleville",
    "sg:classifiers":[
        {
            "category":"Wholesale",
            "subcategory":"Metals & Minerals",
            "type":"Manufacturing & Wholesale Goods"
        }
    ],
    "sg:phone":"+1 401 568 9155",
    "sg:postcode":"02839",
    "sg:province":"RI",
    "sg:tags":[
        "pipe"
    ],
    "wof:name":"JDM Supply Co",
    "wof:placetype":"venue"
},
  "geometry": {"coordinates":[-71.652603,41.955338],"type":"Point"}
}