{
  "type": "Feature",
  "properties": {
    "iso:country":"US",
    "sg:address":"12 Bass Ter",
    "sg:city":"Little Compton",
    "sg:classifiers":[
        {
            "category":"Banks & Credit Unions",
            "subcategory":"Financial Services",
            "type":"Services"
        }
    ],
    "sg:phone":"+1 401 635 2746",
    "sg:postcode":"02837",
    "sg:province":"RI",
    "sg:tags":[
        "investor"
    ],
    "wof:name":"Roy Family Ltd Partnershi",
    "wof:placetype":"venue"
},
  "geometry": {"coordinates":[-71.144305,41.483863],"type":"Point"}
}