{
  "type": "Feature",
  "properties": {
    "iso:country":"US",
    "sg:address":"531 Warren Ave",
    "sg:city":"East Providence",
    "sg:classifiers":[
        {
            "category":"Autos & Motor Vehicles",
            "subcategory":"Automobile Sales",
            "type":"Retail Goods"
        }
    ],
    "sg:phone":"+1 401 438 7508",
    "sg:postcode":"02914",
    "sg:province":"RI",
    "sg:tags":[
        "car",
        "dealer"
    ],
    "wof:name":"Warren Avenue Auto Sales",
    "wof:placetype":"venue"
},
  "geometry": {"coordinates":[-71.36344800000001,41.812181],"type":"Point"}
}