{
  "type": "Feature",
  "properties": {
    "iso:country":"US",
    "sg:address":"339 Market St",
    "sg:city":"Warren",
    "sg:classifiers":[
        {
            "category":"Home & Garden",
            "subcategory":"Furniture",
            "type":"Retail Goods"
        }
    ],
    "sg:phone":"+1 401 289 2070",
    "sg:postcode":"02885",
    "sg:province":"RI",
    "sg:tags":[
        "top",
        "counter"
    ],
    "wof:name":"Counter Top Experience",
    "wof:placetype":"venue"
},
  "geometry": {"coordinates":[-71.27322700000001,41.74298],"type":"Point"}
}