{
  "type": "Feature",
  "properties": {
    "iso:country":"US",
    "sg:address":"28 Christine Dr",
    "sg:city":"Barrington",
    "sg:classifiers":[
        {
            "category":"Professional",
            "type":"Services"
        }
    ],
    "sg:phone":"+1 401 245 5926",
    "sg:postcode":"02806",
    "sg:province":"RI",
    "sg:tags":[
        "establishment"
    ],
    "wof:name":"Power Associates",
    "wof:placetype":"venue"
},
  "geometry": {"coordinates":[-71.29787899999999,41.761089],"type":"Point"}
}