{
  "type": "Feature",
  "properties": {
    "iso:country":"US",
    "sg:address":"192 Lawton Foster Rd N",
    "sg:city":"Hope Valley",
    "sg:classifiers":[
        {
            "category":"Building & Trades",
            "subcategory":"Electrical",
            "type":"Services"
        }
    ],
    "sg:phone":"+1 401 539 2552",
    "sg:postcode":"02832",
    "sg:province":"RI",
    "sg:tags":[
        "electric",
        "contractor"
    ],
    "wof:name":"Santoro Electric Inc",
    "wof:placetype":"venue"
},
  "geometry": {"coordinates":[-71.756283,41.48527],"type":"Point"}
}