{
  "type": "Feature",
  "properties": {
    "iso:country":"US",
    "sg:address":"288 Nelson St",
    "sg:city":"Providence",
    "sg:classifiers":[
        {
            "category":"Real Estate",
            "subcategory":"Real Estate Agent",
            "type":"Services"
        }
    ],
    "sg:phone":"+1 401 751 7070",
    "sg:postcode":"02908",
    "sg:province":"RI",
    "wof:name":"Watkins Real Estate Agency",
    "wof:placetype":"venue"
},
  "geometry": {"coordinates":[-71.444607,41.846112],"type":"Point"}
}