{
  "type": "Feature",
  "properties": {
    "iso:country":"US",
    "sg:address":"249 Academy Ave",
    "sg:city":"Providence",
    "sg:classifiers":[
        {
            "category":"Wholesale",
            "subcategory":"Painting Supplies",
            "type":"Manufacturing & Wholesale Goods"
        },
        {
            "category":"Home & Garden",
            "subcategory":"Garden Supply",
            "type":"Retail Goods"
        },
        {
            "category":"Wholesale",
            "subcategory":"Construction Materials",
            "type":"Manufacturing & Wholesale Goods"
        },
        {
            "category":"Home & Garden",
            "subcategory":"Hardware",
            "type":"Retail Goods"
        }
    ],
    "sg:phone":"+1 401 351 7200",
    "sg:postcode":"02908",
    "sg:province":"RI",
    "sg:tags":[
        "lawn",
        "paint",
        "equipment",
        "part",
        "plumbing",
        "fixtures",
        "store"
    ],
    "sg:website":"http://www.truevalue.com",
    "wof:name":"Mt Pleasant True Value Hardware Inc",
    "wof:placetype":"venue"
},
  "geometry": {"coordinates":[-71.444603,41.831799],"type":"Point"}
}