{
  "type": "Feature",
  "properties": {
    "addr:full":"585 Main St Warren RI 02885",
    "addr:housenumber":"585",
    "addr:postcode":"02885",
    "addr:street":"Main St",
    "iso:country":"US",
    "sg:address":"585 Main St",
    "sg:city":"Warren",
    "sg:classifiers":[
        {
            "category":"Health Services",
            "subcategory":"Optometrist",
            "type":"Services"
        },
        {
            "category":"Health Services",
            "subcategory":"Doctor",
            "type":"Services"
        },
        {
            "category":"Health Services",
            "subcategory":"Health Practitioner",
            "type":"Services"
        }
    ],
    "sg:phone":"+1 401 245 6393",
    "sg:postcode":"02885",
    "sg:province":"RI",
    "sg:tags":[
        "physician",
        "ophthalmology",
        "surgeons",
        "surgeon"
    ],
    "wof:name":"Lemos Jr, Lionel, OD - Koch Eye Associates",
    "wof:placetype":"venue"
},
  "geometry": {"coordinates":[-71.28185499999999,41.727421],"type":"Point"}
}