{
  "type": "Feature",
  "properties": {
    "addr:full":"101 Allagash Trl Narragansett RI 02882",
    "addr:housenumber":"101",
    "addr:postcode":"02882",
    "addr:street":"Allagash Trl",
    "iso:country":"US",
    "sg:address":"101 Allagash Trl",
    "sg:city":"Narragansett",
    "sg:classifiers":[
        {
            "category":"Wholesale",
            "subcategory":"Machinery & Supplies",
            "type":"Manufacturing & Wholesale Goods"
        }
    ],
    "sg:phone":"+1 401 789 6561",
    "sg:postcode":"02882",
    "sg:province":"RI",
    "sg:tags":[
        "equipment",
        "oceanographic"
    ],
    "wof:name":"Pro-Oceanus Systems Inc",
    "wof:placetype":"venue"
},
  "geometry": {"coordinates":[-71.431656,41.479282],"type":"Point"}
}