{
  "type": "Feature",
  "properties": {
    "addr:full":"177 Old River Rd Lincoln RI 02865",
    "addr:housenumber":"177",
    "addr:postcode":"02865",
    "addr:street":"Old River Rd",
    "iso:country":"US",
    "sg:address":"177 Old River Rd",
    "sg:city":"Lincoln",
    "sg:classifiers":[
        {
            "category":"Real Estate",
            "subcategory":"Real Estate Operator",
            "type":"Services"
        }
    ],
    "sg:phone":"+1 401 333 1800",
    "sg:postcode":"02865",
    "sg:province":"RI",
    "sg:tags":[
        "apartment"
    ],
    "wof:name":"Kirkbrae Country Estates Inc",
    "wof:placetype":"venue"
},
  "geometry": {"coordinates":[-71.458603,41.942299],"type":"Point"}
}