{
  "type": "Feature",
  "properties": {
    "addr:full":"4160 Old Post Rd Ste 7 Charlestown RI 02813",
    "addr:housenumber":"4160",
    "addr:postcode":"02813",
    "addr:street":"Old Post Rd Ste 7",
    "iso:country":"US",
    "sg:address":"4160 Old Post Rd Ste 7",
    "sg:city":"Charlestown",
    "sg:classifiers":[
        {
            "category":"Health Services",
            "subcategory":"Doctor",
            "type":"Services"
        }
    ],
    "sg:phone":"+1 401 213 6088",
    "sg:postcode":"02813",
    "sg:province":"RI",
    "wof:name":"Krupp Brandon H MD",
    "wof:placetype":"venue"
},
  "geometry": {"coordinates":[-71.631045,41.384447],"type":"Point"}
}