{
  "type": "Feature",
  "properties": {
    "addr:full":"221 Admiral St Providence RI 02908",
    "addr:housenumber":"221",
    "addr:postcode":"02908",
    "addr:street":"Admiral St",
    "iso:country":"US",
    "sg:address":"221 Admiral St",
    "sg:city":"Providence",
    "sg:classifiers":[
        {
            "category":"Manufacturing",
            "subcategory":"Retail Goods",
            "type":"Manufacturing & Wholesale Goods"
        }
    ],
    "sg:phone":"+1 401 861 6222",
    "sg:postcode":"02908",
    "sg:province":"RI",
    "sg:tags":[
        "manufacturer"
    ],
    "wof:name":"Patriarca Manufacturing Inc",
    "wof:placetype":"venue"
},
  "geometry": {"coordinates":[-71.42313300000001,41.843681],"type":"Point"}
}