{
  "type": "Feature",
  "properties": {
    "iso:country":"US",
    "sg:address":"525 Narragansett Park Dr",
    "sg:city":"Pawtucket",
    "sg:classifiers":[
        {
            "category":"Manufacturing",
            "subcategory":"Tools & Machinery",
            "type":"Manufacturing & Wholesale Goods"
        }
    ],
    "sg:phone":"+1 401 729 1400",
    "sg:postcode":"02861",
    "sg:province":"RI",
    "sg:tags":[
        "instrument",
        "mfg"
    ],
    "sg:website":"www.bio-detek.com",
    "wof:name":"Bio-Detek Inc",
    "wof:placetype":"venue"
},
  "geometry": {"coordinates":[-71.343628,41.862746],"type":"Point"}
}