{
  "type": "Feature",
  "properties": {
    "iso:country":"US",
    "sg:address":"3145 Post Rd",
    "sg:city":"Warwick",
    "sg:classifiers":[
        {
            "category":"Autos & Motor Vehicles",
            "subcategory":"Auto Supplies",
            "type":"Retail Goods"
        },
        {
            "category":"Wholesale",
            "subcategory":"Auto Parts",
            "type":"Manufacturing & Wholesale Goods"
        }
    ],
    "sg:phone":"+1 401 737 7932",
    "sg:postcode":"02886",
    "sg:province":"RI",
    "sg:tags":[
        "equipment",
        "racing",
        "automobile",
        "car"
    ],
    "sg:website":"www.mustangmall.com",
    "wof:name":"Karl's East Coast Speed",
    "wof:placetype":"venue"
},
  "geometry": {"coordinates":[-71.453491,41.700089],"type":"Point"}
}