{
  "type": "Feature",
  "properties": {
    "iso:country":"US",
    "sg:address":"401 Davisville Rd",
    "sg:city":"North Kingstown",
    "sg:classifiers":[
        {
            "category":"Social Services",
            "type":"Services"
        }
    ],
    "sg:phone":"+1 401 884 4593",
    "sg:postcode":"02852",
    "sg:province":"RI",
    "sg:tags":[
        "youth",
        "organization",
        "center"
    ],
    "wof:name":"Quidnessett Youth Ctr",
    "wof:placetype":"venue"
},
  "geometry": {"coordinates":[-71.478094,41.618229],"type":"Point"}
}