{
  "type": "Feature",
  "properties": {
    "iso:country":"US",
    "sg:address":"87 Maple Ave",
    "sg:city":"Barrington",
    "sg:classifiers":[
        {
            "category":"Retail",
            "subcategory":"Auto Repair",
            "type":"Services"
        }
    ],
    "sg:phone":"+1 401 247 9888",
    "sg:postcode":"02806",
    "sg:province":"RI",
    "sg:tags":[
        "automotive",
        "wrecker"
    ],
    "wof:name":"Mike Brandao's Towing",
    "wof:placetype":"venue"
},
  "geometry": {"coordinates":[-71.311863,41.73944],"type":"Point"}
}