{
  "type": "Feature",
  "properties": {
    "iso:country":"US",
    "sg:address":"161 Farnum Pike",
    "sg:city":"Smithfield",
    "sg:classifiers":[
        {
            "category":"Autos & Motor Vehicles",
            "subcategory":"Fuel & Gas Station",
            "type":"Retail Goods"
        }
    ],
    "sg:phone":"+1 401 231 9848",
    "sg:postcode":"02917",
    "sg:province":"RI",
    "sg:tags":[
        "repair",
        "station",
        "gasoline",
        "general"
    ],
    "wof:name":"Smithfield Service Station",
    "wof:placetype":"venue"
},
  "geometry": {"coordinates":[-71.52094099999999,41.894408],"type":"Point"}
}