{
  "type": "Feature",
  "properties": {
    "addr:full":"33 Higginson Ave Central Falls RI 02863",
    "addr:housenumber":"33",
    "addr:postcode":"02863",
    "addr:street":"Higginson Ave",
    "iso:country":"US",
    "sg:address":"33 Higginson Ave",
    "sg:city":"Central Falls",
    "sg:classifiers":[
        {
            "category":"Manufacturing",
            "subcategory":"Tools & Machinery",
            "type":"Manufacturing & Wholesale Goods"
        }
    ],
    "sg:phone":"+1 401 728 0700",
    "sg:postcode":"02863",
    "sg:province":"RI",
    "sg:website":"www.whittet-higgins.com",
    "wof:name":"Whittet-Higgins Co",
    "wof:placetype":"venue"
},
  "geometry": {"coordinates":[-71.404931,41.886389],"type":"Point"}
}