{
  "type": "Feature",
  "properties": {
    "iso:country":"US",
    "sg:address":"255 Main St",
    "sg:city":"Pawtucket",
    "sg:classifiers":[
        {
            "category":"Professional",
            "subcategory":"Detective & Security Services",
            "type":"Services"
        }
    ],
    "sg:phone":"+1 401 728 8409",
    "sg:postcode":"02860",
    "sg:province":"RI",
    "sg:tags":[
        "investigator"
    ],
    "wof:name":"M Brouwer Investigations",
    "wof:placetype":"venue"
},
  "geometry": {"coordinates":[-71.38454400000001,41.877267],"type":"Point"}
}