{
  "type": "Feature",
  "properties": {
    "addr:full":"65 W Independence Way Kingston RI 02881",
    "addr:housenumber":"65",
    "addr:postcode":"02881",
    "addr:street":"W Independence Way",
    "iso:country":"US",
    "sg:address":"65 W Independence Way",
    "sg:city":"Kingston",
    "sg:classifiers":[
        {
            "category":"Health Services",
            "subcategory":"Nursing And Care Facility",
            "type":"Services"
        }
    ],
    "sg:phone":"+1 401 789 5611",
    "sg:postcode":"02881",
    "sg:province":"RI",
    "wof:name":"University Fields Apartments",
    "wof:placetype":"venue"
},
  "geometry": {"coordinates":[-71.540325,41.483413],"type":"Point"}
}