{
  "type": "Feature",
  "properties": {
    "iso:country":"US",
    "sg:address":"203 N Fenner Ave",
    "sg:city":"Middletown",
    "sg:classifiers":[
        {
            "category":"Travel",
            "subcategory":"Hotels & Motels",
            "type":"Entertainment"
        }
    ],
    "sg:phone":"+1 401 841 0484",
    "sg:postcode":"02842",
    "sg:province":"RI",
    "sg:tags":[
        "breakfast",
        "accommodation",
        "bed"
    ],
    "wof:name":"North Fenner Lodge",
    "wof:placetype":"venue"
},
  "geometry": {"coordinates":[-71.298179,41.506096],"type":"Point"}
}