{
  "type": "Feature",
  "properties": {
    "iso:country":"US",
    "sg:address":"25 Old County Rd",
    "sg:city":"Barrington",
    "sg:classifiers":[
        {
            "category":"Social Services",
            "subcategory":"Child Care",
            "type":"Services"
        }
    ],
    "sg:phone":"+1 401 246 0262",
    "sg:postcode":"02806",
    "sg:province":"RI",
    "wof:name":"Wee Care Child Care Ctr",
    "wof:placetype":"venue"
},
  "geometry": {"coordinates":[-71.330078,41.754709],"type":"Point"}
}