{
  "type": "Feature",
  "properties": {
    "iso:country":"US",
    "sg:address":"508 Plainfield St",
    "sg:city":"Providence",
    "sg:classifiers":[
        {
            "category":"Food & Beverages",
            "subcategory":"Groceries & Convenience Stores",
            "type":"Retail Goods"
        },
        {
            "category":"Professional",
            "type":"Services"
        }
    ],
    "sg:phone":"+1 401 946 8044",
    "sg:postcode":"02909",
    "sg:province":"RI",
    "sg:tags":[
        "establishment",
        "market"
    ],
    "wof:name":"Mis Pais Market",
    "wof:placetype":"venue"
},
  "geometry": {"coordinates":[-71.45649299999999,41.813006],"type":"Point"}
}