{
  "type": "Feature",
  "properties": {
    "addr:full":"123 Birch Swamp Rd Warren RI 02885",
    "addr:housenumber":"123",
    "addr:postcode":"02885",
    "addr:street":"Birch Swamp Rd",
    "iso:country":"US",
    "sg:address":"123 Birch Swamp Rd",
    "sg:city":"Warren",
    "sg:classifiers":[
        {
            "category":"Building & Trades",
            "subcategory":"Construction",
            "type":"Services"
        }
    ],
    "sg:phone":"+1 401 247 7811",
    "sg:postcode":"02885",
    "sg:province":"RI",
    "sg:tags":[
        "masonry",
        "contractor"
    ],
    "wof:name":"New England Stone Mason",
    "wof:placetype":"venue"
},
  "geometry": {"coordinates":[-71.26740599999999,41.753998],"type":"Point"}
}