{
  "type": "Feature",
  "properties": {
    "addr:full":"915 Smith St Providence RI 02908",
    "addr:housenumber":"915",
    "addr:postcode":"02908",
    "addr:street":"Smith St",
    "iso:country":"US",
    "sg:address":"915 Smith St",
    "sg:city":"Providence",
    "sg:classifiers":[
        {
            "category":"Professional",
            "subcategory":"Lawyer & Legal Services",
            "type":"Services"
        }
    ],
    "sg:phone":"+1 401 621 7600",
    "sg:postcode":"02908",
    "sg:province":"RI",
    "wof:name":"Lennon Lincoln S Atty",
    "wof:placetype":"venue"
},
  "geometry": {"coordinates":[-71.441299,41.840801],"type":"Point"}
}