{
  "type": "Feature",
  "properties": {
    "iso:country":"US",
    "sg:address":"5211 Old Post Rd",
    "sg:city":"Charlestown",
    "sg:classifiers":[
        {
            "category":"Autos & Motor Vehicles",
            "subcategory":"Boat Sales",
            "type":"Retail Goods"
        }
    ],
    "sg:phone":"+1 401 322 1150",
    "sg:postcode":"02813",
    "sg:province":"RI",
    "sg:tags":[
        "outboard",
        "marine",
        "supply"
    ],
    "wof:name":"Megrews Boats",
    "wof:placetype":"venue"
},
  "geometry": {"coordinates":[-71.712355,41.355091],"type":"Point"}
}