{
  "type": "Feature",
  "properties": {
    "addr:full":"110 Sandy Point Ave Portsmouth RI 02871",
    "addr:housenumber":"110",
    "addr:postcode":"02871",
    "addr:street":"Sandy Point Ave",
    "iso:country":"US",
    "sg:address":"110 Sandy Point Ave",
    "sg:city":"Portsmouth",
    "sg:classifiers":[
        {
            "category":"Organizations",
            "subcategory":"Non-profit Organization",
            "type":"Services"
        }
    ],
    "sg:phone":"+1 401 849 4646",
    "sg:postcode":"02871",
    "sg:province":"RI",
    "wof:name":"Pennfield School",
    "wof:placetype":"venue"
},
  "geometry": {"coordinates":[-71.24535299999999,41.551624],"type":"Point"}
}