{
  "type": "Feature",
  "properties": {
    "addr:full":"1052 Charles St North Providence RI 02904",
    "addr:housenumber":"1052",
    "addr:postcode":"02904",
    "addr:street":"Charles St",
    "iso:country":"US",
    "sg:address":"1052 Charles St",
    "sg:city":"North Providence",
    "sg:classifiers":[
        {
            "category":"Autos & Motor Vehicles",
            "subcategory":"Auto Supplies",
            "type":"Retail Goods"
        }
    ],
    "sg:phone":"+1 401 465 6334",
    "sg:postcode":"02904",
    "sg:province":"RI",
    "sg:tags":[
        "wheel",
        "parts",
        "cover",
        "tire",
        "accessory"
    ],
    "wof:name":"Techno Wheels",
    "wof:placetype":"venue"
},
  "geometry": {"coordinates":[-71.424909,41.86736],"type":"Point"}
}