{
  "type": "Feature",
  "properties": {
    "iso:country":"US",
    "sg:address":"108 Whitford Ave",
    "sg:city":"Providence",
    "sg:classifiers":[
        {
            "category":"Professional",
            "subcategory":"Lawyer & Legal Services",
            "type":"Services"
        }
    ],
    "sg:phone":"+1 401 453 3301",
    "sg:postcode":"02908",
    "sg:province":"RI",
    "wof:name":"Social Security Law Ofc of Michael J Gadoury Atty",
    "wof:placetype":"venue"
},
  "geometry": {"coordinates":[-71.44270299999999,41.8391],"type":"Point"}
}