{
  "type": "Feature",
  "properties": {
    "iso:country":"US",
    "sg:address":"100 Smithfield Ave",
    "sg:city":"Pawtucket",
    "sg:classifiers":[
        {
            "category":"Health Services",
            "subcategory":"Doctor",
            "type":"Services"
        },
        {
            "category":"Health Services",
            "subcategory":"Clinic",
            "type":"Services"
        },
        {
            "category":"Community Center",
            "type":"Public Place"
        }
    ],
    "sg:phone":"+1 401 725 8600",
    "sg:postcode":"02860",
    "sg:province":"RI",
    "sg:tags":[
        "physician",
        "family",
        "medical",
        "practice",
        "surgeons",
        "medicine"
    ],
    "sg:website":"http://www.cresturgentcare.com",
    "wof:name":"Urgent Care of Pawtucket",
    "wof:placetype":"venue"
},
  "geometry": {"coordinates":[-71.41149900000001,41.862],"type":"Point"}
}