{
  "type": "Feature",
  "properties": {
    "addr:full":"11 George St North Providence RI 02911",
    "addr:housenumber":"11",
    "addr:postcode":"02911",
    "addr:street":"George St",
    "iso:country":"US",
    "sg:address":"11 George St",
    "sg:city":"North Providence",
    "sg:classifiers":[
        {
            "category":"Education",
            "subcategory":"School",
            "type":"Public Place"
        }
    ],
    "sg:phone":"+1 401 233 1110",
    "sg:postcode":"02911",
    "sg:province":"RI",
    "wof:name":"NP Special Ed Dept 00000",
    "wof:placetype":"venue"
},
  "geometry": {"coordinates":[-71.48167599999999,41.85631],"type":"Point"}
}