{
  "type": "Feature",
  "properties": {
    "addr:full":"5792 Post Rd East Greenwich RI 02818",
    "addr:housenumber":"5792",
    "addr:postcode":"02818",
    "addr:street":"Post Rd",
    "iso:country":"US",
    "sg:address":"5792 Post Rd",
    "sg:city":"East Greenwich",
    "sg:classifiers":[
        {
            "category":"Shopping",
            "subcategory":"Florist",
            "type":"Retail Goods"
        }
    ],
    "sg:phone":"+1 401 884 8666",
    "sg:postcode":"02818",
    "sg:province":"RI",
    "wof:name":"Busy Bees Flowers",
    "wof:placetype":"venue"
},
  "geometry": {"coordinates":[-71.468666,41.638391],"type":"Point"}
}