{
  "type": "Feature",
  "properties": {
    "iso:country":"US",
    "sg:address":"238 Robinson St",
    "sg:city":"Wakefield",
    "sg:classifiers":[
        {
            "category":"Cinema",
            "subcategory":"Movie Theater",
            "type":"Entertainment"
        }
    ],
    "sg:phone":"+1 401 782 8587",
    "sg:postcode":"02879",
    "sg:province":"RI",
    "wof:name":"Theatre By The Sea",
    "wof:placetype":"venue"
},
  "geometry": {"coordinates":[-71.498734,41.438931],"type":"Point"}
}