{
  "type": "Feature",
  "properties": {
    "iso:country":"US",
    "sg:address":"2101 Mineral Spring Ave",
    "sg:city":"North Providence",
    "sg:classifiers":[
        {
            "category":"Personal",
            "subcategory":"Hair Removal",
            "type":"Services"
        }
    ],
    "sg:phone":"+1 401 232 5336",
    "sg:postcode":"02911",
    "sg:province":"RI",
    "wof:name":"Associates In Electrology",
    "wof:placetype":"venue"
},
  "geometry": {"coordinates":[-71.477898,41.858898],"type":"Point"}
}