{
  "type": "Feature",
  "properties": {
    "iso:country":"US",
    "sg:address":"4232 S County Trl",
    "sg:city":"Charlestown",
    "sg:classifiers":[
        {
            "category":"Building & Trades",
            "subcategory":"Plumbing",
            "type":"Services"
        }
    ],
    "sg:phone":"+1 401 364 0118",
    "sg:postcode":"02813",
    "sg:province":"RI",
    "sg:website":"www.abhoxie.com",
    "wof:name":"A B Hoxie",
    "wof:placetype":"venue"
},
  "geometry": {"coordinates":[-71.64052,41.43398],"type":"Point"}
}