{
  "type": "Feature",
  "properties": {
    "addr:full":"131 Oak St Westerly RI 02891",
    "addr:housenumber":"131",
    "addr:postcode":"02891",
    "addr:street":"Oak St",
    "iso:country":"US",
    "sg:address":"131 Oak St",
    "sg:city":"Westerly",
    "sg:classifiers":[
        {
            "category":"Retail",
            "subcategory":"Auto Repair",
            "type":"Services"
        }
    ],
    "sg:phone":"+1 401 596 5602",
    "sg:postcode":"02891",
    "sg:province":"RI",
    "sg:tags":[
        "body",
        "automobile",
        "painting"
    ],
    "wof:name":"Sal's Auto Body",
    "wof:placetype":"venue"
},
  "geometry": {"coordinates":[-71.809759,41.383656],"type":"Point"}
}