{
  "type": "Feature",
  "properties": {
    "iso:country":"US",
    "sg:address":"54 South St",
    "sg:city":"Providence",
    "sg:classifiers":[
        {
            "category":"Freight",
            "type":"Transportation"
        }
    ],
    "sg:phone":"+1 401 455 0050",
    "sg:postcode":"02903",
    "sg:province":"RI",
    "wof:name":"Executive Transportation",
    "wof:placetype":"venue"
},
  "geometry": {"coordinates":[-71.407089,41.817692],"type":"Point"}
}