{
  "type": "Feature",
  "properties": {
    "iso:country":"US",
    "sg:address":"21 Sunnyside Ave",
    "sg:city":"Johnston",
    "sg:classifiers":[
        {
            "category":"Manufacturing",
            "subcategory":"Metals",
            "type":"Manufacturing & Wholesale Goods"
        }
    ],
    "sg:phone":"+1 401 331 0781",
    "sg:postcode":"02919",
    "sg:province":"RI",
    "sg:tags":[
        "vehicle",
        "stampings",
        "stamping",
        "motor",
        "mfg"
    ],
    "sg:website":"www.hitech-stamping.com",
    "wof:name":"Hi Tech Inc",
    "wof:placetype":"venue"
},
  "geometry": {"coordinates":[-71.470434,41.825581],"type":"Point"}
}