{
  "type": "Feature",
  "properties": {
    "addr:full":"879 W Main Rd Middletown RI 02842",
    "addr:housenumber":"879",
    "addr:postcode":"02842",
    "addr:street":"W Main Rd",
    "iso:country":"US",
    "sg:address":"879 W Main Rd",
    "sg:city":"Middletown",
    "sg:classifiers":[
        {
            "category":"Shopping",
            "subcategory":"Bicycles & Sporting Goods",
            "type":"Retail Goods"
        }
    ],
    "sg:phone":"+1 401 846 7525",
    "sg:postcode":"02842",
    "sg:province":"RI",
    "sg:tags":[
        "shop",
        "repair"
    ],
    "wof:name":"Pedal Power Bicycle Shop Inc",
    "wof:placetype":"venue"
},
  "geometry": {"coordinates":[-71.29618000000001,41.527788],"type":"Point"}
}