{
  "type": "Feature",
  "properties": {
    "iso:country":"US",
    "sg:address":"20 Tamarac Dr",
    "sg:city":"Greenville",
    "sg:classifiers":[
        {
            "category":"Shopping",
            "subcategory":"Catalog Store",
            "type":"Retail Goods"
        }
    ],
    "sg:phone":"+1 401 949 1119",
    "sg:postcode":"02828",
    "sg:province":"RI",
    "sg:tags":[
        "e"
    ],
    "wof:name":"Wholesale Hub",
    "wof:placetype":"venue"
},
  "geometry": {"coordinates":[-71.57381700000001,41.863021],"type":"Point"}
}