{
  "type": "Feature",
  "properties": {
    "iso:country":"US",
    "sg:address":"33 Hazard Ave",
    "sg:city":"East Providence",
    "sg:classifiers":[
        {
            "category":"Retail",
            "subcategory":"Repair Shop",
            "type":"Services"
        }
    ],
    "sg:phone":"+1 401 434 2449",
    "sg:postcode":"02914",
    "sg:province":"RI",
    "sg:tags":[
        "electrical"
    ],
    "wof:name":"James J Poland",
    "wof:placetype":"venue"
},
  "geometry": {"coordinates":[-71.36550200000001,41.800517],"type":"Point"}
}