{
  "type": "Feature",
  "properties": {
    "iso:country":"US",
    "sg:address":"2447 Pawtucket Ave",
    "sg:city":"East Providence",
    "sg:classifiers":[
        {
            "category":"Health Services",
            "subcategory":"Doctor",
            "type":"Services"
        }
    ],
    "sg:phone":"+1 401 434 6441",
    "sg:postcode":"02914",
    "sg:province":"RI",
    "sg:tags":[
        "medical"
    ],
    "wof:name":"J B Valdepenas Dr",
    "wof:placetype":"venue"
},
  "geometry": {"coordinates":[-71.359882,41.808349],"type":"Point"}
}