{
  "type": "Feature",
  "properties": {
    "addr:full":"334 Waterman Ave East Providence RI 02914",
    "addr:housenumber":"334",
    "addr:postcode":"02914",
    "addr:street":"Waterman Ave",
    "iso:country":"US",
    "sg:address":"334 Waterman Ave",
    "sg:city":"East Providence",
    "sg:classifiers":[
        {
            "category":"Organizations",
            "subcategory":"Community Association",
            "type":"Services"
        }
    ],
    "sg:phone":"+1 401 438 1557",
    "sg:postcode":"02914",
    "sg:province":"RI",
    "sg:tags":[
        "fraternal"
    ],
    "wof:name":"Fraternal Order Of Eagles",
    "wof:placetype":"venue"
},
  "geometry": {"coordinates":[-71.36605,41.819501],"type":"Point"}
}