{
  "type": "Feature",
  "properties": {
    "addr:full":"649 Broad St Central Falls RI 02863",
    "addr:housenumber":"649",
    "addr:postcode":"02863",
    "addr:street":"Broad St",
    "iso:country":"US",
    "sg:address":"649 Broad St",
    "sg:city":"Central Falls",
    "sg:classifiers":[
        {
            "category":"Social Services",
            "subcategory":"Adult Care",
            "type":"Services"
        }
    ],
    "sg:phone":"+1 401 725 7045",
    "sg:postcode":"02863",
    "sg:province":"RI",
    "sg:tags":[
        "home",
        "residential"
    ],
    "wof:name":"Blackstone Valley Assisted",
    "wof:placetype":"venue"
},
  "geometry": {"coordinates":[-71.387253,41.888176],"type":"Point"}
}