{
  "type": "Feature",
  "properties": {
    "iso:country":"US",
    "sg:address":"190 Commerce Dr",
    "sg:city":"Warwick",
    "sg:classifiers":[
        {
            "category":"Professional",
            "subcategory":"Lawyer & Legal Services",
            "type":"Services"
        }
    ],
    "sg:phone":"+1 401 615 2811",
    "sg:postcode":"02886",
    "sg:province":"RI",
    "sg:tags":[
        "attorney"
    ],
    "wof:name":"Haronian Paquin Bramley",
    "wof:placetype":"venue"
},
  "geometry": {"coordinates":[-71.420486,41.736835],"type":"Point"}
}