{
  "type": "Feature",
  "properties": {
    "addr:full":"977 Main St West Warwick RI 02893",
    "addr:housenumber":"977",
    "addr:postcode":"02893",
    "addr:street":"Main St",
    "iso:country":"US",
    "sg:address":"977 Main St",
    "sg:city":"West Warwick",
    "sg:classifiers":[
        {
            "category":"Restaurant",
            "type":"Food & Drink"
        }
    ],
    "sg:menulink":"http://www.allmenus.com/ri/west-warwick/56704-dominos-pizza/menu/",
    "sg:phone":"+1 401 826 3636",
    "sg:postcode":"02893",
    "sg:province":"RI",
    "sg:tags":[
        "american",
        "wing",
        "pizza"
    ],
    "wof:name":"Domino's Pizza",
    "wof:placetype":"venue"
},
  "geometry": {"coordinates":[-71.52379999999999,41.715821],"type":"Point"}
}