{
  "type": "Feature",
  "properties": {
    "addr:full":"7 Morrill Ln Providence RI 02904",
    "addr:housenumber":"7",
    "addr:postcode":"02904",
    "addr:street":"Morrill Ln",
    "iso:country":"US",
    "sg:address":"7 Morrill Ln",
    "sg:city":"Providence",
    "sg:classifiers":[
        {
            "category":"Manufacturing",
            "subcategory":"Metals",
            "type":"Manufacturing & Wholesale Goods"
        }
    ],
    "sg:phone":"+1 401 725 8412",
    "sg:postcode":"02904",
    "sg:province":"RI",
    "wof:name":"B & E Polishing Company",
    "wof:placetype":"venue"
},
  "geometry": {"coordinates":[-71.426411,41.866389],"type":"Point"}
}