{
  "type": "Feature",
  "properties": {
    "iso:country":"US",
    "sg:address":"42 Bridgham Farm Rd",
    "sg:city":"Rumford",
    "sg:classifiers":[
        {
            "category":"Real Estate",
            "subcategory":"Real Estate Agent",
            "type":"Services"
        }
    ],
    "sg:phone":"+1 401 421 2222",
    "sg:postcode":"02916",
    "sg:province":"RI",
    "sg:tags":[
        "industrial",
        "commercial",
        "broker"
    ],
    "wof:name":"Commercial Properties Ltd",
    "wof:placetype":"venue"
},
  "geometry": {"coordinates":[-71.34375799999999,41.84034],"type":"Point"}
}