{
  "type": "Feature",
  "properties": {
    "addr:full":"225 Bullocks Point Ave Riverside RI 02915",
    "addr:housenumber":"225",
    "addr:postcode":"02915",
    "addr:street":"Bullocks Point Ave",
    "iso:country":"US",
    "sg:address":"225 Bullocks Point Ave",
    "sg:city":"Riverside",
    "sg:classifiers":[
        {
            "category":"Food & Beverages",
            "subcategory":"Liquor & Beverages",
            "type":"Retail Goods"
        }
    ],
    "sg:phone":"+1 401 433 2900",
    "sg:postcode":"02915",
    "sg:province":"RI",
    "sg:tags":[
        "alcoholic"
    ],
    "wof:name":"Riverside Liquors Inc",
    "wof:placetype":"venue"
},
  "geometry": {"coordinates":[-71.362976,41.772605],"type":"Point"}
}