{
  "type": "Feature",
  "properties": {
    "iso:country":"US",
    "sg:address":"101 Woodville Rd",
    "sg:city":"Hope Valley",
    "sg:classifiers":[
        {
            "category":"Home & Garden",
            "subcategory":"Garden Supply",
            "type":"Retail Goods"
        }
    ],
    "sg:phone":"+1 401 364 3387",
    "sg:postcode":"02832",
    "sg:province":"RI",
    "sg:tags":[
        "nursery",
        "gardening"
    ],
    "wof:name":"Wood River Evergreens Inc",
    "wof:placetype":"venue"
},
  "geometry": {"coordinates":[-71.718498,41.460098],"type":"Point"}
}