{
  "type": "Feature",
  "properties": {
    "addr:full":"155 Plan Way Warwick RI 02886",
    "addr:housenumber":"155",
    "addr:postcode":"02886",
    "addr:street":"Plan Way",
    "iso:country":"US",
    "sg:address":"155 Plan Way",
    "sg:city":"Warwick",
    "sg:classifiers":[
        {
            "category":"Social Services",
            "type":"Services"
        }
    ],
    "sg:phone":"+1 401 738 5600",
    "sg:postcode":"02886",
    "sg:province":"RI",
    "sg:tags":[
        "development",
        "child"
    ],
    "wof:name":"Plan USA",
    "wof:placetype":"venue"
},
  "geometry": {"coordinates":[-71.446412,41.734874],"type":"Point"}
}