{
  "type": "Feature",
  "properties": {
    "iso:country":"US",
    "sg:address":"30 Memorial Blvd",
    "sg:city":"Newport",
    "sg:classifiers":[
        {
            "category":"Travel",
            "subcategory":"Hotels & Motels",
            "type":"Entertainment"
        }
    ],
    "sg:phone":"+1 401 846 0310",
    "sg:postcode":"02840",
    "sg:province":"RI",
    "wof:name":"Inn At Newport Beach",
    "wof:placetype":"venue"
},
  "geometry": {"coordinates":[-71.30986900000001,41.484036],"type":"Point"}
}