{
  "type": "Feature",
  "properties": {
    "iso:country":"US",
    "sg:address":"1525 Smith St Ste 6",
    "sg:city":"North Providence",
    "sg:classifiers":[
        {
            "category":"Health Services",
            "subcategory":"Health Practitioner",
            "type":"Services"
        }
    ],
    "sg:phone":"+1 401 353 8884",
    "sg:postcode":"02911",
    "sg:province":"RI",
    "sg:tags":[
        "therapy",
        "physical"
    ],
    "wof:name":"Lepre Physical Therapy",
    "wof:placetype":"venue"
},
  "geometry": {"coordinates":[-71.46155,41.8503],"type":"Point"}
}