{
  "type": "Feature",
  "properties": {
    "addr:full":"71 Woodland Trl Wakefield RI 02879",
    "addr:housenumber":"71",
    "addr:postcode":"02879",
    "addr:street":"Woodland Trl",
    "iso:country":"US",
    "sg:address":"71 Woodland Trl",
    "sg:city":"Wakefield",
    "sg:classifiers":[
        {
            "category":"Real Estate",
            "subcategory":"Real Estate Agent",
            "type":"Services"
        }
    ],
    "sg:phone":"+1 401 783 3611",
    "sg:postcode":"02879",
    "sg:province":"RI",
    "wof:name":"Kenyon Building Realty LLC",
    "wof:placetype":"venue"
},
  "geometry": {"coordinates":[-71.473635,41.471919],"type":"Point"}
}