{
  "type": "Feature",
  "properties": {
    "addr:full":"14 Michaels Way Westerly RI 02891",
    "addr:housenumber":"14",
    "addr:postcode":"02891",
    "addr:street":"Michaels Way",
    "iso:country":"US",
    "sg:address":"14 Michaels Way",
    "sg:city":"Westerly",
    "sg:classifiers":[
        {
            "category":"Professional",
            "type":"Services"
        }
    ],
    "sg:phone":"+1 401 348 3027",
    "sg:postcode":"02891",
    "sg:province":"RI",
    "sg:tags":[
        "establishment"
    ],
    "wof:name":"Lane & Lane",
    "wof:placetype":"venue"
},
  "geometry": {"coordinates":[-71.800397,41.393975],"type":"Point"}
}