{
  "type": "Feature",
  "properties": {
    "addr:full":"1041 Post Rd Warwick RI 02888",
    "addr:housenumber":"1041",
    "addr:postcode":"02888",
    "addr:street":"Post Rd",
    "iso:country":"US",
    "sg:address":"1041 Post Rd",
    "sg:city":"Warwick",
    "sg:classifiers":[
        {
            "category":"Personal",
            "subcategory":"Beauty Salon",
            "type":"Services"
        }
    ],
    "sg:phone":"+1 401 437 8835",
    "sg:postcode":"02888",
    "sg:province":"RI",
    "wof:name":"K & M Salon",
    "wof:placetype":"venue"
},
  "geometry": {"coordinates":[-71.42328000000001,41.748388],"type":"Point"}
}