{
  "type": "Feature",
  "properties": {
    "iso:country":"US",
    "sg:address":"55 America's Cup Ave",
    "sg:city":"Newport",
    "sg:classifiers":[
        {
            "category":"Building & Trades",
            "subcategory":"Construction",
            "type":"Services"
        }
    ],
    "sg:phone":"+1 401 848 5600",
    "sg:postcode":"02840",
    "sg:province":"RI",
    "sg:tags":[
        "contractor"
    ],
    "wof:name":"Ball & Claw The",
    "wof:placetype":"venue"
},
  "geometry": {"coordinates":[-71.316328,41.487941],"type":"Point"}
}