{
  "type": "Feature",
  "properties": {
    "iso:country":"US",
    "sg:address":"473 Klondike Rd",
    "sg:city":"Charlestown",
    "sg:classifiers":[
        {
            "category":"Building & Trades",
            "subcategory":"Plumbing",
            "type":"Services"
        }
    ],
    "sg:phone":"+1 401 322 0720",
    "sg:postcode":"02813",
    "sg:province":"RI",
    "wof:name":"Morgan Raymond J Sr",
    "wof:placetype":"venue"
},
  "geometry": {"coordinates":[-71.72115100000001,41.381461],"type":"Point"}
}