{
  "type": "Feature",
  "properties": {
    "iso:country":"US",
    "sg:address":"49 Farnum St",
    "sg:city":"Tiverton",
    "sg:classifiers":[
        {
            "category":"Building & Trades",
            "subcategory":"Construction",
            "type":"Services"
        }
    ],
    "sg:phone":"+1 401 624 8366",
    "sg:postcode":"02878",
    "sg:province":"RI",
    "sg:tags":[
        "carpentry",
        "contractor"
    ],
    "wof:name":"Ravin Steel Inc",
    "wof:placetype":"venue"
},
  "geometry": {"coordinates":[-71.15111400000001,41.658544],"type":"Point"}
}