{
  "type": "Feature",
  "properties": {
    "addr:full":"595 Metacom Ave Warren RI 02885",
    "addr:housenumber":"595",
    "addr:postcode":"02885",
    "addr:street":"Metacom Ave",
    "iso:country":"US",
    "sg:address":"595 Metacom Ave",
    "sg:city":"Warren",
    "sg:classifiers":[
        {
            "category":"Retail",
            "subcategory":"Auto Repair",
            "type":"Services"
        }
    ],
    "sg:phone":"+1 401 245 9337",
    "sg:postcode":"02885",
    "sg:province":"RI",
    "sg:tags":[
        "transmission"
    ],
    "wof:name":"Coast To Coast Transmissions",
    "wof:placetype":"venue"
},
  "geometry": {"coordinates":[-71.269296,41.721169],"type":"Point"}
}