{
  "type": "Feature",
  "properties": {
    "iso:country":"US",
    "sg:address":"79 Thames St",
    "sg:city":"Newport",
    "sg:classifiers":[
        {
            "category":"Retail",
            "subcategory":"Repair Shop",
            "type":"Services"
        }
    ],
    "sg:phone":"+1 401 849 6690",
    "sg:postcode":"02840",
    "sg:province":"RI",
    "sg:tags":[
        "used",
        "merchandise"
    ],
    "wof:name":"Antique Clock Restoration",
    "wof:placetype":"venue"
},
  "geometry": {"coordinates":[-71.315405,41.491011],"type":"Point"}
}