{
  "type": "Feature",
  "properties": {
    "iso:country":"US",
    "sg:address":"25 Crest St",
    "sg:city":"Middletown",
    "sg:classifiers":[
        {
            "category":"Professional",
            "subcategory":"Business Services",
            "type":"Services"
        }
    ],
    "sg:phone":"+1 401 619 0007",
    "sg:postcode":"02842",
    "sg:province":"RI",
    "wof:name":"Bevinco",
    "wof:placetype":"venue"
},
  "geometry": {"coordinates":[-71.279856,41.488277],"type":"Point"}
}