{
  "type": "Feature",
  "properties": {
    "iso:country":"US",
    "sg:address":"88 Lawn Ave",
    "sg:city":"Pawtucket",
    "sg:classifiers":[
        {
            "category":"Professional",
            "subcategory":"Computer Services",
            "type":"Services"
        }
    ],
    "sg:phone":"+1 401 258 5042",
    "sg:postcode":"02860",
    "sg:province":"RI",
    "wof:name":"G B Computers",
    "wof:placetype":"venue"
},
  "geometry": {"coordinates":[-71.40237500000001,41.873069],"type":"Point"}
}