{
  "type": "Feature",
  "properties": {
    "iso:country":"US",
    "sg:address":"8 Grenore St",
    "sg:city":"Warwick",
    "sg:classifiers":[
        {
            "category":"Professional",
            "subcategory":"Business Services",
            "type":"Services"
        }
    ],
    "sg:phone":"+1 401 461 4917",
    "sg:postcode":"02888",
    "sg:province":"RI",
    "wof:name":"Airmack Consulting Inc",
    "wof:placetype":"venue"
},
  "geometry": {"coordinates":[-71.388863,41.75956],"type":"Point"}
}