{
  "type": "Feature",
  "properties": {
    "iso:country":"US",
    "sg:address":"175 Eddie Dowling Hwy",
    "sg:city":"Woonsocket",
    "sg:classifiers":[
        {
            "category":"Personal",
            "type":"Services"
        }
    ],
    "sg:phone":"+1 401 767 3300",
    "sg:postcode":"02896",
    "sg:province":"RI",
    "sg:tags":[
        "tuxedo",
        "rent"
    ],
    "wof:name":"Waldorf Tuxedo LLC",
    "wof:placetype":"venue"
},
  "geometry": {"coordinates":[-71.51273399999999,41.978542],"type":"Point"}
}