{
  "type": "Feature",
  "properties": {
    "iso:country":"US",
    "sg:address":"98 Granite St",
    "sg:city":"Westerly",
    "sg:classifiers":[
        {
            "category":"Manufacturing",
            "subcategory":"Tools & Machinery",
            "type":"Manufacturing & Wholesale Goods"
        }
    ],
    "sg:phone":"+1 401 596 2680",
    "sg:postcode":"02891",
    "sg:province":"RI",
    "sg:tags":[
        "equipment",
        "printing"
    ],
    "wof:name":"Concept Engineering",
    "wof:placetype":"venue"
},
  "geometry": {"coordinates":[-71.820477,41.373346],"type":"Point"}
}