{
  "type": "Feature",
  "properties": {
    "addr:full":"80 3rd St Newport RI 02840",
    "addr:housenumber":"80",
    "addr:postcode":"02840",
    "addr:street":"3Rd St",
    "iso:country":"US",
    "sg:address":"80 3rd St",
    "sg:city":"Newport",
    "sg:classifiers":[
        {
            "category":"Restaurant",
            "type":"Food & Drink"
        }
    ],
    "sg:phone":"+1 401 849 1756",
    "sg:postcode":"02840",
    "sg:province":"RI",
    "sg:tags":[
        "eating"
    ],
    "wof:name":"Melanies Gemstone Original",
    "wof:placetype":"venue"
},
  "geometry": {"coordinates":[-71.319419,41.497902],"type":"Point"}
}