{
  "type": "Feature",
  "properties": {
    "iso:country":"US",
    "sg:address":"15 Walts Way",
    "sg:city":"Narragansett",
    "sg:classifiers":[
        {
            "category":"Wholesale",
            "subcategory":"Seafood",
            "type":"Manufacturing & Wholesale Goods"
        }
    ],
    "sg:phone":"+1 401 783 9560",
    "sg:postcode":"02882",
    "sg:province":"RI",
    "wof:name":"Osprey Seafood Inc",
    "wof:placetype":"venue"
},
  "geometry": {"coordinates":[-71.47937899999999,41.42776],"type":"Point"}
}