{
  "type": "Feature",
  "properties": {
    "iso:country":"US",
    "sg:address":"32 Pier Market Pl",
    "sg:city":"Narragansett",
    "sg:classifiers":[
        {
            "category":"Shopping",
            "subcategory":"Gifts & Souvenirs",
            "type":"Retail Goods"
        }
    ],
    "sg:phone":"+1 401 788 8046",
    "sg:postcode":"02882",
    "sg:province":"RI",
    "sg:tags":[
        "shop"
    ],
    "wof:name":"Shell Boutique",
    "wof:placetype":"venue"
},
  "geometry": {"coordinates":[-71.458224,41.431363],"type":"Point"}
}