{
  "type": "Feature",
  "properties": {
    "iso:country":"US",
    "sg:address":"44 Mare Ter",
    "sg:city":"Portsmouth",
    "sg:classifiers":[
        {
            "category":"Shopping",
            "subcategory":"Florist",
            "type":"Retail Goods"
        }
    ],
    "sg:phone":"+1 401 683 0754",
    "sg:postcode":"02871",
    "sg:province":"RI",
    "wof:name":"Floral Designs",
    "wof:placetype":"venue"
},
  "geometry": {"coordinates":[-71.258157,41.62056],"type":"Point"}
}