{
  "type": "Feature",
  "properties": {
    "iso:country":"US",
    "sg:address":"1893 Elmwood Ave",
    "sg:city":"Warwick",
    "sg:classifiers":[
        {
            "category":"Retail",
            "subcategory":"Laundry & Dry Cleaning",
            "type":"Services"
        }
    ],
    "sg:phone":"+1 401 467 8229",
    "sg:postcode":"02888",
    "sg:province":"RI",
    "sg:tags":[
        "commercial"
    ],
    "wof:name":"Lou's Laundry & Dry Cleaning",
    "wof:placetype":"venue"
},
  "geometry": {"coordinates":[-71.424171,41.756759],"type":"Point"}
}