{
  "type": "Feature",
  "properties": {
    "iso:country":"US",
    "sg:address":"92 Imera Ave",
    "sg:city":"Warwick",
    "sg:classifiers":[
        {
            "category":"Retail",
            "subcategory":"Repair Shop",
            "type":"Services"
        }
    ],
    "sg:phone":"+1 401 921 3090",
    "sg:postcode":"02886",
    "sg:province":"RI",
    "sg:tags":[
        "scooter",
        "motorcycle",
        "motor"
    ],
    "wof:name":"Kustom Creations",
    "wof:placetype":"venue"
},
  "geometry": {"coordinates":[-71.440315,41.72692],"type":"Point"}
}