{
  "type": "Feature",
  "properties": {
    "iso:country":"US",
    "sg:address":"85 Willow Ln",
    "sg:city":"Portsmouth",
    "sg:classifiers":[
        {
            "category":"Real Estate",
            "subcategory":"Real Estate Agent",
            "type":"Services"
        }
    ],
    "sg:phone":"+1 401 683 3621",
    "sg:postcode":"02871",
    "sg:province":"RI",
    "wof:name":"Aquidneck Rental Market",
    "wof:placetype":"venue"
},
  "geometry": {"coordinates":[-71.26107500000001,41.614134],"type":"Point"}
}