{
  "type": "Feature",
  "properties": {
    "iso:country":"US",
    "sg:address":"410 Gooseberry Rd",
    "sg:city":"Wakefield",
    "sg:classifiers":[
        {
            "category":"Shopping",
            "subcategory":"Bicycles & Sporting Goods",
            "type":"Retail Goods"
        }
    ],
    "sg:phone":"+1 401 783 7766",
    "sg:postcode":"02879",
    "sg:province":"RI",
    "sg:tags":[
        "tackle",
        "marina",
        "fish"
    ],
    "sg:website":"www.snugharbormarina.com",
    "wof:name":"Snug Harbor Marina",
    "wof:placetype":"venue"
},
  "geometry": {"coordinates":[-71.519474,41.386926],"type":"Point"}
}