{
  "type": "Feature",
  "properties": {
    "iso:country":"US",
    "sg:address":"1815 Smith St",
    "sg:city":"North Providence",
    "sg:classifiers":[
        {
            "category":"Food & Beverages",
            "subcategory":"Groceries & Convenience Stores",
            "type":"Retail Goods"
        }
    ],
    "sg:phone":"+1 401 231 4245",
    "sg:postcode":"02911",
    "sg:province":"RI",
    "wof:name":"Smith Street Express Mart & Solar Gas",
    "wof:placetype":"venue"
},
  "geometry": {"coordinates":[-71.47370100000001,41.854599],"type":"Point"}
}