{
  "type": "Feature",
  "properties": {
    "addr:full":"75 Eagle Peak Rd Pascoag RI 02859",
    "addr:housenumber":"75",
    "addr:postcode":"02859",
    "addr:street":"Eagle Peak Rd",
    "iso:country":"US",
    "sg:address":"75 Eagle Peak Rd",
    "sg:city":"Pascoag",
    "sg:classifiers":[
        {
            "category":"Building & Trades",
            "subcategory":"Construction",
            "type":"Services"
        }
    ],
    "sg:phone":"+1 401 568 9855",
    "sg:postcode":"02859",
    "sg:province":"RI",
    "sg:tags":[
        "house"
    ],
    "wof:name":"Felice Construction",
    "wof:placetype":"venue"
},
  "geometry": {"coordinates":[-71.708747,41.954454],"type":"Point"}
}