{
  "type": "Feature",
  "properties": {
    "iso:country":"US",
    "sg:address":"61 Reservoir Rd",
    "sg:city":"Lincoln",
    "sg:classifiers":[
        {
            "category":"Real Estate",
            "subcategory":"Real Estate Agent",
            "type":"Services"
        }
    ],
    "sg:phone":"+1 401 765 0040",
    "sg:postcode":"02865",
    "sg:province":"RI",
    "wof:name":"Ferron Realty",
    "wof:placetype":"venue"
},
  "geometry": {"coordinates":[-71.48684299999999,41.950919],"type":"Point"}
}