{
  "type": "Feature",
  "properties": {
    "iso:country":"US",
    "sg:address":"2200 E Main Rd",
    "sg:city":"Portsmouth",
    "sg:classifiers":[
        {
            "category":"Government",
            "subcategory":"Office",
            "type":"Public Place"
        }
    ],
    "sg:phone":"+1 401 683 3717",
    "sg:postcode":"02871",
    "sg:province":"RI",
    "sg:tags":[
        "village"
    ],
    "wof:name":"Board Of Review",
    "wof:placetype":"venue"
},
  "geometry": {"coordinates":[-71.253654,41.591108],"type":"Point"}
}