{
  "type": "Feature",
  "properties": {
    "iso:country":"US",
    "sg:address":"92 W Warwick Ave",
    "sg:city":"West Warwick",
    "sg:classifiers":[
        {
            "category":"Wholesale",
            "subcategory":"Durable Goods & Equipment",
            "type":"Manufacturing & Wholesale Goods"
        }
    ],
    "sg:phone":"+1 401 823 8312",
    "sg:postcode":"02893",
    "sg:province":"RI",
    "sg:tags":[
        "exporter"
    ],
    "wof:name":"Paula Collection",
    "wof:placetype":"venue"
},
  "geometry": {"coordinates":[-71.52341800000001,41.696297],"type":"Point"}
}