{
  "type": "Feature",
  "properties": {
    "iso:country":"US",
    "sg:address":"624 Cranston St",
    "sg:city":"Providence",
    "sg:classifiers":[
        {
            "category":"Food & Beverages",
            "subcategory":"Groceries & Convenience Stores",
            "type":"Retail Goods"
        }
    ],
    "sg:phone":"+1 401 831 5280",
    "sg:postcode":"02907",
    "sg:province":"RI",
    "sg:tags":[
        "grocer"
    ],
    "wof:name":"B & R Centerfood",
    "wof:placetype":"venue"
},
  "geometry": {"coordinates":[-71.436076,41.806538],"type":"Point"}
}