{
  "type": "Feature",
  "properties": {
    "addr:full":"267 Spring St Newport RI 02840",
    "addr:housenumber":"267",
    "addr:postcode":"02840",
    "addr:street":"Spring St",
    "iso:country":"US",
    "sg:address":"267 Spring St",
    "sg:city":"Newport",
    "sg:classifiers":[
        {
            "category":"Shopping",
            "subcategory":"Books",
            "type":"Retail Goods"
        }
    ],
    "sg:phone":"+1 404 841 5800",
    "sg:postcode":"02840",
    "sg:province":"RI",
    "wof:name":"St Judes Catholic Book Store",
    "wof:placetype":"venue"
},
  "geometry": {"coordinates":[-71.31298,41.483507],"type":"Point"}
}