{
  "type": "Feature",
  "properties": {
    "addr:full":"57 Manton Ave Providence RI 02909",
    "addr:housenumber":"57",
    "addr:postcode":"02909",
    "addr:street":"Manton Ave",
    "iso:country":"US",
    "sg:address":"57 Manton Ave",
    "sg:city":"Providence",
    "sg:classifiers":[
        {
            "category":"Personal",
            "subcategory":"Beauty Salon",
            "type":"Services"
        }
    ],
    "sg:phone":"+1 401 831 1052",
    "sg:postcode":"02909",
    "sg:province":"RI",
    "sg:tags":[
        "nail",
        "shop",
        "manicuring"
    ],
    "wof:name":"Swan Nail Salon",
    "wof:placetype":"venue"
},
  "geometry": {"coordinates":[-71.444603,41.817799],"type":"Point"}
}