{
  "type": "Feature",
  "properties": {
    "iso:country":"US",
    "sg:address":"153 Weybosset St",
    "sg:city":"Providence",
    "sg:classifiers":[
        {
            "category":"Recreation",
            "type":"Entertainment"
        }
    ],
    "sg:phone":"+1 401 274 1600",
    "sg:postcode":"02903",
    "sg:province":"RI",
    "sg:tags":[
        "martial",
        "arts",
        "instruction"
    ],
    "wof:name":"Uechi Karate School",
    "wof:placetype":"venue"
},
  "geometry": {"coordinates":[-71.411855,41.822302],"type":"Point"}
}