{
  "type": "Feature",
  "properties": {
    "iso:country":"US",
    "sg:address":"99 Byron Blvd",
    "sg:city":"Warwick",
    "sg:classifiers":[
        {
            "category":"Professional",
            "type":"Services"
        }
    ],
    "sg:phone":"+1 401 461 7086",
    "sg:postcode":"02888",
    "sg:province":"RI",
    "sg:tags":[
        "establishment"
    ],
    "wof:name":"St Vincent De Paul Society-St",
    "wof:placetype":"venue"
},
  "geometry": {"coordinates":[-71.40927000000001,41.759533],"type":"Point"}
}