{
  "type": "Feature",
  "properties": {
    "iso:country":"US",
    "sg:address":"210 Willett Ave",
    "sg:city":"Riverside",
    "sg:classifiers":[
        {
            "category":"Personal",
            "subcategory":"Beauty Salon",
            "type":"Services"
        }
    ],
    "sg:phone":"+1 401 437 1204",
    "sg:postcode":"02915",
    "sg:province":"RI",
    "wof:name":"Edwards Hairdressers",
    "wof:placetype":"venue"
},
  "geometry": {"coordinates":[-71.35687799999999,41.775158],"type":"Point"}
}