{
  "type": "Feature",
  "properties": {
    "iso:country":"US",
    "sg:address":"30 Mount Ave",
    "sg:city":"Providence",
    "sg:classifiers":[
        {
            "category":"Professional",
            "subcategory":"Business Services",
            "type":"Services"
        }
    ],
    "sg:phone":"+1 401 861 2955",
    "sg:postcode":"02906",
    "sg:province":"RI",
    "wof:name":"Selim & Assoc",
    "wof:placetype":"venue"
},
  "geometry": {"coordinates":[-71.388198,41.841386],"type":"Point"}
}