{
  "type": "Feature",
  "properties": {
    "iso:country":"US",
    "sg:address":"184 Obed Ave",
    "sg:city":"North Providence",
    "sg:classifiers":[
        {
            "category":"Building & Trades",
            "subcategory":"Electrical",
            "type":"Services"
        }
    ],
    "sg:phone":"+1 401 725 8552",
    "sg:postcode":"02904",
    "sg:province":"RI",
    "sg:tags":[
        "electric",
        "contractor"
    ],
    "wof:name":"Al's Electric",
    "wof:placetype":"venue"
},
  "geometry": {"coordinates":[-71.425915,41.866179],"type":"Point"}
}