{
  "type": "Feature",
  "properties": {
    "iso:country":"US",
    "sg:address":"79 Putnam Pike",
    "sg:city":"Johnston",
    "sg:classifiers":[
        {
            "category":"Restaurant",
            "type":"Food & Drink"
        }
    ],
    "sg:phone":"+1 401 231 3004",
    "sg:postcode":"02919",
    "sg:province":"RI",
    "sg:tags":[
        "italian"
    ],
    "wof:name":"Reali's Fine Italian Cuisine",
    "wof:placetype":"venue"
},
  "geometry": {"coordinates":[-71.492853,41.86233],"type":"Point"}
}