{
  "type": "Feature",
  "properties": {
    "iso:country":"US",
    "sg:address":"190 Front St",
    "sg:city":"Lincoln",
    "sg:classifiers":[
        {
            "category":"Restaurant",
            "type":"Food & Drink"
        }
    ],
    "sg:phone":"+1 401 727 2704",
    "sg:postcode":"02865",
    "sg:province":"RI",
    "wof:name":"Pam's Front Street Grill",
    "wof:placetype":"venue"
},
  "geometry": {"coordinates":[-71.409232,41.9042],"type":"Point"}
}