{
  "type": "Feature",
  "properties": {
    "addr:full":"78 Astral St Warwick RI 02888",
    "addr:housenumber":"78",
    "addr:postcode":"02888",
    "addr:street":"Astral St",
    "iso:country":"US",
    "sg:address":"78 Astral St",
    "sg:city":"Warwick",
    "sg:classifiers":[
        {
            "category":"Professional",
            "subcategory":"Engineering",
            "type":"Services"
        }
    ],
    "sg:phone":"+1 401 463 8322",
    "sg:postcode":"02888",
    "sg:province":"RI",
    "wof:name":"Affordable Coffins",
    "wof:placetype":"venue"
},
  "geometry": {"coordinates":[-71.410713,41.73887],"type":"Point"}
}