{
  "type": "Feature",
  "properties": {
    "iso:country":"US",
    "sg:address":"127 Eldridge St",
    "sg:city":"Cranston",
    "sg:classifiers":[
        {
            "category":"Building & Trades",
            "subcategory":"Construction",
            "type":"Services"
        }
    ],
    "sg:phone":"+1 401 788 1020",
    "sg:postcode":"02910",
    "sg:province":"RI",
    "sg:tags":[
        "contractor"
    ],
    "wof:name":"Stravato Plastering",
    "wof:placetype":"venue"
},
  "geometry": {"coordinates":[-71.437724,41.782979],"type":"Point"}
}