{
  "type": "Feature",
  "properties": {
    "iso:country":"US",
    "sg:address":"1445 Wampanoag Trl",
    "sg:city":"Riverside",
    "sg:classifiers":[
        {
            "category":"Personal",
            "subcategory":"Beauty Salon",
            "type":"Services"
        }
    ],
    "sg:phone":"+1 401 433 5909",
    "sg:postcode":"02915",
    "sg:province":"RI",
    "sg:tags":[
        "shop"
    ],
    "wof:name":"New England Electrology",
    "wof:placetype":"venue"
},
  "geometry": {"coordinates":[-71.33069500000001,41.778169],"type":"Point"}
}