{
  "type": "Feature",
  "properties": {
    "iso:country":"US",
    "sg:address":"4 Richmond St",
    "sg:city":"Providence",
    "sg:classifiers":[
        {
            "category":"Restaurant",
            "type":"Food & Drink"
        }
    ],
    "sg:phone":"+1 401 521 9229",
    "sg:postcode":"02903",
    "sg:province":"RI",
    "sg:tags":[
        "catering"
    ],
    "wof:name":"Gatehouse Catering Co",
    "wof:placetype":"venue"
},
  "geometry": {"coordinates":[-71.411879,41.820733],"type":"Point"}
}