{
  "type": "Feature",
  "properties": {
    "addr:full":"72 Pine St Providence RI 02903",
    "addr:housenumber":"72",
    "addr:postcode":"02903",
    "addr:street":"Pine St",
    "iso:country":"US",
    "sg:address":"72 Pine St",
    "sg:city":"Providence",
    "sg:classifiers":[
        {
            "category":"Banks & Credit Unions",
            "subcategory":"Financial Services",
            "type":"Services"
        }
    ],
    "sg:phone":"+1 877 408 4040",
    "sg:postcode":"02903",
    "sg:province":"RI",
    "sg:tags":[
        "broker",
        "mortgage"
    ],
    "wof:name":"Civic Mortgage Group Inc",
    "wof:placetype":"venue"
},
  "geometry": {"coordinates":[-71.409739,41.822488],"type":"Point"}
}