{
  "type": "Feature",
  "properties": {
    "iso:country":"US",
    "sg:address":"2364 Diamond Hill Rd",
    "sg:city":"Cumberland",
    "sg:classifiers":[
        {
            "category":"Shopping",
            "subcategory":"Clothing, Apparel, & Fashions",
            "type":"Retail Goods"
        }
    ],
    "sg:phone":"+1 401 334 6019",
    "sg:postcode":"02864",
    "sg:province":"RI",
    "sg:tags":[
        "children's",
        "clothing"
    ],
    "wof:name":"Fairytales",
    "wof:placetype":"venue"
},
  "geometry": {"coordinates":[-71.401349,41.955227],"type":"Point"}
}