{
  "type": "Feature",
  "properties": {
    "iso:country":"US",
    "sg:address":"354 Pine St",
    "sg:city":"Pawtucket",
    "sg:classifiers":[
        {
            "category":"Manufacturing",
            "subcategory":"Retail Goods",
            "type":"Manufacturing & Wholesale Goods"
        }
    ],
    "sg:phone":"+1 401 725 1400",
    "sg:postcode":"02860",
    "sg:province":"RI",
    "sg:tags":[
        "manufacturer"
    ],
    "wof:name":"Pee Bee Industries Inc",
    "wof:placetype":"venue"
},
  "geometry": {"coordinates":[-71.393203,41.880591],"type":"Point"}
}