{
  "type": "Feature",
  "properties": {
    "iso:country":"US",
    "sg:address":"23 Arnold St",
    "sg:city":"Wakefield",
    "sg:classifiers":[
        {
            "category":"Health Services",
            "subcategory":"Hospital",
            "type":"Services"
        }
    ],
    "sg:phone":"+1 401 782 1354",
    "sg:postcode":"02879",
    "sg:province":"RI",
    "sg:tags":[
        "mental"
    ],
    "wof:name":"Craig Conover Ms Lmhc Cags",
    "wof:placetype":"venue"
},
  "geometry": {"coordinates":[-71.485401,41.440542],"type":"Point"}
}