{
  "type": "Feature",
  "properties": {
    "iso:country":"US",
    "sg:address":"5 Everett St",
    "sg:city":"Newport",
    "sg:classifiers":[
        {
            "category":"Social Services",
            "type":"Services"
        }
    ],
    "sg:phone":"+1 401 847 2611",
    "sg:postcode":"02840",
    "sg:province":"RI",
    "wof:name":"Child Fmly Svcs of Nwport Cnty",
    "wof:placetype":"venue"
},
  "geometry": {"coordinates":[-71.306515,41.492525],"type":"Point"}
}