{
  "type": "Feature",
  "properties": {
    "iso:country":"US",
    "sg:address":"55 Providence Ave",
    "sg:city":"East Providence",
    "sg:classifiers":[
        {
            "category":"Retail",
            "subcategory":"Auto Repair",
            "type":"Services"
        }
    ],
    "sg:phone":"+1 401 431 1955",
    "sg:postcode":"02915",
    "sg:province":"RI",
    "sg:tags":[
        "truck"
    ],
    "wof:name":"Providence Diesel & Automotive",
    "wof:placetype":"venue"
},
  "geometry": {"coordinates":[-71.359464,41.766634],"type":"Point"}
}