{
  "type": "Feature",
  "properties": {
    "addr:full":"741 Westminster St Providence RI 02903",
    "addr:housenumber":"741",
    "addr:postcode":"02903",
    "addr:street":"Westminster St",
    "iso:country":"US",
    "sg:address":"741 Westminster St",
    "sg:city":"Providence",
    "sg:classifiers":[
        {
            "category":"Real Estate",
            "subcategory":"Developer",
            "type":"Services"
        }
    ],
    "sg:phone":"+1 401 453 0880",
    "sg:postcode":"02903",
    "sg:province":"RI",
    "wof:name":"FJS Assoc",
    "wof:placetype":"venue"
},
  "geometry": {"coordinates":[-71.420511,41.818163],"type":"Point"}
}