{
  "type": "Feature",
  "properties": {
    "iso:country":"US",
    "sg:address":"1445 Wampanoag Trl",
    "sg:city":"Riverside",
    "sg:classifiers":[
        {
            "category":"Banks & Credit Unions",
            "subcategory":"Investment Brokerage",
            "type":"Services"
        }
    ],
    "sg:phone":"+1 401 437 9328",
    "sg:postcode":"02915",
    "sg:province":"RI",
    "sg:tags":[
        "retirement",
        "planning"
    ],
    "wof:name":"DMW Assoc",
    "wof:placetype":"venue"
},
  "geometry": {"coordinates":[-71.33069500000001,41.778169],"type":"Point"}
}