{
  "type": "Feature",
  "properties": {
    "iso:country":"US",
    "sg:address":"3 Evergreen St",
    "sg:city":"Cranston",
    "sg:classifiers":[
        {
            "category":"Health Services",
            "subcategory":"Nursing And Care Facility",
            "type":"Services"
        }
    ],
    "sg:phone":"+1 401 785 3053",
    "sg:postcode":"02910",
    "sg:province":"RI",
    "wof:name":"West Bay Residential Services",
    "wof:placetype":"venue"
},
  "geometry": {"coordinates":[-71.41892300000001,41.768612],"type":"Point"}
}