{
  "type": "Feature",
  "properties": {
    "addr:full":"260 Wilson Ave Rumford RI 02916",
    "addr:housenumber":"260",
    "addr:postcode":"02916",
    "addr:street":"Wilson Ave",
    "iso:country":"US",
    "sg:address":"260 Wilson Ave",
    "sg:city":"Rumford",
    "sg:classifiers":[
        {
            "category":"Communications",
            "subcategory":"Film & Video Production",
            "type":"Services"
        }
    ],
    "sg:phone":"+1 401 431 0092",
    "sg:postcode":"02916",
    "sg:province":"RI",
    "sg:tags":[
        "motion"
    ],
    "wof:name":"Devlo Media",
    "wof:placetype":"venue"
},
  "geometry": {"coordinates":[-71.355773,41.844545],"type":"Point"}
}