{
  "type": "Feature",
  "properties": {
    "addr:full":"25 Circle St Rumford RI 02916",
    "addr:housenumber":"25",
    "addr:postcode":"02916",
    "addr:street":"Circle St",
    "iso:country":"US",
    "sg:address":"25 Circle St",
    "sg:city":"Rumford",
    "sg:classifiers":[
        {
            "category":"Shopping",
            "subcategory":"Jewelry",
            "type":"Retail Goods"
        }
    ],
    "sg:phone":"+1 401 438 2760",
    "sg:postcode":"02916",
    "sg:province":"RI",
    "sg:tags":[
        "designer"
    ],
    "wof:name":"Michael John Ltd",
    "wof:placetype":"venue"
},
  "geometry": {"coordinates":[-71.352966,41.853778],"type":"Point"}
}