{
  "type": "Feature",
  "properties": {
    "iso:country":"US",
    "sg:address":"1368 Broad St",
    "sg:city":"Central Falls",
    "sg:classifiers":[
        {
            "category":"Building & Trades",
            "subcategory":"Locksmith",
            "type":"Services"
        }
    ],
    "sg:phone":"+1 401 889 2205",
    "sg:postcode":"02863",
    "sg:province":"RI",
    "sg:tags":[
        "key"
    ],
    "wof:name":"Aabc Locksmith 24 7",
    "wof:placetype":"venue"
},
  "geometry": {"coordinates":[-71.389257,41.898363],"type":"Point"}
}