{
  "type": "Feature",
  "properties": {
    "iso:country":"US",
    "sg:address":"540 Weeden St",
    "sg:city":"Pawtucket",
    "sg:classifiers":[
        {
            "category":"Professional",
            "subcategory":"Printing & Photocopies",
            "type":"Services"
        }
    ],
    "sg:phone":"+1 401 475 7288",
    "sg:postcode":"02860",
    "sg:province":"RI",
    "sg:tags":[
        "screen"
    ],
    "wof:name":"Classsick Custom",
    "wof:placetype":"venue"
},
  "geometry": {"coordinates":[-71.406418,41.877301],"type":"Point"}
}