{
  "type": "Feature",
  "properties": {
    "iso:country":"US",
    "sg:address":"20 Main St",
    "sg:city":"North Kingstown",
    "sg:classifiers":[
        {
            "category":"Professional",
            "subcategory":"Lawyer & Legal Services",
            "type":"Services"
        }
    ],
    "sg:phone":"+1 401 295 5800",
    "sg:postcode":"02852",
    "sg:province":"RI",
    "sg:tags":[
        "attorney"
    ],
    "wof:name":"Paul A Sollitto",
    "wof:placetype":"venue"
},
  "geometry": {"coordinates":[-71.45126500000001,41.571645],"type":"Point"}
}