{
  "type": "Feature",
  "properties": {
    "addr:full":"138 Mathewson St Providence RI 02903",
    "addr:housenumber":"138",
    "addr:postcode":"02903",
    "addr:street":"Mathewson St",
    "iso:country":"US",
    "sg:address":"138 Mathewson St",
    "sg:city":"Providence",
    "sg:classifiers":[
        {
            "category":"Education",
            "subcategory":"School",
            "type":"Public Place"
        }
    ],
    "sg:phone":"+1 401 278 0563",
    "sg:postcode":"02903",
    "sg:province":"RI",
    "wof:name":"Providence Place Academy",
    "wof:placetype":"venue"
},
  "geometry": {"coordinates":[-71.413961,41.822612],"type":"Point"}
}