{
  "type": "Feature",
  "properties": {
    "iso:country":"US",
    "sg:address":"12 Humbert St",
    "sg:city":"North Providence",
    "sg:classifiers":[
        {
            "category":"Professional",
            "type":"Services"
        }
    ],
    "sg:phone":"+1 401 231 7268",
    "sg:postcode":"02911",
    "sg:province":"RI",
    "wof:name":"J C Molds",
    "wof:placetype":"venue"
},
  "geometry": {"coordinates":[-71.476434,41.84478],"type":"Point"}
}