{
  "type": "Feature",
  "properties": {
    "addr:full":"305 Oliphant Ln Middletown RI 02842",
    "addr:housenumber":"305",
    "addr:postcode":"02842",
    "addr:street":"Oliphant Ln",
    "iso:country":"US",
    "sg:address":"305 Oliphant Ln",
    "sg:city":"Middletown",
    "sg:classifiers":[
        {
            "category":"Wholesale",
            "subcategory":"Electrical",
            "type":"Manufacturing & Wholesale Goods"
        }
    ],
    "sg:phone":"+1 401 846 3333",
    "sg:postcode":"02842",
    "sg:province":"RI",
    "sg:tags":[
        "equipment",
        "electric",
        "supply"
    ],
    "wof:name":"Baynes & Jones Electrical Sups",
    "wof:placetype":"venue"
},
  "geometry": {"coordinates":[-71.280496,41.537401],"type":"Point"}
}