{
  "type": "Feature",
  "properties": {
    "addr:full":"1050 Main St East Greenwich RI 02818",
    "addr:housenumber":"1050",
    "addr:postcode":"02818",
    "addr:street":"Main St",
    "iso:country":"US",
    "sg:address":"1050 Main St",
    "sg:city":"East Greenwich",
    "sg:classifiers":[
        {
            "category":"Health Services",
            "subcategory":"Doctor",
            "type":"Services"
        }
    ],
    "sg:phone":"+1 401 886 7030",
    "sg:postcode":"02818",
    "sg:province":"RI",
    "sg:tags":[
        "physician",
        "surgeon"
    ],
    "wof:name":"Simon Melnick DO",
    "wof:placetype":"venue"
},
  "geometry": {"coordinates":[-71.457634,41.650446],"type":"Point"}
}