{
  "type": "Feature",
  "properties": {
    "addr:full":"468 Weeden St Pawtucket RI 02860",
    "addr:housenumber":"468",
    "addr:postcode":"02860",
    "addr:street":"Weeden St",
    "iso:country":"US",
    "sg:address":"468 Weeden St",
    "sg:city":"Pawtucket",
    "sg:classifiers":[
        {
            "category":"Real Estate",
            "subcategory":"Real Estate Agent",
            "type":"Services"
        }
    ],
    "sg:phone":"+1 401 480 5594",
    "sg:postcode":"02860",
    "sg:province":"RI",
    "wof:name":"Abelinos Enterprise",
    "wof:placetype":"venue"
},
  "geometry": {"coordinates":[-71.403716,41.876982],"type":"Point"}
}