{
  "type": "Feature",
  "properties": {
    "addr:full":"321 Great Island Rd Narragansett RI 02882",
    "addr:housenumber":"321",
    "addr:postcode":"02882",
    "addr:street":"Great Island Rd",
    "iso:country":"US",
    "sg:address":"321 Great Island Rd",
    "sg:city":"Narragansett",
    "sg:classifiers":[
        {
            "category":"Restaurant",
            "type":"Food & Drink"
        }
    ],
    "sg:phone":"+1 401 783 3821",
    "sg:postcode":"02882",
    "sg:province":"RI",
    "wof:name":"Port Side Restaurant",
    "wof:placetype":"venue"
},
  "geometry": {"coordinates":[-71.50691999999999,41.384791],"type":"Point"}
}