{
  "type": "Feature",
  "properties": {
    "addr:full":"288 Oxford St Providence RI 02905",
    "addr:housenumber":"288",
    "addr:postcode":"02905",
    "addr:street":"Oxford St",
    "iso:country":"US",
    "sg:address":"288 Oxford St",
    "sg:city":"Providence",
    "sg:classifiers":[
        {
            "category":"Social Services",
            "subcategory":"Child Care",
            "type":"Services"
        }
    ],
    "sg:phone":"+1 401 461 3631",
    "sg:postcode":"02905",
    "sg:province":"RI",
    "wof:name":"Talitha's Day Care",
    "wof:placetype":"venue"
},
  "geometry": {"coordinates":[-71.41561299999999,41.80091],"type":"Point"}
}