{
  "type": "Feature",
  "properties": {
    "iso:country":"US",
    "sg:address":"860 Tiogue Ave",
    "sg:city":"Coventry",
    "sg:classifiers":[
        {
            "category":"Professional",
            "subcategory":"Lawyer & Legal Services",
            "type":"Services"
        }
    ],
    "sg:phone":"+1 401 828 8282",
    "sg:postcode":"02816",
    "sg:province":"RI",
    "sg:tags":[
        "attorney"
    ],
    "wof:name":"Blasbalg & Hammer",
    "wof:placetype":"venue"
},
  "geometry": {"coordinates":[-71.56795700000001,41.680771],"type":"Point"}
}