{
  "type": "Feature",
  "properties": {
    "addr:full":"6 Butterfield Rd Kingston RI 02881",
    "addr:housenumber":"6",
    "addr:postcode":"02881",
    "addr:street":"Butterfield Rd",
    "iso:country":"US",
    "sg:address":"6 Butterfield Rd",
    "sg:city":"Kingston",
    "sg:classifiers":[
        {
            "category":"Professional",
            "subcategory":"Research",
            "type":"Services"
        }
    ],
    "sg:phone":"+1 401 782 8738",
    "sg:postcode":"02881",
    "sg:province":"RI",
    "sg:tags":[
        "laboratory"
    ],
    "wof:name":"Lab Corp",
    "wof:placetype":"venue"
},
  "geometry": {"coordinates":[-71.531633,41.486763],"type":"Point"}
}