{
  "type": "Feature",
  "properties": {
    "iso:country":"US",
    "sg:address":"37 Baldwin Rd",
    "sg:city":"Portsmouth",
    "sg:classifiers":[
        {
            "category":"Freight",
            "type":"Transportation"
        }
    ],
    "sg:phone":"+1 401 683 4226",
    "sg:postcode":"02871",
    "sg:province":"RI",
    "sg:tags":[
        "trucking"
    ],
    "wof:name":"Coastal Freight Management",
    "wof:placetype":"venue"
},
  "geometry": {"coordinates":[-71.257803,41.581226],"type":"Point"}
}