{
  "type": "Feature",
  "properties": {
    "addr:full":"280 Town Farm Rd Coventry RI 02816",
    "addr:housenumber":"280",
    "addr:postcode":"02816",
    "addr:street":"Town Farm Rd",
    "iso:country":"US",
    "sg:address":"280 Town Farm Rd",
    "sg:city":"Coventry",
    "sg:classifiers":[
        {
            "category":"Building & Trades",
            "subcategory":"Construction",
            "type":"Services"
        }
    ],
    "sg:phone":"+1 401 397 4351",
    "sg:postcode":"02816",
    "sg:province":"RI",
    "sg:tags":[
        "house"
    ],
    "wof:name":"Gauvin Gerard General Contr",
    "wof:placetype":"venue"
},
  "geometry": {"coordinates":[-71.61835499999999,41.710355],"type":"Point"}
}