{
  "type": "Feature",
  "properties": {
    "iso:country":"US",
    "sg:address":"3 Francisco Dr",
    "sg:city":"Middletown",
    "sg:classifiers":[
        {
            "category":"Building & Trades",
            "subcategory":"Cleaning & Sanitation",
            "type":"Services"
        }
    ],
    "sg:phone":"+1 401 846 2897",
    "sg:postcode":"02842",
    "sg:province":"RI",
    "sg:tags":[
        "maintenance"
    ],
    "wof:name":"Imperial Window & Floor Care",
    "wof:placetype":"venue"
},
  "geometry": {"coordinates":[-71.289759,41.527642],"type":"Point"}
}