{
  "type": "Feature",
  "properties": {
    "iso:country":"US",
    "sg:address":"518 Hartford Ave",
    "sg:city":"Providence",
    "sg:classifiers":[
        {
            "category":"Social Services",
            "type":"Services"
        }
    ],
    "sg:phone":"+1 401 273 2000",
    "sg:postcode":"02909",
    "sg:province":"RI",
    "sg:tags":[
        "organization"
    ],
    "wof:name":"Pro-Cap",
    "wof:placetype":"venue"
},
  "geometry": {"coordinates":[-71.46151,41.818892],"type":"Point"}
}