{
  "type": "Feature",
  "properties": {
    "iso:country":"US",
    "sg:address":"106 Phenix Ave",
    "sg:city":"Cranston",
    "sg:classifiers":[
        {
            "category":"Home & Garden",
            "subcategory":"Carpets & Floor Coverings",
            "type":"Retail Goods"
        }
    ],
    "sg:phone":"+1 401 943 8555",
    "sg:postcode":"02920",
    "sg:province":"RI",
    "sg:tags":[
        "dealer",
        "window",
        "rug",
        "treatment"
    ],
    "wof:name":"C & S Interiors Inc",
    "wof:placetype":"venue"
},
  "geometry": {"coordinates":[-71.46989600000001,41.781204],"type":"Point"}
}