{
  "type": "Feature",
  "properties": {
    "iso:country":"US",
    "sg:address":"50 Nashua St",
    "sg:city":"Providence",
    "sg:classifiers":[
        {
            "category":"Insurance",
            "subcategory":"Insurance Agent",
            "type":"Services"
        }
    ],
    "sg:phone":"+1 401 331 9427",
    "sg:postcode":"02904",
    "sg:province":"RI",
    "wof:name":"M & F Insurance Inc",
    "wof:placetype":"venue"
},
  "geometry": {"coordinates":[-71.40409099999999,41.850273],"type":"Point"}
}