{
  "type": "Feature",
  "properties": {
    "iso:country":"US",
    "sg:address":"17 City View Pkwy",
    "sg:city":"Johnston",
    "sg:classifiers":[
        {
            "category":"Building & Trades",
            "subcategory":"Landscaping Services",
            "type":"Services"
        }
    ],
    "sg:phone":"+1 401 831 8928",
    "sg:postcode":"02919",
    "sg:province":"RI",
    "sg:tags":[
        "tree",
        "design",
        "maintenance"
    ],
    "wof:name":"Exterior Design Inc",
    "wof:placetype":"venue"
},
  "geometry": {"coordinates":[-71.483566,41.82336],"type":"Point"}
}