{
  "type": "Feature",
  "properties": {
    "iso:country":"US",
    "sg:address":"333 Adelaide Ave",
    "sg:city":"Providence",
    "sg:classifiers":[
        {
            "category":"Restaurant",
            "type":"Food & Drink"
        }
    ],
    "sg:phone":"+1 401 781 8883",
    "sg:postcode":"02907",
    "sg:province":"RI",
    "wof:name":"Xin's Garden",
    "wof:placetype":"venue"
},
  "geometry": {"coordinates":[-71.42980799999999,41.794519],"type":"Point"}
}