{
  "type": "Feature",
  "properties": {
    "iso:country":"US",
    "sg:address":"512 Main St",
    "sg:city":"Wakefield",
    "sg:classifiers":[
        {
            "category":"Professional",
            "type":"Services"
        }
    ],
    "sg:phone":"+1 401 789 7848",
    "sg:postcode":"02879",
    "sg:province":"RI",
    "sg:tags":[
        "establishment"
    ],
    "wof:name":"Center For Neuropsychology",
    "wof:placetype":"venue"
},
  "geometry": {"coordinates":[-71.50447699999999,41.43571],"type":"Point"}
}