{
  "type": "Feature",
  "properties": {
    "addr:full":"11 Princess Pine Rd Lincoln RI 02865",
    "addr:housenumber":"11",
    "addr:postcode":"02865",
    "addr:street":"Princess Pine Rd",
    "iso:country":"US",
    "sg:address":"11 Princess Pine Rd",
    "sg:city":"Lincoln",
    "sg:classifiers":[
        {
            "category":"Building & Trades",
            "subcategory":"Electrical",
            "type":"Services"
        }
    ],
    "sg:phone":"+1 401 723 0993",
    "sg:postcode":"02865",
    "sg:province":"RI",
    "sg:tags":[
        "electrician"
    ],
    "wof:name":"Mays Electrical Maint Const Co Inc",
    "wof:placetype":"venue"
},
  "geometry": {"coordinates":[-71.46880299999999,41.898899],"type":"Point"}
}