{
  "type": "Feature",
  "properties": {
    "iso:country":"US",
    "sg:address":"164 High St",
    "sg:city":"Westerly",
    "sg:classifiers":[
        {
            "category":"Recreation",
            "type":"Entertainment"
        }
    ],
    "sg:phone":"+1 401 596 8529",
    "sg:postcode":"02891",
    "sg:province":"RI",
    "sg:tags":[
        "ticket"
    ],
    "wof:name":"Ticket Center",
    "wof:placetype":"venue"
},
  "geometry": {"coordinates":[-71.823229,41.386167],"type":"Point"}
}