{
  "type": "Feature",
  "properties": {
    "iso:country":"US",
    "sg:address":"81 Richmond St",
    "sg:city":"Providence",
    "sg:classifiers":[
        {
            "category":"Banks & Credit Unions",
            "subcategory":"Bank",
            "type":"Services"
        }
    ],
    "sg:phone":"+1 401 274 5050",
    "sg:postcode":"02903",
    "sg:province":"RI",
    "sg:tags":[
        "mortgage",
        "loan",
        "broker",
        "real estate"
    ],
    "wof:name":"Friendship Mortgage Co",
    "wof:placetype":"venue"
},
  "geometry": {"coordinates":[-71.41149900000001,41.820599],"type":"Point"}
}