{
  "type": "Feature",
  "properties": {
    "iso:country":"US",
    "sg:address":"64 Westfield Dr",
    "sg:city":"Cranston",
    "sg:classifiers":[
        {
            "category":"Retail",
            "subcategory":"Repair Shop",
            "type":"Services"
        }
    ],
    "sg:phone":"+1 401 942 2655",
    "sg:postcode":"02920",
    "sg:province":"RI",
    "sg:tags":[
        "television",
        "radio",
        "radio-service"
    ],
    "wof:name":"Richard's TV & Electronics",
    "wof:placetype":"venue"
},
  "geometry": {"coordinates":[-71.49474499999999,41.790111],"type":"Point"}
}