{
  "type": "Feature",
  "properties": {
    "addr:full":"64 Benefit St Pawtucket RI 02861",
    "addr:housenumber":"64",
    "addr:postcode":"02861",
    "addr:street":"Benefit St",
    "iso:country":"US",
    "sg:address":"64 Benefit St",
    "sg:city":"Pawtucket",
    "sg:classifiers":[
        {
            "category":"Building & Trades",
            "subcategory":"Construction",
            "type":"Services"
        }
    ],
    "sg:phone":"+1 401 724 5671",
    "sg:postcode":"02861",
    "sg:province":"RI",
    "sg:tags":[
        "excavation",
        "contractor"
    ],
    "wof:name":"A J Excavation Inc",
    "wof:placetype":"venue"
},
  "geometry": {"coordinates":[-71.370006,41.892728],"type":"Point"}
}