{
  "type": "Feature",
  "properties": {
    "iso:country":"US",
    "sg:address":"60 Bay St",
    "sg:city":"Westerly",
    "sg:classifiers":[
        {
            "category":"Shopping",
            "subcategory":"Books",
            "type":"Retail Goods"
        }
    ],
    "sg:phone":"+1 401 348 0940",
    "sg:postcode":"02891",
    "sg:province":"RI",
    "sg:tags":[
        "dealer"
    ],
    "wof:name":"Mo Books N Art",
    "wof:placetype":"venue"
},
  "geometry": {"coordinates":[-71.85774600000001,41.309798],"type":"Point"}
}