{
  "type": "Feature",
  "properties": {
    "iso:country":"US",
    "sg:address":"299 Carpenter St",
    "sg:city":"Providence",
    "sg:classifiers":[
        {
            "category":"Manufacturing",
            "subcategory":"Furniture",
            "type":"Manufacturing & Wholesale Goods"
        },
        {
            "category":"Wholesale",
            "subcategory":"Jewelry",
            "type":"Manufacturing & Wholesale Goods"
        }
    ],
    "sg:phone":"+1 401 331 9567",
    "sg:postcode":"02909",
    "sg:province":"RI",
    "sg:tags":[
        "contractor",
        "wood",
        "mfg"
    ],
    "wof:name":"Stacy Enterprises",
    "wof:placetype":"venue"
},
  "geometry": {"coordinates":[-71.42845,41.818162],"type":"Point"}
}