{
  "type": "Feature",
  "properties": {
    "addr:full":"118 Manton Ave Providence RI 02909",
    "addr:housenumber":"118",
    "addr:postcode":"02909",
    "addr:street":"Manton Ave",
    "iso:country":"US",
    "sg:address":"118 Manton Ave",
    "sg:city":"Providence",
    "sg:classifiers":[
        {
            "category":"Autos & Motor Vehicles",
            "subcategory":"Boat Sales",
            "type":"Retail Goods"
        },
        {
            "category":"Wholesale",
            "subcategory":"Sporting Goods",
            "type":"Manufacturing & Wholesale Goods"
        }
    ],
    "sg:phone":"+1 401 751 3080",
    "sg:postcode":"02909",
    "sg:province":"RI",
    "sg:tags":[
        "top",
        "upholstery",
        "cover"
    ],
    "wof:name":"Canvas Shop",
    "wof:placetype":"venue"
},
  "geometry": {"coordinates":[-71.44655400000001,41.819673],"type":"Point"}
}