{
  "type": "Feature",
  "properties": {
    "addr:full":"238 Mapleton St Cranston RI 02910",
    "addr:housenumber":"238",
    "addr:postcode":"02910",
    "addr:street":"Mapleton St",
    "iso:country":"US",
    "sg:address":"238 Mapleton St",
    "sg:city":"Cranston",
    "sg:classifiers":[
        {
            "category":"Building & Trades",
            "subcategory":"Construction",
            "type":"Services"
        }
    ],
    "sg:phone":"+1 401 467 8331",
    "sg:postcode":"02910",
    "sg:province":"RI",
    "sg:tags":[
        "house",
        "carpentry",
        "contractor"
    ],
    "wof:name":"Paul D Hathaway Carpentry",
    "wof:placetype":"venue"
},
  "geometry": {"coordinates":[-71.432309,41.767952],"type":"Point"}
}