{
  "type": "Feature",
  "properties": {
    "iso:country":"US",
    "sg:address":"2944 Post Rd",
    "sg:city":"Warwick",
    "sg:classifiers":[
        {
            "category":"Building & Trades",
            "subcategory":"Landscaping Services",
            "type":"Services"
        }
    ],
    "sg:phone":"+1 401 737 2042",
    "sg:postcode":"02886",
    "sg:province":"RI",
    "sg:tags":[
        "landscape",
        "contractor"
    ],
    "wof:name":"Hollywood Landscaping Inc",
    "wof:placetype":"venue"
},
  "geometry": {"coordinates":[-71.453676,41.704352],"type":"Point"}
}