{
  "type": "Feature",
  "properties": {
    "iso:country":"US",
    "sg:address":"55 Beach St",
    "sg:city":"Westerly",
    "sg:classifiers":[
        {
            "category":"Shopping",
            "subcategory":"Clothing, Apparel, & Fashions",
            "type":"Retail Goods"
        }
    ],
    "sg:phone":"+1 401 596 3670",
    "sg:postcode":"02891",
    "sg:province":"RI",
    "sg:tags":[
        "cards",
        "costume",
        "jewelry",
        "gift",
        "greeting"
    ],
    "wof:name":"Panache",
    "wof:placetype":"venue"
},
  "geometry": {"coordinates":[-71.829882,41.364994],"type":"Point"}
}