{
  "type": "Feature",
  "properties": {
    "iso:country":"US",
    "sg:address":"50 Park Row W",
    "sg:city":"Providence",
    "sg:classifiers":[
        {
            "category":"Real Estate",
            "subcategory":"Real Estate Operator",
            "type":"Services"
        }
    ],
    "sg:phone":"+1 401 274 5550",
    "sg:postcode":"02903",
    "sg:province":"RI",
    "sg:tags":[
        "apartment"
    ],
    "sg:website":"www.avaloncommunities.com/avalon...",
    "wof:name":"Avalon at Center Place",
    "wof:placetype":"venue"
},
  "geometry": {"coordinates":[-71.412744,41.828682],"type":"Point"}
}