{
  "type": "Feature",
  "properties": {
    "addr:full":"88 Silva Lane Middletown RI 02842",
    "addr:housenumber":"88",
    "addr:postcode":"02842",
    "addr:street":"Silva Lane",
    "iso:country":"US",
    "sg:address":"88 Silva Lane",
    "sg:city":"Middletown",
    "sg:classifiers":[
        {
            "category":"Professional",
            "subcategory":"Computer Services",
            "type":"Services"
        }
    ],
    "sg:phone":"+1 866 848 5848",
    "sg:postcode":"02842",
    "sg:province":"RI",
    "sg:tags":[
        "broadband",
        "wireless-broadband",
        "wimax",
        "4g",
        "internet",
        "redundancy",
        "reliability",
        "t1",
        "ds3",
        "oc3",
        "t3"
    ],
    "sg:website":"http://www.towerstream.com",
    "wof:name":"Towerstream",
    "wof:placetype":"venue"
},
  "geometry": {"coordinates":[-71.285141,41.499219],"type":"Point"}
}