{
  "type": "Feature",
  "properties": {
    "addr:full":"1775 Bald Hill Rd Warwick RI 02886",
    "addr:housenumber":"1775",
    "addr:postcode":"02886",
    "addr:street":"Bald Hill Rd",
    "iso:country":"US",
    "sg:address":"1775 Bald Hill Rd",
    "sg:city":"Warwick",
    "sg:classifiers":[
        {
            "category":"Health Services",
            "subcategory":"Doctor",
            "type":"Services"
        }
    ],
    "sg:phone":"+1 401 822 1866",
    "sg:postcode":"02886",
    "sg:province":"RI",
    "sg:tags":[
        "dentist"
    ],
    "sg:website":"www.aspendent.com",
    "wof:name":"Aspen Dental",
    "wof:placetype":"venue"
},
  "geometry": {"coordinates":[-71.500079,41.691477],"type":"Point"}
}