{
  "type": "Feature",
  "properties": {
    "addr:full":"79 Hobson Ave North Providence RI 02911",
    "addr:housenumber":"79",
    "addr:postcode":"02911",
    "addr:street":"Hobson Ave",
    "iso:country":"US",
    "sg:address":"79 Hobson Ave",
    "sg:city":"North Providence",
    "sg:classifiers":[
        {
            "category":"Real Estate",
            "subcategory":"Real Estate Agent",
            "type":"Services"
        }
    ],
    "sg:phone":"+1 401 232 5450",
    "sg:postcode":"02911",
    "sg:province":"RI",
    "wof:name":"Re/Max Providence",
    "wof:placetype":"venue"
},
  "geometry": {"coordinates":[-71.472798,41.857363],"type":"Point"}
}