{
  "type": "Feature",
  "properties": {
    "iso:country":"US",
    "sg:address":"87 Shore Rd",
    "sg:city":"Riverside",
    "sg:classifiers":[
        {
            "category":"Personal",
            "subcategory":"Beauty Salon",
            "type":"Services"
        }
    ],
    "sg:phone":"+1 401 265 0787",
    "sg:postcode":"02915",
    "sg:province":"RI",
    "wof:name":"Chrissy's Pink Beauty Parlor",
    "wof:placetype":"venue"
},
  "geometry": {"coordinates":[-71.366631,41.766472],"type":"Point"}
}