{
  "type": "Feature",
  "properties": {
    "iso:country":"US",
    "sg:address":"1862 Broad St",
    "sg:city":"Cranston",
    "sg:classifiers":[
        {
            "category":"Wholesale",
            "subcategory":"Non-durable Goods",
            "type":"Manufacturing & Wholesale Goods"
        }
    ],
    "sg:phone":"+1 401 461 4192",
    "sg:postcode":"02905",
    "sg:province":"RI",
    "sg:tags":[
        "advertising"
    ],
    "wof:name":"Boston Business Gifts",
    "wof:placetype":"venue"
},
  "geometry": {"coordinates":[-71.398843,41.775553],"type":"Point"}
}