{
  "type": "Feature",
  "properties": {
    "addr:full":"122 Fountain St Providence RI 02903",
    "addr:housenumber":"122",
    "addr:postcode":"02903",
    "addr:street":"Fountain St",
    "iso:country":"US",
    "sg:address":"122 Fountain St",
    "sg:city":"Providence",
    "sg:classifiers":[
        {
            "category":"Travel",
            "subcategory":"Hotels & Motels",
            "type":"Entertainment"
        },
        {
            "category":"Bars & Pubs",
            "subcategory":"Nightclub",
            "type":"Food & Drink"
        }
    ],
    "sg:phone":"+1 401 751 1133",
    "sg:postcode":"02903",
    "sg:province":"RI",
    "sg:tags":[
        "nightlife"
    ],
    "wof:name":"Sportsman's Inn Inc",
    "wof:placetype":"venue"
},
  "geometry": {"coordinates":[-71.416,41.823601],"type":"Point"}
}