{
  "type": "Feature",
  "properties": {
    "addr:full":"2952 Hartford Ave Johnston RI 02919",
    "addr:housenumber":"2952",
    "addr:postcode":"02919",
    "addr:street":"Hartford Ave",
    "iso:country":"US",
    "sg:address":"2952 Hartford Ave",
    "sg:city":"Johnston",
    "sg:classifiers":[
        {
            "category":"Social Services",
            "subcategory":"Child Care",
            "type":"Services"
        }
    ],
    "sg:phone":"+1 401 934 2807",
    "sg:postcode":"02919",
    "sg:province":"RI",
    "wof:name":"Creative Center Daycare",
    "wof:placetype":"venue"
},
  "geometry": {"coordinates":[-71.564701,41.834608],"type":"Point"}
}