{
  "type": "Feature",
  "properties": {
    "addr:full":"3 Wake Robin Rd Lincoln RI 02865",
    "addr:housenumber":"3",
    "addr:postcode":"02865",
    "addr:street":"Wake Robin Rd",
    "iso:country":"US",
    "sg:address":"3 Wake Robin Rd",
    "sg:city":"Lincoln",
    "sg:classifiers":[
        {
            "category":"Sports & Exercise",
            "subcategory":"Gym",
            "type":"Entertainment"
        }
    ],
    "sg:phone":"+1 401 333 3363",
    "sg:postcode":"02865",
    "sg:province":"RI",
    "sg:tags":[
        "club",
        "health",
        "studio",
        "gymnasium"
    ],
    "wof:name":"Fitness Together Of Lincoln",
    "wof:placetype":"venue"
},
  "geometry": {"coordinates":[-71.47627,41.93392],"type":"Point"}
}