{
  "type": "Feature",
  "properties": {
    "iso:country":"US",
    "sg:address":"1 Clinton St",
    "sg:city":"Woonsocket",
    "sg:classifiers":[
        {
            "category":"Building & Trades",
            "subcategory":"Equipment Rental",
            "type":"Services"
        }
    ],
    "sg:phone":"+1 401 765 4942",
    "sg:postcode":"02895",
    "sg:province":"RI",
    "sg:tags":[
        "yard"
    ],
    "wof:name":"First Choice Rentals",
    "wof:placetype":"venue"
},
  "geometry": {"coordinates":[-71.51263299999999,42.003426],"type":"Point"}
}