{
  "type": "Feature",
  "properties": {
    "addr:full":"727 School St Pawtucket RI 02860",
    "addr:housenumber":"727",
    "addr:postcode":"02860",
    "addr:street":"School St",
    "iso:country":"US",
    "sg:address":"727 School St",
    "sg:city":"Pawtucket",
    "sg:classifiers":[
        {
            "category":"Shopping",
            "subcategory":"Crafts & Fabrics",
            "type":"Retail Goods"
        }
    ],
    "sg:phone":"+1 401 727 9070",
    "sg:postcode":"02860",
    "sg:province":"RI",
    "sg:tags":[
        "mfg",
        "sewing",
        "trimming"
    ],
    "wof:name":"Slater Dye Works",
    "wof:placetype":"venue"
},
  "geometry": {"coordinates":[-71.374444,41.859975],"type":"Point"}
}