{
  "type": "Feature",
  "properties": {
    "iso:country":"US",
    "sg:address":"105 Sockanosset Cross Rd",
    "sg:city":"Cranston",
    "sg:classifiers":[
        {
            "category":"Health Services",
            "subcategory":"Doctor",
            "type":"Services"
        }
    ],
    "sg:phone":"+1 401 946 8400",
    "sg:postcode":"02920",
    "sg:province":"RI",
    "sg:tags":[
        "physician",
        "surgeon"
    ],
    "wof:name":"Crossroads Psychiatric Care",
    "wof:placetype":"venue"
},
  "geometry": {"coordinates":[-71.455647,41.754617],"type":"Point"}
}