{
  "type": "Feature",
  "properties": {
    "iso:country":"US",
    "sg:address":"101 Dyer St Ste 400",
    "sg:city":"Providence",
    "sg:classifiers":[
        {
            "category":"Professional",
            "subcategory":"Lawyer & Legal Services",
            "type":"Services"
        }
    ],
    "sg:phone":"+1 401 351 5070",
    "sg:postcode":"02903",
    "sg:province":"RI",
    "sg:tags":[
        "attorney",
        "practice"
    ],
    "sg:website":"http://www.ntlong.com",
    "wof:name":"Nicholas Long Trott Esq",
    "wof:placetype":"venue"
},
  "geometry": {"coordinates":[-71.40835,41.82334],"type":"Point"}
}