{
  "type": "Feature",
  "properties": {
    "addr:full":"139 Rochambeau Ave Providence RI 02906",
    "addr:housenumber":"139",
    "addr:postcode":"02906",
    "addr:street":"Rochambeau Ave",
    "iso:country":"US",
    "sg:address":"139 Rochambeau Ave",
    "sg:city":"Providence",
    "sg:classifiers":[
        {
            "category":"Shopping",
            "subcategory":"Clothing, Apparel, & Fashions",
            "type":"Retail Goods"
        }
    ],
    "sg:phone":"+1 401 861 0136",
    "sg:postcode":"02906",
    "sg:province":"RI",
    "wof:name":"Dressing Room",
    "wof:placetype":"venue"
},
  "geometry": {"coordinates":[-71.39898599999999,41.846558],"type":"Point"}
}