{
  "type": "Feature",
  "properties": {
    "iso:country":"US",
    "sg:address":"1187 Main",
    "sg:city":"Carolina",
    "sg:classifiers":[
        {
            "category":"Shopping",
            "subcategory":"Pharmacy",
            "type":"Retail Goods"
        }
    ],
    "sg:phone":"+1 401 539 4000",
    "sg:postcode":"02812",
    "sg:province":"RI",
    "sg:tags":[
        "drugstore"
    ],
    "wof:name":"Ocean Pharmacy",
    "wof:placetype":"venue"
},
  "geometry": {"coordinates":[-71.664001,41.4739],"type":"Point"}
}