{
  "type": "Feature",
  "properties": {
    "iso:country":"US",
    "sg:address":"348 Allens Ave",
    "sg:city":"Providence",
    "sg:classifiers":[
        {
            "category":"Food & Beverages",
            "subcategory":"Groceries & Convenience Stores",
            "type":"Retail Goods"
        }
    ],
    "sg:phone":"+1 401 781 1730",
    "sg:postcode":"02905",
    "sg:province":"RI",
    "wof:name":"Cumberland Farms Warehouse",
    "wof:placetype":"venue"
},
  "geometry": {"coordinates":[-71.401408,41.80322],"type":"Point"}
}