{
  "type": "Feature",
  "properties": {
    "iso:country":"US",
    "sg:address":"165 Brookhaven Rd",
    "sg:city":"North Kingstown",
    "sg:classifiers":[
        {
            "category":"Professional",
            "subcategory":"Computer Services",
            "type":"Services"
        }
    ],
    "sg:phone":"+1 401 885 2416",
    "sg:postcode":"02852",
    "sg:province":"RI",
    "sg:tags":[
        "repair"
    ],
    "wof:name":"Peachtree Computing",
    "wof:placetype":"venue"
},
  "geometry": {"coordinates":[-71.453502,41.623738],"type":"Point"}
}