{
  "type": "Feature",
  "properties": {
    "addr:full":"319 Broadway Providence RI 02909",
    "addr:housenumber":"319",
    "addr:postcode":"02909",
    "addr:street":"Broadway",
    "iso:country":"US",
    "sg:address":"319 Broadway",
    "sg:city":"Providence",
    "sg:classifiers":[
        {
            "category":"Shopping",
            "subcategory":"Pharmacy",
            "type":"Retail Goods"
        }
    ],
    "sg:phone":"+1 401 421 9276",
    "sg:postcode":"02909",
    "sg:province":"RI",
    "wof:name":"De Pasquale's Pharmacy",
    "wof:placetype":"venue"
},
  "geometry": {"coordinates":[-71.429322,41.819888],"type":"Point"}
}