{
  "type": "Feature",
  "properties": {
    "iso:country":"US",
    "sg:address":"975 Tiogue Ave",
    "sg:city":"Coventry",
    "sg:classifiers":[
        {
            "category":"Restaurant",
            "type":"Food & Drink"
        }
    ],
    "sg:phone":"+1 401 826 7374",
    "sg:postcode":"02816",
    "sg:province":"RI",
    "sg:tags":[
        "parlor",
        "eating",
        "ice",
        "cream"
    ],
    "wof:name":"Michael Gelina's Ice Cream",
    "wof:placetype":"venue"
},
  "geometry": {"coordinates":[-71.573691,41.680198],"type":"Point"}
}