{
  "type": "Feature",
  "properties": {
    "iso:country":"US",
    "sg:address":"49 Strawberry Field Rd",
    "sg:city":"Warwick",
    "sg:classifiers":[
        {
            "category":"Retail",
            "subcategory":"Repair Shop",
            "type":"Services"
        }
    ],
    "sg:phone":"+1 401 737 8359",
    "sg:postcode":"02886",
    "sg:province":"RI",
    "wof:name":"Putnam Equipment Service Inc",
    "wof:placetype":"venue"
},
  "geometry": {"coordinates":[-71.418584,41.70669],"type":"Point"}
}