{
  "type": "Feature",
  "properties": {
    "iso:country":"US",
    "sg:address":"270 Weybosset St",
    "sg:city":"Providence",
    "sg:classifiers":[
        {
            "category":"Organizations",
            "subcategory":"Professional Association",
            "type":"Services"
        },
        {
            "category":"Social Services",
            "type":"Services"
        }
    ],
    "sg:phone":"+1 401 331 3850",
    "sg:postcode":"02903",
    "sg:province":"RI",
    "sg:tags":[
        "youth",
        "educational",
        "economic",
        "center"
    ],
    "wof:name":"Junior Achievement Of Ri Inc",
    "wof:placetype":"venue"
},
  "geometry": {"coordinates":[-71.412865,41.821163],"type":"Point"}
}