{
  "type": "Feature",
  "properties": {
    "iso:country":"US",
    "sg:address":"77 Franklin St",
    "sg:city":"Westerly",
    "sg:classifiers":[
        {
            "category":"Health Services",
            "subcategory":"Doctor",
            "type":"Services"
        }
    ],
    "sg:phone":"+1 401 596 6464",
    "sg:postcode":"02891",
    "sg:province":"RI",
    "sg:tags":[
        "medical"
    ],
    "wof:name":"Westerly Urgent Care Inc",
    "wof:placetype":"venue"
},
  "geometry": {"coordinates":[-71.81490100000001,41.363264],"type":"Point"}
}