{
  "type": "Feature",
  "properties": {
    "iso:country":"US",
    "sg:address":"184 Woonasquatucket Ave",
    "sg:city":"North Providence",
    "sg:classifiers":[
        {
            "category":"Manufacturing",
            "subcategory":"Jewelry",
            "type":"Manufacturing & Wholesale Goods"
        },
        {
            "category":"Wholesale",
            "subcategory":"Jewelry",
            "type":"Manufacturing & Wholesale Goods"
        }
    ],
    "sg:phone":"+1 401 353 2725",
    "sg:postcode":"02911",
    "sg:province":"RI",
    "sg:tags":[
        "stone",
        "costume",
        "mfg"
    ],
    "wof:name":"Fernando's Originals",
    "wof:placetype":"venue"
},
  "geometry": {"coordinates":[-71.474197,41.839346],"type":"Point"}
}