{
  "type": "Feature",
  "properties": {
    "iso:country":"US",
    "sg:address":"756 Hopkins Hill Rd",
    "sg:city":"West Greenwich",
    "sg:classifiers":[
        {
            "category":"Shopping",
            "subcategory":"Clothing, Apparel, & Fashions",
            "type":"Retail Goods"
        }
    ],
    "sg:phone":"+1 401 392 3644",
    "sg:postcode":"02817",
    "sg:province":"RI",
    "sg:tags":[
        "optical"
    ],
    "wof:name":"Milano Eyewear Inc",
    "wof:placetype":"venue"
},
  "geometry": {"coordinates":[-71.564137,41.616041],"type":"Point"}
}