{
  "type": "Feature",
  "properties": {
    "iso:country":"US",
    "sg:address":"1500 Diamond Hill Rd",
    "sg:city":"Woonsocket",
    "sg:classifiers":[
        {
            "category":"Professional",
            "subcategory":"Accounting & Tax Preparation",
            "type":"Services"
        }
    ],
    "sg:phone":"+1 401 767 0752",
    "sg:postcode":"02895",
    "sg:province":"RI",
    "sg:tags":[
        "return",
        "filing"
    ],
    "sg:website":"www.hrblock.com",
    "wof:name":"H & R Block Tax Svc",
    "wof:placetype":"venue"
},
  "geometry": {"coordinates":[-71.47897,42.015913],"type":"Point"}
}