{
  "type": "Feature",
  "properties": {
    "iso:country":"US",
    "sg:address":"138 Main St",
    "sg:city":"East Greenwich",
    "sg:classifiers":[
        {
            "category":"Restaurant",
            "type":"Food & Drink"
        }
    ],
    "sg:menulink":"http://www.allmenus.com/ri/east-greenwich/54989-taste-of-china-ii/menu/",
    "sg:phone":"+1 401 884 4660",
    "sg:postcode":"02818",
    "sg:province":"RI",
    "sg:tags":[
        "asian",
        "chinese"
    ],
    "wof:name":"Taste Of China II",
    "wof:placetype":"venue"
},
  "geometry": {"coordinates":[-71.450022,41.661995],"type":"Point"}
}