{
  "type": "Feature",
  "properties": {
    "addr:full":"15 College Hill Rd Warwick RI 02886",
    "addr:housenumber":"15",
    "addr:postcode":"02886",
    "addr:street":"College Hill Rd",
    "iso:country":"US",
    "sg:address":"15 College Hill Rd",
    "sg:city":"Warwick",
    "sg:classifiers":[
        {
            "category":"Organizations",
            "subcategory":"Professional Association",
            "type":"Services"
        }
    ],
    "sg:phone":"+1 401 822 1126",
    "sg:postcode":"02886",
    "sg:province":"RI",
    "wof:name":"Muscular Dystrophy Assn Inc Fx",
    "wof:placetype":"venue"
},
  "geometry": {"coordinates":[-71.486406,41.713509],"type":"Point"}
}