{
  "type": "Feature",
  "properties": {
    "iso:country":"US",
    "sg:address":"28 Roberta Ave",
    "sg:city":"Pawtucket",
    "sg:classifiers":[
        {
            "category":"Health Services",
            "subcategory":"Health Practitioner",
            "type":"Services"
        }
    ],
    "sg:phone":"+1 401 723 3364",
    "sg:postcode":"02860",
    "sg:province":"RI",
    "wof:name":"Professional Svcs For Women",
    "wof:placetype":"venue"
},
  "geometry": {"coordinates":[-71.38776799999999,41.857633],"type":"Point"}
}