{
  "type": "Feature",
  "properties": {
    "addr:full":"1625 Mineral Spring Ave Providence RI 02904",
    "addr:housenumber":"1625",
    "addr:postcode":"02904",
    "addr:street":"Mineral Spring Ave",
    "iso:country":"US",
    "sg:address":"1625 Mineral Spring Ave",
    "sg:city":"Providence",
    "sg:classifiers":[
        {
            "category":"Banks & Credit Unions",
            "subcategory":"Bank",
            "type":"Services"
        }
    ],
    "sg:phone":"+1 401 353 3100",
    "sg:postcode":"02904",
    "sg:province":"RI",
    "sg:tags":[
        "national",
        "commercial"
    ],
    "wof:name":"Fleet",
    "wof:placetype":"venue"
},
  "geometry": {"coordinates":[-71.449738,41.864211],"type":"Point"}
}