{
  "type": "Feature",
  "properties": {
    "iso:country":"US",
    "sg:address":"4 Farewell St",
    "sg:city":"Newport",
    "sg:classifiers":[
        {
            "category":"Social Services",
            "subcategory":"Job Training",
            "type":"Services"
        }
    ],
    "sg:phone":"+1 401 845 2158",
    "sg:postcode":"02840",
    "sg:province":"RI",
    "wof:name":"Riverwood Rehab Services Inc",
    "wof:placetype":"venue"
},
  "geometry": {"coordinates":[-71.313389,41.490727],"type":"Point"}
}