{
  "type": "Feature",
  "properties": {
    "iso:country":"US",
    "sg:address":"1225 Cranston St",
    "sg:city":"Cranston",
    "sg:classifiers":[
        {
            "category":"Insurance",
            "subcategory":"Insurance Agent",
            "type":"Services"
        }
    ],
    "sg:phone":"+1 401 942 0450",
    "sg:postcode":"02920",
    "sg:province":"RI",
    "wof:name":"International Insurance Agcy",
    "wof:placetype":"venue"
},
  "geometry": {"coordinates":[-71.45114100000001,41.792778],"type":"Point"}
}