{
  "type": "Feature",
  "properties": {
    "iso:country":"US",
    "sg:address":"523 Main St",
    "sg:city":"Pawtucket",
    "sg:classifiers":[
        {
            "category":"Professional",
            "type":"Services"
        }
    ],
    "sg:phone":"+1 401 724 0609",
    "sg:postcode":"02860",
    "sg:province":"RI",
    "sg:tags":[
        "establishment"
    ],
    "wof:name":"K S Enterprises",
    "wof:placetype":"venue"
},
  "geometry": {"coordinates":[-71.391054,41.875761],"type":"Point"}
}