{
  "type": "Feature",
  "properties": {
    "addr:full":"2 New River Rd Manville RI 02838",
    "addr:housenumber":"2",
    "addr:postcode":"02838",
    "addr:street":"New River Rd",
    "iso:country":"US",
    "sg:address":"2 New River Rd",
    "sg:city":"Manville",
    "sg:classifiers":[
        {
            "category":"Autos & Motor Vehicles",
            "subcategory":"Automobile Sales",
            "type":"Retail Goods"
        }
    ],
    "sg:phone":"+1 401 765 1957",
    "sg:postcode":"02838",
    "sg:province":"RI",
    "sg:tags":[
        "car",
        "dealer"
    ],
    "wof:name":"Speed Eez",
    "wof:placetype":"venue"
},
  "geometry": {"coordinates":[-71.46871899999999,41.969097],"type":"Point"}
}