{
  "type": "Feature",
  "properties": {
    "addr:full":"747 Victory Hwy North Smithfield RI 02896",
    "addr:housenumber":"747",
    "addr:postcode":"02896",
    "addr:street":"Victory Hwy",
    "iso:country":"US",
    "sg:address":"747 Victory Hwy",
    "sg:city":"North Smithfield",
    "sg:classifiers":[
        {
            "category":"Health Services",
            "subcategory":"Doctor",
            "type":"Services"
        }
    ],
    "sg:phone":"+1 401 766 2800",
    "sg:postcode":"02896",
    "sg:province":"RI",
    "sg:tags":[
        "dentist"
    ],
    "wof:name":"Dental Associates-N Smithfield",
    "wof:placetype":"venue"
},
  "geometry": {"coordinates":[-71.5834,42.006804],"type":"Point"}
}