{
  "type": "Feature",
  "properties": {
    "iso:country":"US",
    "sg:address":"409 West Ave",
    "sg:city":"Pawtucket",
    "sg:classifiers":[
        {
            "category":"Retail",
            "subcategory":"Auto Repair",
            "type":"Services"
        }
    ],
    "sg:phone":"+1 401 475 1335",
    "sg:postcode":"02860",
    "sg:province":"RI",
    "sg:tags":[
        "repairing",
        "automobile"
    ],
    "wof:name":"Phil's Mobile Fleet Care Inc",
    "wof:placetype":"venue"
},
  "geometry": {"coordinates":[-71.394718,41.865226],"type":"Point"}
}