{
  "type": "Feature",
  "properties": {
    "iso:country":"US",
    "sg:address":"112 Ashaway Rd",
    "sg:city":"Westerly",
    "sg:classifiers":[
        {
            "category":"Organizations",
            "subcategory":"Religious Organization",
            "type":"Services"
        }
    ],
    "sg:phone":"+1 401 348 8863",
    "sg:postcode":"02891",
    "sg:province":"RI",
    "wof:name":"Jehovahs Witnesses Study",
    "wof:placetype":"venue"
},
  "geometry": {"coordinates":[-71.803253,41.394238],"type":"Point"}
}