{
  "type": "Feature",
  "properties": {
    "iso:country":"US",
    "sg:address":"239 Summer St",
    "sg:city":"Cranston",
    "sg:classifiers":[
        {
            "category":"Professional",
            "subcategory":"Computer Services",
            "type":"Services"
        }
    ],
    "sg:phone":"+1 401 941 3782",
    "sg:postcode":"02910",
    "sg:province":"RI",
    "sg:tags":[
        "internet"
    ],
    "wof:name":"RAD Interactive Marketing",
    "wof:placetype":"venue"
},
  "geometry": {"coordinates":[-71.44510699999999,41.766006],"type":"Point"}
}