{
  "type": "Feature",
  "properties": {
    "iso:country":"US",
    "sg:address":"77 Prudence Ave",
    "sg:city":"Providence",
    "sg:classifiers":[
        {
            "category":"Manufacturing",
            "subcategory":"Metals",
            "type":"Manufacturing & Wholesale Goods"
        }
    ],
    "sg:phone":"+1 401 942 1919",
    "sg:postcode":"02909",
    "sg:province":"RI",
    "sg:tags":[
        "polishing"
    ],
    "wof:name":"Windsor Polishing Co",
    "wof:placetype":"venue"
},
  "geometry": {"coordinates":[-71.460618,41.806683],"type":"Point"}
}