{
  "type": "Feature",
  "properties": {
    "iso:country":"US",
    "sg:address":"70 Homer St",
    "sg:city":"Providence",
    "sg:classifiers":[
        {
            "category":"Retail",
            "subcategory":"Auto Repair",
            "type":"Services"
        }
    ],
    "sg:phone":"+1 401 467 5491",
    "sg:postcode":"02905",
    "sg:province":"RI",
    "sg:tags":[
        "automotive"
    ],
    "wof:name":"Old Dead Volvos",
    "wof:placetype":"venue"
},
  "geometry": {"coordinates":[-71.406561,41.787838],"type":"Point"}
}