{
  "type": "Feature",
  "properties": {
    "iso:country":"US",
    "sg:address":"96 Horseneck Rd",
    "sg:city":"Warwick",
    "sg:classifiers":[
        {
            "category":"Professional",
            "type":"Services"
        }
    ],
    "sg:phone":"+1 401 732 2690",
    "sg:postcode":"02889",
    "sg:province":"RI",
    "sg:tags":[
        "establishment"
    ],
    "wof:name":"Mc O Inc",
    "wof:placetype":"venue"
},
  "geometry": {"coordinates":[-71.402593,41.700655],"type":"Point"}
}