{
  "type": "Feature",
  "properties": {
    "iso:country":"US",
    "sg:address":"66 Levesque St",
    "sg:city":"Warwick",
    "sg:classifiers":[
        {
            "category":"Professional",
            "subcategory":"Engineering",
            "type":"Services"
        }
    ],
    "sg:phone":"+1 401 739 4114",
    "sg:postcode":"02886",
    "sg:province":"RI",
    "sg:tags":[
        "engineer"
    ],
    "wof:name":"Allinson-Lama",
    "wof:placetype":"venue"
},
  "geometry": {"coordinates":[-71.49327700000001,41.714546],"type":"Point"}
}