{
  "type": "Feature",
  "properties": {
    "addr:full":"1171 Main St Wyoming RI 02898",
    "addr:housenumber":"1171",
    "addr:postcode":"02898",
    "addr:street":"Main St",
    "iso:country":"US",
    "sg:address":"1171 Main St",
    "sg:city":"Wyoming",
    "sg:classifiers":[
        {
            "category":"Shopping",
            "subcategory":"Musical Instruments",
            "type":"Retail Goods"
        }
    ],
    "sg:phone":"+1 401 539 7649",
    "sg:postcode":"02898",
    "sg:province":"RI",
    "sg:tags":[
        "music",
        "dealer"
    ],
    "wof:name":"Kropp Sales",
    "wof:placetype":"venue"
},
  "geometry": {"coordinates":[-71.69232599999999,41.512477],"type":"Point"}
}