{
  "type": "Feature",
  "properties": {
    "addr:full":"875 Centerville Rd Warwick RI 02886",
    "addr:housenumber":"875",
    "addr:postcode":"02886",
    "addr:street":"Centerville Rd",
    "iso:country":"US",
    "sg:address":"875 Centerville Rd",
    "sg:city":"Warwick",
    "sg:classifiers":[
        {
            "category":"Health Services",
            "subcategory":"Doctor",
            "type":"Services"
        }
    ],
    "sg:phone":"+1 401 821 0220",
    "sg:postcode":"02886",
    "sg:province":"RI",
    "sg:tags":[
        "physician",
        "surgeon"
    ],
    "wof:name":"Wickford Medical Care",
    "wof:placetype":"venue"
},
  "geometry": {"coordinates":[-71.489835,41.69687],"type":"Point"}
}