{
  "type": "Feature",
  "properties": {
    "iso:country":"US",
    "sg:address":"44 Dunedin St",
    "sg:city":"Cranston",
    "sg:classifiers":[
        {
            "category":"Professional",
            "type":"Services"
        }
    ],
    "sg:phone":"+1 401 333 1117",
    "sg:postcode":"02920",
    "sg:province":"RI",
    "sg:tags":[
        "establishment"
    ],
    "wof:name":"Novo Management Cingular WRLS",
    "wof:placetype":"venue"
},
  "geometry": {"coordinates":[-71.451764,41.802161],"type":"Point"}
}