{
  "type": "Feature",
  "properties": {
    "addr:full":"16 High St Westerly RI 02891",
    "addr:housenumber":"16",
    "addr:postcode":"02891",
    "addr:street":"High St",
    "iso:country":"US",
    "sg:address":"16 High St",
    "sg:city":"Westerly",
    "sg:classifiers":[
        {
            "category":"Communications",
            "subcategory":"News Services",
            "type":"Services"
        }
    ],
    "sg:phone":"+1 401 604 0100",
    "sg:postcode":"02891",
    "sg:province":"RI",
    "sg:tags":[
        "newspaper",
        "feature",
        "syndicate"
    ],
    "wof:name":"Westerly This Week",
    "wof:placetype":"venue"
},
  "geometry": {"coordinates":[-71.829842,41.379425],"type":"Point"}
}