{
  "type": "Feature",
  "properties": {
    "iso:country":"US",
    "sg:address":"176 Columbus Ave",
    "sg:city":"Pawtucket",
    "sg:classifiers":[
        {
            "category":"Bars & Pubs",
            "type":"Food & Drink"
        }
    ],
    "sg:phone":"+1 401 726 9075",
    "sg:postcode":"02860",
    "sg:province":"RI",
    "sg:tags":[
        "lounge"
    ],
    "wof:name":"My Brothers Pub LTD",
    "wof:placetype":"venue"
},
  "geometry": {"coordinates":[-71.364817,41.870488],"type":"Point"}
}