{
  "type": "Feature",
  "properties": {
    "iso:country":"US",
    "sg:address":"1 Spring Wharf",
    "sg:city":"Newport",
    "sg:classifiers":[
        {
            "category":"Manufacturing",
            "subcategory":"Watercraft",
            "type":"Manufacturing & Wholesale Goods"
        }
    ],
    "sg:phone":"+1 401 846 3312",
    "sg:postcode":"02840",
    "sg:province":"RI",
    "sg:tags":[
        "building",
        "repair",
        "wood",
        "boat"
    ],
    "wof:name":"Narragansett Shipwrights Inc",
    "wof:placetype":"venue"
},
  "geometry": {"coordinates":[-71.314876,41.480464],"type":"Point"}
}