{
  "type": "Feature",
  "properties": {
    "iso:country":"US",
    "sg:address":"117 Underwood Ave",
    "sg:city":"Warwick",
    "sg:classifiers":[
        {
            "category":"Retail",
            "subcategory":"Repair Shop",
            "type":"Services"
        }
    ],
    "sg:phone":"+1 401 467 8518",
    "sg:postcode":"02888",
    "sg:province":"RI",
    "wof:name":"Pellerin Precision Gage Co",
    "wof:placetype":"venue"
},
  "geometry": {"coordinates":[-71.414539,41.760183],"type":"Point"}
}