{
  "type": "Feature",
  "properties": {
    "iso:country":"US",
    "sg:address":"1193 Reservoir Ave",
    "sg:city":"Cranston",
    "sg:classifiers":[
        {
            "category":"Professional",
            "subcategory":"Lawyer & Legal Services",
            "type":"Services"
        }
    ],
    "sg:phone":"+1 401 942 4300",
    "sg:postcode":"02920",
    "sg:province":"RI",
    "sg:tags":[
        "attorney"
    ],
    "wof:name":"Gelfuso & Lachut Inc",
    "wof:placetype":"venue"
},
  "geometry": {"coordinates":[-71.455845,41.76867],"type":"Point"}
}