{
  "type": "Feature",
  "properties": {
    "iso:country":"US",
    "sg:address":"711 Front St",
    "sg:city":"Woonsocket",
    "sg:classifiers":[
        {
            "category":"Coffee & Tea",
            "type":"Food & Drink"
        },
        {
            "category":"Bakery",
            "type":"Food & Drink"
        },
        {
            "category":"Bagels",
            "subcategory":"None",
            "type":"Food & Drink"
        },
        {
            "category":"Donuts",
            "subcategory":"None",
            "type":"Food & Drink"
        }
    ],
    "sg:phone":"+1 888 341 7941",
    "sg:postcode":"02895",
    "sg:province":"RI",
    "sg:tags":[
        "shop",
        "espresso",
        "restaurant"
    ],
    "sg:website":"http://worcester.citysearch.com/profile/external/45223964/woonsocket_ri/dunkin_donuts.html?publisher=yellowpages&reference_id=1&placement=ypwebsitemip",
    "wof:name":"Dunkin Donuts",
    "wof:placetype":"venue"
},
  "geometry": {"coordinates":[-71.517675,41.996691],"type":"Point"}
}