{
  "type": "Feature",
  "properties": {
    "iso:country":"US",
    "sg:address":"76 Hammerland Way",
    "sg:city":"Middletown",
    "sg:classifiers":[
        {
            "category":"Professional",
            "subcategory":"Management & Consulting",
            "type":"Services"
        }
    ],
    "sg:phone":"+1 401 846 5500",
    "sg:postcode":"02842",
    "sg:province":"RI",
    "sg:tags":[
        "consultant",
        "engineering"
    ],
    "wof:name":"Bae Systems Applied Technologi",
    "wof:placetype":"venue"
},
  "geometry": {"coordinates":[-71.284682,41.503202],"type":"Point"}
}