{
  "type": "Feature",
  "properties": {
    "addr:full":"226 Bellevue Ave Newport RI 02840",
    "addr:housenumber":"226",
    "addr:postcode":"02840",
    "addr:street":"Bellevue Ave",
    "iso:country":"US",
    "sg:address":"226 Bellevue Ave",
    "sg:city":"Newport",
    "sg:classifiers":[
        {
            "category":"Professional",
            "type":"Services"
        }
    ],
    "sg:phone":"+1 401 849 5559",
    "sg:postcode":"02840",
    "sg:province":"RI",
    "sg:tags":[
        "establishment"
    ],
    "wof:name":"Bellevue Capital Ventures Inc",
    "wof:placetype":"venue"
},
  "geometry": {"coordinates":[-71.308418,41.481819],"type":"Point"}
}