{
  "type": "Feature",
  "properties": {
    "addr:full":"154 Warren Ave Cranston RI 02920",
    "addr:housenumber":"154",
    "addr:postcode":"02920",
    "addr:street":"Warren Ave",
    "iso:country":"US",
    "sg:address":"154 Warren Ave",
    "sg:city":"Cranston",
    "sg:classifiers":[
        {
            "category":"Professional",
            "subcategory":"Computer Services",
            "type":"Services"
        }
    ],
    "sg:phone":"+1 401 854 2932",
    "sg:postcode":"02920",
    "sg:province":"RI",
    "sg:tags":[
        "website",
        "design"
    ],
    "sg:website":"www.sheehanmedia.com",
    "wof:name":"Sheehan Media",
    "wof:placetype":"venue"
},
  "geometry": {"coordinates":[-71.48411299999999,41.743233],"type":"Point"}
}