{
  "type": "Feature",
  "properties": {
    "iso:country":"US",
    "sg:address":"109 Melrose St",
    "sg:city":"Providence",
    "sg:classifiers":[
        {
            "category":"Health Services",
            "subcategory":"Nursing And Care Facility",
            "type":"Services"
        }
    ],
    "sg:phone":"+1 401 490 4646",
    "sg:postcode":"02907",
    "sg:province":"RI",
    "sg:tags":[
        "home",
        "convalescent"
    ],
    "wof:name":"St Elizabeth Court",
    "wof:placetype":"venue"
},
  "geometry": {"coordinates":[-71.42257600000001,41.797798],"type":"Point"}
}