{
  "type": "Feature",
  "properties": {
    "addr:full":"10 Dorrance St Providence RI 02903",
    "addr:housenumber":"10",
    "addr:postcode":"02903",
    "addr:street":"Dorrance St",
    "iso:country":"US",
    "sg:address":"10 Dorrance St",
    "sg:city":"Providence",
    "sg:classifiers":[
        {
            "category":"Manufacturing",
            "subcategory":"Tools & Machinery",
            "type":"Manufacturing & Wholesale Goods"
        }
    ],
    "sg:phone":"+1 401 854 0440",
    "sg:postcode":"02903",
    "sg:province":"RI",
    "sg:tags":[
        "engine",
        "equipment",
        "electrical",
        "mfg"
    ],
    "wof:name":"E S I Holding Inc",
    "wof:placetype":"venue"
},
  "geometry": {"coordinates":[-71.411637,41.823688],"type":"Point"}
}