{
  "type": "Feature",
  "properties": {
    "iso:country":"US",
    "sg:address":"85 Burgess Ave",
    "sg:city":"East Providence",
    "sg:classifiers":[
        {
            "category":"Food & Beverages",
            "subcategory":"Groceries & Convenience Stores",
            "type":"Retail Goods"
        }
    ],
    "sg:phone":"+1 401 438 9169",
    "sg:postcode":"02914",
    "sg:province":"RI",
    "wof:name":"Big Apple Convenience Store",
    "wof:placetype":"venue"
},
  "geometry": {"coordinates":[-71.38267399999999,41.816089],"type":"Point"}
}