{
  "type": "Feature",
  "properties": {
    "addr:full":"8 Maclaine Dr North Providence RI 02904",
    "addr:housenumber":"8",
    "addr:postcode":"02904",
    "addr:street":"Maclaine Dr",
    "iso:country":"US",
    "sg:address":"8 Maclaine Dr",
    "sg:city":"North Providence",
    "sg:classifiers":[
        {
            "category":"Wholesale",
            "subcategory":"Machinery & Supplies",
            "type":"Manufacturing & Wholesale Goods"
        }
    ],
    "sg:phone":"+1 401 354 4700",
    "sg:postcode":"02904",
    "sg:province":"RI",
    "sg:tags":[
        "car"
    ],
    "wof:name":"Mello Enterprises",
    "wof:placetype":"venue"
},
  "geometry": {"coordinates":[-71.451418,41.857596],"type":"Point"}
}