{
  "type": "Feature",
  "properties": {
    "iso:country":"US",
    "sg:address":"17 Forbes St",
    "sg:city":"Riverside",
    "sg:classifiers":[
        {
            "category":"Retail",
            "subcategory":"Laundry & Dry Cleaning",
            "type":"Services"
        }
    ],
    "sg:phone":"+1 401 433 1324",
    "sg:postcode":"02915",
    "sg:province":"RI",
    "wof:name":"Specialty Cleansing Co Inc",
    "wof:placetype":"venue"
},
  "geometry": {"coordinates":[-71.35442500000001,41.77645],"type":"Point"}
}