{
  "type": "Feature",
  "properties": {
    "addr:full":"1219 Cranston St Cranston RI 02920",
    "addr:housenumber":"1219",
    "addr:postcode":"02920",
    "addr:street":"Cranston St",
    "iso:country":"US",
    "sg:address":"1219 Cranston St",
    "sg:city":"Cranston",
    "sg:classifiers":[
        {
            "category":"Food & Beverages",
            "subcategory":"Liquor & Beverages",
            "type":"Retail Goods"
        }
    ],
    "sg:phone":"+1 401 944 2724",
    "sg:postcode":"02920",
    "sg:province":"RI",
    "sg:tags":[
        "alcoholic"
    ],
    "wof:name":"Cranston Liquors",
    "wof:placetype":"venue"
},
  "geometry": {"coordinates":[-71.45062299999999,41.793575],"type":"Point"}
}