{
  "type": "Feature",
  "properties": {
    "iso:country":"US",
    "sg:address":"87 Pawtucket Ave",
    "sg:city":"Pawtucket",
    "sg:classifiers":[
        {
            "category":"Personal",
            "subcategory":"Beauty Salon",
            "type":"Services"
        }
    ],
    "sg:phone":"+1 401 724 9393",
    "sg:postcode":"02860",
    "sg:province":"RI",
    "wof:name":"Felicia's Hair Design",
    "wof:placetype":"venue"
},
  "geometry": {"coordinates":[-71.38682,41.871146],"type":"Point"}
}