{
  "type": "Feature",
  "properties": {
    "iso:country":"US",
    "sg:address":"239 Burrington St",
    "sg:city":"Woonsocket",
    "sg:classifiers":[
        {
            "category":"Retail",
            "subcategory":"Repair Shop",
            "type":"Services"
        }
    ],
    "sg:phone":"+1 401 766 6527",
    "sg:postcode":"02895",
    "sg:province":"RI",
    "wof:name":"Beamer Stellite TV Antenna Svc",
    "wof:placetype":"venue"
},
  "geometry": {"coordinates":[-71.486093,41.986576],"type":"Point"}
}