{
  "type": "Feature",
  "properties": {
    "addr:full":"34 Mount Ave Lincoln RI 02865",
    "addr:housenumber":"34",
    "addr:postcode":"02865",
    "addr:street":"Mount Ave",
    "iso:country":"US",
    "sg:address":"34 Mount Ave",
    "sg:city":"Lincoln",
    "sg:classifiers":[
        {
            "category":"Wholesale",
            "subcategory":"Toys & Hobbies",
            "type":"Manufacturing & Wholesale Goods"
        }
    ],
    "sg:phone":"+1 401 725 8141",
    "sg:postcode":"02865",
    "sg:province":"RI",
    "sg:tags":[
        "electric",
        "vehicle"
    ],
    "wof:name":"Atmos Electric Vehicles Ltd",
    "wof:placetype":"venue"
},
  "geometry": {"coordinates":[-71.428568,41.884923],"type":"Point"}
}