{
  "type": "Feature",
  "properties": {
    "iso:country":"US",
    "sg:address":"341 Providence St",
    "sg:city":"Warwick",
    "sg:classifiers":[
        {
            "category":"Organizations",
            "subcategory":"Community Association",
            "type":"Services"
        }
    ],
    "sg:phone":"+1 401 821 8482",
    "sg:postcode":"02886",
    "sg:province":"RI",
    "wof:name":"Roger Williams Chpt RI",
    "wof:placetype":"venue"
},
  "geometry": {"coordinates":[-71.500964,41.711487],"type":"Point"}
}