{
  "type": "Feature",
  "properties": {
    "addr:full":"111 Pennsylvania Ave Warwick RI 02888",
    "addr:housenumber":"111",
    "addr:postcode":"02888",
    "addr:street":"Pennsylvania Ave",
    "iso:country":"US",
    "sg:address":"111 Pennsylvania Ave",
    "sg:city":"Warwick",
    "sg:classifiers":[
        {
            "category":"Manufacturing",
            "subcategory":"Tools & Machinery",
            "type":"Manufacturing & Wholesale Goods"
        }
    ],
    "sg:phone":"+1 401 737 2155",
    "sg:postcode":"02888",
    "sg:province":"RI",
    "sg:tags":[
        "machine",
        "shop",
        "jobbing"
    ],
    "wof:name":"At Press & Assembly Corp",
    "wof:placetype":"venue"
},
  "geometry": {"coordinates":[-71.44269799999999,41.740445],"type":"Point"}
}