{
  "type": "Feature",
  "properties": {
    "iso:country":"US",
    "sg:address":"217 Sprague St",
    "sg:city":"Portsmouth",
    "sg:classifiers":[
        {
            "category":"Building & Trades",
            "subcategory":"Construction",
            "type":"Services"
        }
    ],
    "sg:phone":"+1 401 683 9719",
    "sg:postcode":"02871",
    "sg:province":"RI",
    "sg:tags":[
        "general",
        "contractor"
    ],
    "wof:name":"Bob Vivieros General Contr",
    "wof:placetype":"venue"
},
  "geometry": {"coordinates":[-71.252376,41.616809],"type":"Point"}
}