{
  "type": "Feature",
  "properties": {
    "addr:full":"282 East Ave Pawtucket RI 02860",
    "addr:housenumber":"282",
    "addr:postcode":"02860",
    "addr:street":"East Ave",
    "iso:country":"US",
    "sg:address":"282 East Ave",
    "sg:city":"Pawtucket",
    "sg:classifiers":[
        {
            "category":"Banks & Credit Unions",
            "subcategory":"Investment Brokerage",
            "type":"Services"
        }
    ],
    "sg:phone":"+1 401 726 4760",
    "sg:postcode":"02860",
    "sg:province":"RI",
    "sg:tags":[
        "advisory",
        "financial"
    ],
    "wof:name":"Blackstone Financial Svc",
    "wof:placetype":"venue"
},
  "geometry": {"coordinates":[-71.386965,41.870721],"type":"Point"}
}