{
  "type": "Feature",
  "properties": {
    "addr:full":"47 Macarthur Blvd Wakefield RI 02879",
    "addr:housenumber":"47",
    "addr:postcode":"02879",
    "addr:street":"Macarthur Blvd",
    "iso:country":"US",
    "sg:address":"47 Macarthur Blvd",
    "sg:city":"Wakefield",
    "sg:classifiers":[
        {
            "category":"Professional",
            "subcategory":"Accounting & Tax Preparation",
            "type":"Services"
        }
    ],
    "sg:phone":"+1 401 783 9865",
    "sg:postcode":"02879",
    "sg:province":"RI",
    "sg:tags":[
        "return"
    ],
    "wof:name":"Mandel and Mandel",
    "wof:placetype":"venue"
},
  "geometry": {"coordinates":[-71.485552,41.438742],"type":"Point"}
}