{
  "type": "Feature",
  "properties": {
    "addr:full":"16 Hillside Rd Cranston RI 02920",
    "addr:housenumber":"16",
    "addr:postcode":"02920",
    "addr:street":"Hillside Rd",
    "iso:country":"US",
    "sg:address":"16 Hillside Rd",
    "sg:city":"Cranston",
    "sg:classifiers":[
        {
            "category":"Utilities",
            "subcategory":"Mobile Phone",
            "type":"Services"
        }
    ],
    "sg:phone":"+1 401 942 1079",
    "sg:postcode":"02920",
    "sg:province":"RI",
    "sg:tags":[
        "telephone",
        "cellular"
    ],
    "wof:name":"Cingular Wireless",
    "wof:placetype":"venue"
},
  "geometry": {"coordinates":[-71.458252,41.764935],"type":"Point"}
}