{
  "type": "Feature",
  "properties": {
    "addr:full":"148 Bellevue Ave Newport RI 02840",
    "addr:housenumber":"148",
    "addr:postcode":"02840",
    "addr:street":"Bellevue Ave",
    "iso:country":"US",
    "sg:address":"148 Bellevue Ave",
    "sg:city":"Newport",
    "sg:classifiers":[
        {
            "category":"Professional",
            "subcategory":"Business Services",
            "type":"Services"
        }
    ],
    "sg:phone":"+1 401 848 2121",
    "sg:postcode":"02840",
    "sg:province":"RI",
    "sg:website":"www.karenvaughan.com",
    "wof:name":"Karen Vaughan Productions",
    "wof:placetype":"venue"
},
  "geometry": {"coordinates":[-71.30850100000001,41.483782],"type":"Point"}
}