{
  "type": "Feature",
  "properties": {
    "iso:country":"US",
    "sg:address":"900 Ten Rod Rd",
    "sg:city":"Exeter",
    "sg:classifiers":[
        {
            "category":"Food & Beverages",
            "subcategory":"Groceries & Convenience Stores",
            "type":"Retail Goods"
        }
    ],
    "sg:phone":"+1 401 295 7218",
    "sg:postcode":"02822",
    "sg:province":"RI",
    "sg:tags":[
        "product",
        "dairy"
    ],
    "wof:name":"A54 21",
    "wof:placetype":"venue"
},
  "geometry": {"coordinates":[-71.597151,41.579385],"type":"Point"}
}