{
  "type": "Feature",
  "properties": {
    "iso:country":"US",
    "sg:address":"14 Murray St",
    "sg:city":"Providence",
    "sg:classifiers":[
        {
            "category":"Retail",
            "subcategory":"Auto Repair",
            "type":"Services"
        }
    ],
    "sg:phone":"+1 401 946 8020",
    "sg:postcode":"02909",
    "sg:province":"RI",
    "sg:tags":[
        "body",
        "automobile",
        "painting"
    ],
    "wof:name":"Murray's Auto Body",
    "wof:placetype":"venue"
},
  "geometry": {"coordinates":[-71.461484,41.80967],"type":"Point"}
}