{
  "type": "Feature",
  "properties": {
    "iso:country":"US",
    "sg:address":"819 Greenwich Ave",
    "sg:city":"Warwick",
    "sg:classifiers":[
        {
            "category":"Health Services",
            "subcategory":"Doctor",
            "type":"Services"
        }
    ],
    "sg:phone":"+1 401 739 8337",
    "sg:postcode":"02886",
    "sg:province":"RI",
    "sg:tags":[
        "dentist"
    ],
    "wof:name":"Warwick Family Dental Grp",
    "wof:placetype":"venue"
},
  "geometry": {"coordinates":[-71.46348500000001,41.715538],"type":"Point"}
}