{
  "type": "Feature",
  "properties": {
    "iso:country":"US",
    "sg:address":"686 Elmwood Ave",
    "sg:city":"Providence",
    "sg:classifiers":[
        {
            "category":"Shopping",
            "subcategory":"Books",
            "type":"Retail Goods"
        }
    ],
    "sg:phone":"+1 401 781 9097",
    "sg:postcode":"02907",
    "sg:province":"RI",
    "wof:name":"Libreria Fuente De Vida",
    "wof:placetype":"venue"
},
  "geometry": {"coordinates":[-71.423686,41.793811],"type":"Point"}
}