{
  "type": "Feature",
  "properties": {
    "iso:country":"US",
    "sg:address":"172 Thames St",
    "sg:city":"Newport",
    "sg:classifiers":[
        {
            "category":"Wholesale",
            "subcategory":"Durable Goods & Equipment",
            "type":"Manufacturing & Wholesale Goods"
        }
    ],
    "sg:phone":"+1 401 847 5955",
    "sg:postcode":"02840",
    "sg:province":"RI",
    "sg:tags":[
        "representative",
        "manufacturer"
    ],
    "wof:name":"Mc Connell Enterprises",
    "wof:placetype":"venue"
},
  "geometry": {"coordinates":[-71.31513200000001,41.489806],"type":"Point"}
}