{
  "type": "Feature",
  "properties": {
    "addr:full":"175 Nate Whipple Hwy Cumberland RI 02864",
    "addr:housenumber":"175",
    "addr:postcode":"02864",
    "addr:street":"Nate Whipple Hwy",
    "iso:country":"US",
    "sg:address":"175 Nate Whipple Hwy",
    "sg:city":"Cumberland",
    "sg:classifiers":[
        {
            "category":"Health Services",
            "subcategory":"Doctor",
            "type":"Services"
        }
    ],
    "sg:phone":"+1 401 658 0040",
    "sg:postcode":"02864",
    "sg:province":"RI",
    "sg:tags":[
        "medical"
    ],
    "wof:name":"Detorie Frank MD",
    "wof:placetype":"venue"
},
  "geometry": {"coordinates":[-71.442238,41.978671],"type":"Point"}
}