{
  "type": "Feature",
  "properties": {
    "iso:country":"US",
    "sg:address":"100 Butler Dr",
    "sg:city":"Providence",
    "sg:classifiers":[
        {
            "category":"Health Services",
            "subcategory":"Health Practitioner",
            "type":"Services"
        }
    ],
    "sg:phone":"+1 401 272 9955",
    "sg:postcode":"02906",
    "sg:province":"RI",
    "sg:tags":[
        "therapist",
        "physical"
    ],
    "wof:name":"Specialized Ortho Physcl Thrpy",
    "wof:placetype":"venue"
},
  "geometry": {"coordinates":[-71.37921799999999,41.844001],"type":"Point"}
}