{
  "type": "Feature",
  "properties": {
    "iso:country":"US",
    "sg:address":"155 Rodman St",
    "sg:city":"Wakefield",
    "sg:classifiers":[
        {
            "category":"Building & Trades",
            "subcategory":"Electrical",
            "type":"Services"
        }
    ],
    "sg:phone":"+1 401 782 1020",
    "sg:postcode":"02879",
    "sg:province":"RI",
    "sg:tags":[
        "electric",
        "contractor"
    ],
    "wof:name":"Electrical Design & Constr",
    "wof:placetype":"venue"
},
  "geometry": {"coordinates":[-71.50668,41.450078],"type":"Point"}
}