{
  "type": "Feature",
  "properties": {
    "addr:full":"3536 Mendon Rd Cumberland RI 02864",
    "addr:housenumber":"3536",
    "addr:postcode":"02864",
    "addr:street":"Mendon Rd",
    "iso:country":"US",
    "sg:address":"3536 Mendon Rd",
    "sg:city":"Cumberland",
    "sg:classifiers":[
        {
            "category":"Retail",
            "subcategory":"Auto Repair",
            "type":"Services"
        }
    ],
    "sg:phone":"+1 401 658 0167",
    "sg:postcode":"02864",
    "sg:province":"RI",
    "sg:tags":[
        "general"
    ],
    "wof:name":"Theriens LLC",
    "wof:placetype":"venue"
},
  "geometry": {"coordinates":[-71.462903,41.979315],"type":"Point"}
}