{
  "type": "Feature",
  "properties": {
    "iso:country":"US",
    "sg:address":"115 Buttonwoods Ave",
    "sg:city":"Warwick",
    "sg:classifiers":[
        {
            "category":"Building & Trades",
            "subcategory":"Construction",
            "type":"Services"
        }
    ],
    "sg:phone":"+1 401 739 2903",
    "sg:postcode":"02886",
    "sg:province":"RI",
    "sg:tags":[
        "hanging",
        "contractor"
    ],
    "wof:name":"Iannucci Painting",
    "wof:placetype":"venue"
},
  "geometry": {"coordinates":[-71.43084899999999,41.703017],"type":"Point"}
}