{
  "type": "Feature",
  "properties": {
    "addr:full":"100 Valley Rd Middletown RI 02842",
    "addr:housenumber":"100",
    "addr:postcode":"02842",
    "addr:street":"Valley Rd",
    "iso:country":"US",
    "sg:address":"100 Valley Rd",
    "sg:city":"Middletown",
    "sg:classifiers":[
        {
            "category":"Health Services",
            "subcategory":"Doctor",
            "type":"Services"
        }
    ],
    "sg:phone":"+1 401 849 4541",
    "sg:postcode":"02842",
    "sg:province":"RI",
    "sg:tags":[
        "dentist"
    ],
    "wof:name":"Gregory Frazier DDS",
    "wof:placetype":"venue"
},
  "geometry": {"coordinates":[-71.29163800000001,41.515859],"type":"Point"}
}