{
  "type": "Feature",
  "properties": {
    "iso:country":"US",
    "sg:address":"459 Central Ave",
    "sg:city":"Pawtucket",
    "sg:classifiers":[
        {
            "category":"Manufacturing",
            "subcategory":"Signs",
            "type":"Manufacturing & Wholesale Goods"
        }
    ],
    "sg:phone":"+1 401 475 2788",
    "sg:postcode":"02861",
    "sg:province":"RI",
    "sg:tags":[
        "specialty",
        "mfg"
    ],
    "wof:name":"Sign Designs RI",
    "wof:placetype":"venue"
},
  "geometry": {"coordinates":[-71.36492200000001,41.885359],"type":"Point"}
}