{
  "type": "Feature",
  "properties": {
    "iso:country":"US",
    "sg:address":"1 Langworthy Rd",
    "sg:city":"Westerly",
    "sg:classifiers":[
        {
            "category":"Government",
            "subcategory":"Fire Station",
            "type":"Public Place"
        }
    ],
    "sg:phone":"+1 401 322 0577",
    "sg:postcode":"02891",
    "sg:province":"RI",
    "sg:tags":[
        "protection"
    ],
    "wof:name":"Dunns Corners Fire Dist",
    "wof:placetype":"venue"
},
  "geometry": {"coordinates":[-71.76840199999999,41.351444],"type":"Point"}
}