{
  "type": "Feature",
  "properties": {
    "iso:country":"US",
    "sg:address":"50 Maple St",
    "sg:city":"Warwick",
    "sg:classifiers":[
        {
            "category":"Health Services",
            "subcategory":"Clinic",
            "type":"Services"
        }
    ],
    "sg:phone":"+1 401 432 7999",
    "sg:postcode":"02888",
    "sg:province":"RI",
    "sg:tags":[
        "home"
    ],
    "wof:name":"A Peace Of Mind Home Care",
    "wof:placetype":"venue"
},
  "geometry": {"coordinates":[-71.438472,41.751131],"type":"Point"}
}