{
  "type": "Feature",
  "properties": {
    "iso:country":"US",
    "sg:address":"68 Belgium St",
    "sg:city":"Cranston",
    "sg:classifiers":[
        {
            "category":"Retail",
            "subcategory":"Repair Shop",
            "type":"Services"
        }
    ],
    "sg:phone":"+1 401 943 7361",
    "sg:postcode":"02920",
    "sg:province":"RI",
    "sg:tags":[
        "cleaning"
    ],
    "wof:name":"All Phaze Cleaning Service",
    "wof:placetype":"venue"
},
  "geometry": {"coordinates":[-71.45849,41.777841],"type":"Point"}
}