{
  "type": "Feature",
  "properties": {
    "iso:country":"US",
    "sg:address":"24 Snell Rd",
    "sg:city":"Little Compton",
    "sg:classifiers":[
        {
            "category":"Recreation",
            "type":"Entertainment"
        }
    ],
    "sg:phone":"+1 401 635 4292",
    "sg:postcode":"02837",
    "sg:province":"RI",
    "wof:name":"Captain Buds",
    "wof:placetype":"venue"
},
  "geometry": {"coordinates":[-71.157616,41.517882],"type":"Point"}
}