{
  "type": "Feature",
  "properties": {
    "iso:country":"US",
    "sg:address":"1678 E Main Rd",
    "sg:city":"Portsmouth",
    "sg:classifiers":[
        {
            "category":"Shopping",
            "type":"Retail Goods"
        }
    ],
    "sg:phone":"+1 401 683 4341",
    "sg:postcode":"02871",
    "sg:province":"RI",
    "sg:tags":[
        "product",
        "wood"
    ],
    "wof:name":"Designs In Wood",
    "wof:placetype":"venue"
},
  "geometry": {"coordinates":[-71.252475,41.580057],"type":"Point"}
}