{
  "type": "Feature",
  "properties": {
    "iso:country":"US",
    "sg:address":"1 Ducarl Dr",
    "sg:city":"Lincoln",
    "sg:classifiers":[
        {
            "category":"Building & Trades",
            "subcategory":"Construction",
            "type":"Services"
        }
    ],
    "sg:phone":"+1 401 333 4875",
    "sg:postcode":"02865",
    "sg:province":"RI",
    "sg:tags":[
        "builder",
        "operative"
    ],
    "wof:name":"Carlson Properties Inc",
    "wof:placetype":"venue"
},
  "geometry": {"coordinates":[-71.435272,41.924122],"type":"Point"}
}