{
  "type": "Feature",
  "properties": {
    "iso:country":"US",
    "sg:address":"52 Carlton St",
    "sg:city":"Cranston",
    "sg:classifiers":[
        {
            "category":"Professional",
            "subcategory":"Computer Services",
            "type":"Services"
        }
    ],
    "sg:phone":"+1 401 785 1533",
    "sg:postcode":"02910",
    "sg:province":"RI",
    "sg:tags":[
        "consultant",
        "designer"
    ],
    "wof:name":"R J Quality Control Inc",
    "wof:placetype":"venue"
},
  "geometry": {"coordinates":[-71.436559,41.786503],"type":"Point"}
}