{
  "type": "Feature",
  "properties": {
    "addr:full":"585 Park Ave Portsmouth RI 02871",
    "addr:housenumber":"585",
    "addr:postcode":"02871",
    "addr:street":"Park Ave",
    "iso:country":"US",
    "sg:address":"585 Park Ave",
    "sg:city":"Portsmouth",
    "sg:classifiers":[
        {
            "category":"Autos & Motor Vehicles",
            "subcategory":"Automobile Sales",
            "type":"Retail Goods"
        }
    ],
    "sg:phone":"+1 401 683 9630",
    "sg:postcode":"02871",
    "sg:province":"RI",
    "sg:tags":[
        "used"
    ],
    "wof:name":"Circle Motors",
    "wof:placetype":"venue"
},
  "geometry": {"coordinates":[-71.223051,41.623749],"type":"Point"}
}