{
  "type": "Feature",
  "properties": {
    "iso:country":"US",
    "sg:address":"247 Lockwood St",
    "sg:city":"Providence",
    "sg:classifiers":[
        {
            "category":"Professional",
            "type":"Services"
        }
    ],
    "sg:phone":"+1 401 861 8896",
    "sg:postcode":"02907",
    "sg:province":"RI",
    "sg:tags":[
        "establishment"
    ],
    "wof:name":"Muslim American Dawah Ctr",
    "wof:placetype":"venue"
},
  "geometry": {"coordinates":[-71.416177,41.813042],"type":"Point"}
}