{
  "type": "Feature",
  "properties": {
    "addr:full":"1240 Pawtucket Ave Rumford RI 02916",
    "addr:housenumber":"1240",
    "addr:postcode":"02916",
    "addr:street":"Pawtucket Ave",
    "iso:country":"US",
    "sg:address":"1240 Pawtucket Ave",
    "sg:city":"Rumford",
    "sg:classifiers":[
        {
            "category":"Social Services",
            "type":"Services"
        }
    ],
    "sg:phone":"+1 401 369 7618",
    "sg:postcode":"02916",
    "sg:province":"RI",
    "sg:tags":[
        "counselor",
        "marriage",
        "family"
    ],
    "wof:name":"Charlene Zienowicz Msw",
    "wof:placetype":"venue"
},
  "geometry": {"coordinates":[-71.34947200000001,41.840608],"type":"Point"}
}