{
  "type": "Feature",
  "properties": {
    "iso:country":"US",
    "sg:address":"163 Main St",
    "sg:city":"Westerly",
    "sg:classifiers":[
        {
            "category":"Banks & Credit Unions",
            "subcategory":"Financial Services",
            "type":"Services"
        }
    ],
    "sg:phone":"+1 401 596 9800",
    "sg:postcode":"02891",
    "sg:province":"RI",
    "sg:tags":[
        "company",
        "holding"
    ],
    "wof:name":"Rjm Enterprises",
    "wof:placetype":"venue"
},
  "geometry": {"coordinates":[-71.83091,41.371735],"type":"Point"}
}