{
  "type": "Feature",
  "properties": {
    "iso:country":"US",
    "sg:address":"345 West Rd",
    "sg:city":"Harrisville",
    "sg:classifiers":[
        {
            "category":"Communications",
            "subcategory":"Film & Video Production",
            "type":"Services"
        },
        {
            "category":"Retail",
            "subcategory":"Event Space",
            "type":"Services"
        },
        {
            "category":"Personal",
            "type":"Services"
        }
    ],
    "sg:phone":"+1 401 567 9171",
    "sg:postcode":"02830",
    "sg:province":"RI",
    "sg:tags":[
        "facility",
        "dvd",
        "services-commercial",
        "duplicating",
        "cd",
        "planning",
        "cassette",
        "reception",
        "party",
        "banquet",
        "hall"
    ],
    "sg:website":"http://www.ecoastvideo.com",
    "wof:name":"East Coast Video Svc",
    "wof:placetype":"venue"
},
  "geometry": {"coordinates":[-71.705353,41.994817],"type":"Point"}
}