{
  "type": "Feature",
  "properties": {
    "addr:full":"296 Angell St Providence RI 02906",
    "addr:housenumber":"296",
    "addr:postcode":"02906",
    "addr:street":"Angell St",
    "iso:country":"US",
    "sg:address":"296 Angell St",
    "sg:city":"Providence",
    "sg:classifiers":[
        {
            "category":"Education",
            "subcategory":"Preschool",
            "type":"Public Place"
        },
        {
            "category":"Education",
            "subcategory":"School",
            "type":"Public Place"
        }
    ],
    "sg:phone":"+1 401 331 8443",
    "sg:postcode":"02906",
    "sg:province":"RI",
    "sg:tags":[
        "elementary"
    ],
    "sg:website":"www.childsplayri.org",
    "wof:name":"Child's Play Nursery Preschool & Kindergarten",
    "wof:placetype":"venue"
},
  "geometry": {"coordinates":[-71.3955,41.828602],"type":"Point"}
}