{
  "type": "Feature",
  "properties": {
    "iso:country":"US",
    "sg:address":"14 Bond Ave",
    "sg:city":"Cumberland",
    "sg:classifiers":[
        {
            "category":"Retail",
            "subcategory":"Auto Rental",
            "type":"Services"
        }
    ],
    "sg:phone":"+1 401 658 0409",
    "sg:postcode":"02864",
    "sg:province":"RI",
    "sg:tags":[
        "renting",
        "truck",
        "leasing"
    ],
    "wof:name":"U-Haul Co",
    "wof:placetype":"venue"
},
  "geometry": {"coordinates":[-71.471851,41.98317],"type":"Point"}
}