{
  "type": "Feature",
  "properties": {
    "iso:country":"US",
    "sg:address":"2 Greenville Ave",
    "sg:city":"Johnston",
    "sg:classifiers":[
        {
            "category":"Restaurant",
            "type":"Food & Drink"
        }
    ],
    "sg:phone":"+1 401 272 3859",
    "sg:postcode":"02919",
    "sg:province":"RI",
    "sg:tags":[
        "breakfast",
        "brunch"
    ],
    "wof:name":"Scramblers II",
    "wof:placetype":"venue"
},
  "geometry": {"coordinates":[-71.470555,41.832705],"type":"Point"}
}