{
  "type": "Feature",
  "properties": {
    "addr:full":"473 Chapel St Harrisville RI 02830",
    "addr:housenumber":"473",
    "addr:postcode":"02830",
    "addr:street":"Chapel St",
    "iso:country":"US",
    "sg:address":"473 Chapel St",
    "sg:city":"Harrisville",
    "sg:classifiers":[
        {
            "category":"Personal",
            "subcategory":"Beauty Salon",
            "type":"Services"
        }
    ],
    "sg:phone":"+1 401 568 4597",
    "sg:postcode":"02830",
    "sg:province":"RI",
    "sg:tags":[
        "shop"
    ],
    "wof:name":"Casual Beauty Shop",
    "wof:placetype":"venue"
},
  "geometry": {"coordinates":[-71.67827200000001,41.966195],"type":"Point"}
}