{
  "type": "Feature",
  "properties": {
    "iso:country":"US",
    "sg:address":"70 Pettaconsett Ave",
    "sg:city":"Cranston",
    "sg:classifiers":[
        {
            "category":"Professional",
            "type":"Services"
        }
    ],
    "sg:phone":"+1 401 467 6354",
    "sg:postcode":"02920",
    "sg:province":"RI",
    "wof:name":"Surprise Woolhse 329 Veterans",
    "wof:placetype":"venue"
},
  "geometry": {"coordinates":[-71.445702,41.752029],"type":"Point"}
}