{
  "type": "Feature",
  "properties": {
    "iso:country":"US",
    "sg:address":"46 Marlborough St",
    "sg:city":"Newport",
    "sg:classifiers":[
        {
            "category":"Retail",
            "subcategory":"Veterinary Services",
            "type":"Services"
        }
    ],
    "sg:phone":"+1 401 845 8387",
    "sg:postcode":"02840",
    "sg:province":"RI",
    "sg:tags":[
        "clinic",
        "veterinarian",
        "hospital"
    ],
    "sg:website":"http://www.kittycornercatclinic.com",
    "wof:name":"Kitty Corner Cat Clinic",
    "wof:placetype":"venue"
},
  "geometry": {"coordinates":[-71.313078,41.491332],"type":"Point"}
}