{
  "type": "Feature",
  "properties": {
    "iso:country":"US",
    "sg:address":"272 Pawtucket Ave",
    "sg:city":"Rumford",
    "sg:classifiers":[
        {
            "category":"Personal",
            "subcategory":"Beauty Salon",
            "type":"Services"
        }
    ],
    "sg:phone":"+1 401 434 5358",
    "sg:postcode":"02916",
    "sg:province":"RI",
    "sg:tags":[
        "shop"
    ],
    "wof:name":"Shelias",
    "wof:placetype":"venue"
},
  "geometry": {"coordinates":[-71.35842599999999,41.851926],"type":"Point"}
}