{
  "type": "Feature",
  "properties": {
    "iso:country":"US",
    "sg:address":"30 Railroad Ave",
    "sg:city":"West Kingston",
    "sg:classifiers":[
        {
            "category":"Manufacturing",
            "subcategory":"Pottery",
            "type":"Manufacturing & Wholesale Goods"
        }
    ],
    "sg:phone":"+1 401 789 0490",
    "sg:postcode":"02892",
    "sg:province":"RI",
    "sg:tags":[
        "product",
        "mfg"
    ],
    "wof:name":"Margaret Tefft",
    "wof:placetype":"venue"
},
  "geometry": {"coordinates":[-71.559662,41.48403],"type":"Point"}
}