{
  "type": "Feature",
  "properties": {
    "addr:full":"791 Dexter St Central Falls RI 02863",
    "addr:housenumber":"791",
    "addr:postcode":"02863",
    "addr:street":"Dexter St",
    "iso:country":"US",
    "sg:address":"791 Dexter St",
    "sg:city":"Central Falls",
    "sg:classifiers":[
        {
            "category":"Professional",
            "subcategory":"Accounting & Tax Preparation",
            "type":"Services"
        }
    ],
    "sg:phone":"+1 401 724 3080",
    "sg:postcode":"02863",
    "sg:province":"RI",
    "sg:tags":[
        "return",
        "filing"
    ],
    "wof:name":"Jaime's Tax Svc",
    "wof:placetype":"venue"
},
  "geometry": {"coordinates":[-71.397908,41.887587],"type":"Point"}
}