{
  "type": "Feature",
  "properties": {
    "addr:full":"224 Post Rd Westerly RI 02891",
    "addr:housenumber":"224",
    "addr:postcode":"02891",
    "addr:street":"Post Rd",
    "iso:country":"US",
    "sg:address":"224 Post Rd",
    "sg:city":"Westerly",
    "sg:classifiers":[
        {
            "category":"Professional",
            "subcategory":"Advertising",
            "type":"Services"
        }
    ],
    "sg:phone":"+1 401 322 5060",
    "sg:postcode":"02891",
    "sg:province":"RI",
    "sg:tags":[
        "mailing",
        "shipping"
    ],
    "wof:name":"UPS Store",
    "wof:placetype":"venue"
},
  "geometry": {"coordinates":[-71.76893800000001,41.351583],"type":"Point"}
}