{
  "type": "Feature",
  "properties": {
    "iso:country":"US",
    "sg:address":"3760 Quaker Ln",
    "sg:city":"North Kingstown",
    "sg:classifiers":[
        {
            "category":"Autos & Motor Vehicles",
            "subcategory":"Automobile Sales",
            "type":"Retail Goods"
        }
    ],
    "sg:phone":"+1 401 294 3395",
    "sg:postcode":"02852",
    "sg:province":"RI",
    "sg:tags":[
        "used"
    ],
    "wof:name":"Pilgrim Subaru",
    "wof:placetype":"venue"
},
  "geometry": {"coordinates":[-71.496827,41.596273],"type":"Point"}
}