{
  "type": "Feature",
  "properties": {
    "iso:country":"US",
    "sg:address":"1204 Main St",
    "sg:city":"West Warwick",
    "sg:classifiers":[
        {
            "category":"Retail",
            "subcategory":"Portrait Studio",
            "type":"Services"
        }
    ],
    "sg:phone":"+1 401 826 8380",
    "sg:postcode":"02893",
    "sg:province":"RI",
    "sg:tags":[
        "photography"
    ],
    "wof:name":"Options Photography",
    "wof:placetype":"venue"
},
  "geometry": {"coordinates":[-71.523578,41.705576],"type":"Point"}
}