{
  "type": "Feature",
  "properties": {
    "addr:full":"626 Oakland Beach Ave Warwick RI 02889",
    "addr:housenumber":"626",
    "addr:postcode":"02889",
    "addr:street":"Oakland Beach Ave",
    "iso:country":"US",
    "sg:address":"626 Oakland Beach Ave",
    "sg:city":"Warwick",
    "sg:classifiers":[
        {
            "category":"Professional",
            "type":"Services"
        }
    ],
    "sg:phone":"+1 401 732 5230",
    "sg:postcode":"02889",
    "sg:province":"RI",
    "sg:tags":[
        "establishment"
    ],
    "wof:name":"Oakies",
    "wof:placetype":"venue"
},
  "geometry": {"coordinates":[-71.398162,41.692372],"type":"Point"}
}