{
  "type": "Feature",
  "properties": {
    "iso:country":"US",
    "sg:address":"2224 Pawtucket Ave",
    "sg:city":"East Providence",
    "sg:classifiers":[
        {
            "category":"Health Services",
            "subcategory":"Dentist",
            "type":"Services"
        }
    ],
    "sg:phone":"+1 401 431 1224",
    "sg:postcode":"02914",
    "sg:province":"RI",
    "wof:name":"We Care For Kids Dental",
    "wof:placetype":"venue"
},
  "geometry": {"coordinates":[-71.356336,41.814989],"type":"Point"}
}