{
  "type": "Feature",
  "properties": {
    "iso:country":"US",
    "sg:address":"14 Enterprise Ln",
    "sg:city":"Smithfield",
    "sg:classifiers":[
        {
            "category":"Building & Trades",
            "subcategory":"Construction",
            "type":"Services"
        }
    ],
    "sg:phone":"+1 401 231 5459",
    "sg:postcode":"02917",
    "sg:province":"RI",
    "sg:tags":[
        "general",
        "contractor"
    ],
    "wof:name":"Dynamic Builders LLC",
    "wof:placetype":"venue"
},
  "geometry": {"coordinates":[-71.53915000000001,41.886778],"type":"Point"}
}