{
  "type": "Feature",
  "properties": {
    "iso:country":"US",
    "sg:address":"53 7th St",
    "sg:city":"East Providence",
    "sg:classifiers":[
        {
            "category":"Real Estate",
            "subcategory":"Real Estate Agent",
            "type":"Services"
        }
    ],
    "sg:phone":"+1 401 438 2153",
    "sg:postcode":"02914",
    "sg:province":"RI",
    "wof:name":"Real Estate Design Svc",
    "wof:placetype":"venue"
},
  "geometry": {"coordinates":[-71.38036200000001,41.813831],"type":"Point"}
}