{
  "type": "Feature",
  "properties": {
    "iso:country":"US",
    "sg:address":"15 Osage Dr",
    "sg:city":"Middletown",
    "sg:classifiers":[
        {
            "category":"Building & Trades",
            "subcategory":"Construction",
            "type":"Services"
        }
    ],
    "sg:phone":"+1 401 274 9500",
    "sg:postcode":"02842",
    "sg:province":"RI",
    "sg:tags":[
        "fire",
        "restoration",
        "damage"
    ],
    "wof:name":"Service Master Clean",
    "wof:placetype":"venue"
},
  "geometry": {"coordinates":[-71.301438,41.541911],"type":"Point"}
}