{
  "type": "Feature",
  "properties": {
    "addr:full":"26 Corey Ave East Greenwich RI 02818",
    "addr:housenumber":"26",
    "addr:postcode":"02818",
    "addr:street":"Corey Ave",
    "iso:country":"US",
    "sg:address":"26 Corey Ave",
    "sg:city":"East Greenwich",
    "sg:classifiers":[
        {
            "category":"Professional",
            "subcategory":"Management & Consulting",
            "type":"Services"
        }
    ],
    "sg:phone":"+1 401 884 6944",
    "sg:postcode":"02818",
    "sg:province":"RI",
    "sg:tags":[
        "marketing",
        "program"
    ],
    "sg:website":"www.si-design.net",
    "wof:name":"Stark Information Design",
    "wof:placetype":"venue"
},
  "geometry": {"coordinates":[-71.451061,41.667329],"type":"Point"}
}