{
  "type": "Feature",
  "properties": {
    "addr:full":"4145 Quaker Ln North Kingstown RI 02852",
    "addr:housenumber":"4145",
    "addr:postcode":"02852",
    "addr:street":"Quaker Ln",
    "iso:country":"US",
    "sg:address":"4145 Quaker Ln",
    "sg:city":"North Kingstown",
    "sg:classifiers":[
        {
            "category":"Banks & Credit Unions",
            "subcategory":"Bank",
            "type":"Services"
        }
    ],
    "sg:phone":"+1 401 294 3094",
    "sg:postcode":"02852",
    "sg:province":"RI",
    "wof:name":"Wave Federal Credit Union",
    "wof:placetype":"venue"
},
  "geometry": {"coordinates":[-71.501822,41.585374],"type":"Point"}
}