{
  "type": "Feature",
  "properties": {
    "addr:full":"508 Warren Ave East Providence RI 02914",
    "addr:housenumber":"508",
    "addr:postcode":"02914",
    "addr:street":"Warren Ave",
    "iso:country":"US",
    "sg:address":"508 Warren Ave",
    "sg:city":"East Providence",
    "sg:phone":"+1 401 434 0051",
    "sg:postcode":"02914",
    "sg:province":"RI",
    "sg:tags":[
        "oil"
    ],
    "wof:name":"Botelho Oil Co",
    "wof:placetype":"venue"
},
  "geometry": {"coordinates":[-71.363106,41.812145],"type":"Point"}
}