{
  "type": "Feature",
  "properties": {
    "iso:country":"US",
    "sg:address":"30 Starline Way",
    "sg:city":"Cranston",
    "sg:classifiers":[
        {
            "category":"Building & Trades",
            "subcategory":"Plumbing",
            "type":"Services"
        }
    ],
    "sg:phone":"+1 401 944 0616",
    "sg:postcode":"02921",
    "sg:province":"RI",
    "sg:tags":[
        "conditioning",
        "air",
        "system",
        "contractor"
    ],
    "wof:name":"S T Smith HTG & AC",
    "wof:placetype":"venue"
},
  "geometry": {"coordinates":[-71.52682799999999,41.788164],"type":"Point"}
}