{
  "type": "Feature",
  "properties": {
    "iso:country":"US",
    "sg:address":"516 S Main St Rear",
    "sg:city":"Woonsocket",
    "sg:classifiers":[
        {
            "category":"Health Services",
            "subcategory":"Dentist",
            "type":"Services"
        }
    ],
    "sg:phone":"+1 401 769 8520",
    "sg:postcode":"02895",
    "sg:province":"RI",
    "wof:name":"Robert E Bartro Dds Pc",
    "wof:placetype":"venue"
},
  "geometry": {"coordinates":[-71.526363,41.992809],"type":"Point"}
}