{
  "type": "Feature",
  "properties": {
    "addr:full":"39 Unity St Woonsocket RI 02895",
    "addr:housenumber":"39",
    "addr:postcode":"02895",
    "addr:street":"Unity St",
    "iso:country":"US",
    "sg:address":"39 Unity St",
    "sg:city":"Woonsocket",
    "sg:classifiers":[
        {
            "category":"Arts & Performance",
            "subcategory":"Theater",
            "type":"Entertainment"
        }
    ],
    "sg:phone":"+1 401 334 2796",
    "sg:postcode":"02895",
    "sg:province":"RI",
    "sg:tags":[
        "karaoke"
    ],
    "wof:name":"Sound Stream Disc Jockey Svc",
    "wof:placetype":"venue"
},
  "geometry": {"coordinates":[-71.507513,41.996972],"type":"Point"}
}