{
  "type": "Feature",
  "properties": {
    "addr:full":"50 Niantic Ave Providence RI 02907",
    "addr:housenumber":"50",
    "addr:postcode":"02907",
    "addr:street":"Niantic Ave",
    "iso:country":"US",
    "sg:address":"50 Niantic Ave",
    "sg:city":"Providence",
    "sg:classifiers":[
        {
            "category":"Wholesale",
            "subcategory":"Hardware",
            "type":"Manufacturing & Wholesale Goods"
        }
    ],
    "sg:phone":"+1 401 946 9444",
    "sg:postcode":"02907",
    "sg:province":"RI",
    "sg:tags":[
        "supply",
        "appliances-small",
        "part",
        "air conditioning"
    ],
    "sg:website":"http://www.johnstonesupply.com",
    "wof:name":"Johnstone Supply",
    "wof:placetype":"venue"
},
  "geometry": {"coordinates":[-71.439296,41.802077],"type":"Point"}
}