{
  "type": "Feature",
  "properties": {
    "addr:full":"180 S Main St Providence RI 02903",
    "addr:housenumber":"180",
    "addr:postcode":"02903",
    "addr:street":"S Main St",
    "iso:country":"US",
    "sg:address":"180 S Main St",
    "sg:city":"Providence",
    "sg:classifiers":[
        {
            "category":"Professional",
            "subcategory":"Lawyer & Legal Services",
            "type":"Services"
        }
    ],
    "sg:phone":"+1 401 861 8200",
    "sg:postcode":"02903",
    "sg:province":"RI",
    "wof:name":"Book Rebecca E",
    "wof:placetype":"venue"
},
  "geometry": {"coordinates":[-71.40679900000001,41.824001],"type":"Point"}
}