{
  "type": "Feature",
  "properties": {
    "iso:country":"US",
    "sg:address":"21 State Hwy 2",
    "sg:city":"Providence",
    "sg:classifiers":[
        {
            "category":"Health Services",
            "subcategory":"Doctor",
            "type":"Services"
        }
    ],
    "sg:phone":"+1 401 456 4461",
    "sg:postcode":"02920",
    "sg:province":"RI",
    "sg:tags":[
        "dentist"
    ],
    "wof:name":"St Joseph Hospital Pediatric",
    "wof:placetype":"venue"
},
  "geometry": {"coordinates":[-71.478905,41.735353],"type":"Point"}
}