{
  "type": "Feature",
  "properties": {
    "addr:full":"8 Hill St Coventry RI 02816",
    "addr:housenumber":"8",
    "addr:postcode":"02816",
    "addr:street":"Hill St",
    "iso:country":"US",
    "sg:address":"8 Hill St",
    "sg:city":"Coventry",
    "sg:classifiers":[
        {
            "category":"Building & Trades",
            "subcategory":"Construction",
            "type":"Services"
        }
    ],
    "sg:phone":"+1 401 822 1669",
    "sg:postcode":"02816",
    "sg:province":"RI",
    "sg:tags":[
        "excavating",
        "contractor"
    ],
    "wof:name":"Norman Chapdelaine Excavating",
    "wof:placetype":"venue"
},
  "geometry": {"coordinates":[-71.547478,41.729119],"type":"Point"}
}