{
  "type": "Feature",
  "properties": {
    "addr:full":"36 State St Woonsocket RI 02895",
    "addr:housenumber":"36",
    "addr:postcode":"02895",
    "addr:street":"State St",
    "iso:country":"US",
    "sg:address":"36 State St",
    "sg:city":"Woonsocket",
    "sg:classifiers":[
        {
            "category":"Building & Trades",
            "subcategory":"Cleaning & Sanitation",
            "type":"Services"
        }
    ],
    "sg:phone":"+1 401 765 4700",
    "sg:postcode":"02895",
    "sg:province":"RI",
    "sg:tags":[
        "janitor"
    ],
    "wof:name":"Cleaning Controls Janitorial",
    "wof:placetype":"venue"
},
  "geometry": {"coordinates":[-71.520689,42.015328],"type":"Point"}
}