{
  "type": "Feature",
  "properties": {
    "iso:country":"US",
    "sg:address":"58 Warren Way",
    "sg:city":"Providence",
    "sg:classifiers":[
        {
            "category":"Organizations",
            "subcategory":"Membership Organization",
            "type":"Services"
        }
    ],
    "sg:phone":"+1 401 781 5319",
    "sg:postcode":"02905",
    "sg:province":"RI",
    "wof:name":"R I Alliance For Lesbian & Gay",
    "wof:placetype":"venue"
},
  "geometry": {"coordinates":[-71.402086,41.802909],"type":"Point"}
}