{
  "type": "Feature",
  "properties": {
    "iso:country":"US",
    "sg:address":"2 Eastnor Rd",
    "sg:city":"Newport",
    "sg:classifiers":[
        {
            "category":"Organizations",
            "subcategory":"Religious Organization",
            "type":"Services"
        }
    ],
    "sg:phone":"+1 401 847 0518",
    "sg:postcode":"02840",
    "sg:province":"RI",
    "wof:name":"Saint Augustins Church Newport",
    "wof:placetype":"venue"
},
  "geometry": {"coordinates":[-71.31591,41.471956],"type":"Point"}
}