{
  "type": "Feature",
  "properties": {
    "iso:country":"US",
    "sg:address":"6 Middlebridge Rd",
    "sg:city":"Narragansett",
    "sg:classifiers":[
        {
            "category":"Building & Trades",
            "subcategory":"Landscaping Services",
            "type":"Services"
        }
    ],
    "sg:phone":"+1 401 782 8793",
    "sg:postcode":"02882",
    "sg:province":"RI",
    "sg:tags":[
        "landscape"
    ],
    "wof:name":"Creating Landscaping",
    "wof:placetype":"venue"
},
  "geometry": {"coordinates":[-71.443043,41.457357],"type":"Point"}
}