{
  "type": "Feature",
  "properties": {
    "iso:country":"US",
    "sg:address":"226 Public St",
    "sg:city":"Providence",
    "sg:classifiers":[
        {
            "category":"Manufacturing",
            "subcategory":"Jewelry",
            "type":"Manufacturing & Wholesale Goods"
        },
        {
            "category":"Education",
            "subcategory":"School",
            "type":"Public Place"
        }
    ],
    "sg:phone":"+1 401 331 0888",
    "sg:postcode":"02905",
    "sg:province":"RI",
    "wof:name":"National School Recognition",
    "wof:placetype":"venue"
},
  "geometry": {"coordinates":[-71.408151,41.807071],"type":"Point"}
}