{
  "type": "Feature",
  "properties": {
    "iso:country":"US",
    "sg:address":"460 Putnam Pike",
    "sg:city":"Greenville",
    "sg:classifiers":[
        {
            "category":"Restaurant",
            "type":"Food & Drink"
        }
    ],
    "sg:menulink":"http://www.allmenus.com/ri/smithfield/151766-a--w-restaurant/menu/",
    "sg:phone":"+1 401 949 9892",
    "sg:postcode":"02828",
    "sg:province":"RI",
    "sg:tags":[
        "food",
        "dog",
        "pub",
        "hot",
        "burger",
        "american"
    ],
    "wof:name":"A & W Restaurant",
    "wof:placetype":"venue"
},
  "geometry": {"coordinates":[-71.535004,41.870102],"type":"Point"}
}