{
  "type": "Feature",
  "properties": {
    "addr:full":"519 Broadway Pawtucket RI 02860",
    "addr:housenumber":"519",
    "addr:postcode":"02860",
    "addr:street":"Broadway",
    "iso:country":"US",
    "sg:address":"519 Broadway",
    "sg:city":"Pawtucket",
    "sg:classifiers":[
        {
            "category":"Retail",
            "subcategory":"Auto Repair",
            "type":"Services"
        }
    ],
    "sg:phone":"+1 401 365 6886",
    "sg:postcode":"02860",
    "sg:province":"RI",
    "wof:name":"M & G Autobody Inc",
    "wof:placetype":"venue"
},
  "geometry": {"coordinates":[-71.374516,41.887698],"type":"Point"}
}