{
  "type": "Feature",
  "properties": {
    "addr:full":"71 Old Tower Hill Rd Wakefield RI 02879",
    "addr:housenumber":"71",
    "addr:postcode":"02879",
    "addr:street":"Old Tower Hill Rd",
    "iso:country":"US",
    "sg:address":"71 Old Tower Hill Rd",
    "sg:city":"Wakefield",
    "sg:classifiers":[
        {
            "category":"Health Services",
            "subcategory":"Clinic",
            "type":"Services"
        }
    ],
    "sg:phone":"+1 401 789 3611",
    "sg:postcode":"02879",
    "sg:province":"RI",
    "sg:tags":[
        "home",
        "temporary"
    ],
    "wof:name":"Nursefinders",
    "wof:placetype":"venue"
},
  "geometry": {"coordinates":[-71.48179500000001,41.442214],"type":"Point"}
}