{
  "type": "Feature",
  "properties": {
    "iso:country":"US",
    "sg:address":"222 W Exchange St",
    "sg:city":"Providence",
    "sg:classifiers":[
        {
            "category":"Government",
            "subcategory":"Office",
            "type":"Public Place"
        }
    ],
    "sg:phone":"+1 401 553 2030",
    "sg:postcode":"02903",
    "sg:province":"RI",
    "sg:tags":[
        "federal",
        "program",
        "adm"
    ],
    "wof:name":"US Commerce Dept",
    "wof:placetype":"venue"
},
  "geometry": {"coordinates":[-71.42089900000001,41.825193],"type":"Point"}
}