{
  "type": "Feature",
  "properties": {
    "iso:country":"US",
    "sg:address":"160 Taunton Ave",
    "sg:city":"East Providence",
    "sg:classifiers":[
        {
            "category":"Professional",
            "subcategory":"Lawyer & Legal Services",
            "type":"Services"
        }
    ],
    "sg:phone":"+1 401 438 9000",
    "sg:postcode":"02914",
    "sg:province":"RI",
    "sg:tags":[
        "attorney"
    ],
    "sg:website":"www.nicholasbarrett.com",
    "wof:name":"Nicholas Barrett Law Offices",
    "wof:placetype":"venue"
},
  "geometry": {"coordinates":[-71.375518,41.819761],"type":"Point"}
}