{
  "type": "Feature",
  "properties": {
    "iso:country":"US",
    "sg:address":"493 Waterman Ave",
    "sg:city":"East Providence",
    "sg:classifiers":[
        {
            "category":"Bars & Pubs",
            "type":"Food & Drink"
        }
    ],
    "sg:phone":"+1 401 434 9531",
    "sg:postcode":"02914",
    "sg:province":"RI",
    "sg:tags":[
        "drinking"
    ],
    "wof:name":"Monforte's Bar",
    "wof:placetype":"venue"
},
  "geometry": {"coordinates":[-71.358459,41.816936],"type":"Point"}
}