{
  "type": "Feature",
  "properties": {
    "iso:country":"US",
    "sg:address":"26 Ship St",
    "sg:city":"Providence",
    "sg:classifiers":[
        {
            "category":"Professional",
            "subcategory":"Management & Consulting",
            "type":"Services"
        }
    ],
    "sg:phone":"+1 401 421 0488",
    "sg:postcode":"02903",
    "sg:province":"RI",
    "sg:tags":[
        "personnel",
        "consultant"
    ],
    "wof:name":"Initial Staffing Svc",
    "wof:placetype":"venue"
},
  "geometry": {"coordinates":[-71.408693,41.819159],"type":"Point"}
}