{
  "type": "Feature",
  "properties": {
    "iso:country":"US",
    "sg:address":"222 Richmond St",
    "sg:city":"Providence",
    "sg:classifiers":[
        {
            "category":"Professional",
            "subcategory":"Lawyer & Legal Services",
            "type":"Services"
        }
    ],
    "sg:phone":"+1 401 456 0709",
    "sg:postcode":"02903",
    "sg:province":"RI",
    "sg:tags":[
        "attorney"
    ],
    "wof:name":"Strauss Factor & Lopes",
    "wof:placetype":"venue"
},
  "geometry": {"coordinates":[-71.40886999999999,41.818986],"type":"Point"}
}