{
  "type": "Feature",
  "properties": {
    "iso:country":"US",
    "sg:address":"757 Broad St",
    "sg:city":"Central Falls",
    "sg:classifiers":[
        {
            "category":"Shopping",
            "subcategory":"Clothing, Apparel, & Fashions",
            "type":"Retail Goods"
        }
    ],
    "sg:phone":"+1 401 725 4801",
    "sg:postcode":"02863",
    "sg:province":"RI",
    "wof:name":"Albitas Boutique",
    "wof:placetype":"venue"
},
  "geometry": {"coordinates":[-71.387254,41.890016],"type":"Point"}
}