{
  "type": "Feature",
  "properties": {
    "iso:country":"US",
    "sg:address":"534 Angell St",
    "sg:city":"Providence",
    "sg:classifiers":[
        {
            "category":"Health Services",
            "subcategory":"Health Practitioner",
            "type":"Services"
        }
    ],
    "sg:phone":"+1 401 621 7739",
    "sg:postcode":"02906",
    "sg:province":"RI",
    "sg:tags":[
        "acupuncture"
    ],
    "wof:name":"Cate Chason",
    "wof:placetype":"venue"
},
  "geometry": {"coordinates":[-71.387106,41.830292],"type":"Point"}
}