{
  "type": "Feature",
  "properties": {
    "iso:country":"US",
    "sg:address":"22 Hilarity St",
    "sg:city":"Providence",
    "sg:classifiers":[
        {
            "category":"Professional",
            "type":"Services"
        }
    ],
    "sg:phone":"+1 401 421 1968",
    "sg:postcode":"02909",
    "sg:province":"RI",
    "wof:name":"Michelle Richardson",
    "wof:placetype":"venue"
},
  "geometry": {"coordinates":[-71.46277000000001,41.820336],"type":"Point"}
}