{
  "type": "Feature",
  "properties": {
    "iso:country":"US",
    "sg:address":"175 Greenwood Ave",
    "sg:city":"Rumford",
    "sg:classifiers":[
        {
            "category":"Professional",
            "type":"Services"
        }
    ],
    "sg:phone":"+1 401 438 1860",
    "sg:postcode":"02916",
    "sg:province":"RI",
    "sg:tags":[
        "establishment"
    ],
    "wof:name":"Cenos Design Works Inc",
    "wof:placetype":"venue"
},
  "geometry": {"coordinates":[-71.35225,41.837457],"type":"Point"}
}