{
  "type": "Feature",
  "properties": {
    "iso:country":"US",
    "sg:address":"116 Granite St",
    "sg:city":"Westerly",
    "sg:classifiers":[
        {
            "category":"Health Services",
            "subcategory":"Doctor",
            "type":"Services"
        }
    ],
    "sg:phone":"+1 401 596 5695",
    "sg:postcode":"02891",
    "sg:province":"RI",
    "sg:tags":[
        "physician",
        "surgeon"
    ],
    "wof:name":"Westerly Radiology Assoc Bllng",
    "wof:placetype":"venue"
},
  "geometry": {"coordinates":[-71.82037099999999,41.372505],"type":"Point"}
}