{
  "type": "Feature",
  "properties": {
    "iso:country":"US",
    "sg:address":"271 Post Rd",
    "sg:city":"Westerly",
    "sg:classifiers":[
        {
            "category":"Recreation",
            "type":"Entertainment"
        }
    ],
    "sg:phone":"+1 401 322 8003",
    "sg:postcode":"02891",
    "sg:province":"RI",
    "sg:tags":[
        "martial",
        "arts",
        "instruction"
    ],
    "wof:name":"Okinawan Karate Institute",
    "wof:placetype":"venue"
},
  "geometry": {"coordinates":[-71.76045499999999,41.351405],"type":"Point"}
}