{
  "type": "Feature",
  "properties": {
    "iso:country":"US",
    "sg:address":"120 W Main Rd",
    "sg:city":"Middletown",
    "sg:classifiers":[
        {
            "category":"Restaurant",
            "type":"Food & Drink"
        }
    ],
    "sg:phone":"+1 401 841 5560",
    "sg:postcode":"02842",
    "sg:province":"RI",
    "sg:tags":[
        "eating"
    ],
    "wof:name":"Rhea's Restaurant",
    "wof:placetype":"venue"
},
  "geometry": {"coordinates":[-71.302103,41.509298],"type":"Point"}
}