{
  "type": "Feature",
  "properties": {
    "addr:full":"19 Sharpe Dr Cranston RI 02920",
    "addr:housenumber":"19",
    "addr:postcode":"02920",
    "addr:street":"Sharpe Dr",
    "iso:country":"US",
    "sg:address":"19 Sharpe Dr",
    "sg:city":"Cranston",
    "sg:classifiers":[
        {
            "category":"Manufacturing",
            "subcategory":"Printing",
            "type":"Manufacturing & Wholesale Goods"
        }
    ],
    "sg:phone":"+1 401 739 7373",
    "sg:postcode":"02920",
    "sg:province":"RI",
    "sg:tags":[
        "lithographic",
        "commercial"
    ],
    "wof:name":"Providence Channel Co",
    "wof:placetype":"venue"
},
  "geometry": {"coordinates":[-71.453828,41.741098],"type":"Point"}
}