{
  "type": "Feature",
  "properties": {
    "addr:full":"680 Kingstown Rd West Kingston RI 02892",
    "addr:housenumber":"680",
    "addr:postcode":"02892",
    "addr:street":"Kingstown Rd West",
    "iso:country":"US",
    "sg:address":"680 Kingstown Rd",
    "sg:city":"West Kingston",
    "sg:classifiers":[
        {
            "category":"Building & Trades",
            "subcategory":"Landscaping Services",
            "type":"Services"
        }
    ],
    "sg:phone":"+1 401 783 7704",
    "sg:postcode":"02892",
    "sg:province":"RI",
    "sg:tags":[
        "crop",
        "general"
    ],
    "wof:name":"Sosnowski Farm",
    "wof:placetype":"venue"
},
  "geometry": {"coordinates":[-71.590717,41.500779],"type":"Point"}
}