{
  "type": "Feature",
  "properties": {
    "addr:full":"169 Osprey Rd Wakefield RI 02879",
    "addr:housenumber":"169",
    "addr:postcode":"02879",
    "addr:street":"Osprey Rd",
    "iso:country":"US",
    "sg:address":"169 Osprey Rd",
    "sg:city":"Wakefield",
    "sg:classifiers":[
        {
            "category":"Professional",
            "subcategory":"Management & Consulting",
            "type":"Services"
        },
        {
            "category":"Education",
            "subcategory":"Special Training",
            "type":"Public Place"
        }
    ],
    "sg:phone":"+1 401 782 2267",
    "sg:postcode":"02879",
    "sg:province":"RI",
    "sg:tags":[
        "sales",
        "program",
        "direct",
        "retail"
    ],
    "wof:name":"Northeast Sales Svcs Inc",
    "wof:placetype":"venue"
},
  "geometry": {"coordinates":[-71.550439,41.385568],"type":"Point"}
}