{
  "type": "Feature",
  "properties": {
    "iso:country":"US",
    "sg:address":"124 Hall Rd",
    "sg:city":"Greene",
    "sg:classifiers":[
        {
            "category":"Manufacturing",
            "subcategory":"Lumber",
            "type":"Manufacturing & Wholesale Goods"
        },
        {
            "category":"Home & Garden",
            "subcategory":"Garden Supply",
            "type":"Retail Goods"
        }
    ],
    "sg:phone":"+1 401 397 3600",
    "sg:postcode":"02827",
    "sg:province":"RI",
    "sg:tags":[
        "operation",
        "timber",
        "tree",
        "christmas",
        "tract"
    ],
    "wof:name":"Greene Tree Farm & Nursery",
    "wof:placetype":"venue"
},
  "geometry": {"coordinates":[-71.72129099999999,41.721193],"type":"Point"}
}