{
  "type": "Feature",
  "properties": {
    "iso:country":"US",
    "sg:address":"1 Evans Way",
    "sg:city":"Cranston",
    "sg:classifiers":[
        {
            "category":"Organizations",
            "subcategory":"Religious Organization",
            "type":"Services"
        }
    ],
    "sg:phone":"+1 401 946 6900",
    "sg:postcode":"02920",
    "sg:province":"RI",
    "sg:tags":[
        "ministry"
    ],
    "wof:name":"Richard W Evans",
    "wof:placetype":"venue"
},
  "geometry": {"coordinates":[-71.469032,41.756282],"type":"Point"}
}