{
  "type": "Feature",
  "properties": {
    "addr:full":"178 Angell St Providence RI 02906",
    "addr:housenumber":"178",
    "addr:postcode":"02906",
    "addr:street":"Angell St",
    "iso:country":"US",
    "sg:address":"178 Angell St",
    "sg:city":"Providence",
    "sg:classifiers":[
        {
            "category":"Food & Beverages",
            "subcategory":"Specialty",
            "type":"Retail Goods"
        }
    ],
    "sg:phone":"+1 401 273 5464",
    "sg:postcode":"02906",
    "sg:province":"RI",
    "sg:tags":[
        "health",
        "market",
        "diet"
    ],
    "sg:website":"www.smoothieking.com",
    "wof:name":"Smoothie King",
    "wof:placetype":"venue"
},
  "geometry": {"coordinates":[-71.400002,41.828098],"type":"Point"}
}