{
  "type": "Feature",
  "properties": {
    "addr:full":"552 Klondike Rd Charlestown RI 02813",
    "addr:housenumber":"552",
    "addr:postcode":"02813",
    "addr:street":"Klondike Rd",
    "iso:country":"US",
    "sg:address":"552 Klondike Rd",
    "sg:city":"Charlestown",
    "sg:classifiers":[
        {
            "category":"Building & Trades",
            "subcategory":"Construction",
            "type":"Services"
        }
    ],
    "sg:phone":"+1 401 322 0368",
    "sg:postcode":"02813",
    "sg:province":"RI",
    "sg:tags":[
        "contractor"
    ],
    "wof:name":"Sacco Enterprises Inc",
    "wof:placetype":"venue"
},
  "geometry": {"coordinates":[-71.726382,41.38445],"type":"Point"}
}