{
  "type": "Feature",
  "properties": {
    "iso:country":"US",
    "sg:address":"328 County Rd",
    "sg:city":"Barrington",
    "sg:classifiers":[
        {
            "category":"Restaurant",
            "type":"Food & Drink"
        }
    ],
    "sg:phone":"+1 401 245 1900",
    "sg:postcode":"02806",
    "sg:province":"RI",
    "sg:tags":[
        "eating"
    ],
    "wof:name":"Princes Hill Deli & Catering",
    "wof:placetype":"venue"
},
  "geometry": {"coordinates":[-71.311689,41.742495],"type":"Point"}
}