{
  "type": "Feature",
  "properties": {
    "iso:country":"US",
    "sg:address":"23 Alderbrook Dr",
    "sg:city":"Cranston",
    "sg:classifiers":[
        {
            "category":"Building & Trades",
            "subcategory":"Construction",
            "type":"Services"
        }
    ],
    "sg:phone":"+1 401 942 8950",
    "sg:postcode":"02920",
    "sg:province":"RI",
    "sg:tags":[
        "speculative",
        "builder"
    ],
    "wof:name":"Alderbrook Builders Inc",
    "wof:placetype":"venue"
},
  "geometry": {"coordinates":[-71.47349699999999,41.757965],"type":"Point"}
}