{
  "type": "Feature",
  "properties": {
    "addr:full":"19 Carrie Ave Rumford RI 02916",
    "addr:housenumber":"19",
    "addr:postcode":"02916",
    "addr:street":"Carrie Ave",
    "iso:country":"US",
    "sg:address":"19 Carrie Ave",
    "sg:city":"Rumford",
    "sg:classifiers":[
        {
            "category":"Real Estate",
            "subcategory":"Real Estate Services",
            "type":"Services"
        },
        {
            "category":"Building & Trades",
            "subcategory":"Pest Control",
            "type":"Services"
        }
    ],
    "sg:phone":"+1 401 434 7418",
    "sg:postcode":"02916",
    "sg:province":"RI",
    "sg:tags":[
        "home",
        "inspector",
        "mothproofing"
    ],
    "sg:website":"www.guardianpestcontrol.biz",
    "wof:name":"Guardian Pest Control Inc",
    "wof:placetype":"venue"
},
  "geometry": {"coordinates":[-71.357591,41.831758],"type":"Point"}
}