{
  "type": "Feature",
  "properties": {
    "iso:country":"US",
    "sg:address":"70 Serrel Sweet Rd",
    "sg:city":"Johnston",
    "sg:classifiers":[
        {
            "category":"Organizations",
            "subcategory":"Community Association",
            "type":"Services"
        }
    ],
    "sg:phone":"+1 401 233 4242",
    "sg:postcode":"02919",
    "sg:province":"RI",
    "wof:name":"Rhode Island Amateur Hock",
    "wof:placetype":"venue"
},
  "geometry": {"coordinates":[-71.492538,41.861042],"type":"Point"}
}