{
  "type": "Feature",
  "properties": {
    "addr:full":"155 Morin St Woonsocket RI 02895",
    "addr:housenumber":"155",
    "addr:postcode":"02895",
    "addr:street":"Morin St",
    "iso:country":"US",
    "sg:address":"155 Morin St",
    "sg:city":"Woonsocket",
    "sg:classifiers":[
        {
            "category":"Arts & Performance",
            "subcategory":"Theater",
            "type":"Entertainment"
        }
    ],
    "sg:phone":"+1 401 356 0888",
    "sg:postcode":"02895",
    "sg:province":"RI",
    "sg:tags":[
        "live",
        "music"
    ],
    "wof:name":"Acoustic Creations",
    "wof:placetype":"venue"
},
  "geometry": {"coordinates":[-71.482405,42.012527],"type":"Point"}
}