{
  "type": "Feature",
  "properties": {
    "addr:full":"1595 Mendon Rd Cumberland RI 02864",
    "addr:housenumber":"1595",
    "addr:postcode":"02864",
    "addr:street":"Mendon Rd",
    "iso:country":"US",
    "sg:address":"1595 Mendon Rd",
    "sg:city":"Cumberland",
    "sg:classifiers":[
        {
            "category":"Professional",
            "subcategory":"Engineering",
            "type":"Services"
        }
    ],
    "sg:phone":"+1 401 334 2327",
    "sg:postcode":"02864",
    "sg:province":"RI",
    "sg:tags":[
        "consulting",
        "engineer"
    ],
    "wof:name":"Chi Engineering Svcs",
    "wof:placetype":"venue"
},
  "geometry": {"coordinates":[-71.43303899999999,41.9403],"type":"Point"}
}