{
  "type": "Feature",
  "properties": {
    "iso:country":"US",
    "sg:address":"167 Old Greenwich Dr",
    "sg:city":"East Greenwich",
    "sg:classifiers":[
        {
            "category":"Social Services",
            "subcategory":"Child Care",
            "type":"Services"
        }
    ],
    "sg:phone":"+1 401 884 8964",
    "sg:postcode":"02818",
    "sg:province":"RI",
    "sg:tags":[
        "kindergarten",
        "academic",
        "school"
    ],
    "wof:name":"East Greenwich Pre School",
    "wof:placetype":"venue"
},
  "geometry": {"coordinates":[-71.47867100000001,41.654637],"type":"Point"}
}