{
  "type": "Feature",
  "properties": {
    "iso:country":"US",
    "sg:address":"95 Main St",
    "sg:city":"Wakefield",
    "sg:classifiers":[
        {
            "category":"Building & Trades",
            "subcategory":"Construction",
            "type":"Services"
        }
    ],
    "sg:phone":"+1 401 792 2200",
    "sg:postcode":"02879",
    "sg:province":"RI",
    "sg:tags":[
        "general",
        "contractor"
    ],
    "wof:name":"Abbey Construction",
    "wof:placetype":"venue"
},
  "geometry": {"coordinates":[-71.491885,41.441228],"type":"Point"}
}