{
  "type": "Feature",
  "properties": {
    "iso:country":"US",
    "sg:address":"250 Wampanoag Trl",
    "sg:city":"Riverside",
    "sg:classifiers":[
        {
            "category":"Health Services",
            "subcategory":"Medical Lab",
            "type":"Services"
        }
    ],
    "sg:phone":"+1 401 433 2616",
    "sg:postcode":"02915",
    "sg:province":"RI",
    "sg:tags":[
        "laboratory"
    ],
    "wof:name":"Quest Diagnostics",
    "wof:placetype":"venue"
},
  "geometry": {"coordinates":[-71.353779,41.795949],"type":"Point"}
}