{
  "type": "Feature",
  "properties": {
    "iso:country":"US",
    "sg:address":"10 Bellewood Ct",
    "sg:city":"North Kingstown",
    "sg:classifiers":[
        {
            "category":"Professional",
            "subcategory":"Management & Consulting",
            "type":"Services"
        }
    ],
    "sg:phone":"+1 401 667 0036",
    "sg:postcode":"02852",
    "sg:province":"RI",
    "wof:name":"Angora Group Inc",
    "wof:placetype":"venue"
},
  "geometry": {"coordinates":[-71.496112,41.566242],"type":"Point"}
}