{
  "type": "Feature",
  "properties": {
    "iso:country":"US",
    "sg:address":"38 Brandon Rd",
    "sg:city":"Cranston",
    "sg:classifiers":[
        {
            "category":"Home & Garden",
            "subcategory":"Building Materials",
            "type":"Retail Goods"
        }
    ],
    "sg:phone":"+1 401 397 6338",
    "sg:postcode":"02910",
    "sg:province":"RI",
    "wof:name":"Rhode Island Windshield Repair",
    "wof:placetype":"venue"
},
  "geometry": {"coordinates":[-71.43043400000001,41.784507],"type":"Point"}
}