{
  "type": "Feature",
  "properties": {
    "addr:full":"455 Post Rd Warwick RI 02888",
    "addr:housenumber":"455",
    "addr:postcode":"02888",
    "addr:street":"Post Rd",
    "iso:country":"US",
    "sg:address":"455 Post Rd",
    "sg:city":"Warwick",
    "sg:classifiers":[
        {
            "category":"Food & Beverages",
            "subcategory":"Bakery",
            "type":"Retail Goods"
        }
    ],
    "sg:phone":"+1 401 461 0060",
    "sg:postcode":"02888",
    "sg:province":"RI",
    "sg:tags":[
        "cookie",
        "cracker"
    ],
    "wof:name":"Nonni's Cookie Jar",
    "wof:placetype":"venue"
},
  "geometry": {"coordinates":[-71.405838,41.759682],"type":"Point"}
}