{
  "type": "Feature",
  "properties": {
    "iso:country":"US",
    "sg:address":"52 Shore Rd",
    "sg:city":"Westerly",
    "sg:classifiers":[
        {
            "category":"Building & Trades",
            "subcategory":"Construction",
            "type":"Services"
        }
    ],
    "sg:phone":"+1 401 596 8841",
    "sg:postcode":"02891",
    "sg:province":"RI",
    "sg:tags":[
        "contractor"
    ],
    "wof:name":"Mike Misto Builders",
    "wof:placetype":"venue"
},
  "geometry": {"coordinates":[-71.819451,41.327915],"type":"Point"}
}