{
  "type": "Feature",
  "properties": {
    "addr:full":"80 Huron St Warwick RI 02889",
    "addr:housenumber":"80",
    "addr:postcode":"02889",
    "addr:street":"Huron St",
    "iso:country":"US",
    "sg:address":"80 Huron St",
    "sg:city":"Warwick",
    "sg:classifiers":[
        {
            "category":"Professional",
            "subcategory":"Lawyer & Legal Services",
            "type":"Services"
        }
    ],
    "sg:phone":"+1 401 738 6077",
    "sg:postcode":"02889",
    "sg:province":"RI",
    "wof:name":"Cap Systems Unlimited",
    "wof:placetype":"venue"
},
  "geometry": {"coordinates":[-71.395753,41.687764],"type":"Point"}
}