{
  "type": "Feature",
  "properties": {
    "iso:country":"US",
    "sg:address":"26 Brownell St",
    "sg:city":"Warren",
    "sg:classifiers":[
        {
            "category":"Real Estate",
            "subcategory":"Real Estate Agent",
            "type":"Services"
        }
    ],
    "sg:phone":"+1 401 245 0117",
    "sg:postcode":"02885",
    "sg:province":"RI",
    "wof:name":"Kindred Properties LLC",
    "wof:placetype":"venue"
},
  "geometry": {"coordinates":[-71.240554,41.699035],"type":"Point"}
}