{
  "type": "Feature",
  "properties": {
    "iso:country":"US",
    "sg:address":"470 Old Baptist Rd",
    "sg:city":"North Kingstown",
    "sg:classifiers":[
        {
            "category":"Professional",
            "subcategory":"Engineering",
            "type":"Services"
        }
    ],
    "sg:phone":"+1 401 884 7392",
    "sg:postcode":"02852",
    "sg:province":"RI",
    "wof:name":"D Z Bailey Engr",
    "wof:placetype":"venue"
},
  "geometry": {"coordinates":[-71.48048900000001,41.602832],"type":"Point"}
}