{
  "type": "Feature",
  "properties": {
    "iso:country":"US",
    "sg:address":"40 Mary St",
    "sg:city":"Newport",
    "sg:classifiers":[
        {
            "category":"Wholesale",
            "subcategory":"Sporting Goods",
            "type":"Manufacturing & Wholesale Goods"
        }
    ],
    "sg:phone":"+1 401 848 6440",
    "sg:postcode":"02840",
    "sg:province":"RI",
    "sg:tags":[
        "wholesaler",
        "distributor"
    ],
    "wof:name":"Z-Clad Distributors LLC",
    "wof:placetype":"venue"
},
  "geometry": {"coordinates":[-71.314346,41.488448],"type":"Point"}
}