{
  "type": "Feature",
  "properties": {
    "iso:country":"US",
    "sg:address":"568 Park Ave",
    "sg:city":"Portsmouth",
    "sg:classifiers":[
        {
            "category":"Bars & Pubs",
            "type":"Food & Drink"
        }
    ],
    "sg:phone":"+1 401 683 9881",
    "sg:postcode":"02871",
    "sg:province":"RI",
    "wof:name":"Island Tap",
    "wof:placetype":"venue"
},
  "geometry": {"coordinates":[-71.226074,41.623605],"type":"Point"}
}