{
  "type": "Feature",
  "properties": {
    "iso:country":"US",
    "sg:address":"326 Warren Ave",
    "sg:city":"East Providence",
    "sg:classifiers":[
        {
            "category":"Manufacturing",
            "subcategory":"Furniture",
            "type":"Manufacturing & Wholesale Goods"
        }
    ],
    "sg:phone":"+1 401 438 4285",
    "sg:postcode":"02914",
    "sg:province":"RI",
    "sg:tags":[
        "mfg"
    ],
    "wof:name":"Olivia Galeria",
    "wof:placetype":"venue"
},
  "geometry": {"coordinates":[-71.367969,41.813311],"type":"Point"}
}