{
  "type": "Feature",
  "properties": {
    "iso:country":"US",
    "sg:address":"167 Gano St",
    "sg:city":"Providence",
    "sg:classifiers":[
        {
            "category":"Health Services",
            "subcategory":"Health Practitioner",
            "type":"Services"
        }
    ],
    "sg:phone":"+1 401 274 4325",
    "sg:postcode":"02906",
    "sg:province":"RI",
    "sg:tags":[
        "clinic",
        "therapist",
        "therapy",
        "physical"
    ],
    "sg:website":"http://www.silkphysicaltherapy.com",
    "wof:name":"Silk Physical Therapy Center",
    "wof:placetype":"venue"
},
  "geometry": {"coordinates":[-71.390404,41.824501],"type":"Point"}
}