{
  "type": "Feature",
  "properties": {
    "addr:full":"50 Narragansett Park Dr East Providence RI 02916",
    "addr:housenumber":"50",
    "addr:postcode":"02916",
    "addr:street":"Narragansett Park Dr",
    "iso:country":"US",
    "sg:address":"50 Narragansett Park Dr",
    "sg:city":"East Providence",
    "sg:classifiers":[
        {
            "category":"Personal",
            "type":"Services"
        },
        {
            "category":"Sports & Exercise",
            "subcategory":"Gym",
            "type":"Entertainment"
        },
        {
            "category":"Arena",
            "subcategory":"Sports Club",
            "type":"Entertainment"
        }
    ],
    "sg:phone":"+1 401 434 1500",
    "sg:postcode":"02916",
    "sg:province":"RI",
    "sg:tags":[
        "trainer",
        "consultant",
        "gymnasium",
        "program",
        "health",
        "fitness",
        "physical"
    ],
    "sg:website":"www.ballyfitness.com/",
    "wof:name":"Bally Total Fitness",
    "wof:placetype":"venue"
},
  "geometry": {"coordinates":[-71.352501,41.858638],"type":"Point"}
}