{
  "type": "Feature",
  "properties": {
    "addr:full":"62 Commercial Way East Providence RI 02914",
    "addr:housenumber":"62",
    "addr:postcode":"02914",
    "addr:street":"Commercial Way",
    "iso:country":"US",
    "sg:address":"62 Commercial Way",
    "sg:city":"East Providence",
    "sg:classifiers":[
        {
            "category":"Government",
            "subcategory":"Police Station",
            "type":"Public Place"
        }
    ],
    "sg:phone":"+1 401 435 7675",
    "sg:postcode":"02914",
    "sg:province":"RI",
    "sg:tags":[
        "department"
    ],
    "wof:name":"East Providence Animal Shelter",
    "wof:placetype":"venue"
},
  "geometry": {"coordinates":[-71.34887000000001,41.814395],"type":"Point"}
}