{
  "type": "Feature",
  "properties": {
    "addr:full":"156 King Philip Rd Rumford RI 02916",
    "addr:housenumber":"156",
    "addr:postcode":"02916",
    "addr:street":"King Philip Rd",
    "iso:country":"US",
    "sg:address":"156 King Philip Rd",
    "sg:city":"Rumford",
    "sg:classifiers":[
        {
            "category":"Professional",
            "subcategory":"Business Services",
            "type":"Services"
        }
    ],
    "sg:phone":"+1 401 435 9175",
    "sg:postcode":"02916",
    "sg:province":"RI",
    "wof:name":"A OK Lead Inspection Inc",
    "wof:placetype":"venue"
},
  "geometry": {"coordinates":[-71.364525,41.831698],"type":"Point"}
}