{
  "type": "Feature",
  "properties": {
    "iso:country":"US",
    "sg:address":"356 Mendon Rd",
    "sg:city":"Cumberland",
    "sg:classifiers":[
        {
            "category":"Restaurant",
            "type":"Food & Drink"
        }
    ],
    "sg:phone":"+1 401 727 2188",
    "sg:postcode":"02864",
    "sg:province":"RI",
    "wof:name":"Royal Panda",
    "wof:placetype":"venue"
},
  "geometry": {"coordinates":[-71.40737799999999,41.919033],"type":"Point"}
}