{
  "type": "Feature",
  "properties": {
    "iso:country":"US",
    "sg:address":"421 Lincoln Ave",
    "sg:city":"Warwick",
    "sg:classifiers":[
        {
            "category":"Building & Trades",
            "subcategory":"Electrical",
            "type":"Services"
        }
    ],
    "sg:phone":"+1 401 737 2750",
    "sg:postcode":"02888",
    "sg:province":"RI",
    "sg:tags":[
        "electrical",
        "contractor"
    ],
    "wof:name":"Croce Electric Company Inc",
    "wof:placetype":"venue"
},
  "geometry": {"coordinates":[-71.43829700000001,41.74391],"type":"Point"}
}