{
  "type": "Feature",
  "properties": {
    "addr:full":"2348 Post Rd Warwick RI 02886",
    "addr:housenumber":"2348",
    "addr:postcode":"02886",
    "addr:street":"Post Rd",
    "iso:country":"US",
    "sg:address":"2348 Post Rd",
    "sg:city":"Warwick",
    "sg:classifiers":[
        {
            "category":"Banks & Credit Unions",
            "subcategory":"Investment Brokerage",
            "type":"Services"
        }
    ],
    "sg:phone":"+1 401 921 1733",
    "sg:postcode":"02886",
    "sg:province":"RI",
    "sg:tags":[
        "advisory",
        "financial"
    ],
    "sg:website":"www.ameriprise.com",
    "wof:name":"Ameriprise Financial",
    "wof:placetype":"venue"
},
  "geometry": {"coordinates":[-71.443333,41.718766],"type":"Point"}
}