{
  "type": "Feature",
  "properties": {
    "iso:country":"US",
    "sg:address":"32 Prospect Hill St",
    "sg:city":"Newport",
    "sg:classifiers":[
        {
            "category":"Travel",
            "subcategory":"Hotels & Motels",
            "type":"Entertainment"
        }
    ],
    "sg:phone":"+1 401 847 7420",
    "sg:postcode":"02840",
    "sg:province":"RI",
    "wof:name":"Prospect Hill Guest House",
    "wof:placetype":"venue"
},
  "geometry": {"coordinates":[-71.314194,41.485411],"type":"Point"}
}