{
  "type": "Feature",
  "properties": {
    "iso:country":"US",
    "sg:address":"1350 Mineral Spring Ave",
    "sg:city":"N Providence",
    "sg:classifiers":[
        {
            "category":"Home & Garden",
            "subcategory":"Furniture",
            "type":"Retail Goods"
        }
    ],
    "sg:phone":"+1 401 724 8900",
    "sg:postcode":"02904",
    "sg:province":"RI",
    "sg:tags":[
        "consumer",
        "household",
        "appliance",
        "store"
    ],
    "sg:website":"www.andorstv.com",
    "wof:name":"Andor's Furniture Showroom",
    "wof:placetype":"venue"
},
  "geometry": {"coordinates":[-71.4375,41.867599],"type":"Point"}
}