{
  "type": "Feature",
  "properties": {
    "iso:country":"US",
    "sg:address":"387 George Waterman Rd",
    "sg:city":"Johnston",
    "sg:classifiers":[
        {
            "category":"Shopping",
            "subcategory":"Florist",
            "type":"Retail Goods"
        }
    ],
    "sg:phone":"+1 401 231 5666",
    "sg:postcode":"02919",
    "sg:province":"RI",
    "wof:name":"Cherry Hill Florist",
    "wof:placetype":"venue"
},
  "geometry": {"coordinates":[-71.48748399999999,41.852851],"type":"Point"}
}