{
  "type": "Feature",
  "properties": {
    "addr:full":"4 Lampercock Ln Lincoln RI 02865",
    "addr:housenumber":"4",
    "addr:postcode":"02865",
    "addr:street":"Lampercock Ln",
    "iso:country":"US",
    "sg:address":"4 Lampercock Ln",
    "sg:city":"Lincoln",
    "sg:classifiers":[
        {
            "category":"Professional",
            "type":"Services"
        }
    ],
    "sg:phone":"+1 401 725 9333",
    "sg:postcode":"02865",
    "sg:province":"RI",
    "wof:name":"Global Postal Services Inc",
    "wof:placetype":"venue"
},
  "geometry": {"coordinates":[-71.470992,41.921662],"type":"Point"}
}