{
  "type": "Feature",
  "properties": {
    "iso:country":"US",
    "sg:address":"12 Benjamin St",
    "sg:city":"Pawtucket",
    "sg:classifiers":[
        {
            "category":"Food & Beverages",
            "subcategory":"Chocolate",
            "type":"Retail Goods"
        }
    ],
    "sg:phone":"+1 401 241 9634",
    "sg:postcode":"02861",
    "sg:province":"RI",
    "sg:tags":[
        "cocoa"
    ],
    "wof:name":"Sinfully Sweet Chocolate",
    "wof:placetype":"venue"
},
  "geometry": {"coordinates":[-71.353313,41.877935],"type":"Point"}
}