{
  "type": "Feature",
  "properties": {
    "addr:full":"850 Warren Ave East Providence RI 02914",
    "addr:housenumber":"850",
    "addr:postcode":"02914",
    "addr:street":"Warren Ave",
    "iso:country":"US",
    "sg:address":"850 Warren Ave",
    "sg:city":"East Providence",
    "sg:classifiers":[
        {
            "category":"Real Estate",
            "subcategory":"Real Estate Operator",
            "type":"Services"
        }
    ],
    "sg:phone":"+1 401 434 8599",
    "sg:postcode":"02914",
    "sg:province":"RI",
    "sg:tags":[
        "apartment"
    ],
    "wof:name":"Wampanoag Village Apartments",
    "wof:placetype":"venue"
},
  "geometry": {"coordinates":[-71.349473,41.808774],"type":"Point"}
}