{
  "type": "Feature",
  "properties": {
    "addr:full":"9 Elmdale Ave Johnston RI 02919",
    "addr:housenumber":"9",
    "addr:postcode":"02919",
    "addr:street":"Elmdale Ave",
    "iso:country":"US",
    "sg:address":"9 Elmdale Ave",
    "sg:city":"Johnston",
    "sg:classifiers":[
        {
            "category":"Health Services",
            "subcategory":"Clinic",
            "type":"Services"
        }
    ],
    "sg:phone":"+1 401 934 3933",
    "sg:postcode":"02919",
    "sg:province":"RI",
    "sg:tags":[
        "education"
    ],
    "wof:name":"Moonlight Novelties",
    "wof:placetype":"venue"
},
  "geometry": {"coordinates":[-71.55723999999999,41.833492],"type":"Point"}
}