{
  "type": "Feature",
  "properties": {
    "iso:country":"US",
    "sg:address":"130 Dorrance St",
    "sg:city":"Providence",
    "sg:classifiers":[
        {
            "category":"Professional",
            "subcategory":"Lawyer & Legal Services",
            "type":"Services"
        }
    ],
    "sg:phone":"+1 401 861 9400",
    "sg:postcode":"02903",
    "sg:province":"RI",
    "sg:tags":[
        "attorney"
    ],
    "wof:name":"Garry Giragosian",
    "wof:placetype":"venue"
},
  "geometry": {"coordinates":[-71.40962399999999,41.822177],"type":"Point"}
}