{
  "type": "Feature",
  "properties": {
    "iso:country":"US",
    "sg:address":"1560 Bulgarmarsh Rd",
    "sg:city":"Tiverton",
    "sg:classifiers":[
        {
            "category":"Shopping",
            "type":"Retail Goods"
        }
    ],
    "sg:phone":"+1 401 624 2975",
    "sg:postcode":"02878",
    "sg:province":"RI",
    "sg:tags":[
        "factory",
        "outlet"
    ],
    "wof:name":"Christina's Curtain Outlet",
    "wof:placetype":"venue"
},
  "geometry": {"coordinates":[-71.145848,41.626564],"type":"Point"}
}