{
  "type": "Feature",
  "properties": {
    "iso:country":"US",
    "sg:address":"23 Brinley St",
    "sg:city":"Newport",
    "sg:classifiers":[
        {
            "category":"Travel",
            "subcategory":"Hotels & Motels",
            "type":"Entertainment"
        }
    ],
    "sg:phone":"+1 401 849 7645",
    "sg:postcode":"02840",
    "sg:province":"RI",
    "sg:tags":[
        "breakfast",
        "inn",
        "bed",
        "accommodation"
    ],
    "sg:website":"www.brinleyvictorian.com",
    "wof:name":"Brinley Victorian Inn Ltd",
    "wof:placetype":"venue"
},
  "geometry": {"coordinates":[-71.30816,41.488652],"type":"Point"}
}