{
  "type": "Feature",
  "properties": {
    "addr:full":"1524 Atwood Ave Johnston RI 02919",
    "addr:housenumber":"1524",
    "addr:postcode":"02919",
    "addr:street":"Atwood Ave",
    "iso:country":"US",
    "sg:address":"1524 Atwood Ave",
    "sg:city":"Johnston",
    "sg:classifiers":[
        {
            "category":"Health Services",
            "subcategory":"Doctor",
            "type":"Services"
        }
    ],
    "sg:phone":"+1 401 521 6080",
    "sg:postcode":"02919",
    "sg:province":"RI",
    "sg:tags":[
        "medical"
    ],
    "wof:name":"A Phillip John MD",
    "wof:placetype":"venue"
},
  "geometry": {"coordinates":[-71.500694,41.829848],"type":"Point"}
}