{
  "type": "Feature",
  "properties": {
    "addr:full":"1076 N Main St Providence RI 02904",
    "addr:housenumber":"1076",
    "addr:postcode":"02904",
    "addr:street":"N Main St",
    "iso:country":"US",
    "sg:address":"1076 N Main St",
    "sg:city":"Providence",
    "sg:classifiers":[
        {
            "category":"Health Services",
            "subcategory":"Clinic",
            "type":"Services"
        }
    ],
    "sg:phone":"+1 401 273 2552",
    "sg:postcode":"02904",
    "sg:province":"RI",
    "wof:name":"Heart Center Inc",
    "wof:placetype":"venue"
},
  "geometry": {"coordinates":[-71.402764,41.850748],"type":"Point"}
}