{
  "type": "Feature",
  "properties": {
    "iso:country":"US",
    "sg:address":"116 Selma St",
    "sg:city":"Cranston",
    "sg:classifiers":[
        {
            "category":"Personal",
            "subcategory":"Barber",
            "type":"Services"
        }
    ],
    "sg:phone":"+1 401 464 6437",
    "sg:postcode":"02920",
    "sg:province":"RI",
    "sg:tags":[
        "shop"
    ],
    "wof:name":"Sals Barber Salon",
    "wof:placetype":"venue"
},
  "geometry": {"coordinates":[-71.46199900000001,41.774693],"type":"Point"}
}