{
  "type": "Feature",
  "properties": {
    "addr:full":"904 Boston Neck Rd Narragansett RI 02882",
    "addr:housenumber":"904",
    "addr:postcode":"02882",
    "addr:street":"Boston Neck Rd",
    "iso:country":"US",
    "sg:address":"904 Boston Neck Rd",
    "sg:city":"Narragansett",
    "sg:classifiers":[
        {
            "category":"Bakery",
            "type":"Food & Drink"
        },
        {
            "category":"Coffee & Tea",
            "type":"Food & Drink"
        },
        {
            "category":"Bagels",
            "type":"Food & Drink"
        },
        {
            "category":"Donuts",
            "type":"Food & Drink"
        }
    ],
    "sg:menulink":"http://www.allmenus.com/ri/narragansett/138845-dunkin-donuts/menu/",
    "sg:phone":"+1 401 788 9430",
    "sg:postcode":"02882",
    "sg:province":"RI",
    "sg:tags":[
        "american",
        "pastry"
    ],
    "wof:name":"Dunkin' Donuts",
    "wof:placetype":"venue"
},
  "geometry": {"coordinates":[-71.43482299999999,41.474783],"type":"Point"}
}