{
  "type": "Feature",
  "properties": {
    "iso:country":"US",
    "sg:address":"10 Central St",
    "sg:city":"Warren",
    "sg:classifiers":[
        {
            "category":"Building & Trades",
            "subcategory":"Construction",
            "type":"Services"
        }
    ],
    "sg:phone":"+1 401 246 0452",
    "sg:postcode":"02885",
    "sg:province":"RI",
    "sg:tags":[
        "general",
        "contractor"
    ],
    "wof:name":"RIPICO Builders",
    "wof:placetype":"venue"
},
  "geometry": {"coordinates":[-71.272389,41.730547],"type":"Point"}
}