{
  "type": "Feature",
  "properties": {
    "iso:country":"US",
    "sg:address":"472 Waterman Ave",
    "sg:city":"East Providence",
    "sg:classifiers":[
        {
            "category":"Restaurant",
            "type":"Food & Drink"
        }
    ],
    "sg:phone":"+1 401 431 1943",
    "sg:postcode":"02914",
    "sg:province":"RI",
    "sg:tags":[
        "eating"
    ],
    "wof:name":"Tropical Ilhas Inc",
    "wof:placetype":"venue"
},
  "geometry": {"coordinates":[-71.36041,41.817623],"type":"Point"}
}