{
  "type": "Feature",
  "properties": {
    "iso:country":"US",
    "sg:address":"645 New London Ave",
    "sg:city":"Cranston",
    "sg:classifiers":[
        {
            "category":"Government",
            "subcategory":"Office",
            "type":"Public Place"
        }
    ],
    "sg:phone":"+1 401 457 4102",
    "sg:postcode":"02920",
    "sg:province":"RI",
    "sg:tags":[
        "government-united",
        "security",
        "national",
        "state"
    ],
    "sg:website":"http://www.newportartillery.org",
    "wof:name":"State National Guard Assn",
    "wof:placetype":"venue"
},
  "geometry": {"coordinates":[-71.468369,41.748044],"type":"Point"}
}