{
  "type": "Feature",
  "properties": {
    "addr:full":"871 Elmwood Ave Providence RI 02907",
    "addr:housenumber":"871",
    "addr:postcode":"02907",
    "addr:street":"Elmwood Ave",
    "iso:country":"US",
    "sg:address":"871 Elmwood Ave",
    "sg:city":"Providence",
    "sg:classifiers":[
        {
            "category":"Food & Beverages",
            "subcategory":"Groceries & Convenience Stores",
            "type":"Retail Goods"
        }
    ],
    "sg:phone":"+1 401 467 2822",
    "sg:postcode":"02907",
    "sg:province":"RI",
    "wof:name":"Savers Mart",
    "wof:placetype":"venue"
},
  "geometry": {"coordinates":[-71.42130400000001,41.789035],"type":"Point"}
}