{
  "type": "Feature",
  "properties": {
    "addr:full":"2 Stafford St Fiskeville RI 02886",
    "addr:housenumber":"2",
    "addr:postcode":"02886",
    "addr:street":"Stafford St",
    "iso:country":"US",
    "sg:address":"2 Stafford St",
    "sg:city":"Fiskeville",
    "sg:classifiers":[
        {
            "category":"Professional",
            "subcategory":"Engineering",
            "type":"Services"
        }
    ],
    "sg:phone":"+1 401 943 1000",
    "sg:postcode":"02886",
    "sg:province":"RI",
    "wof:name":"Diprete Engineering Associates",
    "wof:placetype":"venue"
},
  "geometry": {"coordinates":[-71.463989,41.729873],"type":"Point"}
}