{
  "type": "Feature",
  "properties": {
    "iso:country":"US",
    "sg:address":"815 Reservoir Ave",
    "sg:city":"Cranston",
    "sg:classifiers":[
        {
            "category":"Professional",
            "type":"Services"
        }
    ],
    "sg:phone":"+1 401 944 9188",
    "sg:postcode":"02910",
    "sg:province":"RI",
    "wof:name":"Arrow Credit Svc",
    "wof:placetype":"venue"
},
  "geometry": {"coordinates":[-71.44511300000001,41.778512],"type":"Point"}
}