{
  "type": "Feature",
  "properties": {
    "iso:country":"US",
    "sg:address":"194 Douglas Ave",
    "sg:city":"Providence",
    "sg:classifiers":[
        {
            "category":"Food & Beverages",
            "subcategory":"Groceries & Convenience Stores",
            "type":"Retail Goods"
        }
    ],
    "sg:phone":"+1 401 272 7362",
    "sg:postcode":"02908",
    "sg:province":"RI",
    "sg:tags":[
        "market"
    ],
    "wof:name":"Smith Hill Market",
    "wof:placetype":"venue"
},
  "geometry": {"coordinates":[-71.422096,41.8372],"type":"Point"}
}