{
  "type": "Feature",
  "properties": {
    "addr:full":"1800 Mendon Rd # 6 Cumberland RI 02864",
    "addr:housenumber":"1800",
    "addr:postcode":"02864",
    "addr:street":"Mendon Rd # 6",
    "iso:country":"US",
    "sg:address":"1800 Mendon Rd # 6",
    "sg:city":"Cumberland",
    "sg:classifiers":[
        {
            "category":"Restaurant",
            "type":"Food & Drink"
        }
    ],
    "sg:phone":"+1 401 333 9976",
    "sg:postcode":"02864",
    "sg:province":"RI",
    "sg:tags":[
        "chinese"
    ],
    "wof:name":"Fortune House",
    "wof:placetype":"venue"
},
  "geometry": {"coordinates":[-71.43762,41.945569],"type":"Point"}
}