{
  "type": "Feature",
  "properties": {
    "addr:full":"73 Bellingham St Woonsocket RI 02895",
    "addr:housenumber":"73",
    "addr:postcode":"02895",
    "addr:street":"Bellingham St",
    "iso:country":"US",
    "sg:address":"73 Bellingham St",
    "sg:city":"Woonsocket",
    "sg:classifiers":[
        {
            "category":"Building & Trades",
            "subcategory":"Construction",
            "type":"Services"
        }
    ],
    "sg:phone":"+1 401 769 4346",
    "sg:postcode":"02895",
    "sg:province":"RI",
    "sg:tags":[
        "contractor"
    ],
    "wof:name":"Paul Chamberland",
    "wof:placetype":"venue"
},
  "geometry": {"coordinates":[-71.49788100000001,42.016506],"type":"Point"}
}