{
  "type": "Feature",
  "properties": {
    "iso:country":"US",
    "sg:address":"35 Long Ln",
    "sg:city":"Warren",
    "sg:classifiers":[
        {
            "category":"Real Estate",
            "subcategory":"Real Estate Agent",
            "type":"Services"
        }
    ],
    "sg:phone":"+1 401 245 7310",
    "sg:postcode":"02885",
    "sg:province":"RI",
    "wof:name":"Massasoit Realty Inc",
    "wof:placetype":"venue"
},
  "geometry": {"coordinates":[-71.24792600000001,41.732838],"type":"Point"}
}