{
  "type": "Feature",
  "properties": {
    "iso:country":"US",
    "sg:address":"405 Tiogue Ave",
    "sg:city":"Coventry",
    "sg:classifiers":[
        {
            "category":"Building & Trades",
            "subcategory":"Construction",
            "type":"Services"
        }
    ],
    "sg:phone":"+1 401 828 5005",
    "sg:postcode":"02816",
    "sg:province":"RI",
    "sg:tags":[
        "house"
    ],
    "wof:name":"M Saccoccias Construction & L",
    "wof:placetype":"venue"
},
  "geometry": {"coordinates":[-71.545906,41.683993],"type":"Point"}
}