{
  "type": "Feature",
  "properties": {
    "iso:country":"US",
    "sg:address":"830 Chalkstone Ave",
    "sg:city":"Providence",
    "sg:classifiers":[
        {
            "category":"Health Services",
            "subcategory":"Hospital",
            "type":"Services"
        }
    ],
    "sg:phone":"+1 401 273 7100",
    "sg:postcode":"02908",
    "sg:province":"RI",
    "wof:name":"Veterans Affairs",
    "wof:placetype":"venue"
},
  "geometry": {"coordinates":[-71.434601,41.834099],"type":"Point"}
}