{
  "type": "Feature",
  "properties": {
    "addr:full":"244 Elena St Cranston RI 02920",
    "addr:housenumber":"244",
    "addr:postcode":"02920",
    "addr:street":"Elena St",
    "iso:country":"US",
    "sg:address":"244 Elena St",
    "sg:city":"Cranston",
    "sg:classifiers":[
        {
            "category":"Building & Trades",
            "subcategory":"Pest Control",
            "type":"Services"
        }
    ],
    "sg:phone":"+1 401 943 2606",
    "sg:postcode":"02920",
    "sg:province":"RI",
    "wof:name":"Horizon Pest Control",
    "wof:placetype":"venue"
},
  "geometry": {"coordinates":[-71.48287999999999,41.786911],"type":"Point"}
}