{
  "type": "Feature",
  "properties": {
    "iso:country":"US",
    "sg:address":"20 North Main Street",
    "sg:city":"Providence",
    "sg:classifiers":[
        {
            "category":"Arts & Performance",
            "subcategory":"Art Gallery",
            "type":"Entertainment"
        }
    ],
    "sg:phone":"+1 401 277 4949",
    "sg:postcode":"02903",
    "sg:province":"RI",
    "sg:website":"www.risdworks.com",
    "wof:name":"RISD Works",
    "wof:placetype":"venue"
},
  "geometry": {"coordinates":[-71.40830800000001,41.826285],"type":"Point"}
}