{
  "type": "Feature",
  "properties": {
    "iso:country":"US",
    "sg:address":"330 Freeman Pkwy",
    "sg:city":"Providence",
    "sg:classifiers":[
        {
            "category":"Professional",
            "subcategory":"Management & Consulting",
            "type":"Services"
        }
    ],
    "sg:phone":"+1 401 274 1188",
    "sg:postcode":"02906",
    "sg:province":"RI",
    "wof:name":"Freeman Group Ltd",
    "wof:placetype":"venue"
},
  "geometry": {"coordinates":[-71.38456600000001,41.839101],"type":"Point"}
}