{
  "type": "Feature",
  "properties": {
    "iso:country":"US",
    "sg:address":"440 Child St",
    "sg:city":"Warren",
    "sg:classifiers":[
        {
            "category":"Restaurant",
            "type":"Food & Drink"
        }
    ],
    "sg:phone":"+1 401 247 2930",
    "sg:postcode":"02885",
    "sg:province":"RI",
    "wof:name":"Hat Trick Restaurant",
    "wof:placetype":"venue"
},
  "geometry": {"coordinates":[-71.26643300000001,41.729222],"type":"Point"}
}