{
  "type": "Feature",
  "properties": {
    "addr:full":"2 Grandstand Dr Lincoln RI 02865",
    "addr:housenumber":"2",
    "addr:postcode":"02865",
    "addr:street":"Grandstand Dr",
    "iso:country":"US",
    "sg:address":"2 Grandstand Dr",
    "sg:city":"Lincoln",
    "sg:classifiers":[
        {
            "category":"Professional",
            "subcategory":"Lawyer & Legal Services",
            "type":"Services"
        }
    ],
    "sg:phone":"+1 401 723 3861",
    "sg:postcode":"02865",
    "sg:province":"RI",
    "wof:name":"Petrarca-Karampetsos Jina",
    "wof:placetype":"venue"
},
  "geometry": {"coordinates":[-71.445813,41.878788],"type":"Point"}
}