{
  "type": "Feature",
  "properties": {
    "addr:full":"31 Algonquin Dr Warwick RI 02888",
    "addr:housenumber":"31",
    "addr:postcode":"02888",
    "addr:street":"Algonquin Dr",
    "iso:country":"US",
    "sg:address":"31 Algonquin Dr",
    "sg:city":"Warwick",
    "sg:classifiers":[
        {
            "category":"Professional",
            "type":"Services"
        },
        {
            "category":"Professional",
            "subcategory":"Advertising",
            "type":"Services"
        }
    ],
    "sg:phone":"+1 401 463 9933",
    "sg:postcode":"02888",
    "sg:province":"RI",
    "sg:tags":[
        "agency",
        "establishment",
        "jewelry"
    ],
    "wof:name":"Barry Glucksman & Associates",
    "wof:placetype":"venue"
},
  "geometry": {"coordinates":[-71.396923,41.744433],"type":"Point"}
}