{
  "type": "Feature",
  "properties": {
    "iso:country":"US",
    "sg:address":"582 Metacom Ave",
    "sg:city":"Warren",
    "sg:classifiers":[
        {
            "category":"Shopping",
            "subcategory":"Florist",
            "type":"Retail Goods"
        }
    ],
    "sg:phone":"+1 401 245 6120",
    "sg:postcode":"02885",
    "sg:province":"RI",
    "wof:name":"Ferrazzano Flowers Inc",
    "wof:placetype":"venue"
},
  "geometry": {"coordinates":[-71.26911800000001,41.720976],"type":"Point"}
}