{
  "type": "Feature",
  "properties": {
    "iso:country":"US",
    "sg:address":"496 Main St",
    "sg:city":"Warren",
    "sg:classifiers":[
        {
            "category":"Shopping",
            "subcategory":"Pharmacy",
            "type":"Retail Goods"
        }
    ],
    "sg:phone":"+1 401 245 6767",
    "sg:postcode":"02885",
    "sg:province":"RI",
    "sg:tags":[
        "drug",
        "store"
    ],
    "wof:name":"Delekta Pharmacy Inc",
    "wof:placetype":"venue"
},
  "geometry": {"coordinates":[-71.28218200000001,41.7291],"type":"Point"}
}