{
  "type": "Feature",
  "properties": {
    "iso:country":"US",
    "sg:address":"218 S Ferry Rd",
    "sg:city":"Narragansett",
    "sg:classifiers":[
        {
            "category":"Professional",
            "subcategory":"Business Services",
            "type":"Services"
        }
    ],
    "sg:phone":"+1 401 874 6211",
    "sg:postcode":"02882",
    "sg:province":"RI",
    "sg:tags":[
        "information",
        "bureau",
        "convention"
    ],
    "wof:name":"University Of Ri Visitor Ctr",
    "wof:placetype":"venue"
},
  "geometry": {"coordinates":[-71.42966,41.492438],"type":"Point"}
}