{
  "type": "Feature",
  "properties": {
    "iso:country":"US",
    "sg:address":"196 Stanwood St",
    "sg:city":"Providence",
    "sg:classifiers":[
        {
            "category":"Retail",
            "subcategory":"Self-service Laundry",
            "type":"Services"
        }
    ],
    "sg:phone":"+1 401 785 8413",
    "sg:postcode":"02907",
    "sg:province":"RI",
    "sg:tags":[
        "coin"
    ],
    "wof:name":"Super Laundry Mat",
    "wof:placetype":"venue"
},
  "geometry": {"coordinates":[-71.426068,41.801955],"type":"Point"}
}