{
  "type": "Feature",
  "properties": {
    "iso:country":"US",
    "sg:address":"158 Garden St",
    "sg:city":"Pawtucket",
    "sg:classifiers":[
        {
            "category":"Professional",
            "type":"Services"
        }
    ],
    "sg:phone":"+1 401 722 0057",
    "sg:postcode":"02860",
    "sg:province":"RI",
    "sg:tags":[
        "establishment"
    ],
    "wof:name":"Invensys-Foxboro",
    "wof:placetype":"venue"
},
  "geometry": {"coordinates":[-71.390367,41.871192],"type":"Point"}
}