{
  "type": "Feature",
  "properties": {
    "iso:country":"US",
    "sg:address":"20 Biscuit Hill Rd",
    "sg:city":"Foster",
    "sg:classifiers":[
        {
            "category":"Professional",
            "subcategory":"Management & Consulting",
            "type":"Services"
        }
    ],
    "sg:phone":"+1 401 392 1388",
    "sg:postcode":"02825",
    "sg:province":"RI",
    "sg:tags":[
        "business"
    ],
    "wof:name":"Bisson & Bisson Inc",
    "wof:placetype":"venue"
},
  "geometry": {"coordinates":[-71.69869300000001,41.732883],"type":"Point"}
}