{
  "type": "Feature",
  "properties": {
    "addr:full":"1629 Warwick Ave Warwick RI 02889",
    "addr:housenumber":"1629",
    "addr:postcode":"02889",
    "addr:street":"Warwick Ave",
    "iso:country":"US",
    "sg:address":"1629 Warwick Ave",
    "sg:city":"Warwick",
    "sg:classifiers":[
        {
            "category":"Professional",
            "subcategory":"Accounting & Tax Preparation",
            "type":"Services"
        }
    ],
    "sg:phone":"+1 401 736 0040",
    "sg:postcode":"02889",
    "sg:province":"RI",
    "wof:name":"Kevin Carter CPA",
    "wof:placetype":"venue"
},
  "geometry": {"coordinates":[-71.40666899999999,41.732458],"type":"Point"}
}