{
  "type": "Feature",
  "properties": {
    "addr:full":"10 Macarthur Dr Smithfield RI 02917",
    "addr:housenumber":"10",
    "addr:postcode":"02917",
    "addr:street":"Macarthur Dr",
    "iso:country":"US",
    "sg:address":"10 Macarthur Dr",
    "sg:city":"Smithfield",
    "sg:classifiers":[
        {
            "category":"Building & Trades",
            "subcategory":"Construction",
            "type":"Services"
        }
    ],
    "sg:phone":"+1 401 334 9400",
    "sg:postcode":"02917",
    "sg:province":"RI",
    "sg:tags":[
        "painter"
    ],
    "wof:name":"Superior Painting & Wallcvrngs",
    "wof:placetype":"venue"
},
  "geometry": {"coordinates":[-71.542841,41.897873],"type":"Point"}
}