{
  "type": "Feature",
  "properties": {
    "iso:country":"US",
    "sg:address":"146 Winsor Ave",
    "sg:city":"Johnston",
    "sg:classifiers":[
        {
            "category":"Social Services",
            "subcategory":"Child Care",
            "type":"Services"
        }
    ],
    "sg:phone":"+1 401 732 2184",
    "sg:postcode":"02919",
    "sg:province":"RI",
    "sg:tags":[
        "day"
    ],
    "wof:name":"Ivy League Pre-School Inc",
    "wof:placetype":"venue"
},
  "geometry": {"coordinates":[-71.565145,41.853669],"type":"Point"}
}