{
  "type": "Feature",
  "properties": {
    "addr:full":"1670 Flat River Rd Coventry RI 02816",
    "addr:housenumber":"1670",
    "addr:postcode":"02816",
    "addr:street":"Flat River Rd",
    "iso:country":"US",
    "sg:address":"1670 Flat River Rd",
    "sg:city":"Coventry",
    "sg:classifiers":[
        {
            "category":"Government",
            "subcategory":"Office",
            "type":"Public Place"
        }
    ],
    "sg:phone":"+1 401 822 9150",
    "sg:postcode":"02816",
    "sg:province":"RI",
    "sg:tags":[
        "village"
    ],
    "wof:name":"Coventry Canvassers",
    "wof:placetype":"venue"
},
  "geometry": {"coordinates":[-71.585938,41.700629],"type":"Point"}
}