{
  "type": "Feature",
  "properties": {
    "iso:country":"US",
    "sg:address":"555 Hope St",
    "sg:city":"Bristol",
    "sg:phone":"+1 401 254 1911",
    "sg:postcode":"02809",
    "sg:province":"RI",
    "wof:name":"The Cake Gallery",
    "wof:placetype":"venue"
},
  "geometry": {"coordinates":[-71.27704199999999,41.671756],"type":"Point"}
}