{
  "type": "Feature",
  "properties": {
    "addr:full":"1601 Mineral Spring Ave North Providence RI 02904",
    "addr:housenumber":"1601",
    "addr:postcode":"02904",
    "addr:street":"Mineral Spring Ave",
    "iso:country":"US",
    "sg:address":"1601 Mineral Spring Ave",
    "sg:city":"North Providence",
    "sg:classifiers":[
        {
            "category":"Restaurant",
            "type":"Food & Drink"
        }
    ],
    "sg:phone":"+1 401 354 6868",
    "sg:postcode":"02904",
    "sg:province":"RI",
    "sg:tags":[
        "chinese"
    ],
    "sg:website":"www.kenwok.com",
    "wof:name":"Ken Wok",
    "wof:placetype":"venue"
},
  "geometry": {"coordinates":[-71.44888,41.864731],"type":"Point"}
}