{
  "type": "Feature",
  "properties": {
    "iso:country":"US",
    "sg:address":"200 Cannon St",
    "sg:city":"Cranston",
    "sg:classifiers":[
        {
            "category":"Recreation",
            "type":"Entertainment"
        }
    ],
    "sg:phone":"+1 401 946 5630",
    "sg:postcode":"02920",
    "sg:province":"RI",
    "sg:tags":[
        "amusement"
    ],
    "wof:name":"Gymboree",
    "wof:placetype":"venue"
},
  "geometry": {"coordinates":[-71.475357,41.789789],"type":"Point"}
}