{
  "type": "Feature",
  "properties": {
    "iso:country":"US",
    "sg:address":"343 Kingstown Rd",
    "sg:city":"West Kingston",
    "sg:classifiers":[
        {
            "category":"Shopping",
            "subcategory":"Bicycles & Sporting Goods",
            "type":"Retail Goods"
        }
    ],
    "sg:phone":"+1 401 539 6033",
    "sg:postcode":"02892",
    "sg:province":"RI",
    "wof:name":"Beaver River Golf Club",
    "wof:placetype":"venue"
},
  "geometry": {"coordinates":[-71.649873,41.501943],"type":"Point"}
}