{
  "type": "Feature",
  "properties": {
    "addr:full":"254 Market St Warren RI 02885",
    "addr:housenumber":"254",
    "addr:postcode":"02885",
    "addr:street":"Market St",
    "iso:country":"US",
    "sg:address":"254 Market St",
    "sg:city":"Warren",
    "sg:classifiers":[
        {
            "category":"Wholesale",
            "subcategory":"Non-durable Goods",
            "type":"Manufacturing & Wholesale Goods"
        }
    ],
    "sg:phone":"+1 401 245 3290",
    "sg:postcode":"02885",
    "sg:province":"RI",
    "sg:tags":[
        "ice"
    ],
    "wof:name":"Glacier Ice Co",
    "wof:placetype":"venue"
},
  "geometry": {"coordinates":[-71.273797,41.733564],"type":"Point"}
}