{
  "type": "Feature",
  "properties": {
    "iso:country":"US",
    "sg:address":"342 Manton Ave",
    "sg:city":"Providence",
    "sg:classifiers":[
        {
            "category":"Autos & Motor Vehicles",
            "subcategory":"Fuel & Gas Station",
            "type":"Retail Goods"
        }
    ],
    "sg:phone":"+1 401 351 5233",
    "sg:postcode":"02909",
    "sg:province":"RI",
    "sg:tags":[
        "station",
        "gasoline"
    ],
    "wof:name":"Jordan Services Inc",
    "wof:placetype":"venue"
},
  "geometry": {"coordinates":[-71.451444,41.823486],"type":"Point"}
}