{
  "type": "Feature",
  "properties": {
    "addr:full":"1070 Kingstown Rd Wakefield RI 02879",
    "addr:housenumber":"1070",
    "addr:postcode":"02879",
    "addr:street":"Kingstown Rd",
    "iso:country":"US",
    "sg:address":"1070 Kingstown Rd",
    "sg:city":"Wakefield",
    "sg:classifiers":[
        {
            "category":"Professional",
            "subcategory":"Lawyer & Legal Services",
            "type":"Services"
        }
    ],
    "sg:phone":"+1 401 789 5345",
    "sg:postcode":"02879",
    "sg:province":"RI",
    "sg:tags":[
        "attorney"
    ],
    "wof:name":"Leonard L Bergersen",
    "wof:placetype":"venue"
},
  "geometry": {"coordinates":[-71.498428,41.450998],"type":"Point"}
}