{
  "type": "Feature",
  "properties": {
    "iso:country":"US",
    "sg:address":"492 Dyer Ave",
    "sg:city":"Cranston",
    "sg:classifiers":[
        {
            "category":"Ice Cream",
            "type":"Food & Drink"
        }
    ],
    "sg:menulink":"http://www.allmenus.com/ri/cranston/224889-dels-frozen-lemonade/menu/",
    "sg:postcode":"02920",
    "sg:province":"RI",
    "sg:tags":[
        "smoothy",
        "juice",
        "american"
    ],
    "wof:name":"Del's Frozen Lemonade",
    "wof:placetype":"venue"
},
  "geometry": {"coordinates":[-71.458082,41.800237],"type":"Point"}
}