{
  "type": "Feature",
  "properties": {
    "iso:country":"US",
    "sg:address":"11 West St",
    "sg:city":"Bristol",
    "sg:classifiers":[
        {
            "category":"Building & Trades",
            "subcategory":"Construction",
            "type":"Services"
        }
    ],
    "sg:phone":"+1 401 253 3729",
    "sg:postcode":"02809",
    "sg:province":"RI",
    "sg:tags":[
        "general",
        "contractor"
    ],
    "wof:name":"East Bay General Contractors",
    "wof:placetype":"venue"
},
  "geometry": {"coordinates":[-71.263328,41.673616],"type":"Point"}
}