{
  "type": "Feature",
  "properties": {
    "iso:country":"US",
    "sg:address":"244 Pond St",
    "sg:city":"Wakefield",
    "sg:classifiers":[
        {
            "category":"Building & Trades",
            "subcategory":"Plumbing",
            "type":"Services"
        }
    ],
    "sg:phone":"+1 401 789 8684",
    "sg:postcode":"02879",
    "sg:province":"RI",
    "sg:tags":[
        "fish",
        "contractor"
    ],
    "wof:name":"Barry A Cherms",
    "wof:placetype":"venue"
},
  "geometry": {"coordinates":[-71.50418500000001,41.430441],"type":"Point"}
}