{
  "type": "Feature",
  "properties": {
    "iso:country":"US",
    "sg:address":"150 Colfax St",
    "sg:city":"Providence",
    "sg:classifiers":[
        {
            "category":"Retail",
            "subcategory":"Laundry & Dry Cleaning",
            "type":"Services"
        }
    ],
    "sg:phone":"+1 401 351 2822",
    "sg:postcode":"02905",
    "sg:province":"RI",
    "wof:name":"Legacy Cleaning Services Ltd",
    "wof:placetype":"venue"
},
  "geometry": {"coordinates":[-71.41534,41.798839],"type":"Point"}
}