{
  "type": "Feature",
  "properties": {
    "iso:country":"US",
    "sg:address":"2 Indian Rd",
    "sg:city":"Riverside",
    "sg:classifiers":[
        {
            "category":"Organizations",
            "subcategory":"Professional Association",
            "type":"Services"
        }
    ],
    "sg:phone":"+1 401 433 6985",
    "sg:postcode":"02915",
    "sg:province":"RI",
    "sg:tags":[
        "trade"
    ],
    "wof:name":"Rhode Islnd Chptr Apprs Instit",
    "wof:placetype":"venue"
},
  "geometry": {"coordinates":[-71.355586,41.779469],"type":"Point"}
}