{
  "type": "Feature",
  "properties": {
    "iso:country":"US",
    "sg:address":"6 W Warwick Ave",
    "sg:city":"West Warwick",
    "sg:classifiers":[
        {
            "category":"Food & Beverages",
            "subcategory":"Groceries & Convenience Stores",
            "type":"Retail Goods"
        }
    ],
    "sg:phone":"+1 401 821 8432",
    "sg:postcode":"02893",
    "sg:province":"RI",
    "sg:tags":[
        "grocer"
    ],
    "wof:name":"Wel-Mar Enterprises Inc",
    "wof:placetype":"venue"
},
  "geometry": {"coordinates":[-71.53113999999999,41.695523],"type":"Point"}
}