{
  "type": "Feature",
  "properties": {
    "iso:country":"US",
    "sg:address":"167 Main Rd",
    "sg:city":"Tiverton",
    "sg:classifiers":[
        {
            "category":"Insurance",
            "subcategory":"Insurance Agent",
            "type":"Services"
        }
    ],
    "sg:phone":"+1 401 624 8462",
    "sg:postcode":"02878",
    "sg:province":"RI",
    "wof:name":"Russ Towers Insurance Agency",
    "wof:placetype":"venue"
},
  "geometry": {"coordinates":[-71.186179,41.668369],"type":"Point"}
}