{
  "type": "Feature",
  "properties": {
    "iso:country":"US",
    "sg:address":"130 Taunton Ave",
    "sg:city":"East Providence",
    "sg:classifiers":[
        {
            "category":"Professional",
            "subcategory":"Art Services",
            "type":"Services"
        }
    ],
    "sg:phone":"+1 401 438 1916",
    "sg:postcode":"02914",
    "sg:province":"RI",
    "sg:tags":[
        "commercial",
        "design"
    ],
    "wof:name":"V Design",
    "wof:placetype":"venue"
},
  "geometry": {"coordinates":[-71.37695100000001,41.81977],"type":"Point"}
}