{
  "type": "Feature",
  "properties": {
    "iso:country":"US",
    "sg:address":"95 Riverside Dr",
    "sg:city":"Tiverton",
    "sg:classifiers":[
        {
            "category":"Recreation",
            "subcategory":"Marina",
            "type":"Entertainment"
        }
    ],
    "sg:phone":"+1 401 624 3621",
    "sg:postcode":"02878",
    "sg:province":"RI",
    "sg:tags":[
        "repairing",
        "boat"
    ],
    "wof:name":"Quality Yacht Svc",
    "wof:placetype":"venue"
},
  "geometry": {"coordinates":[-71.211467,41.635375],"type":"Point"}
}