{
  "type": "Feature",
  "properties": {
    "addr:full":"510 E Main Rd Unit 3 Middletown RI 02842",
    "addr:housenumber":"510;3",
    "addr:postcode":"02842",
    "addr:street":"E Main Rd Unit",
    "iso:country":"US",
    "sg:address":"510 E Main Rd Unit 3",
    "sg:city":"Middletown",
    "sg:phone":"+1 401 378 2363",
    "sg:postcode":"02842",
    "sg:province":"RI",
    "wof:name":"Grape Room",
    "wof:placetype":"venue"
},
  "geometry": {"coordinates":[-71.283703,41.521653],"type":"Point"}
}