{
  "type": "Feature",
  "properties": {
    "iso:country":"US",
    "sg:address":"131 Mettatuxet Rd",
    "sg:city":"Narragansett",
    "sg:classifiers":[
        {
            "category":"Building & Trades",
            "subcategory":"Construction",
            "type":"Services"
        }
    ],
    "sg:phone":"+1 401 783 0390",
    "sg:postcode":"02882",
    "sg:province":"RI",
    "sg:tags":[
        "house"
    ],
    "wof:name":"Rcr Building & Remodeling",
    "wof:placetype":"venue"
},
  "geometry": {"coordinates":[-71.44386299999999,41.475037],"type":"Point"}
}