{
  "type": "Feature",
  "properties": {
    "addr:full":"163 Main St Westerly RI 02891",
    "addr:housenumber":"163",
    "addr:postcode":"02891",
    "addr:street":"Main St",
    "iso:country":"US",
    "sg:address":"163 Main St",
    "sg:city":"Westerly",
    "sg:classifiers":[
        {
            "category":"Personal",
            "subcategory":"Beauty Salon",
            "type":"Services"
        }
    ],
    "sg:phone":"+1 401 348 2898",
    "sg:postcode":"02891",
    "sg:province":"RI",
    "wof:name":"Terrie's Beauty Shop",
    "wof:placetype":"venue"
},
  "geometry": {"coordinates":[-71.83091,41.371735],"type":"Point"}
}