{
  "type": "Feature",
  "properties": {
    "addr:full":"32 Campbell St Pawtucket RI 02861",
    "addr:housenumber":"32",
    "addr:postcode":"02861",
    "addr:street":"Campbell St",
    "iso:country":"US",
    "sg:address":"32 Campbell St",
    "sg:city":"Pawtucket",
    "sg:classifiers":[
        {
            "category":"Real Estate",
            "subcategory":"Real Estate Agent",
            "type":"Services"
        }
    ],
    "sg:phone":"+1 401 725 2547",
    "sg:postcode":"02861",
    "sg:province":"RI",
    "wof:name":"G&H Realty LLC",
    "wof:placetype":"venue"
},
  "geometry": {"coordinates":[-71.362827,41.864714],"type":"Point"}
}