{
  "type": "Feature",
  "properties": {
    "addr:full":"154 Providence Pl Providence RI 02903",
    "addr:housenumber":"154",
    "addr:postcode":"02903",
    "addr:street":"Providence Pl",
    "iso:country":"US",
    "sg:address":"154 Providence Pl",
    "sg:city":"Providence",
    "sg:classifiers":[
        {
            "category":"Bakery",
            "type":"Food & Drink"
        },
        {
            "category":"Coffee & Tea",
            "type":"Food & Drink"
        },
        {
            "category":"Bagels",
            "type":"Food & Drink"
        },
        {
            "category":"Donuts",
            "type":"Food & Drink"
        }
    ],
    "sg:menulink":"http://www.allmenus.com/ri/providence/138876-dunkin-donuts/menu/",
    "sg:phone":"+1 401 270 1243",
    "sg:postcode":"02903",
    "sg:province":"RI",
    "sg:tags":[
        "american",
        "pastry"
    ],
    "wof:name":"Dunkin' Donuts",
    "wof:placetype":"venue"
},
  "geometry": {"coordinates":[-71.42415,41.828908],"type":"Point"}
}