{
  "type": "Feature",
  "properties": {
    "iso:country":"US",
    "sg:address":"112 Old Pocasset Rd",
    "sg:city":"Johnston",
    "sg:classifiers":[
        {
            "category":"Shopping",
            "subcategory":"Catalog Store",
            "type":"Retail Goods"
        }
    ],
    "sg:phone":"+1 401 943 2222",
    "sg:postcode":"02919",
    "sg:province":"RI",
    "sg:tags":[
        "mail",
        "house"
    ],
    "wof:name":"A G Arms",
    "wof:placetype":"venue"
},
  "geometry": {"coordinates":[-71.514538,41.818927],"type":"Point"}
}