{
  "type": "Feature",
  "properties": {
    "iso:country":"US",
    "sg:address":"656 Twin Brook Ln",
    "sg:city":"Coventry",
    "sg:classifiers":[
        {
            "category":"Wholesale",
            "subcategory":"Groceries",
            "type":"Manufacturing & Wholesale Goods"
        }
    ],
    "sg:phone":"+1 401 397 5909",
    "sg:postcode":"02816",
    "sg:province":"RI",
    "sg:tags":[
        "confectionery"
    ],
    "wof:name":"Betamat Sales",
    "wof:placetype":"venue"
},
  "geometry": {"coordinates":[-71.656699,41.665872],"type":"Point"}
}