{
  "type": "Feature",
  "properties": {
    "iso:country":"US",
    "sg:address":"243 N Main St",
    "sg:city":"Providence",
    "sg:classifiers":[
        {
            "category":"Professional",
            "subcategory":"Lawyer & Legal Services",
            "type":"Services"
        }
    ],
    "sg:phone":"+1 401 453 4000",
    "sg:postcode":"02903",
    "sg:province":"RI",
    "sg:tags":[
        "attorney"
    ],
    "wof:name":"Mc Kiernan Thompson Mallea",
    "wof:placetype":"venue"
},
  "geometry": {"coordinates":[-71.41026100000001,41.830618],"type":"Point"}
}