{
  "type": "Feature",
  "properties": {
    "iso:country":"US",
    "sg:address":"181 Bellevue Ave",
    "sg:city":"Newport",
    "sg:classifiers":[
        {
            "category":"Restaurant",
            "type":"Food & Drink"
        },
        {
            "category":"Ice Cream",
            "type":"Food & Drink"
        }
    ],
    "sg:menulink":"http://www.allmenus.com/ri/newport/234110-newport-creamery/menu/",
    "sg:phone":"+1 401 846 6332",
    "sg:postcode":"02840",
    "sg:province":"RI",
    "sg:tags":[
        "american",
        "pizza",
        "ice",
        "cream"
    ],
    "wof:name":"Newport Creamery",
    "wof:placetype":"venue"
},
  "geometry": {"coordinates":[-71.308492,41.482801],"type":"Point"}
}