{
  "type": "Feature",
  "properties": {
    "addr:full":"235 Promenade St Rm 500 Providence RI 02908",
    "addr:housenumber":"235;500",
    "addr:postcode":"02908",
    "addr:street":"Promenade St Rm",
    "iso:country":"US",
    "sg:address":"235 Promenade St Rm 500",
    "sg:city":"Providence",
    "sg:classifiers":[
        {
            "category":"Health Services",
            "subcategory":"Optometrist",
            "type":"Services"
        }
    ],
    "sg:phone":"+1 401 331 1501",
    "sg:postcode":"02908",
    "sg:province":"RI",
    "sg:tags":[
        "ophthalmologist"
    ],
    "wof:name":"Ri Society of Eye Physicians & Surgeons",
    "wof:placetype":"venue"
},
  "geometry": {"coordinates":[-71.435799,41.835701],"type":"Point"}
}