{
  "type": "Feature",
  "properties": {
    "addr:full":"28 Graystone St Warwick RI 02886",
    "addr:housenumber":"28",
    "addr:postcode":"02886",
    "addr:street":"Graystone St",
    "iso:country":"US",
    "sg:address":"28 Graystone St",
    "sg:city":"Warwick",
    "sg:classifiers":[
        {
            "category":"Manufacturing",
            "subcategory":"Tools & Machinery",
            "type":"Manufacturing & Wholesale Goods"
        }
    ],
    "sg:phone":"+1 401 737 4646",
    "sg:postcode":"02886",
    "sg:province":"RI",
    "sg:tags":[
        "industrial",
        "ha",
        "mfg"
    ],
    "wof:name":"Droitcour Company",
    "wof:placetype":"venue"
},
  "geometry": {"coordinates":[-71.446996,41.728047],"type":"Point"}
}