{
  "type": "Feature",
  "properties": {
    "iso:country":"US",
    "sg:address":"104 Old Warwick Ave",
    "sg:city":"Warwick",
    "sg:classifiers":[
        {
            "category":"Shopping",
            "subcategory":"Music",
            "type":"Retail Goods"
        }
    ],
    "sg:phone":"+1 401 737 0622",
    "sg:postcode":"02889",
    "sg:province":"RI",
    "sg:tags":[
        "record",
        "tape"
    ],
    "wof:name":"Record Town",
    "wof:placetype":"venue"
},
  "geometry": {"coordinates":[-71.398178,41.712787],"type":"Point"}
}