{
  "type": "Feature",
  "properties": {
    "addr:full":"4820 Old Post Rd Charlestown RI 02813",
    "addr:housenumber":"4820",
    "addr:postcode":"02813",
    "addr:street":"Old Post Rd",
    "iso:country":"US",
    "sg:address":"4820 Old Post Rd",
    "sg:city":"Charlestown",
    "sg:classifiers":[
        {
            "category":"Shopping",
            "subcategory":"Gifts & Souvenirs",
            "type":"Retail Goods"
        }
    ],
    "sg:phone":"+1 401 364 6616",
    "sg:postcode":"02813",
    "sg:province":"RI",
    "sg:tags":[
        "shop"
    ],
    "wof:name":"Fantastic Umbrella Factory",
    "wof:placetype":"venue"
},
  "geometry": {"coordinates":[-71.66083399999999,41.378693],"type":"Point"}
}