{
  "type": "Feature",
  "properties": {
    "iso:country":"US",
    "sg:address":"682 Matunuck Beach Rd",
    "sg:city":"Wakefield",
    "sg:classifiers":[
        {
            "category":"Food & Beverages",
            "subcategory":"Groceries & Convenience Stores",
            "type":"Retail Goods"
        }
    ],
    "sg:phone":"+1 401 788 9000",
    "sg:postcode":"02879",
    "sg:province":"RI",
    "wof:name":"Seaview Marketplace",
    "wof:placetype":"venue"
},
  "geometry": {"coordinates":[-71.54940000000001,41.378101],"type":"Point"}
}