{
  "type": "Feature",
  "properties": {
    "iso:country":"US",
    "sg:address":"87 Estrell Dr",
    "sg:city":"Riverside",
    "sg:classifiers":[
        {
            "category":"Building & Trades",
            "subcategory":"Construction",
            "type":"Services"
        }
    ],
    "sg:phone":"+1 401 433 9022",
    "sg:postcode":"02915",
    "sg:province":"RI",
    "sg:tags":[
        "house"
    ],
    "wof:name":"Amb Home Remodeling LLC",
    "wof:placetype":"venue"
},
  "geometry": {"coordinates":[-71.330046,41.769243],"type":"Point"}
}