{
  "type": "Feature",
  "properties": {
    "iso:country":"US",
    "sg:address":"905 Church Ave",
    "sg:city":"Warwick",
    "sg:classifiers":[
        {
            "category":"Professional",
            "subcategory":"Business Services",
            "type":"Services"
        }
    ],
    "sg:phone":"+1 401 739 4578",
    "sg:postcode":"02889",
    "sg:province":"RI",
    "sg:tags":[
        "plant",
        "design",
        "maintenance"
    ],
    "wof:name":"Tropical Interiors",
    "wof:placetype":"venue"
},
  "geometry": {"coordinates":[-71.409019,41.717618],"type":"Point"}
}