{
  "type": "Feature",
  "properties": {
    "iso:country":"US",
    "sg:address":"71 Messina St",
    "sg:city":"Providence",
    "sg:classifiers":[
        {
            "category":"Building & Trades",
            "subcategory":"Construction",
            "type":"Services"
        }
    ],
    "sg:phone":"+1 401 421 9863",
    "sg:postcode":"02908",
    "sg:province":"RI",
    "sg:tags":[
        "contractor"
    ],
    "wof:name":"Carl Halton Drywall & Plst",
    "wof:placetype":"venue"
},
  "geometry": {"coordinates":[-71.43038900000001,41.848533],"type":"Point"}
}