{
  "type": "Feature",
  "properties": {
    "iso:country":"US",
    "sg:address":"409 N Main St",
    "sg:city":"Woonsocket",
    "sg:classifiers":[
        {
            "category":"Wholesale",
            "subcategory":"Construction Materials",
            "type":"Manufacturing & Wholesale Goods"
        },
        {
            "category":"Building & Trades",
            "subcategory":"Construction",
            "type":"Services"
        }
    ],
    "sg:phone":"+1 401 769 8821",
    "sg:postcode":"02895",
    "sg:province":"RI",
    "sg:tags":[
        "fence",
        "contractor"
    ],
    "wof:name":"USA Fence",
    "wof:placetype":"venue"
},
  "geometry": {"coordinates":[-71.51410300000001,42.011598],"type":"Point"}
}