{
  "type": "Feature",
  "properties": {
    "iso:country":"US",
    "sg:address":"1221 Atwood Ave",
    "sg:city":"Johnston",
    "sg:classifiers":[
        {
            "category":"Shopping",
            "subcategory":"Clothing, Apparel, & Fashions",
            "type":"Retail Goods"
        }
    ],
    "sg:phone":"+1 401 946 2033",
    "sg:postcode":"02919",
    "sg:province":"RI",
    "sg:tags":[
        "tailor"
    ],
    "wof:name":"Lucy's Tailor Shop",
    "wof:placetype":"venue"
},
  "geometry": {"coordinates":[-71.491911,41.806578],"type":"Point"}
}