{
  "type": "Feature",
  "properties": {
    "addr:full":"263 Dexter St Pawtucket RI 02860",
    "addr:housenumber":"263",
    "addr:postcode":"02860",
    "addr:street":"Dexter St",
    "iso:country":"US",
    "sg:address":"263 Dexter St",
    "sg:city":"Pawtucket",
    "sg:classifiers":[
        {
            "category":"Autos & Motor Vehicles",
            "subcategory":"Automobile Sales",
            "type":"Retail Goods"
        }
    ],
    "sg:phone":"+1 401 728 6790",
    "sg:postcode":"02860",
    "sg:province":"RI",
    "sg:tags":[
        "car"
    ],
    "wof:name":"Classic Auto Sales",
    "wof:placetype":"venue"
},
  "geometry": {"coordinates":[-71.391701,41.881901],"type":"Point"}
}