{
  "type": "Feature",
  "properties": {
    "iso:country":"US",
    "sg:address":"155 Schoolhouse Ln",
    "sg:city":"Portsmouth",
    "sg:classifiers":[
        {
            "category":"Building & Trades",
            "subcategory":"Construction",
            "type":"Services"
        }
    ],
    "sg:phone":"+1 401 683 1116",
    "sg:postcode":"02871",
    "sg:province":"RI",
    "sg:tags":[
        "general",
        "contractor"
    ],
    "wof:name":"Brennan Construction Septic",
    "wof:placetype":"venue"
},
  "geometry": {"coordinates":[-71.257515,41.573178],"type":"Point"}
}