{
  "type": "Feature",
  "properties": {
    "addr:full":"158 S Bend St Ste 156 Pawtucket RI 02860",
    "addr:housenumber":"158",
    "addr:postcode":"02860",
    "addr:street":"S Bend St Ste 156",
    "iso:country":"US",
    "sg:address":"158 S Bend St Ste 156",
    "sg:city":"Pawtucket",
    "sg:classifiers":[
        {
            "category":"Bars & Pubs",
            "type":"Food & Drink"
        },
        {
            "category":"Restaurant",
            "type":"Food & Drink"
        }
    ],
    "sg:phone":"+1 401 722 1210",
    "sg:postcode":"02860",
    "sg:province":"RI",
    "sg:tags":[
        "grill",
        "brew"
    ],
    "wof:name":"Galway Bay Pub",
    "wof:placetype":"venue"
},
  "geometry": {"coordinates":[-71.372108,41.873798],"type":"Point"}
}