{
  "type": "Feature",
  "properties": {
    "iso:country":"US",
    "sg:address":"250 Reservoir Ave",
    "sg:city":"Providence",
    "sg:classifiers":[
        {
            "category":"Personal",
            "subcategory":"Beauty Salon",
            "type":"Services"
        }
    ],
    "sg:phone":"+1 401 781 8749",
    "sg:postcode":"02907",
    "sg:province":"RI",
    "sg:tags":[
        "shop"
    ],
    "wof:name":"Al's Hair Salon",
    "wof:placetype":"venue"
},
  "geometry": {"coordinates":[-71.42906000000001,41.790147],"type":"Point"}
}