{
  "type": "Feature",
  "properties": {
    "iso:country":"US",
    "sg:address":"70 Macondray St",
    "sg:city":"Cumberland",
    "sg:classifiers":[
        {
            "category":"Autos & Motor Vehicles",
            "subcategory":"Automobile Sales",
            "type":"Retail Goods"
        },
        {
            "category":"Autos & Motor Vehicles",
            "subcategory":"Auto Supplies",
            "type":"Retail Goods"
        }
    ],
    "sg:phone":"+1 401 725 1225",
    "sg:postcode":"02864",
    "sg:province":"RI",
    "sg:tags":[
        "salvage",
        "rebuilt",
        "part",
        "supplies-used"
    ],
    "sg:website":"http://www.billsautoparts.com",
    "wof:name":"Bills Auto Parts Inc",
    "wof:placetype":"venue"
},
  "geometry": {"coordinates":[-71.39450100000001,41.904369],"type":"Point"}
}