{
  "type": "Feature",
  "properties": {
    "iso:country":"US",
    "sg:address":"2822 Victory Hwy",
    "sg:city":"Harrisville",
    "sg:classifiers":[
        {
            "category":"Retail",
            "subcategory":"Auto Repair",
            "type":"Services"
        }
    ],
    "sg:phone":"+1 401 769 7741",
    "sg:postcode":"02830",
    "sg:province":"RI",
    "sg:tags":[
        "repairing",
        "automobile"
    ],
    "wof:name":"Jasons Trucking",
    "wof:placetype":"venue"
},
  "geometry": {"coordinates":[-71.606435,41.981802],"type":"Point"}
}