{
  "type": "Feature",
  "properties": {
    "addr:full":"860 Waterman Ave East Providence RI 02914",
    "addr:housenumber":"860",
    "addr:postcode":"02914",
    "addr:street":"Waterman Ave",
    "iso:country":"US",
    "sg:address":"860 Waterman Ave",
    "sg:city":"East Providence",
    "sg:classifiers":[
        {
            "category":"Manufacturing",
            "subcategory":"Tools & Machinery",
            "type":"Manufacturing & Wholesale Goods"
        }
    ],
    "sg:phone":"+1 401 434 0617",
    "sg:postcode":"02914",
    "sg:province":"RI",
    "sg:tags":[
        "equipment",
        "system",
        "automation"
    ],
    "wof:name":"Star Automation",
    "wof:placetype":"venue"
},
  "geometry": {"coordinates":[-71.349915,41.812569],"type":"Point"}
}