{
  "type": "Feature",
  "properties": {
    "iso:country":"US",
    "sg:address":"1 Rhodes Pl",
    "sg:city":"Cranston",
    "sg:classifiers":[
        {
            "category":"Education",
            "subcategory":"Special Training",
            "type":"Public Place"
        },
        {
            "category":"Social Services",
            "subcategory":"Child Care",
            "type":"Services"
        }
    ],
    "sg:phone":"+1 401 781 7953",
    "sg:postcode":"02905",
    "sg:province":"RI",
    "sg:tags":[
        "nursery",
        "tutoring",
        "day"
    ],
    "wof:name":"32nd Degree Masonic Learning C",
    "wof:placetype":"venue"
},
  "geometry": {"coordinates":[-71.39193,41.768009],"type":"Point"}
}