{
  "type": "Feature",
  "properties": {
    "iso:country":"US",
    "sg:address":"255 Main St",
    "sg:city":"Pawtucket",
    "sg:classifiers":[
        {
            "category":"Organizations",
            "subcategory":"Non-profit Organization",
            "type":"Services"
        }
    ],
    "sg:phone":"+1 401 721 0723",
    "sg:postcode":"02860",
    "sg:province":"RI",
    "wof:name":"Pawtucket Armory Assn",
    "wof:placetype":"venue"
},
  "geometry": {"coordinates":[-71.38454400000001,41.877267],"type":"Point"}
}