{
  "type": "Feature",
  "properties": {
    "addr:full":"420 Brook Rd Harrisville RI 02830",
    "addr:housenumber":"420",
    "addr:postcode":"02830",
    "addr:street":"Brook Rd",
    "iso:country":"US",
    "sg:address":"420 Brook Rd",
    "sg:city":"Harrisville",
    "sg:classifiers":[
        {
            "category":"Professional",
            "subcategory":"Accounting & Tax Preparation",
            "type":"Services"
        }
    ],
    "sg:phone":"+1 401 567 0160",
    "sg:postcode":"02830",
    "sg:province":"RI",
    "sg:tags":[
        "billing"
    ],
    "wof:name":"Liberty Medical Management Inc",
    "wof:placetype":"venue"
},
  "geometry": {"coordinates":[-71.69014799999999,42.003306],"type":"Point"}
}