{
  "type": "Feature",
  "properties": {
    "addr:full":"106 High St Cumberland RI 02864",
    "addr:housenumber":"106",
    "addr:postcode":"02864",
    "addr:street":"High St",
    "iso:country":"US",
    "sg:address":"106 High St",
    "sg:city":"Cumberland",
    "sg:classifiers":[
        {
            "category":"Building & Trades",
            "subcategory":"Cleaning & Sanitation",
            "type":"Services"
        }
    ],
    "sg:phone":"+1 401 724 4300",
    "sg:postcode":"02864",
    "sg:province":"RI",
    "sg:tags":[
        "janitor"
    ],
    "sg:website":"www.janitechcorp.com",
    "wof:name":"Janitech Industrial Cleaning",
    "wof:placetype":"venue"
},
  "geometry": {"coordinates":[-71.389679,41.903563],"type":"Point"}
}