{
  "type": "Feature",
  "properties": {
    "iso:country":"US",
    "sg:address":"80 Manton Ave",
    "sg:city":"Providence",
    "sg:classifiers":[
        {
            "category":"Shopping",
            "subcategory":"Used Merchandise",
            "type":"Retail Goods"
        }
    ],
    "sg:phone":"+1 401 621 7754",
    "sg:postcode":"02909",
    "sg:province":"RI",
    "sg:tags":[
        "shop",
        "thrift"
    ],
    "wof:name":"Goodwill Industries",
    "wof:placetype":"venue"
},
  "geometry": {"coordinates":[-71.445004,41.81802],"type":"Point"}
}