{
  "type": "Feature",
  "properties": {
    "iso:country":"US",
    "sg:address":"50 Park Ln",
    "sg:city":"Providence",
    "sg:classifiers":[
        {
            "category":"Government",
            "subcategory":"Office",
            "type":"Public Place"
        }
    ],
    "sg:phone":"+1 401 222 3636",
    "sg:postcode":"02907",
    "sg:province":"RI",
    "sg:tags":[
        "telecommunication",
        "authority"
    ],
    "wof:name":"Public Broadcasting Station RI",
    "wof:placetype":"venue"
},
  "geometry": {"coordinates":[-71.436173,41.79469],"type":"Point"}
}