{
  "type": "Feature",
  "properties": {
    "iso:country":"US",
    "sg:address":"1119 Park Ave",
    "sg:city":"Cranston",
    "sg:classifiers":[
        {
            "category":"Retail",
            "subcategory":"Veterinary Services",
            "type":"Services"
        }
    ],
    "sg:phone":"+1 401 943 0770",
    "sg:postcode":"02910",
    "sg:province":"RI",
    "sg:tags":[
        "veterinarian"
    ],
    "wof:name":"Henry E Childers DVM",
    "wof:placetype":"venue"
},
  "geometry": {"coordinates":[-71.44792700000001,41.783072],"type":"Point"}
}