{
  "type": "Feature",
  "properties": {
    "iso:country":"US",
    "sg:address":"92 Modena Ave",
    "sg:city":"Providence",
    "sg:classifiers":[
        {
            "category":"Real Estate",
            "subcategory":"Real Estate Agent",
            "type":"Services"
        }
    ],
    "sg:phone":"+1 401 831 1229",
    "sg:postcode":"02908",
    "sg:province":"RI",
    "wof:name":"Thoan Realty Inc",
    "wof:placetype":"venue"
},
  "geometry": {"coordinates":[-71.449139,41.848624],"type":"Point"}
}