{
  "type": "Feature",
  "properties": {
    "addr:full":"151 Broadway Providence RI 02903",
    "addr:housenumber":"151",
    "addr:postcode":"02903",
    "addr:street":"Broadway",
    "iso:country":"US",
    "sg:address":"151 Broadway",
    "sg:city":"Providence",
    "sg:classifiers":[
        {
            "category":"Professional",
            "subcategory":"Lawyer & Legal Services",
            "type":"Services"
        }
    ],
    "sg:phone":"+1 401 454 0050",
    "sg:postcode":"02903",
    "sg:province":"RI",
    "wof:name":"Jabour Clare T Atty",
    "wof:placetype":"venue"
},
  "geometry": {"coordinates":[-71.422302,41.821499],"type":"Point"}
}