{
  "type": "Feature",
  "properties": {
    "iso:country":"US",
    "sg:address":"387 George Waterman Rd",
    "sg:city":"Johnston",
    "sg:classifiers":[
        {
            "category":"Manufacturing",
            "subcategory":"Jewelry",
            "type":"Manufacturing & Wholesale Goods"
        }
    ],
    "sg:phone":"+1 401 233 9200",
    "sg:postcode":"02919",
    "sg:province":"RI",
    "sg:tags":[
        "precious",
        "metal",
        "mfg"
    ],
    "wof:name":"Roger Michael Ltd",
    "wof:placetype":"venue"
},
  "geometry": {"coordinates":[-71.48748399999999,41.852851],"type":"Point"}
}