{
  "type": "Feature",
  "properties": {
    "iso:country":"US",
    "sg:address":"665 Main St",
    "sg:city":"East Greenwich",
    "sg:classifiers":[
        {
            "category":"Professional",
            "type":"Services"
        }
    ],
    "sg:phone":"+1 401 884 3381",
    "sg:postcode":"02818",
    "sg:province":"RI",
    "sg:tags":[
        "establishment"
    ],
    "wof:name":"Davelen Inc",
    "wof:placetype":"venue"
},
  "geometry": {"coordinates":[-71.453604,41.655951],"type":"Point"}
}