{
  "type": "Feature",
  "properties": {
    "iso:country":"US",
    "sg:address":"2 Ferry St",
    "sg:city":"Jamestown",
    "sg:classifiers":[
        {
            "category":"Manufacturing",
            "subcategory":"Printing",
            "type":"Manufacturing & Wholesale Goods"
        }
    ],
    "sg:phone":"+1 401 423 0205",
    "sg:postcode":"02835",
    "sg:province":"RI",
    "sg:tags":[
        "newspaper"
    ],
    "wof:name":"Jamestown Journal",
    "wof:placetype":"venue"
},
  "geometry": {"coordinates":[-71.383079,41.530788],"type":"Point"}
}