{
  "type": "Feature",
  "properties": {
    "addr:full":"177 Custer St Warwick RI 02889",
    "addr:housenumber":"177",
    "addr:postcode":"02889",
    "addr:street":"Custer St",
    "iso:country":"US",
    "sg:address":"177 Custer St",
    "sg:city":"Warwick",
    "sg:classifiers":[
        {
            "category":"Building & Trades",
            "subcategory":"Landscaping Services",
            "type":"Services"
        }
    ],
    "sg:phone":"+1 401 738 6637",
    "sg:postcode":"02889",
    "sg:province":"RI",
    "sg:tags":[
        "landscape",
        "contractor"
    ],
    "wof:name":"Highline Tree Svc",
    "wof:placetype":"venue"
},
  "geometry": {"coordinates":[-71.410804,41.699476],"type":"Point"}
}