{
  "type": "Feature",
  "properties": {
    "iso:country":"US",
    "sg:address":"575 Wickenden St",
    "sg:city":"Providence",
    "sg:classifiers":[
        {
            "category":"Professional",
            "subcategory":"Management & Consulting",
            "type":"Services"
        }
    ],
    "sg:phone":"+1 401 521 6626",
    "sg:postcode":"02903",
    "sg:province":"RI",
    "sg:tags":[
        "business"
    ],
    "wof:name":"Cycloid-Vision",
    "wof:placetype":"venue"
},
  "geometry": {"coordinates":[-71.391392,41.820227],"type":"Point"}
}