{
  "type": "Feature",
  "properties": {
    "iso:country":"US",
    "sg:address":"235 Plain St",
    "sg:city":"Providence",
    "sg:classifiers":[
        {
            "category":"Health Services",
            "subcategory":"Doctor",
            "type":"Services"
        }
    ],
    "sg:phone":"+1 401 272 1990",
    "sg:postcode":"02905",
    "sg:province":"RI",
    "sg:tags":[
        "gynecologist"
    ],
    "wof:name":"Joseph Demartino MD Ltd",
    "wof:placetype":"venue"
},
  "geometry": {"coordinates":[-71.410892,41.809188],"type":"Point"}
}