{
  "type": "Feature",
  "properties": {
    "iso:country":"US",
    "sg:address":"8 Broad St",
    "sg:city":"Westerly",
    "sg:classifiers":[
        {
            "category":"Shopping",
            "subcategory":"Used Merchandise",
            "type":"Retail Goods"
        }
    ],
    "sg:phone":"+1 401 596 0266",
    "sg:postcode":"02891",
    "sg:province":"RI",
    "wof:name":"Riverside Antiques",
    "wof:placetype":"venue"
},
  "geometry": {"coordinates":[-71.830978,41.377655],"type":"Point"}
}