{
  "type": "Feature",
  "properties": {
    "iso:country":"US",
    "sg:address":"219 Summer St",
    "sg:city":"Woonsocket",
    "sg:classifiers":[
        {
            "category":"Education",
            "subcategory":"School",
            "type":"Public Place"
        }
    ],
    "sg:phone":"+1 401 767 4636",
    "sg:postcode":"02895",
    "sg:province":"RI",
    "wof:name":"Summer Street School",
    "wof:placetype":"venue"
},
  "geometry": {"coordinates":[-71.51749700000001,42.012421],"type":"Point"}
}