{
  "type": "Feature",
  "properties": {
    "addr:full":"399 Jefferson Blvd Warwick RI 02886",
    "addr:housenumber":"399",
    "addr:postcode":"02886",
    "addr:street":"Jefferson Blvd",
    "iso:country":"US",
    "sg:address":"399 Jefferson Blvd",
    "sg:city":"Warwick",
    "sg:classifiers":[
        {
            "category":"Banks & Credit Unions",
            "subcategory":"Bank",
            "type":"Services"
        }
    ],
    "sg:phone":"+1 401 732 2555",
    "sg:postcode":"02886",
    "sg:province":"RI",
    "sg:tags":[
        "mortgage"
    ],
    "wof:name":"Primary Mortgage Corporation",
    "wof:placetype":"venue"
},
  "geometry": {"coordinates":[-71.441868,41.732174],"type":"Point"}
}