{
  "type": "Feature",
  "properties": {
    "addr:full":"106 Airport Access Rd Middletown RI 02842",
    "addr:housenumber":"106",
    "addr:postcode":"02842",
    "addr:street":"Airport Access Rd",
    "iso:country":"US",
    "sg:address":"106 Airport Access Rd",
    "sg:city":"Middletown",
    "sg:classifiers":[
        {
            "category":"Government",
            "subcategory":"Office",
            "type":"Public Place"
        }
    ],
    "sg:phone":"+1 401 275 4710",
    "sg:postcode":"02842",
    "sg:province":"RI",
    "sg:tags":[
        "federal",
        "security"
    ],
    "wof:name":"US Army National Guard",
    "wof:placetype":"venue"
},
  "geometry": {"coordinates":[-71.28483199999999,41.528143],"type":"Point"}
}