{
  "type": "Feature",
  "properties": {
    "addr:full":"200 Gooding Ave Bristol RI 02809",
    "addr:housenumber":"200",
    "addr:postcode":"02809",
    "addr:street":"Gooding Ave",
    "iso:country":"US",
    "sg:address":"200 Gooding Ave",
    "sg:city":"Bristol",
    "sg:classifiers":[
        {
            "category":"Restaurant",
            "type":"Food & Drink"
        }
    ],
    "sg:phone":"+1 401 254 2188",
    "sg:postcode":"02809",
    "sg:province":"RI",
    "sg:tags":[
        "eating"
    ],
    "wof:name":"Archie's Seafood Restaurant",
    "wof:placetype":"venue"
},
  "geometry": {"coordinates":[-71.26365699999999,41.694296],"type":"Point"}
}