{
  "type": "Feature",
  "properties": {
    "addr:full":"719 Pontiac Ave Cranston RI 02910",
    "addr:housenumber":"719",
    "addr:postcode":"02910",
    "addr:street":"Pontiac Ave",
    "iso:country":"US",
    "sg:address":"719 Pontiac Ave",
    "sg:city":"Cranston",
    "sg:classifiers":[
        {
            "category":"Shopping",
            "type":"Retail Goods"
        }
    ],
    "sg:phone":"+1 401 467 6840",
    "sg:postcode":"02910",
    "sg:province":"RI",
    "sg:tags":[
        "chemical",
        "equipment",
        "pool",
        "swimming"
    ],
    "wof:name":"K J Pool & Spa",
    "wof:placetype":"venue"
},
  "geometry": {"coordinates":[-71.440744,41.76623],"type":"Point"}
}