{
  "type": "Feature",
  "properties": {
    "addr:full":"1 Dorrance St Providence RI 02903",
    "addr:housenumber":"1",
    "addr:postcode":"02903",
    "addr:street":"Dorrance St",
    "iso:country":"US",
    "sg:address":"1 Dorrance St",
    "sg:city":"Providence",
    "sg:classifiers":[
        {
            "category":"Government",
            "subcategory":"Jail",
            "type":"Public Place"
        }
    ],
    "sg:phone":"+1 401 458 3020",
    "sg:postcode":"02903",
    "sg:province":"RI",
    "sg:tags":[
        "govt",
        "state",
        "institution"
    ],
    "wof:name":"Corrections Dept",
    "wof:placetype":"venue"
},
  "geometry": {"coordinates":[-71.41276499999999,41.824448],"type":"Point"}
}