{
  "type": "Feature",
  "properties": {
    "iso:country":"US",
    "sg:address":"880 W Main Rd",
    "sg:city":"Middletown",
    "sg:classifiers":[
        {
            "category":"Shopping",
            "subcategory":"Discount & Variety Stores",
            "type":"Retail Goods"
        }
    ],
    "sg:phone":"+1 401 846 2030",
    "sg:postcode":"02842",
    "sg:province":"RI",
    "sg:website":"www.dollartree.com",
    "wof:name":"Dollar Tree",
    "wof:placetype":"venue"
},
  "geometry": {"coordinates":[-71.29631999999999,41.527684],"type":"Point"}
}