{
  "type": "Feature",
  "properties": {
    "iso:country":"US",
    "sg:address":"Main St",
    "sg:city":"Hope Valley",
    "sg:classifiers":[
        {
            "category":"Retail",
            "subcategory":"Funeral Services",
            "type":"Services"
        }
    ],
    "sg:phone":"+1 401 596 2465",
    "sg:postcode":"02832",
    "sg:province":"RI",
    "sg:tags":[
        "cemetery"
    ],
    "wof:name":"S R Avery Funeral Home",
    "wof:placetype":"venue"
},
  "geometry": {"coordinates":[-71.739304,41.5061],"type":"Point"}
}