{
  "type": "Feature",
  "properties": {
    "iso:country":"US",
    "sg:address":"151 Allston Ave",
    "sg:city":"Middletown",
    "sg:classifiers":[
        {
            "category":"Real Estate",
            "subcategory":"Surveying",
            "type":"Services"
        }
    ],
    "sg:phone":"+1 401 846 5659",
    "sg:postcode":"02842",
    "sg:province":"RI",
    "sg:tags":[
        "surveyor"
    ],
    "wof:name":"M J Gaston & Assoc",
    "wof:placetype":"venue"
},
  "geometry": {"coordinates":[-71.279381,41.49032],"type":"Point"}
}