{
  "type": "Feature",
  "properties": {
    "addr:full":"4 Lyndon St Warren RI 02885",
    "addr:housenumber":"4",
    "addr:postcode":"02885",
    "addr:street":"Lyndon St",
    "iso:country":"US",
    "sg:address":"4 Lyndon St",
    "sg:city":"Warren",
    "sg:classifiers":[
        {
            "category":"Professional",
            "subcategory":"Business Services",
            "type":"Services"
        }
    ],
    "sg:phone":"+1 401 245 4223",
    "sg:postcode":"02885",
    "sg:province":"RI",
    "sg:tags":[
        "interpreter",
        "for",
        "language",
        "sign"
    ],
    "wof:name":"Peter A Cappuccilli",
    "wof:placetype":"venue"
},
  "geometry": {"coordinates":[-71.28346500000001,41.727985],"type":"Point"}
}