{
  "type": "Feature",
  "properties": {
    "addr:full":"22 Bullock Ave Barrington RI 02806",
    "addr:housenumber":"22",
    "addr:postcode":"02806",
    "addr:street":"Bullock Ave",
    "iso:country":"US",
    "sg:address":"22 Bullock Ave",
    "sg:city":"Barrington",
    "sg:classifiers":[
        {
            "category":"Professional",
            "subcategory":"Business Services",
            "type":"Services"
        }
    ],
    "sg:phone":"+1 401 245 8193",
    "sg:postcode":"02806",
    "sg:province":"RI",
    "wof:name":"King Oak Assoc Inc",
    "wof:placetype":"venue"
},
  "geometry": {"coordinates":[-71.29234,41.756622],"type":"Point"}
}