{
  "type": "Feature",
  "properties": {
    "iso:country":"US",
    "sg:address":"5 Ambrose St",
    "sg:city":"Providence",
    "sg:classifiers":[
        {
            "category":"Health Services",
            "subcategory":"Doctor",
            "type":"Services"
        }
    ],
    "sg:phone":"+1 401 728 5407",
    "sg:postcode":"02904",
    "sg:province":"RI",
    "sg:tags":[
        "medical"
    ],
    "wof:name":"Dr Paul A Caccia",
    "wof:placetype":"venue"
},
  "geometry": {"coordinates":[-71.428135,41.874512],"type":"Point"}
}