{
  "type": "Feature",
  "properties": {
    "addr:full":"100 Brook Farm Rd N Wakefield RI 02879",
    "addr:housenumber":"100",
    "addr:postcode":"02879",
    "addr:street":"Brook Farm Rd N",
    "iso:country":"US",
    "sg:address":"100 Brook Farm Rd N",
    "sg:city":"Wakefield",
    "sg:classifiers":[
        {
            "category":"Manufacturing",
            "subcategory":"Wood Products",
            "type":"Manufacturing & Wholesale Goods"
        }
    ],
    "sg:phone":"+1 401 789 8825",
    "sg:postcode":"02879",
    "sg:province":"RI",
    "sg:tags":[
        "preserving"
    ],
    "wof:name":"Thayer Wood Products Inc",
    "wof:placetype":"venue"
},
  "geometry": {"coordinates":[-71.552177,41.437823],"type":"Point"}
}