{
  "type": "Feature",
  "properties": {
    "addr:full":"269 Summit Dr Cranston RI 02920",
    "addr:housenumber":"269",
    "addr:postcode":"02920",
    "addr:street":"Summit Dr",
    "iso:country":"US",
    "sg:address":"269 Summit Dr",
    "sg:city":"Cranston",
    "sg:classifiers":[
        {
            "category":"Building & Trades",
            "subcategory":"Landscaping Services",
            "type":"Services"
        }
    ],
    "sg:phone":"+1 401 737 6663",
    "sg:postcode":"02920",
    "sg:province":"RI",
    "wof:name":"Contemporary Landscaping Inc",
    "wof:placetype":"venue"
},
  "geometry": {"coordinates":[-71.471384,41.757252],"type":"Point"}
}