{
  "type": "Feature",
  "properties": {
    "iso:country":"US",
    "sg:address":"61 Primrose Hill Rd",
    "sg:city":"Barrington",
    "sg:classifiers":[
        {
            "category":"Shopping",
            "subcategory":"Clothing, Apparel, & Fashions",
            "type":"Retail Goods"
        }
    ],
    "sg:phone":"+1 401 246 1208",
    "sg:postcode":"02806",
    "sg:province":"RI",
    "sg:tags":[
        "wear"
    ],
    "wof:name":"Kids Only",
    "wof:placetype":"venue"
},
  "geometry": {"coordinates":[-71.328264,41.760529],"type":"Point"}
}