{
  "type": "Feature",
  "properties": {
    "addr:full":"850 Manton Ave Providence RI 02909",
    "addr:housenumber":"850",
    "addr:postcode":"02909",
    "addr:street":"Manton Ave",
    "iso:country":"US",
    "sg:address":"850 Manton Ave",
    "sg:city":"Providence",
    "sg:classifiers":[
        {
            "category":"Retail",
            "subcategory":"Car Wash",
            "type":"Services"
        }
    ],
    "sg:phone":"+1 401 621 7596",
    "sg:postcode":"02909",
    "sg:province":"RI",
    "wof:name":"Swash Express Auto Wash",
    "wof:placetype":"venue"
},
  "geometry": {"coordinates":[-71.467102,41.834099],"type":"Point"}
}