{
  "type": "Feature",
  "properties": {
    "addr:full":"50 Newport Ave Rumford RI 02916",
    "addr:housenumber":"50",
    "addr:postcode":"02916",
    "addr:street":"Newport Ave",
    "iso:country":"US",
    "sg:address":"50 Newport Ave",
    "sg:city":"Rumford",
    "sg:classifiers":[
        {
            "category":"Banks & Credit Unions",
            "subcategory":"Financial Services",
            "type":"Services"
        }
    ],
    "sg:phone":"+1 401 431 9101",
    "sg:postcode":"02916",
    "sg:province":"RI",
    "sg:tags":[
        "broker",
        "mortgage"
    ],
    "sg:website":"www.citifinancial.com",
    "wof:name":"Citifinancial",
    "wof:placetype":"venue"
},
  "geometry": {"coordinates":[-71.354265,41.85746],"type":"Point"}
}