{
  "type": "Feature",
  "properties": {
    "addr:full":"138 Verndale Ave Providence RI 02905",
    "addr:housenumber":"138",
    "addr:postcode":"02905",
    "addr:street":"Verndale Ave",
    "iso:country":"US",
    "sg:address":"138 Verndale Ave",
    "sg:city":"Providence",
    "sg:classifiers":[
        {
            "category":"Communications",
            "subcategory":"Film & Video Production",
            "type":"Services"
        }
    ],
    "sg:phone":"+1 401 467 4357",
    "sg:postcode":"02905",
    "sg:province":"RI",
    "sg:tags":[
        "motion"
    ],
    "wof:name":"Polaris Music Productions",
    "wof:placetype":"venue"
},
  "geometry": {"coordinates":[-71.40989399999999,41.789561],"type":"Point"}
}