{
  "type": "Feature",
  "properties": {
    "iso:country":"US",
    "sg:address":"381 Wickenden St",
    "sg:city":"Providence",
    "sg:classifiers":[
        {
            "category":"Shopping",
            "subcategory":"Jewelry",
            "type":"Retail Goods"
        }
    ],
    "sg:phone":"+1 401 421 8728",
    "sg:postcode":"02903",
    "sg:province":"RI",
    "sg:tags":[
        "platinum",
        "silver",
        "gold"
    ],
    "wof:name":"Oasis Gold",
    "wof:placetype":"venue"
},
  "geometry": {"coordinates":[-71.395746,41.819583],"type":"Point"}
}