{
  "type": "Feature",
  "properties": {
    "iso:country":"US",
    "sg:address":"200 Massasoit Ave",
    "sg:city":"East Providence",
    "sg:classifiers":[
        {
            "category":"Manufacturing",
            "subcategory":"Chemicals & Compounds",
            "type":"Manufacturing & Wholesale Goods"
        }
    ],
    "sg:phone":"+1 401 438 7805",
    "sg:postcode":"02914",
    "sg:province":"RI",
    "sg:tags":[
        "industrial",
        "organic",
        "mfg"
    ],
    "wof:name":"Arch Chemicals Inc",
    "wof:placetype":"venue"
},
  "geometry": {"coordinates":[-71.37410800000001,41.828112],"type":"Point"}
}