{
  "type": "Feature",
  "properties": {
    "addr:full":"909 E Main Rd Middletown RI 02842",
    "addr:housenumber":"909",
    "addr:postcode":"02842",
    "addr:street":"E Main Rd",
    "iso:country":"US",
    "sg:address":"909 E Main Rd",
    "sg:city":"Middletown",
    "sg:classifiers":[
        {
            "category":"Retail",
            "subcategory":"Auto Rental",
            "type":"Services"
        }
    ],
    "sg:phone":"+1 401 847 4800",
    "sg:postcode":"02842",
    "sg:province":"RI",
    "sg:tags":[
        "passenger",
        "leasing",
        "car",
        "driver",
        "equipment",
        "without",
        "rent"
    ],
    "wof:name":"Nunes Leasing Co Inc",
    "wof:placetype":"venue"
},
  "geometry": {"coordinates":[-71.27472899999999,41.527388],"type":"Point"}
}