{
  "type": "Feature",
  "properties": {
    "addr:full":"165 Dean Knauss Dr Narragansett RI 02882",
    "addr:housenumber":"165",
    "addr:postcode":"02882",
    "addr:street":"Dean Knauss Dr",
    "iso:country":"US",
    "sg:address":"165 Dean Knauss Dr",
    "sg:city":"Narragansett",
    "sg:classifiers":[
        {
            "category":"Professional",
            "subcategory":"Management & Consulting",
            "type":"Services"
        }
    ],
    "sg:phone":"+1 401 788 9031",
    "sg:postcode":"02882",
    "sg:province":"RI",
    "sg:tags":[
        "business"
    ],
    "wof:name":"Accurate Envmtl Forecasting",
    "wof:placetype":"venue"
},
  "geometry": {"coordinates":[-71.42812499999999,41.489033],"type":"Point"}
}