{
  "type": "Feature",
  "properties": {
    "iso:country":"US",
    "sg:address":"29 E Shore Rd",
    "sg:city":"Narragansett",
    "sg:classifiers":[
        {
            "category":"Professional",
            "type":"Services"
        }
    ],
    "sg:phone":"+1 401 783 7875",
    "sg:postcode":"02882",
    "sg:province":"RI",
    "sg:tags":[
        "establishment"
    ],
    "wof:name":"Davon Corp",
    "wof:placetype":"venue"
},
  "geometry": {"coordinates":[-71.505854,41.385665],"type":"Point"}
}