{
  "type": "Feature",
  "properties": {
    "addr:full":"10 Weybosset St Providence RI 02903",
    "addr:housenumber":"10",
    "addr:postcode":"02903",
    "addr:street":"Weybosset St",
    "iso:country":"US",
    "sg:address":"10 Weybosset St",
    "sg:city":"Providence",
    "sg:classifiers":[
        {
            "category":"Professional",
            "subcategory":"Accounting & Tax Preparation",
            "type":"Services"
        }
    ],
    "sg:phone":"+1 401 421 4800",
    "sg:postcode":"02903",
    "sg:province":"RI",
    "sg:tags":[
        "accountant",
        "full",
        "public",
        "certified"
    ],
    "wof:name":"Champi Frank J",
    "wof:placetype":"venue"
},
  "geometry": {"coordinates":[-71.409745,41.824879],"type":"Point"}
}