{
  "type": "Feature",
  "properties": {
    "iso:country":"US",
    "sg:address":"205 Manton Ave",
    "sg:city":"Providence",
    "sg:classifiers":[
        {
            "category":"Retail",
            "subcategory":"Repair Shop",
            "type":"Services"
        }
    ],
    "sg:phone":"+1 401 272 5010",
    "sg:postcode":"02909",
    "sg:province":"RI",
    "sg:tags":[
        "tv"
    ],
    "wof:name":"E V Electronics",
    "wof:placetype":"venue"
},
  "geometry": {"coordinates":[-71.447321,41.820506],"type":"Point"}
}