{
  "type": "Feature",
  "properties": {
    "iso:country":"US",
    "sg:address":"300 Quaker Ln",
    "sg:city":"Warwick",
    "sg:classifiers":[
        {
            "category":"Shopping",
            "subcategory":"Computers & Home Electronics",
            "type":"Retail Goods"
        }
    ],
    "sg:phone":"+1 401 823 6861",
    "sg:postcode":"02886",
    "sg:province":"RI",
    "sg:tags":[
        "game",
        "video"
    ],
    "wof:name":"Gamestop",
    "wof:placetype":"venue"
},
  "geometry": {"coordinates":[-71.50103,41.68759],"type":"Point"}
}