{
  "type": "Feature",
  "properties": {
    "iso:country":"US",
    "sg:address":"6 George St",
    "sg:city":"Westerly",
    "sg:classifiers":[
        {
            "category":"Professional",
            "subcategory":"Art Services",
            "type":"Services"
        }
    ],
    "sg:phone":"+1 401 596 7995",
    "sg:postcode":"02891",
    "sg:province":"RI",
    "sg:tags":[
        "commercial",
        "design"
    ],
    "wof:name":"Frezzolini Severance",
    "wof:placetype":"venue"
},
  "geometry": {"coordinates":[-71.824579,41.372628],"type":"Point"}
}