{
  "type": "Feature",
  "properties": {
    "addr:full":"3534 Flat River Rd Coventry RI 02816",
    "addr:housenumber":"3534",
    "addr:postcode":"02816",
    "addr:street":"Flat River Rd",
    "iso:country":"US",
    "sg:address":"3534 Flat River Rd",
    "sg:city":"Coventry",
    "sg:classifiers":[
        {
            "category":"Retail",
            "subcategory":"Auto Repair",
            "type":"Services"
        }
    ],
    "sg:phone":"+1 401 397 7651",
    "sg:postcode":"02816",
    "sg:province":"RI",
    "sg:tags":[
        "general"
    ],
    "wof:name":"M & H Performance Auto",
    "wof:placetype":"venue"
},
  "geometry": {"coordinates":[-71.655968,41.708374],"type":"Point"}
}