{
  "type": "Feature",
  "properties": {
    "addr:full":"9 Cobblestone St Cumberland RI 02864",
    "addr:housenumber":"9",
    "addr:postcode":"02864",
    "addr:street":"Cobblestone St",
    "iso:country":"US",
    "sg:address":"9 Cobblestone St",
    "sg:city":"Cumberland",
    "sg:classifiers":[
        {
            "category":"Freight",
            "type":"Transportation"
        }
    ],
    "sg:phone":"+1 401 475 7268",
    "sg:postcode":"02864",
    "sg:province":"RI",
    "sg:tags":[
        "operator",
        "local",
        "trucking"
    ],
    "wof:name":"1-800-Gotjunk",
    "wof:placetype":"venue"
},
  "geometry": {"coordinates":[-71.411069,42.00354],"type":"Point"}
}