{
  "type": "Feature",
  "properties": {
    "iso:country":"US",
    "sg:address":"1 Jeffrey Rd",
    "sg:city":"Newport",
    "sg:classifiers":[
        {
            "category":"Professional",
            "subcategory":"Business Services",
            "type":"Services"
        }
    ],
    "sg:phone":"+1 401 846 2874",
    "sg:postcode":"02840",
    "sg:province":"RI",
    "wof:name":"Reed Enterprises LLC",
    "wof:placetype":"venue"
},
  "geometry": {"coordinates":[-71.31605399999999,41.459201],"type":"Point"}
}