{
  "type": "Feature",
  "properties": {
    "addr:full":"404 Main St Wakefield RI 02879",
    "addr:housenumber":"404",
    "addr:postcode":"02879",
    "addr:street":"Main St",
    "iso:country":"US",
    "sg:address":"404 Main St",
    "sg:city":"Wakefield",
    "sg:classifiers":[
        {
            "category":"Home & Garden",
            "subcategory":"Household Appliances",
            "type":"Retail Goods"
        }
    ],
    "sg:phone":"+1 401 788 8300",
    "sg:postcode":"02879",
    "sg:province":"RI",
    "sg:tags":[
        "machine",
        "sewing"
    ],
    "wof:name":"Sewing Room The",
    "wof:placetype":"venue"
},
  "geometry": {"coordinates":[-71.50107300000001,41.437078],"type":"Point"}
}