{
  "type": "Feature",
  "properties": {
    "iso:country":"US",
    "sg:address":"385 Niagara St",
    "sg:city":"Providence",
    "sg:classifiers":[
        {
            "category":"Government",
            "subcategory":"Office",
            "type":"Public Place"
        }
    ],
    "sg:phone":"+1 401 467 5410",
    "sg:postcode":"02907",
    "sg:province":"RI",
    "sg:tags":[
        "federal",
        "security"
    ],
    "wof:name":"US Army Reserve",
    "wof:placetype":"venue"
},
  "geometry": {"coordinates":[-71.414064,41.792547],"type":"Point"}
}