{
  "type": "Feature",
  "properties": {
    "addr:full":"137 John St East Providence RI 02914",
    "addr:housenumber":"137",
    "addr:postcode":"02914",
    "addr:street":"John St",
    "iso:country":"US",
    "sg:address":"137 John St",
    "sg:city":"East Providence",
    "sg:classifiers":[
        {
            "category":"Professional",
            "subcategory":"Detective & Security Services",
            "type":"Services"
        }
    ],
    "sg:phone":"+1 401 438 8783",
    "sg:postcode":"02914",
    "sg:province":"RI",
    "sg:tags":[
        "car"
    ],
    "wof:name":"Executive Security",
    "wof:placetype":"venue"
},
  "geometry": {"coordinates":[-71.36959,41.822133],"type":"Point"}
}