{
  "type": "Feature",
  "properties": {
    "iso:country":"US",
    "sg:address":"82 Clinton St",
    "sg:city":"Woonsocket",
    "sg:classifiers":[
        {
            "category":"Social Services",
            "type":"Services"
        }
    ],
    "sg:phone":"+1 401 765 4364",
    "sg:postcode":"02895",
    "sg:province":"RI",
    "sg:tags":[
        "counselor",
        "marriage",
        "family"
    ],
    "wof:name":"Hosanna Lighthouse Ministries",
    "wof:placetype":"venue"
},
  "geometry": {"coordinates":[-71.511199,42.004319],"type":"Point"}
}