{
  "type": "Feature",
  "properties": {
    "addr:full":"19 Valley Rd Middletown RI 02842",
    "addr:housenumber":"19",
    "addr:postcode":"02842",
    "addr:street":"Valley Rd",
    "iso:country":"US",
    "sg:address":"19 Valley Rd",
    "sg:city":"Middletown",
    "sg:classifiers":[
        {
            "category":"Social Services",
            "type":"Services"
        }
    ],
    "sg:phone":"+1 401 841 8896",
    "sg:postcode":"02842",
    "sg:province":"RI",
    "sg:tags":[
        "counselor",
        "marriage",
        "family"
    ],
    "sg:website":"www.cfsnewport.org",
    "wof:name":"Child & Family Svc Of Newport",
    "wof:placetype":"venue"
},
  "geometry": {"coordinates":[-71.294872,41.521829],"type":"Point"}
}