{
  "type": "Feature",
  "properties": {
    "addr:full":"1435 Victory Hwy North Smithfield RI 02896",
    "addr:housenumber":"1435",
    "addr:postcode":"02896",
    "addr:street":"Victory Hwy",
    "iso:country":"US",
    "sg:address":"1435 Victory Hwy",
    "sg:city":"North Smithfield",
    "sg:classifiers":[
        {
            "category":"Shopping",
            "type":"Retail Goods"
        }
    ],
    "sg:phone":"+1 401 767 3618",
    "sg:postcode":"02896",
    "sg:province":"RI",
    "sg:tags":[
        "pet",
        "shop"
    ],
    "wof:name":"Creatures Creatures Creatures",
    "wof:placetype":"venue"
},
  "geometry": {"coordinates":[-71.59817099999999,41.995697],"type":"Point"}
}