{
  "type": "Feature",
  "properties": {
    "iso:country":"US",
    "sg:address":"1061 Fish Rd",
    "sg:city":"Tiverton",
    "sg:classifiers":[
        {
            "category":"Health Services",
            "subcategory":"Health Practitioner",
            "type":"Services"
        }
    ],
    "sg:phone":"+1 401 624 9981",
    "sg:postcode":"02878",
    "sg:province":"RI",
    "sg:tags":[
        "psychologist"
    ],
    "wof:name":"Sakonnet Psychological Assoc",
    "wof:placetype":"venue"
},
  "geometry": {"coordinates":[-71.18758699999999,41.640451],"type":"Point"}
}