{
  "type": "Feature",
  "properties": {
    "addr:full":"10 Arbutus Trl Coventry RI 02816",
    "addr:housenumber":"10",
    "addr:postcode":"02816",
    "addr:street":"Arbutus Trl",
    "iso:country":"US",
    "sg:address":"10 Arbutus Trl",
    "sg:city":"Coventry",
    "sg:classifiers":[
        {
            "category":"Manufacturing",
            "subcategory":"Apparel",
            "type":"Manufacturing & Wholesale Goods"
        }
    ],
    "sg:phone":"+1 401 826 8974",
    "sg:postcode":"02816",
    "sg:province":"RI",
    "wof:name":"Initial Impressions",
    "wof:placetype":"venue"
},
  "geometry": {"coordinates":[-71.59725299999999,41.691974],"type":"Point"}
}