{
  "type": "Feature",
  "properties": {
    "iso:country":"US",
    "sg:address":"26 Lake View Cir",
    "sg:city":"Chepachet",
    "sg:classifiers":[
        {
            "category":"Freight",
            "type":"Transportation"
        }
    ],
    "sg:phone":"+1 401 965 0329",
    "sg:postcode":"02814",
    "sg:province":"RI",
    "sg:tags":[
        "broker",
        "trucking"
    ],
    "wof:name":"Wig Gill Transportation",
    "wof:placetype":"venue"
},
  "geometry": {"coordinates":[-71.687117,41.882651],"type":"Point"}
}