{
  "type": "Feature",
  "properties": {
    "iso:country":"US",
    "sg:address":"93 Pontiac Ave",
    "sg:city":"Cranston",
    "sg:classifiers":[
        {
            "category":"Building & Trades",
            "subcategory":"Cleaning & Sanitation",
            "type":"Services"
        }
    ],
    "sg:phone":"+1 401 345 2564",
    "sg:postcode":"02910",
    "sg:province":"RI",
    "sg:tags":[
        "maintenance"
    ],
    "wof:name":"Alex Commercial Cleaning Inc",
    "wof:placetype":"venue"
},
  "geometry": {"coordinates":[-71.431625,41.786682],"type":"Point"}
}