{
  "type": "Feature",
  "properties": {
    "iso:country":"US",
    "sg:address":"5586 Post Rd",
    "sg:city":"East Greenwich",
    "sg:classifiers":[
        {
            "category":"Health Services",
            "subcategory":"Doctor",
            "type":"Services"
        }
    ],
    "sg:phone":"+1 401 884 8118",
    "sg:postcode":"02818",
    "sg:province":"RI",
    "sg:tags":[
        "dentist"
    ],
    "wof:name":"Affilates In Oral Surgery",
    "wof:placetype":"venue"
},
  "geometry": {"coordinates":[-71.46566199999999,41.64302],"type":"Point"}
}