{
  "type": "Feature",
  "properties": {
    "iso:country":"US",
    "sg:address":"350 Kinsley Ave",
    "sg:city":"Providence",
    "sg:classifiers":[
        {
            "category":"Wholesale",
            "subcategory":"Hardware",
            "type":"Manufacturing & Wholesale Goods"
        }
    ],
    "sg:phone":"+1 401 453 3755",
    "sg:postcode":"02903",
    "sg:province":"RI",
    "sg:tags":[
        "refrigeration",
        "con"
    ],
    "wof:name":"U R I 52",
    "wof:placetype":"venue"
},
  "geometry": {"coordinates":[-71.430533,41.828048],"type":"Point"}
}