{
  "type": "Feature",
  "properties": {
    "addr:full":"24 Brown St North Kingstown RI 02852",
    "addr:housenumber":"24",
    "addr:postcode":"02852",
    "addr:street":"Brown St",
    "iso:country":"US",
    "sg:address":"24 Brown St",
    "sg:city":"North Kingstown",
    "sg:classifiers":[
        {
            "category":"Shopping",
            "type":"Retail Goods"
        }
    ],
    "sg:phone":"+1 401 295 0333",
    "sg:postcode":"02852",
    "sg:province":"RI",
    "sg:tags":[
        "candle"
    ],
    "wof:name":"Gelart Candles Of Wickford",
    "wof:placetype":"venue"
},
  "geometry": {"coordinates":[-71.452716,41.569634],"type":"Point"}
}