{
  "type": "Feature",
  "properties": {
    "iso:country":"US",
    "sg:address":"110 Yale Dr",
    "sg:city":"Coventry",
    "sg:classifiers":[
        {
            "category":"Building & Trades",
            "subcategory":"Plumbing",
            "type":"Services"
        }
    ],
    "sg:phone":"+1 401 822 1725",
    "sg:postcode":"02816",
    "sg:province":"RI",
    "sg:tags":[
        "contractor"
    ],
    "wof:name":"Paul Hoxie Plumbing",
    "wof:placetype":"venue"
},
  "geometry": {"coordinates":[-71.54376600000001,41.68536],"type":"Point"}
}