{
  "type": "Feature",
  "properties": {
    "iso:country":"US",
    "sg:address":"611 Front St",
    "sg:city":"Woonsocket",
    "sg:classifiers":[
        {
            "category":"Freight",
            "type":"Transportation"
        }
    ],
    "sg:phone":"+1 401 766 0259",
    "sg:postcode":"02895",
    "sg:province":"RI",
    "sg:tags":[
        "commercial",
        "storage"
    ],
    "wof:name":"B & B Consumers Storage",
    "wof:placetype":"venue"
},
  "geometry": {"coordinates":[-71.51597599999999,41.996047],"type":"Point"}
}