{
  "type": "Feature",
  "properties": {
    "iso:country":"US",
    "sg:address":"550 S County Trl",
    "sg:city":"Slocum",
    "sg:classifiers":[
        {
            "category":"Building & Trades",
            "subcategory":"Landscaping Services",
            "type":"Services"
        }
    ],
    "sg:phone":"+1 401 295 8449",
    "sg:postcode":"02852",
    "sg:province":"RI",
    "sg:tags":[
        "sod",
        "sodding"
    ],
    "wof:name":"Turf Inc",
    "wof:placetype":"venue"
},
  "geometry": {"coordinates":[-71.518108,41.55918],"type":"Point"}
}