{
  "type": "Feature",
  "properties": {
    "iso:country":"US",
    "sg:address":"95 Scott Rd",
    "sg:city":"Cumberland",
    "sg:classifiers":[
        {
            "category":"Wholesale",
            "subcategory":"Electrical",
            "type":"Manufacturing & Wholesale Goods"
        },
        {
            "category":"Professional",
            "subcategory":"Computer Services",
            "type":"Services"
        }
    ],
    "sg:phone":"+1 401 333 8060",
    "sg:postcode":"02864",
    "sg:province":"RI",
    "sg:tags":[
        "equipment",
        "programming",
        "telephone",
        "system"
    ],
    "wof:name":"Global Voice Connection System",
    "wof:placetype":"venue"
},
  "geometry": {"coordinates":[-71.43092,41.938863],"type":"Point"}
}