{
  "type": "Feature",
  "properties": {
    "addr:full":"100 Dexter St Pawtucket RI 02860",
    "addr:housenumber":"100",
    "addr:postcode":"02860",
    "addr:street":"Dexter St",
    "iso:country":"US",
    "sg:address":"100 Dexter St",
    "sg:city":"Pawtucket",
    "sg:classifiers":[
        {
            "category":"Manufacturing",
            "subcategory":"Tools & Machinery",
            "type":"Manufacturing & Wholesale Goods"
        }
    ],
    "sg:phone":"+1 401 728 0913",
    "sg:postcode":"02860",
    "sg:province":"RI",
    "sg:tags":[
        "chemical",
        "photography",
        "photographic",
        "store",
        "mfg"
    ],
    "wof:name":"Sprint Systems of Photography",
    "wof:placetype":"venue"
},
  "geometry": {"coordinates":[-71.387703,41.879002],"type":"Point"}
}