{
  "type": "Feature",
  "properties": {
    "iso:country":"US",
    "sg:address":"56 Exchange Ter",
    "sg:city":"Providence",
    "sg:classifiers":[
        {
            "category":"Professional",
            "subcategory":"Engineering",
            "type":"Services"
        }
    ],
    "sg:phone":"+1 401 751 5360",
    "sg:postcode":"02903",
    "sg:province":"RI",
    "sg:tags":[
        "engineer"
    ],
    "sg:website":"www.cdm.com",
    "wof:name":"Camp Dresser & Mc Kee Inc",
    "wof:placetype":"venue"
},
  "geometry": {"coordinates":[-71.413083,41.825681],"type":"Point"}
}