{
  "type": "Feature",
  "properties": {
    "addr:full":"90 Uphill Ave Warwick RI 02886",
    "addr:housenumber":"90",
    "addr:postcode":"02886",
    "addr:street":"Uphill Ave",
    "iso:country":"US",
    "sg:address":"90 Uphill Ave",
    "sg:city":"Warwick",
    "sg:classifiers":[
        {
            "category":"Building & Trades",
            "subcategory":"Construction",
            "type":"Services"
        }
    ],
    "sg:phone":"+1 401 737 7037",
    "sg:postcode":"02886",
    "sg:province":"RI",
    "sg:tags":[
        "concrete",
        "contractor"
    ],
    "wof:name":"Rips Co",
    "wof:placetype":"venue"
},
  "geometry": {"coordinates":[-71.42218800000001,41.709143],"type":"Point"}
}