{
  "type": "Feature",
  "properties": {
    "addr:full":"254 Reservoir Ave Providence RI 02907",
    "addr:housenumber":"254",
    "addr:postcode":"02907",
    "addr:street":"Reservoir Ave",
    "iso:country":"US",
    "sg:address":"254 Reservoir Ave",
    "sg:city":"Providence",
    "sg:classifiers":[
        {
            "category":"Health Services",
            "subcategory":"Doctor",
            "type":"Services"
        }
    ],
    "sg:phone":"+1 401 941 2444",
    "sg:postcode":"02907",
    "sg:province":"RI",
    "wof:name":"Luis A Aleman DDS",
    "wof:placetype":"venue"
},
  "geometry": {"coordinates":[-71.428991,41.79026],"type":"Point"}
}