{
  "type": "Feature",
  "properties": {
    "iso:country":"US",
    "sg:address":"222 S Water St",
    "sg:city":"Providence",
    "sg:classifiers":[
        {
            "category":"Health Services",
            "subcategory":"Doctor",
            "type":"Services"
        },
        {
            "category":"Health Services",
            "subcategory":"Clinic",
            "type":"Services"
        },
        {
            "category":"Health Services",
            "subcategory":"Health Practitioner",
            "type":"Services"
        }
    ],
    "sg:phone":"+1 401 273 0044",
    "sg:postcode":"02903",
    "sg:province":"RI",
    "sg:tags":[
        "physician",
        "surgeons",
        "therapist",
        "therapy",
        "medicine",
        "sport",
        "physical"
    ],
    "wof:name":"Ciarniello Physical Therapy",
    "wof:placetype":"venue"
},
  "geometry": {"coordinates":[-71.4058,41.822102],"type":"Point"}
}