{
  "type": "Feature",
  "properties": {
    "iso:country":"US",
    "sg:address":"73 Richmond st",
    "sg:city":"Providence",
    "sg:classifiers":[
        {
            "category":"Recreation",
            "subcategory":"Dance Hall",
            "type":"Entertainment"
        }
    ],
    "sg:phone":"+1 401 351 1977",
    "sg:postcode":"02904",
    "sg:province":"RI",
    "sg:tags":[
        "club"
    ],
    "sg:website":"www.club-hell.com",
    "wof:name":"Club Hell",
    "wof:placetype":"venue"
},
  "geometry": {"coordinates":[-71.411598,41.820301],"type":"Point"}
}