{
  "type": "Feature",
  "properties": {
    "addr:full":"1633 Warwick Ave Warwick RI 02889",
    "addr:housenumber":"1633",
    "addr:postcode":"02889",
    "addr:street":"Warwick Ave",
    "iso:country":"US",
    "sg:address":"1633 Warwick Ave",
    "sg:city":"Warwick",
    "sg:classifiers":[
        {
            "category":"Restaurant",
            "type":"Food & Drink"
        }
    ],
    "sg:phone":"+1 401 738 6470",
    "sg:postcode":"02889",
    "sg:province":"RI",
    "wof:name":"Nick's Place",
    "wof:placetype":"venue"
},
  "geometry": {"coordinates":[-71.406875,41.73206],"type":"Point"}
}