{
  "type": "Feature",
  "properties": {
    "iso:country":"US",
    "sg:address":"73 Downes Ave",
    "sg:city":"Pawtucket",
    "sg:classifiers":[
        {
            "category":"Place Of Worship",
            "type":"Public Place"
        },
        {
            "category":"Organizations",
            "subcategory":"Religious Organization",
            "type":"Services"
        }
    ],
    "sg:phone":"+1 401 725 6324",
    "sg:postcode":"02861",
    "sg:province":"RI",
    "sg:tags":[
        "church"
    ],
    "wof:name":"Darlington Cong Church",
    "wof:placetype":"venue"
},
  "geometry": {"coordinates":[-71.35659800000001,41.8866],"type":"Point"}
}