{
  "type": "Feature",
  "properties": {
    "iso:country":"US",
    "sg:address":"576 Metacom Ave",
    "sg:city":"Bristol",
    "sg:classifiers":[
        {
            "category":"Banks & Credit Unions",
            "subcategory":"Bank",
            "type":"Services"
        }
    ],
    "sg:phone":"+1 401 254 0301",
    "sg:postcode":"02809",
    "sg:province":"RI",
    "wof:name":"Citizens Bank",
    "wof:placetype":"venue"
},
  "geometry": {"coordinates":[-71.26346100000001,41.693972],"type":"Point"}
}