{
  "type": "Feature",
  "properties": {
    "addr:full":"500 Toll Gate Rd Warwick RI 02886",
    "addr:housenumber":"500",
    "addr:postcode":"02886",
    "addr:street":"Toll Gate Rd",
    "iso:country":"US",
    "sg:address":"500 Toll Gate Rd",
    "sg:city":"Warwick",
    "sg:classifiers":[
        {
            "category":"Health Services",
            "subcategory":"Doctor",
            "type":"Services"
        }
    ],
    "sg:phone":"+1 401 739 3900",
    "sg:postcode":"02886",
    "sg:province":"RI",
    "sg:tags":[
        "dentist"
    ],
    "wof:name":"Tollgate Orthodontics",
    "wof:placetype":"venue"
},
  "geometry": {"coordinates":[-71.47901,41.704836],"type":"Point"}
}