{
  "type": "Feature",
  "properties": {
    "iso:country":"US",
    "sg:address":"78 High St",
    "sg:city":"Westerly",
    "sg:classifiers":[
        {
            "category":"Shopping",
            "subcategory":"Clothing, Apparel, & Fashions",
            "type":"Retail Goods"
        }
    ],
    "sg:phone":"+1 401 596 5066",
    "sg:postcode":"02891",
    "sg:province":"RI",
    "sg:tags":[
        "tailor"
    ],
    "wof:name":"Luigi's Tailor Shop",
    "wof:placetype":"venue"
},
  "geometry": {"coordinates":[-71.828861,41.379718],"type":"Point"}
}