{
  "type": "Feature",
  "properties": {
    "iso:country":"US",
    "sg:address":"15 Warren Ave",
    "sg:city":"East Providence",
    "sg:classifiers":[
        {
            "category":"Manufacturing",
            "subcategory":"Signs",
            "type":"Manufacturing & Wholesale Goods"
        }
    ],
    "sg:phone":"+1 401 435 2020",
    "sg:postcode":"02914",
    "sg:province":"RI",
    "wof:name":"Arruda Graphics Inc",
    "wof:placetype":"venue"
},
  "geometry": {"coordinates":[-71.38370500000001,41.818122],"type":"Point"}
}