{
  "type": "Feature",
  "properties": {
    "iso:country":"US",
    "sg:address":"289 New York Ave",
    "sg:city":"Providence",
    "sg:classifiers":[
        {
            "category":"Social Services",
            "subcategory":"Child Care",
            "type":"Services"
        }
    ],
    "sg:phone":"+1 401 467 7548",
    "sg:postcode":"02905",
    "sg:province":"RI",
    "sg:tags":[
        "day"
    ],
    "wof:name":"Corona Jardin Infantile",
    "wof:placetype":"venue"
},
  "geometry": {"coordinates":[-71.39794500000001,41.790949],"type":"Point"}
}