{
  "type": "Feature",
  "properties": {
    "iso:country":"US",
    "sg:address":"460 Bradford Rd",
    "sg:city":"Bradford",
    "sg:classifiers":[
        {
            "category":"Manufacturing",
            "subcategory":"Textiles",
            "type":"Manufacturing & Wholesale Goods"
        }
    ],
    "sg:phone":"+1 401 377 2231",
    "sg:postcode":"02808",
    "sg:province":"RI",
    "sg:tags":[
        "finishing"
    ],
    "sg:website":"www.bdadye.com",
    "wof:name":"Bradford Dyeing Assn Inc",
    "wof:placetype":"venue"
},
  "geometry": {"coordinates":[-71.748741,41.397079],"type":"Point"}
}