{
  "type": "Feature",
  "properties": {
    "addr:full":"15 Hopkins St Providence RI 02903",
    "addr:housenumber":"15",
    "addr:postcode":"02903",
    "addr:street":"Hopkins St",
    "iso:country":"US",
    "sg:address":"15 Hopkins St",
    "sg:city":"Providence",
    "sg:classifiers":[
        {
            "category":"Organizations",
            "subcategory":"Professional Association",
            "type":"Services"
        }
    ],
    "sg:phone":"+1 401 421 0694",
    "sg:postcode":"02903",
    "sg:province":"RI",
    "wof:name":"Hopkins Governor Stephen House",
    "wof:placetype":"venue"
},
  "geometry": {"coordinates":[-71.406736,41.825052],"type":"Point"}
}