{
  "type": "Feature",
  "properties": {
    "iso:country":"US",
    "sg:address":"1 Hillside Ave",
    "sg:city":"Johnston",
    "sg:classifiers":[
        {
            "category":"Retail",
            "subcategory":"Auto Repair",
            "type":"Services"
        }
    ],
    "sg:phone":"+1 401 454 5646",
    "sg:postcode":"02919",
    "sg:province":"RI",
    "sg:tags":[
        "repairing",
        "automobile"
    ],
    "wof:name":"John Dube Auto Mntnc & Repair",
    "wof:placetype":"venue"
},
  "geometry": {"coordinates":[-71.47640199999999,41.807999],"type":"Point"}
}