{
  "type": "Feature",
  "properties": {
    "iso:country":"US",
    "sg:address":"100 Westminster Street",
    "sg:city":"Providence",
    "sg:classifiers":[
        {
            "category":"Food & Beverages",
            "subcategory":"Bakery",
            "type":"Retail Goods"
        }
    ],
    "sg:phone":"+1 401 521 9092",
    "sg:postcode":"02903",
    "sg:province":"RI",
    "sg:tags":[
        "sandwich"
    ],
    "sg:website":"www.aubonpain.com/",
    "wof:name":"Au Bon Pain",
    "wof:placetype":"venue"
},
  "geometry": {"coordinates":[-71.410464,41.82437],"type":"Point"}
}