{
  "type": "Feature",
  "properties": {
    "addr:full":"791 Dexter St Central Falls RI 02863",
    "addr:housenumber":"791",
    "addr:postcode":"02863",
    "addr:street":"Dexter St",
    "iso:country":"US",
    "sg:address":"791 Dexter St",
    "sg:city":"Central Falls",
    "sg:classifiers":[
        {
            "category":"Insurance",
            "subcategory":"Insurance Agent",
            "type":"Services"
        }
    ],
    "sg:phone":"+1 401 722 8810",
    "sg:postcode":"02863",
    "sg:province":"RI",
    "wof:name":"Zuluaga Insurance",
    "wof:placetype":"venue"
},
  "geometry": {"coordinates":[-71.397908,41.887587],"type":"Point"}
}