{
  "type": "Feature",
  "properties": {
    "addr:full":"1958 Smith St Providence RI 02911",
    "addr:housenumber":"1958",
    "addr:postcode":"02911",
    "addr:street":"Smith St",
    "iso:country":"US",
    "sg:address":"1958 Smith St",
    "sg:city":"Providence",
    "sg:classifiers":[
        {
            "category":"Professional",
            "type":"Services"
        }
    ],
    "sg:phone":"+1 401 233 7834",
    "sg:postcode":"02911",
    "sg:province":"RI",
    "sg:tags":[
        "establishment"
    ],
    "wof:name":"Concepts For Adv Tech Inc",
    "wof:placetype":"venue"
},
  "geometry": {"coordinates":[-71.48199200000001,41.856519],"type":"Point"}
}