{
  "type": "Feature",
  "properties": {
    "addr:full":"Post Rd Charlestown RI 02813",
    "addr:postcode":"02813",
    "addr:street":"Post Rd",
    "iso:country":"US",
    "sg:address":"Post Rd",
    "sg:city":"Charlestown",
    "sg:classifiers":[
        {
            "category":"Restaurant",
            "type":"Food & Drink"
        }
    ],
    "sg:phone":"+1 401 364 7495",
    "sg:postcode":"02813",
    "sg:province":"RI",
    "wof:name":"Hitching Post Inc",
    "wof:placetype":"venue"
},
  "geometry": {"coordinates":[-71.680199,41.3932],"type":"Point"}
}