{
  "type": "Feature",
  "properties": {
    "addr:full":"980 Eddie Dowling Hwy North Smithfield RI 02896",
    "addr:housenumber":"980",
    "addr:postcode":"02896",
    "addr:street":"Eddie Dowling Hwy",
    "iso:country":"US",
    "sg:address":"980 Eddie Dowling Hwy",
    "sg:city":"North Smithfield",
    "sg:classifiers":[
        {
            "category":"Banks & Credit Unions",
            "subcategory":"Financial Services",
            "type":"Services"
        }
    ],
    "sg:phone":"+1 401 356 4848",
    "sg:postcode":"02896",
    "sg:province":"RI",
    "sg:tags":[
        "broker",
        "mortgage"
    ],
    "sg:website":"www.victorymortgagecorp.com",
    "wof:name":"Victory Mortgage",
    "wof:placetype":"venue"
},
  "geometry": {"coordinates":[-71.494907,41.961944],"type":"Point"}
}