{
  "type": "Feature",
  "properties": {
    "addr:full":"43 Hawes St Central Falls RI 02863",
    "addr:housenumber":"43",
    "addr:postcode":"02863",
    "addr:street":"Hawes St",
    "iso:country":"US",
    "sg:address":"43 Hawes St",
    "sg:city":"Central Falls",
    "sg:classifiers":[
        {
            "category":"Social Services",
            "subcategory":"Child Care",
            "type":"Services"
        }
    ],
    "sg:phone":"+1 401 723 3050",
    "sg:postcode":"02863",
    "sg:province":"RI",
    "sg:tags":[
        "day"
    ],
    "wof:name":"Y C W A Greater Rhode Island",
    "wof:placetype":"venue"
},
  "geometry": {"coordinates":[-71.388469,41.883496],"type":"Point"}
}