{
  "type": "Feature",
  "properties": {
    "addr:full":"671 Boston Neck Rd North Kingstown RI 02852",
    "addr:housenumber":"671",
    "addr:postcode":"02852",
    "addr:street":"Boston Neck Rd",
    "iso:country":"US",
    "sg:address":"671 Boston Neck Rd",
    "sg:city":"North Kingstown",
    "sg:classifiers":[
        {
            "category":"Cinema",
            "subcategory":"Movie Rental",
            "type":"Entertainment"
        }
    ],
    "sg:phone":"+1 401 295 5550",
    "sg:postcode":"02852",
    "sg:province":"RI",
    "sg:tags":[
        "leasing",
        "video",
        "disc",
        "tape"
    ],
    "wof:name":"Hunt Video Hut",
    "wof:placetype":"venue"
},
  "geometry": {"coordinates":[-71.440934,41.554097],"type":"Point"}
}