{
  "type": "Feature",
  "properties": {
    "addr:full":"941 Namquid Dr Warwick RI 02888",
    "addr:housenumber":"941",
    "addr:postcode":"02888",
    "addr:street":"Namquid Dr",
    "iso:country":"US",
    "sg:address":"941 Namquid Dr",
    "sg:city":"Warwick",
    "sg:classifiers":[
        {
            "category":"Shopping",
            "subcategory":"Used Merchandise",
            "type":"Retail Goods"
        }
    ],
    "sg:phone":"+1 401 463 3310",
    "sg:postcode":"02888",
    "sg:province":"RI",
    "wof:name":"Home Again Consignment Shop",
    "wof:placetype":"venue"
},
  "geometry": {"coordinates":[-71.405415,41.741912],"type":"Point"}
}