{
  "type": "Feature",
  "properties": {
    "addr:full":"290 Smith St North Kingstown RI 02886",
    "addr:housenumber":"290",
    "addr:postcode":"02886",
    "addr:street":"Smith St",
    "iso:country":"US",
    "sg:address":"290 Smith St",
    "sg:city":"North Kingstown",
    "sg:classifiers":[
        {
            "category":"Retail",
            "subcategory":"Repair Shop",
            "type":"Services"
        }
    ],
    "sg:phone":"+1 401 295 1811",
    "sg:postcode":"02886",
    "sg:province":"RI",
    "sg:tags":[
        "welding"
    ],
    "wof:name":"Kelly Welding & Fabrication",
    "wof:placetype":"venue"
},
  "geometry": {"coordinates":[-71.446197,41.706351],"type":"Point"}
}