{
  "type": "Feature",
  "properties": {
    "iso:country":"US",
    "sg:address":"1348 Broad St",
    "sg:city":"Providence",
    "sg:classifiers":[
        {
            "category":"Professional",
            "type":"Services"
        }
    ],
    "sg:phone":"+1 401 461 1733",
    "sg:postcode":"02905",
    "sg:province":"RI",
    "wof:name":"Take Out Trash Inc",
    "wof:placetype":"venue"
},
  "geometry": {"coordinates":[-71.405197,41.790366],"type":"Point"}
}