{
  "type": "Feature",
  "properties": {
    "iso:country":"US",
    "sg:address":"45 Lakeside Dr",
    "sg:city":"Smithfield",
    "sg:classifiers":[
        {
            "category":"Shopping",
            "type":"Retail Goods"
        },
        {
            "category":"Shopping",
            "subcategory":"Gifts & Souvenirs",
            "type":"Retail Goods"
        }
    ],
    "sg:phone":"+1 401 233 2753",
    "sg:postcode":"02917",
    "sg:province":"RI",
    "sg:tags":[
        "shop",
        "merchandise"
    ],
    "wof:name":"Penny Lane Country Store Inc",
    "wof:placetype":"venue"
},
  "geometry": {"coordinates":[-71.518944,41.898844],"type":"Point"}
}