{
  "type": "Feature",
  "properties": {
    "iso:country":"US",
    "sg:address":"44 Barton Ave",
    "sg:city":"Warren",
    "sg:classifiers":[
        {
            "category":"Home & Garden",
            "subcategory":"Garden Supply",
            "type":"Retail Goods"
        }
    ],
    "sg:phone":"+1 401 245 6325",
    "sg:postcode":"02885",
    "sg:province":"RI",
    "sg:tags":[
        "ha",
        "merchandise"
    ],
    "wof:name":"Crosstown Antiques",
    "wof:placetype":"venue"
},
  "geometry": {"coordinates":[-71.243065,41.72289],"type":"Point"}
}