{
  "type": "Feature",
  "properties": {
    "iso:country":"US",
    "sg:address":"259 Macklin St",
    "sg:city":"Cranston",
    "sg:classifiers":[
        {
            "category":"Wholesale",
            "subcategory":"Machinery & Supplies",
            "type":"Manufacturing & Wholesale Goods"
        }
    ],
    "sg:phone":"+1 401 946 1300",
    "sg:postcode":"02920",
    "sg:province":"RI",
    "sg:tags":[
        "compressor",
        "gas"
    ],
    "sg:website":"www.calsupplycompany.com",
    "wof:name":"Cal Supply Co",
    "wof:placetype":"venue"
},
  "geometry": {"coordinates":[-71.463516,41.780027],"type":"Point"}
}