{
  "type": "Feature",
  "properties": {
    "addr:full":"11 Sachem Rd Bristol RI 02809",
    "addr:housenumber":"11",
    "addr:postcode":"02809",
    "addr:street":"Sachem Rd",
    "iso:country":"US",
    "sg:address":"11 Sachem Rd",
    "sg:city":"Bristol",
    "sg:classifiers":[
        {
            "category":"Shopping",
            "subcategory":"Computers & Home Electronics",
            "type":"Retail Goods"
        }
    ],
    "sg:phone":"+1 401 254 9799",
    "sg:postcode":"02809",
    "sg:province":"RI",
    "sg:tags":[
        "equipment",
        "dealer"
    ],
    "wof:name":"Harbor Light Computers Inc",
    "wof:placetype":"venue"
},
  "geometry": {"coordinates":[-71.268237,41.710907],"type":"Point"}
}