{
  "type": "Feature",
  "properties": {
    "iso:country":"US",
    "sg:address":"765 Westminster St",
    "sg:city":"Providence",
    "sg:classifiers":[
        {
            "category":"Professional",
            "subcategory":"Management & Consulting",
            "type":"Services"
        }
    ],
    "sg:phone":"+1 401 331 9559",
    "sg:postcode":"02903",
    "sg:province":"RI",
    "sg:tags":[
        "sales",
        "house",
        "construction",
        "direct",
        "retail"
    ],
    "wof:name":"Jacob Leech Inc",
    "wof:placetype":"venue"
},
  "geometry": {"coordinates":[-71.420838,41.818017],"type":"Point"}
}