{
  "type": "Feature",
  "properties": {
    "iso:country":"US",
    "sg:address":"135 Mauran Ave",
    "sg:city":"East Providence",
    "sg:classifiers":[
        {
            "category":"Building & Trades",
            "subcategory":"Plumbing",
            "type":"Services"
        }
    ],
    "sg:phone":"+1 401 435 6899",
    "sg:postcode":"02914",
    "sg:province":"RI",
    "sg:tags":[
        "conditioning",
        "air",
        "system",
        "contractor"
    ],
    "wof:name":"Dynamic Air Systems",
    "wof:placetype":"venue"
},
  "geometry": {"coordinates":[-71.38310799999999,41.816215],"type":"Point"}
}