{
  "type": "Feature",
  "properties": {
    "addr:full":"1580 Wampanoag Trl Barrington RI 02806",
    "addr:housenumber":"1580",
    "addr:postcode":"02806",
    "addr:street":"Wampanoag Trl",
    "iso:country":"US",
    "sg:address":"1580 Wampanoag Trl",
    "sg:city":"Barrington",
    "sg:classifiers":[
        {
            "category":"Sports & Exercise",
            "subcategory":"Gym",
            "type":"Entertainment"
        }
    ],
    "sg:phone":"+1 401 245 2911",
    "sg:postcode":"02806",
    "sg:province":"RI",
    "sg:tags":[
        "fitness",
        "physical",
        "facility"
    ],
    "wof:name":"Body By Design",
    "wof:placetype":"venue"
},
  "geometry": {"coordinates":[-71.32465999999999,41.771374],"type":"Point"}
}