{
  "type": "Feature",
  "properties": {
    "iso:country":"US",
    "sg:address":"217 Valley St",
    "sg:city":"Providence",
    "sg:classifiers":[
        {
            "category":"Building & Trades",
            "subcategory":"Construction",
            "type":"Services"
        }
    ],
    "sg:phone":"+1 401 490 4641",
    "sg:postcode":"02909",
    "sg:province":"RI",
    "sg:tags":[
        "contractor"
    ],
    "wof:name":"Builders & Conslnt Intl LLC",
    "wof:placetype":"venue"
},
  "geometry": {"coordinates":[-71.439747,41.822869],"type":"Point"}
}