{
  "type": "Feature",
  "properties": {
    "iso:country":"US",
    "sg:address":"172 Bellevue Ave",
    "sg:city":"Newport",
    "sg:classifiers":[
        {
            "category":"Professional",
            "subcategory":"Computer Services",
            "type":"Services"
        }
    ],
    "sg:phone":"+1 401 841 5141",
    "sg:postcode":"02840",
    "sg:province":"RI",
    "sg:tags":[
        "prepackaged",
        "software"
    ],
    "wof:name":"Genesys Telecom Labs",
    "wof:placetype":"venue"
},
  "geometry": {"coordinates":[-71.308431,41.483488],"type":"Point"}
}