{
  "type": "Feature",
  "properties": {
    "iso:country":"US",
    "sg:address":"10 Mellbridge Dr",
    "sg:city":"Wakefield",
    "sg:classifiers":[
        {
            "category":"Education",
            "subcategory":"Special Training",
            "type":"Public Place"
        }
    ],
    "sg:phone":"+1 401 789 8062",
    "sg:postcode":"02879",
    "sg:province":"RI",
    "sg:tags":[
        "professor"
    ],
    "wof:name":"Wayne Velicer",
    "wof:placetype":"venue"
},
  "geometry": {"coordinates":[-71.519856,41.457137],"type":"Point"}
}