{
  "type": "Feature",
  "properties": {
    "addr:full":"931 Atwood Ave Johnston RI 02919",
    "addr:housenumber":"931",
    "addr:postcode":"02919",
    "addr:street":"Atwood Ave",
    "iso:country":"US",
    "sg:address":"931 Atwood Ave",
    "sg:city":"Johnston",
    "sg:classifiers":[
        {
            "category":"Education",
            "subcategory":"School",
            "type":"Public Place"
        }
    ],
    "sg:phone":"+1 401 944 2993",
    "sg:postcode":"02919",
    "sg:province":"RI",
    "sg:tags":[
        "religious"
    ],
    "wof:name":"St Rocco's School",
    "wof:placetype":"venue"
},
  "geometry": {"coordinates":[-71.483639,41.796553],"type":"Point"}
}