{
  "type": "Feature",
  "properties": {
    "iso:country":"US",
    "sg:address":"23 Canal St",
    "sg:city":"Westerly",
    "sg:classifiers":[
        {
            "category":"Restaurant",
            "type":"Food & Drink"
        }
    ],
    "sg:phone":"+1 401 596 4308",
    "sg:postcode":"02891",
    "sg:province":"RI",
    "wof:name":"Hilltop Cafe",
    "wof:placetype":"venue"
},
  "geometry": {"coordinates":[-71.83240499999999,41.383573],"type":"Point"}
}