{
  "type": "Feature",
  "properties": {
    "iso:country":"US",
    "sg:address":"1125 Green End Ave",
    "sg:city":"Middletown",
    "sg:classifiers":[
        {
            "category":"Local Transit",
            "type":"Transportation"
        }
    ],
    "sg:phone":"+1 401 846 7090",
    "sg:postcode":"02842",
    "sg:province":"RI",
    "sg:tags":[
        "passenger"
    ],
    "wof:name":"Moonlite Limousine",
    "wof:placetype":"venue"
},
  "geometry": {"coordinates":[-71.26114699999999,41.509503],"type":"Point"}
}