{
  "type": "Feature",
  "properties": {
    "iso:country":"US",
    "sg:address":"604 Charles St",
    "sg:city":"Providence",
    "sg:classifiers":[
        {
            "category":"Wholesale",
            "subcategory":"Painting Supplies",
            "type":"Manufacturing & Wholesale Goods"
        }
    ],
    "sg:phone":"+1 401 954 6195",
    "sg:postcode":"02904",
    "sg:province":"RI",
    "sg:tags":[
        "paint-wholesale",
        "manufacturer"
    ],
    "wof:name":"Jeffrey Guardiola Painting",
    "wof:placetype":"venue"
},
  "geometry": {"coordinates":[-71.42034099999999,41.852772],"type":"Point"}
}