{
  "type": "Feature",
  "properties": {
    "addr:full":"253 Pascoag Main St Pascoag RI 02859",
    "addr:housenumber":"253",
    "addr:postcode":"02859",
    "addr:street":"Pascoag Main St",
    "iso:country":"US",
    "sg:address":"253 Pascoag Main St",
    "sg:city":"Pascoag",
    "sg:classifiers":[
        {
            "category":"Utilities",
            "subcategory":"Water",
            "type":"Services"
        },
        {
            "category":"Utilities",
            "subcategory":"Electric",
            "type":"Services"
        }
    ],
    "sg:phone":"+1 401 568 6222",
    "sg:postcode":"02859",
    "sg:province":"RI",
    "sg:tags":[
        "company-utility",
        "system",
        "supply"
    ],
    "wof:name":"Water Division",
    "wof:placetype":"venue"
},
  "geometry": {"coordinates":[-71.701121,41.959291],"type":"Point"}
}