{
  "type": "Feature",
  "properties": {
    "addr:full":"622 Hatchery Rd North Kingstown RI 02852",
    "addr:housenumber":"622",
    "addr:postcode":"02852",
    "addr:street":"Hatchery Rd",
    "iso:country":"US",
    "sg:address":"622 Hatchery Rd",
    "sg:city":"North Kingstown",
    "sg:classifiers":[
        {
            "category":"Building & Trades",
            "subcategory":"Plumbing",
            "type":"Services"
        }
    ],
    "sg:phone":"+1 401 294 2268",
    "sg:postcode":"02852",
    "sg:province":"RI",
    "sg:tags":[
        "residential",
        "heating",
        "repair"
    ],
    "wof:name":"Howards Heating Service",
    "wof:placetype":"venue"
},
  "geometry": {"coordinates":[-71.511537,41.565383],"type":"Point"}
}