{
  "type": "Feature",
  "properties": {
    "iso:country":"US",
    "sg:address":"320 Hill St",
    "sg:city":"Coventry",
    "sg:classifiers":[
        {
            "category":"Professional",
            "type":"Services"
        }
    ],
    "sg:phone":"+1 401 826 8576",
    "sg:postcode":"02816",
    "sg:province":"RI",
    "wof:name":"Eric Tellier Jantech Svc",
    "wof:placetype":"venue"
},
  "geometry": {"coordinates":[-71.544667,41.719491],"type":"Point"}
}