{
  "type": "Feature",
  "properties": {
    "addr:full":"235 Central Ave Pawtucket RI 02860",
    "addr:housenumber":"235",
    "addr:postcode":"02860",
    "addr:street":"Central Ave",
    "iso:country":"US",
    "sg:address":"235 Central Ave",
    "sg:city":"Pawtucket",
    "sg:classifiers":[
        {
            "category":"Professional",
            "subcategory":"Secretarial Services",
            "type":"Services"
        }
    ],
    "sg:phone":"+1 401 726 0495",
    "sg:postcode":"02860",
    "sg:province":"RI",
    "sg:tags":[
        "reporting"
    ],
    "wof:name":"Busy Bee Bureau",
    "wof:placetype":"venue"
},
  "geometry": {"coordinates":[-71.372944,41.88421],"type":"Point"}
}