{
  "type": "Feature",
  "properties": {
    "addr:full":"294 Main St East Greenwich RI 02818",
    "addr:housenumber":"294",
    "addr:postcode":"02818",
    "addr:street":"Main St",
    "iso:country":"US",
    "sg:address":"294 Main St",
    "sg:city":"East Greenwich",
    "sg:classifiers":[
        {
            "category":"Professional",
            "subcategory":"Advertising",
            "type":"Services"
        }
    ],
    "sg:phone":"+1 401 541 9000",
    "sg:postcode":"02818",
    "sg:province":"RI",
    "sg:tags":[
        "counselor"
    ],
    "wof:name":"Walsh & Assoc",
    "wof:placetype":"venue"
},
  "geometry": {"coordinates":[-71.450096,41.659354],"type":"Point"}
}