{
  "type": "Feature",
  "properties": {
    "addr:full":"425 Quaker Ln West Warwick RI 02893",
    "addr:housenumber":"425",
    "addr:postcode":"02893",
    "addr:street":"Quaker Ln",
    "iso:country":"US",
    "sg:address":"425 Quaker Ln",
    "sg:city":"West Warwick",
    "sg:classifiers":[
        {
            "category":"Food & Beverages",
            "subcategory":"Groceries & Convenience Stores",
            "type":"Retail Goods"
        },
        {
            "category":"Autos & Motor Vehicles",
            "subcategory":"Fuel & Gas Station",
            "type":"Retail Goods"
        }
    ],
    "sg:phone":"+1 401 826 2880",
    "sg:postcode":"02893",
    "sg:province":"RI",
    "sg:tags":[
        "oil"
    ],
    "wof:name":"Sunoco A Plus",
    "wof:placetype":"venue"
},
  "geometry": {"coordinates":[-71.501093,41.687543],"type":"Point"}
}