{
  "type": "Feature",
  "properties": {
    "addr:full":"2 Barnes St Greenville RI 02828",
    "addr:housenumber":"2",
    "addr:postcode":"02828",
    "addr:street":"Barnes St",
    "iso:country":"US",
    "sg:address":"2 Barnes St",
    "sg:city":"Greenville",
    "sg:classifiers":[
        {
            "category":"Retail",
            "subcategory":"Auto Repair",
            "type":"Services"
        }
    ],
    "sg:phone":"+1 401 949 7347",
    "sg:postcode":"02828",
    "sg:province":"RI",
    "sg:tags":[
        "body"
    ],
    "wof:name":"RI Dentworks Inc",
    "wof:placetype":"venue"
},
  "geometry": {"coordinates":[-71.542542,41.87204],"type":"Point"}
}