{
  "type": "Feature",
  "properties": {
    "iso:country":"US",
    "sg:address":"61 Wine St",
    "sg:city":"Cranston",
    "sg:classifiers":[
        {
            "category":"Wholesale",
            "subcategory":"Machinery & Supplies",
            "type":"Manufacturing & Wholesale Goods"
        }
    ],
    "sg:phone":"+1 401 943 0856",
    "sg:postcode":"02920",
    "sg:province":"RI",
    "sg:tags":[
        "equipment",
        "establishment"
    ],
    "wof:name":"Fagundes Floor Coverng",
    "wof:placetype":"venue"
},
  "geometry": {"coordinates":[-71.47812399999999,41.769311],"type":"Point"}
}