{
  "type": "Feature",
  "properties": {
    "iso:country":"US",
    "sg:address":"94 Belmont Rd",
    "sg:city":"Cranston",
    "sg:classifiers":[
        {
            "category":"Shopping",
            "subcategory":"Pets & Pet Supplies",
            "type":"Retail Goods"
        }
    ],
    "sg:phone":"+1 401 837 4660",
    "sg:postcode":"02910",
    "sg:province":"RI",
    "sg:tags":[
        "furnishing",
        "dog",
        "store",
        "cat"
    ],
    "wof:name":"Pet Pals",
    "wof:placetype":"venue"
},
  "geometry": {"coordinates":[-71.433587,41.769433],"type":"Point"}
}