{
  "type": "Feature",
  "properties": {
    "iso:country":"US",
    "sg:address":"805 Park Ave",
    "sg:city":"Woonsocket",
    "sg:classifiers":[
        {
            "category":"Autos & Motor Vehicles",
            "subcategory":"Fuel & Gas Station",
            "type":"Retail Goods"
        }
    ],
    "sg:phone":"+1 401 765 1230",
    "sg:postcode":"02895",
    "sg:province":"RI",
    "sg:tags":[
        "station",
        "gasoline"
    ],
    "wof:name":"Sunoco",
    "wof:placetype":"venue"
},
  "geometry": {"coordinates":[-71.514483,41.992433],"type":"Point"}
}