{
  "type": "Feature",
  "properties": {
    "iso:country":"US",
    "sg:address":"737 Hope St",
    "sg:city":"Providence",
    "sg:classifiers":[
        {
            "category":"Personal",
            "subcategory":"Beauty Salon",
            "type":"Services"
        }
    ],
    "sg:phone":"+1 401 490 9299",
    "sg:postcode":"02906",
    "sg:province":"RI",
    "wof:name":"Padapsy Salon",
    "wof:placetype":"venue"
},
  "geometry": {"coordinates":[-71.39612,41.846541],"type":"Point"}
}