{
  "type": "Feature",
  "properties": {
    "iso:country":"US",
    "sg:address":"530 Wood St",
    "sg:city":"Bristol",
    "sg:classifiers":[
        {
            "category":"Real Estate",
            "subcategory":"Architect",
            "type":"Services"
        }
    ],
    "sg:phone":"+1 401 254 2032",
    "sg:postcode":"02809",
    "sg:province":"RI",
    "sg:tags":[
        "architectural"
    ],
    "wof:name":"Urban Design Group",
    "wof:placetype":"venue"
},
  "geometry": {"coordinates":[-71.272294,41.674392],"type":"Point"}
}