{
  "type": "Feature",
  "properties": {
    "addr:full":"267 Social St Woonsocket RI 02895",
    "addr:postcode":"02895",
    "addr:street":"Social St",
    "iso:country":"US",
    "sg:address":"267 Social St",
    "sg:city":"Woonsocket",
    "sg:classifiers":[
        {
            "category":"Personal",
            "type":"Services"
        }
    ],
    "sg:phone":"+1 401 765 3506",
    "sg:postcode":"02895",
    "sg:province":"RI",
    "wof:name":"Ultimate Rayz Tanning Spa Inc",
    "wof:placetype":"venue"
},
  "geometry": {"coordinates":[-71.50596299999999,42.008359],"type":"Point"}
}