{
  "type": "Feature",
  "properties": {
    "iso:country":"US",
    "sg:address":"28 Westerly Bradford Rd",
    "sg:city":"Westerly",
    "sg:classifiers":[
        {
            "category":"Retail",
            "subcategory":"Auto Repair",
            "type":"Services"
        }
    ],
    "sg:phone":"+1 401 596 2233",
    "sg:postcode":"02891",
    "sg:province":"RI",
    "sg:tags":[
        "repairing",
        "automobile"
    ],
    "wof:name":"G & G Auto Repair Svc",
    "wof:placetype":"venue"
},
  "geometry": {"coordinates":[-71.800589,41.384243],"type":"Point"}
}