{
  "type": "Feature",
  "properties": {
    "iso:country":"US",
    "sg:address":"59 W Warwick Ave",
    "sg:city":"West Warwick",
    "sg:classifiers":[
        {
            "category":"Organizations",
            "subcategory":"Religious Organization",
            "type":"Services"
        }
    ],
    "sg:phone":"+1 401 823 3800",
    "sg:postcode":"02893",
    "sg:province":"RI",
    "sg:tags":[
        "church"
    ],
    "wof:name":"Full Life Christian Fellowship",
    "wof:placetype":"venue"
},
  "geometry": {"coordinates":[-71.5261,41.695777],"type":"Point"}
}