{
  "type": "Feature",
  "properties": {
    "iso:country":"US",
    "sg:address":"34 Robin Hood Dr",
    "sg:city":"Riverside",
    "sg:classifiers":[
        {
            "category":"Wholesale",
            "subcategory":"Machinery & Supplies",
            "type":"Manufacturing & Wholesale Goods"
        }
    ],
    "sg:phone":"+1 401 270 1909",
    "sg:postcode":"02915",
    "sg:province":"RI",
    "wof:name":"Arrow Limousine",
    "wof:placetype":"venue"
},
  "geometry": {"coordinates":[-71.343097,41.766273],"type":"Point"}
}