{
  "type": "Feature",
  "properties": {
    "addr:full":"79 Vincent Way Cranston RI 02921",
    "addr:housenumber":"79",
    "addr:postcode":"02921",
    "addr:street":"Vincent Way",
    "iso:country":"US",
    "sg:address":"79 Vincent Way",
    "sg:city":"Cranston",
    "sg:classifiers":[
        {
            "category":"Professional",
            "subcategory":"Business Services",
            "type":"Services"
        }
    ],
    "sg:phone":"+1 401 943 0369",
    "sg:postcode":"02921",
    "sg:province":"RI",
    "wof:name":"PS &B Enterprises Inc",
    "wof:placetype":"venue"
},
  "geometry": {"coordinates":[-71.506612,41.764241],"type":"Point"}
}