{
  "type": "Feature",
  "properties": {
    "iso:country":"US",
    "sg:address":"21 Planet St",
    "sg:city":"Providence",
    "sg:classifiers":[
        {
            "category":"Communications",
            "type":"Services"
        }
    ],
    "sg:phone":"+1 401 831 2778",
    "sg:postcode":"02903",
    "sg:province":"RI",
    "sg:tags":[
        "web",
        "design"
    ],
    "wof:name":"Answer Pit",
    "wof:placetype":"venue"
},
  "geometry": {"coordinates":[-71.4058,41.823299],"type":"Point"}
}