{
  "type": "Feature",
  "properties": {
    "iso:country":"US",
    "sg:address":"1500 Broad St",
    "sg:city":"Providence",
    "sg:classifiers":[
        {
            "category":"Personal",
            "subcategory":"Beauty Salon",
            "type":"Services"
        }
    ],
    "sg:phone":"+1 401 461 4844",
    "sg:postcode":"02905",
    "sg:province":"RI",
    "sg:tags":[
        "shop"
    ],
    "wof:name":"Natural Nails",
    "wof:placetype":"venue"
},
  "geometry": {"coordinates":[-71.402039,41.786674],"type":"Point"}
}