{
  "type": "Feature",
  "properties": {
    "addr:full":"712 Oaklawn Ave Cranston RI 02920",
    "addr:housenumber":"712",
    "addr:postcode":"02920",
    "addr:street":"Oaklawn Ave",
    "iso:country":"US",
    "sg:address":"712 Oaklawn Ave",
    "sg:city":"Cranston",
    "sg:classifiers":[
        {
            "category":"Health Services",
            "subcategory":"Doctor",
            "type":"Services"
        }
    ],
    "sg:phone":"+1 401 944 6050",
    "sg:postcode":"02920",
    "sg:province":"RI",
    "sg:tags":[
        "dentist"
    ],
    "sg:website":"www.drbobdmd.com",
    "wof:name":"Robert C Impagliazzo DDS",
    "wof:placetype":"venue"
},
  "geometry": {"coordinates":[-71.476964,41.75349],"type":"Point"}
}