{
  "type": "Feature",
  "properties": {
    "addr:full":"1028 Boston Neck Rd North Kingstown RI 02852",
    "addr:housenumber":"1028",
    "addr:postcode":"02852",
    "addr:street":"Boston Neck Rd",
    "iso:country":"US",
    "sg:address":"1028 Boston Neck Rd",
    "sg:city":"North Kingstown",
    "sg:classifiers":[
        {
            "category":"Shopping",
            "subcategory":"Bicycles & Sporting Goods",
            "type":"Retail Goods"
        }
    ],
    "sg:phone":"+1 401 295 0642",
    "sg:postcode":"02852",
    "sg:province":"RI",
    "sg:tags":[
        "gun",
        "gunsmith"
    ],
    "wof:name":"Kane's Gun Shop",
    "wof:placetype":"venue"
},
  "geometry": {"coordinates":[-71.440983,41.54341],"type":"Point"}
}