{
  "type": "Feature",
  "properties": {
    "iso:country":"US",
    "sg:address":"331 Market St",
    "sg:city":"Warren",
    "sg:classifiers":[
        {
            "category":"Manufacturing",
            "subcategory":"Metals",
            "type":"Manufacturing & Wholesale Goods"
        }
    ],
    "sg:phone":"+1 401 247 1999",
    "sg:postcode":"02885",
    "sg:province":"RI",
    "sg:tags":[
        "product",
        "wire",
        "fabricated"
    ],
    "sg:website":"www.hanscominc.com",
    "wof:name":"Hanscom Inc",
    "wof:placetype":"venue"
},
  "geometry": {"coordinates":[-71.274368,41.73831],"type":"Point"}
}