{
  "type": "Feature",
  "properties": {
    "addr:full":"1 Meadowbrook Rd North Providence RI 02911",
    "addr:housenumber":"1",
    "addr:postcode":"02911",
    "addr:street":"Meadowbrook Rd",
    "iso:country":"US",
    "sg:address":"1 Meadowbrook Rd",
    "sg:city":"North Providence",
    "sg:classifiers":[
        {
            "category":"Real Estate",
            "subcategory":"Real Estate Agent",
            "type":"Services"
        }
    ],
    "sg:phone":"+1 401 353 0227",
    "sg:postcode":"02911",
    "sg:province":"RI",
    "sg:tags":[
        "rental"
    ],
    "wof:name":"Illiano Giuseppe",
    "wof:placetype":"venue"
},
  "geometry": {"coordinates":[-71.471588,41.845768],"type":"Point"}
}