{
  "type": "Feature",
  "properties": {
    "iso:country":"US",
    "sg:address":"306 Union Ave",
    "sg:city":"Providence",
    "sg:classifiers":[
        {
            "category":"Bars & Pubs",
            "type":"Food & Drink"
        }
    ],
    "sg:phone":"+1 401 944 0450",
    "sg:postcode":"02909",
    "sg:province":"RI",
    "sg:tags":[
        "drinking"
    ],
    "wof:name":"Union Avenue Pub",
    "wof:placetype":"venue"
},
  "geometry": {"coordinates":[-71.446226,41.807216],"type":"Point"}
}