{
  "type": "Feature",
  "properties": {
    "iso:country":"US",
    "sg:address":"1315 W Main Rd",
    "sg:city":"Middletown",
    "sg:classifiers":[
        {
            "category":"Home & Garden",
            "subcategory":"Home Furnishings",
            "type":"Retail Goods"
        }
    ],
    "sg:phone":"+1 401 847 0999",
    "sg:postcode":"02842",
    "sg:province":"RI",
    "sg:tags":[
        "linen"
    ],
    "wof:name":"Linens 'n Things",
    "wof:placetype":"venue"
},
  "geometry": {"coordinates":[-71.292579,41.534701],"type":"Point"}
}