{
  "type": "Feature",
  "properties": {
    "iso:country":"US",
    "sg:address":"19 Burnside St",
    "sg:city":"Bristol",
    "sg:classifiers":[
        {
            "category":"Wholesale",
            "subcategory":"Machinery & Supplies",
            "type":"Manufacturing & Wholesale Goods"
        }
    ],
    "sg:phone":"+1 401 253 9930",
    "sg:postcode":"02809",
    "sg:province":"RI",
    "sg:tags":[
        "equipment",
        "transportation"
    ],
    "wof:name":"Navinvest Marine Services USA",
    "wof:placetype":"venue"
},
  "geometry": {"coordinates":[-71.271478,41.663692],"type":"Point"}
}