{
  "type": "Feature",
  "properties": {
    "iso:country":"US",
    "sg:address":"194 Smith St",
    "sg:city":"Providence",
    "sg:classifiers":[
        {
            "category":"Organizations",
            "subcategory":"Labor Organization",
            "type":"Services"
        }
    ],
    "sg:phone":"+1 401 751 7100",
    "sg:postcode":"02908",
    "sg:province":"RI",
    "wof:name":"Rhode Island A F L-C I O",
    "wof:placetype":"venue"
},
  "geometry": {"coordinates":[-71.41764999999999,41.831955],"type":"Point"}
}