{
  "type": "Feature",
  "properties": {
    "addr:full":"15 Eton Rd Barrington RI 02806",
    "addr:housenumber":"15",
    "addr:postcode":"02806",
    "addr:street":"Eton Rd",
    "iso:country":"US",
    "sg:address":"15 Eton Rd",
    "sg:city":"Barrington",
    "sg:classifiers":[
        {
            "category":"Banks & Credit Unions",
            "subcategory":"Financial Services",
            "type":"Services"
        }
    ],
    "sg:phone":"+1 401 245 6209",
    "sg:postcode":"02806",
    "sg:province":"RI",
    "sg:tags":[
        "management",
        "investment"
    ],
    "wof:name":"The Barrington Land Conservation Trust Inc",
    "wof:placetype":"venue"
},
  "geometry": {"coordinates":[-71.303764,41.739561],"type":"Point"}
}