{
  "type": "Feature",
  "properties": {
    "iso:country":"US",
    "sg:address":"258 Rockland Rd",
    "sg:city":"North Scituate",
    "sg:classifiers":[
        {
            "category":"Personal",
            "type":"Services"
        }
    ],
    "sg:phone":"+1 401 647 9016",
    "sg:postcode":"02857",
    "sg:province":"RI",
    "wof:name":"New Way Home Service",
    "wof:placetype":"venue"
},
  "geometry": {"coordinates":[-71.625502,41.818737],"type":"Point"}
}