{
  "type": "Feature",
  "properties": {
    "iso:country":"US",
    "sg:address":"310 Maple Ave",
    "sg:city":"Barrington",
    "sg:classifiers":[
        {
            "category":"Social Services",
            "type":"Services"
        }
    ],
    "sg:phone":"+1 401 245 7900",
    "sg:postcode":"02806",
    "sg:province":"RI",
    "sg:tags":[
        "organization",
        "welfare"
    ],
    "wof:name":"Oceanstate Community Resources",
    "wof:placetype":"venue"
},
  "geometry": {"coordinates":[-71.318505,41.738828],"type":"Point"}
}