{
  "type": "Feature",
  "properties": {
    "iso:country":"US",
    "sg:address":"6 Carriage Ln",
    "sg:city":"Kingston",
    "sg:classifiers":[
        {
            "category":"Education",
            "subcategory":"College",
            "type":"Public Place"
        }
    ],
    "sg:phone":"+1 401 874 5016",
    "sg:postcode":"02881",
    "sg:province":"RI",
    "sg:tags":[
        "medical"
    ],
    "wof:name":"Pharmacy Practice",
    "wof:placetype":"venue"
},
  "geometry": {"coordinates":[-71.51918000000001,41.486129],"type":"Point"}
}