{
  "type": "Feature",
  "properties": {
    "iso:country":"US",
    "sg:address":"1 Maritime Dr",
    "sg:city":"Portsmouth",
    "sg:classifiers":[
        {
            "category":"Autos & Motor Vehicles",
            "subcategory":"Boat Sales",
            "type":"Retail Goods"
        }
    ],
    "sg:phone":"+1 401 683 5858",
    "sg:postcode":"02813",
    "sg:province":"RI",
    "sg:tags":[
        "top",
        "upholstery",
        "cover"
    ],
    "sg:website":"www.ssfabricproducts.com",
    "wof:name":"S & S Fabric Products",
    "wof:placetype":"venue"
},
  "geometry": {"coordinates":[-71.634636,41.381023],"type":"Point"}
}