{
  "type": "Feature",
  "properties": {
    "iso:country":"US",
    "sg:address":"64 Olney Arnold Rd",
    "sg:city":"Cranston",
    "sg:classifiers":[
        {
            "category":"Professional",
            "subcategory":"Accounting & Tax Preparation",
            "type":"Services"
        }
    ],
    "sg:phone":"+1 401 942 9964",
    "sg:postcode":"02921",
    "sg:province":"RI",
    "sg:tags":[
        "transmission",
        "return"
    ],
    "wof:name":"Taxes By Harry",
    "wof:placetype":"venue"
},
  "geometry": {"coordinates":[-71.495394,41.757833],"type":"Point"}
}