{
  "type": "Feature",
  "properties": {
    "iso:country":"US",
    "sg:address":"169 Mill St",
    "sg:city":"Cranston",
    "sg:classifiers":[
        {
            "category":"Wholesale",
            "subcategory":"Sporting Goods",
            "type":"Manufacturing & Wholesale Goods"
        }
    ],
    "sg:phone":"+1 401 461 1999",
    "sg:postcode":"02905",
    "sg:province":"RI",
    "sg:tags":[
        "equipment",
        "golf",
        "supply"
    ],
    "wof:name":"Swing Fitness Products",
    "wof:placetype":"venue"
},
  "geometry": {"coordinates":[-71.41266299999999,41.768471],"type":"Point"}
}