{
  "type": "Feature",
  "properties": {
    "iso:country":"US",
    "sg:address":"580 Metacom Ave",
    "sg:city":"Bristol",
    "sg:classifiers":[
        {
            "category":"Health Services",
            "subcategory":"Health Practitioner",
            "type":"Services"
        }
    ],
    "sg:phone":"+1 401 253 0095",
    "sg:postcode":"02809",
    "sg:province":"RI",
    "wof:name":"Hands-On-Therapy",
    "wof:placetype":"venue"
},
  "geometry": {"coordinates":[-71.26340500000001,41.69377],"type":"Point"}
}