{
  "type": "Feature",
  "properties": {
    "iso:country":"US",
    "sg:address":"146 Aquidneck Ave",
    "sg:city":"Middletown",
    "sg:classifiers":[
        {
            "category":"Restaurant",
            "type":"Food & Drink"
        }
    ],
    "sg:phone":"+1 401 846 8411",
    "sg:postcode":"02842",
    "sg:province":"RI",
    "wof:name":"Gerturde's Gallery",
    "wof:placetype":"venue"
},
  "geometry": {"coordinates":[-71.284469,41.493877],"type":"Point"}
}