{
  "type": "Feature",
  "properties": {
    "iso:country":"US",
    "sg:address":"38 High St",
    "sg:city":"Westerly",
    "sg:classifiers":[
        {
            "category":"Shopping",
            "subcategory":"Clothing, Apparel, & Fashions",
            "type":"Retail Goods"
        }
    ],
    "sg:phone":"+1 401 596 4144",
    "sg:postcode":"02891",
    "sg:province":"RI",
    "wof:name":"Kisses",
    "wof:placetype":"venue"
},
  "geometry": {"coordinates":[-71.830169,41.378691],"type":"Point"}
}