{
  "type": "Feature",
  "properties": {
    "iso:country":"US",
    "sg:address":"685 Admiral St",
    "sg:city":"Providence",
    "sg:classifiers":[
        {
            "category":"Bakery",
            "type":"Food & Drink"
        }
    ],
    "sg:phone":"+1 401 228 0081",
    "sg:postcode":"02908",
    "sg:province":"RI",
    "wof:name":"Lasalle Bakery",
    "wof:placetype":"venue"
},
  "geometry": {"coordinates":[-71.439201,41.849201],"type":"Point"}
}