{
  "type": "Feature",
  "properties": {
    "iso:country":"US",
    "sg:address":"116 Holland Dr",
    "sg:city":"Wakefield",
    "sg:classifiers":[
        {
            "category":"Building & Trades",
            "subcategory":"Electrical",
            "type":"Services"
        }
    ],
    "sg:phone":"+1 401 789 1840",
    "sg:postcode":"02879",
    "sg:province":"RI",
    "sg:tags":[
        "electrical",
        "contractor"
    ],
    "wof:name":"PAV Electric",
    "wof:placetype":"venue"
},
  "geometry": {"coordinates":[-71.473077,41.444033],"type":"Point"}
}