{
  "type": "Feature",
  "properties": {
    "iso:country":"US",
    "sg:address":"71 Oak St",
    "sg:city":"Ashaway",
    "sg:classifiers":[
        {
            "category":"Building & Trades",
            "subcategory":"Landscaping Services",
            "type":"Services"
        }
    ],
    "sg:phone":"+1 401 315 0429",
    "sg:postcode":"02804",
    "sg:province":"RI",
    "wof:name":"Honey Do Services",
    "wof:placetype":"venue"
},
  "geometry": {"coordinates":[-71.78034,41.412069],"type":"Point"}
}