{
  "type": "Feature",
  "properties": {
    "addr:full":"15 America St Cumberland RI 02864",
    "addr:housenumber":"15",
    "addr:postcode":"02864",
    "addr:street":"America St",
    "iso:country":"US",
    "sg:address":"15 America St",
    "sg:city":"Cumberland",
    "sg:classifiers":[
        {
            "category":"Banks & Credit Unions",
            "subcategory":"Investment Brokerage",
            "type":"Services"
        }
    ],
    "sg:phone":"+1 401 658 5600",
    "sg:postcode":"02864",
    "sg:province":"RI",
    "sg:tags":[
        "security"
    ],
    "wof:name":"SunAmerica",
    "wof:placetype":"venue"
},
  "geometry": {"coordinates":[-71.386745,41.901429],"type":"Point"}
}