{
  "type": "Feature",
  "properties": {
    "addr:full":"19 Saint James Rd Narragansett RI 02882",
    "addr:housenumber":"19",
    "addr:postcode":"02882",
    "addr:street":"Saint James Rd",
    "iso:country":"US",
    "sg:address":"19 Saint James Rd",
    "sg:city":"Narragansett",
    "sg:classifiers":[
        {
            "category":"Health Services",
            "subcategory":"Doctor",
            "type":"Services"
        }
    ],
    "sg:phone":"+1 401 783 3200",
    "sg:postcode":"02882",
    "sg:province":"RI",
    "sg:tags":[
        "medical"
    ],
    "wof:name":"Thomas McCauley",
    "wof:placetype":"venue"
},
  "geometry": {"coordinates":[-71.477732,41.388969],"type":"Point"}
}