{
  "type": "Feature",
  "properties": {
    "iso:country":"US",
    "sg:address":"4 Frank Ave",
    "sg:city":"West Kingston",
    "sg:classifiers":[
        {
            "category":"Building & Trades",
            "subcategory":"Construction",
            "type":"Services"
        }
    ],
    "sg:phone":"+1 401 792 9799",
    "sg:postcode":"02892",
    "sg:province":"RI",
    "sg:tags":[
        "general",
        "contractor"
    ],
    "wof:name":"Davitt Design Build Inc",
    "wof:placetype":"venue"
},
  "geometry": {"coordinates":[-71.55826399999999,41.484932],"type":"Point"}
}