{
  "type": "Feature",
  "properties": {
    "iso:country":"US",
    "sg:address":"83 Waterman Ave",
    "sg:city":"Johnston",
    "sg:classifiers":[
        {
            "category":"Social Services",
            "subcategory":"Child Care",
            "type":"Services"
        }
    ],
    "sg:phone":"+1 401 349 0711",
    "sg:postcode":"02919",
    "sg:province":"RI",
    "sg:tags":[
        "day"
    ],
    "wof:name":"Little Angels Daycare Inc",
    "wof:placetype":"venue"
},
  "geometry": {"coordinates":[-71.478938,41.833726],"type":"Point"}
}