{
  "type": "Feature",
  "properties": {
    "iso:country":"US",
    "sg:address":"25 Old Beach Rd",
    "sg:city":"Newport",
    "sg:classifiers":[
        {
            "category":"Restaurant",
            "type":"Food & Drink"
        }
    ],
    "sg:phone":"+1 401 848 2579",
    "sg:postcode":"02840",
    "sg:province":"RI",
    "sg:tags":[
        "eating"
    ],
    "wof:name":"Blue Plate Diner Inc",
    "wof:placetype":"venue"
},
  "geometry": {"coordinates":[-71.30658699999999,41.48655],"type":"Point"}
}