{
  "type": "Feature",
  "properties": {
    "iso:country":"US",
    "sg:address":"375 Metacom Ave",
    "sg:city":"Bristol",
    "sg:classifiers":[
        {
            "category":"Health Services",
            "subcategory":"Doctor",
            "type":"Services"
        },
        {
            "category":"Health Services",
            "subcategory":"Health Practitioner",
            "type":"Services"
        }
    ],
    "sg:phone":"+1 401 253 3900",
    "sg:postcode":"02809",
    "sg:province":"RI",
    "sg:tags":[
        "physician",
        "surgeon",
        "surgeons",
        "ophthalmology"
    ],
    "wof:name":"Dominick Zangari Jr Md Inc",
    "wof:placetype":"venue"
},
  "geometry": {"coordinates":[-71.25973500000001,41.676813],"type":"Point"}
}