{
  "type": "Feature",
  "properties": {
    "iso:country":"US",
    "sg:address":"150 Exchange St",
    "sg:city":"Pawtucket",
    "sg:classifiers":[
        {
            "category":"Education",
            "subcategory":"School",
            "type":"Public Place"
        }
    ],
    "sg:phone":"+1 401 729 6400",
    "sg:postcode":"02860",
    "sg:province":"RI",
    "wof:name":"Tolman High School",
    "wof:placetype":"venue"
},
  "geometry": {"coordinates":[-71.380678,41.879848],"type":"Point"}
}