{
  "type": "Feature",
  "properties": {
    "addr:full":"62 Alfred Stone Rd Providence RI 02906",
    "addr:housenumber":"62",
    "addr:postcode":"02906",
    "addr:street":"Alfred Stone Rd",
    "iso:country":"US",
    "sg:address":"62 Alfred Stone Rd",
    "sg:city":"Providence",
    "sg:classifiers":[
        {
            "category":"Professional",
            "subcategory":"Management & Consulting",
            "type":"Services"
        }
    ],
    "sg:phone":"+1 401 521 2052",
    "sg:postcode":"02906",
    "sg:province":"RI",
    "sg:tags":[
        "educational"
    ],
    "wof:name":"Joseph L Costa",
    "wof:placetype":"venue"
},
  "geometry": {"coordinates":[-71.389894,41.856383],"type":"Point"}
}