{
  "type": "Feature",
  "properties": {
    "iso:country":"US",
    "sg:address":"720 Central Ave",
    "sg:city":"Pawtucket",
    "sg:classifiers":[
        {
            "category":"Insurance",
            "subcategory":"Insurance Agent",
            "type":"Services"
        }
    ],
    "sg:phone":"+1 401 728 8686",
    "sg:postcode":"02861",
    "sg:province":"RI",
    "wof:name":"Allstate Insurance Co",
    "wof:placetype":"venue"
},
  "geometry": {"coordinates":[-71.35543800000001,41.887678],"type":"Point"}
}