{
  "type": "Feature",
  "properties": {
    "iso:country":"US",
    "sg:address":"2701 E Main Rd",
    "sg:city":"Portsmouth",
    "sg:classifiers":[
        {
            "category":"Retail",
            "subcategory":"Portrait Studio",
            "type":"Services"
        }
    ],
    "sg:phone":"+1 401 683 3754",
    "sg:postcode":"02871",
    "sg:province":"RI",
    "sg:tags":[
        "photographer"
    ],
    "sg:website":"www.armorandmartelphoto.com",
    "wof:name":"Armor & Martel Photography",
    "wof:placetype":"venue"
},
  "geometry": {"coordinates":[-71.247665,41.602483],"type":"Point"}
}