{
  "type": "Feature",
  "properties": {
    "iso:country":"US",
    "sg:address":"110 Main St",
    "sg:city":"East Greenwich",
    "sg:classifiers":[
        {
            "category":"Shopping",
            "subcategory":"Clothing, Apparel, & Fashions",
            "type":"Retail Goods"
        }
    ],
    "sg:phone":"+1 401 886 0885",
    "sg:postcode":"02818",
    "sg:province":"RI",
    "wof:name":"Bridal Garden",
    "wof:placetype":"venue"
},
  "geometry": {"coordinates":[-71.449972,41.662569],"type":"Point"}
}