{
  "type": "Feature",
  "properties": {
    "iso:country":"US",
    "sg:address":"213 Robinson St",
    "sg:city":"South Kingstown",
    "sg:classifiers":[
        {
            "category":"Real Estate",
            "subcategory":"Real Estate Agent",
            "type":"Services"
        }
    ],
    "sg:phone":"+1 401 792 7095",
    "sg:postcode":"02879",
    "sg:province":"RI",
    "wof:name":"Eclectibles",
    "wof:placetype":"venue"
},
  "geometry": {"coordinates":[-71.49758199999999,41.438692],"type":"Point"}
}