{
  "type": "Feature",
  "properties": {
    "iso:country":"US",
    "sg:address":"365 Bungy Rd",
    "sg:city":"North Scituate",
    "sg:classifiers":[
        {
            "category":"Manufacturing",
            "subcategory":"Retail Goods",
            "type":"Manufacturing & Wholesale Goods"
        }
    ],
    "sg:phone":"+1 401 647 2940",
    "sg:postcode":"02857",
    "sg:province":"RI",
    "sg:tags":[
        "product",
        "mfg"
    ],
    "wof:name":"Combined Industries Inc",
    "wof:placetype":"venue"
},
  "geometry": {"coordinates":[-71.66814599999999,41.848751],"type":"Point"}
}