{
  "type": "Feature",
  "properties": {
    "addr:full":"45 Baker St Providence RI 02905",
    "addr:housenumber":"45",
    "addr:postcode":"02905",
    "addr:street":"Baker St",
    "iso:country":"US",
    "sg:address":"45 Baker St",
    "sg:city":"Providence",
    "sg:classifiers":[
        {
            "category":"Manufacturing",
            "subcategory":"Jewelry",
            "type":"Manufacturing & Wholesale Goods"
        }
    ],
    "sg:phone":"+1 401 467 3420",
    "sg:postcode":"02905",
    "sg:province":"RI",
    "sg:tags":[
        "costume",
        "mfg"
    ],
    "wof:name":"Argonne Jewelry Co Inc",
    "wof:placetype":"venue"
},
  "geometry": {"coordinates":[-71.399539,41.793588],"type":"Point"}
}