{
  "type": "Feature",
  "properties": {
    "iso:country":"US",
    "sg:address":"149 Danielson Pike",
    "sg:city":"Foster",
    "sg:classifiers":[
        {
            "category":"Building & Trades",
            "subcategory":"Electrical",
            "type":"Services"
        }
    ],
    "sg:phone":"+1 401 647 3355",
    "sg:postcode":"02825",
    "sg:province":"RI",
    "sg:tags":[
        "work",
        "electrical"
    ],
    "wof:name":"Martucci Electric Company",
    "wof:placetype":"venue"
},
  "geometry": {"coordinates":[-71.762097,41.808703],"type":"Point"}
}