{
  "type": "Feature",
  "properties": {
    "iso:country":"US",
    "sg:address":"40 Cole St",
    "sg:city":"Warren",
    "sg:classifiers":[
        {
            "category":"Personal",
            "subcategory":"Beauty Salon",
            "type":"Services"
        }
    ],
    "sg:phone":"+1 401 245 5575",
    "sg:postcode":"02885",
    "sg:province":"RI",
    "wof:name":"Salon At 40",
    "wof:placetype":"venue"
},
  "geometry": {"coordinates":[-71.280163,41.729019],"type":"Point"}
}