{
  "type": "Feature",
  "properties": {
    "iso:country":"US",
    "sg:address":"58 Cardinal Dr",
    "sg:city":"North Kingstown",
    "sg:classifiers":[
        {
            "category":"Real Estate",
            "subcategory":"Real Estate Agent",
            "type":"Services"
        }
    ],
    "sg:phone":"+1 401 667 2706",
    "sg:postcode":"02852",
    "sg:province":"RI",
    "sg:tags":[
        "appraiser"
    ],
    "wof:name":"Appraisal Dynamics",
    "wof:placetype":"venue"
},
  "geometry": {"coordinates":[-71.483018,41.543299],"type":"Point"}
}