{
  "type": "Feature",
  "properties": {
    "iso:country":"US",
    "sg:address":"101 Main St",
    "sg:city":"Pawtucket",
    "sg:classifiers":[
        {
            "category":"Education",
            "subcategory":"School",
            "type":"Public Place"
        }
    ],
    "sg:phone":"+1 401 726 3804",
    "sg:postcode":"02860",
    "sg:province":"RI",
    "wof:name":"Academic Enterprises",
    "wof:placetype":"venue"
},
  "geometry": {"coordinates":[-71.382071,41.875759],"type":"Point"}
}