{
  "type": "Feature",
  "properties": {
    "addr:full":"5668 Post Rd Charlestown RI 02813",
    "addr:housenumber":"5668",
    "addr:postcode":"02813",
    "addr:street":"Post Rd",
    "iso:country":"US",
    "sg:address":"5668 Post Rd",
    "sg:city":"Charlestown",
    "sg:classifiers":[
        {
            "category":"Retail",
            "subcategory":"Veterinary Services",
            "type":"Services"
        }
    ],
    "sg:phone":"+1 401 322 1420",
    "sg:postcode":"02813",
    "sg:province":"RI",
    "sg:tags":[
        "veterinarian"
    ],
    "wof:name":"Dunn J Lawrence Dr",
    "wof:placetype":"venue"
},
  "geometry": {"coordinates":[-71.70617900000001,41.356089],"type":"Point"}
}