{
  "type": "Feature",
  "properties": {
    "iso:country":"US",
    "sg:address":"1201 New London Ave",
    "sg:city":"Cranston",
    "sg:classifiers":[
        {
            "category":"Restaurant",
            "type":"Food & Drink"
        }
    ],
    "sg:menulink":"http://www.allmenus.com/ri/cranston/53987-ninety-nine-99-restaurant/menu/",
    "sg:phone":"+1 401 463 9993",
    "sg:postcode":"02920",
    "sg:province":"RI",
    "sg:tags":[
        "american"
    ],
    "wof:name":"Ninety Nine (99) Restaurant",
    "wof:placetype":"venue"
},
  "geometry": {"coordinates":[-71.481798,41.73541],"type":"Point"}
}