{
  "type": "Feature",
  "properties": {
    "iso:country":"US",
    "sg:address":"55 Bradford St Ste 203",
    "sg:city":"Providence",
    "sg:classifiers":[
        {
            "category":"Professional",
            "subcategory":"Lawyer & Legal Services",
            "type":"Services"
        }
    ],
    "sg:phone":"+1 401 621 8600",
    "sg:postcode":"02903",
    "sg:province":"RI",
    "wof:name":"Caron Robt J Atty",
    "wof:placetype":"venue"
},
  "geometry": {"coordinates":[-71.42179899999999,41.823601],"type":"Point"}
}