{
  "type": "Feature",
  "properties": {
    "iso:country":"US",
    "sg:address":"9 New London Ave",
    "sg:city":"Cranston",
    "sg:classifiers":[
        {
            "category":"Banks & Credit Unions",
            "subcategory":"Bank",
            "type":"Services"
        }
    ],
    "sg:phone":"+1 401 275 1700",
    "sg:postcode":"02920",
    "sg:province":"RI",
    "wof:name":"Washington Mutual",
    "wof:placetype":"venue"
},
  "geometry": {"coordinates":[-71.459619,41.761421],"type":"Point"}
}