{
  "type": "Feature",
  "properties": {
    "addr:full":"8 Sycamore Dr Coventry RI 02816",
    "addr:housenumber":"8",
    "addr:postcode":"02816",
    "addr:street":"Sycamore Dr",
    "iso:country":"US",
    "sg:address":"8 Sycamore Dr",
    "sg:city":"Coventry",
    "sg:classifiers":[
        {
            "category":"Professional",
            "subcategory":"Detective & Security Services",
            "type":"Services"
        }
    ],
    "sg:phone":"+1 401 397 1862",
    "sg:postcode":"02816",
    "sg:province":"RI",
    "sg:tags":[
        "car"
    ],
    "wof:name":"Investigative Information Svcs",
    "wof:placetype":"venue"
},
  "geometry": {"coordinates":[-71.577585,41.661865],"type":"Point"}
}