{
  "type": "Feature",
  "properties": {
    "addr:full":"27 Smithfield Rd Providence RI 02904",
    "addr:housenumber":"27",
    "addr:postcode":"02904",
    "addr:street":"Smithfield Rd",
    "iso:country":"US",
    "sg:address":"27 Smithfield Rd",
    "sg:city":"Providence",
    "sg:classifiers":[
        {
            "category":"Shopping",
            "subcategory":"Hobbies, Toys, & Games",
            "type":"Retail Goods"
        }
    ],
    "sg:phone":"+1 401 353 1381",
    "sg:postcode":"02904",
    "sg:province":"RI",
    "sg:tags":[
        "store"
    ],
    "wof:name":"Kb Toy Works",
    "wof:placetype":"venue"
},
  "geometry": {"coordinates":[-71.448071,41.855769],"type":"Point"}
}