{
  "type": "Feature",
  "properties": {
    "iso:country":"US",
    "sg:address":"2419 Hartford Ave",
    "sg:city":"Johnston",
    "sg:classifiers":[
        {
            "category":"Communications",
            "type":"Services"
        }
    ],
    "sg:phone":"+1 401 934 1600",
    "sg:postcode":"02919",
    "sg:province":"RI",
    "wof:name":"ACN Academic Communications",
    "wof:placetype":"venue"
},
  "geometry": {"coordinates":[-71.539654,41.829928],"type":"Point"}
}