{
  "type": "Feature",
  "properties": {
    "addr:full":"5 W Main Rd Little Compton RI 02837",
    "addr:housenumber":"5",
    "addr:postcode":"02837",
    "addr:street":"W Main Rd",
    "iso:country":"US",
    "sg:address":"5 W Main Rd",
    "sg:city":"Little Compton",
    "sg:classifiers":[
        {
            "category":"Building & Trades",
            "subcategory":"Construction",
            "type":"Services"
        }
    ],
    "sg:phone":"+1 401 635 4653",
    "sg:postcode":"02837",
    "sg:province":"RI",
    "sg:tags":[
        "house"
    ],
    "wof:name":"Scd Fine Home Bldg",
    "wof:placetype":"venue"
},
  "geometry": {"coordinates":[-71.197355,41.547879],"type":"Point"}
}