{
  "type": "Feature",
  "properties": {
    "iso:country":"US",
    "sg:address":"518 Thames St",
    "sg:city":"Newport",
    "sg:classifiers":[
        {
            "category":"Shopping",
            "type":"Retail Goods"
        }
    ],
    "sg:phone":"+1 401 619 1930",
    "sg:postcode":"02840",
    "sg:province":"RI",
    "sg:tags":[
        "art",
        "gallery",
        "dealer"
    ],
    "wof:name":"Montanaro Gallery",
    "wof:placetype":"venue"
},
  "geometry": {"coordinates":[-71.314216,41.478998],"type":"Point"}
}