{
  "type": "Feature",
  "properties": {
    "iso:country":"US",
    "sg:address":"6 Haversham Rd",
    "sg:city":"Westerly",
    "sg:classifiers":[
        {
            "category":"Building & Trades",
            "subcategory":"Construction",
            "type":"Services"
        }
    ],
    "sg:phone":"+1 401 322 1055",
    "sg:postcode":"02891",
    "sg:province":"RI",
    "sg:tags":[
        "home",
        "builder"
    ],
    "wof:name":"Smart Wired Homes Inc",
    "wof:placetype":"venue"
},
  "geometry": {"coordinates":[-71.75,41.342506],"type":"Point"}
}