{
  "type": "Feature",
  "properties": {
    "iso:country":"US",
    "sg:address":"54 Vermont Ave",
    "sg:city":"Warwick",
    "sg:classifiers":[
        {
            "category":"Professional",
            "subcategory":"Engineering",
            "type":"Services"
        }
    ],
    "sg:phone":"+1 401 734 4444",
    "sg:postcode":"02888",
    "sg:province":"RI",
    "sg:tags":[
        "engineer"
    ],
    "wof:name":"ERA Engineering",
    "wof:placetype":"venue"
},
  "geometry": {"coordinates":[-71.439894,41.739579],"type":"Point"}
}