{
  "type": "Feature",
  "properties": {
    "addr:full":"553 Hope St Bristol RI 02809",
    "addr:housenumber":"553",
    "addr:postcode":"02809",
    "addr:street":"Hope St",
    "iso:country":"US",
    "sg:address":"553 Hope St",
    "sg:city":"Bristol",
    "sg:classifiers":[
        {
            "category":"Restaurant",
            "type":"Food & Drink"
        }
    ],
    "sg:phone":"+1 401 253 9828",
    "sg:postcode":"02809",
    "sg:province":"RI",
    "wof:name":"Ozzie's Family Restaurant",
    "wof:placetype":"venue"
},
  "geometry": {"coordinates":[-71.277101,41.6716],"type":"Point"}
}