{
  "type": "Feature",
  "properties": {
    "iso:country":"US",
    "sg:address":"189 Wood St",
    "sg:city":"Bristol",
    "sg:classifiers":[
        {
            "category":"Restaurant",
            "type":"Food & Drink"
        }
    ],
    "sg:phone":"+1 401 396 9258",
    "sg:postcode":"02809",
    "sg:province":"RI",
    "sg:tags":[
        "caterer"
    ],
    "wof:name":"Sophie's Kitchen",
    "wof:placetype":"venue"
},
  "geometry": {"coordinates":[-71.26920200000001,41.665869],"type":"Point"}
}