{
  "type": "Feature",
  "properties": {
    "iso:country":"US",
    "sg:address":"406 Broadway",
    "sg:city":"Pawtucket",
    "sg:classifiers":[
        {
            "category":"Retail",
            "subcategory":"Car Wash",
            "type":"Services"
        }
    ],
    "sg:phone":"+1 401 729 5325",
    "sg:postcode":"02860",
    "sg:province":"RI",
    "sg:tags":[
        "polishing",
        "washing"
    ],
    "wof:name":"Super Clean Car Wash",
    "wof:placetype":"venue"
},
  "geometry": {"coordinates":[-71.376099,41.884602],"type":"Point"}
}