{
  "type": "Feature",
  "properties": {
    "addr:full":"130 Pascoag Main St Pascoag RI 02859",
    "addr:housenumber":"130",
    "addr:postcode":"02859",
    "addr:street":"Pascoag Main St",
    "iso:country":"US",
    "sg:address":"130 Pascoag Main St",
    "sg:city":"Pascoag",
    "sg:classifiers":[
        {
            "category":"Restaurant",
            "type":"Food & Drink"
        }
    ],
    "sg:phone":"+1 401 568 3077",
    "sg:postcode":"02859",
    "sg:province":"RI",
    "sg:website":"www.subway.com",
    "wof:name":"Subway Sandwiches & Salads",
    "wof:placetype":"venue"
},
  "geometry": {"coordinates":[-71.701469,41.958559],"type":"Point"}
}