{
  "type": "Feature",
  "properties": {
    "iso:country":"US",
    "sg:address":"1075 Park Ave",
    "sg:city":"Woonsocket",
    "sg:classifiers":[
        {
            "category":"Retail",
            "subcategory":"Laundry & Dry Cleaning",
            "type":"Services"
        },
        {
            "category":"Home & Garden",
            "subcategory":"Carpets & Floor Coverings",
            "type":"Retail Goods"
        }
    ],
    "sg:phone":"+1 401 769 2221",
    "sg:postcode":"02895",
    "sg:province":"RI",
    "sg:tags":[
        "installs",
        "cleaners",
        "rug"
    ],
    "wof:name":"Canavans Floor Covering Inc",
    "wof:placetype":"venue"
},
  "geometry": {"coordinates":[-71.515237,41.988748],"type":"Point"}
}