{
  "type": "Feature",
  "properties": {
    "iso:country":"US",
    "sg:address":"572 Tiogue Ave",
    "sg:city":"Coventry",
    "sg:classifiers":[
        {
            "category":"Shopping",
            "subcategory":"Hobbies, Toys, & Games",
            "type":"Retail Goods"
        }
    ],
    "sg:phone":"+1 401 615 3831",
    "sg:postcode":"02816",
    "sg:province":"RI",
    "sg:tags":[
        "craft"
    ],
    "wof:name":"Scrappers Discount",
    "wof:placetype":"venue"
},
  "geometry": {"coordinates":[-71.54841,41.685136],"type":"Point"}
}