{
  "type": "Feature",
  "properties": {
    "iso:country":"US",
    "sg:address":"2346 Post Rd",
    "sg:city":"Warwick",
    "sg:classifiers":[
        {
            "category":"Professional",
            "subcategory":"Management & Consulting",
            "type":"Services"
        }
    ],
    "sg:phone":"+1 401 732 4350",
    "sg:postcode":"02886",
    "sg:province":"RI",
    "sg:tags":[
        "consultant",
        "business"
    ],
    "sg:website":"www.copleycg.com",
    "wof:name":"Copley Consulting Group",
    "wof:placetype":"venue"
},
  "geometry": {"coordinates":[-71.443347,41.718736],"type":"Point"}
}