{
  "type": "Feature",
  "properties": {
    "addr:full":"6 Cindy Ln Coventry RI 02816",
    "addr:housenumber":"6",
    "addr:postcode":"02816",
    "addr:street":"Cindy Ln",
    "iso:country":"US",
    "sg:address":"6 Cindy Ln",
    "sg:city":"Coventry",
    "sg:classifiers":[
        {
            "category":"Organizations",
            "subcategory":"Religious Organization",
            "type":"Services"
        }
    ],
    "sg:phone":"+1 401 821 8719",
    "sg:postcode":"02816",
    "sg:province":"RI",
    "sg:tags":[
        "school"
    ],
    "wof:name":"St Xavier Academy",
    "wof:placetype":"venue"
},
  "geometry": {"coordinates":[-71.555572,41.696467],"type":"Point"}
}