{
  "type": "Feature",
  "properties": {
    "iso:country":"US",
    "sg:address":"172 Washington St",
    "sg:city":"Warwick",
    "sg:classifiers":[
        {
            "category":"Organizations",
            "subcategory":"Professional Association",
            "type":"Services"
        },
        {
            "category":"Organizations",
            "subcategory":"Community Association",
            "type":"Services"
        }
    ],
    "sg:phone":"+1 401 467 8940",
    "sg:postcode":"02888",
    "sg:province":"RI",
    "sg:tags":[
        "military"
    ],
    "wof:name":"Veterans Foreign Wars Post 183",
    "wof:placetype":"venue"
},
  "geometry": {"coordinates":[-71.40165399999999,41.7565],"type":"Point"}
}