{
  "type": "Feature",
  "properties": {
    "addr:full":"1636 Cranston St Cranston RI 02920",
    "addr:housenumber":"1636",
    "addr:postcode":"02920",
    "addr:street":"Cranston St",
    "iso:country":"US",
    "sg:address":"1636 Cranston St",
    "sg:city":"Cranston",
    "sg:classifiers":[
        {
            "category":"Personal",
            "subcategory":"Beauty Salon",
            "type":"Services"
        }
    ],
    "sg:phone":"+1 401 942 4446",
    "sg:postcode":"02920",
    "sg:province":"RI",
    "wof:name":"Salon Kioma",
    "wof:placetype":"venue"
},
  "geometry": {"coordinates":[-71.463959,41.78606],"type":"Point"}
}