{
  "type": "Feature",
  "properties": {
    "iso:country":"US",
    "sg:address":"646 Bristol Ferry Rd",
    "sg:city":"Portsmouth",
    "sg:classifiers":[
        {
            "category":"Retail",
            "subcategory":"Repair Shop",
            "type":"Services"
        }
    ],
    "sg:phone":"+1 401 683 5635",
    "sg:postcode":"02871",
    "sg:province":"RI",
    "wof:name":"Meikle Marine & Machine Inc",
    "wof:placetype":"venue"
},
  "geometry": {"coordinates":[-71.253745,41.632048],"type":"Point"}
}