{
  "type": "Feature",
  "properties": {
    "addr:full":"820 Tiogue Ave Coventry RI 02816",
    "addr:housenumber":"820",
    "addr:postcode":"02816",
    "addr:street":"Tiogue Ave",
    "iso:country":"US",
    "sg:address":"820 Tiogue Ave",
    "sg:city":"Coventry",
    "sg:classifiers":[
        {
            "category":"Personal",
            "subcategory":"Beauty Salon",
            "type":"Services"
        }
    ],
    "sg:phone":"+1 401 821 8487",
    "sg:postcode":"02816",
    "sg:province":"RI",
    "sg:tags":[
        "manicuring"
    ],
    "wof:name":"Nails By Viv",
    "wof:placetype":"venue"
},
  "geometry": {"coordinates":[-71.56339199999999,41.681888],"type":"Point"}
}