{
  "type": "Feature",
  "properties": {
    "addr:full":"366 North Rd Hope RI 02831",
    "addr:housenumber":"366",
    "addr:postcode":"02831",
    "addr:street":"North Rd",
    "iso:country":"US",
    "sg:address":"366 North Rd",
    "sg:city":"Hope",
    "sg:classifiers":[
        {
            "category":"Arts & Performance",
            "subcategory":"Theater",
            "type":"Entertainment"
        }
    ],
    "sg:phone":"+1 401 996 0670",
    "sg:postcode":"02831",
    "sg:province":"RI",
    "sg:tags":[
        "live",
        "music"
    ],
    "wof:name":"Classic Sound",
    "wof:placetype":"venue"
},
  "geometry": {"coordinates":[-71.566277,41.739594],"type":"Point"}
}