{
  "type": "Feature",
  "properties": {
    "addr:full":"10 Squantum St Cranston RI 02920",
    "addr:housenumber":"10",
    "addr:postcode":"02920",
    "addr:street":"Squantum St",
    "iso:country":"US",
    "sg:address":"10 Squantum St",
    "sg:city":"Cranston",
    "sg:classifiers":[
        {
            "category":"Building & Trades",
            "subcategory":"Construction",
            "type":"Services"
        }
    ],
    "sg:phone":"+1 401 942 2460",
    "sg:postcode":"02920",
    "sg:province":"RI",
    "sg:tags":[
        "floor",
        "laying",
        "contractor"
    ],
    "wof:name":"Stuart C Dodge",
    "wof:placetype":"venue"
},
  "geometry": {"coordinates":[-71.47706700000001,41.764503],"type":"Point"}
}