{
  "type": "Feature",
  "properties": {
    "addr:full":"2244 Plainfield Pike Cranston RI 02921",
    "addr:housenumber":"2244",
    "addr:postcode":"02921",
    "addr:street":"Plainfield Pike",
    "iso:country":"US",
    "sg:address":"2244 Plainfield Pike",
    "sg:city":"Cranston",
    "sg:classifiers":[
        {
            "category":"Utilities",
            "subcategory":"Mobile Phone",
            "type":"Services"
        }
    ],
    "sg:phone":"+1 401 275 2003",
    "sg:postcode":"02921",
    "sg:province":"RI",
    "sg:tags":[
        "telephone",
        "cellular"
    ],
    "wof:name":"Nextel",
    "wof:placetype":"venue"
},
  "geometry": {"coordinates":[-71.51617299999999,41.788582],"type":"Point"}
}