{
  "type": "Feature",
  "properties": {
    "addr:full":"164 Summit Ave Providence RI 02906",
    "addr:housenumber":"164",
    "addr:postcode":"02906",
    "addr:street":"Summit Ave",
    "iso:country":"US",
    "sg:address":"164 Summit Ave",
    "sg:city":"Providence",
    "sg:classifiers":[
        {
            "category":"Health Services",
            "subcategory":"Doctor",
            "type":"Services"
        }
    ],
    "sg:phone":"+1 401 793 4242",
    "sg:postcode":"02906",
    "sg:province":"RI",
    "sg:tags":[
        "medical"
    ],
    "wof:name":"Lifespans",
    "wof:placetype":"venue"
},
  "geometry": {"coordinates":[-71.39769699999999,41.851502],"type":"Point"}
}