{
  "type": "Feature",
  "properties": {
    "iso:country":"US",
    "sg:address":"197 Slater Ave",
    "sg:city":"Providence",
    "sg:classifiers":[
        {
            "category":"Professional",
            "subcategory":"Business Services",
            "type":"Services"
        }
    ],
    "sg:phone":"+1 401 351 2544",
    "sg:postcode":"02906",
    "sg:province":"RI",
    "sg:tags":[
        "development",
        "toy",
        "research"
    ],
    "wof:name":"Dml Associates Inc",
    "wof:placetype":"venue"
},
  "geometry": {"coordinates":[-71.38703099999999,41.840782],"type":"Point"}
}