{
  "type": "Feature",
  "properties": {
    "iso:country":"US",
    "sg:address":"14B Ainsworth St",
    "sg:city":"Providence",
    "sg:classifiers":[
        {
            "category":"Retail",
            "subcategory":"Auto Repair",
            "type":"Services"
        }
    ],
    "sg:phone":"+1 401 621 8090",
    "sg:postcode":"02904",
    "sg:province":"RI",
    "wof:name":"Volante's Service Station",
    "wof:placetype":"venue"
},
  "geometry": {"coordinates":[-71.441597,41.855701],"type":"Point"}
}