{
  "type": "Feature",
  "properties": {
    "iso:country":"US",
    "sg:address":"224 East Ave",
    "sg:city":"Pawtucket",
    "sg:classifiers":[
        {
            "category":"Retail",
            "subcategory":"Laundry & Dry Cleaning",
            "type":"Services"
        }
    ],
    "sg:phone":"+1 401 725 9022",
    "sg:postcode":"02860",
    "sg:province":"RI",
    "sg:tags":[
        "cleaner"
    ],
    "wof:name":"Mr USA 1 Hour Cleaner",
    "wof:placetype":"venue"
},
  "geometry": {"coordinates":[-71.387199,41.870998],"type":"Point"}
}