{
  "type": "Feature",
  "properties": {
    "addr:full":"2851 Pawtucket Ave Riverside RI 02915",
    "addr:housenumber":"2851",
    "addr:postcode":"02915",
    "addr:street":"Pawtucket Ave",
    "iso:country":"US",
    "sg:address":"2851 Pawtucket Ave",
    "sg:city":"Riverside",
    "sg:classifiers":[
        {
            "category":"Food & Beverages",
            "subcategory":"Groceries & Convenience Stores",
            "type":"Retail Goods"
        },
        {
            "category":"Autos & Motor Vehicles",
            "subcategory":"Fuel & Gas Station",
            "type":"Retail Goods"
        }
    ],
    "sg:phone":"+1 401 435 5252",
    "sg:postcode":"02915",
    "sg:province":"RI",
    "sg:tags":[
        "oil",
        "gasoline"
    ],
    "wof:name":"Riverside Auto Service & Gas",
    "wof:placetype":"venue"
},
  "geometry": {"coordinates":[-71.36391399999999,41.796504],"type":"Point"}
}