{
  "type": "Feature",
  "properties": {
    "addr:full":"35 Red Chimney Dr Warwick RI 02886",
    "addr:housenumber":"35",
    "addr:postcode":"02886",
    "addr:street":"Red Chimney Dr",
    "iso:country":"US",
    "sg:address":"35 Red Chimney Dr",
    "sg:city":"Warwick",
    "sg:classifiers":[
        {
            "category":"Education",
            "subcategory":"School",
            "type":"Public Place"
        }
    ],
    "sg:phone":"+1 401 734 3535",
    "sg:postcode":"02886",
    "sg:province":"RI",
    "sg:tags":[
        "elementary"
    ],
    "wof:name":"Cedar Hill Elementary School",
    "wof:placetype":"venue"
},
  "geometry": {"coordinates":[-71.46258400000001,41.681787],"type":"Point"}
}