{
  "type": "Feature",
  "properties": {
    "addr:full":"163 Lafayette St Pawtucket RI 02860",
    "addr:housenumber":"163",
    "addr:postcode":"02860",
    "addr:street":"Lafayette St",
    "iso:country":"US",
    "sg:address":"163 Lafayette St",
    "sg:city":"Pawtucket",
    "sg:classifiers":[
        {
            "category":"Home & Garden",
            "subcategory":"Garden Supply",
            "type":"Retail Goods"
        }
    ],
    "sg:phone":"+1 401 723 8023",
    "sg:postcode":"02860",
    "sg:province":"RI",
    "sg:tags":[
        "sprinkler"
    ],
    "wof:name":"Affordable & Quality",
    "wof:placetype":"venue"
},
  "geometry": {"coordinates":[-71.394863,41.857552],"type":"Point"}
}