{
  "type": "Feature",
  "properties": {
    "iso:country":"US",
    "sg:address":"193 Seneca Ave",
    "sg:city":"Pawtucket",
    "sg:classifiers":[
        {
            "category":"Social Services",
            "subcategory":"Child Care",
            "type":"Services"
        }
    ],
    "sg:phone":"+1 401 728 0256",
    "sg:postcode":"02860",
    "sg:province":"RI",
    "sg:tags":[
        "day"
    ],
    "wof:name":"Quinlan Family Home Day Care",
    "wof:placetype":"venue"
},
  "geometry": {"coordinates":[-71.417254,41.86001],"type":"Point"}
}