{
  "type": "Feature",
  "properties": {
    "addr:full":"1394 Douglas Ave North Providence RI 02904",
    "addr:housenumber":"1394",
    "addr:postcode":"02904",
    "addr:street":"Douglas Ave",
    "iso:country":"US",
    "sg:address":"1394 Douglas Ave",
    "sg:city":"North Providence",
    "sg:classifiers":[
        {
            "category":"Restaurant",
            "type":"Food & Drink"
        }
    ],
    "sg:phone":"+1 401 383 4808",
    "sg:postcode":"02904",
    "sg:province":"RI",
    "sg:tags":[
        "pizza"
    ],
    "wof:name":"New England House of Pizza",
    "wof:placetype":"venue"
},
  "geometry": {"coordinates":[-71.453096,41.863148],"type":"Point"}
}