{
  "type": "Feature",
  "properties": {
    "iso:country":"US",
    "sg:address":"44 Broadway",
    "sg:city":"Newport",
    "sg:classifiers":[
        {
            "category":"Personal",
            "type":"Services"
        }
    ],
    "sg:phone":"+1 401 847 4155",
    "sg:postcode":"02840",
    "sg:province":"RI",
    "wof:name":"Anchor Steam Tattoo Gallery",
    "wof:placetype":"venue"
},
  "geometry": {"coordinates":[-71.311584,41.491931],"type":"Point"}
}