{
  "type": "Feature",
  "properties": {
    "addr:full":"3438 Post Rd Warwick RI 02886",
    "addr:housenumber":"3438",
    "addr:postcode":"02886",
    "addr:street":"Post Rd",
    "iso:country":"US",
    "sg:address":"3438 Post Rd",
    "sg:city":"Warwick",
    "sg:classifiers":[
        {
            "category":"Local Transit",
            "type":"Transportation"
        }
    ],
    "sg:phone":"+1 401 265 5356",
    "sg:postcode":"02886",
    "sg:province":"RI",
    "sg:tags":[
        "passenger"
    ],
    "wof:name":"Airport Car Express",
    "wof:placetype":"venue"
},
  "geometry": {"coordinates":[-71.457936,41.695441],"type":"Point"}
}