{
  "type": "Feature",
  "properties": {
    "addr:full":"707 Park Ave Cranston RI 02910",
    "addr:housenumber":"707",
    "addr:postcode":"02910",
    "addr:street":"Park Ave",
    "iso:country":"US",
    "sg:address":"707 Park Ave",
    "sg:city":"Cranston",
    "sg:classifiers":[
        {
            "category":"Organizations",
            "subcategory":"Religious Organization",
            "type":"Services"
        }
    ],
    "sg:phone":"+1 401 467 3830",
    "sg:postcode":"02910",
    "sg:province":"RI",
    "sg:tags":[
        "church"
    ],
    "sg:website":"www.gatewayupc.org",
    "wof:name":"Gateway United Pentecostal Chr",
    "wof:placetype":"venue"
},
  "geometry": {"coordinates":[-71.428849,41.777593],"type":"Point"}
}