{
  "type": "Feature",
  "properties": {
    "iso:country":"US",
    "sg:address":"200 Ten Rod Rd",
    "sg:city":"Exeter",
    "sg:classifiers":[
        {
            "category":"Home & Garden",
            "subcategory":"Garden Supply",
            "type":"Retail Goods"
        }
    ],
    "sg:phone":"+1 401 294 2852",
    "sg:postcode":"02822",
    "sg:province":"RI",
    "sg:tags":[
        "nurseryman"
    ],
    "wof:name":"G A De Coster",
    "wof:placetype":"venue"
},
  "geometry": {"coordinates":[-71.536925,41.577228],"type":"Point"}
}