{
  "type": "Feature",
  "properties": {
    "addr:full":"# 1-8 East Providence RI 02914",
    "addr:postcode":"02914",
    "iso:country":"US",
    "sg:address":"# 1-8",
    "sg:city":"East Providence",
    "sg:classifiers":[
        {
            "category":"Education",
            "subcategory":"School",
            "type":"Public Place"
        }
    ],
    "sg:phone":"+1 401 434 3153",
    "sg:postcode":"02914",
    "sg:province":"RI",
    "wof:name":"St Francis Xavier Church",
    "wof:placetype":"venue"
},
  "geometry": {"coordinates":[-71.377858,41.816081],"type":"Point"}
}