{
  "type": "Feature",
  "properties": {
    "iso:country":"US",
    "sg:address":"255 Pocasset Ave",
    "sg:city":"Providence",
    "sg:classifiers":[
        {
            "category":"Retail",
            "subcategory":"Auto Repair",
            "type":"Services"
        }
    ],
    "sg:phone":"+1 401 944 9815",
    "sg:postcode":"02909",
    "sg:province":"RI",
    "sg:tags":[
        "repairing",
        "automobile"
    ],
    "wof:name":"Billy Dee's Svc Ctr",
    "wof:placetype":"venue"
},
  "geometry": {"coordinates":[-71.455772,41.808323],"type":"Point"}
}