{
  "type": "Feature",
  "properties": {
    "iso:country":"US",
    "sg:address":"127 Dorrance St",
    "sg:city":"Providence",
    "sg:classifiers":[
        {
            "category":"Professional",
            "subcategory":"Lawyer & Legal Services",
            "type":"Services"
        }
    ],
    "sg:phone":"+1 401 453 1355",
    "sg:postcode":"02903",
    "sg:province":"RI",
    "wof:name":"Dennis Stephen J Atty",
    "wof:placetype":"venue"
},
  "geometry": {"coordinates":[-71.410301,41.822399],"type":"Point"}
}