{
  "type": "Feature",
  "properties": {
    "addr:full":"231 Water St Block Island RI 02885",
    "addr:housenumber":"231",
    "addr:postcode":"02885",
    "addr:street":"Water St",
    "iso:country":"US",
    "sg:address":"231 Water St",
    "sg:city":"Block Island",
    "sg:classifiers":[
        {
            "category":"Travel",
            "subcategory":"Hotels & Motels",
            "type":"Entertainment"
        }
    ],
    "sg:phone":"+1 401 466 2932",
    "sg:postcode":"02885",
    "sg:province":"RI",
    "wof:name":"Inn At Old Harbour",
    "wof:placetype":"venue"
},
  "geometry": {"coordinates":[-71.28533,41.731032],"type":"Point"}
}