{
  "type": "Feature",
  "properties": {
    "iso:country":"US",
    "sg:address":"45 Lee St",
    "sg:city":"Pawtucket",
    "sg:classifiers":[
        {
            "category":"Professional",
            "subcategory":"Art Services",
            "type":"Services"
        }
    ],
    "sg:phone":"+1 401 722 0350",
    "sg:postcode":"02861",
    "sg:province":"RI",
    "sg:tags":[
        "photographer"
    ],
    "wof:name":"Christy Christopoulos Phtgrphy",
    "wof:placetype":"venue"
},
  "geometry": {"coordinates":[-71.35855599999999,41.891054],"type":"Point"}
}