{
  "type": "Feature",
  "properties": {
    "iso:country":"US",
    "sg:address":"36 Roger Williams Dr",
    "sg:city":"Greenville",
    "sg:classifiers":[
        {
            "category":"Travel",
            "subcategory":"Hotels & Motels",
            "type":"Entertainment"
        }
    ],
    "sg:phone":"+1 401 949 3003",
    "sg:postcode":"02828",
    "sg:province":"RI",
    "sg:tags":[
        "operation"
    ],
    "wof:name":"Ocean Resort Casino Convention",
    "wof:placetype":"venue"
},
  "geometry": {"coordinates":[-71.55839400000001,41.861115],"type":"Point"}
}