{
  "type": "Feature",
  "properties": {
    "iso:country":"US",
    "sg:address":"852 Admiral St",
    "sg:city":"Providence",
    "sg:classifiers":[
        {
            "category":"Food & Beverages",
            "subcategory":"Groceries & Convenience Stores",
            "type":"Retail Goods"
        }
    ],
    "sg:phone":"+1 401 490 3101",
    "sg:postcode":"02904",
    "sg:province":"RI",
    "wof:name":"Jehova Nissi Market",
    "wof:placetype":"venue"
},
  "geometry": {"coordinates":[-71.444806,41.851558],"type":"Point"}
}