{
  "type": "Feature",
  "properties": {
    "iso:country":"US",
    "sg:address":"857 Post Rd",
    "sg:city":"Warwick",
    "sg:classifiers":[
        {
            "category":"Health Services",
            "subcategory":"Doctor",
            "type":"Services"
        }
    ],
    "sg:phone":"+1 401 467 3115",
    "sg:postcode":"02888",
    "sg:province":"RI",
    "sg:tags":[
        "physician",
        "surgeon"
    ],
    "wof:name":"Associates In Primary Care",
    "wof:placetype":"venue"
},
  "geometry": {"coordinates":[-71.41583,41.752712],"type":"Point"}
}