{
  "type": "Feature",
  "properties": {
    "iso:country":"US",
    "sg:address":"984 Mendon Rd",
    "sg:city":"Cumberland",
    "sg:classifiers":[
        {
            "category":"Personal",
            "type":"Services"
        }
    ],
    "sg:phone":"+1 401 333 6399",
    "sg:postcode":"02864",
    "sg:province":"RI",
    "sg:tags":[
        "tattoo",
        "parlor"
    ],
    "wof:name":"Altered Images Tattoo",
    "wof:placetype":"venue"
},
  "geometry": {"coordinates":[-71.421402,41.929298],"type":"Point"}
}