{
  "type": "Feature",
  "properties": {
    "iso:country":"US",
    "sg:address":"2731 Pawtucket Ave",
    "sg:city":"East Providence",
    "sg:classifiers":[
        {
            "category":"Communications",
            "type":"Services"
        }
    ],
    "sg:phone":"+1 401 435 6688",
    "sg:postcode":"02914",
    "sg:province":"RI",
    "wof:name":"RHI Communications",
    "wof:placetype":"venue"
},
  "geometry": {"coordinates":[-71.36242300000001,41.801114],"type":"Point"}
}