{
  "type": "Feature",
  "properties": {
    "addr:full":"105 Franklin St Westerly RI 02891",
    "addr:housenumber":"105",
    "addr:postcode":"02891",
    "addr:street":"Franklin St",
    "iso:country":"US",
    "sg:address":"105 Franklin St",
    "sg:city":"Westerly",
    "sg:classifiers":[
        {
            "category":"Home & Garden",
            "subcategory":"Furniture",
            "type":"Retail Goods"
        }
    ],
    "sg:phone":"+1 401 596 7070",
    "sg:postcode":"02891",
    "sg:province":"RI",
    "sg:tags":[
        "custom",
        "kitchen",
        "install",
        "cabinet"
    ],
    "sg:website":"www.southcountycabinets.com",
    "wof:name":"South County Cabinets",
    "wof:placetype":"venue"
},
  "geometry": {"coordinates":[-71.813355,41.362308],"type":"Point"}
}