{
  "type": "Feature",
  "properties": {
    "addr:full":"10 Eagle St Providence RI 02908",
    "addr:housenumber":"10",
    "addr:postcode":"02908",
    "addr:street":"Eagle St",
    "iso:country":"US",
    "sg:address":"10 Eagle St",
    "sg:city":"Providence",
    "sg:classifiers":[
        {
            "category":"Shopping",
            "subcategory":"Clothing, Apparel, & Fashions",
            "type":"Retail Goods"
        }
    ],
    "sg:phone":"+1 401 781 2868",
    "sg:postcode":"02908",
    "sg:province":"RI",
    "sg:tags":[
        "t"
    ],
    "wof:name":"R I Graphics & Screen Printing",
    "wof:placetype":"venue"
},
  "geometry": {"coordinates":[-71.435907,41.826915],"type":"Point"}
}