{
  "type": "Feature",
  "properties": {
    "iso:country":"US",
    "sg:address":"45 Thompson Hill Dr",
    "sg:city":"Cumberland",
    "sg:classifiers":[
        {
            "category":"Cinema",
            "subcategory":"Movie Rental",
            "type":"Entertainment"
        }
    ],
    "sg:phone":"+1 401 333 8147",
    "sg:postcode":"02864",
    "sg:province":"RI",
    "sg:tags":[
        "video",
        "tape"
    ],
    "wof:name":"Taunton North Inc",
    "wof:placetype":"venue"
},
  "geometry": {"coordinates":[-71.403621,41.968333],"type":"Point"}
}