{
  "type": "Feature",
  "properties": {
    "iso:country":"US",
    "sg:address":"529 Plainfield St",
    "sg:city":"Providence",
    "sg:classifiers":[
        {
            "category":"Social Services",
            "type":"Services"
        }
    ],
    "sg:phone":"+1 401 944 8300",
    "sg:postcode":"02909",
    "sg:province":"RI",
    "sg:tags":[
        "center",
        "community"
    ],
    "wof:name":"Senior Citizens of Hope",
    "wof:placetype":"venue"
},
  "geometry": {"coordinates":[-71.45591,41.813254],"type":"Point"}
}