{
  "type": "Feature",
  "properties": {
    "iso:country":"US",
    "sg:address":"595 Killingly St",
    "sg:city":"Johnston",
    "sg:classifiers":[
        {
            "category":"Banks & Credit Unions",
            "subcategory":"Bank",
            "type":"Services"
        }
    ],
    "sg:phone":"+1 401 621 2519",
    "sg:postcode":"02919",
    "sg:province":"RI",
    "sg:tags":[
        "loan",
        "real estate"
    ],
    "wof:name":"Commercial Loan Inventors Inc",
    "wof:placetype":"venue"
},
  "geometry": {"coordinates":[-71.47223700000001,41.826664],"type":"Point"}
}