{
  "type": "Feature",
  "properties": {
    "addr:full":"33 Centerville Rd Warwick RI 02886",
    "addr:housenumber":"33",
    "addr:postcode":"02886",
    "addr:street":"Centerville Rd",
    "iso:country":"US",
    "sg:address":"33 Centerville Rd",
    "sg:city":"Warwick",
    "sg:classifiers":[
        {
            "category":"Banks & Credit Unions",
            "subcategory":"Investment Brokerage",
            "type":"Services"
        }
    ],
    "sg:phone":"+1 401 737 5405",
    "sg:postcode":"02886",
    "sg:province":"RI",
    "sg:tags":[
        "advisory",
        "financial"
    ],
    "wof:name":"Prudentcial Financial",
    "wof:placetype":"venue"
},
  "geometry": {"coordinates":[-71.461499,41.69866],"type":"Point"}
}