{
  "type": "Feature",
  "properties": {
    "iso:country":"US",
    "sg:address":"150 Main St",
    "sg:city":"Pawtucket",
    "sg:classifiers":[
        {
            "category":"Health Services",
            "subcategory":"Doctor",
            "type":"Services"
        }
    ],
    "sg:phone":"+1 401 727 2200",
    "sg:postcode":"02860",
    "sg:province":"RI",
    "wof:name":"Pawtucket General Medical",
    "wof:placetype":"venue"
},
  "geometry": {"coordinates":[-71.38356,41.876483],"type":"Point"}
}