{
  "type": "Feature",
  "properties": {
    "iso:country":"US",
    "sg:address":"700 Aquidneck Ave",
    "sg:city":"Middletown",
    "sg:classifiers":[
        {
            "category":"Professional",
            "subcategory":"Management & Consulting",
            "type":"Services"
        }
    ],
    "sg:phone":"+1 401 846 3254",
    "sg:postcode":"02842",
    "sg:province":"RI",
    "wof:name":"Main Event",
    "wof:placetype":"venue"
},
  "geometry": {"coordinates":[-71.28263699999999,41.507414],"type":"Point"}
}