{
  "type": "Feature",
  "properties": {
    "addr:full":"1 Masthead Dr Warwick RI 02886",
    "addr:housenumber":"1",
    "addr:postcode":"02886",
    "addr:street":"Masthead Dr",
    "iso:country":"US",
    "sg:address":"1 Masthead Dr",
    "sg:city":"Warwick",
    "sg:classifiers":[
        {
            "category":"Autos & Motor Vehicles",
            "subcategory":"Boat Sales",
            "type":"Retail Goods"
        }
    ],
    "sg:phone":"+1 401 886 7899",
    "sg:postcode":"02886",
    "sg:province":"RI",
    "sg:tags":[
        "dealer",
        "sales"
    ],
    "wof:name":"Bassett Boat Company Inc",
    "wof:placetype":"venue"
},
  "geometry": {"coordinates":[-71.45088199999999,41.684708],"type":"Point"}
}