{
  "type": "Feature",
  "properties": {
    "addr:full":"22 Paull St Bristol RI 02809",
    "addr:housenumber":"22",
    "addr:postcode":"02809",
    "addr:street":"Paull St",
    "iso:country":"US",
    "sg:address":"22 Paull St",
    "sg:city":"Bristol",
    "sg:classifiers":[
        {
            "category":"Building & Trades",
            "subcategory":"Construction",
            "type":"Services"
        }
    ],
    "sg:phone":"+1 401 253 8613",
    "sg:postcode":"02809",
    "sg:province":"RI",
    "sg:tags":[
        "contractor"
    ],
    "wof:name":"Mj Masonry Corp",
    "wof:placetype":"venue"
},
  "geometry": {"coordinates":[-71.27677300000001,41.681927],"type":"Point"}
}