{
  "type": "Feature",
  "properties": {
    "iso:country":"US",
    "sg:address":"6 Lark Industrial Dr",
    "sg:city":"Greenville",
    "sg:classifiers":[
        {
            "category":"Wholesale",
            "subcategory":"Machinery & Supplies",
            "type":"Manufacturing & Wholesale Goods"
        }
    ],
    "sg:phone":"+1 401 949 3390",
    "sg:postcode":"02828",
    "sg:province":"RI",
    "sg:tags":[
        "repair",
        "gas",
        "appliance"
    ],
    "wof:name":"S & M Distributing Co",
    "wof:placetype":"venue"
},
  "geometry": {"coordinates":[-71.536027,41.867492],"type":"Point"}
}