{
  "type": "Feature",
  "properties": {
    "iso:country":"US",
    "sg:address":"747 Victory Hwy",
    "sg:city":"North Smithfield",
    "sg:classifiers":[
        {
            "category":"Banks & Credit Unions",
            "subcategory":"Bank",
            "type":"Services"
        }
    ],
    "sg:phone":"+1 401 671 6500",
    "sg:postcode":"02896",
    "sg:province":"RI",
    "sg:tags":[
        "loan",
        "real estate"
    ],
    "wof:name":"Stockton Turner Co",
    "wof:placetype":"venue"
},
  "geometry": {"coordinates":[-71.5834,42.006804],"type":"Point"}
}