{
  "type": "Feature",
  "properties": {
    "iso:country":"US",
    "sg:address":"60 Zone St",
    "sg:city":"Providence",
    "sg:classifiers":[
        {
            "category":"Professional",
            "type":"Services"
        }
    ],
    "sg:phone":"+1 401 751 5116",
    "sg:postcode":"02908",
    "sg:province":"RI",
    "wof:name":"Serenditity Art Studio",
    "wof:placetype":"venue"
},
  "geometry": {"coordinates":[-71.427201,41.833076],"type":"Point"}
}