{
  "type": "Feature",
  "properties": {
    "addr:full":"56 Bridge St Newport RI 02840",
    "addr:housenumber":"56",
    "addr:postcode":"02840",
    "addr:street":"Bridge St",
    "iso:country":"US",
    "sg:address":"56 Bridge St",
    "sg:city":"Newport",
    "sg:classifiers":[
        {
            "category":"Shopping",
            "type":"Retail Goods"
        }
    ],
    "sg:phone":"+1 401 619 0820",
    "sg:postcode":"02840",
    "sg:province":"RI",
    "sg:tags":[
        "merchandise"
    ],
    "wof:name":"Custom Yacht Outfitters",
    "wof:placetype":"venue"
},
  "geometry": {"coordinates":[-71.318451,41.492067],"type":"Point"}
}