{
  "type": "Feature",
  "properties": {
    "iso:country":"US",
    "sg:address":"700 Main St",
    "sg:city":"West Warwick",
    "sg:classifiers":[
        {
            "category":"Retail",
            "subcategory":"Auto Repair",
            "type":"Services"
        }
    ],
    "sg:phone":"+1 401 828 9710",
    "sg:postcode":"02893",
    "sg:province":"RI",
    "sg:tags":[
        "general"
    ],
    "wof:name":"Sprague Repair Service",
    "wof:placetype":"venue"
},
  "geometry": {"coordinates":[-71.53265399999999,41.721683],"type":"Point"}
}