{
  "type": "Feature",
  "properties": {
    "iso:country":"US",
    "sg:address":"1 Turks Head Pl Ste 321",
    "sg:city":"Providence",
    "sg:classifiers":[
        {
            "category":"Professional",
            "subcategory":"Employment Agencies",
            "type":"Services"
        }
    ],
    "sg:phone":"+1 401 831 5550",
    "sg:postcode":"02903",
    "sg:province":"RI",
    "wof:name":"Johnson & Tregar Assoc",
    "wof:placetype":"venue"
},
  "geometry": {"coordinates":[-71.40979799999999,41.824799],"type":"Point"}
}