{
  "type": "Feature",
  "properties": {
    "iso:country":"US",
    "sg:address":"369 S Main St",
    "sg:city":"Providence",
    "sg:classifiers":[
        {
            "category":"Professional",
            "subcategory":"Lawyer & Legal Services",
            "type":"Services"
        }
    ],
    "sg:phone":"+1 401 521 3100",
    "sg:postcode":"02903",
    "sg:province":"RI",
    "wof:name":"Homonoff Levine & Pulner",
    "wof:placetype":"venue"
},
  "geometry": {"coordinates":[-71.403702,41.820999],"type":"Point"}
}