{
  "type": "Feature",
  "properties": {
    "iso:country":"US",
    "sg:address":"2000 Pawtucket Ave",
    "sg:city":"East Providence",
    "sg:classifiers":[
        {
            "category":"Education",
            "subcategory":"School",
            "type":"Public Place"
        }
    ],
    "sg:phone":"+1 401 438 4619",
    "sg:postcode":"02914",
    "sg:province":"RI",
    "wof:name":"Compass Group North American Division",
    "wof:placetype":"venue"
},
  "geometry": {"coordinates":[-71.35622100000001,41.821207],"type":"Point"}
}