{
  "type": "Feature",
  "properties": {
    "iso:country":"US",
    "sg:address":"50 Abbott Run Valley Rd",
    "sg:city":"Cumberland",
    "sg:classifiers":[
        {
            "category":"Wholesale",
            "subcategory":"Non-durable Goods",
            "type":"Manufacturing & Wholesale Goods"
        }
    ],
    "sg:phone":"+1 401 334 6707",
    "sg:postcode":"02864",
    "sg:province":"RI",
    "sg:tags":[
        "advertising"
    ],
    "wof:name":"Ballyhoo Promotions",
    "wof:placetype":"venue"
},
  "geometry": {"coordinates":[-71.38765600000001,41.952583],"type":"Point"}
}