{
  "type": "Feature",
  "properties": {
    "addr:full":"4 Barbato Dr Johnston RI 02919",
    "addr:housenumber":"4",
    "addr:postcode":"02919",
    "addr:street":"Barbato Dr",
    "iso:country":"US",
    "sg:address":"4 Barbato Dr",
    "sg:city":"Johnston",
    "sg:classifiers":[
        {
            "category":"Shopping",
            "subcategory":"Beauty & Cosmetics",
            "type":"Retail Goods"
        }
    ],
    "sg:phone":"+1 401 232 0604",
    "sg:postcode":"02919",
    "sg:province":"RI",
    "sg:tags":[
        "merchandise"
    ],
    "wof:name":"Harmony Perfect",
    "wof:placetype":"venue"
},
  "geometry": {"coordinates":[-71.498197,41.840443],"type":"Point"}
}