{
  "type": "Feature",
  "properties": {
    "addr:full":"7 Garfield Ave Cranston RI 02920",
    "addr:housenumber":"7",
    "addr:postcode":"02920",
    "addr:street":"Garfield Ave",
    "iso:country":"US",
    "sg:address":"7 Garfield Ave",
    "sg:city":"Cranston",
    "sg:classifiers":[
        {
            "category":"Shopping",
            "subcategory":"Computers & Home Electronics",
            "type":"Retail Goods"
        }
    ],
    "sg:phone":"+1 401 944 1143",
    "sg:postcode":"02920",
    "sg:province":"RI",
    "sg:tags":[
        "game",
        "video"
    ],
    "wof:name":"Gamestop",
    "wof:placetype":"venue"
},
  "geometry": {"coordinates":[-71.44177000000001,41.801664],"type":"Point"}
}