{
  "type": "Feature",
  "properties": {
    "iso:country":"US",
    "sg:address":"381 Angell St",
    "sg:city":"Providence",
    "sg:classifiers":[
        {
            "category":"Health Services",
            "subcategory":"Doctor",
            "type":"Services"
        }
    ],
    "sg:phone":"+1 401 272 4900",
    "sg:postcode":"02906",
    "sg:province":"RI",
    "sg:tags":[
        "dentist"
    ],
    "wof:name":"Sunnyside Family Dental",
    "wof:placetype":"venue"
},
  "geometry": {"coordinates":[-71.392799,41.8293],"type":"Point"}
}