{
  "type": "Feature",
  "properties": {
    "addr:full":"51 Eustis Ave Newport RI 02840",
    "addr:housenumber":"51",
    "addr:postcode":"02840",
    "addr:street":"Eustis Ave",
    "iso:country":"US",
    "sg:address":"51 Eustis Ave",
    "sg:city":"Newport",
    "sg:classifiers":[
        {
            "category":"Manufacturing",
            "subcategory":"Printing",
            "type":"Manufacturing & Wholesale Goods"
        }
    ],
    "sg:phone":"+1 401 847 1417",
    "sg:postcode":"02840",
    "sg:province":"RI",
    "sg:tags":[
        "commercial"
    ],
    "wof:name":"Prime Litho Printing",
    "wof:placetype":"venue"
},
  "geometry": {"coordinates":[-71.300589,41.497147],"type":"Point"}
}