{
  "type": "Feature",
  "properties": {
    "iso:country":"US",
    "sg:address":"48 Nashua St",
    "sg:city":"Providence",
    "sg:classifiers":[
        {
            "category":"Professional",
            "subcategory":"Lawyer & Legal Services",
            "type":"Services"
        }
    ],
    "sg:phone":"+1 401 453 1550",
    "sg:postcode":"02904",
    "sg:province":"RI",
    "wof:name":"Paul A Lancia",
    "wof:placetype":"venue"
},
  "geometry": {"coordinates":[-71.404079,41.850361],"type":"Point"}
}