{
  "type": "Feature",
  "properties": {
    "addr:full":"73 Branch Pike Smithfield RI 02917",
    "addr:housenumber":"73",
    "addr:postcode":"02917",
    "addr:street":"Branch Pike",
    "iso:country":"US",
    "sg:address":"73 Branch Pike",
    "sg:city":"Smithfield",
    "sg:classifiers":[
        {
            "category":"Social Services",
            "subcategory":"Adult Care",
            "type":"Services"
        }
    ],
    "sg:phone":"+1 401 233 2218",
    "sg:postcode":"02917",
    "sg:province":"RI",
    "sg:tags":[
        "home",
        "group"
    ],
    "wof:name":"Branch Pike Residence",
    "wof:placetype":"venue"
},
  "geometry": {"coordinates":[-71.541849,41.934581],"type":"Point"}
}