{
  "type": "Feature",
  "properties": {
    "addr:full":"16 Bay Spring Ave Barrington RI 02806",
    "addr:housenumber":"16",
    "addr:postcode":"02806",
    "addr:street":"Bay Spring Ave",
    "iso:country":"US",
    "sg:address":"16 Bay Spring Ave",
    "sg:city":"Barrington",
    "sg:classifiers":[
        {
            "category":"Organizations",
            "subcategory":"Non-profit Organization",
            "type":"Services"
        }
    ],
    "sg:phone":"+1 401 246 2110",
    "sg:postcode":"02806",
    "sg:province":"RI",
    "sg:tags":[
        "charitable",
        "institution"
    ],
    "wof:name":"Jay Steenhuysen & Assoc",
    "wof:placetype":"venue"
},
  "geometry": {"coordinates":[-71.344274,41.747932],"type":"Point"}
}