{
  "type": "Feature",
  "properties": {
    "iso:country":"US",
    "sg:address":"784 Main St",
    "sg:city":"East Greenwich",
    "sg:classifiers":[
        {
            "category":"Personal",
            "subcategory":"Beauty Salon",
            "type":"Services"
        }
    ],
    "sg:phone":"+1 401 885 3232",
    "sg:postcode":"02818",
    "sg:province":"RI",
    "sg:tags":[
        "manicuring"
    ],
    "wof:name":"Nails By Viv",
    "wof:placetype":"venue"
},
  "geometry": {"coordinates":[-71.454365,41.654575],"type":"Point"}
}