{
  "type": "Feature",
  "properties": {
    "iso:country":"US",
    "sg:address":"407 Buttonwoods Ave",
    "sg:city":"Warwick",
    "sg:classifiers":[
        {
            "category":"Building & Trades",
            "subcategory":"Construction",
            "type":"Services"
        }
    ],
    "sg:phone":"+1 401 732 5464",
    "sg:postcode":"02886",
    "sg:province":"RI",
    "sg:tags":[
        "steel",
        "erection",
        "contractor",
        "including",
        "placeman",
        "structural"
    ],
    "wof:name":"Iroquois Steel Erection Inc",
    "wof:placetype":"venue"
},
  "geometry": {"coordinates":[-71.42750599999999,41.695215],"type":"Point"}
}