{
  "type": "Feature",
  "properties": {
    "iso:country":"US",
    "sg:address":"135 Laurel Hill Ave",
    "sg:city":"Providence",
    "sg:classifiers":[
        {
            "category":"Communications",
            "type":"Services"
        }
    ],
    "sg:phone":"+1 401 943 7394",
    "sg:postcode":"02909",
    "sg:province":"RI",
    "wof:name":"P T Communications",
    "wof:placetype":"venue"
},
  "geometry": {"coordinates":[-71.455583,41.813464],"type":"Point"}
}