{
  "type": "Feature",
  "properties": {
    "iso:country":"US",
    "sg:address":"33 Bleachery Ct",
    "sg:city":"Warwick",
    "sg:classifiers":[
        {
            "category":"Retail",
            "subcategory":"Repair Shop",
            "type":"Services"
        }
    ],
    "sg:phone":"+1 401 732 5222",
    "sg:postcode":"02886",
    "sg:province":"RI",
    "sg:tags":[
        "industrial",
        "commercial",
        "boiler"
    ],
    "wof:name":"AD&d Wldg & Boiler Works Inc",
    "wof:placetype":"venue"
},
  "geometry": {"coordinates":[-71.465812,41.728852],"type":"Point"}
}