{
  "type": "Feature",
  "properties": {
    "iso:country":"US",
    "sg:address":"113 Tiogue Ave",
    "sg:city":"Coventry",
    "sg:classifiers":[
        {
            "category":"Manufacturing",
            "subcategory":"Furniture",
            "type":"Manufacturing & Wholesale Goods"
        }
    ],
    "sg:phone":"+1 401 822 1181",
    "sg:postcode":"02816",
    "sg:province":"RI",
    "sg:tags":[
        "consultant",
        "filing"
    ],
    "wof:name":"Professional Records Inc",
    "wof:placetype":"venue"
},
  "geometry": {"coordinates":[-71.533434,41.679763],"type":"Point"}
}