{
  "type": "Feature",
  "properties": {
    "iso:country":"US",
    "sg:address":"4015 Quaker Ln",
    "sg:city":"North Kingstown",
    "sg:classifiers":[
        {
            "category":"Restaurant",
            "type":"Food & Drink"
        }
    ],
    "sg:phone":"+1 401 295 1533",
    "sg:postcode":"02852",
    "sg:province":"RI",
    "sg:tags":[
        "eating"
    ],
    "wof:name":"Snoopy's Diner",
    "wof:placetype":"venue"
},
  "geometry": {"coordinates":[-71.501339,41.588985],"type":"Point"}
}