{
  "type": "Feature",
  "properties": {
    "iso:country":"US",
    "sg:address":"141 Coggeshall Ave",
    "sg:city":"Newport",
    "sg:classifiers":[
        {
            "category":"Travel",
            "subcategory":"Hotels & Motels",
            "type":"Entertainment"
        }
    ],
    "sg:phone":"+1 401 847 1651",
    "sg:postcode":"02840",
    "sg:province":"RI",
    "sg:tags":[
        "operation"
    ],
    "wof:name":"Almy Cottage",
    "wof:placetype":"venue"
},
  "geometry": {"coordinates":[-71.30851699999999,41.461437],"type":"Point"}
}