{
  "type": "Feature",
  "properties": {
    "addr:full":"65 Union Ave Harrisville RI 02830",
    "addr:housenumber":"65",
    "addr:postcode":"02830",
    "addr:street":"Union Ave",
    "iso:country":"US",
    "sg:address":"65 Union Ave",
    "sg:city":"Harrisville",
    "sg:classifiers":[
        {
            "category":"Building & Trades",
            "subcategory":"Construction",
            "type":"Services"
        }
    ],
    "sg:phone":"+1 401 568 4440",
    "sg:postcode":"02830",
    "sg:province":"RI",
    "wof:name":"Public Works Dept",
    "wof:placetype":"venue"
},
  "geometry": {"coordinates":[-71.69347500000001,41.965937],"type":"Point"}
}