{
  "type": "Feature",
  "properties": {
    "iso:country":"US",
    "sg:address":"152 Angell St",
    "sg:city":"Providence",
    "sg:classifiers":[
        {
            "category":"Retail",
            "subcategory":"Auto Repair",
            "type":"Services"
        }
    ],
    "sg:phone":"+1 401 751 3090",
    "sg:postcode":"02906",
    "sg:province":"RI",
    "sg:tags":[
        "repairing",
        "automobile"
    ],
    "wof:name":"East Side Svc Ctr",
    "wof:placetype":"venue"
},
  "geometry": {"coordinates":[-71.40181699999999,41.828042],"type":"Point"}
}