{
  "type": "Feature",
  "properties": {
    "iso:country":"US",
    "sg:address":"156 Bayview Ave",
    "sg:city":"Bristol",
    "sg:classifiers":[
        {
            "category":"Autos & Motor Vehicles",
            "subcategory":"Fuel & Gas Station",
            "type":"Retail Goods"
        }
    ],
    "sg:phone":"+1 401 254 8852",
    "sg:postcode":"02809",
    "sg:province":"RI",
    "sg:tags":[
        "oil"
    ],
    "wof:name":"SRB Auto Svc",
    "wof:placetype":"venue"
},
  "geometry": {"coordinates":[-71.266846,41.678219],"type":"Point"}
}