{
  "type": "Feature",
  "properties": {
    "iso:country":"US",
    "sg:address":"874 Old Greenwich Dr",
    "sg:city":"East Greenwich",
    "sg:classifiers":[
        {
            "category":"Real Estate",
            "subcategory":"Real Estate Agent",
            "type":"Services"
        }
    ],
    "sg:phone":"+1 401 885 0081",
    "sg:postcode":"02818",
    "sg:province":"RI",
    "sg:tags":[
        "inspection"
    ],
    "wof:name":"Alpha Home Inspection Svc",
    "wof:placetype":"venue"
},
  "geometry": {"coordinates":[-71.478381,41.655054],"type":"Point"}
}