{
  "type": "Feature",
  "properties": {
    "iso:country":"US",
    "sg:address":"225 East Ave",
    "sg:city":"Pawtucket",
    "sg:classifiers":[
        {
            "category":"Health Services",
            "subcategory":"Doctor",
            "type":"Services"
        }
    ],
    "sg:phone":"+1 401 725 8989",
    "sg:postcode":"02860",
    "sg:province":"RI",
    "sg:tags":[
        "podiatrist"
    ],
    "wof:name":"Enander Mark W Podiatrst",
    "wof:placetype":"venue"
},
  "geometry": {"coordinates":[-71.387001,41.871101],"type":"Point"}
}