{
  "type": "Feature",
  "properties": {
    "iso:country":"US",
    "sg:address":"295 Promenade St",
    "sg:city":"Providence",
    "sg:classifiers":[
        {
            "category":"Insurance",
            "subcategory":"Insurance Agent",
            "type":"Services"
        }
    ],
    "sg:phone":"+1 401 274 7877",
    "sg:postcode":"02908",
    "sg:province":"RI",
    "sg:tags":[
        "consultant"
    ],
    "wof:name":"Benefit Development Group",
    "wof:placetype":"venue"
},
  "geometry": {"coordinates":[-71.422943,41.829239],"type":"Point"}
}