{
  "type": "Feature",
  "properties": {
    "addr:full":"38 Main St Westerly RI 02891",
    "addr:housenumber":"38",
    "addr:postcode":"02891",
    "addr:street":"Main St",
    "iso:country":"US",
    "sg:address":"38 Main St",
    "sg:city":"Westerly",
    "sg:classifiers":[
        {
            "category":"Utilities",
            "subcategory":"Telephone",
            "type":"Services"
        }
    ],
    "sg:phone":"+1 401 348 6453",
    "sg:postcode":"02891",
    "sg:province":"RI",
    "sg:tags":[
        "telecommunication"
    ],
    "wof:name":"Verizon",
    "wof:placetype":"venue"
},
  "geometry": {"coordinates":[-71.831384,41.376969],"type":"Point"}
}