{
  "type": "Feature",
  "properties": {
    "addr:full":"3 Poplar Cir Cranston RI 02920",
    "addr:housenumber":"3",
    "addr:postcode":"02920",
    "addr:street":"Poplar Cir",
    "iso:country":"US",
    "sg:address":"3 Poplar Cir",
    "sg:city":"Cranston",
    "sg:classifiers":[
        {
            "category":"Manufacturing",
            "subcategory":"Jewelry",
            "type":"Manufacturing & Wholesale Goods"
        }
    ],
    "sg:phone":"+1 401 421 4674",
    "sg:postcode":"02920",
    "sg:province":"RI",
    "sg:tags":[
        "precious",
        "metal",
        "costume",
        "mfg"
    ],
    "wof:name":"Brown & Mills Corporation",
    "wof:placetype":"venue"
},
  "geometry": {"coordinates":[-71.45414700000001,41.756323],"type":"Point"}
}