{
  "type": "Feature",
  "properties": {
    "addr:full":"761 Nooseneck Hill Rd West Greenwich RI 02817",
    "addr:housenumber":"761",
    "addr:postcode":"02817",
    "addr:street":"Nooseneck Hill Rd",
    "iso:country":"US",
    "sg:address":"761 Nooseneck Hill Rd",
    "sg:city":"West Greenwich",
    "sg:classifiers":[
        {
            "category":"Wholesale",
            "subcategory":"Non-durable Goods",
            "type":"Manufacturing & Wholesale Goods"
        }
    ],
    "sg:phone":"+1 401 397 2201",
    "sg:postcode":"02817",
    "sg:province":"RI",
    "wof:name":"Ocean State Advertising Inc",
    "wof:placetype":"venue"
},
  "geometry": {"coordinates":[-71.63527499999999,41.615855],"type":"Point"}
}