{
  "type": "Feature",
  "properties": {
    "addr:full":"1163 Charles St North Providence RI 02904",
    "addr:housenumber":"1163",
    "addr:postcode":"02904",
    "addr:street":"Charles St",
    "iso:country":"US",
    "sg:address":"1163 Charles St",
    "sg:city":"North Providence",
    "sg:classifiers":[
        {
            "category":"Wholesale",
            "subcategory":"Electrical",
            "type":"Manufacturing & Wholesale Goods"
        }
    ],
    "sg:phone":"+1 401 727 0030",
    "sg:postcode":"02904",
    "sg:province":"RI",
    "sg:tags":[
        "sound",
        "equipment",
        "electronics",
        "system"
    ],
    "sg:website":"www.csiri.com",
    "wof:name":"Communication Systems Inc",
    "wof:placetype":"venue"
},
  "geometry": {"coordinates":[-71.426903,41.870701],"type":"Point"}
}