{
  "type": "Feature",
  "properties": {
    "iso:country":"US",
    "sg:address":"40 Fresno Rd",
    "sg:city":"Warwick",
    "sg:classifiers":[
        {
            "category":"Retail",
            "subcategory":"Auto Repair",
            "type":"Services"
        }
    ],
    "sg:phone":"+1 401 738 5162",
    "sg:postcode":"02886",
    "sg:province":"RI",
    "sg:tags":[
        "general"
    ],
    "wof:name":"Airport Auto Body",
    "wof:placetype":"venue"
},
  "geometry": {"coordinates":[-71.441158,41.726992],"type":"Point"}
}