{
  "type": "Feature",
  "properties": {
    "iso:country":"US",
    "sg:address":"6 Isthmus Rd",
    "sg:city":"Foster",
    "sg:classifiers":[
        {
            "category":"Organizations",
            "subcategory":"Labor Organization",
            "type":"Services"
        }
    ],
    "sg:phone":"+1 401 647 5305",
    "sg:postcode":"02825",
    "sg:province":"RI",
    "wof:name":"Iaap Prvidence Chapter 217130",
    "wof:placetype":"venue"
},
  "geometry": {"coordinates":[-71.686933,41.769295],"type":"Point"}
}