{
  "type": "Feature",
  "properties": {
    "addr:full":"2340 Diamond Hill Rd Cumberland RI 02864",
    "addr:housenumber":"2340",
    "addr:postcode":"02864",
    "addr:street":"Diamond Hill Rd",
    "iso:country":"US",
    "sg:address":"2340 Diamond Hill Rd",
    "sg:city":"Cumberland",
    "sg:classifiers":[
        {
            "category":"Professional",
            "subcategory":"Lawyer & Legal Services",
            "type":"Services"
        }
    ],
    "sg:phone":"+1 401 333 8200",
    "sg:postcode":"02864",
    "sg:province":"RI",
    "sg:tags":[
        "attorney"
    ],
    "wof:name":"Kevin P Landry Law Offices",
    "wof:placetype":"venue"
},
  "geometry": {"coordinates":[-71.401703,41.9534],"type":"Point"}
}