{
  "type": "Feature",
  "properties": {
    "addr:full":"422 Warwick Ave Warwick RI 02888",
    "addr:housenumber":"422",
    "addr:postcode":"02888",
    "addr:street":"Warwick Ave",
    "iso:country":"US",
    "sg:address":"422 Warwick Ave",
    "sg:city":"Warwick",
    "sg:classifiers":[
        {
            "category":"Bagels",
            "type":"Food & Drink"
        },
        {
            "category":"Coffee & Tea",
            "type":"Food & Drink"
        },
        {
            "category":"Food & Beverages",
            "subcategory":"Bakery",
            "type":"Retail Goods"
        },
        {
            "category":"Bakery",
            "type":"Food & Drink"
        },
        {
            "category":"Donuts",
            "type":"Food & Drink"
        }
    ],
    "sg:menulink":"http://www.allmenus.com/ri/warwick/138917-dunkin-donuts/menu/",
    "sg:phone":"+1 401 785 9332",
    "sg:postcode":"02888",
    "sg:province":"RI",
    "sg:tags":[
        "coffee",
        "tea",
        "american",
        "bagel",
        "bakery",
        "pastry"
    ],
    "wof:name":"Dunkin' Donuts",
    "wof:placetype":"venue"
},
  "geometry": {"coordinates":[-71.405002,41.764664],"type":"Point"}
}