{
  "type": "Feature",
  "properties": {
    "addr:full":"94 Pettaconsett Ave Warwick RI 02888",
    "addr:housenumber":"94",
    "addr:postcode":"02888",
    "addr:street":"Pettaconsett Ave",
    "iso:country":"US",
    "sg:address":"94 Pettaconsett Ave",
    "sg:city":"Warwick",
    "sg:classifiers":[
        {
            "category":"Professional",
            "subcategory":"Accounting & Tax Preparation",
            "type":"Services"
        }
    ],
    "sg:phone":"+1 401 781 3721",
    "sg:postcode":"02888",
    "sg:province":"RI",
    "wof:name":"Djs Bookkeeping",
    "wof:placetype":"venue"
},
  "geometry": {"coordinates":[-71.43106899999999,41.74917],"type":"Point"}
}