{
  "type": "Feature",
  "properties": {
    "iso:country":"US",
    "sg:address":"15 Railroad Ave",
    "sg:city":"Westerly",
    "sg:classifiers":[
        {
            "category":"Restaurant",
            "type":"Food & Drink"
        }
    ],
    "sg:menulink":"http://www.allmenus.com/ri/westerly/245016-thai-pepper/menu/",
    "sg:phone":"+1 401 348 0511",
    "sg:postcode":"02891",
    "sg:province":"RI",
    "sg:tags":[
        "thai",
        "asian"
    ],
    "wof:name":"Thai Pepper",
    "wof:placetype":"venue"
},
  "geometry": {"coordinates":[-71.82968200000001,41.380814],"type":"Point"}
}