{
  "type": "Feature",
  "properties": {
    "iso:country":"US",
    "sg:address":"9 Newman Ave",
    "sg:city":"Rumford",
    "sg:classifiers":[
        {
            "category":"Wholesale",
            "subcategory":"Jewelry",
            "type":"Manufacturing & Wholesale Goods"
        }
    ],
    "sg:phone":"+1 401 435 4854",
    "sg:postcode":"02916",
    "sg:province":"RI",
    "sg:tags":[
        "contractor"
    ],
    "wof:name":"Five Star Jewelry",
    "wof:placetype":"venue"
},
  "geometry": {"coordinates":[-71.354786,41.840454],"type":"Point"}
}