{
  "type": "Feature",
  "properties": {
    "iso:country":"US",
    "sg:address":"68 Scituate Ave",
    "sg:city":"Johnston",
    "sg:classifiers":[
        {
            "category":"Freight",
            "type":"Transportation"
        }
    ],
    "sg:phone":"+1 401 942 0704",
    "sg:postcode":"02919",
    "sg:province":"RI",
    "sg:tags":[
        "operator",
        "trucking"
    ],
    "wof:name":"Giardiana Transport",
    "wof:placetype":"venue"
},
  "geometry": {"coordinates":[-71.496048,41.804844],"type":"Point"}
}