{
  "type": "Feature",
  "properties": {
    "addr:full":"500 Stony Ln North Kingstown RI 02852",
    "addr:housenumber":"500",
    "addr:postcode":"02852",
    "addr:street":"Stony Ln",
    "iso:country":"US",
    "sg:address":"500 Stony Ln",
    "sg:city":"North Kingstown",
    "sg:classifiers":[
        {
            "category":"Retail",
            "subcategory":"Animal Services",
            "type":"Services"
        }
    ],
    "sg:phone":"+1 401 294 2400",
    "sg:postcode":"02852",
    "sg:province":"RI",
    "sg:tags":[
        "specialty"
    ],
    "wof:name":"Stony Lane Kennels Inc",
    "wof:placetype":"venue"
},
  "geometry": {"coordinates":[-71.482057,41.591257],"type":"Point"}
}