{
  "type": "Feature",
  "properties": {
    "iso:country":"US",
    "sg:address":"19 Brown Ave",
    "sg:city":"Johnston",
    "sg:classifiers":[
        {
            "category":"Professional",
            "type":"Services"
        }
    ],
    "sg:phone":"+1 401 764 0063",
    "sg:postcode":"02919",
    "sg:province":"RI",
    "sg:tags":[
        "establishment"
    ],
    "wof:name":"G-Force Customs",
    "wof:placetype":"venue"
},
  "geometry": {"coordinates":[-71.54846000000001,41.834363],"type":"Point"}
}