{
  "type": "Feature",
  "properties": {
    "iso:country":"US",
    "sg:address":"22 Charlene Ave",
    "sg:city":"Westerly",
    "sg:classifiers":[
        {
            "category":"Building & Trades",
            "subcategory":"Construction",
            "type":"Services"
        }
    ],
    "sg:phone":"+1 401 322 0679",
    "sg:postcode":"02891",
    "sg:province":"RI",
    "sg:tags":[
        "contractor"
    ],
    "wof:name":"South Cnty Stripping & Sealing",
    "wof:placetype":"venue"
},
  "geometry": {"coordinates":[-71.770259,41.341033],"type":"Point"}
}