{
  "type": "Feature",
  "properties": {
    "iso:country":"US",
    "sg:address":"100 Amica Way",
    "sg:city":"Lincoln",
    "sg:classifiers":[
        {
            "category":"Insurance",
            "subcategory":"Hazard Insurance",
            "type":"Services"
        }
    ],
    "sg:phone":"+1 401 334 0108",
    "sg:postcode":"02865",
    "sg:province":"RI",
    "sg:website":"www.amica.com",
    "wof:name":"Amica Mutual Insurance Company",
    "wof:placetype":"venue"
},
  "geometry": {"coordinates":[-71.460999,41.944199],"type":"Point"}
}