{
  "type": "Feature",
  "properties": {
    "iso:country":"US",
    "sg:address":"830 Dyer Ave",
    "sg:city":"Cranston",
    "sg:classifiers":[
        {
            "category":"Manufacturing",
            "subcategory":"Apparel",
            "type":"Manufacturing & Wholesale Goods"
        },
        {
            "category":"Wholesale",
            "subcategory":"Furniture",
            "type":"Manufacturing & Wholesale Goods"
        }
    ],
    "sg:phone":"+1 401 946 1737",
    "sg:postcode":"02920",
    "sg:province":"RI",
    "sg:tags":[
        "wire",
        "shelving",
        "closet",
        "install",
        "accessory"
    ],
    "wof:name":"Shelf Improvement Corporation",
    "wof:placetype":"venue"
},
  "geometry": {"coordinates":[-71.455996,41.787327],"type":"Point"}
}