{
  "type": "Feature",
  "properties": {
    "addr:full":"555 Metacom Ave Bristol RI 02809",
    "addr:housenumber":"555",
    "addr:postcode":"02809",
    "addr:street":"Metacom Ave",
    "iso:country":"US",
    "sg:address":"555 Metacom Ave",
    "sg:city":"Bristol",
    "sg:classifiers":[
        {
            "category":"Personal",
            "type":"Services"
        }
    ],
    "sg:phone":"+1 401 254 0400",
    "sg:postcode":"02809",
    "sg:province":"RI",
    "sg:tags":[
        "therapist",
        "massage"
    ],
    "wof:name":"In Touch",
    "wof:placetype":"venue"
},
  "geometry": {"coordinates":[-71.26331,41.692518],"type":"Point"}
}