{
  "type": "Feature",
  "properties": {
    "addr:full":"59 Shore Ave Warwick RI 02889",
    "addr:housenumber":"59",
    "addr:postcode":"02889",
    "addr:street":"Shore Ave",
    "iso:country":"US",
    "sg:address":"59 Shore Ave",
    "sg:city":"Warwick",
    "sg:classifiers":[
        {
            "category":"Building & Trades",
            "subcategory":"Construction",
            "type":"Services"
        }
    ],
    "sg:phone":"+1 401 732 6907",
    "sg:postcode":"02889",
    "sg:province":"RI",
    "sg:tags":[
        "carpentry",
        "contractor"
    ],
    "wof:name":"Davis Mac Carpentry",
    "wof:placetype":"venue"
},
  "geometry": {"coordinates":[-71.36682399999999,41.705508],"type":"Point"}
}