{
  "type": "Feature",
  "properties": {
    "iso:country":"US",
    "sg:address":"224 Benefit Street",
    "sg:city":"Providence",
    "sg:classifiers":[
        {
            "category":"Museum",
            "type":"Entertainment"
        }
    ],
    "sg:phone":"+1 401 454 6500",
    "sg:postcode":"02909",
    "sg:province":"RI",
    "sg:website":"www.risd.edu/museum.cfm",
    "wof:name":"RISD Museum",
    "wof:placetype":"venue"
},
  "geometry": {"coordinates":[-71.40712000000001,41.826523],"type":"Point"}
}