{
  "type": "Feature",
  "properties": {
    "iso:country":"US",
    "sg:address":"141 Power Rd",
    "sg:city":"Pawtucket",
    "sg:classifiers":[
        {
            "category":"Professional",
            "subcategory":"Lawyer & Legal Services",
            "type":"Services"
        }
    ],
    "sg:phone":"+1 401 722 4550",
    "sg:postcode":"02860",
    "sg:province":"RI",
    "wof:name":"Famiglietti & Carlin Ltd",
    "wof:placetype":"venue"
},
  "geometry": {"coordinates":[-71.413359,41.86425],"type":"Point"}
}