{
  "type": "Feature",
  "properties": {
    "iso:country":"US",
    "sg:address":"35 Dion Ave",
    "sg:city":"Tiverton",
    "sg:classifiers":[
        {
            "category":"Home & Garden",
            "subcategory":"Hardware",
            "type":"Retail Goods"
        }
    ],
    "sg:phone":"+1 401 625 5128",
    "sg:postcode":"02878",
    "sg:province":"RI",
    "wof:name":"A1 Enterprises",
    "wof:placetype":"venue"
},
  "geometry": {"coordinates":[-71.14023,41.588438],"type":"Point"}
}