{
  "type": "Feature",
  "properties": {
    "iso:country":"US",
    "sg:address":"921 Warwick Ave",
    "sg:city":"Warwick",
    "sg:classifiers":[
        {
            "category":"Real Estate",
            "subcategory":"Real Estate Agent",
            "type":"Services"
        }
    ],
    "sg:phone":"+1 401 781 1260",
    "sg:postcode":"02888",
    "sg:province":"RI",
    "sg:tags":[
        "building",
        "opera",
        "nonresidential"
    ],
    "wof:name":"Alton Properties LLC",
    "wof:placetype":"venue"
},
  "geometry": {"coordinates":[-71.404106,41.750086],"type":"Point"}
}