{
  "type": "Feature",
  "properties": {
    "addr:full":"724 Elmwood Ave Providence RI 02907",
    "addr:housenumber":"724",
    "addr:postcode":"02907",
    "addr:street":"Elmwood Ave",
    "iso:country":"US",
    "sg:address":"724 Elmwood Ave",
    "sg:city":"Providence",
    "sg:classifiers":[
        {
            "category":"Local Transit",
            "type":"Transportation"
        }
    ],
    "sg:phone":"+1 401 461 0273",
    "sg:postcode":"02907",
    "sg:province":"RI",
    "sg:tags":[
        "bus",
        "line"
    ],
    "wof:name":"J & J Transportation",
    "wof:placetype":"venue"
},
  "geometry": {"coordinates":[-71.42289599999999,41.792328],"type":"Point"}
}