{
  "type": "Feature",
  "properties": {
    "iso:country":"US",
    "sg:address":"8 Hope Furnace Rd",
    "sg:city":"Hope",
    "sg:classifiers":[
        {
            "category":"Personal",
            "subcategory":"Beauty Salon",
            "type":"Services"
        }
    ],
    "sg:phone":"+1 401 823 1290",
    "sg:postcode":"02831",
    "sg:province":"RI",
    "sg:tags":[
        "shop"
    ],
    "wof:name":"Rachels Creations Full Service",
    "wof:placetype":"venue"
},
  "geometry": {"coordinates":[-71.56881300000001,41.729905],"type":"Point"}
}