{
  "type": "Feature",
  "properties": {
    "iso:country":"US",
    "sg:address":"34 Potter Rd",
    "sg:city":"Wakefield",
    "sg:classifiers":[
        {
            "category":"Professional",
            "subcategory":"Management & Consulting",
            "type":"Services"
        }
    ],
    "sg:phone":"+1 401 783 8899",
    "sg:postcode":"02879",
    "sg:province":"RI",
    "sg:tags":[
        "business"
    ],
    "wof:name":"Seafood Market Analyst",
    "wof:placetype":"venue"
},
  "geometry": {"coordinates":[-71.529269,41.390673],"type":"Point"}
}