{
  "type": "Feature",
  "properties": {
    "addr:full":"20 Stewart St Warwick RI 02889",
    "addr:housenumber":"20",
    "addr:postcode":"02889",
    "addr:street":"Stewart St",
    "iso:country":"US",
    "sg:address":"20 Stewart St",
    "sg:city":"Warwick",
    "sg:classifiers":[
        {
            "category":"Professional",
            "subcategory":"Business Services",
            "type":"Services"
        }
    ],
    "sg:phone":"+1 501 779 2687",
    "sg:postcode":"02889",
    "sg:province":"RI",
    "wof:name":"KG Relocations",
    "wof:placetype":"venue"
},
  "geometry": {"coordinates":[-71.394296,41.69614],"type":"Point"}
}