{
  "type": "Feature",
  "properties": {
    "iso:country":"US",
    "sg:address":"32 Mechanic Ave",
    "sg:city":"Woonsocket",
    "sg:classifiers":[
        {
            "category":"Manufacturing",
            "subcategory":"Chemicals & Compounds",
            "type":"Manufacturing & Wholesale Goods"
        }
    ],
    "sg:phone":"+1 401 765 0503",
    "sg:postcode":"02895",
    "sg:province":"RI",
    "sg:tags":[
        "adhesive",
        "manufacturer",
        "formulation",
        "epoxy",
        "custom"
    ],
    "wof:name":"Alpha International Corp",
    "wof:placetype":"venue"
},
  "geometry": {"coordinates":[-71.512424,42.009552],"type":"Point"}
}