{
  "type": "Feature",
  "properties": {
    "iso:country":"US",
    "sg:address":"106 Ferry Rd",
    "sg:city":"Bristol",
    "sg:classifiers":[
        {
            "category":"Real Estate",
            "subcategory":"Real Estate Agent",
            "type":"Services"
        }
    ],
    "sg:phone":"+1 401 253 9226",
    "sg:postcode":"02809",
    "sg:province":"RI",
    "wof:name":"Perry Family Realty LLC",
    "wof:placetype":"venue"
},
  "geometry": {"coordinates":[-71.265103,41.655448],"type":"Point"}
}