{
  "type": "Feature",
  "properties": {
    "addr:full":"1031 Ten Rod Rd North Kingstown RI 02852",
    "addr:housenumber":"1031",
    "addr:postcode":"02852",
    "addr:street":"Ten Rod Rd",
    "iso:country":"US",
    "sg:address":"1031 Ten Rod Rd",
    "sg:city":"North Kingstown",
    "sg:classifiers":[
        {
            "category":"Professional",
            "subcategory":"Accounting & Tax Preparation",
            "type":"Services"
        }
    ],
    "sg:phone":"+1 401 267 0164",
    "sg:postcode":"02852",
    "sg:province":"RI",
    "sg:tags":[
        "return",
        "filing"
    ],
    "wof:name":"H & R Block",
    "wof:placetype":"venue"
},
  "geometry": {"coordinates":[-71.49521,41.582432],"type":"Point"}
}