{
  "type": "Feature",
  "properties": {
    "iso:country":"US",
    "sg:address":"1206 Broad St",
    "sg:city":"Providence",
    "sg:classifiers":[
        {
            "category":"Bars & Pubs",
            "subcategory":"Nightclub",
            "type":"Food & Drink"
        }
    ],
    "sg:phone":"+1 401 865 6085",
    "sg:postcode":"02905",
    "sg:province":"RI",
    "sg:tags":[
        "club",
        "night"
    ],
    "wof:name":"La Isla Night Club",
    "wof:placetype":"venue"
},
  "geometry": {"coordinates":[-71.40877,41.793456],"type":"Point"}
}