{
  "type": "Feature",
  "properties": {
    "iso:country":"US",
    "sg:address":"171 Broadway",
    "sg:city":"Providence",
    "sg:classifiers":[
        {
            "category":"Professional",
            "subcategory":"Lawyer & Legal Services",
            "type":"Services"
        }
    ],
    "sg:phone":"+1 401 331 2191",
    "sg:postcode":"02903",
    "sg:province":"RI",
    "wof:name":"Durant Robert J Atty",
    "wof:placetype":"venue"
},
  "geometry": {"coordinates":[-71.42289700000001,41.821201],"type":"Point"}
}