{
  "type": "Feature",
  "properties": {
    "addr:full":"1800 Mendon Rd Cumberland RI 02864",
    "addr:housenumber":"1800",
    "addr:postcode":"02864",
    "addr:street":"Mendon Rd",
    "iso:country":"US",
    "sg:address":"1800 Mendon Rd",
    "sg:city":"Cumberland",
    "sg:classifiers":[
        {
            "category":"Wholesale",
            "subcategory":"Groceries",
            "type":"Manufacturing & Wholesale Goods"
        }
    ],
    "sg:phone":"+1 401 333 8848",
    "sg:postcode":"02864",
    "sg:province":"RI",
    "sg:tags":[
        "food",
        "product"
    ],
    "wof:name":"Simmering Soups",
    "wof:placetype":"venue"
},
  "geometry": {"coordinates":[-71.436166,41.944068],"type":"Point"}
}