{
  "type": "Feature",
  "properties": {
    "iso:country":"US",
    "sg:address":"166 Central Ave",
    "sg:city":"East Providence",
    "sg:classifiers":[
        {
            "category":"Local Transit",
            "type":"Transportation"
        }
    ],
    "sg:phone":"+1 401 434 6629",
    "sg:postcode":"02914",
    "sg:province":"RI",
    "sg:tags":[
        "passenger"
    ],
    "wof:name":"East Providence Limousine Inc",
    "wof:placetype":"venue"
},
  "geometry": {"coordinates":[-71.367035,41.823143],"type":"Point"}
}