{
  "type": "Feature",
  "properties": {
    "addr:full":"1403 Mendon Rd Cumberland RI 02864",
    "addr:housenumber":"1403",
    "addr:postcode":"02864",
    "addr:street":"Mendon Rd",
    "iso:country":"US",
    "sg:address":"1403 Mendon Rd",
    "sg:city":"Cumberland",
    "sg:classifiers":[
        {
            "category":"Professional",
            "subcategory":"Business Services",
            "type":"Services"
        }
    ],
    "sg:phone":"+1 401 334 4306",
    "sg:postcode":"02864",
    "sg:province":"RI",
    "sg:tags":[
        "drafting"
    ],
    "wof:name":"Drafting Sub Contractor",
    "wof:placetype":"venue"
},
  "geometry": {"coordinates":[-71.426905,41.933638],"type":"Point"}
}