{
  "type": "Feature",
  "properties": {
    "iso:country":"US",
    "sg:address":"189 Governor St",
    "sg:city":"Providence",
    "sg:classifiers":[
        {
            "category":"Health Services",
            "subcategory":"Clinic",
            "type":"Services"
        }
    ],
    "sg:phone":"+1 401 831 5262",
    "sg:postcode":"02906",
    "sg:province":"RI",
    "sg:tags":[
        "counseling",
        "mental"
    ],
    "wof:name":"Brenman Allan J Dr Psycholgst",
    "wof:placetype":"venue"
},
  "geometry": {"coordinates":[-71.393799,41.827],"type":"Point"}
}