{
  "type": "Feature",
  "properties": {
    "iso:country":"US",
    "sg:address":"1974 Mineral Spring Ave",
    "sg:city":"North Providence",
    "sg:classifiers":[
        {
            "category":"Food & Beverages",
            "subcategory":"Liquor & Beverages",
            "type":"Retail Goods"
        }
    ],
    "sg:phone":"+1 401 437 6400",
    "sg:postcode":"02904",
    "sg:province":"RI",
    "sg:tags":[
        "beer",
        "spirit",
        "wine"
    ],
    "wof:name":"Laurito's Liquors of North Providence",
    "wof:placetype":"venue"
},
  "geometry": {"coordinates":[-71.47090900000001,41.859706],"type":"Point"}
}