{
  "type": "Feature",
  "properties": {
    "addr:full":"55 Corliss St Providence RI 02904",
    "addr:housenumber":"55",
    "addr:postcode":"02904",
    "addr:street":"Corliss St",
    "iso:country":"US",
    "sg:address":"55 Corliss St",
    "sg:city":"Providence",
    "sg:classifiers":[
        {
            "category":"Government",
            "subcategory":"Post Office",
            "type":"Public Place"
        }
    ],
    "sg:phone":"+1 401 457 1600",
    "sg:postcode":"02904",
    "sg:province":"RI",
    "wof:name":"US Post Office",
    "wof:placetype":"venue"
},
  "geometry": {"coordinates":[-71.413231,41.83967],"type":"Point"}
}