{
  "type": "Feature",
  "properties": {
    "iso:country":"US",
    "sg:address":"8 Court Dr",
    "sg:city":"Lincoln",
    "sg:classifiers":[
        {
            "category":"Wholesale",
            "subcategory":"Home Furnishings",
            "type":"Manufacturing & Wholesale Goods"
        }
    ],
    "sg:phone":"+1 401 333 1166",
    "sg:postcode":"02865",
    "sg:province":"RI",
    "sg:tags":[
        "rug",
        "carpet"
    ],
    "wof:name":"CDS Inc",
    "wof:placetype":"venue"
},
  "geometry": {"coordinates":[-71.48042,41.930756],"type":"Point"}
}