{
  "type": "Feature",
  "properties": {
    "iso:country":"US",
    "sg:address":"226 Arlington Ave",
    "sg:city":"Warwick",
    "sg:classifiers":[
        {
            "category":"Retail",
            "subcategory":"Auto Repair",
            "type":"Services"
        }
    ],
    "sg:phone":"+1 401 263 1089",
    "sg:postcode":"02889",
    "sg:province":"RI",
    "sg:tags":[
        "general"
    ],
    "wof:name":"Motion Auto & Rv LLC",
    "wof:placetype":"venue"
},
  "geometry": {"coordinates":[-71.372332,41.701272],"type":"Point"}
}