{
  "type": "Feature",
  "properties": {
    "addr:full":"127 School St Pawtucket RI 02860",
    "addr:housenumber":"127",
    "addr:postcode":"02860",
    "addr:street":"School St",
    "iso:country":"US",
    "sg:address":"127 School St",
    "sg:city":"Pawtucket",
    "sg:classifiers":[
        {
            "category":"Health Services",
            "subcategory":"Doctor",
            "type":"Services"
        }
    ],
    "sg:phone":"+1 401 729 9400",
    "sg:postcode":"02860",
    "sg:province":"RI",
    "sg:tags":[
        "medicine",
        "physician",
        "surgeon",
        "sport"
    ],
    "sg:website":"www.sportsmedcenter.com",
    "wof:name":"Sports Medicine Orthopedics & Podiatry",
    "wof:placetype":"venue"
},
  "geometry": {"coordinates":[-71.380501,41.872601],"type":"Point"}
}