{
  "type": "Feature",
  "properties": {
    "iso:country":"US",
    "sg:address":"81 Black Point Ln",
    "sg:city":"Portsmouth",
    "sg:classifiers":[
        {
            "category":"Professional",
            "type":"Services"
        }
    ],
    "sg:phone":"+1 401 849 3833",
    "sg:postcode":"02871",
    "sg:province":"RI",
    "wof:name":"International Power Services",
    "wof:placetype":"venue"
},
  "geometry": {"coordinates":[-71.24341,41.53298],"type":"Point"}
}