{
  "type": "Feature",
  "properties": {
    "iso:country":"US",
    "sg:address":"29 South Rd",
    "sg:city":"Exeter",
    "sg:classifiers":[
        {
            "category":"Retail",
            "subcategory":"Repair Shop",
            "type":"Services"
        }
    ],
    "sg:phone":"+1 401 294 6523",
    "sg:postcode":"02822",
    "sg:province":"RI",
    "sg:tags":[
        "cesspool",
        "installation",
        "cleaning",
        "septic"
    ],
    "wof:name":"Ronnies Professional Services",
    "wof:placetype":"venue"
},
  "geometry": {"coordinates":[-71.53409000000001,41.575634],"type":"Point"}
}