{
  "type": "Feature",
  "properties": {
    "iso:country":"US",
    "sg:address":"410 Tiogue Ave",
    "sg:city":"Coventry",
    "sg:classifiers":[
        {
            "category":"Professional",
            "type":"Services"
        }
    ],
    "sg:phone":"+1 401 823 7800",
    "sg:postcode":"02816",
    "sg:province":"RI",
    "sg:tags":[
        "establishment"
    ],
    "wof:name":"Society For Amateur Scientists",
    "wof:placetype":"venue"
},
  "geometry": {"coordinates":[-71.545906,41.683993],"type":"Point"}
}