{
  "type": "Feature",
  "properties": {
    "addr:full":"142 Crest Dr Pawtucket RI 02861",
    "addr:housenumber":"142",
    "addr:postcode":"02861",
    "addr:street":"Crest Dr",
    "iso:country":"US",
    "sg:address":"142 Crest Dr",
    "sg:city":"Pawtucket",
    "sg:classifiers":[
        {
            "category":"Home & Garden",
            "subcategory":"Garden Supply",
            "type":"Retail Goods"
        }
    ],
    "sg:phone":"+1 401 727 2711",
    "sg:postcode":"02861",
    "sg:province":"RI",
    "sg:tags":[
        "sprinkler"
    ],
    "wof:name":"Datop Sprinkler Specialists",
    "wof:placetype":"venue"
},
  "geometry": {"coordinates":[-71.34200800000001,41.897907],"type":"Point"}
}