{
  "type": "Feature",
  "properties": {
    "addr:full":"14 Victory St South Kingstown RI 02879",
    "addr:housenumber":"14",
    "addr:postcode":"02879",
    "addr:street":"Victory St",
    "iso:country":"US",
    "sg:address":"14 Victory St",
    "sg:city":"South Kingstown",
    "sg:classifiers":[
        {
            "category":"Building & Trades",
            "subcategory":"Construction",
            "type":"Services"
        }
    ],
    "sg:phone":"+1 401 788 3525",
    "sg:postcode":"02879",
    "sg:province":"RI",
    "sg:tags":[
        "excavating",
        "contractor"
    ],
    "wof:name":"William Rose Inc",
    "wof:placetype":"venue"
},
  "geometry": {"coordinates":[-71.502048,41.443947],"type":"Point"}
}