{
  "type": "Feature",
  "properties": {
    "addr:full":"6 Primrose Ln Providence RI 02904",
    "addr:housenumber":"6",
    "addr:postcode":"02904",
    "addr:street":"Primrose Ln",
    "iso:country":"US",
    "sg:address":"6 Primrose Ln",
    "sg:city":"Providence",
    "sg:classifiers":[
        {
            "category":"Freight",
            "type":"Transportation"
        }
    ],
    "sg:phone":"+1 401 737 9421",
    "sg:postcode":"02904",
    "sg:province":"RI",
    "sg:tags":[
        "operator",
        "local",
        "trucking"
    ],
    "wof:name":"A Andrade Son Construction",
    "wof:placetype":"venue"
},
  "geometry": {"coordinates":[-71.460778,41.865661],"type":"Point"}
}