{
  "type": "Feature",
  "properties": {
    "iso:country":"US",
    "sg:address":"1070 Broad St",
    "sg:city":"Providence",
    "sg:classifiers":[
        {
            "category":"Restaurant",
            "type":"Food & Drink"
        }
    ],
    "sg:phone":"+1 401 780 8975",
    "sg:postcode":"02905",
    "sg:province":"RI",
    "wof:name":"Las Palmas Restaurant",
    "wof:placetype":"venue"
},
  "geometry": {"coordinates":[-71.412505,41.796681],"type":"Point"}
}