{
  "type": "Feature",
  "properties": {
    "iso:country":"US",
    "sg:address":"1257 Chalkstone Ave",
    "sg:city":"Providence",
    "sg:classifiers":[
        {
            "category":"Shopping",
            "subcategory":"Bicycles & Sporting Goods",
            "type":"Retail Goods"
        }
    ],
    "sg:phone":"+1 401 270 2576",
    "sg:postcode":"02908",
    "sg:province":"RI",
    "wof:name":"K&J Sports",
    "wof:placetype":"venue"
},
  "geometry": {"coordinates":[-71.45005399999999,41.832763],"type":"Point"}
}