{
  "type": "Feature",
  "properties": {
    "iso:country":"US",
    "sg:address":"26 Lindy Ave",
    "sg:city":"Providence",
    "sg:classifiers":[
        {
            "category":"Building & Trades",
            "subcategory":"Construction",
            "type":"Services"
        }
    ],
    "sg:phone":"+1 401 270 3020",
    "sg:postcode":"02908",
    "sg:province":"RI",
    "sg:tags":[
        "house"
    ],
    "wof:name":"Step By Step Construction RI",
    "wof:placetype":"venue"
},
  "geometry": {"coordinates":[-71.44931,41.834396],"type":"Point"}
}