{
  "type": "Feature",
  "properties": {
    "iso:country":"US",
    "sg:address":"59 Pershing St",
    "sg:city":"Cranston",
    "sg:classifiers":[
        {
            "category":"Freight",
            "type":"Transportation"
        }
    ],
    "sg:phone":"+1 401 270 0323",
    "sg:postcode":"02910",
    "sg:province":"RI",
    "sg:tags":[
        "operator",
        "local",
        "trucking"
    ],
    "wof:name":"Rl Jencks Trucking LLC",
    "wof:placetype":"venue"
},
  "geometry": {"coordinates":[-71.44174599999999,41.784432],"type":"Point"}
}