{
  "type": "Feature",
  "properties": {
    "iso:country":"US",
    "sg:address":"11 Belaire Dr",
    "sg:city":"Johnston",
    "sg:classifiers":[
        {
            "category":"Wholesale",
            "subcategory":"Non-durable Goods",
            "type":"Manufacturing & Wholesale Goods"
        }
    ],
    "sg:phone":"+1 401 231 4325",
    "sg:postcode":"02919",
    "sg:province":"RI",
    "sg:tags":[
        "calendar"
    ],
    "wof:name":"BBC Calendar & Advertising",
    "wof:placetype":"venue"
},
  "geometry": {"coordinates":[-71.48956,41.834495],"type":"Point"}
}