{
  "type": "Feature",
  "properties": {
    "iso:country":"US",
    "sg:address":"76 Holly Ln",
    "sg:city":"Cumberland",
    "sg:classifiers":[
        {
            "category":"Professional",
            "subcategory":"Testing Lab",
            "type":"Services"
        }
    ],
    "sg:phone":"+1 401 727 2550",
    "sg:postcode":"02864",
    "sg:province":"RI",
    "sg:tags":[
        "correction",
        "radon"
    ],
    "wof:name":"Radon Management",
    "wof:placetype":"venue"
},
  "geometry": {"coordinates":[-71.385606,41.974374],"type":"Point"}
}