{
  "type": "Feature",
  "properties": {
    "addr:full":"2312 Pawtucket Ave East Providence RI 02914",
    "addr:postcode":"2312;02914",
    "addr:street":"Pawtucket Ave",
    "iso:country":"US",
    "sg:address":"2312 Pawtucket Ave",
    "sg:city":"East Providence",
    "sg:classifiers":[
        {
            "category":"Retail",
            "subcategory":"Auto Rental",
            "type":"Services"
        }
    ],
    "sg:phone":"+1 401 435 3300",
    "sg:postcode":"02914",
    "sg:province":"RI",
    "sg:tags":[
        "renting",
        "automobile"
    ],
    "wof:name":"Thrifty Car Rental",
    "wof:placetype":"venue"
},
  "geometry": {"coordinates":[-71.358445,41.812043],"type":"Point"}
}