{
  "type": "Feature",
  "properties": {
    "iso:country":"US",
    "sg:address":"204 Rounds Ave",
    "sg:city":"Providence",
    "sg:classifiers":[
        {
            "category":"Shopping",
            "subcategory":"Used Merchandise",
            "type":"Retail Goods"
        }
    ],
    "sg:phone":"+1 401 781 9348",
    "sg:postcode":"02907",
    "sg:province":"RI",
    "wof:name":"Kevorkians Antiques & No",
    "wof:placetype":"venue"
},
  "geometry": {"coordinates":[-71.428061,41.787753],"type":"Point"}
}