{
  "type": "Feature",
  "properties": {
    "addr:full":"146 Anoka Ave Barrington RI 02806",
    "addr:housenumber":"146",
    "addr:postcode":"02806",
    "addr:street":"Anoka Ave",
    "iso:country":"US",
    "sg:address":"146 Anoka Ave",
    "sg:city":"Barrington",
    "sg:classifiers":[
        {
            "category":"Banks & Credit Unions",
            "subcategory":"Investment Brokerage",
            "type":"Services"
        }
    ],
    "sg:phone":"+1 401 245 0856",
    "sg:postcode":"02806",
    "sg:province":"RI",
    "sg:tags":[
        "advisory",
        "financial"
    ],
    "wof:name":"Mc Nair & Mc Nair",
    "wof:placetype":"venue"
},
  "geometry": {"coordinates":[-71.312515,41.738532],"type":"Point"}
}