{
  "type": "Feature",
  "properties": {
    "addr:full":"21 Mount Hope Ave Providence RI 02906",
    "addr:housenumber":"21",
    "addr:postcode":"02906",
    "addr:street":"Mount Hope Ave",
    "iso:country":"US",
    "sg:address":"21 Mount Hope Ave",
    "sg:city":"Providence",
    "sg:classifiers":[
        {
            "category":"Building & Trades",
            "subcategory":"Construction",
            "type":"Services"
        }
    ],
    "sg:phone":"+1 401 751 3344",
    "sg:postcode":"02906",
    "sg:province":"RI",
    "sg:tags":[
        "industrial"
    ],
    "wof:name":"Drw Construction Inc",
    "wof:placetype":"venue"
},
  "geometry": {"coordinates":[-71.402086,41.840363],"type":"Point"}
}