{
  "type": "Feature",
  "properties": {
    "addr:full":"1224 Broad St Providence RI 02905",
    "addr:housenumber":"1224",
    "addr:postcode":"02905",
    "addr:street":"Broad St",
    "iso:country":"US",
    "sg:address":"1224 Broad St",
    "sg:city":"Providence",
    "sg:classifiers":[
        {
            "category":"Restaurant",
            "type":"Food & Drink"
        }
    ],
    "sg:phone":"+1 401 941 3598",
    "sg:postcode":"02905",
    "sg:province":"RI",
    "sg:tags":[
        "eating"
    ],
    "wof:name":"Malecon Restaurant Inc",
    "wof:placetype":"venue"
},
  "geometry": {"coordinates":[-71.408125,41.793046],"type":"Point"}
}