{
  "type": "Feature",
  "properties": {
    "iso:country":"US",
    "sg:address":"20 Rogler Farm Rd",
    "sg:city":"Smithfield",
    "sg:classifiers":[
        {
            "category":"Professional",
            "subcategory":"Advertising",
            "type":"Services"
        }
    ],
    "sg:phone":"+1 401 231 2480",
    "sg:postcode":"02917",
    "sg:province":"RI",
    "sg:tags":[
        "mail",
        "mailing",
        "direct",
        "shipping"
    ],
    "wof:name":"Pro Typing & Mailing Service",
    "wof:placetype":"venue"
},
  "geometry": {"coordinates":[-71.544662,41.927906],"type":"Point"}
}