{
  "type": "Feature",
  "properties": {
    "iso:country":"US",
    "sg:address":"40 Fenwood Ave",
    "sg:city":"Smithfield",
    "sg:classifiers":[
        {
            "category":"Recreation",
            "type":"Entertainment"
        }
    ],
    "sg:phone":"+1 401 231 9771",
    "sg:postcode":"02917",
    "sg:province":"RI",
    "sg:tags":[
        "club",
        "membership"
    ],
    "wof:name":"P A Club",
    "wof:placetype":"venue"
},
  "geometry": {"coordinates":[-71.502917,41.88575],"type":"Point"}
}