{
  "type": "Feature",
  "properties": {
    "iso:country":"US",
    "sg:address":"55 Memorial Blvd",
    "sg:city":"Newport",
    "sg:classifiers":[
        {
            "category":"Professional",
            "subcategory":"Lawyer & Legal Services",
            "type":"Services"
        }
    ],
    "sg:phone":"+1 401 841 5700",
    "sg:postcode":"02840",
    "sg:province":"RI",
    "sg:tags":[
        "attorney"
    ],
    "wof:name":"Jeremy W Howe",
    "wof:placetype":"venue"
},
  "geometry": {"coordinates":[-71.303284,41.483424],"type":"Point"}
}