{
  "type": "Feature",
  "properties": {
    "iso:country":"US",
    "sg:address":"9 Church St",
    "sg:city":"Pascoag",
    "sg:classifiers":[
        {
            "category":"Manufacturing",
            "subcategory":"Printing",
            "type":"Manufacturing & Wholesale Goods"
        }
    ],
    "sg:phone":"+1 401 568 2565",
    "sg:postcode":"02859",
    "sg:province":"RI",
    "sg:tags":[
        "newspaper",
        "publishing"
    ],
    "wof:name":"Evening Call Publishing Co",
    "wof:placetype":"venue"
},
  "geometry": {"coordinates":[-71.704694,41.956619],"type":"Point"}
}