{
  "type": "Feature",
  "properties": {
    "iso:country":"US",
    "sg:address":"1894 Smith St",
    "sg:city":"North Providence",
    "sg:classifiers":[
        {
            "category":"Professional",
            "type":"Services"
        }
    ],
    "sg:phone":"+1 401 233 0115",
    "sg:postcode":"02911",
    "sg:province":"RI",
    "sg:tags":[
        "establishment"
    ],
    "wof:name":"Prism Technologies Inc",
    "wof:placetype":"venue"
},
  "geometry": {"coordinates":[-71.477817,41.855399],"type":"Point"}
}