{
  "type": "Feature",
  "properties": {
    "iso:country":"US",
    "sg:address":"543 Branch Ave",
    "sg:city":"Providence",
    "sg:classifiers":[
        {
            "category":"Retail",
            "subcategory":"Repair Shop",
            "type":"Services"
        },
        {
            "category":"Wholesale",
            "subcategory":"Electrical",
            "type":"Manufacturing & Wholesale Goods"
        }
    ],
    "sg:phone":"+1 401 351 7848",
    "sg:postcode":"02904",
    "sg:province":"RI",
    "sg:tags":[
        "cleaners",
        "household",
        "parts",
        "appliance",
        "vacuum"
    ],
    "wof:name":"Advantage Sewing & Vacuum Ctr",
    "wof:placetype":"venue"
},
  "geometry": {"coordinates":[-71.42141599999999,41.850899],"type":"Point"}
}