{
  "type": "Feature",
  "properties": {
    "iso:country":"US",
    "sg:address":"1390 Mendon Rd",
    "sg:city":"Cumberland",
    "sg:classifiers":[
        {
            "category":"Personal",
            "subcategory":"Beauty Salon",
            "type":"Services"
        }
    ],
    "sg:phone":"+1 401 334 1025",
    "sg:postcode":"02864",
    "sg:province":"RI",
    "sg:tags":[
        "shop"
    ],
    "wof:name":"Shears Of Cumberland Inc",
    "wof:placetype":"venue"
},
  "geometry": {"coordinates":[-71.42719700000001,41.933734],"type":"Point"}
}