{
  "type": "Feature",
  "properties": {
    "iso:country":"US",
    "sg:address":"34 Bellevue Ave",
    "sg:city":"Westerly",
    "sg:classifiers":[
        {
            "category":"Banks & Credit Unions",
            "subcategory":"Bank",
            "type":"Services"
        }
    ],
    "sg:phone":"+1 401 315 0083",
    "sg:postcode":"02891",
    "sg:province":"RI",
    "sg:tags":[
        "loan",
        "real estate"
    ],
    "wof:name":"Argent Mortgage Wholesale",
    "wof:placetype":"venue"
},
  "geometry": {"coordinates":[-71.816748,41.379983],"type":"Point"}
}