{
  "type": "Feature",
  "properties": {
    "addr:full":"71 Olive St Providence RI 02906",
    "addr:housenumber":"71",
    "addr:postcode":"02906",
    "addr:street":"Olive St",
    "iso:country":"US",
    "sg:address":"71 Olive St",
    "sg:city":"Providence",
    "sg:classifiers":[
        {
            "category":"Shopping",
            "subcategory":"Books",
            "type":"Retail Goods"
        }
    ],
    "sg:phone":"+1 401 863 3168",
    "sg:postcode":"02906",
    "sg:province":"RI",
    "sg:tags":[
        "dealer"
    ],
    "wof:name":"Brown Bookstore",
    "wof:placetype":"venue"
},
  "geometry": {"coordinates":[-71.401847,41.828321],"type":"Point"}
}