{
  "type": "Feature",
  "properties": {
    "iso:country":"US",
    "sg:address":"37 Meadow Rd",
    "sg:city":"Woonsocket",
    "sg:classifiers":[
        {
            "category":"Farming",
            "subcategory":"Farm",
            "type":"Manufacturing & Wholesale Goods"
        }
    ],
    "sg:phone":"+1 401 765 2850",
    "sg:postcode":"02895",
    "sg:province":"RI",
    "sg:tags":[
        "crop",
        "general"
    ],
    "wof:name":"George J Hickey",
    "wof:placetype":"venue"
},
  "geometry": {"coordinates":[-71.522141,42.009216],"type":"Point"}
}