{
  "type": "Feature",
  "properties": {
    "iso:country":"US",
    "sg:address":"204 Carleton St",
    "sg:city":"Providence",
    "sg:classifiers":[
        {
            "category":"Restaurant",
            "type":"Food & Drink"
        }
    ],
    "sg:phone":"+1 401 331 8279",
    "sg:postcode":"02908",
    "sg:province":"RI",
    "sg:tags":[
        "family"
    ],
    "wof:name":"Katchy Kitchen",
    "wof:placetype":"venue"
},
  "geometry": {"coordinates":[-71.44666100000001,41.825589],"type":"Point"}
}