{
  "type": "Feature",
  "properties": {
    "addr:full":"10 Reynolds Rd Chepachet RI 02814",
    "addr:housenumber":"10",
    "addr:postcode":"02814",
    "addr:street":"Reynolds Rd",
    "iso:country":"US",
    "sg:address":"10 Reynolds Rd",
    "sg:city":"Chepachet",
    "sg:classifiers":[
        {
            "category":"Arts & Performance",
            "subcategory":"Theater",
            "type":"Entertainment"
        }
    ],
    "sg:phone":"+1 401 647 1996",
    "sg:postcode":"02814",
    "sg:province":"RI",
    "sg:tags":[
        "live",
        "music"
    ],
    "wof:name":"System Disc Jockey",
    "wof:placetype":"venue"
},
  "geometry": {"coordinates":[-71.76925799999999,41.915508],"type":"Point"}
}