{
  "type": "Feature",
  "properties": {
    "addr:full":"93 Hazel St Woonsocket RI 02895",
    "addr:housenumber":"93",
    "addr:postcode":"02895",
    "addr:street":"Hazel St",
    "iso:country":"US",
    "sg:address":"93 Hazel St",
    "sg:city":"Woonsocket",
    "sg:classifiers":[
        {
            "category":"Retail",
            "subcategory":"Auto Rental",
            "type":"Services"
        }
    ],
    "sg:phone":"+1 401 765 4197",
    "sg:postcode":"02895",
    "sg:province":"RI",
    "sg:tags":[
        "renting",
        "truck",
        "leasing"
    ],
    "wof:name":"Budget Truck Rental",
    "wof:placetype":"venue"
},
  "geometry": {"coordinates":[-71.505222,42.011281],"type":"Point"}
}