{
  "type": "Feature",
  "properties": {
    "iso:country":"US",
    "sg:address":"500 Indian Corner Rd",
    "sg:city":"Saunderstown",
    "sg:classifiers":[
        {
            "category":"Wholesale",
            "subcategory":"Toys & Hobbies",
            "type":"Manufacturing & Wholesale Goods"
        }
    ],
    "sg:phone":"+1 401 295 4693",
    "sg:postcode":"02874",
    "sg:province":"RI",
    "sg:tags":[
        "wholesaler"
    ],
    "wof:name":"Brewers Wholesale Supl Wrhse",
    "wof:placetype":"venue"
},
  "geometry": {"coordinates":[-71.508387,41.532112],"type":"Point"}
}