{
  "type": "Feature",
  "properties": {
    "iso:country":"US",
    "sg:address":"1205 Park Ave",
    "sg:city":"Woonsocket",
    "sg:classifiers":[
        {
            "category":"Health Services",
            "subcategory":"Chiropractor",
            "type":"Services"
        }
    ],
    "sg:phone":"+1 401 769 3854",
    "sg:postcode":"02895",
    "sg:province":"RI",
    "wof:name":"Ramella Chiropractic Offices",
    "wof:placetype":"venue"
},
  "geometry": {"coordinates":[-71.51565600000001,41.986654],"type":"Point"}
}