{
  "type": "Feature",
  "properties": {
    "iso:country":"US",
    "sg:address":"871 Harris Ave",
    "sg:city":"Woonsocket",
    "sg:classifiers":[
        {
            "category":"Organizations",
            "subcategory":"Religious Organization",
            "type":"Services"
        }
    ],
    "sg:phone":"+1 401 769 8320",
    "sg:postcode":"02895",
    "sg:province":"RI",
    "sg:tags":[
        "churches-lutheran",
        "church"
    ],
    "wof:name":"Saint Mark Lutheran Church",
    "wof:placetype":"venue"
},
  "geometry": {"coordinates":[-71.527473,42.014568],"type":"Point"}
}