{
  "type": "Feature",
  "properties": {
    "iso:country":"US",
    "sg:address":"16 Catherine St",
    "sg:city":"Newport",
    "sg:classifiers":[
        {
            "category":"Travel",
            "subcategory":"Hotels & Motels",
            "type":"Entertainment"
        }
    ],
    "sg:phone":"+1 401 849 2469",
    "sg:postcode":"02840",
    "sg:province":"RI",
    "wof:name":"Inn On Bellevue",
    "wof:placetype":"venue"
},
  "geometry": {"coordinates":[-71.30773000000001,41.487508],"type":"Point"}
}