{
  "type": "Feature",
  "properties": {
    "addr:full":"630 Rathbun St Blackstone RI 01504",
    "addr:housenumber":"630",
    "addr:postcode":"01504",
    "addr:street":"Rathbun St",
    "iso:country":"US",
    "sg:address":"630 Rathbun St",
    "sg:city":"Blackstone",
    "sg:classifiers":[
        {
            "category":"Organizations",
            "subcategory":"Religious Organization",
            "type":"Services"
        }
    ],
    "sg:phone":"+1 508 883 7206",
    "sg:postcode":"01504",
    "sg:province":"RI",
    "sg:tags":[
        "clergy"
    ],
    "wof:name":"St Theresa's Rectory",
    "wof:placetype":"venue"
},
  "geometry": {"coordinates":[-71.501668,42.018687],"type":"Point"}
}