{
  "type": "Feature",
  "properties": {
    "iso:country":"US",
    "sg:address":"390 Main St",
    "sg:city":"Wakefield",
    "sg:classifiers":[
        {
            "category":"Health Services",
            "subcategory":"Doctor",
            "type":"Services"
        }
    ],
    "sg:phone":"+1 401 789 8693",
    "sg:postcode":"02879",
    "sg:province":"RI",
    "wof:name":"Joseph L Di Sano",
    "wof:placetype":"venue"
},
  "geometry": {"coordinates":[-71.50066700000001,41.437305],"type":"Point"}
}