{
  "type": "Feature",
  "properties": {
    "addr:full":"1099 Broad St Providence RI 02905",
    "addr:housenumber":"1099",
    "addr:postcode":"02905",
    "addr:street":"Broad St",
    "iso:country":"US",
    "sg:address":"1099 Broad St",
    "sg:city":"Providence",
    "sg:classifiers":[
        {
            "category":"Shopping",
            "subcategory":"Used Merchandise",
            "type":"Retail Goods"
        }
    ],
    "sg:phone":"+1 401 461 2693",
    "sg:postcode":"02905",
    "sg:province":"RI",
    "wof:name":"Tko Pawn Brokers",
    "wof:placetype":"venue"
},
  "geometry": {"coordinates":[-71.410836,41.795028],"type":"Point"}
}