{
  "type": "Feature",
  "properties": {
    "addr:full":"170 Fountain Ave Cranston RI 02920",
    "addr:housenumber":"170",
    "addr:postcode":"02920",
    "addr:street":"Fountain Ave",
    "iso:country":"US",
    "sg:address":"170 Fountain Ave",
    "sg:city":"Cranston",
    "sg:classifiers":[
        {
            "category":"Building & Trades",
            "subcategory":"Construction",
            "type":"Services"
        }
    ],
    "sg:phone":"+1 401 942 6420",
    "sg:postcode":"02920",
    "sg:province":"RI",
    "sg:tags":[
        "sheet",
        "metal",
        "contractor"
    ],
    "wof:name":"Duct Systems Inc",
    "wof:placetype":"venue"
},
  "geometry": {"coordinates":[-71.45452400000001,41.795055],"type":"Point"}
}