{
  "type": "Feature",
  "properties": {
    "addr:full":"3457 Post Rd Warwick RI 02886",
    "addr:housenumber":"3457",
    "addr:postcode":"02886",
    "addr:street":"Post Rd",
    "iso:country":"US",
    "sg:address":"3457 Post Rd",
    "sg:city":"Warwick",
    "sg:classifiers":[
        {
            "category":"Professional",
            "subcategory":"Lawyer & Legal Services",
            "type":"Services"
        }
    ],
    "sg:phone":"+1 401 732 4970",
    "sg:postcode":"02886",
    "sg:province":"RI",
    "sg:tags":[
        "attorney"
    ],
    "wof:name":"James A Vespia",
    "wof:placetype":"venue"
},
  "geometry": {"coordinates":[-71.45702,41.694257],"type":"Point"}
}