{
  "type": "Feature",
  "properties": {
    "iso:country":"US",
    "sg:address":"1452 Broncos Hwy",
    "sg:city":"Harrisville",
    "sg:classifiers":[
        {
            "category":"Personal",
            "subcategory":"Barber",
            "type":"Services"
        }
    ],
    "sg:phone":"+1 401 567 9009",
    "sg:postcode":"02830",
    "sg:province":"RI",
    "wof:name":"One 02 Barber Shop",
    "wof:placetype":"venue"
},
  "geometry": {"coordinates":[-71.64269299999999,41.968282],"type":"Point"}
}