{
  "type": "Feature",
  "properties": {
    "iso:country":"US",
    "sg:address":"33 Red Feather Trl N",
    "sg:city":"Wakefield",
    "sg:classifiers":[
        {
            "category":"Building & Trades",
            "subcategory":"Construction",
            "type":"Services"
        }
    ],
    "sg:phone":"+1 401 789 0339",
    "sg:postcode":"02879",
    "sg:province":"RI",
    "sg:tags":[
        "contractor"
    ],
    "wof:name":"Miro & Sons Masonry",
    "wof:placetype":"venue"
},
  "geometry": {"coordinates":[-71.462306,41.477447],"type":"Point"}
}