{
  "type": "Feature",
  "properties": {
    "iso:country":"US",
    "sg:address":"46 Spice Bush Trl",
    "sg:city":"Narragansett",
    "sg:classifiers":[
        {
            "category":"Building & Trades",
            "subcategory":"Construction",
            "type":"Services"
        }
    ],
    "sg:phone":"+1 401 789 6819",
    "sg:postcode":"02882",
    "sg:province":"RI",
    "sg:tags":[
        "house"
    ],
    "wof:name":"Timberline Construction Inc",
    "wof:placetype":"venue"
},
  "geometry": {"coordinates":[-71.445059,41.473736],"type":"Point"}
}