{
  "type": "Feature",
  "properties": {
    "addr:full":"78 Dean St Providence RI 02903",
    "addr:housenumber":"78",
    "addr:postcode":"02903",
    "addr:street":"Dean St",
    "iso:country":"US",
    "sg:address":"78 Dean St",
    "sg:city":"Providence",
    "sg:classifiers":[
        {
            "category":"Professional",
            "subcategory":"Employment Agencies",
            "type":"Services"
        }
    ],
    "sg:phone":"+1 401 751 8900",
    "sg:postcode":"02903",
    "sg:province":"RI",
    "sg:website":"www.laborready.com",
    "wof:name":"Labor Ready",
    "wof:placetype":"venue"
},
  "geometry": {"coordinates":[-71.425301,41.824402],"type":"Point"}
}