{
  "type": "Feature",
  "properties": {
    "iso:country":"US",
    "sg:address":"25 Creighton St",
    "sg:city":"Providence",
    "sg:classifiers":[
        {
            "category":"Real Estate",
            "subcategory":"Architect",
            "type":"Services"
        }
    ],
    "sg:phone":"+1 401 521 6867",
    "sg:postcode":"02906",
    "sg:province":"RI",
    "wof:name":"Bradford Derek Archt",
    "wof:placetype":"venue"
},
  "geometry": {"coordinates":[-71.40479999999999,41.8335],"type":"Point"}
}