{
  "type": "Feature",
  "properties": {
    "iso:country":"US",
    "sg:address":"640 Thames St",
    "sg:city":"Newport",
    "sg:classifiers":[
        {
            "category":"Real Estate",
            "subcategory":"Real Estate Agent",
            "type":"Services"
        }
    ],
    "sg:phone":"+1 401 849 9192",
    "sg:postcode":"02840",
    "sg:province":"RI",
    "sg:website":"www.c21accessamerica.com",
    "wof:name":"Century 21 Access America",
    "wof:placetype":"venue"
},
  "geometry": {"coordinates":[-71.313941,41.475604],"type":"Point"}
}