{
  "type": "Feature",
  "properties": {
    "addr:full":"100 N Main St Providence RI 02903",
    "addr:housenumber":"100",
    "addr:postcode":"02903",
    "addr:street":"N Main St",
    "iso:country":"US",
    "sg:address":"100 N Main St",
    "sg:city":"Providence",
    "sg:classifiers":[
        {
            "category":"Building & Trades",
            "subcategory":"Locksmith",
            "type":"Services"
        }
    ],
    "sg:phone":"+1 401 515 0240",
    "sg:postcode":"02903",
    "sg:province":"RI",
    "sg:tags":[
        "key"
    ],
    "wof:name":"My 24 7 Locksmith",
    "wof:placetype":"venue"
},
  "geometry": {"coordinates":[-71.40945000000001,41.827857],"type":"Point"}
}