{
  "type": "Feature",
  "properties": {
    "iso:country":"US",
    "sg:address":"4430 Post Rd",
    "sg:city":"East Greenwich",
    "sg:classifiers":[
        {
            "category":"Real Estate",
            "subcategory":"Real Estate Operator",
            "type":"Services"
        }
    ],
    "sg:phone":"+1 401 884 1702",
    "sg:postcode":"02818",
    "sg:province":"RI",
    "sg:tags":[
        "condominium"
    ],
    "wof:name":"Ocean Point Condominiums",
    "wof:placetype":"venue"
},
  "geometry": {"coordinates":[-71.448154,41.670912],"type":"Point"}
}