{
  "type": "Feature",
  "properties": {
    "iso:country":"US",
    "sg:address":"1676 E Main Rd",
    "sg:city":"Portsmouth",
    "sg:classifiers":[
        {
            "category":"Wholesale",
            "subcategory":"Machinery & Supplies",
            "type":"Manufacturing & Wholesale Goods"
        }
    ],
    "sg:phone":"+1 401 683 3199",
    "sg:postcode":"02871",
    "sg:province":"RI",
    "sg:tags":[
        "durable"
    ],
    "sg:website":"www.malcom.com",
    "wof:name":"Malcom Co",
    "wof:placetype":"venue"
},
  "geometry": {"coordinates":[-71.252478,41.580086],"type":"Point"}
}