{
  "type": "Feature",
  "properties": {
    "iso:country":"US",
    "sg:address":"124 Washington St",
    "sg:city":"Providence",
    "sg:classifiers":[
        {
            "category":"Professional",
            "subcategory":"Accounting & Tax Preparation",
            "type":"Services"
        }
    ],
    "sg:phone":"+1 401 861 2086",
    "sg:postcode":"02903",
    "sg:province":"RI",
    "wof:name":"Verdolino & Lowey PC",
    "wof:placetype":"venue"
},
  "geometry": {"coordinates":[-71.41542699999999,41.822575],"type":"Point"}
}