{
  "type": "Feature",
  "properties": {
    "addr:full":"25 Maxson St Ashaway RI 02804",
    "addr:housenumber":"25",
    "addr:postcode":"02804",
    "addr:street":"Maxson St",
    "iso:country":"US",
    "sg:address":"25 Maxson St",
    "sg:city":"Ashaway",
    "sg:classifiers":[
        {
            "category":"Organizations",
            "subcategory":"Religious Organization",
            "type":"Services"
        }
    ],
    "sg:phone":"+1 401 377 4917",
    "sg:postcode":"02804",
    "sg:province":"RI",
    "sg:tags":[
        "church"
    ],
    "wof:name":"Babcock Presbyterian Church",
    "wof:placetype":"venue"
},
  "geometry": {"coordinates":[-71.79518899999999,41.41454],"type":"Point"}
}