{
  "type": "Feature",
  "properties": {
    "addr:full":"2510 Mendon Rd Cumberland RI 02864",
    "addr:housenumber":"2510",
    "addr:postcode":"02864",
    "addr:street":"Mendon Rd",
    "iso:country":"US",
    "sg:address":"2510 Mendon Rd",
    "sg:city":"Cumberland",
    "sg:classifiers":[
        {
            "category":"Social Services",
            "subcategory":"Adult Care",
            "type":"Services"
        }
    ],
    "sg:phone":"+1 401 658 3992",
    "sg:postcode":"02864",
    "sg:province":"RI",
    "sg:tags":[
        "residential"
    ],
    "wof:name":"House Of Compassion Inc",
    "wof:placetype":"venue"
},
  "geometry": {"coordinates":[-71.444343,41.961695],"type":"Point"}
}