{
  "type": "Feature",
  "properties": {
    "iso:country":"US",
    "sg:address":"100 Rustic Hill Rd",
    "sg:city":"Chepachet",
    "sg:classifiers":[
        {
            "category":"Travel",
            "subcategory":"Campground",
            "type":"Entertainment"
        }
    ],
    "sg:phone":"+1 401 647 7377",
    "sg:postcode":"02857",
    "sg:province":"RI",
    "wof:name":"Camp Ponagansett",
    "wof:placetype":"venue"
},
  "geometry": {"coordinates":[-71.679672,41.867031],"type":"Point"}
}