{
  "type": "Feature",
  "properties": {
    "iso:country":"US",
    "sg:address":"55 State St",
    "sg:city":"Narragansett",
    "sg:classifiers":[
        {
            "category":"Farming",
            "subcategory":"Fish & Marine Products",
            "type":"Manufacturing & Wholesale Goods"
        }
    ],
    "sg:phone":"+1 401 284 0025",
    "sg:postcode":"02882",
    "sg:province":"RI",
    "sg:tags":[
        "fisherman"
    ],
    "wof:name":"North East Safety Training Co",
    "wof:placetype":"venue"
},
  "geometry": {"coordinates":[-71.50956600000001,41.380368],"type":"Point"}
}