{
  "type": "Feature",
  "properties": {
    "addr:full":"77 Dorrance St Providence RI 02903",
    "addr:housenumber":"77",
    "addr:postcode":"02903",
    "addr:street":"Dorrance St",
    "iso:country":"US",
    "sg:address":"77 Dorrance St",
    "sg:city":"Providence",
    "sg:classifiers":[
        {
            "category":"Government",
            "subcategory":"Office",
            "type":"Public Place"
        }
    ],
    "sg:phone":"+1 401 222 2847",
    "sg:postcode":"02903",
    "sg:province":"RI",
    "sg:tags":[
        "govt",
        "agency"
    ],
    "wof:name":"Child Support Enforcement",
    "wof:placetype":"venue"
},
  "geometry": {"coordinates":[-71.411276,41.82327],"type":"Point"}
}