{
  "type": "Feature",
  "properties": {
    "iso:country":"US",
    "sg:address":"46 Log Rd",
    "sg:city":"Smithfield",
    "sg:classifiers":[
        {
            "category":"Retail",
            "subcategory":"Auto Repair",
            "type":"Services"
        }
    ],
    "sg:phone":"+1 401 232 0517",
    "sg:postcode":"02917",
    "sg:province":"RI",
    "sg:tags":[
        "body",
        "collision"
    ],
    "wof:name":"Finish Line Collision Centre",
    "wof:placetype":"venue"
},
  "geometry": {"coordinates":[-71.544336,41.897658],"type":"Point"}
}