{
  "type": "Feature",
  "properties": {
    "iso:country":"US",
    "sg:address":"37 Main St",
    "sg:city":"Albion",
    "sg:classifiers":[
        {
            "category":"Personal",
            "subcategory":"Beauty Salon",
            "type":"Services"
        }
    ],
    "sg:phone":"+1 401 333 0070",
    "sg:postcode":"02802",
    "sg:province":"RI",
    "wof:name":"Image Makers Co",
    "wof:placetype":"venue"
},
  "geometry": {"coordinates":[-71.45569399999999,41.953233],"type":"Point"}
}