{
  "type": "Feature",
  "properties": {
    "addr:full":"32 Becker St Warwick RI 02886",
    "addr:housenumber":"32",
    "addr:postcode":"02886",
    "addr:street":"Becker St",
    "iso:country":"US",
    "sg:address":"32 Becker St",
    "sg:city":"Warwick",
    "sg:classifiers":[
        {
            "category":"Insurance",
            "subcategory":"Insurance Agent",
            "type":"Services"
        }
    ],
    "sg:phone":"+1 401 732 5993",
    "sg:postcode":"02886",
    "sg:province":"RI",
    "sg:tags":[
        "audit"
    ],
    "wof:name":"Kenneth Manzi & Assoc",
    "wof:placetype":"venue"
},
  "geometry": {"coordinates":[-71.476472,41.700385],"type":"Point"}
}