{
  "type": "Feature",
  "properties": {
    "addr:full":"401 Clinton St Woonsocket RI 02895",
    "addr:housenumber":"401",
    "addr:postcode":"02895",
    "addr:street":"Clinton St",
    "iso:country":"US",
    "sg:address":"401 Clinton St",
    "sg:city":"Woonsocket",
    "sg:classifiers":[
        {
            "category":"Restaurant",
            "type":"Food & Drink"
        }
    ],
    "sg:phone":"+1 401 765 8888",
    "sg:postcode":"02895",
    "sg:province":"RI",
    "sg:tags":[
        "eating"
    ],
    "wof:name":"Boston Super Buffet",
    "wof:placetype":"venue"
},
  "geometry": {"coordinates":[-71.50751700000001,42.006106],"type":"Point"}
}