{
  "type": "Feature",
  "properties": {
    "iso:country":"US",
    "sg:address":"3 Elson Dr",
    "sg:city":"Riverside",
    "sg:classifiers":[
        {
            "category":"Insurance",
            "subcategory":"Insurance Agent",
            "type":"Services"
        }
    ],
    "sg:phone":"+1 401 433 2257",
    "sg:postcode":"02915",
    "sg:province":"RI",
    "wof:name":"Luso American Life Insurance",
    "wof:placetype":"venue"
},
  "geometry": {"coordinates":[-71.328998,41.769103],"type":"Point"}
}