{
  "type": "Feature",
  "properties": {
    "iso:country":"US",
    "sg:address":"295 Main Rd",
    "sg:city":"Tiverton",
    "sg:classifiers":[
        {
            "category":"Personal",
            "subcategory":"Tanning Parlor",
            "type":"Services"
        }
    ],
    "sg:phone":"+1 401 625 5550",
    "sg:postcode":"02878",
    "sg:province":"RI",
    "sg:tags":[
        "salon"
    ],
    "wof:name":"Endless Summer",
    "wof:placetype":"venue"
},
  "geometry": {"coordinates":[-71.18765999999999,41.66555],"type":"Point"}
}