{
  "type": "Feature",
  "properties": {
    "addr:full":"53 Waterman Ave East Providence RI 02914",
    "addr:housenumber":"53",
    "addr:postcode":"02914",
    "addr:street":"Waterman Ave",
    "iso:country":"US",
    "sg:address":"53 Waterman Ave",
    "sg:city":"East Providence",
    "sg:classifiers":[
        {
            "category":"Personal",
            "subcategory":"Beauty Salon",
            "type":"Services"
        }
    ],
    "sg:phone":"+1 401 438 3533",
    "sg:postcode":"02914",
    "sg:province":"RI",
    "sg:tags":[
        "manicuring"
    ],
    "wof:name":"Nails By Lisa",
    "wof:placetype":"venue"
},
  "geometry": {"coordinates":[-71.377352,41.825355],"type":"Point"}
}