{
  "type": "Feature",
  "properties": {
    "addr:full":"1308 Stafford Rd Tiverton RI 02878",
    "addr:housenumber":"1308",
    "addr:postcode":"02878",
    "addr:street":"Stafford Rd",
    "iso:country":"US",
    "sg:address":"1308 Stafford Rd",
    "sg:city":"Tiverton",
    "sg:classifiers":[
        {
            "category":"Restaurant",
            "type":"Food & Drink"
        }
    ],
    "sg:phone":"+1 401 624 1450",
    "sg:postcode":"02878",
    "sg:province":"RI",
    "sg:tags":[
        "eating"
    ],
    "wof:name":"D B Mart",
    "wof:placetype":"venue"
},
  "geometry": {"coordinates":[-71.14658300000001,41.626234],"type":"Point"}
}