{
  "type": "Feature",
  "properties": {
    "iso:country":"US",
    "sg:address":"145 Providence Pl",
    "sg:city":"Providence",
    "sg:classifiers":[
        {
            "category":"Shopping",
            "subcategory":"Clothing, Apparel, & Fashions",
            "type":"Retail Goods"
        }
    ],
    "sg:phone":"+1 401 270 4507",
    "sg:postcode":"02903",
    "sg:province":"RI",
    "sg:website":"www.ardenb.com",
    "wof:name":"Arden B",
    "wof:placetype":"venue"
},
  "geometry": {"coordinates":[-71.418789,41.827787],"type":"Point"}
}