{
  "type": "Feature",
  "properties": {
    "iso:country":"US",
    "sg:address":"180 Rabbitt Hill Rd",
    "sg:city":"Cumberland",
    "sg:classifiers":[
        {
            "category":"Home & Garden",
            "subcategory":"Building Materials",
            "type":"Retail Goods"
        },
        {
            "category":"Manufacturing",
            "subcategory":"Glass & Minerals",
            "type":"Manufacturing & Wholesale Goods"
        }
    ],
    "sg:phone":"+1 401 334 2280",
    "sg:postcode":"02864",
    "sg:province":"RI",
    "sg:tags":[
        "concrete",
        "brick",
        "prod",
        "block"
    ],
    "wof:name":"Walter's Concrete Form Co",
    "wof:placetype":"venue"
},
  "geometry": {"coordinates":[-71.39170300000001,41.926527],"type":"Point"}
}