{
  "type": "Feature",
  "properties": {
    "addr:full":"805 N Main St Providence RI 02904",
    "addr:housenumber":"805",
    "addr:postcode":"02904",
    "addr:street":"N Main St",
    "iso:country":"US",
    "sg:address":"805 N Main St",
    "sg:city":"Providence",
    "sg:classifiers":[
        {
            "category":"Restaurant",
            "type":"Food & Drink"
        }
    ],
    "sg:phone":"+1 401 272 3950",
    "sg:postcode":"02904",
    "sg:province":"RI",
    "sg:website":"www.kfc.com",
    "wof:name":"Kentucky Fried Chicken",
    "wof:placetype":"venue"
},
  "geometry": {"coordinates":[-71.40799699999999,41.841599],"type":"Point"}
}