{
  "type": "Feature",
  "properties": {
    "addr:full":"1265 Mendon Rd Cumberland RI 02864",
    "addr:housenumber":"1265",
    "addr:postcode":"02864",
    "addr:street":"Mendon Rd",
    "iso:country":"US",
    "sg:address":"1265 Mendon Rd",
    "sg:city":"Cumberland",
    "sg:classifiers":[
        {
            "category":"Real Estate",
            "subcategory":"Real Estate Operator",
            "type":"Services"
        }
    ],
    "sg:phone":"+1 401 767 3000",
    "sg:postcode":"02864",
    "sg:province":"RI",
    "sg:tags":[
        "building",
        "apartment"
    ],
    "wof:name":"Beaudoin Realty",
    "wof:placetype":"venue"
},
  "geometry": {"coordinates":[-71.426542,41.933049],"type":"Point"}
}