{
  "type": "Feature",
  "properties": {
    "iso:country":"US",
    "sg:address":"1248 Warwick Ave",
    "sg:city":"Warwick",
    "sg:classifiers":[
        {
            "category":"Manufacturing",
            "subcategory":"Printing",
            "type":"Manufacturing & Wholesale Goods"
        }
    ],
    "sg:phone":"+1 401 463 5570",
    "sg:postcode":"02888",
    "sg:province":"RI",
    "sg:tags":[
        "commercial"
    ],
    "wof:name":"Art's Printing Ctr",
    "wof:placetype":"venue"
},
  "geometry": {"coordinates":[-71.40785099999999,41.741988],"type":"Point"}
}