{
  "type": "Feature",
  "properties": {
    "addr:full":"48 Cliff Dr Bristol RI 02809",
    "addr:housenumber":"48",
    "addr:postcode":"02809",
    "addr:street":"Cliff Dr",
    "iso:country":"US",
    "sg:address":"48 Cliff Dr",
    "sg:city":"Bristol",
    "sg:classifiers":[
        {
            "category":"Organizations",
            "subcategory":"Membership Organization",
            "type":"Services"
        }
    ],
    "sg:phone":"+1 401 253 5023",
    "sg:postcode":"02809",
    "sg:province":"RI",
    "wof:name":"Beach Terrace Improvement",
    "wof:placetype":"venue"
},
  "geometry": {"coordinates":[-71.288889,41.701518],"type":"Point"}
}