{
  "type": "Feature",
  "properties": {
    "iso:country":"US",
    "sg:address":"227 County Rd",
    "sg:city":"Barrington",
    "sg:classifiers":[
        {
            "category":"Autos & Motor Vehicles",
            "subcategory":"Fuel & Gas Station",
            "type":"Retail Goods"
        }
    ],
    "sg:phone":"+1 401 245 9346",
    "sg:postcode":"02806",
    "sg:province":"RI",
    "sg:tags":[
        "station",
        "gasoline",
        "oil"
    ],
    "wof:name":"Barrington Getty Svc",
    "wof:placetype":"venue"
},
  "geometry": {"coordinates":[-71.30572100000001,41.738126],"type":"Point"}
}