{
  "type": "Feature",
  "properties": {
    "iso:country":"US",
    "sg:address":"45 Lakehurst Ave",
    "sg:city":"Coventry",
    "sg:classifiers":[
        {
            "category":"Professional",
            "type":"Services"
        }
    ],
    "sg:phone":"+1 401 392 0234",
    "sg:postcode":"02816",
    "sg:province":"RI",
    "sg:tags":[
        "establishment"
    ],
    "wof:name":"Trudeau Group Home",
    "wof:placetype":"venue"
},
  "geometry": {"coordinates":[-71.609472,41.673045],"type":"Point"}
}