{
  "type": "Feature",
  "properties": {
    "iso:country":"US",
    "sg:address":"351 S Water St",
    "sg:city":"Providence",
    "sg:classifiers":[
        {
            "category":"Restaurant",
            "type":"Food & Drink"
        }
    ],
    "sg:phone":"+1 401 831 8767",
    "sg:postcode":"02903",
    "sg:province":"RI",
    "wof:name":"For Crepe Sake",
    "wof:placetype":"venue"
},
  "geometry": {"coordinates":[-71.404404,41.820499],"type":"Point"}
}