{
  "type": "Feature",
  "properties": {
    "iso:country":"US",
    "sg:address":"31 Birchwood Dr",
    "sg:city":"Bristol",
    "sg:classifiers":[
        {
            "category":"Building & Trades",
            "subcategory":"Construction",
            "type":"Services"
        }
    ],
    "sg:phone":"+1 401 253 9998",
    "sg:postcode":"02809",
    "sg:province":"RI",
    "sg:tags":[
        "general",
        "contractor"
    ],
    "wof:name":"Lopes Construction & Landscpg",
    "wof:placetype":"venue"
},
  "geometry": {"coordinates":[-71.257133,41.70621],"type":"Point"}
}