{
  "type": "Feature",
  "properties": {
    "iso:country":"US",
    "sg:address":"285 Main St",
    "sg:city":"Woonsocket",
    "sg:classifiers":[
        {
            "category":"Government",
            "subcategory":"Court House",
            "type":"Public Place"
        }
    ],
    "sg:phone":"+1 401 762 6340",
    "sg:postcode":"02895",
    "sg:province":"RI",
    "sg:tags":[
        "justice",
        "peace"
    ],
    "wof:name":"Justice Resource Corp",
    "wof:placetype":"venue"
},
  "geometry": {"coordinates":[-71.512733,42.003872],"type":"Point"}
}