{
  "type": "Feature",
  "properties": {
    "addr:full":"830 Cumberland Hill Rd Woonsocket RI 02895",
    "addr:housenumber":"830",
    "addr:postcode":"02895",
    "addr:street":"Cumberland Hill Rd",
    "iso:country":"US",
    "sg:address":"830 Cumberland Hill Rd",
    "sg:city":"Woonsocket",
    "sg:classifiers":[
        {
            "category":"Home & Garden",
            "subcategory":"Building Materials",
            "type":"Retail Goods"
        }
    ],
    "sg:phone":"+1 401 769 8128",
    "sg:postcode":"02895",
    "sg:province":"RI",
    "sg:tags":[
        "hardware",
        "lumber"
    ],
    "wof:name":"Pepin Lumber",
    "wof:placetype":"venue"
},
  "geometry": {"coordinates":[-71.48805299999999,41.995449],"type":"Point"}
}