{
  "type": "Feature",
  "properties": {
    "addr:full":"23 Arnold St Wakefield RI 02879",
    "addr:housenumber":"23",
    "addr:postcode":"02879",
    "addr:street":"Arnold St",
    "iso:country":"US",
    "sg:address":"23 Arnold St",
    "sg:city":"Wakefield",
    "sg:classifiers":[
        {
            "category":"Professional",
            "subcategory":"Computer Services",
            "type":"Services"
        }
    ],
    "sg:phone":"+1 401 788 9415",
    "sg:postcode":"02879",
    "sg:province":"RI",
    "sg:tags":[
        "programing",
        "custom"
    ],
    "sg:website":"www.splendorofflorence.com",
    "wof:name":"Non-Profit Technologies",
    "wof:placetype":"venue"
},
  "geometry": {"coordinates":[-71.485401,41.440542],"type":"Point"}
}