{
  "type": "Feature",
  "properties": {
    "iso:country":"US",
    "sg:address":"267 Social St",
    "sg:city":"Woonsocket",
    "sg:classifiers":[
        {
            "category":"Personal",
            "type":"Services"
        },
        {
            "category":"Personal",
            "subcategory":"Beauty Salon",
            "type":"Services"
        }
    ],
    "sg:phone":"+1 401 762 0828",
    "sg:postcode":"02895",
    "sg:province":"RI",
    "sg:tags":[
        "shop",
        "electrolysis"
    ],
    "wof:name":"Vivian's Electrolysis Salon",
    "wof:placetype":"venue"
},
  "geometry": {"coordinates":[-71.50596299999999,42.008359],"type":"Point"}
}