{
  "type": "Feature",
  "properties": {
    "addr:full":"14 High St Barrington RI 02806",
    "addr:housenumber":"14",
    "addr:postcode":"02806",
    "addr:street":"High St",
    "iso:country":"US",
    "sg:address":"14 High St",
    "sg:city":"Barrington",
    "sg:classifiers":[
        {
            "category":"Insurance",
            "subcategory":"Insurance Agent",
            "type":"Services"
        }
    ],
    "sg:phone":"+1 401 246 1738",
    "sg:postcode":"02806",
    "sg:province":"RI",
    "wof:name":"Kraunelis Insurance Agency LLC",
    "wof:placetype":"venue"
},
  "geometry": {"coordinates":[-71.339865,41.74828],"type":"Point"}
}