{
  "type": "Feature",
  "properties": {
    "iso:country":"US",
    "sg:address":"220 Plainfield St",
    "sg:city":"Providence",
    "sg:classifiers":[
        {
            "category":"Local Transit",
            "type":"Transportation"
        }
    ],
    "sg:phone":"+1 401 464 9800",
    "sg:postcode":"02909",
    "sg:province":"RI",
    "sg:tags":[
        "passenger"
    ],
    "wof:name":"A Night On The Town Limo Svc",
    "wof:placetype":"venue"
},
  "geometry": {"coordinates":[-71.447039,41.814327],"type":"Point"}
}