{
  "type": "Feature",
  "properties": {
    "addr:full":"41 Hagerstown Rd Warwick RI 02886",
    "addr:housenumber":"41",
    "addr:postcode":"02886",
    "addr:street":"Hagerstown Rd",
    "iso:country":"US",
    "sg:address":"41 Hagerstown Rd",
    "sg:city":"Warwick",
    "sg:classifiers":[
        {
            "category":"Building & Trades",
            "subcategory":"Construction",
            "type":"Services"
        }
    ],
    "sg:phone":"+1 401 739 3615",
    "sg:postcode":"02886",
    "sg:province":"RI",
    "sg:tags":[
        "house"
    ],
    "wof:name":"Rapson Building & Remodeling",
    "wof:placetype":"venue"
},
  "geometry": {"coordinates":[-71.41955799999999,41.692376],"type":"Point"}
}