{
  "type": "Feature",
  "properties": {
    "iso:country":"US",
    "sg:address":"81 Broad St Apt 1",
    "sg:city":"Cumberland",
    "sg:classifiers":[
        {
            "category":"Wholesale",
            "subcategory":"Office Equipment",
            "type":"Manufacturing & Wholesale Goods"
        },
        {
            "category":"Shopping",
            "subcategory":"Stationery & Office Supplies",
            "type":"Retail Goods"
        },
        {
            "category":"Shopping",
            "subcategory":"Computers & Home Electronics",
            "type":"Retail Goods"
        }
    ],
    "sg:phone":"+1 401 723 8991",
    "sg:postcode":"02864",
    "sg:province":"RI",
    "sg:tags":[
        "register",
        "autographic",
        "cash",
        "typewriter"
    ],
    "sg:website":"http://www.bsne.net",
    "wof:name":"Business Systems of New England Inc",
    "wof:placetype":"venue"
},
  "geometry": {"coordinates":[-71.39094900000001,41.901454],"type":"Point"}
}