{
  "type": "Feature",
  "properties": {
    "addr:full":"96 Hoyt Ave Rumford RI 02916",
    "addr:housenumber":"96",
    "addr:postcode":"02916",
    "addr:street":"Hoyt Ave",
    "iso:country":"US",
    "sg:address":"96 Hoyt Ave",
    "sg:city":"Rumford",
    "sg:classifiers":[
        {
            "category":"Social Services",
            "type":"Services"
        },
        {
            "category":"Shopping",
            "subcategory":"Bicycles & Sporting Goods",
            "type":"Retail Goods"
        },
        {
            "category":"Professional",
            "subcategory":"Employment Agencies",
            "type":"Services"
        },
        {
            "category":"Organizations",
            "subcategory":"Membership Organization",
            "type":"Services"
        },
        {
            "category":"Sports & Exercise",
            "subcategory":"Golf",
            "type":"Entertainment"
        }
    ],
    "sg:phone":"+1 401 434 9899",
    "sg:postcode":"02916",
    "sg:province":"RI",
    "sg:tags":[
        "placement",
        "course",
        "club",
        "supply",
        "private",
        "equipment",
        "workers'",
        "volunteer"
    ],
    "sg:website":"http://www.northeastamateur.com",
    "wof:name":"Wannamoisett Country Club",
    "wof:placetype":"venue"
},
  "geometry": {"coordinates":[-71.357552,41.844429],"type":"Point"}
}