{
  "type": "Feature",
  "properties": {
    "iso:country":"US",
    "sg:address":"46 Summit Rd",
    "sg:city":"Cumberland",
    "sg:classifiers":[
        {
            "category":"Professional",
            "type":"Services"
        }
    ],
    "sg:phone":"+1 401 333 3219",
    "sg:postcode":"02864",
    "sg:province":"RI",
    "wof:name":"M E Marine LLC",
    "wof:placetype":"venue"
},
  "geometry": {"coordinates":[-71.415997,41.954317],"type":"Point"}
}