{
  "type": "Feature",
  "properties": {
    "addr:full":"102 Reservoir Rd Coventry RI 02816",
    "addr:housenumber":"102",
    "addr:postcode":"02816",
    "addr:street":"Reservoir Rd",
    "iso:country":"US",
    "sg:address":"102 Reservoir Rd",
    "sg:city":"Coventry",
    "sg:classifiers":[
        {
            "category":"Shopping",
            "type":"Retail Goods"
        }
    ],
    "sg:phone":"+1 401 828 0380",
    "sg:postcode":"02816",
    "sg:province":"RI",
    "sg:tags":[
        "merchandise"
    ],
    "wof:name":"Masterpiece Gallery",
    "wof:placetype":"venue"
},
  "geometry": {"coordinates":[-71.59020099999999,41.689611],"type":"Point"}
}