{
  "type": "Feature",
  "properties": {
    "iso:country":"US",
    "sg:address":"740 Greenville Ave",
    "sg:city":"Johnston",
    "sg:classifiers":[
        {
            "category":"Freight",
            "type":"Transportation"
        }
    ],
    "sg:phone":"+1 401 233 9163",
    "sg:postcode":"02919",
    "sg:province":"RI",
    "sg:tags":[
        "operator",
        "trucking"
    ],
    "wof:name":"P Magnone Carriers Inc",
    "wof:placetype":"venue"
},
  "geometry": {"coordinates":[-71.514115,41.850196],"type":"Point"}
}