{
  "type": "Feature",
  "properties": {
    "iso:country":"US",
    "sg:address":"4 Sharpe Dr",
    "sg:city":"Cranston",
    "sg:classifiers":[
        {
            "category":"Manufacturing",
            "subcategory":"Jewelry",
            "type":"Manufacturing & Wholesale Goods"
        }
    ],
    "sg:phone":"+1 401 463 7604",
    "sg:postcode":"02920",
    "sg:province":"RI",
    "sg:tags":[
        "costume"
    ],
    "wof:name":"Grosse Jewels Ny Inc",
    "wof:placetype":"venue"
},
  "geometry": {"coordinates":[-71.454902,41.740296],"type":"Point"}
}