{
  "type": "Feature",
  "properties": {
    "iso:country":"US",
    "sg:address":"28 Kay St",
    "sg:city":"Newport",
    "sg:classifiers":[
        {
            "category":"Professional",
            "type":"Services"
        },
        {
            "category":"Marine",
            "type":"Transportation"
        }
    ],
    "sg:phone":"+1 401 849 3754",
    "sg:postcode":"02840",
    "sg:province":"RI",
    "sg:tags":[
        "towing"
    ],
    "wof:name":"Spengos Marine Services Inc",
    "wof:placetype":"venue"
},
  "geometry": {"coordinates":[-71.3082,41.49004],"type":"Point"}
}