{
  "type": "Feature",
  "properties": {
    "iso:country":"US",
    "sg:address":"11 Hawthorne St",
    "sg:city":"Providence",
    "sg:classifiers":[
        {
            "category":"Organizations",
            "subcategory":"Non-profit Organization",
            "type":"Services"
        },
        {
            "category":"Social Services",
            "subcategory":"Child Care",
            "type":"Services"
        }
    ],
    "sg:phone":"+1 401 781 6996",
    "sg:postcode":"02907",
    "sg:province":"RI",
    "sg:tags":[
        "day"
    ],
    "wof:name":"Family Outreach Center Inc",
    "wof:placetype":"venue"
},
  "geometry": {"coordinates":[-71.42725799999999,41.800917],"type":"Point"}
}