{
  "type": "Feature",
  "properties": {
    "iso:country":"US",
    "sg:address":"1243 Mineral Spring Ave",
    "sg:city":"Pawtucket",
    "sg:classifiers":[
        {
            "category":"Home & Garden",
            "subcategory":"Furniture",
            "type":"Retail Goods"
        }
    ],
    "sg:phone":"+1 401 725 1170",
    "sg:postcode":"02860",
    "sg:province":"RI",
    "sg:tags":[
        "store"
    ],
    "wof:name":"Kams Colonial Shop",
    "wof:placetype":"venue"
},
  "geometry": {"coordinates":[-71.391296,41.8755],"type":"Point"}
}