{
  "type": "Feature",
  "properties": {
    "addr:full":"121 South Main Street Providence RI 02903",
    "addr:housenumber":"121",
    "addr:postcode":"02903",
    "addr:street":"South Main Street",
    "iso:country":"US",
    "sg:address":"121 South Main Street",
    "sg:city":"Providence",
    "sg:classifiers":[
        {
            "category":"Restaurant",
            "type":"Food & Drink"
        }
    ],
    "sg:phone":"+1 401 351 8570",
    "sg:postcode":"02903",
    "sg:province":"RI",
    "sg:tags":[
        "seafood"
    ],
    "sg:website":"www.hemenwaysrestaurant.com",
    "wof:name":"Hemenway's",
    "wof:placetype":"venue"
},
  "geometry": {"coordinates":[-71.406738,41.824123],"type":"Point"}
}