{
  "type": "Feature",
  "properties": {
    "iso:country":"US",
    "sg:address":"742 Hope St",
    "sg:city":"Providence",
    "sg:classifiers":[
        {
            "category":"Shopping",
            "subcategory":"Books",
            "type":"Retail Goods"
        }
    ],
    "sg:phone":"+1 401 351 0110",
    "sg:postcode":"02906",
    "sg:province":"RI",
    "sg:tags":[
        "dealer"
    ],
    "wof:name":"Ye Old Book Shoppe",
    "wof:placetype":"venue"
},
  "geometry": {"coordinates":[-71.395951,41.847239],"type":"Point"}
}