{
  "type": "Feature",
  "properties": {
    "addr:full":"648 Metacom Ave Warren RI 02885",
    "addr:housenumber":"648",
    "addr:postcode":"02885",
    "addr:street":"Metacom Ave",
    "iso:country":"US",
    "sg:address":"648 Metacom Ave",
    "sg:city":"Warren",
    "sg:classifiers":[
        {
            "category":"Restaurant",
            "type":"Food & Drink"
        }
    ],
    "sg:phone":"+1 401 245 5200",
    "sg:postcode":"02885",
    "sg:province":"RI",
    "wof:name":"Blimpie Subs & Salads",
    "wof:placetype":"venue"
},
  "geometry": {"coordinates":[-71.26797500000001,41.715119],"type":"Point"}
}