{
  "type": "Feature",
  "properties": {
    "iso:country":"US",
    "sg:address":"700 East Ave",
    "sg:city":"Warwick",
    "sg:classifiers":[
        {
            "category":"Home & Garden",
            "subcategory":"Building Materials",
            "type":"Retail Goods"
        }
    ],
    "sg:phone":"+1 401 828 7145",
    "sg:postcode":"02886",
    "sg:province":"RI",
    "sg:website":"www.northeastdistributors.com",
    "wof:name":"Northeast Distributors Inc",
    "wof:placetype":"venue"
},
  "geometry": {"coordinates":[-71.486632,41.719698],"type":"Point"}
}