{
  "type": "Feature",
  "properties": {
    "addr:full":"35 Kenney Dr Cranston RI 02920",
    "addr:housenumber":"35",
    "addr:postcode":"02920",
    "addr:street":"Kenney Dr",
    "iso:country":"US",
    "sg:address":"35 Kenney Dr",
    "sg:city":"Cranston",
    "sg:classifiers":[
        {
            "category":"Manufacturing",
            "subcategory":"Tools & Machinery",
            "type":"Manufacturing & Wholesale Goods"
        }
    ],
    "sg:phone":"+1 401 463 1800",
    "sg:postcode":"02920",
    "sg:province":"RI",
    "sg:tags":[
        "industry",
        "special"
    ],
    "wof:name":"Yushin America Inc",
    "wof:placetype":"venue"
},
  "geometry": {"coordinates":[-71.44671,41.746718],"type":"Point"}
}