{
  "type": "Feature",
  "properties": {
    "iso:country":"US",
    "sg:address":"1006 Charles St",
    "sg:city":"Providence",
    "sg:classifiers":[
        {
            "category":"Professional",
            "subcategory":"Engineering",
            "type":"Services"
        }
    ],
    "sg:phone":"+1 401 726 8780",
    "sg:postcode":"02904",
    "sg:province":"RI",
    "wof:name":"D & B Engineering",
    "wof:placetype":"venue"
},
  "geometry": {"coordinates":[-71.42398799999999,41.865223],"type":"Point"}
}