{
  "type": "Feature",
  "properties": {
    "iso:country":"US",
    "sg:address":"768 Atwood Ave",
    "sg:city":"Cranston",
    "sg:classifiers":[
        {
            "category":"Shopping",
            "subcategory":"Computers & Home Electronics",
            "type":"Retail Goods"
        }
    ],
    "sg:phone":"+1 401 943 4202",
    "sg:postcode":"02920",
    "sg:province":"RI",
    "sg:tags":[
        "equipment",
        "electronic",
        "supply"
    ],
    "wof:name":"Electronic Connection",
    "wof:placetype":"venue"
},
  "geometry": {"coordinates":[-71.47789,41.79388],"type":"Point"}
}