{
  "type": "Feature",
  "properties": {
    "addr:full":"33 Annawamscutt Dr Bristol RI 02809",
    "addr:housenumber":"33",
    "addr:postcode":"02809",
    "addr:street":"Annawamscutt Dr",
    "iso:country":"US",
    "sg:address":"33 Annawamscutt Dr",
    "sg:city":"Bristol",
    "sg:classifiers":[
        {
            "category":"Retail",
            "subcategory":"Repair Shop",
            "type":"Services"
        }
    ],
    "sg:phone":"+1 401 254 1177",
    "sg:postcode":"02809",
    "sg:province":"RI",
    "sg:tags":[
        "taxidermist"
    ],
    "wof:name":"Big John's Taxidermists",
    "wof:placetype":"venue"
},
  "geometry": {"coordinates":[-71.259479,41.687084],"type":"Point"}
}