{
  "type": "Feature",
  "properties": {
    "iso:country":"US",
    "sg:address":"73 Valley Rd",
    "sg:city":"Middletown",
    "sg:classifiers":[
        {
            "category":"Government",
            "subcategory":"Office",
            "type":"Public Place"
        }
    ],
    "sg:phone":"+1 401 847 2038",
    "sg:postcode":"02842",
    "sg:province":"RI",
    "wof:name":"Labor & Training Dept",
    "wof:placetype":"venue"
},
  "geometry": {"coordinates":[-71.292061,41.516479],"type":"Point"}
}