{
  "type": "Feature",
  "properties": {
    "addr:full":"734 Eddy St Providence RI 02903",
    "addr:housenumber":"734",
    "addr:postcode":"02903",
    "addr:street":"Eddy St",
    "iso:country":"US",
    "sg:address":"734 Eddy St",
    "sg:city":"Providence",
    "sg:classifiers":[
        {
            "category":"Bagels",
            "type":"Food & Drink"
        },
        {
            "category":"Coffee & Tea",
            "type":"Food & Drink"
        },
        {
            "category":"Food & Beverages",
            "subcategory":"Bakery",
            "type":"Retail Goods"
        },
        {
            "category":"Bakery",
            "type":"Food & Drink"
        },
        {
            "category":"Donuts",
            "type":"Food & Drink"
        }
    ],
    "sg:menulink":"http://www.allmenus.com/ri/providence/138891-dunkin-donuts/menu/",
    "sg:phone":"+1 401 621 2390",
    "sg:postcode":"02903",
    "sg:province":"RI",
    "sg:tags":[
        "coffee",
        "tea",
        "american",
        "bagel",
        "bakery",
        "pastry"
    ],
    "wof:name":"Dunkin' Donuts",
    "wof:placetype":"venue"
},
  "geometry": {"coordinates":[-71.407,41.808159],"type":"Point"}
}