{
  "type": "Feature",
  "properties": {
    "addr:full":"90 Chase Hill Rd Ashaway RI 02804",
    "addr:housenumber":"90",
    "addr:postcode":"02804",
    "addr:street":"Chase Hill Rd",
    "iso:country":"US",
    "sg:address":"90 Chase Hill Rd",
    "sg:city":"Ashaway",
    "sg:classifiers":[
        {
            "category":"Shopping",
            "subcategory":"Clothing, Apparel, & Fashions",
            "type":"Retail Goods"
        }
    ],
    "sg:phone":"+1 401 377 8956",
    "sg:postcode":"02804",
    "sg:province":"RI",
    "sg:tags":[
        "designer"
    ],
    "wof:name":"Partners In Design Inc",
    "wof:placetype":"venue"
},
  "geometry": {"coordinates":[-71.785788,41.401416],"type":"Point"}
}