{
  "type": "Feature",
  "properties": {
    "iso:country":"US",
    "sg:address":"8 Angell Ct",
    "sg:city":"Providence",
    "sg:classifiers":[
        {
            "category":"Professional",
            "subcategory":"Lawyer & Legal Services",
            "type":"Services"
        }
    ],
    "sg:phone":"+1 401 453 4173",
    "sg:postcode":"02906",
    "sg:province":"RI",
    "wof:name":"Charles Sturtevant Legal Svcs",
    "wof:placetype":"venue"
},
  "geometry": {"coordinates":[-71.390334,41.82995],"type":"Point"}
}