{
  "type": "Feature",
  "properties": {
    "iso:country":"US",
    "sg:address":"445 Promenade St",
    "sg:city":"Providence",
    "sg:classifiers":[
        {
            "category":"Restaurant",
            "type":"Food & Drink"
        }
    ],
    "sg:menulink":"http://www.allmenus.com/ri/providence/215260-burger-king/menu/",
    "sg:phone":"+1 401 331 7050",
    "sg:postcode":"02908",
    "sg:province":"RI",
    "sg:tags":[
        "burger",
        "american"
    ],
    "wof:name":"Burger King",
    "wof:placetype":"venue"
},
  "geometry": {"coordinates":[-71.426818,41.82928],"type":"Point"}
}