{
  "type": "Feature",
  "properties": {
    "addr:full":"713 Westminster St Providence RI 02903",
    "addr:housenumber":"713",
    "addr:postcode":"02903",
    "addr:street":"Westminster St",
    "iso:country":"US",
    "sg:address":"713 Westminster St",
    "sg:city":"Providence",
    "sg:classifiers":[
        {
            "category":"Shopping",
            "type":"Retail Goods"
        }
    ],
    "sg:phone":"+1 401 351 2004",
    "sg:postcode":"02903",
    "sg:province":"RI",
    "sg:tags":[
        "art",
        "gallery",
        "dealer"
    ],
    "wof:name":"Abode",
    "wof:placetype":"venue"
},
  "geometry": {"coordinates":[-71.41978400000001,41.818539],"type":"Point"}
}