{
  "type": "Feature",
  "properties": {
    "addr:full":"1635 Fish Rd Tiverton RI 02878",
    "addr:housenumber":"1635",
    "addr:postcode":"02878",
    "addr:street":"Fish Rd",
    "iso:country":"US",
    "sg:address":"1635 Fish Rd",
    "sg:city":"Tiverton",
    "sg:classifiers":[
        {
            "category":"Wholesale",
            "subcategory":"Construction Materials",
            "type":"Manufacturing & Wholesale Goods"
        }
    ],
    "sg:phone":"+1 401 624 9900",
    "sg:postcode":"02878",
    "sg:province":"RI",
    "sg:tags":[
        "recycled",
        "stone",
        "quarry"
    ],
    "wof:name":"Viking Stone Corp",
    "wof:placetype":"venue"
},
  "geometry": {"coordinates":[-71.183707,41.625727],"type":"Point"}
}