{
  "type": "Feature",
  "properties": {
    "iso:country":"US",
    "sg:address":"352 Waterman Ave",
    "sg:city":"Smithfield",
    "sg:classifiers":[
        {
            "category":"Retail",
            "subcategory":"Animal Services",
            "type":"Services"
        }
    ],
    "sg:phone":"+1 401 233 9733",
    "sg:postcode":"02917",
    "sg:province":"RI",
    "sg:tags":[
        "pet",
        "grooming",
        "washing"
    ],
    "wof:name":"Family Companion Pet Salon",
    "wof:placetype":"venue"
},
  "geometry": {"coordinates":[-71.49947899999999,41.87675],"type":"Point"}
}