{
  "type": "Feature",
  "properties": {
    "addr:full":"560 Broadway Pawtucket RI 02860",
    "addr:housenumber":"560",
    "addr:postcode":"02860",
    "addr:street":"Broadway",
    "iso:country":"US",
    "sg:address":"560 Broadway",
    "sg:city":"Pawtucket",
    "sg:classifiers":[
        {
            "category":"Restaurant",
            "type":"Food & Drink"
        }
    ],
    "sg:phone":"+1 401 729 8030",
    "sg:postcode":"02860",
    "sg:province":"RI",
    "sg:tags":[
        "chinese"
    ],
    "wof:name":"Great China",
    "wof:placetype":"venue"
},
  "geometry": {"coordinates":[-71.37400100000001,41.888802],"type":"Point"}
}