{
  "type": "Feature",
  "properties": {
    "addr:full":"19 Linden St Pawtucket RI 02861",
    "addr:housenumber":"19",
    "addr:postcode":"02861",
    "addr:street":"Linden St",
    "iso:country":"US",
    "sg:address":"19 Linden St",
    "sg:city":"Pawtucket",
    "sg:classifiers":[
        {
            "category":"Manufacturing",
            "subcategory":"Glass & Minerals",
            "type":"Manufacturing & Wholesale Goods"
        }
    ],
    "sg:phone":"+1 401 725 7299",
    "sg:postcode":"02861",
    "sg:province":"RI",
    "sg:tags":[
        "concrete",
        "brick",
        "prod",
        "block"
    ],
    "wof:name":"Castcrete",
    "wof:placetype":"venue"
},
  "geometry": {"coordinates":[-71.35992,41.886192],"type":"Point"}
}