{
  "type": "Feature",
  "properties": {
    "iso:country":"US",
    "sg:address":"216 E Shore Rd",
    "sg:city":"Jamestown",
    "sg:classifiers":[
        {
            "category":"Health Services",
            "subcategory":"Doctor",
            "type":"Services"
        }
    ],
    "sg:phone":"+1 401 423 0449",
    "sg:postcode":"02835",
    "sg:province":"RI",
    "sg:tags":[
        "medical"
    ],
    "wof:name":"Orthopaedic Assoc Inc",
    "wof:placetype":"venue"
},
  "geometry": {"coordinates":[-71.36520400000001,41.527379],"type":"Point"}
}