{
  "type": "Feature",
  "properties": {
    "iso:country":"US",
    "sg:address":"300 Broadway",
    "sg:city":"Pawtucket",
    "sg:classifiers":[
        {
            "category":"Health Services",
            "subcategory":"Nursing And Care Facility",
            "type":"Services"
        }
    ],
    "sg:phone":"+1 401 725 7921",
    "sg:postcode":"02860",
    "sg:province":"RI",
    "sg:tags":[
        "home",
        "retirement",
        "community"
    ],
    "wof:name":"Vincent J Doyle Manor",
    "wof:placetype":"venue"
},
  "geometry": {"coordinates":[-71.37777699999999,41.881687],"type":"Point"}
}