{
  "type": "Feature",
  "properties": {
    "iso:country":"US",
    "sg:address":"162 Lincoln Ave",
    "sg:city":"Barrington",
    "sg:classifiers":[
        {
            "category":"Organizations",
            "subcategory":"Non-profit Organization",
            "type":"Services"
        }
    ],
    "sg:phone":"+1 401 245 4361",
    "sg:postcode":"02806",
    "sg:province":"RI",
    "sg:tags":[
        "social"
    ],
    "wof:name":"Rhode Island Advocates For Gif",
    "wof:placetype":"venue"
},
  "geometry": {"coordinates":[-71.32505,41.74634],"type":"Point"}
}