{
  "type": "Feature",
  "properties": {
    "iso:country":"US",
    "sg:address":"251A Weybosset St",
    "sg:city":"Providence",
    "sg:classifiers":[
        {
            "category":"Shopping",
            "subcategory":"Shoes",
            "type":"Retail Goods"
        }
    ],
    "sg:phone":"+1 401 351 2112",
    "sg:postcode":"02903",
    "sg:province":"RI",
    "sg:tags":[
        "store"
    ],
    "wof:name":"Sneaker Junkies",
    "wof:placetype":"venue"
},
  "geometry": {"coordinates":[-71.412722,41.821219],"type":"Point"}
}