{
  "type": "Feature",
  "properties": {
    "addr:full":"121 Hope St Providence RI 02906",
    "addr:housenumber":"121",
    "addr:postcode":"02906",
    "addr:street":"Hope St",
    "iso:country":"US",
    "sg:address":"121 Hope St",
    "sg:city":"Providence",
    "sg:classifiers":[
        {
            "category":"Education",
            "subcategory":"Library",
            "type":"Public Place"
        }
    ],
    "sg:phone":"+1 401 331 8575",
    "sg:postcode":"02906",
    "sg:province":"RI",
    "sg:tags":[
        "museum"
    ],
    "wof:name":"R I Historical Society",
    "wof:placetype":"venue"
},
  "geometry": {"coordinates":[-71.396675,41.823],"type":"Point"}
}