{
  "type": "Feature",
  "properties": {
    "addr:full":"1 New Rd Rumford RI 02916",
    "addr:housenumber":"1",
    "addr:postcode":"02916",
    "addr:street":"New Rd",
    "iso:country":"US",
    "sg:address":"1 New Rd",
    "sg:city":"Rumford",
    "sg:classifiers":[
        {
            "category":"Organizations",
            "subcategory":"Community Association",
            "type":"Services"
        }
    ],
    "sg:phone":"+1 401 434 4620",
    "sg:postcode":"02916",
    "sg:province":"RI",
    "sg:tags":[
        "fraternal"
    ],
    "wof:name":"Knights Of Columbus",
    "wof:placetype":"venue"
},
  "geometry": {"coordinates":[-71.358452,41.855053],"type":"Point"}
}