{
  "type": "Feature",
  "properties": {
    "iso:country":"US",
    "sg:address":"11 Limerock Rd",
    "sg:city":"Smithfield",
    "sg:classifiers":[
        {
            "category":"Education",
            "subcategory":"School",
            "type":"Public Place"
        }
    ],
    "sg:phone":"+1 401 231 6652",
    "sg:postcode":"02917",
    "sg:province":"RI",
    "sg:website":"www.laperche.org",
    "wof:name":"LA Perch Elementary School",
    "wof:placetype":"venue"
},
  "geometry": {"coordinates":[-71.505549,41.899115],"type":"Point"}
}