{
  "type": "Feature",
  "properties": {
    "addr:full":"362 Broadway Providence RI 02909",
    "addr:housenumber":"362",
    "addr:postcode":"02909",
    "addr:street":"Broadway",
    "iso:country":"US",
    "sg:address":"362 Broadway",
    "sg:city":"Providence",
    "sg:classifiers":[
        {
            "category":"Health Services",
            "subcategory":"Doctor",
            "type":"Services"
        }
    ],
    "sg:phone":"+1 401 272 1550",
    "sg:postcode":"02909",
    "sg:province":"RI",
    "sg:tags":[
        "medical"
    ],
    "wof:name":"Constance M Brennan MD",
    "wof:placetype":"venue"
},
  "geometry": {"coordinates":[-71.429914,41.819625],"type":"Point"}
}