{
  "type": "Feature",
  "properties": {
    "iso:country":"US",
    "sg:address":"1003 Park Ave",
    "sg:city":"Cranston",
    "sg:classifiers":[
        {
            "category":"Autos & Motor Vehicles",
            "subcategory":"Automobile Sales",
            "type":"Retail Goods"
        }
    ],
    "sg:phone":"+1 401 942 9568",
    "sg:postcode":"02910",
    "sg:province":"RI",
    "wof:name":"Volare Motors",
    "wof:placetype":"venue"
},
  "geometry": {"coordinates":[-71.44246800000001,41.781923],"type":"Point"}
}