{
  "type": "Feature",
  "properties": {
    "addr:full":"76 Newport Ave Pawtucket RI 02861",
    "addr:housenumber":"76",
    "addr:postcode":"02861",
    "addr:street":"Newport Ave",
    "iso:country":"US",
    "sg:address":"76 Newport Ave",
    "sg:city":"Pawtucket",
    "sg:classifiers":[
        {
            "category":"Autos & Motor Vehicles",
            "subcategory":"Fuel & Gas Station",
            "type":"Retail Goods"
        }
    ],
    "sg:phone":"+1 401 722 1295",
    "sg:postcode":"02861",
    "sg:province":"RI",
    "sg:website":"www.citgo.com",
    "wof:name":"Jeha Citgo",
    "wof:placetype":"venue"
},
  "geometry": {"coordinates":[-71.35430100000001,41.862202],"type":"Point"}
}