{
  "type": "Feature",
  "properties": {
    "iso:country":"US",
    "sg:address":"31 Bullocks Point Ave",
    "sg:city":"Riverside",
    "sg:classifiers":[
        {
            "category":"Real Estate",
            "subcategory":"Real Estate Operator",
            "type":"Services"
        }
    ],
    "sg:phone":"+1 401 437 0440",
    "sg:postcode":"02915",
    "sg:province":"RI",
    "sg:tags":[
        "condominium"
    ],
    "wof:name":"Stonegate Condominiums",
    "wof:placetype":"venue"
},
  "geometry": {"coordinates":[-71.36327900000001,41.777732],"type":"Point"}
}