{
  "type": "Feature",
  "properties": {
    "iso:country":"US",
    "sg:address":"14 Lisbon St",
    "sg:city":"Providence",
    "sg:classifiers":[
        {
            "category":"Building & Trades",
            "subcategory":"Construction",
            "type":"Services"
        }
    ],
    "sg:phone":"+1 401 952 8022",
    "sg:postcode":"02908",
    "sg:province":"RI",
    "sg:tags":[
        "paving",
        "contractor"
    ],
    "wof:name":"Asphalt Driveways",
    "wof:placetype":"venue"
},
  "geometry": {"coordinates":[-71.43461499999999,41.831329],"type":"Point"}
}