{
  "type": "Feature",
  "properties": {
    "iso:country":"US",
    "sg:address":"6 Mallory Ct",
    "sg:city":"Bristol",
    "sg:classifiers":[
        {
            "category":"Professional",
            "subcategory":"Computer Services",
            "type":"Services"
        }
    ],
    "sg:phone":"+1 401 254 1523",
    "sg:postcode":"02809",
    "sg:province":"RI",
    "sg:tags":[
        "related"
    ],
    "wof:name":"Sbicon",
    "wof:placetype":"venue"
},
  "geometry": {"coordinates":[-71.261225,41.693933],"type":"Point"}
}