{
  "type": "Feature",
  "properties": {
    "addr:full":"199 Connell Hwy Newport RI 02840",
    "addr:housenumber":"199",
    "addr:postcode":"02840",
    "addr:street":"Connell Hwy",
    "iso:country":"US",
    "sg:address":"199 Connell Hwy",
    "sg:city":"Newport",
    "sg:classifiers":[
        {
            "category":"Home & Garden",
            "subcategory":"Furniture",
            "type":"Retail Goods"
        }
    ],
    "sg:phone":"+1 401 846 2853",
    "sg:postcode":"02840",
    "sg:province":"RI",
    "sg:tags":[
        "mattress"
    ],
    "wof:name":"Mattress Giant Corporation",
    "wof:placetype":"venue"
},
  "geometry": {"coordinates":[-71.317661,41.512519],"type":"Point"}
}