{
  "type": "Feature",
  "properties": {
    "iso:country":"US",
    "sg:address":"41 Pachet Brook Rd",
    "sg:city":"Little Compton",
    "sg:classifiers":[
        {
            "category":"Utilities",
            "subcategory":"Natural Gas",
            "type":"Services"
        }
    ],
    "sg:phone":"+1 401 635 8399",
    "sg:postcode":"02837",
    "sg:province":"RI",
    "sg:tags":[
        "distribution"
    ],
    "wof:name":"Gas Master Inc",
    "wof:placetype":"venue"
},
  "geometry": {"coordinates":[-71.1725,41.550684],"type":"Point"}
}