{
  "type": "Feature",
  "properties": {
    "addr:full":"35 Laurel Wood Dr East Greenwich RI 02818",
    "addr:housenumber":"35",
    "addr:postcode":"02818",
    "addr:street":"Laurel Wood Dr",
    "iso:country":"US",
    "sg:address":"35 Laurel Wood Dr",
    "sg:city":"East Greenwich",
    "sg:classifiers":[
        {
            "category":"Health Services",
            "subcategory":"Doctor",
            "type":"Services"
        }
    ],
    "sg:phone":"+1 401 884 4092",
    "sg:postcode":"02818",
    "sg:province":"RI",
    "sg:tags":[
        "medical"
    ],
    "wof:name":"Latha Pisharodi",
    "wof:placetype":"venue"
},
  "geometry": {"coordinates":[-71.475938,41.655291],"type":"Point"}
}