{
  "type": "Feature",
  "properties": {
    "iso:country":"US",
    "sg:address":"11 Sunrise Rd",
    "sg:city":"Cranston",
    "sg:classifiers":[
        {
            "category":"Restaurant",
            "type":"Food & Drink"
        }
    ],
    "sg:phone":"+1 401 823 7079",
    "sg:postcode":"02920",
    "sg:province":"RI",
    "sg:tags":[
        "eating"
    ],
    "wof:name":"Demos Pizza Factory Inc",
    "wof:placetype":"venue"
},
  "geometry": {"coordinates":[-71.48452399999999,41.739166],"type":"Point"}
}