{
  "type": "Feature",
  "properties": {
    "iso:country":"US",
    "sg:address":"5 Circuit Dr",
    "sg:city":"Warren",
    "sg:classifiers":[
        {
            "category":"Building & Trades",
            "subcategory":"Construction",
            "type":"Services"
        }
    ],
    "sg:phone":"+1 401 247 4256",
    "sg:postcode":"02885",
    "sg:province":"RI",
    "sg:tags":[
        "house"
    ],
    "wof:name":"Pine Ridge Builders Inc",
    "wof:placetype":"venue"
},
  "geometry": {"coordinates":[-71.24185199999999,41.699878],"type":"Point"}
}