{
  "type": "Feature",
  "properties": {
    "iso:country":"US",
    "sg:address":"1 Crestwood Dr",
    "sg:city":"Johnston",
    "sg:classifiers":[
        {
            "category":"Real Estate",
            "subcategory":"Real Estate Agent",
            "type":"Services"
        }
    ],
    "sg:phone":"+1 401 944 0104",
    "sg:postcode":"02919",
    "sg:province":"RI",
    "wof:name":"Middlebridge Reality",
    "wof:placetype":"venue"
},
  "geometry": {"coordinates":[-71.498886,41.810843],"type":"Point"}
}