{
  "type": "Feature",
  "properties": {
    "iso:country":"US",
    "sg:address":"476 High St",
    "sg:city":"Central Falls",
    "sg:classifiers":[
        {
            "category":"Organizations",
            "subcategory":"Non-profit Organization",
            "type":"Services"
        }
    ],
    "sg:phone":"+1 401 723 2220",
    "sg:postcode":"02863",
    "sg:province":"RI",
    "sg:tags":[
        "information",
        "alcoholism",
        "treatment"
    ],
    "wof:name":"A A Intl Group",
    "wof:placetype":"venue"
},
  "geometry": {"coordinates":[-71.383917,41.885704],"type":"Point"}
}