{
  "type": "Feature",
  "properties": {
    "iso:country":"US",
    "sg:address":"5 Mary Ave",
    "sg:city":"East Providence",
    "sg:classifiers":[
        {
            "category":"Building & Trades",
            "subcategory":"Construction",
            "type":"Services"
        }
    ],
    "sg:phone":"+1 401 632 0047",
    "sg:postcode":"02914",
    "sg:province":"RI",
    "sg:tags":[
        "general",
        "contractor"
    ],
    "wof:name":"D Huard Construction",
    "wof:placetype":"venue"
},
  "geometry": {"coordinates":[-71.371075,41.820077],"type":"Point"}
}