{
  "type": "Feature",
  "properties": {
    "iso:country":"US",
    "sg:address":"50 Surrey Ln",
    "sg:city":"North Kingstown",
    "sg:classifiers":[
        {
            "category":"Communications",
            "subcategory":"Film & Video Production",
            "type":"Services"
        }
    ],
    "sg:phone":"+1 401 884 0188",
    "sg:postcode":"02852",
    "sg:province":"RI",
    "sg:tags":[
        "motion"
    ],
    "wof:name":"Laptew Productions",
    "wof:placetype":"venue"
},
  "geometry": {"coordinates":[-71.48084900000001,41.605211],"type":"Point"}
}