{
  "type": "Feature",
  "properties": {
    "addr:full":"2 Brook St Providence RI 02906",
    "addr:housenumber":"2",
    "addr:postcode":"02906",
    "addr:street":"Brook St",
    "iso:country":"US",
    "sg:address":"2 Brook St",
    "sg:city":"Providence",
    "sg:classifiers":[
        {
            "category":"Professional",
            "subcategory":"Lawyer & Legal Services",
            "type":"Services"
        }
    ],
    "sg:phone":"+1 401 861 1940",
    "sg:postcode":"02906",
    "sg:province":"RI",
    "wof:name":"William C Bowling Atty",
    "wof:placetype":"venue"
},
  "geometry": {"coordinates":[-71.398201,41.819038],"type":"Point"}
}