{
  "type": "Feature",
  "properties": {
    "iso:country":"US",
    "sg:address":"365 Waterman Ave",
    "sg:city":"East Providence",
    "sg:classifiers":[
        {
            "category":"Retail",
            "subcategory":"Auto Rental",
            "type":"Services"
        }
    ],
    "sg:phone":"+1 401 438 8550",
    "sg:postcode":"02914",
    "sg:province":"RI",
    "sg:tags":[
        "renting",
        "passenger",
        "car",
        "automobile"
    ],
    "sg:website":"www.enterprise.com",
    "wof:name":"Enterprise Rent-A-Car",
    "wof:placetype":"venue"
},
  "geometry": {"coordinates":[-71.36491100000001,41.818913],"type":"Point"}
}