{
  "type": "Feature",
  "properties": {
    "addr:full":"200 1st Ave Cranston RI 02910",
    "addr:housenumber":"200",
    "addr:postcode":"02910",
    "addr:street":"1St Ave",
    "iso:country":"US",
    "sg:address":"200 1st Ave",
    "sg:city":"Cranston",
    "sg:classifiers":[
        {
            "category":"Wholesale",
            "subcategory":"Home Furnishings",
            "type":"Manufacturing & Wholesale Goods"
        }
    ],
    "sg:phone":"+1 401 467 1030",
    "sg:postcode":"02910",
    "sg:province":"RI",
    "sg:tags":[
        "floor",
        "covering"
    ],
    "wof:name":"G & M Company Inc",
    "wof:placetype":"venue"
},
  "geometry": {"coordinates":[-71.42081399999999,41.766652],"type":"Point"}
}