{
  "type": "Feature",
  "properties": {
    "iso:country":"US",
    "sg:address":"470 Gaskill St",
    "sg:city":"Woonsocket",
    "sg:classifiers":[
        {
            "category":"Building & Trades",
            "subcategory":"Construction",
            "type":"Services"
        }
    ],
    "sg:phone":"+1 401 766 5988",
    "sg:postcode":"02895",
    "sg:province":"RI",
    "sg:tags":[
        "hanging",
        "contractor"
    ],
    "wof:name":"St Sauveur & Sons Painting",
    "wof:placetype":"venue"
},
  "geometry": {"coordinates":[-71.518021,42.015548],"type":"Point"}
}