{
  "type": "Feature",
  "properties": {
    "iso:country":"US",
    "sg:address":"51 Quail Ln",
    "sg:city":"Charlestown",
    "sg:classifiers":[
        {
            "category":"Food & Beverages",
            "subcategory":"Specialty",
            "type":"Retail Goods"
        }
    ],
    "sg:phone":"+1 401 364 5095",
    "sg:postcode":"02813",
    "sg:province":"RI",
    "sg:tags":[
        "health",
        "diet"
    ],
    "wof:name":"Herbalife Distributor",
    "wof:placetype":"venue"
},
  "geometry": {"coordinates":[-71.68147,41.388369],"type":"Point"}
}