{
  "type": "Feature",
  "properties": {
    "addr:full":"105 Old Greenwich Dr East Greenwich RI 02818",
    "addr:housenumber":"105",
    "addr:postcode":"02818",
    "addr:street":"Old Greenwich Dr",
    "iso:country":"US",
    "sg:address":"105 Old Greenwich Dr",
    "sg:city":"East Greenwich",
    "sg:classifiers":[
        {
            "category":"Building & Trades",
            "subcategory":"Construction",
            "type":"Services"
        }
    ],
    "sg:phone":"+1 401 885 5300",
    "sg:postcode":"02818",
    "sg:province":"RI",
    "sg:tags":[
        "general",
        "contractor"
    ],
    "wof:name":"Salt Pond Construction",
    "wof:placetype":"venue"
},
  "geometry": {"coordinates":[-71.47868099999999,41.654602],"type":"Point"}
}