{
  "type": "Feature",
  "properties": {
    "iso:country":"US",
    "sg:address":"341 Broadway",
    "sg:city":"Providence",
    "sg:classifiers":[
        {
            "category":"Health Services",
            "subcategory":"Hospital",
            "type":"Services"
        }
    ],
    "sg:phone":"+1 401 274 2844",
    "sg:postcode":"02909",
    "sg:province":"RI",
    "sg:tags":[
        "specialty"
    ],
    "wof:name":"David J Stern",
    "wof:placetype":"venue"
},
  "geometry": {"coordinates":[-71.428681,41.820092],"type":"Point"}
}