{
  "type": "Feature",
  "properties": {
    "iso:country":"US",
    "sg:address":"910 W Shore Rd",
    "sg:city":"Warwick",
    "sg:classifiers":[
        {
            "category":"Shopping",
            "type":"Retail Goods"
        }
    ],
    "sg:phone":"+1 401 463 5297",
    "sg:postcode":"02889",
    "sg:province":"RI",
    "sg:tags":[
        "equipment",
        "telephone",
        "supply"
    ],
    "wof:name":"Bay Communications",
    "wof:placetype":"venue"
},
  "geometry": {"coordinates":[-71.378479,41.721033],"type":"Point"}
}