{
  "type": "Feature",
  "properties": {
    "addr:full":"5770 Post Rd East Greenwich RI 02818",
    "addr:housenumber":"5770",
    "addr:postcode":"02818",
    "addr:street":"Post Rd",
    "iso:country":"US",
    "sg:address":"5770 Post Rd",
    "sg:city":"East Greenwich",
    "sg:classifiers":[
        {
            "category":"Government",
            "subcategory":"Office",
            "type":"Public Place"
        }
    ],
    "sg:phone":"+1 401 884 0251",
    "sg:postcode":"02818",
    "sg:province":"RI",
    "wof:name":"State Office",
    "wof:placetype":"venue"
},
  "geometry": {"coordinates":[-71.468825,41.639441],"type":"Point"}
}