{
  "type": "Feature",
  "properties": {
    "iso:country":"US",
    "sg:address":"996 Smith St",
    "sg:city":"Providence",
    "sg:classifiers":[
        {
            "category":"Professional",
            "subcategory":"Lawyer & Legal Services",
            "type":"Services"
        }
    ],
    "sg:phone":"+1 401 353 0600",
    "sg:postcode":"02908",
    "sg:province":"RI",
    "sg:tags":[
        "attorney"
    ],
    "wof:name":"Maryann Patalano",
    "wof:placetype":"venue"
},
  "geometry": {"coordinates":[-71.444956,41.842388],"type":"Point"}
}