{
  "type": "Feature",
  "properties": {
    "addr:full":"930 Wellington Ave Cranston RI 02910",
    "addr:housenumber":"930",
    "addr:postcode":"02910",
    "addr:street":"Wellington Ave",
    "iso:country":"US",
    "sg:address":"930 Wellington Ave",
    "sg:city":"Cranston",
    "sg:classifiers":[
        {
            "category":"Manufacturing",
            "subcategory":"Jewelry",
            "type":"Manufacturing & Wholesale Goods"
        }
    ],
    "sg:phone":"+1 401 467 8000",
    "sg:postcode":"02910",
    "sg:province":"RI",
    "sg:tags":[
        "metal",
        "casting",
        "mfg"
    ],
    "wof:name":"Hallmark Metals Corp",
    "wof:placetype":"venue"
},
  "geometry": {"coordinates":[-71.430132,41.764426],"type":"Point"}
}