{
  "type": "Feature",
  "properties": {
    "iso:country":"US",
    "sg:address":"40 Sonoma Ct",
    "sg:city":"Providence",
    "sg:classifiers":[
        {
            "category":"Communications",
            "type":"Services"
        }
    ],
    "sg:phone":"+1 401 383 6771",
    "sg:postcode":"02909",
    "sg:province":"RI",
    "sg:tags":[
        "web",
        "design"
    ],
    "wof:name":"Virtual and More",
    "wof:placetype":"venue"
},
  "geometry": {"coordinates":[-71.442048,41.819844],"type":"Point"}
}