{
  "type": "Feature",
  "properties": {
    "iso:country":"US",
    "sg:address":"1 Hill Ave",
    "sg:city":"North Scituate",
    "sg:classifiers":[
        {
            "category":"Farming",
            "subcategory":"Farm",
            "type":"Manufacturing & Wholesale Goods"
        }
    ],
    "sg:phone":"+1 401 949 1694",
    "sg:postcode":"02857",
    "sg:province":"RI",
    "wof:name":"Knight Farm",
    "wof:placetype":"venue"
},
  "geometry": {"coordinates":[-71.573685,41.830799],"type":"Point"}
}