{
  "type": "Feature",
  "properties": {
    "iso:country":"US",
    "sg:address":"25 Greene Ave",
    "sg:city":"Cranston",
    "sg:classifiers":[
        {
            "category":"Insurance",
            "subcategory":"Hazard Insurance",
            "type":"Services"
        }
    ],
    "sg:phone":"+1 401 946 1156",
    "sg:postcode":"02920",
    "sg:province":"RI",
    "sg:tags":[
        "carrier",
        "surety"
    ],
    "wof:name":"Angelo Menna Insurance In",
    "wof:placetype":"venue"
},
  "geometry": {"coordinates":[-71.467461,41.782874],"type":"Point"}
}