{
  "type": "Feature",
  "properties": {
    "iso:country":"US",
    "sg:address":"66 Friendship St",
    "sg:city":"Newport",
    "sg:classifiers":[
        {
            "category":"Organizations",
            "subcategory":"Religious Organization",
            "type":"Services"
        }
    ],
    "sg:phone":"+1 401 849 4969",
    "sg:postcode":"02840",
    "sg:province":"RI",
    "wof:name":"Sure Foundation Ministries",
    "wof:placetype":"venue"
},
  "geometry": {"coordinates":[-71.303146,41.495478],"type":"Point"}
}