{
  "type": "Feature",
  "properties": {
    "addr:full":"105 Valley St East Providence RI 02914",
    "addr:housenumber":"105",
    "addr:postcode":"02914",
    "addr:street":"Valley St",
    "iso:country":"US",
    "sg:address":"105 Valley St",
    "sg:city":"East Providence",
    "sg:classifiers":[
        {
            "category":"Building & Trades",
            "subcategory":"Construction",
            "type":"Services"
        }
    ],
    "sg:phone":"+1 401 431 2600",
    "sg:postcode":"02914",
    "sg:province":"RI",
    "sg:tags":[
        "demolition",
        "contractor"
    ],
    "wof:name":"Advanced Construction Tech Crp",
    "wof:placetype":"venue"
},
  "geometry": {"coordinates":[-71.380099,41.823286],"type":"Point"}
}