{
  "type": "Feature",
  "properties": {
    "addr:full":"31 W Main Rd Middletown RI 02842",
    "addr:housenumber":"31",
    "addr:postcode":"02842",
    "addr:street":"W Main Rd",
    "iso:country":"US",
    "sg:address":"31 W Main Rd",
    "sg:city":"Middletown",
    "sg:classifiers":[
        {
            "category":"Travel",
            "subcategory":"Hotels & Motels",
            "type":"Entertainment"
        }
    ],
    "sg:phone":"+1 401 847 2735",
    "sg:postcode":"02842",
    "sg:province":"RI",
    "sg:website":"www.historicinnsofnewport.com",
    "wof:name":"Newport Gateway Hotel",
    "wof:placetype":"venue"
},
  "geometry": {"coordinates":[-71.30147599999999,41.506293],"type":"Point"}
}