{
  "type": "Feature",
  "properties": {
    "iso:country":"US",
    "sg:address":"1 Ralston St",
    "sg:city":"Providence",
    "sg:classifiers":[
        {
            "category":"Real Estate",
            "subcategory":"Real Estate Agent",
            "type":"Services"
        }
    ],
    "sg:phone":"+1 401 521 6469",
    "sg:postcode":"02904",
    "sg:province":"RI",
    "wof:name":"Twin Del Realty Co Inc",
    "wof:placetype":"venue"
},
  "geometry": {"coordinates":[-71.427414,41.859179],"type":"Point"}
}