{
  "type": "Feature",
  "properties": {
    "iso:country":"US",
    "sg:address":"6663 Post Rd",
    "sg:city":"North Kingstown",
    "sg:classifiers":[
        {
            "category":"Personal",
            "subcategory":"Beauty Salon",
            "type":"Services"
        }
    ],
    "sg:phone":"+1 401 884 0127",
    "sg:postcode":"02852",
    "sg:province":"RI",
    "sg:tags":[
        "manicuring"
    ],
    "wof:name":"Lucky Nail",
    "wof:placetype":"venue"
},
  "geometry": {"coordinates":[-71.457886,41.615803],"type":"Point"}
}