{
  "type": "Feature",
  "properties": {
    "addr:full":"521 Sandy Ln Warwick RI 02889",
    "addr:housenumber":"521",
    "addr:postcode":"02889",
    "addr:street":"Sandy Ln",
    "iso:country":"US",
    "sg:address":"521 Sandy Ln",
    "sg:city":"Warwick",
    "sg:classifiers":[
        {
            "category":"Home & Garden",
            "subcategory":"Building Materials",
            "type":"Retail Goods"
        }
    ],
    "sg:phone":"+1 401 782 1600",
    "sg:postcode":"02889",
    "sg:province":"RI",
    "sg:tags":[
        "glass",
        "window",
        "plate"
    ],
    "wof:name":"Payless Auto Glass Of Ri Inc",
    "wof:placetype":"venue"
},
  "geometry": {"coordinates":[-71.39988700000001,41.712289],"type":"Point"}
}