{
  "type": "Feature",
  "properties": {
    "addr:full":"190 Plainfield St Providence RI 02909",
    "addr:housenumber":"190",
    "addr:postcode":"02909",
    "addr:street":"Plainfield St",
    "iso:country":"US",
    "sg:address":"190 Plainfield St",
    "sg:city":"Providence",
    "sg:classifiers":[
        {
            "category":"Restaurant",
            "type":"Food & Drink"
        }
    ],
    "sg:phone":"+1 401 942 3783",
    "sg:postcode":"02909",
    "sg:province":"RI",
    "sg:tags":[
        "chinese"
    ],
    "wof:name":"China House Restaurant",
    "wof:placetype":"venue"
},
  "geometry": {"coordinates":[-71.446701,41.814899],"type":"Point"}
}