{
  "type": "Feature",
  "properties": {
    "iso:country":"US",
    "sg:address":"6 Blackstone Valley Pl",
    "sg:city":"Lincoln",
    "sg:classifiers":[
        {
            "category":"Health Services",
            "subcategory":"Doctor",
            "type":"Services"
        }
    ],
    "sg:phone":"+1 401 334 3700",
    "sg:postcode":"02865",
    "sg:province":"RI",
    "sg:tags":[
        "orthopedist"
    ],
    "sg:website":"www.ogi-docs.com",
    "wof:name":"Singer Ira J MD",
    "wof:placetype":"venue"
},
  "geometry": {"coordinates":[-71.45729799999999,41.935501],"type":"Point"}
}