{
  "type": "Feature",
  "properties": {
    "iso:country":"US",
    "sg:address":"1615 Pontiac Ave",
    "sg:city":"Cranston",
    "sg:classifiers":[
        {
            "category":"Real Estate",
            "subcategory":"Real Estate Services",
            "type":"Services"
        }
    ],
    "sg:phone":"+1 401 751 8090",
    "sg:postcode":"02920",
    "sg:province":"RI",
    "sg:tags":[
        "company",
        "title",
        "escrow"
    ],
    "wof:name":"Liberty Title & Escrow Co Inc",
    "wof:placetype":"venue"
},
  "geometry": {"coordinates":[-71.46194,41.739346],"type":"Point"}
}