{
  "type": "Feature",
  "properties": {
    "addr:full":"1372 Park Ave Cranston RI 02920",
    "addr:housenumber":"1372",
    "addr:postcode":"02920",
    "addr:street":"Park Ave",
    "iso:country":"US",
    "sg:address":"1372 Park Ave",
    "sg:city":"Cranston",
    "sg:classifiers":[
        {
            "category":"Retail",
            "subcategory":"Auto Repair",
            "type":"Services"
        }
    ],
    "sg:phone":"+1 401 943 9370",
    "sg:postcode":"02920",
    "sg:province":"RI",
    "sg:tags":[
        "installs",
        "automotive",
        "glass"
    ],
    "wof:name":"Triumph Auto Glass",
    "wof:placetype":"venue"
},
  "geometry": {"coordinates":[-71.459129,41.783687],"type":"Point"}
}