{
  "type": "Feature",
  "properties": {
    "iso:country":"US",
    "sg:address":"705 Central Ave",
    "sg:city":"Pawtucket",
    "sg:classifiers":[
        {
            "category":"Organizations",
            "subcategory":"Religious Organization",
            "type":"Services"
        }
    ],
    "sg:phone":"+1 401 722 4221",
    "sg:postcode":"02861",
    "sg:province":"RI",
    "wof:name":"St Leo The Great Convent",
    "wof:placetype":"venue"
},
  "geometry": {"coordinates":[-71.354568,41.88772],"type":"Point"}
}