{
  "type": "Feature",
  "properties": {
    "iso:country":"US",
    "sg:address":"238 Thayer St",
    "sg:city":"Providence",
    "sg:classifiers":[
        {
            "category":"Banks & Credit Unions",
            "subcategory":"Bank",
            "type":"Services"
        }
    ],
    "sg:phone":"+1 401 276 1539",
    "sg:postcode":"02906",
    "sg:province":"RI",
    "sg:tags":[
        "state",
        "commercial"
    ],
    "wof:name":"Fleet",
    "wof:placetype":"venue"
},
  "geometry": {"coordinates":[-71.400589,41.827685],"type":"Point"}
}