{
  "type": "Feature",
  "properties": {
    "iso:country":"US",
    "sg:address":"35 Nardolillo St",
    "sg:city":"Johnston",
    "sg:classifiers":[
        {
            "category":"Building & Trades",
            "subcategory":"Construction",
            "type":"Services"
        }
    ],
    "sg:phone":"+1 401 946 9142",
    "sg:postcode":"02919",
    "sg:province":"RI",
    "sg:tags":[
        "house"
    ],
    "wof:name":"New Look Remodeling",
    "wof:placetype":"venue"
},
  "geometry": {"coordinates":[-71.49897,41.795573],"type":"Point"}
}