{
  "type": "Feature",
  "properties": {
    "iso:country":"US",
    "sg:address":"1030 Main St",
    "sg:city":"West Warwick",
    "sg:classifiers":[
        {
            "category":"Health Services",
            "subcategory":"Doctor",
            "type":"Services"
        }
    ],
    "sg:phone":"+1 401 821 7022",
    "sg:postcode":"02893",
    "sg:province":"RI",
    "wof:name":"Hanley Christopher J Jr",
    "wof:placetype":"venue"
},
  "geometry": {"coordinates":[-71.523499,41.712691],"type":"Point"}
}