{
  "type": "Feature",
  "properties": {
    "addr:full":"184 Woonasquatucket Ave North Providence RI 02911",
    "addr:housenumber":"184",
    "addr:postcode":"02911",
    "addr:street":"Woonasquatucket Ave",
    "iso:country":"US",
    "sg:address":"184 Woonasquatucket Ave",
    "sg:city":"North Providence",
    "sg:classifiers":[
        {
            "category":"Manufacturing",
            "subcategory":"Jewelry",
            "type":"Manufacturing & Wholesale Goods"
        }
    ],
    "sg:phone":"+1 401 354 6500",
    "sg:postcode":"02911",
    "sg:province":"RI",
    "sg:tags":[
        "mfg",
        "novelty",
        "except",
        "costume",
        "article",
        "religious"
    ],
    "wof:name":"Berkander Company Inc",
    "wof:placetype":"venue"
},
  "geometry": {"coordinates":[-71.474197,41.839346],"type":"Point"}
}