{
  "type": "Feature",
  "properties": {
    "iso:country":"US",
    "sg:address":"1500 Diamond Hill Rd",
    "sg:city":"Woonsocket",
    "sg:classifiers":[
        {
            "category":"Shopping",
            "type":"Retail Goods"
        }
    ],
    "sg:phone":"+1 401 769 2681",
    "sg:postcode":"02895",
    "sg:province":"RI",
    "sg:tags":[
        "hearing",
        "equipment",
        "supply",
        "impaired"
    ],
    "sg:website":"www.miracle-ear.com",
    "wof:name":"Miracle-Ear",
    "wof:placetype":"venue"
},
  "geometry": {"coordinates":[-71.47897,42.015913],"type":"Point"}
}