{
  "type": "Feature",
  "properties": {
    "iso:country":"US",
    "sg:address":"40 Asylum Rd",
    "sg:city":"Warwick",
    "sg:classifiers":[
        {
            "category":"Education",
            "subcategory":"School",
            "type":"Public Place"
        }
    ],
    "sg:phone":"+1 401 734 3690",
    "sg:postcode":"02886",
    "sg:province":"RI",
    "sg:tags":[
        "elementary"
    ],
    "wof:name":"Park Elementary School",
    "wof:placetype":"venue"
},
  "geometry": {"coordinates":[-71.41897899999999,41.69326],"type":"Point"}
}