{
  "type": "Feature",
  "properties": {
    "iso:country":"US",
    "sg:address":"692 Aquidneck Ave",
    "sg:city":"Middletown",
    "sg:classifiers":[
        {
            "category":"Professional",
            "subcategory":"Business Services",
            "type":"Services"
        }
    ],
    "sg:phone":"+1 401 849 6111",
    "sg:postcode":"02842",
    "sg:province":"RI",
    "sg:tags":[
        "engraver"
    ],
    "sg:website":"www.signaturesofnewport.com",
    "wof:name":"Signatures Of Newport",
    "wof:placetype":"venue"
},
  "geometry": {"coordinates":[-71.28156799999999,41.50467],"type":"Point"}
}