{
  "type": "Feature",
  "properties": {
    "addr:full":"114 Providence Pl Providence RI 02903",
    "addr:housenumber":"114",
    "addr:postcode":"02903",
    "addr:street":"Providence Pl",
    "iso:country":"US",
    "sg:address":"114 Providence Pl",
    "sg:city":"Providence",
    "sg:classifiers":[
        {
            "category":"Shopping",
            "subcategory":"Clothing, Apparel, & Fashions",
            "type":"Retail Goods"
        }
    ],
    "sg:phone":"+1 401 270 4270",
    "sg:postcode":"02903",
    "sg:province":"RI",
    "sg:tags":[
        "family"
    ],
    "wof:name":"American Eagle Outfitters",
    "wof:placetype":"venue"
},
  "geometry": {"coordinates":[-71.41894499999999,41.827686],"type":"Point"}
}