{
  "type": "Feature",
  "properties": {
    "iso:country":"US",
    "sg:address":"1 Charlestown Beach Rd",
    "sg:city":"Charlestown",
    "sg:classifiers":[
        {
            "category":"Sports & Exercise",
            "subcategory":"Gym",
            "type":"Entertainment"
        }
    ],
    "sg:phone":"+1 401 364 1606",
    "sg:postcode":"02813",
    "sg:province":"RI",
    "sg:tags":[
        "club",
        "health",
        "studio",
        "gymnasium"
    ],
    "wof:name":"Curves",
    "wof:placetype":"venue"
},
  "geometry": {"coordinates":[-71.624138,41.380527],"type":"Point"}
}