{
  "type": "Feature",
  "properties": {
    "iso:country":"US",
    "sg:address":"560 Atwood Ave",
    "sg:city":"Cranston",
    "sg:classifiers":[
        {
            "category":"Personal",
            "subcategory":"Beauty Salon",
            "type":"Services"
        }
    ],
    "sg:phone":"+1 401 831 0330",
    "sg:postcode":"02920",
    "sg:province":"RI",
    "sg:tags":[
        "shop"
    ],
    "wof:name":"Salon Rio",
    "wof:placetype":"venue"
},
  "geometry": {"coordinates":[-71.472679,41.791934],"type":"Point"}
}