{
  "type": "Feature",
  "properties": {
    "iso:country":"US",
    "sg:address":"90 Worcester Ave",
    "sg:city":"Riverside",
    "sg:classifiers":[
        {
            "category":"Real Estate",
            "subcategory":"Real Estate Services",
            "type":"Services"
        }
    ],
    "sg:phone":"+1 401 433 1281",
    "sg:postcode":"02915",
    "sg:province":"RI",
    "sg:tags":[
        "vacancy",
        "apartment",
        "rental",
        "finder",
        "listing"
    ],
    "wof:name":"Susan Freda Studio",
    "wof:placetype":"venue"
},
  "geometry": {"coordinates":[-71.357463,41.764653],"type":"Point"}
}