{
  "type": "Feature",
  "properties": {
    "iso:country":"US",
    "sg:address":"33 North Rd",
    "sg:city":"Wakefield",
    "sg:classifiers":[
        {
            "category":"Professional",
            "subcategory":"Business Services",
            "type":"Services"
        }
    ],
    "sg:phone":"+1 401 782 0702",
    "sg:postcode":"02879",
    "sg:province":"RI",
    "sg:tags":[
        "benefit",
        "management"
    ],
    "wof:name":"Mim Health Plans",
    "wof:placetype":"venue"
},
  "geometry": {"coordinates":[-71.496509,41.452693],"type":"Point"}
}