{
  "type": "Feature",
  "properties": {
    "iso:country":"US",
    "sg:address":"39 Winslow Ave",
    "sg:city":"Warwick",
    "sg:classifiers":[
        {
            "category":"Real Estate",
            "subcategory":"Real Estate Agent",
            "type":"Services"
        }
    ],
    "sg:phone":"+1 401 739 1135",
    "sg:postcode":"02886",
    "sg:province":"RI",
    "wof:name":"Cleo E Lachapelle Real Estate",
    "wof:placetype":"venue"
},
  "geometry": {"coordinates":[-71.45411799999999,41.703551],"type":"Point"}
}