{
  "type": "Feature",
  "properties": {
    "iso:country":"US",
    "sg:address":"208 Governor St",
    "sg:city":"Providence",
    "sg:classifiers":[
        {
            "category":"Sports & Exercise",
            "subcategory":"Gym",
            "type":"Entertainment"
        }
    ],
    "sg:phone":"+1 401 453 0303",
    "sg:postcode":"02906",
    "sg:province":"RI",
    "sg:tags":[
        "trainer"
    ],
    "wof:name":"Body Renaissance Llc",
    "wof:placetype":"venue"
},
  "geometry": {"coordinates":[-71.394048,41.827703],"type":"Point"}
}