{
  "type": "Feature",
  "properties": {
    "iso:country":"US",
    "sg:address":"231 Seaside Dr",
    "sg:city":"Jamestown",
    "sg:classifiers":[
        {
            "category":"Real Estate",
            "subcategory":"Real Estate Agent",
            "type":"Services"
        }
    ],
    "sg:phone":"+1 401 295 5441",
    "sg:postcode":"02835",
    "sg:province":"RI",
    "wof:name":"Compass Realty",
    "wof:placetype":"venue"
},
  "geometry": {"coordinates":[-71.38846700000001,41.532994],"type":"Point"}
}