{
  "type": "Feature",
  "properties": {
    "iso:country":"US",
    "sg:address":"62 Danielson Pike",
    "sg:city":"North Scituate",
    "sg:classifiers":[
        {
            "category":"Retail",
            "subcategory":"Repair Shop",
            "type":"Services"
        }
    ],
    "sg:phone":"+1 401 647 2909",
    "sg:postcode":"02857",
    "sg:province":"RI",
    "sg:tags":[
        "upholsterer"
    ],
    "wof:name":"Gerald D Emin Upholstery",
    "wof:placetype":"venue"
},
  "geometry": {"coordinates":[-71.580389,41.832976],"type":"Point"}
}