{
  "type": "Feature",
  "properties": {
    "iso:country":"US",
    "sg:address":"950 Broad St",
    "sg:city":"Providence",
    "sg:classifiers":[
        {
            "category":"Restaurant",
            "type":"Food & Drink"
        }
    ],
    "sg:phone":"+1 401 461 3760",
    "sg:postcode":"02905",
    "sg:province":"RI",
    "wof:name":"Brother's Famous Pizza",
    "wof:placetype":"venue"
},
  "geometry": {"coordinates":[-71.415018,41.798666],"type":"Point"}
}