{
  "type": "Feature",
  "properties": {
    "iso:country":"US",
    "sg:address":"1663 Mineral Spring Ave",
    "sg:city":"Providence",
    "sg:classifiers":[
        {
            "category":"Shopping",
            "subcategory":"Optical Goods",
            "type":"Retail Goods"
        }
    ],
    "sg:phone":"+1 401 353 3200",
    "sg:postcode":"02904",
    "sg:province":"RI",
    "sg:tags":[
        "store"
    ],
    "wof:name":"Vision World",
    "wof:placetype":"venue"
},
  "geometry": {"coordinates":[-71.45076899999999,41.863982],"type":"Point"}
}