{
  "type": "Feature",
  "properties": {
    "iso:country":"US",
    "sg:address":"445 Grange Rd",
    "sg:city":"North Smithfield",
    "sg:classifiers":[
        {
            "category":"Professional",
            "subcategory":"Engineering",
            "type":"Services"
        },
        {
            "category":"Manufacturing",
            "subcategory":"Toys & Sporting Goods",
            "type":"Manufacturing & Wholesale Goods"
        }
    ],
    "sg:phone":"+1 401 765 3833",
    "sg:postcode":"02896",
    "sg:province":"RI",
    "sg:tags":[
        "engineer",
        "mfg"
    ],
    "wof:name":"Acorn Meadow Designs",
    "wof:placetype":"venue"
},
  "geometry": {"coordinates":[-71.540662,41.946358],"type":"Point"}
}