{
  "type": "Feature",
  "properties": {
    "iso:country":"US",
    "sg:address":"929 Atwells Ave",
    "sg:city":"Providence",
    "sg:classifiers":[
        {
            "category":"Personal",
            "subcategory":"Beauty Salon",
            "type":"Services"
        }
    ],
    "sg:phone":"+1 401 331 4097",
    "sg:postcode":"02909",
    "sg:province":"RI",
    "sg:tags":[
        "shop"
    ],
    "wof:name":"Heidi S Hair Salon",
    "wof:placetype":"venue"
},
  "geometry": {"coordinates":[-71.448064,41.825105],"type":"Point"}
}