{
  "type": "Feature",
  "properties": {
    "iso:country":"US",
    "sg:address":"7 Loyola Ter",
    "sg:city":"Newport",
    "sg:classifiers":[
        {
            "category":"Retail",
            "subcategory":"Repair Shop",
            "type":"Services"
        }
    ],
    "sg:phone":"+1 401 849 6856",
    "sg:postcode":"02840",
    "sg:province":"RI",
    "sg:tags":[
        "miscellaneous"
    ],
    "wof:name":"Martin Douglas Inc",
    "wof:placetype":"venue"
},
  "geometry": {"coordinates":[-71.29989399999999,41.498849],"type":"Point"}
}