{
  "type": "Feature",
  "properties": {
    "addr:full":"Matunuck Beach Rd South Kingstown RI 02879",
    "addr:postcode":"02879",
    "addr:street":"Matunuck Beach Rd South",
    "iso:country":"US",
    "sg:address":"Matunuck Beach Rd",
    "sg:city":"South Kingstown",
    "sg:classifiers":[
        {
            "category":"Recreation",
            "subcategory":"Water Park",
            "type":"Entertainment"
        }
    ],
    "sg:postcode":"02879",
    "sg:province":"RI",
    "sg:tags":[
        "beach"
    ],
    "wof:name":"South Kingstown Town Beach",
    "wof:placetype":"venue"
},
  "geometry": {"coordinates":[-71.549663,41.38548],"type":"Point"}
}