{
  "type": "Feature",
  "properties": {
    "iso:country":"US",
    "sg:address":"3502 Mendon Rd",
    "sg:city":"Cumberland",
    "sg:classifiers":[
        {
            "category":"Government",
            "subcategory":"Fire Station",
            "type":"Public Place"
        }
    ],
    "sg:phone":"+1 401 658 0544",
    "sg:postcode":"02864",
    "sg:province":"RI",
    "sg:tags":[
        "protection"
    ],
    "sg:website":"www.cumberlandhillfire.com",
    "wof:name":"Cumberland Hill Fire Dept",
    "wof:placetype":"venue"
},
  "geometry": {"coordinates":[-71.461575,41.979015],"type":"Point"}
}