{
  "type": "Feature",
  "properties": {
    "iso:country":"US",
    "sg:address":"265 Post Rd",
    "sg:city":"Westerly",
    "sg:classifiers":[
        {
            "category":"Restaurant",
            "type":"Food & Drink"
        }
    ],
    "sg:menulink":"http://www.allmenus.com/ri/westerly/249149-w-b-codys/menu/",
    "sg:phone":"+1 401 322 4070",
    "sg:postcode":"02891",
    "sg:province":"RI",
    "sg:tags":[
        "american"
    ],
    "wof:name":"W. B. Cody's",
    "wof:placetype":"venue"
},
  "geometry": {"coordinates":[-71.76597599999999,41.351704],"type":"Point"}
}