{
  "type": "Feature",
  "properties": {
    "iso:country":"US",
    "sg:address":"294 Great Island Rd",
    "sg:city":"Narragansett",
    "sg:classifiers":[
        {
            "category":"Restaurant",
            "type":"Food & Drink"
        }
    ],
    "sg:phone":"+1 401 284 0246",
    "sg:postcode":"02882",
    "sg:province":"RI",
    "sg:tags":[
        "eating"
    ],
    "wof:name":"Wheelhouse Restaurant",
    "wof:placetype":"venue"
},
  "geometry": {"coordinates":[-71.507009,41.384964],"type":"Point"}
}