{
  "type": "Feature",
  "properties": {
    "iso:country":"US",
    "sg:address":"125 Newell Ave",
    "sg:city":"Pawtucket",
    "sg:classifiers":[
        {
            "category":"Retail",
            "subcategory":"Auto Rental",
            "type":"Services"
        }
    ],
    "sg:phone":"+1 401 724 8573",
    "sg:postcode":"02860",
    "sg:province":"RI",
    "sg:tags":[
        "renting",
        "truck",
        "leasing"
    ],
    "wof:name":"U-Haul Co",
    "wof:placetype":"venue"
},
  "geometry": {"coordinates":[-71.400451,41.869327],"type":"Point"}
}