{
  "type": "Feature",
  "properties": {
    "addr:full":"145 Dewolf Ave Bristol RI 02809",
    "addr:housenumber":"145",
    "addr:postcode":"02809",
    "addr:street":"Dewolf Ave",
    "iso:country":"US",
    "sg:address":"145 Dewolf Ave",
    "sg:city":"Bristol",
    "sg:classifiers":[
        {
            "category":"Manufacturing",
            "subcategory":"Watercraft",
            "type":"Manufacturing & Wholesale Goods"
        }
    ],
    "sg:phone":"+1 401 253 4176",
    "sg:postcode":"02809",
    "sg:province":"RI",
    "sg:tags":[
        "boat"
    ],
    "wof:name":"Ocean Scout Marine",
    "wof:placetype":"venue"
},
  "geometry": {"coordinates":[-71.26331,41.674092],"type":"Point"}
}