{
  "type": "Feature",
  "properties": {
    "iso:country":"US",
    "sg:address":"64 Halsey St",
    "sg:city":"Newport",
    "sg:classifiers":[
        {
            "category":"Building & Trades",
            "subcategory":"Electrical",
            "type":"Services"
        }
    ],
    "sg:phone":"+1 401 849 5656",
    "sg:postcode":"02840",
    "sg:province":"RI",
    "sg:tags":[
        "electric",
        "contractor"
    ],
    "wof:name":"Coastal Electric",
    "wof:placetype":"venue"
},
  "geometry": {"coordinates":[-71.314982,41.505707],"type":"Point"}
}