{
  "type": "Feature",
  "properties": {
    "addr:full":"308 Waterman Ave Smithfield RI 02917",
    "addr:housenumber":"308",
    "addr:postcode":"02917",
    "addr:street":"Waterman Ave",
    "iso:country":"US",
    "sg:address":"308 Waterman Ave",
    "sg:city":"Smithfield",
    "sg:classifiers":[
        {
            "category":"Retail",
            "subcategory":"Auto Repair",
            "type":"Services"
        }
    ],
    "sg:phone":"+1 401 231 1490",
    "sg:postcode":"02917",
    "sg:province":"RI",
    "sg:tags":[
        "repairing",
        "automobile",
        "general"
    ],
    "wof:name":"Murphy's Service Ctr",
    "wof:placetype":"venue"
},
  "geometry": {"coordinates":[-71.498364,41.875887],"type":"Point"}
}