{
  "type": "Feature",
  "properties": {
    "iso:country":"US",
    "sg:address":"2740 Wallum Lake Rd",
    "sg:city":"Pascoag",
    "sg:classifiers":[
        {
            "category":"Home & Garden",
            "subcategory":"Building Materials",
            "type":"Retail Goods"
        }
    ],
    "sg:phone":"+1 401 568 6812",
    "sg:postcode":"02859",
    "sg:province":"RI",
    "sg:tags":[
        "windows"
    ],
    "wof:name":"Couture Carpentry Svc",
    "wof:placetype":"venue"
},
  "geometry": {"coordinates":[-71.75361700000001,42.003339],"type":"Point"}
}