{
  "type": "Feature",
  "properties": {
    "iso:country":"US",
    "sg:address":"1067 Warwick Ave",
    "sg:city":"Warwick",
    "sg:classifiers":[
        {
            "category":"Insurance",
            "subcategory":"Insurance Agent",
            "type":"Services"
        }
    ],
    "sg:phone":"+1 401 941 4900",
    "sg:postcode":"02888",
    "sg:province":"RI",
    "wof:name":"Shailer & Greene Inc",
    "wof:placetype":"venue"
},
  "geometry": {"coordinates":[-71.40552599999999,41.746935],"type":"Point"}
}