{
  "type": "Feature",
  "properties": {
    "iso:country":"US",
    "sg:address":"72 Fales Rd",
    "sg:city":"Bristol",
    "sg:classifiers":[
        {
            "category":"Building & Trades",
            "subcategory":"Electrical",
            "type":"Services"
        }
    ],
    "sg:phone":"+1 401 253 4983",
    "sg:postcode":"02809",
    "sg:province":"RI",
    "sg:tags":[
        "work",
        "electrical"
    ],
    "wof:name":"Vans Electric",
    "wof:placetype":"venue"
},
  "geometry": {"coordinates":[-71.283962,41.69112],"type":"Point"}
}