{
  "type": "Feature",
  "properties": {
    "iso:country":"US",
    "sg:address":"1050 Reservoir Ave",
    "sg:city":"Cranston",
    "sg:classifiers":[
        {
            "category":"Real Estate",
            "subcategory":"Real Estate Agent",
            "type":"Services"
        }
    ],
    "sg:phone":"+1 401 738 6020",
    "sg:postcode":"02910",
    "sg:province":"RI",
    "wof:name":"Albert Realtors Better Homes",
    "wof:placetype":"venue"
},
  "geometry": {"coordinates":[-71.452105,41.772355],"type":"Point"}
}