{
  "type": "Feature",
  "properties": {
    "iso:country":"US",
    "sg:address":"249 Connell Hwy",
    "sg:city":"Newport",
    "sg:classifiers":[
        {
            "category":"Travel",
            "subcategory":"Hotels & Motels",
            "type":"Entertainment"
        }
    ],
    "sg:phone":"+1 401 848 0600",
    "sg:postcode":"02840",
    "sg:province":"RI",
    "sg:website":"www.motel6.com",
    "wof:name":"Motel 6",
    "wof:placetype":"venue"
},
  "geometry": {"coordinates":[-71.317847,41.510714],"type":"Point"}
}