{
  "type": "Feature",
  "properties": {
    "iso:country":"US",
    "sg:address":"1200 N Main St",
    "sg:city":"Providence",
    "sg:phone":"+1 401 272 3048",
    "sg:postcode":"02904",
    "sg:province":"RI",
    "sg:website":"http://www.riteaid.com",
    "wof:name":"Rite Aid",
    "wof:placetype":"venue"
},
  "geometry": {"coordinates":[-71.40137900000001,41.852993],"type":"Point"}
}