{
  "type": "Feature",
  "properties": {
    "addr:full":"1094 Bald Hill Rd Warwick RI 02886",
    "addr:housenumber":"1094",
    "addr:postcode":"02886",
    "addr:street":"Bald Hill Rd",
    "iso:country":"US",
    "sg:address":"1094 Bald Hill Rd",
    "sg:city":"Warwick",
    "sg:classifiers":[
        {
            "category":"Food & Beverages",
            "subcategory":"Specialty",
            "type":"Retail Goods"
        }
    ],
    "sg:phone":"+1 401 615 0665",
    "sg:postcode":"02886",
    "sg:province":"RI",
    "sg:tags":[
        "health",
        "diet"
    ],
    "wof:name":"Water To Go Diet & Nutri Ctr",
    "wof:placetype":"venue"
},
  "geometry": {"coordinates":[-71.494046,41.703159],"type":"Point"}
}