{
  "type": "Feature",
  "properties": {
    "addr:full":"587 Kingstown Rd Wakefield RI 02879",
    "addr:housenumber":"587",
    "addr:postcode":"02879",
    "addr:street":"Kingstown Rd",
    "iso:country":"US",
    "sg:address":"587 Kingstown Rd",
    "sg:city":"Wakefield",
    "sg:classifiers":[
        {
            "category":"Personal",
            "subcategory":"Beauty Salon",
            "type":"Services"
        }
    ],
    "sg:phone":"+1 401 789 3827",
    "sg:postcode":"02879",
    "sg:province":"RI",
    "sg:tags":[
        "shop"
    ],
    "wof:name":"Coiffures Unlimited",
    "wof:placetype":"venue"
},
  "geometry": {"coordinates":[-71.488457,41.441513],"type":"Point"}
}