{
  "type": "Feature",
  "properties": {
    "addr:full":"16 Corey Trl Wyoming RI 02898",
    "addr:housenumber":"16",
    "addr:postcode":"02898",
    "addr:street":"Corey Trl",
    "iso:country":"US",
    "sg:address":"16 Corey Trl",
    "sg:city":"Wyoming",
    "sg:classifiers":[
        {
            "category":"Building & Trades",
            "subcategory":"Construction",
            "type":"Services"
        }
    ],
    "sg:phone":"+1 401 539 2885",
    "sg:postcode":"02898",
    "sg:province":"RI",
    "sg:tags":[
        "concrete",
        "contractor"
    ],
    "wof:name":"Hathaway Concrete",
    "wof:placetype":"venue"
},
  "geometry": {"coordinates":[-71.702943,41.511509],"type":"Point"}
}