{
  "type": "Feature",
  "properties": {
    "iso:country":"US",
    "sg:address":"91 Countryside Dr",
    "sg:city":"Cumberland",
    "sg:classifiers":[
        {
            "category":"Professional",
            "subcategory":"Computer Services",
            "type":"Services"
        }
    ],
    "sg:phone":"+1 401 405 0394",
    "sg:postcode":"02864",
    "sg:province":"RI",
    "sg:tags":[
        "consultant",
        "designer"
    ],
    "wof:name":"SHE Incorporated",
    "wof:placetype":"venue"
},
  "geometry": {"coordinates":[-71.448019,41.976347],"type":"Point"}
}