{
  "type": "Feature",
  "properties": {
    "iso:country":"US",
    "sg:address":"12 Dodge St",
    "sg:city":"North Providence",
    "sg:classifiers":[
        {
            "category":"Building & Trades",
            "subcategory":"Construction",
            "type":"Services"
        }
    ],
    "sg:phone":"+1 401 723 0270",
    "sg:postcode":"02904",
    "sg:province":"RI",
    "sg:tags":[
        "tile",
        "dealer"
    ],
    "wof:name":"M Billo Tile Co",
    "wof:placetype":"venue"
},
  "geometry": {"coordinates":[-71.426671,41.865221],"type":"Point"}
}