{
  "type": "Feature",
  "properties": {
    "addr:full":"16 Orchard Ave Warren RI 02885",
    "addr:housenumber":"16",
    "addr:postcode":"02885",
    "addr:street":"Orchard Ave",
    "iso:country":"US",
    "sg:address":"16 Orchard Ave",
    "sg:city":"Warren",
    "sg:classifiers":[
        {
            "category":"Shopping",
            "type":"Retail Goods"
        }
    ],
    "sg:phone":"+1 401 245 2077",
    "sg:postcode":"02885",
    "sg:province":"RI",
    "sg:tags":[
        "aquarium"
    ],
    "wof:name":"Coral Reef Aquarium Mntnc",
    "wof:placetype":"venue"
},
  "geometry": {"coordinates":[-71.260566,41.728386],"type":"Point"}
}