{
  "type": "Feature",
  "properties": {
    "addr:full":"915 Chalkstone Ave Providence RI 02908",
    "addr:housenumber":"915",
    "addr:postcode":"02908",
    "addr:street":"Chalkstone Ave",
    "iso:country":"US",
    "sg:address":"915 Chalkstone Ave",
    "sg:city":"Providence",
    "sg:classifiers":[
        {
            "category":"Shopping",
            "subcategory":"Tobacco",
            "type":"Retail Goods"
        }
    ],
    "sg:phone":"+1 401 351 7322",
    "sg:postcode":"02908",
    "sg:province":"RI",
    "sg:tags":[
        "shop",
        "cigarette",
        "cigar"
    ],
    "wof:name":"It's All Good",
    "wof:placetype":"venue"
},
  "geometry": {"coordinates":[-71.43740099999999,41.832802],"type":"Point"}
}