{
  "type": "Feature",
  "properties": {
    "iso:country":"US",
    "sg:address":"96 Lakehurst Ave",
    "sg:city":"Coventry",
    "sg:classifiers":[
        {
            "category":"Building & Trades",
            "subcategory":"Construction",
            "type":"Services"
        }
    ],
    "sg:phone":"+1 401 397 2819",
    "sg:postcode":"02816",
    "sg:province":"RI",
    "sg:tags":[
        "excavation",
        "contractor"
    ],
    "wof:name":"R & T Santos Inc",
    "wof:placetype":"venue"
},
  "geometry": {"coordinates":[-71.611023,41.672051],"type":"Point"}
}