{
  "type": "Feature",
  "properties": {
    "iso:country":"US",
    "sg:address":"56 Caswell St",
    "sg:city":"Narragansett",
    "sg:classifiers":[
        {
            "category":"Real Estate",
            "subcategory":"Real Estate Agent",
            "type":"Services"
        }
    ],
    "sg:phone":"+1 401 789 7818",
    "sg:postcode":"02882",
    "sg:province":"RI",
    "wof:name":"C&G Realty LLC",
    "wof:placetype":"venue"
},
  "geometry": {"coordinates":[-71.46037699999999,41.430843],"type":"Point"}
}