{
  "type": "Feature",
  "properties": {
    "addr:full":"700 Aquidneck Ave Middletown RI 02842",
    "addr:housenumber":"700",
    "addr:postcode":"02842",
    "addr:street":"Aquidneck Ave",
    "iso:country":"US",
    "sg:address":"700 Aquidneck Ave",
    "sg:city":"Middletown",
    "sg:classifiers":[
        {
            "category":"Shopping",
            "subcategory":"Hobbies, Toys, & Games",
            "type":"Retail Goods"
        }
    ],
    "sg:phone":"+1 401 846 3349",
    "sg:postcode":"02842",
    "sg:province":"RI",
    "sg:tags":[
        "merchandise"
    ],
    "wof:name":"Arnold Art Center",
    "wof:placetype":"venue"
},
  "geometry": {"coordinates":[-71.28263699999999,41.507414],"type":"Point"}
}