{
  "type": "Feature",
  "properties": {
    "addr:full":"1288 Greenwich Ave Warwick RI 02886",
    "addr:housenumber":"1288",
    "addr:postcode":"02886",
    "addr:street":"Greenwich Ave",
    "iso:country":"US",
    "sg:address":"1288 Greenwich Ave",
    "sg:city":"Warwick",
    "sg:classifiers":[
        {
            "category":"Bars & Pubs",
            "type":"Food & Drink"
        }
    ],
    "sg:phone":"+1 401 738 5433",
    "sg:postcode":"02886",
    "sg:province":"RI",
    "sg:tags":[
        "drinking"
    ],
    "wof:name":"Down East Ltd",
    "wof:placetype":"venue"
},
  "geometry": {"coordinates":[-71.46101299999999,41.702738],"type":"Point"}
}