{
  "type": "Feature",
  "properties": {
    "iso:country":"US",
    "sg:address":"16 Campbell St",
    "sg:city":"Pawtucket",
    "sg:classifiers":[
        {
            "category":"Freight",
            "type":"Transportation"
        }
    ],
    "sg:phone":"+1 401 725 8527",
    "sg:postcode":"02861",
    "sg:province":"RI",
    "sg:tags":[
        "trucking"
    ],
    "wof:name":"Scotts Trucking LLC",
    "wof:placetype":"venue"
},
  "geometry": {"coordinates":[-71.362228,41.864714],"type":"Point"}
}