{
  "type": "Feature",
  "properties": {
    "addr:full":"2220 Plainfield Pike Cranston RI 02921",
    "addr:housenumber":"2220",
    "addr:postcode":"02921",
    "addr:street":"Plainfield Pike",
    "iso:country":"US",
    "sg:address":"2220 Plainfield Pike",
    "sg:city":"Cranston",
    "sg:classifiers":[
        {
            "category":"Professional",
            "type":"Services"
        }
    ],
    "sg:phone":"+1 401 464 4003",
    "sg:postcode":"02921",
    "sg:province":"RI",
    "sg:tags":[
        "establishment"
    ],
    "wof:name":"Deublin Co",
    "wof:placetype":"venue"
},
  "geometry": {"coordinates":[-71.517431,41.788602],"type":"Point"}
}