{
  "type": "Feature",
  "properties": {
    "addr:full":"244 Davis Dr Pascoag RI 02859",
    "addr:housenumber":"244",
    "addr:postcode":"02859",
    "addr:street":"Davis Dr Pascoag",
    "iso:country":"US",
    "sg:address":"244 Davis Dr",
    "sg:city":"Pascoag",
    "sg:classifiers":[
        {
            "category":"Recreation",
            "type":"Entertainment"
        }
    ],
    "sg:phone":"+1 401 710 9602",
    "sg:postcode":"02859",
    "sg:province":"RI",
    "sg:tags":[
        "instruction",
        "gymnastic"
    ],
    "wof:name":"Sports Kids Gymnastics",
    "wof:placetype":"venue"
},
  "geometry": {"coordinates":[-71.68264600000001,41.936979],"type":"Point"}
}