{
  "type": "Feature",
  "properties": {
    "iso:country":"US",
    "sg:address":"1076 Aquidneck Ave",
    "sg:city":"Middletown",
    "sg:classifiers":[
        {
            "category":"Farming",
            "subcategory":"Fish & Marine Products",
            "type":"Manufacturing & Wholesale Goods"
        }
    ],
    "sg:phone":"+1 401 846 8872",
    "sg:postcode":"02842",
    "sg:province":"RI",
    "sg:tags":[
        "shellfish",
        "fishing"
    ],
    "wof:name":"Newport Lobster Co",
    "wof:placetype":"venue"
},
  "geometry": {"coordinates":[-71.283157,41.517717],"type":"Point"}
}