{
  "type": "Feature",
  "properties": {
    "iso:country":"US",
    "sg:address":"225 Chapman St",
    "sg:city":"Providence",
    "sg:classifiers":[
        {
            "category":"Health Services",
            "subcategory":"Doctor",
            "type":"Services"
        }
    ],
    "sg:phone":"+1 401 941 6357",
    "sg:postcode":"02905",
    "sg:province":"RI",
    "sg:tags":[
        "physician",
        "surgeon"
    ],
    "wof:name":"University Orthopedics",
    "wof:placetype":"venue"
},
  "geometry": {"coordinates":[-71.402613,41.792368],"type":"Point"}
}