{
  "type": "Feature",
  "properties": {
    "iso:country":"US",
    "sg:address":"192 Pilgrim Ave",
    "sg:city":"Coventry",
    "sg:classifiers":[
        {
            "category":"Shopping",
            "subcategory":"Music",
            "type":"Retail Goods"
        },
        {
            "category":"Cinema",
            "subcategory":"Movie Rental",
            "type":"Entertainment"
        }
    ],
    "sg:phone":"+1 401 821 7390",
    "sg:postcode":"02816",
    "sg:province":"RI",
    "sg:tags":[
        "leasing",
        "video",
        "disc",
        "tape"
    ],
    "wof:name":"Uptown Music and Video",
    "wof:placetype":"venue"
},
  "geometry": {"coordinates":[-71.546986,41.686087],"type":"Point"}
}