{
  "type": "Feature",
  "properties": {
    "iso:country":"US",
    "sg:address":"200 Briarbrook Dr",
    "sg:city":"North Kingstown",
    "sg:classifiers":[
        {
            "category":"Building & Trades",
            "subcategory":"Construction",
            "type":"Services"
        }
    ],
    "sg:phone":"+1 401 884 8778",
    "sg:postcode":"02852",
    "sg:province":"RI",
    "sg:tags":[
        "concrete",
        "contractor"
    ],
    "wof:name":"D & M Concrete Forms Inc",
    "wof:placetype":"venue"
},
  "geometry": {"coordinates":[-71.445228,41.62779],"type":"Point"}
}