{
  "type": "Feature",
  "properties": {
    "iso:country":"US",
    "sg:address":"63 Tom Harvey Rd",
    "sg:city":"Westerly",
    "sg:classifiers":[
        {
            "category":"Building & Trades",
            "subcategory":"Construction",
            "type":"Services"
        }
    ],
    "sg:phone":"+1 401 596 6699",
    "sg:postcode":"02891",
    "sg:province":"RI",
    "sg:tags":[
        "general",
        "contractor"
    ],
    "wof:name":"STJ Construction Co LLC",
    "wof:placetype":"venue"
},
  "geometry": {"coordinates":[-71.815583,41.343524],"type":"Point"}
}