{
  "type": "Feature",
  "properties": {
    "addr:full":"58 High St Wakefield RI 02879",
    "addr:housenumber":"58",
    "addr:postcode":"02879",
    "addr:street":"High St",
    "iso:country":"US",
    "sg:address":"58 High St",
    "sg:city":"Wakefield",
    "sg:classifiers":[
        {
            "category":"Restaurant",
            "type":"Food & Drink"
        }
    ],
    "sg:phone":"+1 401 783 3292",
    "sg:postcode":"02879",
    "sg:province":"RI",
    "wof:name":"Quick Rick's",
    "wof:placetype":"venue"
},
  "geometry": {"coordinates":[-71.502132,41.437687],"type":"Point"}
}