{
  "type": "Feature",
  "properties": {
    "iso:country":"US",
    "sg:address":"1185 N Main Rd",
    "sg:city":"Jamestown",
    "sg:classifiers":[
        {
            "category":"Professional",
            "type":"Services"
        }
    ],
    "sg:phone":"+1 401 423 1373",
    "sg:postcode":"02835",
    "sg:province":"RI",
    "sg:tags":[
        "establishment"
    ],
    "wof:name":"Thoughtforms Corp",
    "wof:placetype":"venue"
},
  "geometry": {"coordinates":[-71.375129,41.561021],"type":"Point"}
}