{
  "type": "Feature",
  "properties": {
    "iso:country":"US",
    "sg:address":"288 Thayer St",
    "sg:city":"Providence",
    "sg:classifiers":[
        {
            "category":"Restaurant",
            "type":"Food & Drink"
        }
    ],
    "sg:menulink":"http://www.allmenus.com/ri/providence/236093-ronzio-pizza/menu/",
    "sg:phone":"+1 401 751 4990",
    "sg:postcode":"02906",
    "sg:province":"RI",
    "sg:tags":[
        "sandwich",
        "pizza"
    ],
    "wof:name":"Ronzio Pizza & Subs",
    "wof:placetype":"venue"
},
  "geometry": {"coordinates":[-71.401036,41.82984],"type":"Point"}
}