{
  "type": "Feature",
  "properties": {
    "addr:full":"234 Wickenden St Providence RI 02903",
    "addr:housenumber":"234",
    "addr:postcode":"02903",
    "addr:street":"Wickenden St",
    "iso:country":"US",
    "sg:address":"234 Wickenden St",
    "sg:city":"Providence",
    "sg:classifiers":[
        {
            "category":"Restaurant",
            "type":"Food & Drink"
        }
    ],
    "sg:phone":"+1 401 751 2477",
    "sg:postcode":"02903",
    "sg:province":"RI",
    "sg:tags":[
        "breakfast",
        "brunch"
    ],
    "wof:name":"Brickway On Wickenden",
    "wof:placetype":"venue"
},
  "geometry": {"coordinates":[-71.398697,41.819302],"type":"Point"}
}