{
  "type": "Feature",
  "properties": {
    "iso:country":"US",
    "sg:address":"5601 Post Rd",
    "sg:city":"East Greenwich",
    "sg:classifiers":[
        {
            "category":"Restaurant",
            "type":"Food & Drink"
        }
    ],
    "sg:menulink":"http://www.allmenus.com/ri/east-greenwich/236097-ronzio-pizza/menu/",
    "sg:phone":"+1 401 541 7200",
    "sg:postcode":"02818",
    "sg:province":"RI",
    "sg:tags":[
        "sandwich",
        "pizza"
    ],
    "wof:name":"Ronzio Pizza & Subs",
    "wof:placetype":"venue"
},
  "geometry": {"coordinates":[-71.466684,41.642843],"type":"Point"}
}