{
  "type": "Feature",
  "properties": {
    "iso:country":"US",
    "sg:address":"15 Cheryl Ave",
    "sg:city":"Portsmouth",
    "sg:classifiers":[
        {
            "category":"Arts & Performance",
            "subcategory":"Theater",
            "type":"Entertainment"
        }
    ],
    "sg:phone":"+1 401 849 1290",
    "sg:postcode":"02871",
    "sg:province":"RI",
    "sg:tags":[
        "band",
        "musician",
        "orchestra",
        "group"
    ],
    "sg:website":"www.newportlivemusic.com",
    "wof:name":"Mac Chrupcala Orchestras",
    "wof:placetype":"venue"
},
  "geometry": {"coordinates":[-71.249663,41.537451],"type":"Point"}
}