{
  "type": "Feature",
  "properties": {
    "iso:country":"US",
    "sg:address":"830 Waterman Ave",
    "sg:city":"East Providence",
    "sg:classifiers":[
        {
            "category":"Manufacturing",
            "subcategory":"Metals",
            "type":"Manufacturing & Wholesale Goods"
        }
    ],
    "sg:phone":"+1 401 438 7092",
    "sg:postcode":"02914",
    "sg:province":"RI",
    "sg:tags":[
        "product",
        "primary"
    ],
    "wof:name":"Gardener Specialty Metals",
    "wof:placetype":"venue"
},
  "geometry": {"coordinates":[-71.352222,41.81417],"type":"Point"}
}