{
  "type": "Feature",
  "properties": {
    "addr:full":"50 Holden St Providence RI 02908",
    "addr:housenumber":"50",
    "addr:postcode":"02908",
    "addr:street":"Holden St",
    "iso:country":"US",
    "sg:address":"50 Holden St",
    "sg:city":"Providence",
    "sg:classifiers":[
        {
            "category":"Professional",
            "subcategory":"Engineering",
            "type":"Services"
        }
    ],
    "sg:phone":"+1 401 861 5990",
    "sg:postcode":"02908",
    "sg:province":"RI",
    "sg:tags":[
        "engineer"
    ],
    "wof:name":"Tutela Engineering Associates",
    "wof:placetype":"venue"
},
  "geometry": {"coordinates":[-71.418498,41.831596],"type":"Point"}
}