{
  "type": "Feature",
  "properties": {
    "iso:country":"US",
    "sg:address":"215 W Park St",
    "sg:city":"Providence",
    "sg:classifiers":[
        {
            "category":"Wholesale",
            "subcategory":"Durable Goods & Equipment",
            "type":"Manufacturing & Wholesale Goods"
        },
        {
            "category":"Wholesale",
            "subcategory":"Jewelry",
            "type":"Manufacturing & Wholesale Goods"
        }
    ],
    "sg:phone":"+1 401 331 4010",
    "sg:postcode":"02908",
    "sg:province":"RI",
    "sg:tags":[
        "stone",
        "representative",
        "manufacturer"
    ],
    "wof:name":"Elms Industries Inc",
    "wof:placetype":"venue"
},
  "geometry": {"coordinates":[-71.427182,41.831683],"type":"Point"}
}