{
  "type": "Feature",
  "properties": {
    "iso:country":"US",
    "sg:address":"1697 Main Rd",
    "sg:city":"Tiverton",
    "sg:classifiers":[
        {
            "category":"Autos & Motor Vehicles",
            "subcategory":"Boat Sales",
            "type":"Retail Goods"
        }
    ],
    "sg:phone":"+1 401 624 4075",
    "sg:postcode":"02878",
    "sg:province":"RI",
    "sg:tags":[
        "outboard",
        "yard",
        "marine",
        "supply"
    ],
    "wof:name":"Standish Boat Yard Inc",
    "wof:placetype":"venue"
},
  "geometry": {"coordinates":[-71.211236,41.629436],"type":"Point"}
}