{
  "type": "Feature",
  "properties": {
    "iso:country":"US",
    "sg:address":"63 Gordon Ave",
    "sg:city":"Warwick",
    "sg:classifiers":[
        {
            "category":"Professional",
            "subcategory":"Secretarial Services",
            "type":"Services"
        }
    ],
    "sg:phone":"+1 401 921 2346",
    "sg:postcode":"02889",
    "sg:province":"RI",
    "sg:tags":[
        "resume"
    ],
    "wof:name":"Foodservice Resumes",
    "wof:placetype":"venue"
},
  "geometry": {"coordinates":[-71.401624,41.698699],"type":"Point"}
}