{
  "type": "Feature",
  "properties": {
    "iso:country":"US",
    "sg:address":"2 Evarts St",
    "sg:city":"Newport",
    "sg:classifiers":[
        {
            "category":"Building & Trades",
            "subcategory":"Construction",
            "type":"Services"
        }
    ],
    "sg:phone":"+1 401 847 0117",
    "sg:postcode":"02840",
    "sg:province":"RI",
    "sg:tags":[
        "general"
    ],
    "wof:name":"C W Enterprise Inc",
    "wof:placetype":"venue"
},
  "geometry": {"coordinates":[-71.315406,41.500009],"type":"Point"}
}