{
  "type": "Feature",
  "properties": {
    "addr:full":"79 Pilsudski St Providence RI 02909",
    "addr:housenumber":"79",
    "addr:postcode":"02909",
    "addr:street":"Pilsudski St",
    "iso:country":"US",
    "sg:address":"79 Pilsudski St",
    "sg:city":"Providence",
    "sg:classifiers":[
        {
            "category":"Freight",
            "type":"Transportation"
        }
    ],
    "sg:phone":"+1 401 946 3900",
    "sg:postcode":"02909",
    "sg:province":"RI",
    "sg:tags":[
        "trucking"
    ],
    "wof:name":"H & H Trucking Inc",
    "wof:placetype":"venue"
},
  "geometry": {"coordinates":[-71.442071,41.813427],"type":"Point"}
}