{
  "type": "Feature",
  "properties": {
    "addr:full":"44 Kings Grant Rd Saunderstown RI 02874",
    "addr:housenumber":"44",
    "addr:postcode":"02874",
    "addr:street":"Kings Grant Rd",
    "iso:country":"US",
    "sg:address":"44 Kings Grant Rd",
    "sg:city":"Saunderstown",
    "sg:classifiers":[
        {
            "category":"Professional",
            "type":"Services"
        }
    ],
    "sg:phone":"+1 401 294 9657",
    "sg:postcode":"02874",
    "sg:province":"RI",
    "sg:tags":[
        "establishment"
    ],
    "wof:name":"Toloudis Constantin",
    "wof:placetype":"venue"
},
  "geometry": {"coordinates":[-71.427386,41.52064],"type":"Point"}
}