{
  "type": "Feature",
  "properties": {
    "iso:country":"US",
    "sg:address":"427 Park Ave",
    "sg:city":"Woonsocket",
    "sg:classifiers":[
        {
            "category":"Personal",
            "subcategory":"Beauty Salon",
            "type":"Services"
        }
    ],
    "sg:phone":"+1 401 767 5944",
    "sg:postcode":"02895",
    "sg:province":"RI",
    "sg:tags":[
        "shop"
    ],
    "wof:name":"Personally Yours Salon",
    "wof:placetype":"venue"
},
  "geometry": {"coordinates":[-71.51161500000001,41.997067],"type":"Point"}
}