{
  "type": "Feature",
  "properties": {
    "iso:country":"US",
    "sg:address":"53 Waite St",
    "sg:city":"Providence",
    "sg:classifiers":[
        {
            "category":"Personal",
            "subcategory":"Beauty Salon",
            "type":"Services"
        }
    ],
    "sg:phone":"+1 401 942 4630",
    "sg:postcode":"02908",
    "sg:province":"RI",
    "sg:tags":[
        "shop"
    ],
    "wof:name":"Nail Biz",
    "wof:placetype":"venue"
},
  "geometry": {"coordinates":[-71.442207,41.850452],"type":"Point"}
}