{
  "type": "Feature",
  "properties": {
    "addr:full":"95 Peleg Rd Portsmouth RI 02871",
    "addr:housenumber":"95",
    "addr:postcode":"02871",
    "addr:street":"Peleg Rd",
    "iso:country":"US",
    "sg:address":"95 Peleg Rd",
    "sg:city":"Portsmouth",
    "sg:classifiers":[
        {
            "category":"Manufacturing",
            "subcategory":"Printing",
            "type":"Manufacturing & Wholesale Goods"
        }
    ],
    "sg:phone":"+1 401 683 1955",
    "sg:postcode":"02871",
    "sg:province":"RI",
    "sg:tags":[
        "newspaper"
    ],
    "wof:name":"Journal Roman Archaeology LLC",
    "wof:placetype":"venue"
},
  "geometry": {"coordinates":[-71.247552,41.583659],"type":"Point"}
}