{
  "type": "Feature",
  "properties": {
    "addr:full":"94 Kane Ave Middletown RI 02842",
    "addr:housenumber":"94",
    "addr:postcode":"02842",
    "addr:street":"Kane Ave",
    "iso:country":"US",
    "sg:address":"94 Kane Ave",
    "sg:city":"Middletown",
    "sg:classifiers":[
        {
            "category":"Travel",
            "subcategory":"Hotels & Motels",
            "type":"Entertainment"
        }
    ],
    "sg:phone":"+1 401 846 2259",
    "sg:postcode":"02842",
    "sg:province":"RI",
    "sg:tags":[
        "breakfast",
        "accommodation",
        "bed"
    ],
    "wof:name":"Bartram's B & B",
    "wof:placetype":"venue"
},
  "geometry": {"coordinates":[-71.27406999999999,41.48539],"type":"Point"}
}