{
  "type": "Feature",
  "properties": {
    "addr:full":"89 Franklin St Westerly RI 02891",
    "addr:housenumber":"89",
    "addr:postcode":"02891",
    "addr:street":"Franklin St",
    "iso:country":"US",
    "sg:address":"89 Franklin St",
    "sg:city":"Westerly",
    "sg:classifiers":[
        {
            "category":"Retail",
            "subcategory":"Auto Repair",
            "type":"Services"
        }
    ],
    "sg:phone":"+1 401 596 3620",
    "sg:postcode":"02891",
    "sg:province":"RI",
    "sg:tags":[
        "automotive"
    ],
    "wof:name":"Expressway",
    "wof:placetype":"venue"
},
  "geometry": {"coordinates":[-71.814325,41.362848],"type":"Point"}
}