{
  "type": "Feature",
  "properties": {
    "iso:country":"US",
    "sg:address":"15 Beechwood Ct",
    "sg:city":"Warren",
    "sg:classifiers":[
        {
            "category":"Building & Trades",
            "subcategory":"Construction",
            "type":"Services"
        }
    ],
    "sg:phone":"+1 401 245 2606",
    "sg:postcode":"02885",
    "sg:province":"RI",
    "sg:tags":[
        "house"
    ],
    "wof:name":"JMJ Constuction Company Inc",
    "wof:placetype":"venue"
},
  "geometry": {"coordinates":[-71.275786,41.716464],"type":"Point"}
}