{
  "type": "Feature",
  "properties": {
    "iso:country":"US",
    "sg:address":"11 Bowens Wharf",
    "sg:city":"Newport",
    "sg:classifiers":[
        {
            "category":"Restaurant",
            "type":"Food & Drink"
        }
    ],
    "sg:menulink":"http://www.allmenus.com/ri/newport/285900-diegos/menu/",
    "sg:phone":"+1 401 619 2640",
    "sg:postcode":"02840",
    "sg:province":"RI",
    "sg:tags":[
        "mexican"
    ],
    "wof:name":"Diego's",
    "wof:placetype":"venue"
},
  "geometry": {"coordinates":[-71.31565399999999,41.48714],"type":"Point"}
}