{
  "type": "Feature",
  "properties": {
    "addr:full":"25 Starline Way Cranston RI 02921",
    "addr:housenumber":"25",
    "addr:postcode":"02921",
    "addr:street":"Starline Way",
    "iso:country":"US",
    "sg:address":"25 Starline Way",
    "sg:city":"Cranston",
    "sg:classifiers":[
        {
            "category":"Manufacturing",
            "subcategory":"Jewelry",
            "type":"Manufacturing & Wholesale Goods"
        }
    ],
    "sg:phone":"+1 401 421 3377",
    "sg:postcode":"02921",
    "sg:province":"RI",
    "sg:website":"www.cmdesignsinc.com",
    "wof:name":"C & M Designs Inc",
    "wof:placetype":"venue"
},
  "geometry": {"coordinates":[-71.527055,41.78824],"type":"Point"}
}