{
  "type": "Feature",
  "properties": {
    "iso:country":"US",
    "sg:address":"39 Circuit Dr",
    "sg:city":"Narragansett",
    "sg:classifiers":[
        {
            "category":"Building & Trades",
            "subcategory":"Construction",
            "type":"Services"
        }
    ],
    "sg:phone":"+1 401 789 7365",
    "sg:postcode":"02882",
    "sg:province":"RI",
    "sg:tags":[
        "dry wall",
        "contractor"
    ],
    "wof:name":"Michael Kavanagh Construction",
    "wof:placetype":"venue"
},
  "geometry": {"coordinates":[-71.44489299999999,41.480568],"type":"Point"}
}