{
  "type": "Feature",
  "properties": {
    "iso:country":"US",
    "sg:address":"65 High St",
    "sg:city":"Westerly",
    "sg:classifiers":[
        {
            "category":"Restaurant",
            "type":"Food & Drink"
        }
    ],
    "sg:menulink":"http://www.allmenus.com/ri/westerly/244801-billias-mediterranean-grille/menu/",
    "sg:phone":"+1 401 596 2211",
    "sg:postcode":"02891",
    "sg:province":"RI",
    "sg:tags":[
        "greek"
    ],
    "wof:name":"Billias Mediterranean Grille",
    "wof:placetype":"venue"
},
  "geometry": {"coordinates":[-71.82660799999999,41.380466],"type":"Point"}
}