{
  "type": "Feature",
  "properties": {
    "iso:country":"US",
    "sg:address":"617 Smith St",
    "sg:city":"Providence",
    "sg:classifiers":[
        {
            "category":"Banks & Credit Unions",
            "subcategory":"Bank",
            "type":"Services"
        }
    ],
    "sg:phone":"+1 401 331 2300",
    "sg:postcode":"02908",
    "sg:province":"RI",
    "sg:tags":[
        "mortgage",
        "loan",
        "broker",
        "real estate"
    ],
    "wof:name":"Marpro",
    "wof:placetype":"venue"
},
  "geometry": {"coordinates":[-71.43150300000001,41.836601],"type":"Point"}
}