{
  "type": "Feature",
  "properties": {
    "addr:full":"6725 Post Rd North Kingstown RI 02852",
    "addr:housenumber":"6725",
    "addr:postcode":"02852",
    "addr:street":"Post Rd",
    "iso:country":"US",
    "sg:address":"6725 Post Rd",
    "sg:city":"North Kingstown",
    "sg:classifiers":[
        {
            "category":"Wholesale",
            "subcategory":"Medical Equipment & Supplies",
            "type":"Manufacturing & Wholesale Goods"
        }
    ],
    "sg:phone":"+1 401 886 4830",
    "sg:postcode":"02852",
    "sg:province":"RI",
    "sg:tags":[
        "x",
        "apparatus"
    ],
    "wof:name":"X Ray Assoc Inc",
    "wof:placetype":"venue"
},
  "geometry": {"coordinates":[-71.457931,41.615514],"type":"Point"}
}