{
  "type": "Feature",
  "properties": {
    "iso:country":"US",
    "sg:address":"250 Rand St Ofc",
    "sg:city":"Central Falls",
    "sg:classifiers":[
        {
            "category":"Real Estate",
            "subcategory":"Real Estate Operator",
            "type":"Services"
        }
    ],
    "sg:phone":"+1 401 724 2815",
    "sg:postcode":"02863",
    "sg:province":"RI",
    "sg:tags":[
        "apartment"
    ],
    "wof:name":"Rand Place Apts",
    "wof:placetype":"venue"
},
  "geometry": {"coordinates":[-71.39569899999999,41.889],"type":"Point"}
}