{
  "type": "Feature",
  "properties": {
    "iso:country":"US",
    "sg:address":"885 S Main St",
    "sg:city":"Pascoag",
    "sg:classifiers":[
        {
            "category":"Manufacturing",
            "subcategory":"Printing",
            "type":"Manufacturing & Wholesale Goods"
        }
    ],
    "sg:phone":"+1 401 568 1110",
    "sg:postcode":"02859",
    "sg:province":"RI",
    "sg:tags":[
        "label"
    ],
    "sg:website":"www.gslabels.com",
    "wof:name":"G S Inc",
    "wof:placetype":"venue"
},
  "geometry": {"coordinates":[-71.68311,41.939304],"type":"Point"}
}