{
  "type": "Feature",
  "properties": {
    "iso:country":"US",
    "sg:address":"285 Bullocks Point Ave",
    "sg:city":"Riverside",
    "sg:classifiers":[
        {
            "category":"Shopping",
            "subcategory":"Bicycles & Sporting Goods",
            "type":"Retail Goods"
        }
    ],
    "sg:phone":"+1 401 437 2630",
    "sg:postcode":"02915",
    "sg:province":"RI",
    "sg:tags":[
        "bait",
        "fishing"
    ],
    "wof:name":"Archies Bait & Tackle",
    "wof:placetype":"venue"
},
  "geometry": {"coordinates":[-71.361519,41.770569],"type":"Point"}
}