{
  "type": "Feature",
  "properties": {
    "iso:country":"US",
    "sg:address":"7 Randall Ave",
    "sg:city":"Johnston",
    "sg:classifiers":[
        {
            "category":"Building & Trades",
            "subcategory":"Construction",
            "type":"Services"
        }
    ],
    "sg:phone":"+1 401 942 5055",
    "sg:postcode":"02919",
    "sg:province":"RI",
    "sg:tags":[
        "house"
    ],
    "wof:name":"D Delfino Gen Contr",
    "wof:placetype":"venue"
},
  "geometry": {"coordinates":[-71.5055,41.798839],"type":"Point"}
}