{
  "type": "Feature",
  "properties": {
    "addr:full":"115 Cedar St Providence RI 02903",
    "addr:housenumber":"115",
    "addr:postcode":"02903",
    "addr:street":"Cedar St",
    "iso:country":"US",
    "sg:address":"115 Cedar St",
    "sg:city":"Providence",
    "sg:classifiers":[
        {
            "category":"Professional",
            "subcategory":"Lawyer & Legal Services",
            "type":"Services"
        }
    ],
    "sg:phone":"+1 401 521 5040",
    "sg:postcode":"02903",
    "sg:province":"RI",
    "wof:name":"Legal Information & Referral Services Fr Snr Ctzns",
    "wof:placetype":"venue"
},
  "geometry": {"coordinates":[-71.424301,41.824799],"type":"Point"}
}