{
  "type": "Feature",
  "properties": {
    "iso:country":"US",
    "sg:address":"583 Central Ave",
    "sg:city":"Pawtucket",
    "sg:classifiers":[
        {
            "category":"Personal",
            "subcategory":"Beauty Salon",
            "type":"Services"
        }
    ],
    "sg:phone":"+1 401 722 3335",
    "sg:postcode":"02861",
    "sg:province":"RI",
    "sg:tags":[
        "shop"
    ],
    "wof:name":"Carla & Co",
    "wof:placetype":"venue"
},
  "geometry": {"coordinates":[-71.36022199999999,41.886388],"type":"Point"}
}