{
  "type": "Feature",
  "properties": {
    "addr:full":"55 Lambert Lind Hwy Warwick RI 02886",
    "addr:housenumber":"55",
    "addr:postcode":"02886",
    "addr:street":"Lambert Lind Hwy",
    "iso:country":"US",
    "sg:address":"55 Lambert Lind Hwy",
    "sg:city":"Warwick",
    "sg:classifiers":[
        {
            "category":"Shopping",
            "subcategory":"Shoes",
            "type":"Retail Goods"
        }
    ],
    "sg:phone":"+1 401 737 3613",
    "sg:postcode":"02886",
    "sg:province":"RI",
    "wof:name":"Krystal Men",
    "wof:placetype":"venue"
},
  "geometry": {"coordinates":[-71.476907,41.729172],"type":"Point"}
}