{
  "type": "Feature",
  "properties": {
    "iso:country":"US",
    "sg:address":"434 Bellevue Ave",
    "sg:city":"Newport",
    "sg:classifiers":[
        {
            "category":"Professional",
            "type":"Services"
        }
    ],
    "sg:phone":"+1 401 848 8445",
    "sg:postcode":"02840",
    "sg:province":"RI",
    "sg:tags":[
        "establishment"
    ],
    "wof:name":"Gallagher & Gallagher",
    "wof:placetype":"venue"
},
  "geometry": {"coordinates":[-71.30770099999999,41.475074],"type":"Point"}
}