{
  "type": "Feature",
  "properties": {
    "iso:country":"US",
    "sg:address":"292 Elmwood Ave",
    "sg:city":"Providence",
    "sg:classifiers":[
        {
            "category":"Social Services",
            "subcategory":"Adult Care",
            "type":"Services"
        }
    ],
    "sg:phone":"+1 401 831 5993",
    "sg:postcode":"02907",
    "sg:province":"RI",
    "sg:tags":[
        "home",
        "residential"
    ],
    "wof:name":"Warren Manor II",
    "wof:placetype":"venue"
},
  "geometry": {"coordinates":[-71.42555900000001,41.804137],"type":"Point"}
}