{
  "type": "Feature",
  "properties": {
    "iso:country":"US",
    "sg:address":"845 North Main Street, Suite 8",
    "sg:city":"Providence",
    "sg:classifiers":[
        {
            "category":"Health Services",
            "subcategory":"Chiropractor",
            "type":"Services"
        }
    ],
    "sg:phone":"+1 401 351 8960",
    "sg:postcode":"02904",
    "sg:province":"RI",
    "sg:website":"www.naturalalternativesinc.com",
    "wof:name":"Natural Alternatives",
    "wof:placetype":"venue"
},
  "geometry": {"coordinates":[-71.406988,41.842902],"type":"Point"}
}