{
  "type": "Feature",
  "properties": {
    "addr:full":"157 Clifford St Providence RI 02903",
    "addr:housenumber":"157",
    "addr:postcode":"02903",
    "addr:street":"Clifford St",
    "iso:country":"US",
    "sg:address":"157 Clifford St",
    "sg:city":"Providence",
    "sg:classifiers":[
        {
            "category":"Manufacturing",
            "subcategory":"Jewelry",
            "type":"Manufacturing & Wholesale Goods"
        }
    ],
    "sg:phone":"+1 401 421 2978",
    "sg:postcode":"02903",
    "sg:province":"RI",
    "wof:name":"Clayton Co",
    "wof:placetype":"venue"
},
  "geometry": {"coordinates":[-71.41189300000001,41.818702],"type":"Point"}
}