{
  "type": "Feature",
  "properties": {
    "iso:country":"US",
    "sg:address":"319 Hope St",
    "sg:city":"Providence",
    "sg:classifiers":[
        {
            "category":"Banks & Credit Unions",
            "subcategory":"Investment Brokerage",
            "type":"Services"
        },
        {
            "category":"Real Estate",
            "subcategory":"Real Estate Operator",
            "type":"Services"
        }
    ],
    "sg:phone":"+1 401 751 6630",
    "sg:postcode":"02906",
    "sg:province":"RI",
    "sg:tags":[
        "building",
        "operation",
        "industrial",
        "commercial"
    ],
    "wof:name":"Baroque Investments Inc",
    "wof:placetype":"venue"
},
  "geometry": {"coordinates":[-71.40128199999999,41.833935],"type":"Point"}
}