{
  "type": "Feature",
  "properties": {
    "addr:full":"9 John St Barrington RI 02806",
    "addr:housenumber":"9",
    "addr:postcode":"02806",
    "addr:street":"John St",
    "iso:country":"US",
    "sg:address":"9 John St",
    "sg:city":"Barrington",
    "sg:classifiers":[
        {
            "category":"Freight",
            "type":"Transportation"
        }
    ],
    "sg:phone":"+1 401 437 0849",
    "sg:postcode":"02806",
    "sg:province":"RI",
    "sg:tags":[
        "operator",
        "trucking"
    ],
    "wof:name":"E & G Transport Inc",
    "wof:placetype":"venue"
},
  "geometry": {"coordinates":[-71.341943,41.757655],"type":"Point"}
}