{
  "type": "Feature",
  "properties": {
    "addr:full":"167 Point St Providence RI 02903",
    "addr:housenumber":"167",
    "addr:postcode":"02903",
    "addr:street":"Point St",
    "iso:country":"US",
    "sg:address":"167 Point St",
    "sg:city":"Providence",
    "sg:classifiers":[
        {
            "category":"Health Services",
            "subcategory":"Doctor",
            "type":"Services"
        }
    ],
    "sg:phone":"+1 800 927 1230",
    "sg:postcode":"02903",
    "sg:province":"RI",
    "sg:tags":[
        "orthopedist"
    ],
    "sg:website":"www.lifespanorthopedics.com",
    "wof:name":"Lifespan Orthopedics",
    "wof:placetype":"venue"
},
  "geometry": {"coordinates":[-71.410225,41.81599],"type":"Point"}
}