{
  "type": "Feature",
  "properties": {
    "iso:country":"US",
    "sg:address":"1559 Elmwood Ave",
    "sg:city":"Cranston",
    "sg:classifiers":[
        {
            "category":"Manufacturing",
            "subcategory":"Tools & Machinery",
            "type":"Manufacturing & Wholesale Goods"
        }
    ],
    "sg:phone":"+1 401 941 6230",
    "sg:postcode":"02910",
    "sg:province":"RI",
    "sg:tags":[
        "limb",
        "durable",
        "rent",
        "artificial",
        "mfg"
    ],
    "wof:name":"Artificial Limb Co",
    "wof:placetype":"venue"
},
  "geometry": {"coordinates":[-71.42523199999999,41.766262],"type":"Point"}
}