{
  "type": "Feature",
  "properties": {
    "addr:full":"36 Exchange Ter Providence RI 02903",
    "addr:housenumber":"36",
    "addr:postcode":"02903",
    "addr:street":"Exchange Ter",
    "iso:country":"US",
    "sg:address":"36 Exchange Ter",
    "sg:city":"Providence",
    "sg:classifiers":[
        {
            "category":"Professional",
            "subcategory":"Lawyer & Legal Services",
            "type":"Services"
        }
    ],
    "sg:phone":"+1 401 453 1500",
    "sg:postcode":"02903",
    "sg:province":"RI",
    "wof:name":"Eskey Michael T Atty",
    "wof:placetype":"venue"
},
  "geometry": {"coordinates":[-71.411598,41.826],"type":"Point"}
}