{
  "type": "Feature",
  "properties": {
    "addr:full":"825 Mineral Spring Ave Pawtucket RI 02860",
    "addr:housenumber":"825",
    "addr:postcode":"02860",
    "addr:street":"Mineral Spring Ave",
    "iso:country":"US",
    "sg:address":"825 Mineral Spring Ave",
    "sg:city":"Pawtucket",
    "sg:classifiers":[
        {
            "category":"Organizations",
            "subcategory":"Religious Organization",
            "type":"Services"
        }
    ],
    "sg:phone":"+1 401 724 9198",
    "sg:postcode":"02860",
    "sg:province":"RI",
    "sg:tags":[
        "church"
    ],
    "wof:name":"Jehovah's Witnesses",
    "wof:placetype":"venue"
},
  "geometry": {"coordinates":[-71.417592,41.870405],"type":"Point"}
}