{
  "type": "Feature",
  "properties": {
    "iso:country":"US",
    "sg:address":"4063 S County Trl",
    "sg:city":"Charlestown",
    "sg:classifiers":[
        {
            "category":"Retail",
            "subcategory":"Auto Repair",
            "type":"Services"
        }
    ],
    "sg:phone":"+1 401 364 7714",
    "sg:postcode":"02813",
    "sg:province":"RI",
    "sg:tags":[
        "body",
        "shop"
    ],
    "wof:name":"J R's Auto Body",
    "wof:placetype":"venue"
},
  "geometry": {"coordinates":[-71.62960099999999,41.443401],"type":"Point"}
}