{
  "type": "Feature",
  "properties": {
    "addr:full":"500 Anthony Rd Portsmouth RI 02871",
    "addr:housenumber":"500",
    "addr:postcode":"02871",
    "addr:street":"Anthony Rd",
    "iso:country":"US",
    "sg:address":"500 Anthony Rd",
    "sg:city":"Portsmouth",
    "sg:classifiers":[
        {
            "category":"Recreation",
            "type":"Entertainment"
        }
    ],
    "sg:phone":"+1 401 683 0955",
    "sg:postcode":"02871",
    "sg:province":"RI",
    "sg:tags":[
        "club",
        "country"
    ],
    "wof:name":"Montaup Country Club",
    "wof:placetype":"venue"
},
  "geometry": {"coordinates":[-71.24463,41.631419],"type":"Point"}
}