{
  "type": "Feature",
  "properties": {
    "iso:country":"US",
    "sg:address":"105 Pawtucket Ave",
    "sg:city":"Rumford",
    "sg:classifiers":[
        {
            "category":"Professional",
            "type":"Services"
        }
    ],
    "sg:phone":"+1 401 434 0898",
    "sg:postcode":"02916",
    "sg:province":"RI",
    "sg:tags":[
        "establishment"
    ],
    "wof:name":"Harborside Park II LLC",
    "wof:placetype":"venue"
},
  "geometry": {"coordinates":[-71.36234,41.855196],"type":"Point"}
}