{
  "type": "Feature",
  "properties": {
    "iso:country":"US",
    "sg:address":"3145 Diamond Hill Rd",
    "sg:city":"Cumberland",
    "sg:classifiers":[
        {
            "category":"Farming",
            "subcategory":"Vineyard",
            "type":"Manufacturing & Wholesale Goods"
        },
        {
            "category":"Manufacturing",
            "subcategory":"Food",
            "type":"Manufacturing & Wholesale Goods"
        }
    ],
    "sg:phone":"+1 401 333 2751",
    "sg:postcode":"02864",
    "sg:province":"RI",
    "sg:tags":[
        "shop",
        "winery"
    ],
    "sg:website":"www.favorlabel.com",
    "wof:name":"Diamond Hill Vineyards",
    "wof:placetype":"venue"
},
  "geometry": {"coordinates":[-71.40949500000001,41.97963],"type":"Point"}
}