{
  "type": "Feature",
  "properties": {
    "addr:full":"471 Broad St Cumberland RI 02864",
    "addr:housenumber":"471",
    "addr:postcode":"02864",
    "addr:street":"Broad St",
    "iso:country":"US",
    "sg:address":"471 Broad St",
    "sg:city":"Cumberland",
    "sg:classifiers":[
        {
            "category":"Professional",
            "subcategory":"Art Services",
            "type":"Services"
        }
    ],
    "sg:phone":"+1 401 475 5757",
    "sg:postcode":"02864",
    "sg:province":"RI",
    "sg:tags":[
        "graphic",
        "designer"
    ],
    "wof:name":"OCA Enterprises",
    "wof:placetype":"venue"
},
  "geometry": {"coordinates":[-71.39673000000001,41.912989],"type":"Point"}
}