{
  "type": "Feature",
  "properties": {
    "iso:country":"US",
    "sg:address":"44 Avon Ave",
    "sg:city":"Jamestown",
    "sg:classifiers":[
        {
            "category":"Building & Trades",
            "subcategory":"Construction",
            "type":"Services"
        }
    ],
    "sg:phone":"+1 401 423 1118",
    "sg:postcode":"02889",
    "sg:province":"RI",
    "sg:tags":[
        "repairing",
        "remodeling",
        "contractor"
    ],
    "wof:name":"Ironwood Renovations",
    "wof:placetype":"venue"
},
  "geometry": {"coordinates":[-71.365409,41.702948],"type":"Point"}
}