{
  "type": "Feature",
  "properties": {
    "addr:full":"149 Atlantic Ave Westerly RI 02891",
    "addr:housenumber":"149",
    "addr:postcode":"02891",
    "addr:street":"Atlantic Ave",
    "iso:country":"US",
    "sg:address":"149 Atlantic Ave",
    "sg:city":"Westerly",
    "sg:classifiers":[
        {
            "category":"Travel",
            "subcategory":"Hotels & Motels",
            "type":"Entertainment"
        }
    ],
    "sg:phone":"+1 401 596 5616",
    "sg:postcode":"02891",
    "sg:province":"RI",
    "sg:website":"www.sandyshore.com",
    "wof:name":"Sandy Shore Motel & Apts",
    "wof:placetype":"venue"
},
  "geometry": {"coordinates":[-71.811206,41.32177],"type":"Point"}
}