{
  "type": "Feature",
  "properties": {
    "iso:country":"US",
    "sg:address":"78 Pearl St",
    "sg:city":"Providence",
    "sg:classifiers":[
        {
            "category":"Travel",
            "subcategory":"Travel Agent",
            "type":"Entertainment"
        }
    ],
    "sg:phone":"+1 401 521 4545",
    "sg:postcode":"02905",
    "sg:province":"RI",
    "sg:tags":[
        "agency"
    ],
    "wof:name":"Providence Travel Inc",
    "wof:placetype":"venue"
},
  "geometry": {"coordinates":[-71.414669,41.81148],"type":"Point"}
}