{
  "type": "Feature",
  "properties": {
    "iso:country":"US",
    "sg:address":"70 Bath St",
    "sg:city":"Providence",
    "sg:classifiers":[
        {
            "category":"Restaurant",
            "type":"Food & Drink"
        }
    ],
    "sg:phone":"+1 401 273 0006",
    "sg:postcode":"02908",
    "sg:province":"RI",
    "sg:tags":[
        "caterer"
    ],
    "wof:name":"Lindley Food Svc",
    "wof:placetype":"venue"
},
  "geometry": {"coordinates":[-71.4251,41.832473],"type":"Point"}
}