{
  "type": "Feature",
  "properties": {
    "iso:country":"US",
    "sg:address":"135 Providence Pl",
    "sg:city":"Providence",
    "sg:classifiers":[
        {
            "category":"Government",
            "subcategory":"Office",
            "type":"Public Place"
        }
    ],
    "sg:phone":"+1 401 270 4430",
    "sg:postcode":"02903",
    "sg:province":"RI",
    "sg:tags":[
        "city"
    ],
    "wof:name":"Johnson Controls Inc",
    "wof:placetype":"venue"
},
  "geometry": {"coordinates":[-71.418823,41.8278],"type":"Point"}
}