{
  "type": "Feature",
  "properties": {
    "addr:full":"210 Furey Ave Tiverton RI 02878",
    "addr:housenumber":"210",
    "addr:postcode":"02878",
    "addr:street":"Furey Ave",
    "iso:country":"US",
    "sg:address":"210 Furey Ave",
    "sg:city":"Tiverton",
    "sg:classifiers":[
        {
            "category":"Building & Trades",
            "subcategory":"Construction",
            "type":"Services"
        }
    ],
    "sg:phone":"+1 401 624 9775",
    "sg:postcode":"02878",
    "sg:province":"RI",
    "sg:tags":[
        "house"
    ],
    "wof:name":"JC Services Inc",
    "wof:placetype":"venue"
},
  "geometry": {"coordinates":[-71.171657,41.615018],"type":"Point"}
}