{
  "type": "Feature",
  "properties": {
    "addr:full":"154 Lancaster St Providence RI 02906",
    "addr:housenumber":"154",
    "addr:postcode":"02906",
    "addr:street":"Lancaster St",
    "iso:country":"US",
    "sg:address":"154 Lancaster St",
    "sg:city":"Providence",
    "sg:classifiers":[
        {
            "category":"Professional",
            "subcategory":"Business Services",
            "type":"Services"
        }
    ],
    "sg:phone":"+1 401 439 8049",
    "sg:postcode":"02906",
    "sg:province":"RI",
    "wof:name":"Pillar To Post",
    "wof:placetype":"venue"
},
  "geometry": {"coordinates":[-71.399931,41.845835],"type":"Point"}
}