{
  "type": "Feature",
  "properties": {
    "iso:country":"US",
    "sg:address":"142 Boon St",
    "sg:city":"Narragansett",
    "sg:classifiers":[
        {
            "category":"Restaurant",
            "type":"Food & Drink"
        }
    ],
    "sg:phone":"+1 401 783 6420",
    "sg:postcode":"02882",
    "sg:province":"RI",
    "sg:tags":[
        "eating"
    ],
    "wof:name":"Dad's Place",
    "wof:placetype":"venue"
},
  "geometry": {"coordinates":[-71.459648,41.426338],"type":"Point"}
}