{
  "type": "Feature",
  "properties": {
    "iso:country":"US",
    "sg:address":"582 Hopkins Hill Rd",
    "sg:city":"West Greenwich",
    "sg:classifiers":[
        {
            "category":"Real Estate",
            "subcategory":"Architect",
            "type":"Services"
        }
    ],
    "sg:phone":"+1 401 392 0596",
    "sg:postcode":"02817",
    "sg:province":"RI",
    "wof:name":"Karl F Sauerbrey",
    "wof:placetype":"venue"
},
  "geometry": {"coordinates":[-71.564123,41.621636],"type":"Point"}
}