{
  "type": "Feature",
  "properties": {
    "iso:country":"US",
    "sg:address":"342 Broad St",
    "sg:city":"Providence",
    "sg:classifiers":[
        {
            "category":"Food & Beverages",
            "subcategory":"Liquor & Beverages",
            "type":"Retail Goods"
        }
    ],
    "sg:phone":"+1 401 621 8095",
    "sg:postcode":"02907",
    "sg:province":"RI",
    "sg:tags":[
        "beer",
        "wine",
        "spirit",
        "alcoholic"
    ],
    "wof:name":"Fruit Hill Liquor",
    "wof:placetype":"venue"
},
  "geometry": {"coordinates":[-71.42150100000001,41.814201],"type":"Point"}
}