{
  "type": "Feature",
  "properties": {
    "iso:country":"US",
    "sg:address":"579 Atwells Ave",
    "sg:city":"Providence",
    "sg:classifiers":[
        {
            "category":"Restaurant",
            "type":"Food & Drink"
        }
    ],
    "sg:phone":"+1 401 751 7827",
    "sg:postcode":"02909",
    "sg:province":"RI",
    "sg:website":"www.subway.com",
    "wof:name":"Subway Sandwiches & Salads",
    "wof:placetype":"venue"
},
  "geometry": {"coordinates":[-71.43646200000001,41.824547],"type":"Point"}
}