{
  "type": "Feature",
  "properties": {
    "iso:country":"US",
    "sg:address":"39 Maude Ave",
    "sg:city":"Coventry",
    "sg:classifiers":[
        {
            "category":"Banks & Credit Unions",
            "subcategory":"Bank",
            "type":"Services"
        }
    ],
    "sg:phone":"+1 401 615 9460",
    "sg:postcode":"02816",
    "sg:province":"RI",
    "sg:tags":[
        "loan",
        "real estate"
    ],
    "wof:name":"Lincoln Mortgage Corp",
    "wof:placetype":"venue"
},
  "geometry": {"coordinates":[-71.569704,41.673677],"type":"Point"}
}