{
  "type": "Feature",
  "properties": {
    "iso:country":"US",
    "sg:address":"417 Broad St",
    "sg:city":"Cumberland",
    "sg:classifiers":[
        {
            "category":"Restaurant",
            "type":"Food & Drink"
        }
    ],
    "sg:phone":"+1 401 475 9676",
    "sg:postcode":"02864",
    "sg:province":"RI",
    "wof:name":"Peppers Deli",
    "wof:placetype":"venue"
},
  "geometry": {"coordinates":[-71.395708,41.91156],"type":"Point"}
}