{
  "type": "Feature",
  "properties": {
    "iso:country":"US",
    "sg:address":"21 Gardner Ave",
    "sg:city":"North Providence",
    "sg:classifiers":[
        {
            "category":"Professional",
            "subcategory":"Management & Consulting",
            "type":"Services"
        }
    ],
    "sg:phone":"+1 401 353 3342",
    "sg:postcode":"02911",
    "sg:province":"RI",
    "sg:tags":[
        "business"
    ],
    "wof:name":"Intuition",
    "wof:placetype":"venue"
},
  "geometry": {"coordinates":[-71.461842,41.847468],"type":"Point"}
}