{
  "type": "Feature",
  "properties": {
    "iso:country":"US",
    "sg:address":"60 Metropolitan Dr",
    "sg:city":"Warwick",
    "sg:classifiers":[
        {
            "category":"Personal",
            "type":"Services"
        },
        {
            "category":"Building & Trades",
            "subcategory":"Construction",
            "type":"Services"
        }
    ],
    "sg:phone":"+1 401 738 1820",
    "sg:postcode":"02886",
    "sg:province":"RI",
    "sg:tags":[
        "washing",
        "house",
        "wallpaper",
        "contractor",
        "wallcoverings-installation",
        "painting"
    ],
    "wof:name":"Petitpas Painting",
    "wof:placetype":"venue"
},
  "geometry": {"coordinates":[-71.424408,41.69442],"type":"Point"}
}