{
  "type": "Feature",
  "properties": {
    "iso:country":"US",
    "sg:address":"82 Cleveland St",
    "sg:city":"Wakefield",
    "sg:classifiers":[
        {
            "category":"Building & Trades",
            "subcategory":"Landscaping Services",
            "type":"Services"
        }
    ],
    "sg:phone":"+1 401 789 2323",
    "sg:postcode":"02879",
    "sg:province":"RI",
    "sg:tags":[
        "landscape",
        "contractor"
    ],
    "wof:name":"Wakefield Landscape Co",
    "wof:placetype":"venue"
},
  "geometry": {"coordinates":[-71.493959,41.444567],"type":"Point"}
}