{
  "type": "Feature",
  "properties": {
    "addr:full":"57 Water St Warren RI 02885",
    "addr:housenumber":"57",
    "addr:postcode":"02885",
    "addr:street":"Water St",
    "iso:country":"US",
    "sg:address":"57 Water St",
    "sg:city":"Warren",
    "sg:classifiers":[
        {
            "category":"Restaurant",
            "type":"Food & Drink"
        }
    ],
    "sg:phone":"+1 401 245 9499",
    "sg:postcode":"02885",
    "sg:province":"RI",
    "sg:tags":[
        "eating"
    ],
    "wof:name":"Bing Sum Restaurant",
    "wof:placetype":"venue"
},
  "geometry": {"coordinates":[-71.28542400000001,41.734187],"type":"Point"}
}