{
  "type": "Feature",
  "properties": {
    "addr:full":"162 Main St Wakefield RI 02879",
    "addr:housenumber":"162",
    "addr:postcode":"02879",
    "addr:street":"Main St",
    "iso:country":"US",
    "sg:address":"162 Main St",
    "sg:city":"Wakefield",
    "sg:classifiers":[
        {
            "category":"Manufacturing",
            "subcategory":"Tools & Machinery",
            "type":"Manufacturing & Wholesale Goods"
        }
    ],
    "sg:phone":"+1 401 783 0063",
    "sg:postcode":"02879",
    "sg:province":"RI",
    "sg:tags":[
        "orthopedic",
        "appliance"
    ],
    "wof:name":"South County Artificial Limb",
    "wof:placetype":"venue"
},
  "geometry": {"coordinates":[-71.494084,41.440854],"type":"Point"}
}