{
  "type": "Feature",
  "properties": {
    "addr:full":"582 S Main St Woonsocket RI 02895",
    "addr:housenumber":"582",
    "addr:postcode":"02895",
    "addr:street":"S Main St",
    "iso:country":"US",
    "sg:address":"582 S Main St",
    "sg:city":"Woonsocket",
    "sg:classifiers":[
        {
            "category":"Personal",
            "subcategory":"Beauty Salon",
            "type":"Services"
        }
    ],
    "sg:phone":"+1 401 765 4087",
    "sg:postcode":"02895",
    "sg:province":"RI",
    "wof:name":"Tangles Hair Design",
    "wof:placetype":"venue"
},
  "geometry": {"coordinates":[-71.52957499999999,41.990755],"type":"Point"}
}