{
  "type": "Feature",
  "properties": {
    "addr:full":"70 Gibson Rd Bristol RI 02809",
    "addr:housenumber":"70",
    "addr:postcode":"02809",
    "addr:street":"Gibson Rd",
    "iso:country":"US",
    "sg:address":"70 Gibson Rd",
    "sg:city":"Bristol",
    "sg:classifiers":[
        {
            "category":"Professional",
            "subcategory":"Business Services",
            "type":"Services"
        }
    ],
    "sg:phone":"+1 401 253 8443",
    "sg:postcode":"02809",
    "sg:province":"RI",
    "wof:name":"Straight Answer Marine Service",
    "wof:placetype":"venue"
},
  "geometry": {"coordinates":[-71.28632500000001,41.696358],"type":"Point"}
}