{
  "type": "Feature",
  "properties": {
    "addr:full":"41 East Ave Westerly RI 02891",
    "addr:housenumber":"41",
    "addr:postcode":"02891",
    "addr:street":"East Ave",
    "iso:country":"US",
    "sg:address":"41 East Ave",
    "sg:city":"Westerly",
    "sg:classifiers":[
        {
            "category":"Health Services",
            "subcategory":"Doctor",
            "type":"Services"
        }
    ],
    "sg:phone":"+1 401 596 7736",
    "sg:postcode":"02891",
    "sg:province":"RI",
    "sg:tags":[
        "medical"
    ],
    "wof:name":"Tobias M Goodman MD",
    "wof:placetype":"venue"
},
  "geometry": {"coordinates":[-71.819706,41.363914],"type":"Point"}
}