{
  "type": "Feature",
  "properties": {
    "iso:country":"US",
    "sg:address":"2506 Pawtucket Ave",
    "sg:city":"East Providence",
    "sg:classifiers":[
        {
            "category":"Home & Garden",
            "subcategory":"Household Appliances",
            "type":"Retail Goods"
        }
    ],
    "sg:phone":"+1 401 434 3330",
    "sg:postcode":"02914",
    "sg:province":"RI",
    "wof:name":"Rinebolt Appliance Service",
    "wof:placetype":"venue"
},
  "geometry": {"coordinates":[-71.360103,41.807338],"type":"Point"}
}