{
  "type": "Feature",
  "properties": {
    "iso:country":"US",
    "sg:address":"145 Main St",
    "sg:city":"Warren",
    "sg:classifiers":[
        {
            "category":"Food & Beverages",
            "subcategory":"Liquor & Beverages",
            "type":"Retail Goods"
        }
    ],
    "sg:phone":"+1 401 245 1776",
    "sg:postcode":"02885",
    "sg:province":"RI",
    "wof:name":"1776 Liquors",
    "wof:placetype":"venue"
},
  "geometry": {"coordinates":[-71.285737,41.735794],"type":"Point"}
}