{
  "type": "Feature",
  "properties": {
    "iso:country":"US",
    "sg:address":"743 Indian Corner Rd",
    "sg:city":"Slocum",
    "sg:classifiers":[
        {
            "category":"Government",
            "subcategory":"Post Office",
            "type":"Public Place"
        }
    ],
    "sg:phone":"+1 401 000 1111",
    "sg:postcode":"02877",
    "sg:province":"RI",
    "wof:name":"US Post Office",
    "wof:placetype":"venue"
},
  "geometry": {"coordinates":[-71.50967199999999,41.531929],"type":"Point"}
}