{
  "type": "Feature",
  "properties": {
    "addr:full":"91 Friendship St Providence RI 02903",
    "addr:housenumber":"91",
    "addr:postcode":"02903",
    "addr:street":"Friendship St",
    "iso:country":"US",
    "sg:address":"91 Friendship St",
    "sg:city":"Providence",
    "sg:classifiers":[
        {
            "category":"Professional",
            "subcategory":"Lawyer & Legal Services",
            "type":"Services"
        }
    ],
    "sg:phone":"+1 401 455 9600",
    "sg:postcode":"02903",
    "sg:province":"RI",
    "wof:name":"Ciresi Mary June Atty",
    "wof:placetype":"venue"
},
  "geometry": {"coordinates":[-71.4105,41.8209],"type":"Point"}
}