{
  "type": "Feature",
  "properties": {
    "iso:country":"US",
    "sg:address":"3103 Post Rd",
    "sg:city":"Wakefield",
    "sg:classifiers":[
        {
            "category":"Professional",
            "subcategory":"Advertising",
            "type":"Services"
        }
    ],
    "sg:phone":"+1 401 789 8059",
    "sg:postcode":"02879",
    "sg:province":"RI",
    "sg:tags":[
        "mail",
        "direct"
    ],
    "wof:name":"Direct Solution",
    "wof:placetype":"venue"
},
  "geometry": {"coordinates":[-71.592395,41.395782],"type":"Point"}
}