{
  "type": "Feature",
  "properties": {
    "iso:country":"US",
    "sg:address":"71 Hill Ave",
    "sg:city":"North Scituate",
    "sg:classifiers":[
        {
            "category":"Professional",
            "subcategory":"Testing Lab",
            "type":"Services"
        }
    ],
    "sg:phone":"+1 401 934 2021",
    "sg:postcode":"02857",
    "sg:province":"RI",
    "sg:tags":[
        "tool",
        "hand"
    ],
    "sg:website":"www.precisioninstruments.com",
    "wof:name":"Precision Instruments Inc",
    "wof:placetype":"venue"
},
  "geometry": {"coordinates":[-71.57405900000001,41.829693],"type":"Point"}
}