{
  "type": "Feature",
  "properties": {
    "iso:country":"US",
    "sg:address":"1427 Hartford Ave",
    "sg:city":"Johnston",
    "sg:classifiers":[
        {
            "category":"Restaurant",
            "type":"Food & Drink"
        }
    ],
    "sg:menulink":"http://www.allmenus.com/ri/johnston/173061-wendys/menu/",
    "sg:phone":"+1 401 831 4590",
    "sg:postcode":"02919",
    "sg:province":"RI",
    "sg:tags":[
        "burger",
        "american",
        "soup"
    ],
    "wof:name":"Wendy's",
    "wof:placetype":"venue"
},
  "geometry": {"coordinates":[-71.50070599999999,41.824313],"type":"Point"}
}