{
  "type": "Feature",
  "properties": {
    "iso:country":"US",
    "sg:address":"349 Centerville Rd",
    "sg:city":"Warwick",
    "sg:classifiers":[
        {
            "category":"Professional",
            "type":"Services"
        }
    ],
    "sg:phone":"+1 401 739 9006",
    "sg:postcode":"02886",
    "sg:province":"RI",
    "sg:tags":[
        "establishment"
    ],
    "wof:name":"Community Living Of Rhode Is",
    "wof:placetype":"venue"
},
  "geometry": {"coordinates":[-71.47494399999999,41.697636],"type":"Point"}
}