{
  "type": "Feature",
  "properties": {
    "iso:country":"US",
    "sg:address":"615 Jefferson Blvd",
    "sg:city":"Warwick",
    "sg:classifiers":[
        {
            "category":"Health Services",
            "subcategory":"Doctor",
            "type":"Services"
        }
    ],
    "sg:phone":"+1 401 732 5566",
    "sg:postcode":"02886",
    "sg:province":"RI",
    "wof:name":"Varone Robt J Ltd",
    "wof:placetype":"venue"
},
  "geometry": {"coordinates":[-71.44213499999999,41.731484],"type":"Point"}
}