{
  "type": "Feature",
  "properties": {
    "addr:full":"337 Admiral St Providence RI 02908",
    "addr:housenumber":"337",
    "addr:postcode":"02908",
    "addr:street":"Admiral St",
    "iso:country":"US",
    "sg:address":"337 Admiral St",
    "sg:city":"Providence",
    "sg:classifiers":[
        {
            "category":"Retail",
            "subcategory":"Auto Repair",
            "type":"Services"
        }
    ],
    "sg:phone":"+1 401 454 8181",
    "sg:postcode":"02908",
    "sg:province":"RI",
    "wof:name":"Lucio's Auto Sales and Service",
    "wof:placetype":"venue"
},
  "geometry": {"coordinates":[-71.427696,41.8456],"type":"Point"}
}