{
  "type": "Feature",
  "properties": {
    "addr:full":"410 S Main St Providence RI 02903",
    "addr:housenumber":"410",
    "addr:postcode":"02903",
    "addr:street":"S Main St",
    "iso:country":"US",
    "sg:address":"410 S Main St",
    "sg:city":"Providence",
    "sg:classifiers":[
        {
            "category":"Professional",
            "subcategory":"Lawyer & Legal Services",
            "type":"Services"
        }
    ],
    "sg:phone":"+1 401 421 7800",
    "sg:postcode":"02903",
    "sg:province":"RI",
    "wof:name":"Rhode Island Laborers Legal Service Plans",
    "wof:placetype":"venue"
},
  "geometry": {"coordinates":[-71.403603,41.820702],"type":"Point"}
}