{
  "type": "Feature",
  "properties": {
    "iso:country":"US",
    "sg:address":"529 Broad St",
    "sg:city":"Providence",
    "sg:classifiers":[
        {
            "category":"Banks & Credit Unions",
            "subcategory":"Financial Services",
            "type":"Services"
        }
    ],
    "sg:phone":"+1 401 421 2200",
    "sg:postcode":"02907",
    "sg:province":"RI",
    "sg:tags":[
        "investor"
    ],
    "wof:name":"Baguti Investments LLC",
    "wof:placetype":"venue"
},
  "geometry": {"coordinates":[-71.421024,41.809577],"type":"Point"}
}