{
  "type": "Feature",
  "properties": {
    "iso:country":"US",
    "sg:address":"27 Mill St",
    "sg:city":"Johnston",
    "sg:classifiers":[
        {
            "category":"Shopping",
            "subcategory":"Luggage & Leather Goods",
            "type":"Retail Goods"
        }
    ],
    "sg:phone":"+1 401 464 4211",
    "sg:postcode":"02919",
    "sg:province":"RI",
    "wof:name":"All American Leather",
    "wof:placetype":"venue"
},
  "geometry": {"coordinates":[-71.485575,41.795623],"type":"Point"}
}