{
  "type": "Feature",
  "properties": {
    "iso:country":"US",
    "sg:address":"355 Main St",
    "sg:city":"Wakefield",
    "sg:classifiers":[
        {
            "category":"Manufacturing",
            "subcategory":"Pottery",
            "type":"Manufacturing & Wholesale Goods"
        }
    ],
    "sg:phone":"+1 401 284 1606",
    "sg:postcode":"02879",
    "sg:province":"RI",
    "sg:tags":[
        "dish",
        "retail"
    ],
    "wof:name":"Dishes of Distinction Inc",
    "wof:placetype":"venue"
},
  "geometry": {"coordinates":[-71.500259,41.437748],"type":"Point"}
}