{
  "type": "Feature",
  "properties": {
    "addr:full":"267 Barton St Pawtucket RI 02860",
    "addr:housenumber":"267",
    "addr:postcode":"02860",
    "addr:street":"Barton St",
    "iso:country":"US",
    "sg:address":"267 Barton St",
    "sg:city":"Pawtucket",
    "sg:classifiers":[
        {
            "category":"Food & Beverages",
            "subcategory":"Liquor & Beverages",
            "type":"Retail Goods"
        }
    ],
    "sg:phone":"+1 401 724 7220",
    "sg:postcode":"02860",
    "sg:province":"RI",
    "sg:tags":[
        "beer",
        "spirit",
        "store",
        "wine"
    ],
    "wof:name":"Dexter Warehouse Liquors Inc",
    "wof:placetype":"venue"
},
  "geometry": {"coordinates":[-71.3909,41.880299],"type":"Point"}
}