{
  "type": "Feature",
  "properties": {
    "addr:full":"101 Reservoir Ave Providence RI 02907",
    "addr:housenumber":"101",
    "addr:postcode":"02907",
    "addr:street":"Reservoir Ave",
    "iso:country":"US",
    "sg:address":"101 Reservoir Ave",
    "sg:city":"Providence",
    "sg:classifiers":[
        {
            "category":"Retail",
            "subcategory":"Laundry & Dry Cleaning",
            "type":"Services"
        }
    ],
    "sg:phone":"+1 401 781 9010",
    "sg:postcode":"02907",
    "sg:province":"RI",
    "sg:tags":[
        "drycleaning",
        "plant",
        "agent",
        "garment"
    ],
    "wof:name":"April Rainbow Cleansers",
    "wof:placetype":"venue"
},
  "geometry": {"coordinates":[-71.42662,41.794525],"type":"Point"}
}