{
  "type": "Feature",
  "properties": {
    "iso:country":"US",
    "sg:address":"182 Gano St",
    "sg:city":"Providence",
    "sg:classifiers":[
        {
            "category":"Professional",
            "subcategory":"Lawyer & Legal Services",
            "type":"Services"
        }
    ],
    "sg:phone":"+1 401 421 7000",
    "sg:postcode":"02906",
    "sg:province":"RI",
    "sg:tags":[
        "attorney"
    ],
    "wof:name":"Catherine E Graziano",
    "wof:placetype":"venue"
},
  "geometry": {"coordinates":[-71.390317,41.824702],"type":"Point"}
}