{
  "type": "Feature",
  "properties": {
    "iso:country":"US",
    "sg:address":"20 Weeks Hill Rd",
    "sg:city":"Greene",
    "sg:classifiers":[
        {
            "category":"Retail",
            "subcategory":"Auto Repair",
            "type":"Services"
        }
    ],
    "sg:phone":"+1 401 397 9022",
    "sg:postcode":"02827",
    "sg:province":"RI",
    "sg:tags":[
        "body",
        "automobile",
        "painting",
        "general"
    ],
    "wof:name":"Weeks Hill Auto Ltd",
    "wof:placetype":"venue"
},
  "geometry": {"coordinates":[-71.685396,41.692874],"type":"Point"}
}