{
  "type": "Feature",
  "properties": {
    "iso:country":"US",
    "sg:address":"19 Pier Market Pl",
    "sg:city":"Narragansett",
    "sg:classifiers":[
        {
            "category":"Retail",
            "subcategory":"Laundry & Dry Cleaning",
            "type":"Services"
        }
    ],
    "sg:phone":"+1 401 782 6499",
    "sg:postcode":"02882",
    "sg:province":"RI",
    "wof:name":"J & L Laundry",
    "wof:placetype":"venue"
},
  "geometry": {"coordinates":[-71.45834499999999,41.431501],"type":"Point"}
}