{
  "type": "Feature",
  "properties": {
    "iso:country":"US",
    "sg:address":"10 Mark Dr",
    "sg:city":"Cranston",
    "sg:classifiers":[
        {
            "category":"Manufacturing",
            "subcategory":"Tools & Machinery",
            "type":"Manufacturing & Wholesale Goods"
        }
    ],
    "sg:phone":"+1 401 941 4888",
    "sg:postcode":"02920",
    "sg:province":"RI",
    "sg:tags":[
        "model",
        "maker"
    ],
    "wof:name":"Anthony S Calabro",
    "wof:placetype":"venue"
},
  "geometry": {"coordinates":[-71.47545599999999,41.745308],"type":"Point"}
}