{
  "type": "Feature",
  "properties": {
    "addr:full":"36 Newport Ave Pawtucket RI 02861",
    "addr:housenumber":"36",
    "addr:postcode":"02861",
    "addr:street":"Newport Ave",
    "iso:country":"US",
    "sg:address":"36 Newport Ave",
    "sg:city":"Pawtucket",
    "sg:classifiers":[
        {
            "category":"Retail",
            "subcategory":"Auto Repair",
            "type":"Services"
        }
    ],
    "sg:phone":"+1 401 722 5257",
    "sg:postcode":"02861",
    "sg:province":"RI",
    "sg:tags":[
        "muffler",
        "shop",
        "installation",
        "sale"
    ],
    "wof:name":"Meineke Discount Mufflers",
    "wof:placetype":"venue"
},
  "geometry": {"coordinates":[-71.354415,41.85859],"type":"Point"}
}