{
  "type": "Feature",
  "properties": {
    "iso:country":"US",
    "sg:address":"778 Reservoir Ave",
    "sg:city":"Cranston",
    "sg:classifiers":[
        {
            "category":"Health Services",
            "subcategory":"Medical Lab",
            "type":"Services"
        }
    ],
    "sg:phone":"+1 401 943 7178",
    "sg:postcode":"02910",
    "sg:province":"RI",
    "sg:tags":[
        "laboratory"
    ],
    "wof:name":"Oral Research Lab",
    "wof:placetype":"venue"
},
  "geometry": {"coordinates":[-71.444659,41.778605],"type":"Point"}
}