{
  "type": "Feature",
  "properties": {
    "iso:country":"US",
    "sg:address":"59 S County Trl",
    "sg:city":"Wakefield",
    "sg:classifiers":[
        {
            "category":"Restaurant",
            "type":"Food & Drink"
        }
    ],
    "sg:phone":"+1 401 284 1311",
    "sg:postcode":"02822",
    "sg:province":"RI",
    "wof:name":"Shogun Steak & Seafood",
    "wof:placetype":"venue"
},
  "geometry": {"coordinates":[-71.519937,41.555703],"type":"Point"}
}