{
  "type": "Feature",
  "properties": {
    "addr:full":"15 Church St Warren RI 02885",
    "addr:housenumber":"15",
    "addr:postcode":"02885",
    "addr:street":"Church St",
    "iso:country":"US",
    "sg:address":"15 Church St",
    "sg:city":"Warren",
    "sg:classifiers":[
        {
            "category":"Retail",
            "subcategory":"Funeral Services",
            "type":"Services"
        }
    ],
    "sg:phone":"+1 401 245 4999",
    "sg:postcode":"02885",
    "sg:province":"RI",
    "sg:tags":[
        "director"
    ],
    "wof:name":"William J Smith & Sons Funeral",
    "wof:placetype":"venue"
},
  "geometry": {"coordinates":[-71.283294,41.730015],"type":"Point"}
}