{
  "type": "Feature",
  "properties": {
    "iso:country":"US",
    "sg:address":"47 Morgan Ave",
    "sg:city":"Johnston",
    "sg:classifiers":[
        {
            "category":"Professional",
            "subcategory":"Accounting & Tax Preparation",
            "type":"Services"
        }
    ],
    "sg:phone":"+1 401 943 2756",
    "sg:postcode":"02919",
    "sg:province":"RI",
    "wof:name":"David Criscuolo CPA",
    "wof:placetype":"venue"
},
  "geometry": {"coordinates":[-71.47208500000001,41.80174],"type":"Point"}
}