{
  "type": "Feature",
  "properties": {
    "iso:country":"US",
    "sg:address":"172 Broadway",
    "sg:city":"Providence",
    "sg:classifiers":[
        {
            "category":"Health Services",
            "subcategory":"Chiropractor",
            "type":"Services"
        }
    ],
    "sg:phone":"+1 401 521 2225",
    "sg:postcode":"02903",
    "sg:province":"RI",
    "wof:name":"Anania Chiropractic",
    "wof:placetype":"venue"
},
  "geometry": {"coordinates":[-71.42289700000001,41.8214],"type":"Point"}
}