{
  "type": "Feature",
  "properties": {
    "addr:full":"44 Bowen Briggs Ave Warwick RI 02886",
    "addr:housenumber":"44",
    "addr:postcode":"02886",
    "addr:street":"Bowen Briggs Ave",
    "iso:country":"US",
    "sg:address":"44 Bowen Briggs Ave",
    "sg:city":"Warwick",
    "sg:classifiers":[
        {
            "category":"Recreation",
            "subcategory":"Picnic Area",
            "type":"Entertainment"
        },
        {
            "category":"Community Center",
            "type":"Public Place"
        }
    ],
    "sg:phone":"+1 401 578 9021",
    "sg:postcode":"02886",
    "sg:province":"RI",
    "sg:tags":[
        "amusement",
        "arcade"
    ],
    "wof:name":"Lhd Training Inc.",
    "wof:placetype":"venue"
},
  "geometry": {"coordinates":[-71.44483700000001,41.699169],"type":"Point"}
}