{
  "type": "Feature",
  "properties": {
    "iso:country":"US",
    "sg:address":"331 Metacom Ave",
    "sg:city":"Bristol",
    "sg:classifiers":[
        {
            "category":"Autos & Motor Vehicles",
            "subcategory":"Automobile Sales",
            "type":"Retail Goods"
        }
    ],
    "sg:phone":"+1 401 253 5600",
    "sg:postcode":"02809",
    "sg:province":"RI",
    "sg:tags":[
        "car",
        "dealer"
    ],
    "wof:name":"King Phillip Motors Inc",
    "wof:placetype":"venue"
},
  "geometry": {"coordinates":[-71.260429,41.67965],"type":"Point"}
}