{
  "type": "Feature",
  "properties": {
    "addr:full":"897 Post Rd Warwick RI 02888",
    "addr:housenumber":"897",
    "addr:postcode":"02888",
    "addr:street":"Post Rd",
    "iso:country":"US",
    "sg:address":"897 Post Rd",
    "sg:city":"Warwick",
    "sg:classifiers":[
        {
            "category":"Restaurant",
            "type":"Food & Drink"
        }
    ],
    "sg:phone":"+1 401 461 8920",
    "sg:postcode":"02888",
    "sg:province":"RI",
    "wof:name":"Portofino",
    "wof:placetype":"venue"
},
  "geometry": {"coordinates":[-71.416873,41.751996],"type":"Point"}
}