{
  "type": "Feature",
  "properties": {
    "addr:full":"2032 Plainfield Pike Cranston RI 02921",
    "addr:housenumber":"2032",
    "addr:postcode":"02921",
    "addr:street":"Plainfield Pike",
    "iso:country":"US",
    "sg:address":"2032 Plainfield Pike",
    "sg:city":"Cranston",
    "sg:classifiers":[
        {
            "category":"Ice Cream",
            "type":"Food & Drink"
        }
    ],
    "sg:menulink":"http://www.allmenus.com/ri/johnston/224843-dels-frozen-lemonade/menu/",
    "sg:postcode":"02921",
    "sg:province":"RI",
    "sg:tags":[
        "smoothy",
        "juice",
        "american"
    ],
    "wof:name":"Del's Frozen Lemonade",
    "wof:placetype":"venue"
},
  "geometry": {"coordinates":[-71.509945,41.788628],"type":"Point"}
}