{
  "type": "Feature",
  "properties": {
    "iso:country":"US",
    "sg:address":"61 Winter St",
    "sg:city":"Manville",
    "sg:classifiers":[
        {
            "category":"Recreation",
            "type":"Entertainment"
        }
    ],
    "sg:phone":"+1 401 765 4300",
    "sg:postcode":"02838",
    "sg:province":"RI",
    "wof:name":"Designed Def Mrtial Arts Stdio",
    "wof:placetype":"venue"
},
  "geometry": {"coordinates":[-71.474243,41.97028],"type":"Point"}
}