{
  "type": "Feature",
  "properties": {
    "addr:full":"310 Maple Ave Barrington RI 02806",
    "addr:housenumber":"310",
    "addr:postcode":"02806",
    "addr:street":"Maple Ave",
    "iso:country":"US",
    "sg:address":"310 Maple Ave",
    "sg:city":"Barrington",
    "sg:classifiers":[
        {
            "category":"Personal",
            "type":"Services"
        }
    ],
    "sg:phone":"+1 401 247 2220",
    "sg:postcode":"02806",
    "sg:province":"RI",
    "sg:tags":[
        "therapist",
        "massage"
    ],
    "wof:name":"A Touch Of Health Massage Co",
    "wof:placetype":"venue"
},
  "geometry": {"coordinates":[-71.318505,41.738828],"type":"Point"}
}