{
  "type": "Feature",
  "properties": {
    "addr:full":"35 Trenton St Pawtucket RI 02860",
    "addr:housenumber":"35",
    "addr:postcode":"02860",
    "addr:street":"Trenton St",
    "iso:country":"US",
    "sg:address":"35 Trenton St",
    "sg:city":"Pawtucket",
    "sg:classifiers":[
        {
            "category":"Building & Trades",
            "subcategory":"Electrical",
            "type":"Services"
        }
    ],
    "sg:phone":"+1 401 331 6624",
    "sg:postcode":"02860",
    "sg:province":"RI",
    "sg:tags":[
        "electrician"
    ],
    "wof:name":"East Side Elect Co",
    "wof:placetype":"venue"
},
  "geometry": {"coordinates":[-71.394302,41.859699],"type":"Point"}
}