{
  "type": "Feature",
  "properties": {
    "iso:country":"US",
    "sg:address":"44 Lauriston St",
    "sg:city":"Providence",
    "sg:classifiers":[
        {
            "category":"Professional",
            "subcategory":"Art Services",
            "type":"Services"
        }
    ],
    "sg:phone":"+1 401 453 6650",
    "sg:postcode":"02906",
    "sg:province":"RI",
    "sg:tags":[
        "business"
    ],
    "wof:name":"Second Story Graphics",
    "wof:placetype":"venue"
},
  "geometry": {"coordinates":[-71.395622,41.848957],"type":"Point"}
}