{
  "type": "Feature",
  "properties": {
    "iso:country":"US",
    "sg:address":"36 Linton St",
    "sg:city":"Providence",
    "sg:classifiers":[
        {
            "category":"Building & Trades",
            "subcategory":"Construction",
            "type":"Services"
        }
    ],
    "sg:phone":"+1 401 258 8223",
    "sg:postcode":"02908",
    "sg:province":"RI",
    "sg:tags":[
        "resurfacing",
        "laying",
        "refinishing",
        "floor"
    ],
    "wof:name":"Abba Wood Floor Refinishers",
    "wof:placetype":"venue"
},
  "geometry": {"coordinates":[-71.444203,41.831367],"type":"Point"}
}