{
  "type": "Feature",
  "properties": {
    "iso:country":"US",
    "sg:address":"27 Yarmouth Dr",
    "sg:city":"Westerly",
    "sg:classifiers":[
        {
            "category":"Bars & Pubs",
            "type":"Food & Drink"
        },
        {
            "category":"Bars & Pubs",
            "subcategory":"Lounge",
            "type":"Food & Drink"
        }
    ],
    "sg:phone":"+1 401 212 7592",
    "sg:postcode":"02891",
    "sg:province":"RI",
    "sg:tags":[
        "cocktail"
    ],
    "wof:name":"Grey Sail Brewing Company",
    "wof:placetype":"venue"
},
  "geometry": {"coordinates":[-71.80929999999999,41.340922],"type":"Point"}
}