{
  "type": "Feature",
  "properties": {
    "iso:country":"US",
    "sg:address":"460 Reservoir Ave",
    "sg:city":"Cranston",
    "sg:classifiers":[
        {
            "category":"Home & Garden",
            "subcategory":"Home Furnishings",
            "type":"Retail Goods"
        }
    ],
    "sg:phone":"+1 401 785 1588",
    "sg:postcode":"02910",
    "sg:province":"RI",
    "wof:name":"Pier 1 Imports 214",
    "wof:placetype":"venue"
},
  "geometry": {"coordinates":[-71.435616,41.785152],"type":"Point"}
}