{
  "type": "Feature",
  "properties": {
    "addr:full":"131 Mendon Rd Cumberland RI 02864",
    "addr:housenumber":"131",
    "addr:postcode":"02864",
    "addr:street":"Mendon Rd",
    "iso:country":"US",
    "sg:address":"131 Mendon Rd",
    "sg:city":"Cumberland",
    "sg:classifiers":[
        {
            "category":"Personal",
            "subcategory":"Beauty Salon",
            "type":"Services"
        }
    ],
    "sg:phone":"+1 401 334 8338",
    "sg:postcode":"02864",
    "sg:province":"RI",
    "wof:name":"Hair It Is",
    "wof:placetype":"venue"
},
  "geometry": {"coordinates":[-71.404611,41.91579],"type":"Point"}
}