{
  "type": "Feature",
  "properties": {
    "addr:full":"135 Gano St Providence RI 02906",
    "addr:housenumber":"135",
    "addr:postcode":"02906",
    "addr:street":"Gano St",
    "iso:country":"US",
    "sg:address":"135 Gano St",
    "sg:city":"Providence",
    "sg:classifiers":[
        {
            "category":"Home & Garden",
            "subcategory":"Garden Supply",
            "type":"Retail Goods"
        }
    ],
    "sg:phone":"+1 401 351 4330",
    "sg:postcode":"02906",
    "sg:province":"RI",
    "sg:tags":[
        "florist",
        "center"
    ],
    "sg:website":"www.anewleafflorist.org",
    "wof:name":"A New Leaf",
    "wof:placetype":"venue"
},
  "geometry": {"coordinates":[-71.390198,41.823502],"type":"Point"}
}