{
  "type": "Feature",
  "properties": {
    "iso:country":"US",
    "sg:address":"11 10th St",
    "sg:city":"East Providence",
    "sg:classifiers":[
        {
            "category":"Education",
            "subcategory":"Music School",
            "type":"Public Place"
        }
    ],
    "sg:phone":"+1 401 751 2501",
    "sg:postcode":"02914",
    "sg:province":"RI",
    "sg:tags":[
        "instrument",
        "teacher",
        "musical"
    ],
    "wof:name":"Sugal Mouthpieces Inc",
    "wof:placetype":"venue"
},
  "geometry": {"coordinates":[-71.37658399999999,41.815278],"type":"Point"}
}