{
  "type": "Feature",
  "properties": {
    "iso:country":"US",
    "sg:address":"1161 Main Ave",
    "sg:city":"Warwick",
    "sg:classifiers":[
        {
            "category":"Shopping",
            "subcategory":"Computers & Home Electronics",
            "type":"Retail Goods"
        }
    ],
    "sg:phone":"+1 401 738 3651",
    "sg:postcode":"02886",
    "sg:province":"RI",
    "sg:tags":[
        "repair"
    ],
    "wof:name":"Shanley TV Service",
    "wof:placetype":"venue"
},
  "geometry": {"coordinates":[-71.46158200000001,41.716403],"type":"Point"}
}