{
  "type": "Feature",
  "properties": {
    "iso:country":"US",
    "sg:address":"555 Valley St",
    "sg:city":"Providence",
    "sg:classifiers":[
        {
            "category":"Manufacturing",
            "subcategory":"Jewelry",
            "type":"Manufacturing & Wholesale Goods"
        }
    ],
    "sg:phone":"+1 401 831 9532",
    "sg:postcode":"02908",
    "sg:province":"RI",
    "wof:name":"G & D Jewelry",
    "wof:placetype":"venue"
},
  "geometry": {"coordinates":[-71.430504,41.830444],"type":"Point"}
}