{
  "type": "Feature",
  "properties": {
    "iso:country":"US",
    "sg:address":"37 Macarthur Dr",
    "sg:city":"Smithfield",
    "sg:classifiers":[
        {
            "category":"Home & Garden",
            "subcategory":"Hardware",
            "type":"Retail Goods"
        }
    ],
    "sg:phone":"+1 401 233 2471",
    "sg:postcode":"02917",
    "sg:province":"RI",
    "wof:name":"True North Consul",
    "wof:placetype":"venue"
},
  "geometry": {"coordinates":[-71.541448,41.896495],"type":"Point"}
}