{
  "type": "Feature",
  "properties": {
    "iso:country":"US",
    "sg:address":"277 Waterman Ave",
    "sg:city":"Smithfield",
    "sg:classifiers":[
        {
            "category":"Health Services",
            "subcategory":"Doctor",
            "type":"Services"
        },
        {
            "category":"Social Services",
            "type":"Services"
        }
    ],
    "sg:phone":"+1 401 331 7778",
    "sg:postcode":"02917",
    "sg:province":"RI",
    "sg:tags":[
        "physician",
        "surgeon",
        "counselor",
        "marriage",
        "family"
    ],
    "wof:name":"Human Services Consultants Inc",
    "wof:placetype":"venue"
},
  "geometry": {"coordinates":[-71.49282100000001,41.869977],"type":"Point"}
}