{
  "type": "Feature",
  "properties": {
    "iso:country":"US",
    "sg:address":"601 Metacom Ave",
    "sg:city":"Warren",
    "sg:classifiers":[
        {
            "category":"Shopping",
            "subcategory":"Department Store",
            "type":"Retail Goods"
        }
    ],
    "sg:phone":"+1 401 245 8920",
    "sg:postcode":"02885",
    "sg:province":"RI",
    "sg:website":"www.oceanstatejoblot.com",
    "wof:name":"Ocean State Job Lot",
    "wof:placetype":"venue"
},
  "geometry": {"coordinates":[-71.268883,41.719442],"type":"Point"}
}