{
  "type": "Feature",
  "properties": {
    "iso:country":"US",
    "sg:address":"22 Center St",
    "sg:city":"Bristol",
    "sg:classifiers":[
        {
            "category":"Building & Trades",
            "subcategory":"Construction",
            "type":"Services"
        }
    ],
    "sg:phone":"+1 401 253 4559",
    "sg:postcode":"02809",
    "sg:province":"RI",
    "sg:tags":[
        "contractor"
    ],
    "wof:name":"Raul Machado Construction Co",
    "wof:placetype":"venue"
},
  "geometry": {"coordinates":[-71.264394,41.672381],"type":"Point"}
}