{
  "type": "Feature",
  "properties": {
    "iso:country":"US",
    "sg:address":"7 Muratore Ln",
    "sg:city":"Narragansett",
    "sg:classifiers":[
        {
            "category":"Real Estate",
            "subcategory":"Real Estate Agent",
            "type":"Services"
        }
    ],
    "sg:phone":"+1 401 783 6063",
    "sg:postcode":"02882",
    "sg:province":"RI",
    "sg:tags":[
        "investment"
    ],
    "wof:name":"Timeless Properties Inc",
    "wof:placetype":"venue"
},
  "geometry": {"coordinates":[-71.43414300000001,41.483923],"type":"Point"}
}