{
  "type": "Feature",
  "properties": {
    "iso:country":"US",
    "sg:address":"1637 Mineral Spring Ave",
    "sg:city":"Providence",
    "sg:classifiers":[
        {
            "category":"Health Services",
            "subcategory":"Health Practitioner",
            "type":"Services"
        }
    ],
    "sg:phone":"+1 401 353 8884",
    "sg:postcode":"02904",
    "sg:province":"RI",
    "wof:name":"Lepre Physical Therapy",
    "wof:placetype":"venue"
},
  "geometry": {"coordinates":[-71.449326,41.864287],"type":"Point"}
}