{
  "type": "Feature",
  "properties": {
    "iso:country":"US",
    "sg:address":"41 Briarbrook Dr",
    "sg:city":"North Kingstown",
    "sg:classifiers":[
        {
            "category":"Real Estate",
            "subcategory":"Real Estate Agent",
            "type":"Services"
        }
    ],
    "sg:phone":"+1 401 885 0937",
    "sg:postcode":"02852",
    "sg:province":"RI",
    "wof:name":"Appraisal Service",
    "wof:placetype":"venue"
},
  "geometry": {"coordinates":[-71.44727399999999,41.625402],"type":"Point"}
}