{
  "type": "Feature",
  "properties": {
    "iso:country":"US",
    "sg:address":"166 Broadway",
    "sg:city":"Providence",
    "sg:classifiers":[
        {
            "category":"Professional",
            "subcategory":"Art Services",
            "type":"Services"
        }
    ],
    "sg:phone":"+1 401 831 1183",
    "sg:postcode":"02903",
    "sg:province":"RI",
    "sg:tags":[
        "artist"
    ],
    "wof:name":"Turtle Soup On Broadway",
    "wof:placetype":"venue"
},
  "geometry": {"coordinates":[-71.423157,41.821192],"type":"Point"}
}