{
  "type": "Feature",
  "properties": {
    "iso:country":"US",
    "sg:address":"13 Sharon Dr",
    "sg:city":"Coventry",
    "sg:classifiers":[
        {
            "category":"Building & Trades",
            "subcategory":"Electrical",
            "type":"Services"
        },
        {
            "category":"Building & Trades",
            "subcategory":"Plumbing",
            "type":"Services"
        }
    ],
    "sg:phone":"+1 401 822 4198",
    "sg:postcode":"02816",
    "sg:province":"RI",
    "sg:tags":[
        "rod",
        "lightning",
        "installation",
        "contractor"
    ],
    "wof:name":"Pierce Fire Protection Svcs",
    "wof:placetype":"venue"
},
  "geometry": {"coordinates":[-71.60537600000001,41.694196],"type":"Point"}
}