{
  "type": "Feature",
  "properties": {
    "iso:country":"US",
    "sg:address":"1172 Main St",
    "sg:city":"Wyoming",
    "sg:classifiers":[
        {
            "category":"Restaurant",
            "type":"Food & Drink"
        }
    ],
    "sg:phone":"+1 401 539 9060",
    "sg:postcode":"02898",
    "sg:province":"RI",
    "sg:tags":[
        "chinese"
    ],
    "sg:website":"balivillage.net",
    "wof:name":"Bali Village Restaurant",
    "wof:placetype":"venue"
},
  "geometry": {"coordinates":[-71.696736,41.513748],"type":"Point"}
}