{
  "type": "Feature",
  "properties": {
    "iso:country":"US",
    "sg:address":"22 Lockbridge St",
    "sg:city":"Pawtucket",
    "sg:classifiers":[
        {
            "category":"Mining & Drilling",
            "type":"Manufacturing & Wholesale Goods"
        },
        {
            "category":"Wholesale",
            "subcategory":"Construction Materials",
            "type":"Manufacturing & Wholesale Goods"
        },
        {
            "category":"Home & Garden",
            "subcategory":"Building Materials",
            "type":"Retail Goods"
        }
    ],
    "sg:phone":"+1 401 728 8200",
    "sg:postcode":"02860",
    "sg:province":"RI",
    "sg:tags":[
        "boring",
        "breaking",
        "contractor",
        "concrete",
        "cutting",
        "sawing"
    ],
    "sg:website":"http://www.cutriteccc.com",
    "wof:name":"Cut Rite Concrete Cutting Corporation",
    "wof:placetype":"venue"
},
  "geometry": {"coordinates":[-71.406021,41.877268],"type":"Point"}
}