{
  "type": "Feature",
  "properties": {
    "iso:country":"US",
    "sg:address":"96 2nd Ave",
    "sg:city":"Woonsocket",
    "sg:classifiers":[
        {
            "category":"Education",
            "subcategory":"School",
            "type":"Public Place"
        }
    ],
    "sg:phone":"+1 401 767 5474",
    "sg:postcode":"02895",
    "sg:province":"RI",
    "wof:name":"Thundermist Health Center",
    "wof:placetype":"venue"
},
  "geometry": {"coordinates":[-71.52579299999999,41.998438],"type":"Point"}
}