{
  "type": "Feature",
  "properties": {
    "addr:full":"104 Hilltop Dr East Greenwich RI 02818",
    "addr:housenumber":"104",
    "addr:postcode":"02818",
    "addr:street":"Hilltop Dr",
    "iso:country":"US",
    "sg:address":"104 Hilltop Dr",
    "sg:city":"East Greenwich",
    "sg:classifiers":[
        {
            "category":"Professional",
            "type":"Services"
        }
    ],
    "sg:phone":"+1 401 885 9543",
    "sg:postcode":"02818",
    "sg:province":"RI",
    "wof:name":"At Your Service LLC",
    "wof:placetype":"venue"
},
  "geometry": {"coordinates":[-71.4573,41.665866],"type":"Point"}
}