{
  "type": "Feature",
  "properties": {
    "iso:country":"US",
    "sg:address":"50 Liberty St",
    "sg:city":"Central Falls",
    "sg:classifiers":[
        {
            "category":"Personal",
            "subcategory":"Beauty Salon",
            "type":"Services"
        }
    ],
    "sg:phone":"+1 401 722 8440",
    "sg:postcode":"02863",
    "sg:province":"RI",
    "sg:tags":[
        "shop"
    ],
    "wof:name":"Marysia's House Of Beauty",
    "wof:placetype":"venue"
},
  "geometry": {"coordinates":[-71.401859,41.891818],"type":"Point"}
}