{
  "type": "Feature",
  "properties": {
    "iso:country":"US",
    "sg:address":"80 Lambert Lind Hwy",
    "sg:city":"Warwick",
    "sg:classifiers":[
        {
            "category":"Retail",
            "subcategory":"Photofinishing",
            "type":"Services"
        }
    ],
    "sg:phone":"+1 401 737 8114",
    "sg:postcode":"02886",
    "sg:province":"RI",
    "sg:tags":[
        "laboratory",
        "finishing",
        "photo"
    ],
    "wof:name":"Rapid Development",
    "wof:placetype":"venue"
},
  "geometry": {"coordinates":[-71.47647600000001,41.72854],"type":"Point"}
}