{
  "type": "Feature",
  "properties": {
    "iso:country":"US",
    "sg:address":"1294 Westminster St",
    "sg:city":"Providence",
    "sg:classifiers":[
        {
            "category":"Shopping",
            "subcategory":"Clothing, Apparel, & Fashions",
            "type":"Retail Goods"
        },
        {
            "category":"Personal",
            "subcategory":"Beauty Salon",
            "type":"Services"
        }
    ],
    "sg:phone":"+1 401 274 7750",
    "sg:postcode":"02909",
    "sg:province":"RI",
    "sg:tags":[
        "cosmetic",
        "supply"
    ],
    "wof:name":"Mariama's Hair Store & Braids",
    "wof:placetype":"venue"
},
  "geometry": {"coordinates":[-71.43119799999999,41.8167],"type":"Point"}
}