{
  "type": "Feature",
  "properties": {
    "iso:country":"US",
    "sg:address":"42 Phillips Ave",
    "sg:city":"Warwick",
    "sg:classifiers":[
        {
            "category":"Banks & Credit Unions",
            "subcategory":"Bank",
            "type":"Services"
        }
    ],
    "sg:phone":"+1 401 467 1876",
    "sg:postcode":"02888",
    "sg:province":"RI",
    "sg:tags":[
        "broker",
        "mortgage",
        "general"
    ],
    "wof:name":"East Coast Financial Corp",
    "wof:placetype":"venue"
},
  "geometry": {"coordinates":[-71.430318,41.752578],"type":"Point"}
}