{
  "type": "Feature",
  "properties": {
    "iso:country":"US",
    "sg:address":"298 Newport Ave",
    "sg:city":"Rumford",
    "sg:classifiers":[
        {
            "category":"Professional",
            "subcategory":"Employment Agencies",
            "type":"Services"
        }
    ],
    "sg:phone":"+1 401 434 1990",
    "sg:postcode":"02916",
    "sg:province":"RI",
    "sg:tags":[
        "opportunity"
    ],
    "wof:name":"Job Connection LTD",
    "wof:placetype":"venue"
},
  "geometry": {"coordinates":[-71.35445300000001,41.849041],"type":"Point"}
}