{
  "type": "Feature",
  "properties": {
    "addr:full":"10 Prospect St Providence RI 02912",
    "addr:housenumber":"10",
    "addr:postcode":"02912",
    "addr:street":"Prospect St",
    "iso:country":"US",
    "sg:address":"10 Prospect St",
    "sg:city":"Providence",
    "sg:classifiers":[
        {
            "category":"Education",
            "subcategory":"Library",
            "type":"Public Place"
        }
    ],
    "sg:phone":"+1 401 863 2165",
    "sg:postcode":"02912",
    "sg:province":"RI",
    "wof:name":"John D. Rockefeller, Jr. Library",
    "wof:placetype":"venue"
},
  "geometry": {"coordinates":[-71.404523,41.825568],"type":"Point"}
}