{
  "type": "Feature",
  "properties": {
    "iso:country":"US",
    "sg:address":"118 Rollingwood Dr",
    "sg:city":"North Kingstown",
    "sg:classifiers":[
        {
            "category":"Shopping",
            "subcategory":"Hobbies, Toys, & Games",
            "type":"Retail Goods"
        }
    ],
    "sg:phone":"+1 401 295 8326",
    "sg:postcode":"02852",
    "sg:province":"RI",
    "wof:name":"Toy Lady",
    "wof:placetype":"venue"
},
  "geometry": {"coordinates":[-71.508132,41.571051],"type":"Point"}
}