{
  "type": "Feature",
  "properties": {
    "iso:country":"US",
    "sg:address":"405 Webster Ave",
    "sg:city":"Cranston",
    "sg:classifiers":[
        {
            "category":"Home & Garden",
            "subcategory":"Building Materials",
            "type":"Retail Goods"
        },
        {
            "category":"Retail",
            "subcategory":"Auto Repair",
            "type":"Services"
        }
    ],
    "sg:phone":"+1 401 942 0980",
    "sg:postcode":"02920",
    "sg:province":"RI",
    "sg:tags":[
        "plate",
        "window",
        "windshield",
        "replacement",
        "glass"
    ],
    "wof:name":"Jack's Auto Glass",
    "wof:placetype":"venue"
},
  "geometry": {"coordinates":[-71.446251,41.80283],"type":"Point"}
}