{
  "type": "Feature",
  "properties": {
    "addr:full":"470 Thames St Newport RI 02840",
    "addr:housenumber":"470",
    "addr:postcode":"02840",
    "addr:street":"Thames St",
    "iso:country":"US",
    "sg:address":"470 Thames St",
    "sg:city":"Newport",
    "sg:classifiers":[
        {
            "category":"Personal",
            "subcategory":"Beauty Salon",
            "type":"Services"
        }
    ],
    "sg:phone":"+1 401 841 9243",
    "sg:postcode":"02840",
    "sg:province":"RI",
    "wof:name":"Angel Hair & Nails",
    "wof:placetype":"venue"
},
  "geometry": {"coordinates":[-71.314255,41.48038],"type":"Point"}
}