{
  "type": "Feature",
  "properties": {
    "iso:country":"US",
    "sg:address":"11 Sextant Ln",
    "sg:city":"Narragansett",
    "sg:classifiers":[
        {
            "category":"Freight",
            "type":"Transportation"
        }
    ],
    "sg:phone":"+1 401 789 2550",
    "sg:postcode":"02882",
    "sg:province":"RI",
    "sg:tags":[
        "commercial",
        "storage"
    ],
    "wof:name":"Anchor Self Storage",
    "wof:placetype":"venue"
},
  "geometry": {"coordinates":[-71.43586999999999,41.49188],"type":"Point"}
}