{
  "type": "Feature",
  "properties": {
    "addr:full":"824 Broad St Providence RI 02907",
    "addr:housenumber":"824",
    "addr:postcode":"02907",
    "addr:street":"Broad St",
    "iso:country":"US",
    "sg:address":"824 Broad St",
    "sg:city":"Providence",
    "sg:classifiers":[
        {
            "category":"Building & Trades",
            "subcategory":"Construction",
            "type":"Services"
        }
    ],
    "sg:phone":"+1 401 274 3887",
    "sg:postcode":"02907",
    "sg:province":"RI",
    "sg:tags":[
        "general",
        "contractor"
    ],
    "wof:name":"W & J Assoc",
    "wof:placetype":"venue"
},
  "geometry": {"coordinates":[-71.418077,41.801208],"type":"Point"}
}