{
  "type": "Feature",
  "properties": {
    "iso:country":"US",
    "sg:address":"31 Windmill Ln",
    "sg:city":"Rumford",
    "sg:classifiers":[
        {
            "category":"Real Estate",
            "subcategory":"Real Estate Agent",
            "type":"Services"
        }
    ],
    "sg:phone":"+1 401 435 4242",
    "sg:postcode":"02916",
    "sg:province":"RI",
    "sg:tags":[
        "appraisal",
        "broker"
    ],
    "wof:name":"Promised Land Inc",
    "wof:placetype":"venue"
},
  "geometry": {"coordinates":[-71.344002,41.83934],"type":"Point"}
}