{
  "type": "Feature",
  "properties": {
    "addr:full":"73 Rose Hill Dr Cranston RI 02920",
    "addr:housenumber":"73",
    "addr:postcode":"02920",
    "addr:street":"Rose Hill Dr",
    "iso:country":"US",
    "sg:address":"73 Rose Hill Dr",
    "sg:city":"Cranston",
    "sg:classifiers":[
        {
            "category":"Manufacturing",
            "subcategory":"Signs",
            "type":"Manufacturing & Wholesale Goods"
        }
    ],
    "sg:phone":"+1 401 463 8907",
    "sg:postcode":"02920",
    "sg:province":"RI",
    "sg:tags":[
        "specialty",
        "mfg"
    ],
    "wof:name":"Adlsportsdisplays Co",
    "wof:placetype":"venue"
},
  "geometry": {"coordinates":[-71.47671200000001,41.735869],"type":"Point"}
}