{
  "type": "Feature",
  "properties": {
    "iso:country":"US",
    "sg:address":"341 Broadway",
    "sg:city":"Providence",
    "sg:classifiers":[
        {
            "category":"Real Estate",
            "subcategory":"Real Estate Agent",
            "type":"Services"
        }
    ],
    "sg:phone":"+1 401 274 2414",
    "sg:postcode":"02909",
    "sg:province":"RI",
    "wof:name":"Lori A Rosa Realty",
    "wof:placetype":"venue"
},
  "geometry": {"coordinates":[-71.428681,41.820092],"type":"Point"}
}