{
  "type": "Feature",
  "properties": {
    "iso:country":"US",
    "sg:address":"444 Quaker Ln",
    "sg:city":"Warwick",
    "sg:classifiers":[
        {
            "category":"Restaurant",
            "type":"Food & Drink"
        }
    ],
    "sg:menulink":"http://www.allmenus.com/ri/warwick/11303-dennys/menu/",
    "sg:phone":"+1 401 826 7613",
    "sg:postcode":"02886",
    "sg:province":"RI",
    "sg:tags":[
        "american",
        "diner"
    ],
    "wof:name":"Denny's",
    "wof:placetype":"venue"
},
  "geometry": {"coordinates":[-71.500641,41.684251],"type":"Point"}
}