{
  "type": "Feature",
  "properties": {
    "addr:full":"31 Friendship St Westerly RI 02891",
    "addr:housenumber":"31",
    "addr:postcode":"02891",
    "addr:street":"Friendship St",
    "iso:country":"US",
    "sg:address":"31 Friendship St",
    "sg:city":"Westerly",
    "sg:classifiers":[
        {
            "category":"Retail",
            "subcategory":"Repair Shop",
            "type":"Services"
        }
    ],
    "sg:phone":"+1 401 348 0311",
    "sg:postcode":"02891",
    "sg:province":"RI",
    "sg:tags":[
        "repairing",
        "lawn",
        "mower"
    ],
    "wof:name":"Friendship Mower Repair",
    "wof:placetype":"venue"
},
  "geometry": {"coordinates":[-71.828515,41.382948],"type":"Point"}
}