{
  "type": "Feature",
  "properties": {
    "addr:full":"604 Dyer Ave Cranston RI 02920",
    "addr:housenumber":"604",
    "addr:postcode":"02920",
    "addr:street":"Dyer Ave",
    "iso:country":"US",
    "sg:address":"604 Dyer Ave",
    "sg:city":"Cranston",
    "sg:classifiers":[
        {
            "category":"Personal",
            "subcategory":"Beauty Salon",
            "type":"Services"
        }
    ],
    "sg:phone":"+1 401 274 8117",
    "sg:postcode":"02920",
    "sg:province":"RI",
    "wof:name":"Lisa Papa Hair Design",
    "wof:placetype":"venue"
},
  "geometry": {"coordinates":[-71.45742,41.796155],"type":"Point"}
}