{
  "type": "Feature",
  "properties": {
    "iso:country":"US",
    "sg:address":"83 Power Rd",
    "sg:city":"Pawtucket",
    "sg:classifiers":[
        {
            "category":"Building & Trades",
            "subcategory":"Construction",
            "type":"Services"
        }
    ],
    "sg:phone":"+1 401 727 1757",
    "sg:postcode":"02860",
    "sg:province":"RI",
    "sg:tags":[
        "contractor"
    ],
    "sg:website":"www.colettacontracting.com",
    "wof:name":"Coletta Contracting Company Inc",
    "wof:placetype":"venue"
},
  "geometry": {"coordinates":[-71.412002,41.861426],"type":"Point"}
}