{
  "type": "Feature",
  "properties": {
    "iso:country":"US",
    "sg:address":"1800 Post Rd",
    "sg:city":"Warwick",
    "sg:classifiers":[
        {
            "category":"Arts & Performance",
            "subcategory":"Theater",
            "type":"Entertainment"
        },
        {
            "category":"Professional",
            "subcategory":"Management & Consulting",
            "type":"Services"
        }
    ],
    "sg:phone":"+1 401 738 1133",
    "sg:postcode":"02886",
    "sg:province":"RI",
    "sg:tags":[
        "band",
        "orchestra"
    ],
    "wof:name":"AA Musicians Exchange",
    "wof:placetype":"venue"
},
  "geometry": {"coordinates":[-71.436685,41.732505],"type":"Point"}
}