{
  "type": "Feature",
  "properties": {
    "iso:country":"US",
    "sg:address":"711 East Ave",
    "sg:city":"Pawtucket",
    "sg:classifiers":[
        {
            "category":"Food & Beverages",
            "subcategory":"Groceries & Convenience Stores",
            "type":"Retail Goods"
        }
    ],
    "sg:phone":"+1 401 722 5590",
    "sg:postcode":"02860",
    "sg:province":"RI",
    "sg:website":"www.cumberlandfarms.com",
    "wof:name":"Cumberland Farms 1232",
    "wof:placetype":"venue"
},
  "geometry": {"coordinates":[-71.39071300000001,41.85794],"type":"Point"}
}