{
  "type": "Feature",
  "properties": {
    "addr:full":"17 Rufus St Pawtucket RI 02860",
    "addr:housenumber":"17",
    "addr:postcode":"02860",
    "addr:street":"Rufus St",
    "iso:country":"US",
    "sg:address":"17 Rufus St",
    "sg:city":"Pawtucket",
    "sg:classifiers":[
        {
            "category":"Building & Trades",
            "subcategory":"Construction",
            "type":"Services"
        }
    ],
    "sg:phone":"+1 401 726 4180",
    "sg:postcode":"02860",
    "sg:province":"RI",
    "sg:tags":[
        "layer",
        "carpet"
    ],
    "wof:name":"A & G Carpet Installation",
    "wof:placetype":"venue"
},
  "geometry": {"coordinates":[-71.41315400000001,41.878946],"type":"Point"}
}