{
  "type": "Feature",
  "properties": {
    "iso:country":"US",
    "sg:address":"970 Willett Ave",
    "sg:city":"Riverside",
    "sg:classifiers":[
        {
            "category":"Autos & Motor Vehicles",
            "subcategory":"Fuel & Gas Station",
            "type":"Retail Goods"
        }
    ],
    "sg:phone":"+1 401 433 4326",
    "sg:postcode":"02915",
    "sg:province":"RI",
    "sg:tags":[
        "oil"
    ],
    "wof:name":"Willett Texaco",
    "wof:placetype":"venue"
},
  "geometry": {"coordinates":[-71.346501,41.759516],"type":"Point"}
}