{
  "type": "Feature",
  "properties": {
    "addr:full":"298 Park Ave Cranston RI 02905",
    "addr:housenumber":"298",
    "addr:postcode":"02905",
    "addr:street":"Park Ave",
    "iso:country":"US",
    "sg:address":"298 Park Ave",
    "sg:city":"Cranston",
    "sg:classifiers":[
        {
            "category":"Ice Cream",
            "type":"Food & Drink"
        }
    ],
    "sg:menulink":"http://www.allmenus.com/ri/cranston/224844-dels-frozen-lemonade/menu/",
    "sg:postcode":"02905",
    "sg:province":"RI",
    "sg:tags":[
        "smoothy",
        "juice",
        "american"
    ],
    "wof:name":"Del's Frozen Lemonade",
    "wof:placetype":"venue"
},
  "geometry": {"coordinates":[-71.411041,41.772051],"type":"Point"}
}