{
  "type": "Feature",
  "properties": {
    "iso:country":"US",
    "sg:address":"240 Bullocks Point Ave",
    "sg:city":"Riverside",
    "sg:classifiers":[
        {
            "category":"Restaurant",
            "type":"Food & Drink"
        }
    ],
    "sg:phone":"+1 401 433 1931",
    "sg:postcode":"02915",
    "sg:province":"RI",
    "sg:tags":[
        "parlor",
        "ice",
        "cream"
    ],
    "wof:name":"Dairy-Bee",
    "wof:placetype":"venue"
},
  "geometry": {"coordinates":[-71.362976,41.772605],"type":"Point"}
}