{
  "type": "Feature",
  "properties": {
    "addr:full":"44 Providence Pl Providence RI 02903",
    "addr:housenumber":"44",
    "addr:postcode":"02903",
    "addr:street":"Providence Pl",
    "iso:country":"US",
    "sg:address":"44 Providence Pl",
    "sg:city":"Providence",
    "sg:classifiers":[
        {
            "category":"Shopping",
            "subcategory":"Clothing, Apparel, & Fashions",
            "type":"Retail Goods"
        }
    ],
    "sg:phone":"+1 401 270 4777",
    "sg:postcode":"02903",
    "sg:province":"RI",
    "wof:name":"Eddie Bauer Sportswear",
    "wof:placetype":"venue"
},
  "geometry": {"coordinates":[-71.417733,41.827437],"type":"Point"}
}