{
  "type": "Feature",
  "properties": {
    "iso:country":"US",
    "sg:address":"38 Ives Rd",
    "sg:city":"East Greenwich",
    "sg:classifiers":[
        {
            "category":"Professional",
            "subcategory":"Management & Consulting",
            "type":"Services"
        }
    ],
    "sg:phone":"+1 401 885 4954",
    "sg:postcode":"02818",
    "sg:province":"RI",
    "wof:name":"Consulting Source Inc",
    "wof:placetype":"venue"
},
  "geometry": {"coordinates":[-71.41116599999999,41.661714],"type":"Point"}
}