{
  "type": "Feature",
  "properties": {
    "iso:country":"US",
    "sg:address":"19 Railroad Ave",
    "sg:city":"Westerly",
    "sg:classifiers":[
        {
            "category":"Communications",
            "subcategory":"Radio Station",
            "type":"Services"
        }
    ],
    "sg:phone":"+1 401 596 6795",
    "sg:postcode":"02891",
    "sg:province":"RI",
    "sg:tags":[
        "broadcast"
    ],
    "wof:name":"WCRI",
    "wof:placetype":"venue"
},
  "geometry": {"coordinates":[-71.829009,41.381265],"type":"Point"}
}