{
  "type": "Feature",
  "properties": {
    "addr:full":"15 Verndale Cir Bristol RI 02809",
    "addr:housenumber":"15",
    "addr:postcode":"02809",
    "addr:street":"Verndale Cir",
    "iso:country":"US",
    "sg:address":"15 Verndale Cir",
    "sg:city":"Bristol",
    "sg:classifiers":[
        {
            "category":"Shopping",
            "subcategory":"Florist",
            "type":"Retail Goods"
        }
    ],
    "sg:phone":"+1 401 253 7050",
    "sg:postcode":"02809",
    "sg:province":"RI",
    "wof:name":"Mainly Flowers",
    "wof:placetype":"venue"
},
  "geometry": {"coordinates":[-71.278362,41.694624],"type":"Point"}
}