{
  "type": "Feature",
  "properties": {
    "iso:country":"US",
    "sg:address":"225 Newman Ave",
    "sg:city":"Rumford",
    "sg:classifiers":[
        {
            "category":"Shopping",
            "subcategory":"Used Merchandise",
            "type":"Retail Goods"
        }
    ],
    "sg:phone":"+1 401 438 5989",
    "sg:postcode":"02916",
    "sg:province":"RI",
    "sg:tags":[
        "antique"
    ],
    "wof:name":"Liberty Antiques & Appraisals",
    "wof:placetype":"venue"
},
  "geometry": {"coordinates":[-71.347387,41.841379],"type":"Point"}
}