{
  "type": "Feature",
  "properties": {
    "iso:country":"US",
    "sg:address":"712 Nate Whipple Hwy",
    "sg:city":"Cumberland",
    "sg:classifiers":[
        {
            "category":"Professional",
            "type":"Services"
        }
    ],
    "sg:phone":"+1 401 334 2685",
    "sg:postcode":"02864",
    "sg:province":"RI",
    "wof:name":"NRI Community Svc",
    "wof:placetype":"venue"
},
  "geometry": {"coordinates":[-71.38971600000001,41.976428],"type":"Point"}
}