{
  "type": "Feature",
  "properties": {
    "iso:country":"US",
    "sg:address":"2435 Warwick Ave",
    "sg:city":"Warwick",
    "sg:classifiers":[
        {
            "category":"Retail",
            "subcategory":"Funeral Services",
            "type":"Services"
        }
    ],
    "sg:phone":"+1 401 738 1977",
    "sg:postcode":"02889",
    "sg:province":"RI",
    "sg:tags":[
        "director"
    ],
    "wof:name":"Quinn Thomas & Walter Funeral",
    "wof:placetype":"venue"
},
  "geometry": {"coordinates":[-71.39847399999999,41.710271],"type":"Point"}
}