{
  "type": "Feature",
  "properties": {
    "iso:country":"US",
    "sg:address":"41 Brandon St",
    "sg:city":"Warwick",
    "sg:classifiers":[
        {
            "category":"Building & Trades",
            "subcategory":"Construction",
            "type":"Services"
        }
    ],
    "sg:phone":"+1 401 785 0580",
    "sg:postcode":"02888",
    "sg:province":"RI",
    "sg:tags":[
        "general",
        "contractor"
    ],
    "wof:name":"M C Renovations",
    "wof:placetype":"venue"
},
  "geometry": {"coordinates":[-71.4126,41.757762],"type":"Point"}
}