{
  "type": "Feature",
  "properties": {
    "iso:country":"US",
    "sg:address":"801 Broad St",
    "sg:city":"Central Falls",
    "sg:classifiers":[
        {
            "category":"Organizations",
            "subcategory":"Community Association",
            "type":"Services"
        }
    ],
    "sg:phone":"+1 401 475 2533",
    "sg:postcode":"02863",
    "sg:province":"RI",
    "sg:tags":[
        "military"
    ],
    "wof:name":"Era Vietnam Veterans Assn",
    "wof:placetype":"venue"
},
  "geometry": {"coordinates":[-71.387271,41.890226],"type":"Point"}
}