{
  "type": "Feature",
  "properties": {
    "iso:country":"US",
    "sg:address":"83 Park St",
    "sg:city":"Providence",
    "sg:classifiers":[
        {
            "category":"Arts & Performance",
            "subcategory":"Theater",
            "type":"Entertainment"
        }
    ],
    "sg:phone":"+1 401 331 6060",
    "sg:postcode":"02903",
    "sg:province":"RI",
    "sg:tags":[
        "opera",
        "company"
    ],
    "sg:website":"www.operaprovidence.org",
    "wof:name":"Opera Providence",
    "wof:placetype":"venue"
},
  "geometry": {"coordinates":[-71.417123,41.831273],"type":"Point"}
}