{
  "type": "Feature",
  "properties": {
    "addr:full":"37 Young St Newport RI 02840",
    "addr:housenumber":"37",
    "addr:postcode":"02840",
    "addr:street":"Young St",
    "iso:country":"US",
    "sg:address":"37 Young St",
    "sg:city":"Newport",
    "sg:classifiers":[
        {
            "category":"Restaurant",
            "type":"Food & Drink"
        }
    ],
    "sg:phone":"+1 401 842 0011",
    "sg:postcode":"02840",
    "sg:province":"RI",
    "sg:tags":[
        "gourmet",
        "delicatessen"
    ],
    "wof:name":"Putti Palace Cafe Inc",
    "wof:placetype":"venue"
},
  "geometry": {"coordinates":[-71.313142,41.481583],"type":"Point"}
}