{
  "type": "Feature",
  "properties": {
    "iso:country":"US",
    "sg:address":"55 Beach St",
    "sg:city":"Westerly",
    "sg:classifiers":[
        {
            "category":"Personal",
            "subcategory":"Beauty Salon",
            "type":"Services"
        }
    ],
    "sg:phone":"+1 401 596 4400",
    "sg:postcode":"02891",
    "sg:province":"RI",
    "sg:tags":[
        "shop"
    ],
    "wof:name":"Haircraft Designs",
    "wof:placetype":"venue"
},
  "geometry": {"coordinates":[-71.829882,41.364994],"type":"Point"}
}