{
  "type": "Feature",
  "properties": {
    "addr:full":"1023 Social St Woonsocket RI 02895",
    "addr:housenumber":"1023",
    "addr:postcode":"02895",
    "addr:street":"Social St",
    "iso:country":"US",
    "sg:address":"1023 Social St",
    "sg:city":"Woonsocket",
    "sg:classifiers":[
        {
            "category":"Autos & Motor Vehicles",
            "subcategory":"Fuel & Gas Station",
            "type":"Retail Goods"
        }
    ],
    "sg:phone":"+1 401 769 6489",
    "sg:postcode":"02895",
    "sg:province":"RI",
    "sg:tags":[
        "station",
        "gasoline"
    ],
    "wof:name":"Coastal Gas Station",
    "wof:placetype":"venue"
},
  "geometry": {"coordinates":[-71.500524,42.015046],"type":"Point"}
}