{
  "type": "Feature",
  "properties": {
    "addr:full":"1491 Atwood Ave Johnston RI 02919",
    "addr:housenumber":"1491",
    "addr:postcode":"02919",
    "addr:street":"Atwood Ave",
    "iso:country":"US",
    "sg:address":"1491 Atwood Ave",
    "sg:city":"Johnston",
    "sg:classifiers":[
        {
            "category":"Banks & Credit Unions",
            "subcategory":"Bank",
            "type":"Services"
        },
        {
            "category":"Banks & Credit Unions",
            "subcategory":"Financial Services",
            "type":"Services"
        }
    ],
    "sg:phone":"+1 401 278 6070",
    "sg:postcode":"02919",
    "sg:province":"RI",
    "sg:tags":[
        "commercial",
        "loan",
        "internet",
        "saving",
        "banking"
    ],
    "sg:website":"http://www.bofa.com",
    "wof:name":"Bank Of America",
    "wof:placetype":"venue"
},
  "geometry": {"coordinates":[-71.49887099999999,41.823471],"type":"Point"}
}