{
  "type": "Feature",
  "properties": {
    "iso:country":"US",
    "sg:address":"501 Roosevelt Ave",
    "sg:city":"Central Falls",
    "sg:classifiers":[
        {
            "category":"Shopping",
            "subcategory":"Used Merchandise",
            "type":"Retail Goods"
        }
    ],
    "sg:phone":"+1 401 724 1020",
    "sg:postcode":"02863",
    "sg:province":"RI",
    "wof:name":"Straightline Used Furniture",
    "wof:placetype":"venue"
},
  "geometry": {"coordinates":[-71.382167,41.886466],"type":"Point"}
}