{
  "type": "Feature",
  "properties": {
    "addr:full":"68 Broadway Pawtucket RI 02860",
    "addr:housenumber":"68",
    "addr:postcode":"02860",
    "addr:street":"Broadway",
    "iso:country":"US",
    "sg:address":"68 Broadway",
    "sg:city":"Pawtucket",
    "sg:classifiers":[
        {
            "category":"Retail",
            "subcategory":"Funeral Services",
            "type":"Services"
        }
    ],
    "sg:phone":"+1 401 723 1312",
    "sg:postcode":"02860",
    "sg:province":"RI",
    "sg:tags":[
        "cemetery"
    ],
    "sg:website":"www.manningheffern.com",
    "wof:name":"Manning-Heffern Funeral Home",
    "wof:placetype":"venue"
},
  "geometry": {"coordinates":[-71.3806,41.8769],"type":"Point"}
}