{
  "type": "Feature",
  "properties": {
    "addr:full":"23 Brown St North Kingstown RI 02852",
    "addr:housenumber":"23",
    "addr:postcode":"02852",
    "addr:street":"Brown St",
    "iso:country":"US",
    "sg:address":"23 Brown St",
    "sg:city":"North Kingstown",
    "sg:classifiers":[
        {
            "category":"Real Estate",
            "subcategory":"Architect",
            "type":"Services"
        }
    ],
    "sg:phone":"+1 401 294 1684",
    "sg:postcode":"02852",
    "sg:province":"RI",
    "sg:tags":[
        "course",
        "golf"
    ],
    "wof:name":"Beckman-Weremay LTD",
    "wof:placetype":"venue"
},
  "geometry": {"coordinates":[-71.452552,41.569714],"type":"Point"}
}