{
  "type": "Feature",
  "properties": {
    "iso:country":"US",
    "sg:address":"1049 Smithfield Ave",
    "sg:city":"Lincoln",
    "sg:classifiers":[
        {
            "category":"Professional",
            "subcategory":"Management & Consulting",
            "type":"Services"
        }
    ],
    "sg:phone":"+1 401 725 3339",
    "sg:postcode":"02865",
    "sg:province":"RI",
    "sg:tags":[
        "business"
    ],
    "wof:name":"Joan P Hobbs",
    "wof:placetype":"venue"
},
  "geometry": {"coordinates":[-71.413017,41.887905],"type":"Point"}
}