{
  "type": "Feature",
  "properties": {
    "iso:country":"US",
    "sg:address":"50 Esten Ave",
    "sg:city":"Pawtucket",
    "sg:classifiers":[
        {
            "category":"Manufacturing",
            "subcategory":"Textiles",
            "type":"Manufacturing & Wholesale Goods"
        }
    ],
    "sg:phone":"+1 401 724 9000",
    "sg:postcode":"02860",
    "sg:province":"RI",
    "sg:tags":[
        "bonding",
        "fabric",
        "laminating"
    ],
    "sg:website":"www.cooleygroup.com",
    "wof:name":"Cooley Group",
    "wof:placetype":"venue"
},
  "geometry": {"coordinates":[-71.40231799999999,41.865805],"type":"Point"}
}