{
  "type": "Feature",
  "properties": {
    "addr:full":"3 Humbert St North Providence RI 02911",
    "addr:housenumber":"3",
    "addr:postcode":"02911",
    "addr:street":"Humbert St",
    "iso:country":"US",
    "sg:address":"3 Humbert St",
    "sg:city":"North Providence",
    "sg:classifiers":[
        {
            "category":"Retail",
            "subcategory":"Self-service Laundry",
            "type":"Services"
        }
    ],
    "sg:phone":"+1 401 232 0340",
    "sg:postcode":"02911",
    "sg:province":"RI",
    "sg:tags":[
        "coin"
    ],
    "wof:name":"Sudsational Laundry Service",
    "wof:placetype":"venue"
},
  "geometry": {"coordinates":[-71.475945,41.84478],"type":"Point"}
}