{
  "type": "Feature",
  "properties": {
    "iso:country":"US",
    "sg:address":"115 Scituate Vista Dr",
    "sg:city":"Cranston",
    "sg:classifiers":[
        {
            "category":"Real Estate",
            "subcategory":"Real Estate Operator",
            "type":"Services"
        }
    ],
    "sg:phone":"+1 401 942 9650",
    "sg:postcode":"02921",
    "sg:province":"RI",
    "sg:tags":[
        "apartment",
        "complex"
    ],
    "wof:name":"Scituate Vista Apartments",
    "wof:placetype":"venue"
},
  "geometry": {"coordinates":[-71.48850899999999,41.77653],"type":"Point"}
}