{
  "type": "Feature",
  "properties": {
    "iso:country":"US",
    "sg:address":"125 Arthur W Devine Blvd",
    "sg:city":"Warwick",
    "sg:classifiers":[
        {
            "category":"Government",
            "subcategory":"Office",
            "type":"Public Place"
        }
    ],
    "sg:phone":"+1 401 739 4949",
    "sg:postcode":"02886",
    "sg:province":"RI",
    "sg:tags":[
        "management"
    ],
    "wof:name":"Sewer Dept",
    "wof:placetype":"venue"
},
  "geometry": {"coordinates":[-71.44805100000001,41.737567],"type":"Point"}
}