{
  "type": "Feature",
  "properties": {
    "addr:full":"285 Armistice Blvd Pawtucket RI 02861",
    "addr:housenumber":"285",
    "addr:postcode":"02861",
    "addr:street":"Armistice Blvd",
    "iso:country":"US",
    "sg:address":"285 Armistice Blvd",
    "sg:city":"Pawtucket",
    "sg:classifiers":[
        {
            "category":"Restaurant",
            "type":"Food & Drink"
        }
    ],
    "sg:phone":"+1 401 726 9564",
    "sg:postcode":"02861",
    "sg:province":"RI",
    "sg:website":"www.mcdonalds.com",
    "wof:name":"McDonald's of Pawtucket",
    "wof:placetype":"venue"
},
  "geometry": {"coordinates":[-71.36370100000001,41.880199],"type":"Point"}
}