{
  "type": "Feature",
  "properties": {
    "addr:full":"4 Mowry St Providence RI 02908",
    "addr:housenumber":"4",
    "addr:postcode":"02908",
    "addr:street":"Mowry St",
    "iso:country":"US",
    "sg:address":"4 Mowry St",
    "sg:city":"Providence",
    "sg:classifiers":[
        {
            "category":"Education",
            "subcategory":"Music School",
            "type":"Public Place"
        }
    ],
    "sg:phone":"+1 401 273 0346",
    "sg:postcode":"02908",
    "sg:province":"RI",
    "sg:tags":[
        "instrument",
        "teacher",
        "musical"
    ],
    "wof:name":"Cicchetti Gino Piano Technician",
    "wof:placetype":"venue"
},
  "geometry": {"coordinates":[-71.429199,41.843601],"type":"Point"}
}