{
  "type": "Feature",
  "properties": {
    "iso:country":"US",
    "sg:address":"318 Lafayette St",
    "sg:city":"Pawtucket",
    "sg:classifiers":[
        {
            "category":"Professional",
            "type":"Services"
        }
    ],
    "sg:phone":"+1 401 724 6530",
    "sg:postcode":"02860",
    "sg:province":"RI",
    "sg:tags":[
        "sculptor"
    ],
    "wof:name":"Ben Tre Ltd",
    "wof:placetype":"venue"
},
  "geometry": {"coordinates":[-71.396101,41.857285],"type":"Point"}
}