{
  "type": "Feature",
  "properties": {
    "iso:country":"US",
    "sg:address":"557 Weaver Hill Rd",
    "sg:city":"Coventry",
    "sg:classifiers":[
        {
            "category":"Health Services",
            "subcategory":"Nursing And Care Facility",
            "type":"Services"
        }
    ],
    "sg:phone":"+1 401 397 5001",
    "sg:postcode":"02816",
    "sg:province":"RI",
    "sg:tags":[
        "home",
        "convalescent"
    ],
    "wof:name":"Alpine Nursing Home",
    "wof:placetype":"venue"
},
  "geometry": {"coordinates":[-71.66644700000001,41.665055],"type":"Point"}
}