{
  "type": "Feature",
  "properties": {
    "iso:country":"US",
    "sg:address":"87 Duncan Rd",
    "sg:city":"Warwick",
    "sg:classifiers":[
        {
            "category":"Real Estate",
            "subcategory":"Real Estate Agent",
            "type":"Services"
        }
    ],
    "sg:phone":"+1 401 737 9741",
    "sg:postcode":"02886",
    "sg:province":"RI",
    "wof:name":"Carol S Shaw Inc",
    "wof:placetype":"venue"
},
  "geometry": {"coordinates":[-71.42282899999999,41.695726],"type":"Point"}
}