{
  "type": "Feature",
  "properties": {
    "addr:full":"1076 Park Ave Cranston RI 02910",
    "addr:housenumber":"1076",
    "addr:postcode":"02910",
    "addr:street":"Park Ave",
    "iso:country":"US",
    "sg:address":"1076 Park Ave",
    "sg:city":"Cranston",
    "sg:classifiers":[
        {
            "category":"Personal",
            "subcategory":"Beauty Salon",
            "type":"Services"
        }
    ],
    "sg:phone":"+1 401 464 4044",
    "sg:postcode":"02910",
    "sg:province":"RI",
    "sg:tags":[
        "shop"
    ],
    "wof:name":"Salon Panache",
    "wof:placetype":"venue"
},
  "geometry": {"coordinates":[-71.44544999999999,41.782379],"type":"Point"}
}