{
  "type": "Feature",
  "properties": {
    "addr:full":"1152 High St Central Falls RI 02863",
    "addr:housenumber":"1152",
    "addr:postcode":"02863",
    "addr:street":"High St",
    "iso:country":"US",
    "sg:address":"1152 High St",
    "sg:city":"Central Falls",
    "sg:classifiers":[
        {
            "category":"Manufacturing",
            "subcategory":"Paper Products",
            "type":"Manufacturing & Wholesale Goods"
        }
    ],
    "sg:phone":"+1 401 725 4300",
    "sg:postcode":"02863",
    "sg:province":"RI",
    "sg:tags":[
        "box"
    ],
    "sg:website":"www.fullerbox.com",
    "wof:name":"Fuller Packaging Inc",
    "wof:placetype":"venue"
},
  "geometry": {"coordinates":[-71.383477,41.894365],"type":"Point"}
}