{
  "type": "Feature",
  "properties": {
    "addr:full":"7 Columbus Ave Westerly RI 02891",
    "addr:housenumber":"7",
    "addr:postcode":"02891",
    "addr:street":"Columbus Ave",
    "iso:country":"US",
    "sg:address":"7 Columbus Ave",
    "sg:city":"Westerly",
    "sg:classifiers":[
        {
            "category":"Personal",
            "subcategory":"Beauty Salon",
            "type":"Services"
        }
    ],
    "sg:phone":"+1 401 596 1945",
    "sg:postcode":"02891",
    "sg:province":"RI",
    "wof:name":"Agnes Ann's Beauty Nook",
    "wof:placetype":"venue"
},
  "geometry": {"coordinates":[-71.830162,41.389286],"type":"Point"}
}