{
  "type": "Feature",
  "properties": {
    "addr:full":"102 Newport St Woonsocket RI 02895",
    "addr:housenumber":"102",
    "addr:postcode":"02895",
    "addr:street":"Newport St",
    "iso:country":"US",
    "sg:address":"102 Newport St",
    "sg:city":"Woonsocket",
    "sg:classifiers":[
        {
            "category":"Personal",
            "subcategory":"Beauty Salon",
            "type":"Services"
        }
    ],
    "sg:phone":"+1 401 762 4926",
    "sg:postcode":"02895",
    "sg:province":"RI",
    "sg:tags":[
        "shop"
    ],
    "wof:name":"Styling Unlmited By Viv Cherie",
    "wof:placetype":"venue"
},
  "geometry": {"coordinates":[-71.51379300000001,41.987408],"type":"Point"}
}