{
  "type": "Feature",
  "properties": {
    "addr:full":"478 Waterman Ave East Providence RI 02914",
    "addr:housenumber":"478",
    "addr:postcode":"02914",
    "addr:street":"Waterman Ave",
    "iso:country":"US",
    "sg:address":"478 Waterman Ave",
    "sg:city":"East Providence",
    "sg:classifiers":[
        {
            "category":"Retail",
            "subcategory":"Auto Repair",
            "type":"Services"
        }
    ],
    "sg:phone":"+1 401 434 9895",
    "sg:postcode":"02914",
    "sg:province":"RI",
    "sg:tags":[
        "automotive"
    ],
    "wof:name":"Mobile Intellect",
    "wof:placetype":"venue"
},
  "geometry": {"coordinates":[-71.359703,41.817313],"type":"Point"}
}