{
  "type": "Feature",
  "properties": {
    "addr:full":"465 Lonsdale Ave Pawtucket RI 02860",
    "addr:housenumber":"465",
    "addr:postcode":"02860",
    "addr:street":"Lonsdale Ave",
    "iso:country":"US",
    "sg:address":"465 Lonsdale Ave",
    "sg:city":"Pawtucket",
    "sg:classifiers":[
        {
            "category":"Food & Beverages",
            "subcategory":"Liquor & Beverages",
            "type":"Retail Goods"
        }
    ],
    "sg:phone":"+1 401 728 2300",
    "sg:postcode":"02860",
    "sg:province":"RI",
    "sg:tags":[
        "beer",
        "spirit",
        "wine"
    ],
    "wof:name":"Lonsdale Wine & Spirits",
    "wof:placetype":"venue"
},
  "geometry": {"coordinates":[-71.4002,41.879902],"type":"Point"}
}