{
  "type": "Feature",
  "properties": {
    "addr:full":"590 Pleasant Valley Pkwy Providence RI 02908",
    "addr:housenumber":"590",
    "addr:postcode":"02908",
    "addr:street":"Pleasant Valley Pkwy",
    "iso:country":"US",
    "sg:address":"590 Pleasant Valley Pkwy",
    "sg:city":"Providence",
    "sg:classifiers":[
        {
            "category":"Professional",
            "subcategory":"Lawyer & Legal Services",
            "type":"Services"
        }
    ],
    "sg:phone":"+1 401 421 1993",
    "sg:postcode":"02908",
    "sg:province":"RI",
    "wof:name":"Ryan Thomas J",
    "wof:placetype":"venue"
},
  "geometry": {"coordinates":[-71.442001,41.834702],"type":"Point"}
}