{
  "type": "Feature",
  "properties": {
    "iso:country":"US",
    "sg:address":"2 Chestnut Dr",
    "sg:city":"East Greenwich",
    "sg:classifiers":[
        {
            "category":"Social Services",
            "type":"Services"
        }
    ],
    "sg:phone":"+1 401 885 1704",
    "sg:postcode":"02818",
    "sg:province":"RI",
    "sg:tags":[
        "organization",
        "welfare"
    ],
    "wof:name":"Ymca-Greater Providence",
    "wof:placetype":"venue"
},
  "geometry": {"coordinates":[-71.480766,41.636058],"type":"Point"}
}