{
  "type": "Feature",
  "properties": {
    "iso:country":"US",
    "sg:address":"310 Maple Ave",
    "sg:city":"Barrington",
    "sg:classifiers":[
        {
            "category":"Health Services",
            "subcategory":"Doctor",
            "type":"Services"
        }
    ],
    "sg:phone":"+1 401 245 2154",
    "sg:postcode":"02806",
    "sg:province":"RI",
    "sg:tags":[
        "osteopathic"
    ],
    "wof:name":"Medical Group of RI Inc",
    "wof:placetype":"venue"
},
  "geometry": {"coordinates":[-71.318505,41.738828],"type":"Point"}
}