{
  "type": "Feature",
  "properties": {
    "iso:country":"US",
    "sg:address":"893 Allens Ave",
    "sg:city":"Providence",
    "sg:classifiers":[
        {
            "category":"Professional",
            "type":"Services"
        }
    ],
    "sg:phone":"+1 401 467 9026",
    "sg:postcode":"02905",
    "sg:province":"RI",
    "sg:tags":[
        "establishment"
    ],
    "wof:name":"Frans Place",
    "wof:placetype":"venue"
},
  "geometry": {"coordinates":[-71.39684800000001,41.791479],"type":"Point"}
}