{
  "type": "Feature",
  "properties": {
    "iso:country":"US",
    "sg:address":"133 Webster St",
    "sg:city":"Pawtucket",
    "sg:classifiers":[
        {
            "category":"Building & Trades",
            "subcategory":"Construction",
            "type":"Services"
        }
    ],
    "sg:phone":"+1 401 726 0078",
    "sg:postcode":"02861",
    "sg:province":"RI",
    "sg:tags":[
        "plastering",
        "contractor"
    ],
    "wof:name":"MSL Plastering",
    "wof:placetype":"venue"
},
  "geometry": {"coordinates":[-71.365908,41.890686],"type":"Point"}
}