{
  "type": "Feature",
  "properties": {
    "addr:full":"1347 Hartford Ave Johnston RI 02919",
    "addr:housenumber":"1347",
    "addr:postcode":"02919",
    "addr:street":"Hartford Ave",
    "iso:country":"US",
    "sg:address":"1347 Hartford Ave",
    "sg:city":"Johnston",
    "sg:classifiers":[
        {
            "category":"Health Services",
            "subcategory":"Doctor",
            "type":"Services"
        }
    ],
    "sg:phone":"+1 401 861 7643",
    "sg:postcode":"02919",
    "sg:province":"RI",
    "sg:tags":[
        "dentist"
    ],
    "wof:name":"Arthur L Mansolillo DDS",
    "wof:placetype":"venue"
},
  "geometry": {"coordinates":[-71.495632,41.823277],"type":"Point"}
}