{
  "type": "Feature",
  "properties": {
    "iso:country":"US",
    "sg:address":"672 East Ave",
    "sg:city":"Warwick",
    "sg:classifiers":[
        {
            "category":"Building & Trades",
            "subcategory":"Landscaping Services",
            "type":"Services"
        }
    ],
    "sg:phone":"+1 401 828 6700",
    "sg:postcode":"02886",
    "sg:province":"RI",
    "sg:tags":[
        "spraying",
        "lawn"
    ],
    "wof:name":"Rhode Island Lawn & Tree Co",
    "wof:placetype":"venue"
},
  "geometry": {"coordinates":[-71.48689,41.720003],"type":"Point"}
}