{
  "type": "Feature",
  "properties": {
    "iso:country":"US",
    "sg:address":"167 Jenks Ave",
    "sg:city":"Central Falls",
    "sg:classifiers":[
        {
            "category":"Professional",
            "subcategory":"Business Services",
            "type":"Services"
        }
    ],
    "sg:phone":"+1 401 728 5349",
    "sg:postcode":"02863",
    "sg:province":"RI",
    "wof:name":"Parduf Enterprises Inc",
    "wof:placetype":"venue"
},
  "geometry": {"coordinates":[-71.392709,41.896971],"type":"Point"}
}