{
  "type": "Feature",
  "properties": {
    "addr:full":"20 Catamore Blvd East Providence RI 02914",
    "addr:housenumber":"20",
    "addr:postcode":"02914",
    "addr:street":"Catamore Blvd",
    "iso:country":"US",
    "sg:address":"20 Catamore Blvd",
    "sg:city":"East Providence",
    "sg:classifiers":[
        {
            "category":"Health Services",
            "subcategory":"Medical Lab",
            "type":"Services"
        }
    ],
    "sg:phone":"+1 401 432 2520",
    "sg:postcode":"02914",
    "sg:province":"RI",
    "sg:tags":[
        "x",
        "laboratory"
    ],
    "sg:website":"www.rimirad.com",
    "wof:name":"Rhode Island Medical Imaging",
    "wof:placetype":"venue"
},
  "geometry": {"coordinates":[-71.34343,41.802188],"type":"Point"}
}