{
  "type": "Feature",
  "properties": {
    "iso:country":"US",
    "sg:address":"25 Enterprise Ct",
    "sg:city":"Newport",
    "sg:classifiers":[
        {
            "category":"Professional",
            "subcategory":"Engineering",
            "type":"Services"
        }
    ],
    "sg:phone":"+1 401 849 8550",
    "sg:postcode":"02840",
    "sg:province":"RI",
    "wof:name":"GP Technologies",
    "wof:placetype":"venue"
},
  "geometry": {"coordinates":[-71.321624,41.508309],"type":"Point"}
}