{
  "type": "Feature",
  "properties": {
    "addr:full":"119 Meadow St Warwick RI 02886",
    "addr:housenumber":"119",
    "addr:postcode":"02886",
    "addr:street":"Meadow St",
    "iso:country":"US",
    "sg:address":"119 Meadow St",
    "sg:city":"Warwick",
    "sg:classifiers":[
        {
            "category":"Building & Trades",
            "subcategory":"Construction",
            "type":"Services"
        }
    ],
    "sg:phone":"+1 401 737 2746",
    "sg:postcode":"02886",
    "sg:province":"RI",
    "sg:tags":[
        "residential",
        "contractor",
        "sp",
        "nonresidential"
    ],
    "wof:name":"Architctral Preservation Group",
    "wof:placetype":"venue"
},
  "geometry": {"coordinates":[-71.46147999999999,41.696876],"type":"Point"}
}