{
  "type": "Feature",
  "properties": {
    "iso:country":"US",
    "sg:address":"1417 Atwood Ave",
    "sg:city":"Johnston",
    "sg:classifiers":[
        {
            "category":"Building & Trades",
            "subcategory":"Construction",
            "type":"Services"
        }
    ],
    "sg:phone":"+1 401 946 8500",
    "sg:postcode":"02919",
    "sg:province":"RI",
    "sg:tags":[
        "contractor"
    ],
    "wof:name":"Altieri Glass",
    "wof:placetype":"venue"
},
  "geometry": {"coordinates":[-71.497169,41.818397],"type":"Point"}
}