{
  "type": "Feature",
  "properties": {
    "iso:country":"US",
    "sg:address":"459 Broad St",
    "sg:city":"Cumberland",
    "sg:classifiers":[
        {
            "category":"Personal",
            "subcategory":"Beauty Salon",
            "type":"Services"
        }
    ],
    "sg:phone":"+1 401 721 2271",
    "sg:postcode":"02864",
    "sg:province":"RI",
    "wof:name":"Quick Cut Salon",
    "wof:placetype":"venue"
},
  "geometry": {"coordinates":[-71.39599200000001,41.912091],"type":"Point"}
}