{
  "type": "Feature",
  "properties": {
    "addr:full":"731 Hope St Providence RI 02906",
    "addr:housenumber":"731",
    "addr:postcode":"02906",
    "addr:street":"Hope St",
    "iso:country":"US",
    "sg:address":"731 Hope St",
    "sg:city":"Providence",
    "sg:classifiers":[
        {
            "category":"Personal",
            "subcategory":"Beauty Salon",
            "type":"Services"
        }
    ],
    "sg:phone":"+1 401 751 0230",
    "sg:postcode":"02906",
    "sg:province":"RI",
    "sg:tags":[
        "hair"
    ],
    "wof:name":"Best Little Hair House",
    "wof:placetype":"venue"
},
  "geometry": {"coordinates":[-71.39604,41.846747],"type":"Point"}
}