{
  "type": "Feature",
  "properties": {
    "iso:country":"US",
    "sg:address":"80 Delaine St",
    "sg:city":"Providence",
    "sg:classifiers":[
        {
            "category":"Wholesale",
            "subcategory":"Scrap",
            "type":"Manufacturing & Wholesale Goods"
        }
    ],
    "sg:phone":"+1 401 454 4924",
    "sg:postcode":"02909",
    "sg:province":"RI",
    "sg:tags":[
        "recycling",
        "industrial",
        "metal",
        "center",
        "nonferrous"
    ],
    "wof:name":"Ocean State Metals Inc",
    "wof:placetype":"venue"
},
  "geometry": {"coordinates":[-71.442132,41.819356],"type":"Point"}
}