{
  "type": "Feature",
  "properties": {
    "iso:country":"US",
    "sg:address":"95 Clemence St",
    "sg:city":"Providence",
    "sg:classifiers":[
        {
            "category":"Bars & Pubs",
            "type":"Food & Drink"
        }
    ],
    "sg:phone":"+1 401 276 4244",
    "sg:postcode":"02903",
    "sg:province":"RI",
    "wof:name":"Big Bar",
    "wof:placetype":"venue"
},
  "geometry": {"coordinates":[-71.41279900000001,41.822144],"type":"Point"}
}