{
  "type": "Feature",
  "properties": {
    "addr:full":"56 Spruce St Westerly RI 02891",
    "addr:housenumber":"56",
    "addr:postcode":"02891",
    "addr:street":"Spruce St",
    "iso:country":"US",
    "sg:address":"56 Spruce St",
    "sg:city":"Westerly",
    "sg:classifiers":[
        {
            "category":"Social Services",
            "type":"Services"
        }
    ],
    "sg:phone":"+1 401 596 9276",
    "sg:postcode":"02891",
    "sg:province":"RI",
    "sg:tags":[
        "organization",
        "welfare"
    ],
    "wof:name":"Warm Shelter Inc",
    "wof:placetype":"venue"
},
  "geometry": {"coordinates":[-71.823342,41.382655],"type":"Point"}
}