{
  "type": "Feature",
  "properties": {
    "addr:full":"1229 Westminster St Providence RI 02909",
    "addr:housenumber":"1229",
    "addr:postcode":"02909",
    "addr:street":"Westminster St",
    "iso:country":"US",
    "sg:address":"1229 Westminster St",
    "sg:city":"Providence",
    "sg:classifiers":[
        {
            "category":"Professional",
            "type":"Services"
        }
    ],
    "sg:phone":"+1 401 453 2882",
    "sg:postcode":"02909",
    "sg:province":"RI",
    "sg:tags":[
        "establishment"
    ],
    "wof:name":"Global Crossings",
    "wof:placetype":"venue"
},
  "geometry": {"coordinates":[-71.430038,41.816823],"type":"Point"}
}