{
  "type": "Feature",
  "properties": {
    "iso:country":"US",
    "sg:address":"51 Sockanosset Cross Rd",
    "sg:city":"Cranston",
    "sg:classifiers":[
        {
            "category":"Education",
            "subcategory":"Special Training",
            "type":"Public Place"
        }
    ],
    "sg:phone":"+1 401 785 2666",
    "sg:postcode":"02920",
    "sg:province":"RI",
    "wof:name":"Autism Project of Rhode Island",
    "wof:placetype":"venue"
},
  "geometry": {"coordinates":[-71.45229999999999,41.752724],"type":"Point"}
}