{
  "type": "Feature",
  "properties": {
    "addr:full":"176 6th St Providence RI 02906",
    "addr:housenumber":"176",
    "addr:postcode":"02906",
    "addr:street":"6Th St",
    "iso:country":"US",
    "sg:address":"176 6th St",
    "sg:city":"Providence",
    "sg:classifiers":[
        {
            "category":"Shopping",
            "subcategory":"Clothing, Apparel, & Fashions",
            "type":"Retail Goods"
        }
    ],
    "sg:phone":"+1 401 274 1068",
    "sg:postcode":"02906",
    "sg:province":"RI",
    "wof:name":"Bodytropolis",
    "wof:placetype":"venue"
},
  "geometry": {"coordinates":[-71.394976,41.850999],"type":"Point"}
}