{
  "type": "Feature",
  "properties": {
    "iso:country":"US",
    "sg:address":"2335 Main Rd",
    "sg:city":"Tiverton",
    "sg:classifiers":[
        {
            "category":"Restaurant",
            "type":"Food & Drink"
        }
    ],
    "sg:phone":"+1 401 624 3100",
    "sg:postcode":"02878",
    "sg:province":"RI",
    "wof:name":"Evelyn's Nanaquaket Drive-In",
    "wof:placetype":"venue"
},
  "geometry": {"coordinates":[-71.20321,41.617387],"type":"Point"}
}