{
  "type": "Feature",
  "properties": {
    "iso:country":"US",
    "sg:address":"901 Broad St",
    "sg:city":"Central Falls",
    "sg:classifiers":[
        {
            "category":"Personal",
            "subcategory":"Beauty Salon",
            "type":"Services"
        }
    ],
    "sg:phone":"+1 401 727 8565",
    "sg:postcode":"02863",
    "sg:province":"RI",
    "wof:name":"Sisters Beauty Salon",
    "wof:placetype":"venue"
},
  "geometry": {"coordinates":[-71.387451,41.891935],"type":"Point"}
}