{
  "type": "Feature",
  "properties": {
    "iso:country":"US",
    "sg:address":"583 Fair St",
    "sg:city":"Warwick",
    "sg:classifiers":[
        {
            "category":"Arts & Performance",
            "subcategory":"Theater",
            "type":"Entertainment"
        }
    ],
    "sg:phone":"+1 401 941 3700",
    "sg:postcode":"02888",
    "sg:province":"RI",
    "sg:tags":[
        "band",
        "orchestra"
    ],
    "wof:name":"Moonlighters",
    "wof:placetype":"venue"
},
  "geometry": {"coordinates":[-71.393916,41.747759],"type":"Point"}
}