{
  "type": "Feature",
  "properties": {
    "addr:full":"7630 Post Rd North Kingstown RI 02852",
    "addr:housenumber":"7630",
    "addr:postcode":"02852",
    "addr:street":"Post Rd",
    "iso:country":"US",
    "sg:address":"7630 Post Rd",
    "sg:city":"North Kingstown",
    "sg:classifiers":[
        {
            "category":"Professional",
            "subcategory":"Business Services",
            "type":"Services"
        }
    ],
    "sg:phone":"+1 401 294 1210",
    "sg:postcode":"02852",
    "sg:province":"RI",
    "wof:name":"Delfino & Associates Cpas",
    "wof:placetype":"venue"
},
  "geometry": {"coordinates":[-71.45870600000001,41.585357],"type":"Point"}
}