{
  "type": "Feature",
  "properties": {
    "iso:country":"US",
    "sg:address":"24 What Cheer Rd",
    "sg:city":"Narragansett",
    "sg:classifiers":[
        {
            "category":"Wholesale",
            "subcategory":"Machinery & Supplies",
            "type":"Manufacturing & Wholesale Goods"
        }
    ],
    "sg:phone":"+1 401 284 0213",
    "sg:postcode":"02882",
    "sg:province":"RI",
    "sg:tags":[
        "equipment",
        "industrial"
    ],
    "wof:name":"Hydro Logic Process Eqp LLC",
    "wof:placetype":"venue"
},
  "geometry": {"coordinates":[-71.425552,41.485419],"type":"Point"}
}