{
  "type": "Feature",
  "properties": {
    "iso:country":"US",
    "sg:address":"30 Almy St",
    "sg:city":"Warwick",
    "sg:classifiers":[
        {
            "category":"Education",
            "subcategory":"School",
            "type":"Public Place"
        }
    ],
    "sg:phone":"+1 401 734 3240",
    "sg:postcode":"02886",
    "sg:province":"RI",
    "sg:tags":[
        "elementary"
    ],
    "wof:name":"Lippitt Elementary School",
    "wof:placetype":"venue"
},
  "geometry": {"coordinates":[-71.42303,41.707225],"type":"Point"}
}