{
  "type": "Feature",
  "properties": {
    "iso:country":"US",
    "sg:address":"86 Knight St",
    "sg:city":"Warwick",
    "sg:classifiers":[
        {
            "category":"Freight",
            "type":"Transportation"
        },
        {
            "category":"Utilities",
            "subcategory":"Refuse",
            "type":"Services"
        }
    ],
    "sg:phone":"+1 401 732 6131",
    "sg:postcode":"02886",
    "sg:province":"RI",
    "sg:tags":[
        "construction",
        "garbage",
        "collection"
    ],
    "wof:name":"Roll-A-Way Disposal Inc",
    "wof:placetype":"venue"
},
  "geometry": {"coordinates":[-71.463498,41.729543],"type":"Point"}
}