{
  "type": "Feature",
  "properties": {
    "addr:full":"600 Hopkins Hollow Rd Greene RI 02827",
    "addr:housenumber":"600",
    "addr:postcode":"02827",
    "addr:street":"Hopkins Hollow Rd",
    "iso:country":"US",
    "sg:address":"600 Hopkins Hollow Rd",
    "sg:city":"Greene",
    "sg:classifiers":[
        {
            "category":"Professional",
            "type":"Services"
        }
    ],
    "sg:phone":"+1 401 397 5785",
    "sg:postcode":"02827",
    "sg:province":"RI",
    "sg:tags":[
        "establishment"
    ],
    "wof:name":"Greene Co",
    "wof:placetype":"venue"
},
  "geometry": {"coordinates":[-71.75293499999999,41.67962],"type":"Point"}
}