{
  "type": "Feature",
  "properties": {
    "addr:full":"298 W Exchange St Providence RI 02903",
    "addr:housenumber":"298",
    "addr:postcode":"02903",
    "addr:street":"W Exchange St",
    "iso:country":"US",
    "sg:address":"298 W Exchange St",
    "sg:city":"Providence",
    "sg:classifiers":[
        {
            "category":"Health Services",
            "subcategory":"Health Practitioner",
            "type":"Services"
        }
    ],
    "sg:phone":"+1 401 272 2774",
    "sg:postcode":"02903",
    "sg:province":"RI",
    "sg:tags":[
        "therapy",
        "physical"
    ],
    "wof:name":"Advantage Physical Therapy",
    "wof:placetype":"venue"
},
  "geometry": {"coordinates":[-71.42266600000001,41.825275],"type":"Point"}
}