{
  "type": "Feature",
  "properties": {
    "addr:full":"1193 Tiogue Ave Coventry RI 02816",
    "addr:housenumber":"1193",
    "addr:postcode":"02816",
    "addr:street":"Tiogue Ave",
    "iso:country":"US",
    "sg:address":"1193 Tiogue Ave",
    "sg:city":"Coventry",
    "sg:classifiers":[
        {
            "category":"Education",
            "subcategory":"Special Training",
            "type":"Public Place"
        }
    ],
    "sg:phone":"+1 401 823 0011",
    "sg:postcode":"02816",
    "sg:province":"RI",
    "sg:tags":[
        "tutoring"
    ],
    "wof:name":"Sylvan Learning Ctr",
    "wof:placetype":"venue"
},
  "geometry": {"coordinates":[-71.581631,41.679073],"type":"Point"}
}