{
  "type": "Feature",
  "properties": {
    "iso:country":"US",
    "sg:address":"67 S Fair St",
    "sg:city":"Warwick",
    "sg:classifiers":[
        {
            "category":"Professional",
            "subcategory":"Business Services",
            "type":"Services"
        }
    ],
    "sg:phone":"+1 401 467 5641",
    "sg:postcode":"02888",
    "sg:province":"RI",
    "sg:tags":[
        "handwriting",
        "expert"
    ],
    "wof:name":"Patchis & Wayne",
    "wof:placetype":"venue"
},
  "geometry": {"coordinates":[-71.393384,41.760526],"type":"Point"}
}