{
  "type": "Feature",
  "properties": {
    "iso:country":"US",
    "sg:address":"148 Blackstone Blvd",
    "sg:city":"Providence",
    "sg:classifiers":[
        {
            "category":"Health Services",
            "subcategory":"Doctor",
            "type":"Services"
        }
    ],
    "sg:phone":"+1 401 331 7360",
    "sg:postcode":"02906",
    "sg:province":"RI",
    "sg:tags":[
        "medical"
    ],
    "wof:name":"John S Dziob MD",
    "wof:placetype":"venue"
},
  "geometry": {"coordinates":[-71.38522399999999,41.836851],"type":"Point"}
}