{
  "type": "Feature",
  "properties": {
    "iso:country":"US",
    "sg:address":"90 Weybosset St",
    "sg:city":"Providence",
    "sg:classifiers":[
        {
            "category":"Retail",
            "subcategory":"Auto Rental",
            "type":"Services"
        }
    ],
    "sg:phone":"+1 401 861 4408",
    "sg:postcode":"02903",
    "sg:province":"RI",
    "sg:tags":[
        "renting",
        "automobile",
        "car"
    ],
    "sg:website":"www.enterprise.com",
    "wof:name":"Enterprise Rent A Car",
    "wof:placetype":"venue"
},
  "geometry": {"coordinates":[-71.41036800000001,41.823416],"type":"Point"}
}