{
  "type": "Feature",
  "properties": {
    "addr:full":"562 Broadway Pawtucket RI 02860",
    "addr:housenumber":"562",
    "addr:postcode":"02860",
    "addr:street":"Broadway",
    "iso:country":"US",
    "sg:address":"562 Broadway",
    "sg:city":"Pawtucket",
    "sg:classifiers":[
        {
            "category":"Shopping",
            "subcategory":"Department Store",
            "type":"Retail Goods"
        }
    ],
    "sg:phone":"+1 401 724 7254",
    "sg:postcode":"02860",
    "sg:province":"RI",
    "sg:tags":[
        "shop"
    ],
    "wof:name":"J L Superstores",
    "wof:placetype":"venue"
},
  "geometry": {"coordinates":[-71.37438,41.888446],"type":"Point"}
}