{
  "type": "Feature",
  "properties": {
    "iso:country":"US",
    "sg:address":"55 Claverick St",
    "sg:city":"Providence",
    "sg:classifiers":[
        {
            "category":"Health Services",
            "subcategory":"Doctor",
            "type":"Services"
        }
    ],
    "sg:phone":"+1 401 490 4110",
    "sg:postcode":"02903",
    "sg:province":"RI",
    "wof:name":"Doberstein Curtis E MD",
    "wof:placetype":"venue"
},
  "geometry": {"coordinates":[-71.411903,41.817699],"type":"Point"}
}