{
  "type": "Feature",
  "properties": {
    "addr:full":"172 Pond St Woonsocket RI 02895",
    "addr:housenumber":"172",
    "addr:postcode":"02895",
    "addr:street":"Pond St",
    "iso:country":"US",
    "sg:address":"172 Pond St",
    "sg:city":"Woonsocket",
    "sg:classifiers":[
        {
            "category":"Health Services",
            "subcategory":"Health Practitioner",
            "type":"Services"
        }
    ],
    "sg:phone":"+1 401 765 6363",
    "sg:postcode":"02895",
    "sg:province":"RI",
    "wof:name":"Paul Aubuchon PHD Office",
    "wof:placetype":"venue"
},
  "geometry": {"coordinates":[-71.51064599999999,42.007647],"type":"Point"}
}