{
  "type": "Feature",
  "properties": {
    "iso:country":"US",
    "sg:address":"1400 Oaklawn Ave",
    "sg:city":"Cranston",
    "sg:classifiers":[
        {
            "category":"Shopping",
            "subcategory":"Bicycles & Sporting Goods",
            "type":"Retail Goods"
        }
    ],
    "sg:phone":"+1 401 463 5884",
    "sg:postcode":"02920",
    "sg:province":"RI",
    "sg:tags":[
        "equipment",
        "exercise"
    ],
    "wof:name":"Nordic Track",
    "wof:placetype":"venue"
},
  "geometry": {"coordinates":[-71.47702,41.732336],"type":"Point"}
}