{
  "type": "Feature",
  "properties": {
    "addr:full":"24 Laurel St Ashaway RI 02804",
    "addr:housenumber":"24",
    "addr:postcode":"02804",
    "addr:street":"Laurel St",
    "iso:country":"US",
    "sg:address":"24 Laurel St",
    "sg:city":"Ashaway",
    "sg:classifiers":[
        {
            "category":"Manufacturing",
            "subcategory":"Tools & Machinery",
            "type":"Manufacturing & Wholesale Goods"
        }
    ],
    "sg:phone":"+1 401 377 2221",
    "sg:postcode":"02804",
    "sg:province":"RI",
    "sg:tags":[
        "physician",
        "surgeon"
    ],
    "wof:name":"Ashaway Line & Twine Mfg",
    "wof:placetype":"venue"
},
  "geometry": {"coordinates":[-71.791769,41.4234],"type":"Point"}
}