{
  "type": "Feature",
  "properties": {
    "iso:country":"US",
    "sg:address":"104 Old Tower Hill Rd",
    "sg:city":"Wakefield",
    "sg:classifiers":[
        {
            "category":"Autos & Motor Vehicles",
            "subcategory":"Automobile Sales",
            "type":"Retail Goods"
        }
    ],
    "sg:phone":"+1 401 783 3303",
    "sg:postcode":"02879",
    "sg:province":"RI",
    "sg:tags":[
        "repair",
        "dealer",
        "car",
        "general"
    ],
    "sg:website":"www.speedcraft.com",
    "wof:name":"New Speedcraft Volkswagen",
    "wof:placetype":"venue"
},
  "geometry": {"coordinates":[-71.482608,41.442276],"type":"Point"}
}