{
  "type": "Feature",
  "properties": {
    "addr:full":"960 Broad St Providence RI 02905",
    "addr:housenumber":"960",
    "addr:postcode":"02905",
    "addr:street":"Broad St",
    "iso:country":"US",
    "sg:address":"960 Broad St",
    "sg:city":"Providence",
    "sg:classifiers":[
        {
            "category":"Shopping",
            "subcategory":"Pharmacy",
            "type":"Retail Goods"
        }
    ],
    "sg:phone":"+1 401 461 4383",
    "sg:postcode":"02905",
    "sg:province":"RI",
    "sg:website":"www.cvs.com",
    "wof:name":"CVS Pharmacy",
    "wof:placetype":"venue"
},
  "geometry": {"coordinates":[-71.415466,41.798851],"type":"Point"}
}