{
  "type": "Feature",
  "properties": {
    "iso:country":"US",
    "sg:address":"455 George Washington Hwy",
    "sg:city":"Smithfield",
    "sg:classifiers":[
        {
            "category":"Manufacturing",
            "subcategory":"Metals",
            "type":"Manufacturing & Wholesale Goods"
        }
    ],
    "sg:phone":"+1 401 231 2100",
    "sg:postcode":"02917",
    "sg:province":"RI",
    "sg:tags":[
        "barrels",
        "drum"
    ],
    "sg:website":"www.americancontainernet.com",
    "wof:name":"American Container Net",
    "wof:placetype":"venue"
},
  "geometry": {"coordinates":[-71.49682799999999,41.929187],"type":"Point"}
}