{
  "type": "Feature",
  "properties": {
    "iso:country":"US",
    "sg:address":"124 Washington St",
    "sg:city":"Providence",
    "sg:classifiers":[
        {
            "category":"Communications",
            "subcategory":"Film & Video Production",
            "type":"Services"
        }
    ],
    "sg:phone":"+1 401 523 4222",
    "sg:postcode":"02903",
    "sg:province":"RI",
    "sg:tags":[
        "motion"
    ],
    "wof:name":"A Media LLC",
    "wof:placetype":"venue"
},
  "geometry": {"coordinates":[-71.41542699999999,41.822575],"type":"Point"}
}