{
  "type": "Feature",
  "properties": {
    "addr:full":"1654 Main St West Warwick RI 02893",
    "addr:housenumber":"1654",
    "addr:postcode":"02893",
    "addr:street":"Main St",
    "iso:country":"US",
    "sg:address":"1654 Main St",
    "sg:city":"West Warwick",
    "sg:classifiers":[
        {
            "category":"Manufacturing",
            "subcategory":"Tools & Machinery",
            "type":"Manufacturing & Wholesale Goods"
        }
    ],
    "sg:phone":"+1 401 828 1394",
    "sg:postcode":"02893",
    "sg:province":"RI",
    "sg:tags":[
        "machine",
        "shop",
        "job"
    ],
    "wof:name":"Deery Tool & Engineering Inc",
    "wof:placetype":"venue"
},
  "geometry": {"coordinates":[-71.52257899999999,41.687177],"type":"Point"}
}