{
  "type": "Feature",
  "properties": {
    "addr:full":"19 W Main Rd Middletown RI 02842",
    "addr:housenumber":"19",
    "addr:postcode":"02842",
    "addr:street":"W Main Rd",
    "iso:country":"US",
    "sg:address":"19 W Main Rd",
    "sg:city":"Middletown",
    "sg:classifiers":[
        {
            "category":"Shopping",
            "subcategory":"Clothing, Apparel, & Fashions",
            "type":"Retail Goods"
        }
    ],
    "sg:phone":"+1 401 848 2426",
    "sg:postcode":"02842",
    "sg:province":"RI",
    "sg:tags":[
        "tuxedo"
    ],
    "wof:name":"Roberts Tuxedo Co",
    "wof:placetype":"venue"
},
  "geometry": {"coordinates":[-71.301496,41.506547],"type":"Point"}
}