{
  "type": "Feature",
  "properties": {
    "addr:full":"115 Vandewater St Providence RI 02908",
    "addr:housenumber":"115",
    "addr:postcode":"02908",
    "addr:street":"Vandewater St",
    "iso:country":"US",
    "sg:address":"115 Vandewater St",
    "sg:city":"Providence",
    "sg:classifiers":[
        {
            "category":"Professional",
            "subcategory":"Management & Consulting",
            "type":"Services"
        }
    ],
    "sg:phone":"+1 401 273 1197",
    "sg:postcode":"02908",
    "sg:province":"RI",
    "wof:name":"The Organizer",
    "wof:placetype":"venue"
},
  "geometry": {"coordinates":[-71.43038,41.851524],"type":"Point"}
}