{
  "type": "Feature",
  "properties": {
    "iso:country":"US",
    "sg:address":"55 Bradford St",
    "sg:city":"Providence",
    "sg:classifiers":[
        {
            "category":"Social Services",
            "type":"Services"
        }
    ],
    "sg:phone":"+1 401 421 7472",
    "sg:postcode":"02903",
    "sg:province":"RI",
    "sg:tags":[
        "profit",
        "organization",
        "welfare",
        "volunteer"
    ],
    "wof:name":"Capitol Regions Rsvp",
    "wof:placetype":"venue"
},
  "geometry": {"coordinates":[-71.42184,41.823503],"type":"Point"}
}