{
  "type": "Feature",
  "properties": {
    "addr:full":"38 Bellevue Ave Newport RI 02840",
    "addr:housenumber":"38",
    "addr:postcode":"02840",
    "addr:street":"Bellevue Ave",
    "iso:country":"US",
    "sg:address":"38 Bellevue Ave",
    "sg:city":"Newport",
    "sg:classifiers":[
        {
            "category":"Real Estate",
            "subcategory":"Real Estate Agent",
            "type":"Services"
        }
    ],
    "sg:phone":"+1 401 847 8470",
    "sg:postcode":"02840",
    "sg:province":"RI",
    "wof:name":"J W Riker Suburban Offices",
    "wof:placetype":"venue"
},
  "geometry": {"coordinates":[-71.309082,41.486554],"type":"Point"}
}