{
  "type": "Feature",
  "properties": {
    "addr:full":"499 Hope Furnace Rd Hope RI 02831",
    "addr:housenumber":"499",
    "addr:postcode":"02831",
    "addr:street":"Hope Furnace Rd",
    "iso:country":"US",
    "sg:address":"499 Hope Furnace Rd",
    "sg:city":"Hope",
    "sg:classifiers":[
        {
            "category":"Building & Trades",
            "subcategory":"Construction",
            "type":"Services"
        }
    ],
    "sg:phone":"+1 401 828 8889",
    "sg:postcode":"02831",
    "sg:province":"RI",
    "sg:tags":[
        "house",
        "siding",
        "contractor"
    ],
    "wof:name":"Northeast Siding & Remodeling",
    "wof:placetype":"venue"
},
  "geometry": {"coordinates":[-71.59858199999999,41.728725],"type":"Point"}
}