{
  "type": "Feature",
  "properties": {
    "iso:country":"US",
    "sg:address":"29 Wilcox Ave",
    "sg:city":"Pawtucket",
    "sg:classifiers":[
        {
            "category":"Health Services",
            "subcategory":"Clinic",
            "type":"Services"
        }
    ],
    "sg:phone":"+1 401 723 0353",
    "sg:postcode":"02860",
    "sg:province":"RI",
    "sg:tags":[
        "counseling",
        "mental"
    ],
    "wof:name":"Bettigole Bryna B Psychothrpist",
    "wof:placetype":"venue"
},
  "geometry": {"coordinates":[-71.38659699999999,41.8638],"type":"Point"}
}