{
  "type": "Feature",
  "properties": {
    "iso:country":"US",
    "sg:address":"60 Sea Breeze Ln",
    "sg:city":"Bristol",
    "sg:classifiers":[
        {
            "category":"Building & Trades",
            "subcategory":"Construction",
            "type":"Services"
        }
    ],
    "sg:phone":"+1 401 254 1844",
    "sg:postcode":"02809",
    "sg:province":"RI",
    "sg:tags":[
        "designer",
        "marine",
        "contractor"
    ],
    "wof:name":"Calore Rigging Corp",
    "wof:placetype":"venue"
},
  "geometry": {"coordinates":[-71.286402,41.707086],"type":"Point"}
}