{
  "type": "Feature",
  "properties": {
    "addr:full":"6 W Warwick Ave West Warwick RI 02893",
    "addr:housenumber":"6",
    "addr:postcode":"02893",
    "addr:street":"W Warwick Ave",
    "iso:country":"US",
    "sg:address":"6 W Warwick Ave",
    "sg:city":"West Warwick",
    "sg:classifiers":[
        {
            "category":"Banks & Credit Unions",
            "subcategory":"Bank",
            "type":"Services"
        }
    ],
    "sg:phone":"+1 401 822 3005",
    "sg:postcode":"02893",
    "sg:province":"RI",
    "sg:tags":[
        "loan",
        "real estate"
    ],
    "wof:name":"Associate Mortgage Finders LTD",
    "wof:placetype":"venue"
},
  "geometry": {"coordinates":[-71.53113999999999,41.695523],"type":"Point"}
}