{
  "type": "Feature",
  "properties": {
    "addr:full":"65 Child St Warren RI 02885",
    "addr:housenumber":"65",
    "addr:postcode":"02885",
    "addr:street":"Child St",
    "iso:country":"US",
    "sg:address":"65 Child St",
    "sg:city":"Warren",
    "sg:classifiers":[
        {
            "category":"Ice Cream",
            "type":"Food & Drink"
        }
    ],
    "sg:menulink":"http://www.allmenus.com/ri/warren/224858-dels-frozen-lemonade/menu/",
    "sg:postcode":"02885",
    "sg:province":"RI",
    "sg:tags":[
        "smoothy",
        "juice",
        "american"
    ],
    "wof:name":"Del's Frozen Lemonade",
    "wof:placetype":"venue"
},
  "geometry": {"coordinates":[-71.280232,41.730171],"type":"Point"}
}