{
  "type": "Feature",
  "properties": {
    "addr:full":"259 Thames St Bristol RI 02809",
    "addr:housenumber":"259",
    "addr:postcode":"02809",
    "addr:street":"Thames St",
    "iso:country":"US",
    "sg:address":"259 Thames St",
    "sg:city":"Bristol",
    "sg:classifiers":[
        {
            "category":"Recreation",
            "type":"Entertainment"
        }
    ],
    "sg:phone":"+1 401 253 3811",
    "sg:postcode":"02809",
    "sg:province":"RI",
    "sg:tags":[
        "instruction",
        "yoga"
    ],
    "wof:name":"Core Pilates & Yoga Studio",
    "wof:placetype":"venue"
},
  "geometry": {"coordinates":[-71.277743,41.669202],"type":"Point"}
}