{
  "type": "Feature",
  "properties": {
    "iso:country":"US",
    "sg:address":"6 Cedar Swamp Rd",
    "sg:city":"Smithfield",
    "sg:classifiers":[
        {
            "category":"Retail",
            "subcategory":"Car Wash",
            "type":"Services"
        }
    ],
    "sg:phone":"+1 401 231 1061",
    "sg:postcode":"02917",
    "sg:province":"RI",
    "sg:tags":[
        "carwash"
    ],
    "wof:name":"Apple Valley Car Wash Inc",
    "wof:placetype":"venue"
},
  "geometry": {"coordinates":[-71.53672,41.876985],"type":"Point"}
}