{
  "type": "Feature",
  "properties": {
    "addr:full":"50 Browning Dr North Kingstown RI 02852",
    "addr:housenumber":"50",
    "addr:postcode":"02852",
    "addr:street":"Browning Dr",
    "iso:country":"US",
    "sg:address":"50 Browning Dr",
    "sg:city":"North Kingstown",
    "sg:classifiers":[
        {
            "category":"Real Estate",
            "subcategory":"Architect",
            "type":"Services"
        }
    ],
    "sg:phone":"+1 401 294 9396",
    "sg:postcode":"02852",
    "sg:province":"RI",
    "wof:name":"Heinzmann Architects",
    "wof:placetype":"venue"
},
  "geometry": {"coordinates":[-71.49927700000001,41.58511],"type":"Point"}
}