{
  "type": "Feature",
  "properties": {
    "iso:country":"US",
    "sg:address":"1822 Mineral Spring Ave",
    "sg:city":"North Providence",
    "sg:classifiers":[
        {
            "category":"Health Services",
            "subcategory":"Doctor",
            "type":"Services"
        }
    ],
    "sg:phone":"+1 401 353 4422",
    "sg:postcode":"02904",
    "sg:province":"RI",
    "sg:tags":[
        "practice",
        "family"
    ],
    "wof:name":"Mineral Spring Family Practice",
    "wof:placetype":"venue"
},
  "geometry": {"coordinates":[-71.461502,41.861698],"type":"Point"}
}