{
  "type": "Feature",
  "properties": {
    "addr:full":"82 Winsor Ave Johnston RI 02919",
    "addr:housenumber":"82",
    "addr:postcode":"02919",
    "addr:street":"Winsor Ave",
    "iso:country":"US",
    "sg:address":"82 Winsor Ave",
    "sg:city":"Johnston",
    "sg:classifiers":[
        {
            "category":"Utilities",
            "type":"Services"
        }
    ],
    "sg:phone":"+1 401 949 8069",
    "sg:postcode":"02919",
    "sg:province":"RI",
    "wof:name":"Driveway Dumpster",
    "wof:placetype":"venue"
},
  "geometry": {"coordinates":[-71.55024,41.853931],"type":"Point"}
}