{
  "type": "Feature",
  "properties": {
    "iso:country":"US",
    "sg:address":"50 Asylum Rd",
    "sg:city":"Warren",
    "sg:classifiers":[
        {
            "category":"Education",
            "subcategory":"School",
            "type":"Public Place"
        }
    ],
    "sg:phone":"+1 401 245 1460",
    "sg:postcode":"02885",
    "sg:province":"RI",
    "wof:name":"Hugh Cole Elementary School",
    "wof:placetype":"venue"
},
  "geometry": {"coordinates":[-71.254932,41.725313],"type":"Point"}
}