{
  "type": "Feature",
  "properties": {
    "iso:country":"US",
    "sg:address":"165 Olde Mill Ln",
    "sg:city":"North Kingstown",
    "sg:classifiers":[
        {
            "category":"Professional",
            "subcategory":"Art Services",
            "type":"Services"
        }
    ],
    "sg:phone":"+1 401 884 7433",
    "sg:postcode":"02852",
    "sg:province":"RI",
    "sg:tags":[
        "commercial",
        "design"
    ],
    "wof:name":"Susan Calitri",
    "wof:placetype":"venue"
},
  "geometry": {"coordinates":[-71.478531,41.623136],"type":"Point"}
}