{
  "type": "Feature",
  "properties": {
    "addr:full":"100 Boone St North Kingstown RI 02852",
    "addr:housenumber":"100",
    "addr:postcode":"02852",
    "addr:street":"Boone St",
    "iso:country":"US",
    "sg:address":"100 Boone St",
    "sg:city":"North Kingstown",
    "sg:classifiers":[
        {
            "category":"Education",
            "subcategory":"Library",
            "type":"Public Place"
        }
    ],
    "sg:phone":"+1 401 294 3306",
    "sg:postcode":"02852",
    "sg:province":"RI",
    "sg:website":"www.nklibrary.org",
    "wof:name":"North Kingstown Free Library",
    "wof:placetype":"venue"
},
  "geometry": {"coordinates":[-71.457964,41.568656],"type":"Point"}
}