{
  "type": "Feature",
  "properties": {
    "iso:country":"US",
    "sg:address":"750 East Ave",
    "sg:city":"Pawtucket",
    "sg:classifiers":[
        {
            "category":"Professional",
            "subcategory":"Lawyer & Legal Services",
            "type":"Services"
        }
    ],
    "sg:phone":"+1 401 726 1999",
    "sg:postcode":"02860",
    "sg:province":"RI",
    "wof:name":"Troxell Victoria R",
    "wof:placetype":"venue"
},
  "geometry": {"coordinates":[-71.390618,41.857553],"type":"Point"}
}