{
  "type": "Feature",
  "properties": {
    "iso:country":"US",
    "sg:address":"1589 Putnam Pike",
    "sg:city":"Chepachet",
    "sg:classifiers":[
        {
            "category":"Travel",
            "subcategory":"Campground",
            "type":"Entertainment"
        }
    ],
    "sg:phone":"+1 401 568 3580",
    "sg:postcode":"02814",
    "sg:province":"RI",
    "sg:tags":[
        "camp"
    ],
    "wof:name":"Mater Spei Day Camp",
    "wof:placetype":"venue"
},
  "geometry": {"coordinates":[-71.700468,41.918853],"type":"Point"}
}