{
  "type": "Feature",
  "properties": {
    "iso:country":"US",
    "sg:address":"120 Corliss St",
    "sg:city":"Providence",
    "sg:classifiers":[
        {
            "category":"Wholesale",
            "subcategory":"Medical Equipment & Supplies",
            "type":"Manufacturing & Wholesale Goods"
        }
    ],
    "sg:phone":"+1 401 331 3838",
    "sg:postcode":"02904",
    "sg:province":"RI",
    "sg:tags":[
        "optical",
        "machinery"
    ],
    "sg:website":"http://www.melleroptics.com",
    "wof:name":"Laser Research Optics",
    "wof:placetype":"venue"
},
  "geometry": {"coordinates":[-71.412521,41.84116],"type":"Point"}
}