{
  "type": "Feature",
  "properties": {
    "iso:country":"US",
    "sg:address":"1681 Cranston St",
    "sg:city":"Cranston",
    "sg:classifiers":[
        {
            "category":"Health Services",
            "subcategory":"Medical Lab",
            "type":"Services"
        }
    ],
    "sg:phone":"+1 401 942 2962",
    "sg:postcode":"02920",
    "sg:province":"RI",
    "sg:tags":[
        "laboratory"
    ],
    "wof:name":"Quest Diagnotics",
    "wof:placetype":"venue"
},
  "geometry": {"coordinates":[-71.464658,41.783822],"type":"Point"}
}