{
  "type": "Feature",
  "properties": {
    "iso:country":"US",
    "sg:address":"3520 Post Rd",
    "sg:city":"Warwick",
    "sg:classifiers":[
        {
            "category":"Health Services",
            "subcategory":"Doctor",
            "type":"Services"
        },
        {
            "category":"Health Services",
            "subcategory":"Clinic",
            "type":"Services"
        },
        {
            "category":"Community Center",
            "type":"Public Place"
        }
    ],
    "sg:phone":"+1 401 921 5800",
    "sg:postcode":"02886",
    "sg:province":"RI",
    "sg:tags":[
        "physician",
        "immunology",
        "pediatrics-otorhinolaryngology",
        "medical",
        "allergy",
        "surgeons",
        "otorhinolaryngology",
        "treatment",
        "throat",
        "surgeon",
        "ear",
        "nose"
    ],
    "wof:name":"Ent & Allergy",
    "wof:placetype":"venue"
},
  "geometry": {"coordinates":[-71.456394,41.693254],"type":"Point"}
}