{
  "type": "Feature",
  "properties": {
    "iso:country":"US",
    "sg:address":"130 Seamans St",
    "sg:city":"Providence",
    "sg:classifiers":[
        {
            "category":"Real Estate",
            "subcategory":"Real Estate Services",
            "type":"Services"
        }
    ],
    "sg:phone":"+1 401 255 9594",
    "sg:postcode":"02908",
    "sg:province":"RI",
    "sg:tags":[
        "buyer",
        "broker"
    ],
    "wof:name":"Dober Investment Group, Inc",
    "wof:placetype":"venue"
},
  "geometry": {"coordinates":[-71.438987,41.853338],"type":"Point"}
}