{
  "type": "Feature",
  "properties": {
    "iso:country":"US",
    "sg:address":"3068 E Main Rd",
    "sg:city":"Portsmouth",
    "sg:classifiers":[
        {
            "category":"Freight",
            "type":"Transportation"
        }
    ],
    "sg:phone":"+1 401 272 7979",
    "sg:postcode":"02871",
    "sg:province":"RI",
    "sg:tags":[
        "operator",
        "local",
        "trucking"
    ],
    "wof:name":"Champion Movers",
    "wof:placetype":"venue"
},
  "geometry": {"coordinates":[-71.24627599999999,41.612743],"type":"Point"}
}