{
  "type": "Feature",
  "properties": {
    "iso:country":"US",
    "sg:address":"677 Putnam Pike",
    "sg:city":"Chepachet",
    "sg:classifiers":[
        {
            "category":"Food & Beverages",
            "subcategory":"Liquor & Beverages",
            "type":"Retail Goods"
        }
    ],
    "sg:phone":"+1 401 568 2222",
    "sg:postcode":"02814",
    "sg:province":"RI",
    "wof:name":"Christy's Liquors",
    "wof:placetype":"venue"
},
  "geometry": {"coordinates":[-71.636267,41.904073],"type":"Point"}
}