{
  "type": "Feature",
  "properties": {
    "addr:full":"246 Front St Lincoln RI 02865",
    "addr:housenumber":"246",
    "addr:postcode":"02865",
    "addr:street":"Front St",
    "iso:country":"US",
    "sg:address":"246 Front St",
    "sg:city":"Lincoln",
    "sg:classifiers":[
        {
            "category":"Recreation",
            "type":"Entertainment"
        }
    ],
    "sg:phone":"+1 401 728 1972",
    "sg:postcode":"02865",
    "sg:province":"RI",
    "sg:tags":[
        "martial",
        "arts",
        "instruction"
    ],
    "wof:name":"USA Karate",
    "wof:placetype":"venue"
},
  "geometry": {"coordinates":[-71.409363,41.904129],"type":"Point"}
}