{
  "type": "Feature",
  "properties": {
    "iso:country":"US",
    "sg:address":"1104 Warwick Ave",
    "sg:city":"Warwick",
    "sg:classifiers":[
        {
            "category":"Shopping",
            "subcategory":"Gifts & Souvenirs",
            "type":"Retail Goods"
        }
    ],
    "sg:phone":"+1 401 461 9191",
    "sg:postcode":"02888",
    "sg:province":"RI",
    "wof:name":"Off The Hook",
    "wof:placetype":"venue"
},
  "geometry": {"coordinates":[-71.40643799999999,41.745161],"type":"Point"}
}