{
  "type": "Feature",
  "properties": {
    "addr:full":"30 Freeway Dr Cranston RI 02920",
    "addr:housenumber":"30",
    "addr:postcode":"02920",
    "addr:street":"Freeway Dr",
    "iso:country":"US",
    "sg:address":"30 Freeway Dr",
    "sg:city":"Cranston",
    "sg:classifiers":[
        {
            "category":"Building & Trades",
            "subcategory":"Electrical",
            "type":"Services"
        }
    ],
    "sg:phone":"+1 401 467 2222",
    "sg:postcode":"02920",
    "sg:province":"RI",
    "sg:tags":[
        "electric",
        "contractor"
    ],
    "wof:name":"Reilly Electric",
    "wof:placetype":"venue"
},
  "geometry": {"coordinates":[-71.451193,41.750809],"type":"Point"}
}