{
  "type": "Feature",
  "properties": {
    "iso:country":"US",
    "sg:address":"1120 Toll Gate Rd",
    "sg:city":"Warwick",
    "sg:classifiers":[
        {
            "category":"Shopping",
            "subcategory":"Optical Goods",
            "type":"Retail Goods"
        }
    ],
    "sg:phone":"+1 401 822 2020",
    "sg:postcode":"02886",
    "sg:province":"RI",
    "wof:name":"Richard B Belhumeur Dr",
    "wof:placetype":"venue"
},
  "geometry": {"coordinates":[-71.495705,41.710757],"type":"Point"}
}