{
  "type": "Feature",
  "properties": {
    "addr:full":"16 Wildacre Dr Cranston RI 02920",
    "addr:housenumber":"16",
    "addr:postcode":"02920",
    "addr:street":"Wildacre Dr",
    "iso:country":"US",
    "sg:address":"16 Wildacre Dr",
    "sg:city":"Cranston",
    "sg:classifiers":[
        {
            "category":"Professional",
            "type":"Services"
        }
    ],
    "sg:phone":"+1 401 944 4759",
    "sg:postcode":"02920",
    "sg:province":"RI",
    "wof:name":"145 Newport Ave LLC",
    "wof:placetype":"venue"
},
  "geometry": {"coordinates":[-71.473635,41.749433],"type":"Point"}
}