{
  "type": "Feature",
  "properties": {
    "iso:country":"US",
    "sg:address":"57 Clover Ct",
    "sg:city":"North Kingstown",
    "sg:classifiers":[
        {
            "category":"Food & Beverages",
            "subcategory":"Bakery",
            "type":"Retail Goods"
        }
    ],
    "sg:phone":"+1 401 583 0087",
    "sg:postcode":"02852",
    "sg:province":"RI",
    "sg:tags":[
        "baker"
    ],
    "wof:name":"Beach Bum Don's Inc",
    "wof:placetype":"venue"
},
  "geometry": {"coordinates":[-71.46209500000001,41.559496],"type":"Point"}
}