{
  "type": "Feature",
  "properties": {
    "iso:country":"US",
    "sg:address":"238 Armington St",
    "sg:city":"Cranston",
    "sg:classifiers":[
        {
            "category":"Retail",
            "subcategory":"Repair Shop",
            "type":"Services"
        }
    ],
    "sg:phone":"+1 401 521 6677",
    "sg:postcode":"02905",
    "sg:province":"RI",
    "sg:tags":[
        "upholsterer"
    ],
    "wof:name":"Don L's LTD",
    "wof:placetype":"venue"
},
  "geometry": {"coordinates":[-71.399843,41.78301],"type":"Point"}
}