{
  "type": "Feature",
  "properties": {
    "iso:country":"US",
    "sg:address":"485 Old Greenwich Dr",
    "sg:city":"East Greenwich",
    "sg:classifiers":[
        {
            "category":"Social Services",
            "type":"Services"
        }
    ],
    "sg:phone":"+1 401 885 6278",
    "sg:postcode":"02818",
    "sg:province":"RI",
    "wof:name":"Instant Crisis Communication M",
    "wof:placetype":"venue"
},
  "geometry": {"coordinates":[-71.478644,41.654851],"type":"Point"}
}