{
  "type": "Feature",
  "properties": {
    "iso:country":"US",
    "sg:address":"210 Barton St",
    "sg:city":"Pawtucket",
    "sg:classifiers":[
        {
            "category":"Restaurant",
            "type":"Food & Drink"
        }
    ],
    "sg:phone":"+1 401 722 5467",
    "sg:postcode":"02860",
    "sg:province":"RI",
    "sg:tags":[
        "shop",
        "coffee"
    ],
    "wof:name":"Cimbali Espresso And Cappuccino",
    "wof:placetype":"venue"
},
  "geometry": {"coordinates":[-71.38979399999999,41.881225],"type":"Point"}
}