{
  "type": "Feature",
  "properties": {
    "iso:country":"US",
    "sg:address":"1345 Wampanoag Trl",
    "sg:city":"Riverside",
    "sg:classifiers":[
        {
            "category":"Autos & Motor Vehicles",
            "subcategory":"Fuel & Gas Station",
            "type":"Retail Goods"
        }
    ],
    "sg:phone":"+1 401 437 1669",
    "sg:postcode":"02915",
    "sg:province":"RI",
    "sg:tags":[
        "station",
        "gasoline"
    ],
    "wof:name":"Sonocco",
    "wof:placetype":"venue"
},
  "geometry": {"coordinates":[-71.326908,41.774541],"type":"Point"}
}