{
  "type": "Feature",
  "properties": {
    "iso:country":"US",
    "sg:address":"38 Wilbur Ave",
    "sg:city":"Cranston",
    "sg:classifiers":[
        {
            "category":"Building & Trades",
            "subcategory":"Construction",
            "type":"Services"
        }
    ],
    "sg:phone":"+1 401 943 5161",
    "sg:postcode":"02920",
    "sg:province":"RI",
    "sg:tags":[
        "house"
    ],
    "wof:name":"Bellini Corporation",
    "wof:placetype":"venue"
},
  "geometry": {"coordinates":[-71.48132200000001,41.746997],"type":"Point"}
}