{
  "type": "Feature",
  "properties": {
    "addr:full":"350 Kingstown Rd Narragansett RI 02882",
    "addr:housenumber":"350",
    "addr:postcode":"02882",
    "addr:street":"Kingstown Rd",
    "iso:country":"US",
    "sg:address":"350 Kingstown Rd",
    "sg:city":"Narragansett",
    "sg:classifiers":[
        {
            "category":"Health Services",
            "subcategory":"Doctor",
            "type":"Services"
        }
    ],
    "sg:phone":"+1 401 783 8565",
    "sg:postcode":"02882",
    "sg:province":"RI",
    "sg:tags":[
        "dentist"
    ],
    "wof:name":"Endodontic Associates",
    "wof:placetype":"venue"
},
  "geometry": {"coordinates":[-71.48035299999999,41.434303],"type":"Point"}
}