{
  "type": "Feature",
  "properties": {
    "addr:full":"451 Lapham Farm Rd Pascoag RI 02859",
    "addr:housenumber":"451",
    "addr:postcode":"02859",
    "addr:street":"Lapham Farm Rd",
    "iso:country":"US",
    "sg:address":"451 Lapham Farm Rd",
    "sg:city":"Pascoag",
    "sg:classifiers":[
        {
            "category":"Banks & Credit Unions",
            "subcategory":"Bank",
            "type":"Services"
        }
    ],
    "sg:phone":"+1 401 568 6832",
    "sg:postcode":"02859",
    "sg:province":"RI",
    "sg:tags":[
        "mortgage"
    ],
    "wof:name":"Victory Mortgage Corp",
    "wof:placetype":"venue"
},
  "geometry": {"coordinates":[-71.67537400000001,41.943758],"type":"Point"}
}