{
  "type": "Feature",
  "properties": {
    "addr:full":"117 Reservoir Rd Chepachet RI 02814",
    "addr:housenumber":"117",
    "addr:postcode":"02814",
    "addr:street":"Reservoir Rd",
    "iso:country":"US",
    "sg:address":"117 Reservoir Rd",
    "sg:city":"Chepachet",
    "sg:classifiers":[
        {
            "category":"Government",
            "subcategory":"Office",
            "type":"Public Place"
        }
    ],
    "sg:phone":"+1 401 568 0083",
    "sg:postcode":"02814",
    "sg:province":"RI",
    "sg:tags":[
        "hearing",
        "reporter"
    ],
    "wof:name":"Thomas P Gerseny",
    "wof:placetype":"venue"
},
  "geometry": {"coordinates":[-71.698302,41.924419],"type":"Point"}
}