{
  "type": "Feature",
  "properties": {
    "iso:country":"US",
    "sg:address":"110 King Philip Rd",
    "sg:city":"East Providence",
    "sg:classifiers":[
        {
            "category":"Wholesale",
            "subcategory":"Machinery & Supplies",
            "type":"Manufacturing & Wholesale Goods"
        }
    ],
    "sg:phone":"+1 401 431 0990",
    "sg:postcode":"02916",
    "sg:province":"RI",
    "sg:tags":[
        "equipment",
        "janitorial",
        "glove"
    ],
    "sg:website":"www.ugoldinc.com",
    "wof:name":"Universal Gold Inc.",
    "wof:placetype":"venue"
},
  "geometry": {"coordinates":[-71.365784,41.832535],"type":"Point"}
}