{
  "type": "Feature",
  "properties": {
    "addr:full":"30 Martin St Ste 4A7 Cumberland RI 02864",
    "addr:housenumber":"30",
    "addr:postcode":"02864",
    "addr:street":"Martin St Ste 4A7",
    "iso:country":"US",
    "sg:address":"30 Martin St Ste 4A7",
    "sg:city":"Cumberland",
    "sg:classifiers":[
        {
            "category":"Retail",
            "subcategory":"Repair Shop",
            "type":"Services"
        },
        {
            "category":"Wholesale",
            "subcategory":"Construction Materials",
            "type":"Manufacturing & Wholesale Goods"
        },
        {
            "category":"Building & Trades",
            "subcategory":"Construction",
            "type":"Services"
        }
    ],
    "sg:phone":"+1 401 333 2443",
    "sg:postcode":"02864",
    "sg:province":"RI",
    "sg:tags":[
        "supply",
        "refinish",
        "caning",
        "planning",
        "kitchen",
        "remodeling",
        "furniture"
    ],
    "wof:name":"Richard's Furniture Refinishing",
    "wof:placetype":"venue"
},
  "geometry": {"coordinates":[-71.425725,41.92838],"type":"Point"}
}