{
  "type": "Feature",
  "properties": {
    "iso:country":"US",
    "sg:address":"702 Broad St",
    "sg:city":"Central Falls",
    "sg:classifiers":[
        {
            "category":"Organizations",
            "subcategory":"Religious Organization",
            "type":"Services"
        }
    ],
    "sg:phone":"+1 401 725 5010",
    "sg:postcode":"02863",
    "sg:province":"RI",
    "sg:website":"www.iglesiagetsemani.org",
    "wof:name":"Casa De Oracion Getsemani",
    "wof:placetype":"venue"
},
  "geometry": {"coordinates":[-71.387356,41.888992],"type":"Point"}
}