{
  "type": "Feature",
  "properties": {
    "iso:country":"US",
    "sg:address":"747 Main St",
    "sg:city":"Warren",
    "sg:classifiers":[
        {
            "category":"Food & Beverages",
            "subcategory":"Groceries & Convenience Stores",
            "type":"Retail Goods"
        }
    ],
    "sg:phone":"+1 401 245 9438",
    "sg:postcode":"02885",
    "sg:province":"RI",
    "wof:name":"Super Mart",
    "wof:placetype":"venue"
},
  "geometry": {"coordinates":[-71.28146700000001,41.723981],"type":"Point"}
}