{
  "type": "Feature",
  "properties": {
    "addr:full":"599 Arnold Rd Coventry RI 02816",
    "addr:housenumber":"599",
    "addr:postcode":"02816",
    "addr:street":"Arnold Rd",
    "iso:country":"US",
    "sg:address":"599 Arnold Rd",
    "sg:city":"Coventry",
    "sg:classifiers":[
        {
            "category":"Real Estate",
            "subcategory":"Real Estate Agent",
            "type":"Services"
        }
    ],
    "sg:phone":"+1 401 615 2306",
    "sg:postcode":"02816",
    "sg:province":"RI",
    "wof:name":"Home Work Realty",
    "wof:placetype":"venue"
},
  "geometry": {"coordinates":[-71.546987,41.66609],"type":"Point"}
}