{
  "type": "Feature",
  "properties": {
    "iso:country":"US",
    "sg:address":"128 Main St",
    "sg:city":"Woonsocket",
    "sg:classifiers":[
        {
            "category":"Personal",
            "subcategory":"Beauty Salon",
            "type":"Services"
        }
    ],
    "sg:phone":"+1 401 766 3966",
    "sg:postcode":"02895",
    "sg:province":"RI",
    "sg:tags":[
        "shop"
    ],
    "wof:name":"Mane Event Hair Salon",
    "wof:placetype":"venue"
},
  "geometry": {"coordinates":[-71.513997,42.002725],"type":"Point"}
}