{
  "type": "Feature",
  "properties": {
    "addr:full":"42 Charlesfield St Providence RI 02906",
    "addr:housenumber":"42",
    "addr:postcode":"02906",
    "addr:street":"Charlesfield St",
    "iso:country":"US",
    "sg:address":"42 Charlesfield St",
    "sg:city":"Providence",
    "sg:classifiers":[
        {
            "category":"Organizations",
            "subcategory":"Community Association",
            "type":"Services"
        }
    ],
    "sg:phone":"+1 401 421 0270",
    "sg:postcode":"02906",
    "sg:province":"RI",
    "sg:tags":[
        "drinking"
    ],
    "wof:name":"Gcb",
    "wof:placetype":"venue"
},
  "geometry": {"coordinates":[-71.40201,41.823671],"type":"Point"}
}