{
  "type": "Feature",
  "properties": {
    "iso:country":"US",
    "sg:address":"1717 Ten Rod Rd",
    "sg:city":"North Kingstown",
    "sg:classifiers":[
        {
            "category":"Food & Beverages",
            "subcategory":"Groceries & Convenience Stores",
            "type":"Retail Goods"
        }
    ],
    "sg:phone":"+1 401 295 5106",
    "sg:postcode":"02852",
    "sg:province":"RI",
    "wof:name":"Oatley's Convenience Store",
    "wof:placetype":"venue"
},
  "geometry": {"coordinates":[-71.51583599999999,41.576198],"type":"Point"}
}