{
  "type": "Feature",
  "properties": {
    "iso:country":"US",
    "sg:address":"67 Winthrop Rd",
    "sg:city":"Warwick",
    "sg:classifiers":[
        {
            "category":"Building & Trades",
            "subcategory":"Construction",
            "type":"Services"
        }
    ],
    "sg:phone":"+1 401 785 2398",
    "sg:postcode":"02888",
    "sg:province":"RI",
    "sg:tags":[
        "hanging",
        "contractor"
    ],
    "wof:name":"Harold Breedon Jr Painting",
    "wof:placetype":"venue"
},
  "geometry": {"coordinates":[-71.3874,41.753921],"type":"Point"}
}