{
  "type": "Feature",
  "properties": {
    "iso:country":"US",
    "sg:address":"30 Orchard Meadows Dr",
    "sg:city":"Smithfield",
    "sg:classifiers":[
        {
            "category":"Shopping",
            "subcategory":"Clothing, Apparel, & Fashions",
            "type":"Retail Goods"
        }
    ],
    "sg:phone":"+1 401 273 3737",
    "sg:postcode":"02917",
    "sg:province":"RI",
    "wof:name":"Circa Viso",
    "wof:placetype":"venue"
},
  "geometry": {"coordinates":[-71.49283,41.909223],"type":"Point"}
}