{
  "type": "Feature",
  "properties": {
    "addr:full":"95 Hathaway St Providence RI 02907",
    "addr:housenumber":"95",
    "addr:postcode":"02907",
    "addr:street":"Hathaway St",
    "iso:country":"US",
    "sg:address":"95 Hathaway St",
    "sg:city":"Providence",
    "sg:classifiers":[
        {
            "category":"Retail",
            "subcategory":"Repair Shop",
            "type":"Services"
        },
        {
            "category":"Wholesale",
            "subcategory":"Jewelry",
            "type":"Manufacturing & Wholesale Goods"
        }
    ],
    "sg:phone":"+1 401 461 2620",
    "sg:postcode":"02907",
    "sg:province":"RI",
    "sg:tags":[
        "contractor"
    ],
    "wof:name":"Song Jewelry Inc",
    "wof:placetype":"venue"
},
  "geometry": {"coordinates":[-71.421639,41.776738],"type":"Point"}
}