{
  "type": "Feature",
  "properties": {
    "iso:country":"US",
    "sg:address":"53 Amflex Dr",
    "sg:city":"Cranston",
    "sg:classifiers":[
        {
            "category":"Wholesale",
            "subcategory":"Plants",
            "type":"Manufacturing & Wholesale Goods"
        }
    ],
    "sg:phone":"+1 401 751 4333",
    "sg:postcode":"02921",
    "sg:province":"RI",
    "sg:tags":[
        "florist"
    ],
    "wof:name":"Bay State & Johnson",
    "wof:placetype":"venue"
},
  "geometry": {"coordinates":[-71.511421,41.786043],"type":"Point"}
}