{
  "type": "Feature",
  "properties": {
    "addr:full":"570 Pontiac Ave Cranston RI 02910",
    "addr:housenumber":"570",
    "addr:postcode":"02910",
    "addr:street":"Pontiac Ave",
    "iso:country":"US",
    "sg:address":"570 Pontiac Ave",
    "sg:city":"Cranston",
    "sg:classifiers":[
        {
            "category":"Shopping",
            "subcategory":"Pharmacy",
            "type":"Retail Goods"
        }
    ],
    "sg:phone":"+1 401 781 6360",
    "sg:postcode":"02910",
    "sg:province":"RI",
    "sg:website":"www.brooks-rx.com",
    "wof:name":"Brooks Pharmacy",
    "wof:placetype":"venue"
},
  "geometry": {"coordinates":[-71.436885,41.772211],"type":"Point"}
}