{
  "type": "Feature",
  "properties": {
    "iso:country":"US",
    "sg:address":"164 Centerville Rd",
    "sg:city":"Warwick",
    "sg:classifiers":[
        {
            "category":"Real Estate",
            "subcategory":"Developer",
            "type":"Services"
        }
    ],
    "sg:phone":"+1 401 737 2508",
    "sg:postcode":"02886",
    "sg:province":"RI",
    "wof:name":"420 Corporation",
    "wof:placetype":"venue"
},
  "geometry": {"coordinates":[-71.46641,41.69764],"type":"Point"}
}