{
  "type": "Feature",
  "properties": {
    "addr:full":"26 Shore Rd Westerly RI 02891",
    "addr:housenumber":"26",
    "addr:postcode":"02891",
    "addr:street":"Shore Rd",
    "iso:country":"US",
    "sg:address":"26 Shore Rd",
    "sg:city":"Westerly",
    "sg:classifiers":[
        {
            "category":"Communications",
            "subcategory":"Film & Video Production",
            "type":"Services"
        }
    ],
    "sg:phone":"+1 401 596 6271",
    "sg:postcode":"02891",
    "sg:province":"RI",
    "sg:tags":[
        "motion"
    ],
    "wof:name":"Pettys Productions",
    "wof:placetype":"venue"
},
  "geometry": {"coordinates":[-71.82468900000001,41.326823],"type":"Point"}
}