{
  "type": "Feature",
  "properties": {
    "addr:full":"6 Pawtucket Ave Bristol RI 02809",
    "addr:housenumber":"6",
    "addr:postcode":"02809",
    "addr:street":"Pawtucket Ave",
    "iso:country":"US",
    "sg:address":"6 Pawtucket Ave",
    "sg:city":"Bristol",
    "sg:classifiers":[
        {
            "category":"Building & Trades",
            "subcategory":"Construction",
            "type":"Services"
        }
    ],
    "sg:phone":"+1 401 253 7313",
    "sg:postcode":"02809",
    "sg:province":"RI",
    "sg:tags":[
        "designer"
    ],
    "wof:name":"Product Design & Devmnt Inc",
    "wof:placetype":"venue"
},
  "geometry": {"coordinates":[-71.25913199999999,41.71313],"type":"Point"}
}