{
  "type": "Feature",
  "properties": {
    "iso:country":"US",
    "sg:address":"70 Jefferson Blvd",
    "sg:city":"Warwick",
    "sg:classifiers":[
        {
            "category":"Professional",
            "subcategory":"Lawyer & Legal Services",
            "type":"Services"
        }
    ],
    "sg:phone":"+1 401 785 4400",
    "sg:postcode":"02888",
    "sg:province":"RI",
    "wof:name":"Modonna & Thomas",
    "wof:placetype":"venue"
},
  "geometry": {"coordinates":[-71.435203,41.752417],"type":"Point"}
}