{
  "type": "Feature",
  "properties": {
    "addr:full":"85 Old Rose Hill Rd Wakefield RI 02879",
    "addr:housenumber":"85",
    "addr:postcode":"02879",
    "addr:street":"Old Rose Hill Rd",
    "iso:country":"US",
    "sg:address":"85 Old Rose Hill Rd",
    "sg:city":"Wakefield",
    "sg:classifiers":[
        {
            "category":"Building & Trades",
            "subcategory":"Construction",
            "type":"Services"
        }
    ],
    "sg:phone":"+1 401 783 0226",
    "sg:postcode":"02879",
    "sg:province":"RI",
    "sg:tags":[
        "nonresidential"
    ],
    "wof:name":"Accent Builders Inc",
    "wof:placetype":"venue"
},
  "geometry": {"coordinates":[-71.49825300000001,41.485647],"type":"Point"}
}