{
  "type": "Feature",
  "properties": {
    "iso:country":"US",
    "sg:address":"7 Cedar Path",
    "sg:city":"Lincoln",
    "sg:classifiers":[
        {
            "category":"Professional",
            "type":"Services"
        }
    ],
    "sg:phone":"+1 401 723 9153",
    "sg:postcode":"02865",
    "sg:province":"RI",
    "wof:name":"Wallace Young",
    "wof:placetype":"venue"
},
  "geometry": {"coordinates":[-71.462935,41.887377],"type":"Point"}
}