{
  "type": "Feature",
  "properties": {
    "addr:full":"445 Putnam Pike Greenville RI 02828",
    "addr:housenumber":"445",
    "addr:postcode":"02828",
    "addr:street":"Putnam Pike",
    "iso:country":"US",
    "sg:address":"445 Putnam Pike",
    "sg:city":"Greenville",
    "sg:classifiers":[
        {
            "category":"Restaurant",
            "type":"Food & Drink"
        }
    ],
    "sg:phone":"+1 401 231 6600",
    "sg:postcode":"02828",
    "sg:province":"RI",
    "sg:website":"www.subway.com",
    "wof:name":"Subway Sandwiches & Salads",
    "wof:placetype":"venue"
},
  "geometry": {"coordinates":[-71.52804999999999,41.870134],"type":"Point"}
}