{
  "type": "Feature",
  "properties": {
    "addr:full":"1839 Smith St North Providence RI 02911",
    "addr:housenumber":"1839",
    "addr:postcode":"02911",
    "addr:street":"Smith St",
    "iso:country":"US",
    "sg:address":"1839 Smith St",
    "sg:city":"North Providence",
    "sg:classifiers":[
        {
            "category":"Wholesale",
            "subcategory":"Fruits & Vegetables",
            "type":"Manufacturing & Wholesale Goods"
        }
    ],
    "sg:phone":"+1 401 231 4766",
    "sg:postcode":"02911",
    "sg:province":"RI",
    "sg:tags":[
        "veggie"
    ],
    "wof:name":"Simply Seasonal",
    "wof:placetype":"venue"
},
  "geometry": {"coordinates":[-71.47329000000001,41.854831],"type":"Point"}
}