{
  "type": "Feature",
  "properties": {
    "iso:country":"US",
    "sg:address":"63 Sulyma St",
    "sg:city":"Cumberland",
    "sg:classifiers":[
        {
            "category":"Arts & Performance",
            "subcategory":"Theater",
            "type":"Entertainment"
        }
    ],
    "sg:phone":"+1 401 439 3272",
    "sg:postcode":"02864",
    "sg:province":"RI",
    "sg:tags":[
        "live",
        "music"
    ],
    "wof:name":"Master Audio Works & Fuel",
    "wof:placetype":"venue"
},
  "geometry": {"coordinates":[-71.459677,41.970574],"type":"Point"}
}