{
  "type": "Feature",
  "properties": {
    "iso:country":"US",
    "sg:address":"605 Broadway",
    "sg:city":"Pawtucket",
    "sg:classifiers":[
        {
            "category":"Bars & Pubs",
            "type":"Food & Drink"
        }
    ],
    "sg:phone":"+1 401 723 2970",
    "sg:postcode":"02860",
    "sg:province":"RI",
    "wof:name":"Jim's Bar & Grill",
    "wof:placetype":"venue"
},
  "geometry": {"coordinates":[-71.37366299999999,41.889531],"type":"Point"}
}