{
  "type": "Feature",
  "properties": {
    "addr:full":"1310 Jefferson Blvd Warwick RI 02886",
    "addr:housenumber":"1310",
    "addr:postcode":"02886",
    "addr:street":"Jefferson Blvd",
    "iso:country":"US",
    "sg:address":"1310 Jefferson Blvd",
    "sg:city":"Warwick",
    "sg:classifiers":[
        {
            "category":"Retail",
            "subcategory":"Auto Repair",
            "type":"Services"
        }
    ],
    "sg:phone":"+1 401 732 3200",
    "sg:postcode":"02886",
    "sg:province":"RI",
    "sg:tags":[
        "wrecker"
    ],
    "wof:name":"City Towing Inc",
    "wof:placetype":"venue"
},
  "geometry": {"coordinates":[-71.44842,41.712922],"type":"Point"}
}