{
  "type": "Feature",
  "properties": {
    "iso:country":"US",
    "sg:address":"708 Providence St",
    "sg:city":"Woonsocket",
    "sg:classifiers":[
        {
            "category":"Building & Trades",
            "subcategory":"Construction",
            "type":"Services"
        }
    ],
    "sg:phone":"+1 401 766 8453",
    "sg:postcode":"02895",
    "sg:province":"RI",
    "sg:tags":[
        "tile",
        "dealer"
    ],
    "wof:name":"Brien Tile Co",
    "wof:placetype":"venue"
},
  "geometry": {"coordinates":[-71.522018,41.98737],"type":"Point"}
}