{
  "type": "Feature",
  "properties": {
    "iso:country":"US",
    "sg:address":"16 Roxbury Rd",
    "sg:city":"Narragansett",
    "sg:classifiers":[
        {
            "category":"Building & Trades",
            "subcategory":"Plumbing",
            "type":"Services"
        }
    ],
    "sg:phone":"+1 401 792 8406",
    "sg:postcode":"02882",
    "sg:province":"RI",
    "sg:tags":[
        "air",
        "heating",
        "contractor"
    ],
    "wof:name":"Byrne Mechanical Inc",
    "wof:placetype":"venue"
},
  "geometry": {"coordinates":[-71.41897299999999,41.481817],"type":"Point"}
}