{
  "type": "Feature",
  "properties": {
    "iso:country":"US",
    "sg:address":"75 Hamilton Gate Ct",
    "sg:city":"North Kingstown",
    "sg:classifiers":[
        {
            "category":"Manufacturing",
            "subcategory":"Jewelry",
            "type":"Manufacturing & Wholesale Goods"
        }
    ],
    "sg:phone":"+1 401 295 8737",
    "sg:postcode":"02852",
    "sg:province":"RI",
    "sg:tags":[
        "precious",
        "metal",
        "mfg"
    ],
    "wof:name":"CW Richards",
    "wof:placetype":"venue"
},
  "geometry": {"coordinates":[-71.440923,41.542004],"type":"Point"}
}