{
  "type": "Feature",
  "properties": {
    "addr:full":"2077 Diamond Hill Rd Cumberland RI 02864",
    "addr:housenumber":"2077",
    "addr:postcode":"02864",
    "addr:street":"Diamond Hill Rd",
    "iso:country":"US",
    "sg:address":"2077 Diamond Hill Rd",
    "sg:city":"Cumberland",
    "sg:classifiers":[
        {
            "category":"Food & Beverages",
            "subcategory":"Groceries & Convenience Stores",
            "type":"Retail Goods"
        }
    ],
    "sg:phone":"+1 401 334 9362",
    "sg:postcode":"02864",
    "sg:province":"RI",
    "wof:name":"Daves Fruitland of Cumberland",
    "wof:placetype":"venue"
},
  "geometry": {"coordinates":[-71.403616,41.946086],"type":"Point"}
}