{
  "type": "Feature",
  "properties": {
    "iso:country":"US",
    "sg:address":"247 Thayer St",
    "sg:city":"Providence",
    "sg:classifiers":[
        {
            "category":"Food & Beverages",
            "subcategory":"Groceries & Convenience Stores",
            "type":"Retail Goods"
        }
    ],
    "sg:phone":"+1 401 831 9229",
    "sg:postcode":"02906",
    "sg:province":"RI",
    "wof:name":"Store 24 Inc",
    "wof:placetype":"venue"
},
  "geometry": {"coordinates":[-71.400679,41.828435],"type":"Point"}
}