{
  "type": "Feature",
  "properties": {
    "iso:country":"US",
    "sg:address":"151 Berkeley St",
    "sg:city":"East Providence",
    "sg:classifiers":[
        {
            "category":"Building & Trades",
            "subcategory":"Cleaning & Sanitation",
            "type":"Services"
        }
    ],
    "sg:phone":"+1 401 435 6611",
    "sg:postcode":"02914",
    "sg:province":"RI",
    "sg:tags":[
        "janitor",
        "maintenance"
    ],
    "wof:name":"New England Janitorial Svcs",
    "wof:placetype":"venue"
},
  "geometry": {"coordinates":[-71.37617899999999,41.810973],"type":"Point"}
}