{
  "type": "Feature",
  "properties": {
    "iso:country":"US",
    "sg:address":"339 Market St",
    "sg:city":"Warren",
    "sg:classifiers":[
        {
            "category":"Wholesale",
            "subcategory":"Plants",
            "type":"Manufacturing & Wholesale Goods"
        }
    ],
    "sg:phone":"+1 401 245 1738",
    "sg:postcode":"02885",
    "sg:province":"RI",
    "wof:name":"A & M Greenhouses",
    "wof:placetype":"venue"
},
  "geometry": {"coordinates":[-71.27322700000001,41.74298],"type":"Point"}
}