{
  "type": "Feature",
  "properties": {
    "addr:full":"Ashaway Bradford Rd Bradford RI 02808",
    "addr:postcode":"02808",
    "addr:street":"Bradford Rd",
    "iso:country":"US",
    "sg:address":"Ashaway Bradford Rd",
    "sg:city":"Bradford",
    "sg:classifiers":[
        {
            "category":"Food & Beverages",
            "subcategory":"Groceries & Convenience Stores",
            "type":"Retail Goods"
        }
    ],
    "sg:phone":"+1 401 377 8109",
    "sg:postcode":"02808",
    "sg:province":"RI",
    "wof:name":"Pete's Grocery",
    "wof:placetype":"venue"
},
  "geometry": {"coordinates":[-71.748299,41.407398],"type":"Point"}
}