{
  "type": "Feature",
  "properties": {
    "iso:country":"US",
    "sg:address":"243 Crescent Ave",
    "sg:city":"Cranston",
    "sg:classifiers":[
        {
            "category":"Real Estate",
            "subcategory":"Real Estate Operator",
            "type":"Services"
        }
    ],
    "sg:phone":"+1 401 433 3100",
    "sg:postcode":"02910",
    "sg:province":"RI",
    "sg:tags":[
        "for",
        "housing",
        "elderly",
        "manages",
        "subsidized",
        "owns"
    ],
    "wof:name":"Crescent Park Manor",
    "wof:placetype":"venue"
},
  "geometry": {"coordinates":[-71.4447,41.785516],"type":"Point"}
}