{
  "type": "Feature",
  "properties": {
    "iso:country":"US",
    "sg:address":"591 Beverage Hill Ave",
    "sg:city":"Pawtucket",
    "sg:classifiers":[
        {
            "category":"Manufacturing",
            "subcategory":"Printing",
            "type":"Manufacturing & Wholesale Goods"
        }
    ],
    "sg:phone":"+1 401 725 2971",
    "sg:postcode":"02861",
    "sg:province":"RI",
    "sg:tags":[
        "commercial",
        "printer",
        "lithographic"
    ],
    "wof:name":"Flash Instant Print",
    "wof:placetype":"venue"
},
  "geometry": {"coordinates":[-71.355431,41.860867],"type":"Point"}
}