{
  "type": "Feature",
  "properties": {
    "iso:country":"US",
    "sg:address":"185 Jefferson Blvd",
    "sg:city":"Warwick",
    "sg:classifiers":[
        {
            "category":"Manufacturing",
            "subcategory":"Jewelry",
            "type":"Manufacturing & Wholesale Goods"
        }
    ],
    "sg:phone":"+1 401 738 1227",
    "sg:postcode":"02888",
    "sg:province":"RI",
    "sg:tags":[
        "precious",
        "metal",
        "findings",
        "manufacturer"
    ],
    "wof:name":"Prime Time Mfg Inc",
    "wof:placetype":"venue"
},
  "geometry": {"coordinates":[-71.438863,41.740483],"type":"Point"}
}