{
  "type": "Feature",
  "properties": {
    "iso:country":"US",
    "sg:address":"20 Paull St",
    "sg:city":"Bristol",
    "sg:classifiers":[
        {
            "category":"Building & Trades",
            "subcategory":"Landscaping Services",
            "type":"Services"
        }
    ],
    "sg:phone":"+1 401 253 6426",
    "sg:postcode":"02809",
    "sg:province":"RI",
    "sg:tags":[
        "landscape",
        "contractor"
    ],
    "wof:name":"Ramsay's Inc",
    "wof:placetype":"venue"
},
  "geometry": {"coordinates":[-71.276765,41.682065],"type":"Point"}
}