{
  "type": "Feature",
  "properties": {
    "iso:country":"US",
    "sg:address":"90 Rolfe Sq",
    "sg:city":"Cranston",
    "sg:classifiers":[
        {
            "category":"Restaurant",
            "type":"Food & Drink"
        }
    ],
    "sg:phone":"+1 401 461 0646",
    "sg:postcode":"02910",
    "sg:province":"RI",
    "sg:tags":[
        "asian",
        "chinese",
        "pan"
    ],
    "sg:website":"http://www.kingsgardenrestaurant.com",
    "wof:name":"King's Garden Restaurant",
    "wof:placetype":"venue"
},
  "geometry": {"coordinates":[-71.437006,41.775303],"type":"Point"}
}