{
  "type": "Feature",
  "properties": {
    "iso:country":"US",
    "sg:address":"39 Touro St",
    "sg:city":"Newport",
    "sg:classifiers":[
        {
            "category":"Travel",
            "subcategory":"Travel Agent",
            "type":"Entertainment"
        }
    ],
    "sg:phone":"+1 401 848 0300",
    "sg:postcode":"02840",
    "sg:province":"RI",
    "sg:tags":[
        "operator",
        "tour",
        "agency"
    ],
    "sg:website":"www.innnewport.com",
    "wof:name":"Taylor-Made Reservations",
    "wof:placetype":"venue"
},
  "geometry": {"coordinates":[-71.314673,41.489777],"type":"Point"}
}