{
  "type": "Feature",
  "properties": {
    "iso:country":"US",
    "sg:address":"150 Waterman St",
    "sg:city":"Providence",
    "sg:classifiers":[
        {
            "category":"Social Services",
            "subcategory":"Child Care",
            "type":"Services"
        }
    ],
    "sg:phone":"+1 401 273 5151",
    "sg:postcode":"02906",
    "sg:province":"RI",
    "sg:tags":[
        "elementary",
        "school"
    ],
    "sg:website":"www.angelcaremontessori.com",
    "wof:name":"Angel Care Montessori",
    "wof:placetype":"venue"
},
  "geometry": {"coordinates":[-71.396202,41.827499],"type":"Point"}
}