{
  "type": "Feature",
  "properties": {
    "addr:full":"1 Chestnut St Providence RI 02903",
    "addr:housenumber":"1",
    "addr:postcode":"02903",
    "addr:street":"Chestnut St",
    "iso:country":"US",
    "sg:address":"1 Chestnut St",
    "sg:city":"Providence",
    "sg:classifiers":[
        {
            "category":"Manufacturing",
            "subcategory":"Retail Goods",
            "type":"Manufacturing & Wholesale Goods"
        }
    ],
    "sg:phone":"+1 401 277 2453",
    "sg:postcode":"02903",
    "sg:province":"RI",
    "sg:tags":[
        "assembly",
        "fabricating"
    ],
    "wof:name":"Bike Tech",
    "wof:placetype":"venue"
},
  "geometry": {"coordinates":[-71.412933,41.819438],"type":"Point"}
}