{
  "type": "Feature",
  "properties": {
    "addr:full":"95 Commercial Way East Providence RI 02914",
    "addr:housenumber":"95",
    "addr:postcode":"02914",
    "addr:street":"Commercial Way",
    "iso:country":"US",
    "sg:address":"95 Commercial Way",
    "sg:city":"East Providence",
    "sg:classifiers":[
        {
            "category":"Freight",
            "type":"Transportation"
        }
    ],
    "sg:phone":"+1 401 435 0028",
    "sg:postcode":"02914",
    "sg:province":"RI",
    "sg:tags":[
        "commercial",
        "storage",
        "general"
    ],
    "wof:name":"Lionel Mini Storage Inc",
    "wof:placetype":"venue"
},
  "geometry": {"coordinates":[-71.34837899999999,41.81972],"type":"Point"}
}