{
  "type": "Feature",
  "properties": {
    "iso:country":"US",
    "sg:address":"9 Horta Dr",
    "sg:city":"West Warwick",
    "sg:classifiers":[
        {
            "category":"Building & Trades",
            "subcategory":"Cleaning & Sanitation",
            "type":"Services"
        }
    ],
    "sg:phone":"+1 401 828 3860",
    "sg:postcode":"02893",
    "sg:province":"RI",
    "sg:tags":[
        "maintenance"
    ],
    "wof:name":"Howard Realty Inc",
    "wof:placetype":"venue"
},
  "geometry": {"coordinates":[-71.517866,41.729887],"type":"Point"}
}