{
  "type": "Feature",
  "properties": {
    "addr:full":"410 Tiogue Ave Coventry RI 02816",
    "addr:housenumber":"410",
    "addr:postcode":"02816",
    "addr:street":"Tiogue Ave",
    "iso:country":"US",
    "sg:address":"410 Tiogue Ave",
    "sg:city":"Coventry",
    "sg:classifiers":[
        {
            "category":"Utilities",
            "subcategory":"Mobile Phone",
            "type":"Services"
        }
    ],
    "sg:phone":"+1 401 615 0271",
    "sg:postcode":"02816",
    "sg:province":"RI",
    "sg:tags":[
        "telephone",
        "cellular"
    ],
    "wof:name":"Phone Booth",
    "wof:placetype":"venue"
},
  "geometry": {"coordinates":[-71.545906,41.683993],"type":"Point"}
}