{
  "type": "Feature",
  "properties": {
    "iso:country":"US",
    "sg:address":"12 Carter St",
    "sg:city":"Providence",
    "sg:classifiers":[
        {
            "category":"Education",
            "subcategory":"School",
            "type":"Public Place"
        }
    ],
    "sg:phone":"+1 401 467 9777",
    "sg:postcode":"02907",
    "sg:province":"RI",
    "sg:tags":[
        "organization",
        "religious"
    ],
    "wof:name":"Sam Miguel Education Center",
    "wof:placetype":"venue"
},
  "geometry": {"coordinates":[-71.426891,41.80009],"type":"Point"}
}