{
  "type": "Feature",
  "properties": {
    "iso:country":"US",
    "sg:address":"39 Pierce St",
    "sg:city":"Westerly",
    "sg:classifiers":[
        {
            "category":"Retail",
            "subcategory":"Repair Shop",
            "type":"Services"
        }
    ],
    "sg:phone":"+1 401 596 6556",
    "sg:postcode":"02891",
    "sg:province":"RI",
    "sg:tags":[
        "upholsterer"
    ],
    "wof:name":"Nick Upholstery Co",
    "wof:placetype":"venue"
},
  "geometry": {"coordinates":[-71.82708100000001,41.386976],"type":"Point"}
}