{
  "type": "Feature",
  "properties": {
    "iso:country":"US",
    "sg:address":"225 Main St",
    "sg:city":"Pawtucket",
    "sg:classifiers":[
        {
            "category":"Professional",
            "subcategory":"Lawyer & Legal Services",
            "type":"Services"
        }
    ],
    "sg:phone":"+1 401 722 8900",
    "sg:postcode":"02860",
    "sg:province":"RI",
    "sg:tags":[
        "attorney"
    ],
    "wof:name":"Moretti & Perlow Law Offices",
    "wof:placetype":"venue"
},
  "geometry": {"coordinates":[-71.38519700000001,41.877494],"type":"Point"}
}