{
  "type": "Feature",
  "properties": {
    "iso:country":"US",
    "sg:address":"982 Tiogue Ave",
    "sg:city":"Coventry",
    "sg:classifiers":[
        {
            "category":"Health Services",
            "subcategory":"Hospital",
            "type":"Services"
        }
    ],
    "sg:phone":"+1 401 615 7255",
    "sg:postcode":"02816",
    "sg:province":"RI",
    "sg:tags":[
        "treatment",
        "psychiatric",
        "facility"
    ],
    "wof:name":"Angel Street Psychiatry",
    "wof:placetype":"venue"
},
  "geometry": {"coordinates":[-71.575603,41.679762],"type":"Point"}
}