{
  "type": "Feature",
  "properties": {
    "iso:country":"US",
    "sg:address":"15 Chestnut St",
    "sg:city":"Cumberland",
    "sg:classifiers":[
        {
            "category":"Education",
            "subcategory":"Special Training",
            "type":"Public Place"
        }
    ],
    "sg:phone":"+1 401 726 6973",
    "sg:postcode":"02864",
    "sg:province":"RI",
    "sg:tags":[
        "g"
    ],
    "wof:name":"Frank A Santos Jr",
    "wof:placetype":"venue"
},
  "geometry": {"coordinates":[-71.400195,41.926534],"type":"Point"}
}