{
  "type": "Feature",
  "properties": {
    "iso:country":"US",
    "sg:address":"82 Robinson St",
    "sg:city":"Wakefield",
    "sg:classifiers":[
        {
            "category":"Professional",
            "subcategory":"Computer Services",
            "type":"Services"
        }
    ],
    "sg:phone":"+1 401 788 8004",
    "sg:postcode":"02879",
    "sg:province":"RI",
    "sg:tags":[
        "to",
        "desk",
        "programming",
        "business",
        "custom"
    ],
    "wof:name":"Stonegate Productions Inc",
    "wof:placetype":"venue"
},
  "geometry": {"coordinates":[-71.49114,41.438778],"type":"Point"}
}