{
  "type": "Feature",
  "properties": {
    "addr:full":"33 Russell Ave Newport RI 02840",
    "addr:housenumber":"33",
    "addr:postcode":"02840",
    "addr:street":"Russell Ave",
    "iso:country":"US",
    "sg:address":"33 Russell Ave",
    "sg:city":"Newport",
    "sg:classifiers":[
        {
            "category":"Travel",
            "subcategory":"Hotels & Motels",
            "type":"Entertainment"
        }
    ],
    "sg:phone":"+1 401 846 5408",
    "sg:postcode":"02840",
    "sg:province":"RI",
    "sg:tags":[
        "breakfast",
        "accommodation",
        "bed"
    ],
    "wof:name":"Bluestone Bed & Breakfast",
    "wof:placetype":"venue"
},
  "geometry": {"coordinates":[-71.306662,41.503177],"type":"Point"}
}