{
  "type": "Feature",
  "properties": {
    "iso:country":"US",
    "sg:address":"231 Japonica St",
    "sg:city":"Pawtucket",
    "sg:classifiers":[
        {
            "category":"Organizations",
            "subcategory":"Professional Association",
            "type":"Services"
        }
    ],
    "sg:phone":"+1 401 475 5525",
    "sg:postcode":"02860",
    "sg:province":"RI",
    "sg:tags":[
        "business",
        "trade"
    ],
    "wof:name":"International Trading Co",
    "wof:placetype":"venue"
},
  "geometry": {"coordinates":[-71.370683,41.888008],"type":"Point"}
}