{
  "type": "Feature",
  "properties": {
    "addr:full":"347 N Broadway Rumford RI 02916",
    "addr:housenumber":"347",
    "addr:postcode":"02916",
    "addr:street":"N Broadway",
    "iso:country":"US",
    "sg:address":"347 N Broadway",
    "sg:city":"Rumford",
    "sg:classifiers":[
        {
            "category":"Personal",
            "subcategory":"Beauty Salon",
            "type":"Services"
        }
    ],
    "sg:phone":"+1 401 438 3533",
    "sg:postcode":"02916",
    "sg:province":"RI",
    "sg:tags":[
        "manicuring"
    ],
    "wof:name":"Nail Emporium",
    "wof:placetype":"venue"
},
  "geometry": {"coordinates":[-71.361104,41.832257],"type":"Point"}
}