{
  "type": "Feature",
  "properties": {
    "iso:country":"US",
    "sg:address":"142 Sweet Allen Farm Rd",
    "sg:city":"Wakefield",
    "sg:classifiers":[
        {
            "category":"Professional",
            "subcategory":"Art Services",
            "type":"Services"
        }
    ],
    "sg:phone":"+1 401 782 3752",
    "sg:postcode":"02879",
    "sg:province":"RI",
    "sg:tags":[
        "photography",
        "commercial"
    ],
    "wof:name":"Bob Lewis & Associates",
    "wof:placetype":"venue"
},
  "geometry": {"coordinates":[-71.52261300000001,41.457],"type":"Point"}
}