{
  "type": "Feature",
  "properties": {
    "iso:country":"US",
    "sg:address":"1438 Park Ave",
    "sg:city":"Woonsocket",
    "sg:classifiers":[
        {
            "category":"Health Services",
            "subcategory":"Doctor",
            "type":"Services"
        }
    ],
    "sg:phone":"+1 401 762 3044",
    "sg:postcode":"02895",
    "sg:province":"RI",
    "sg:tags":[
        "dentist"
    ],
    "wof:name":"Jeffrey Dodge DDS",
    "wof:placetype":"venue"
},
  "geometry": {"coordinates":[-71.51564999999999,41.985358],"type":"Point"}
}