{
  "type": "Feature",
  "properties": {
    "iso:country":"US",
    "sg:address":"167 Indiana Ave",
    "sg:city":"Providence",
    "sg:classifiers":[
        {
            "category":"Retail",
            "subcategory":"Repair Shop",
            "type":"Services"
        },
        {
            "category":"Shopping",
            "subcategory":"Musical Instruments",
            "type":"Retail Goods"
        }
    ],
    "sg:phone":"+1 401 941 2604",
    "sg:postcode":"02905",
    "sg:province":"RI",
    "sg:tags":[
        "repairing",
        "piano",
        "refinishing"
    ],
    "wof:name":"Dr J The Piano Doctor",
    "wof:placetype":"venue"
},
  "geometry": {"coordinates":[-71.399213,41.790024],"type":"Point"}
}