{
  "type": "Feature",
  "properties": {
    "addr:full":"777 Kingstown Rd South Kingstown RI 02879",
    "addr:housenumber":"777",
    "addr:postcode":"02879",
    "addr:street":"Kingstown Rd",
    "iso:country":"US",
    "sg:address":"777 Kingstown Rd",
    "sg:city":"South Kingstown",
    "sg:classifiers":[
        {
            "category":"Personal",
            "type":"Services"
        }
    ],
    "sg:phone":"+1 401 792 9300",
    "sg:postcode":"02879",
    "sg:province":"RI",
    "sg:tags":[
        "therapist",
        "massage"
    ],
    "wof:name":"Denise Tucker Muscular Therapy",
    "wof:placetype":"venue"
},
  "geometry": {"coordinates":[-71.48995499999999,41.445989],"type":"Point"}
}