{
  "type": "Feature",
  "properties": {
    "iso:country":"US",
    "sg:address":"1137 Park Ave",
    "sg:city":"Cranston",
    "sg:classifiers":[
        {
            "category":"Retail",
            "subcategory":"Laundry & Dry Cleaning",
            "type":"Services"
        }
    ],
    "sg:phone":"+1 401 942 7270",
    "sg:postcode":"02910",
    "sg:province":"RI",
    "sg:tags":[
        "garment",
        "plant",
        "agent",
        "drycleaning"
    ],
    "wof:name":"Stadium Cleaners",
    "wof:placetype":"venue"
},
  "geometry": {"coordinates":[-71.449393,41.783469],"type":"Point"}
}