{
  "type": "Feature",
  "properties": {
    "iso:country":"US",
    "sg:address":"1015 Tiogue Ave",
    "sg:city":"Coventry",
    "sg:classifiers":[
        {
            "category":"Personal",
            "subcategory":"Beauty Salon",
            "type":"Services"
        }
    ],
    "sg:phone":"+1 401 821 0400",
    "sg:postcode":"02816",
    "sg:province":"RI",
    "wof:name":"A Salon Galleria & Spa",
    "wof:placetype":"venue"
},
  "geometry": {"coordinates":[-71.57868999999999,41.679358],"type":"Point"}
}