{
  "type": "Feature",
  "properties": {
    "addr:full":"36 Osceola Ave Narragansett RI 02882",
    "addr:housenumber":"36",
    "addr:postcode":"02882",
    "addr:street":"Osceola Ave",
    "iso:country":"US",
    "sg:address":"36 Osceola Ave",
    "sg:city":"Narragansett",
    "sg:classifiers":[
        {
            "category":"Building & Trades",
            "subcategory":"Landscaping Services",
            "type":"Services"
        }
    ],
    "sg:phone":"+1 401 783 4791",
    "sg:postcode":"02882",
    "sg:province":"RI",
    "sg:tags":[
        "landscape"
    ],
    "wof:name":"Park Place Landscape Inc",
    "wof:placetype":"venue"
},
  "geometry": {"coordinates":[-71.438315,41.482394],"type":"Point"}
}