{
  "type": "Feature",
  "properties": {
    "addr:full":"405 Church St Pascoag RI 02859",
    "addr:housenumber":"405",
    "addr:postcode":"02859",
    "addr:street":"Church St",
    "iso:country":"US",
    "sg:address":"405 Church St",
    "sg:city":"Pascoag",
    "sg:classifiers":[
        {
            "category":"Restaurant",
            "type":"Food & Drink"
        }
    ],
    "sg:phone":"+1 401 568 7187",
    "sg:postcode":"02859",
    "sg:province":"RI",
    "wof:name":"Serio's Pizzarama",
    "wof:placetype":"venue"
},
  "geometry": {"coordinates":[-71.712639,41.964535],"type":"Point"}
}