{
  "type": "Feature",
  "properties": {
    "iso:country":"US",
    "sg:address":"12 Tanglewood Dr",
    "sg:city":"Greenville",
    "sg:classifiers":[
        {
            "category":"Real Estate",
            "subcategory":"Real Estate Agent",
            "type":"Services"
        }
    ],
    "sg:phone":"+1 401 949 8080",
    "sg:postcode":"02828",
    "sg:province":"RI",
    "wof:name":"Lancia Appraisal Service",
    "wof:placetype":"venue"
},
  "geometry": {"coordinates":[-71.57053999999999,41.872505],"type":"Point"}
}