{
  "type": "Feature",
  "properties": {
    "addr:full":"80 Access Rd Warwick RI 02886",
    "addr:housenumber":"80",
    "addr:postcode":"02886",
    "addr:street":"Access Rd",
    "iso:country":"US",
    "sg:address":"80 Access Rd",
    "sg:city":"Warwick",
    "sg:classifiers":[
        {
            "category":"Wholesale",
            "subcategory":"Machinery & Supplies",
            "type":"Manufacturing & Wholesale Goods"
        }
    ],
    "sg:phone":"+1 401 736 0515",
    "sg:postcode":"02886",
    "sg:province":"RI",
    "sg:tags":[
        "bearing"
    ],
    "wof:name":"Motion Industries Inc",
    "wof:placetype":"venue"
},
  "geometry": {"coordinates":[-71.448148,41.734448],"type":"Point"}
}