{
  "type": "Feature",
  "properties": {
    "iso:country":"US",
    "sg:address":"593 Budlong Rd",
    "sg:city":"Cranston",
    "sg:classifiers":[
        {
            "category":"Health Services",
            "subcategory":"Doctor",
            "type":"Services"
        }
    ],
    "sg:phone":"+1 401 942 1546",
    "sg:postcode":"02920",
    "sg:province":"RI",
    "wof:name":"John E Baldoni DDS",
    "wof:placetype":"venue"
},
  "geometry": {"coordinates":[-71.458927,41.767035],"type":"Point"}
}