{
  "type": "Feature",
  "properties": {
    "iso:country":"US",
    "sg:address":"1675 Diamond Hill Rd",
    "sg:city":"Woonsocket",
    "sg:classifiers":[
        {
            "category":"Banks & Credit Unions",
            "subcategory":"Bank",
            "type":"Services"
        }
    ],
    "sg:phone":"+1 401 766 8500",
    "sg:postcode":"02895",
    "sg:province":"RI",
    "wof:name":"Citizens Bank",
    "wof:placetype":"venue"
},
  "geometry": {"coordinates":[-71.477144,42.015505],"type":"Point"}
}