{
  "type": "Feature",
  "properties": {
    "iso:country":"US",
    "sg:address":"57 Mount Hope Ave",
    "sg:city":"Bristol",
    "sg:classifiers":[
        {
            "category":"Autos & Motor Vehicles",
            "subcategory":"Auto Supplies",
            "type":"Retail Goods"
        }
    ],
    "sg:phone":"+1 401 253 6313",
    "sg:postcode":"02809",
    "sg:province":"RI",
    "sg:tags":[
        "automobile",
        "parts"
    ],
    "wof:name":"Bristol Auto Supply",
    "wof:placetype":"venue"
},
  "geometry": {"coordinates":[-71.266847,41.670248],"type":"Point"}
}