{
  "type": "Feature",
  "properties": {
    "addr:full":"201 Old Greenwich Dr East Greenwich RI 02818",
    "addr:housenumber":"201",
    "addr:postcode":"02818",
    "addr:street":"Old Greenwich Dr",
    "iso:country":"US",
    "sg:address":"201 Old Greenwich Dr",
    "sg:city":"East Greenwich",
    "sg:classifiers":[
        {
            "category":"Farming",
            "subcategory":"Nursery",
            "type":"Manufacturing & Wholesale Goods"
        }
    ],
    "sg:phone":"+1 401 397 3347",
    "sg:postcode":"02818",
    "sg:province":"RI",
    "sg:tags":[
        "farm",
        "tree",
        "christmas"
    ],
    "wof:name":"Leydens Grn Acrs Chrstms Tr",
    "wof:placetype":"venue"
},
  "geometry": {"coordinates":[-71.478668,41.654658],"type":"Point"}
}