{
  "type": "Feature",
  "properties": {
    "iso:country":"US",
    "sg:address":"62 Blackstone Blvd",
    "sg:city":"Providence",
    "sg:classifiers":[
        {
            "category":"Health Services",
            "subcategory":"Doctor",
            "type":"Services"
        },
        {
            "category":"Health Services",
            "subcategory":"Hospital",
            "type":"Services"
        }
    ],
    "sg:phone":"+1 401 751 6768",
    "sg:postcode":"02906",
    "sg:province":"RI",
    "sg:tags":[
        "consultant",
        "medical",
        "practice",
        "nursing",
        "home"
    ],
    "wof:name":"Nolan Md Mph, Patricia A",
    "wof:placetype":"venue"
},
  "geometry": {"coordinates":[-71.384441,41.834792],"type":"Point"}
}