{
  "type": "Feature",
  "properties": {
    "addr:full":"555 Nooseneck Hill Rd Exeter RI 02822",
    "addr:housenumber":"555",
    "addr:postcode":"02822",
    "addr:street":"Nooseneck Hill Rd",
    "iso:country":"US",
    "sg:address":"555 Nooseneck Hill Rd",
    "sg:city":"Exeter",
    "sg:classifiers":[
        {
            "category":"Manufacturing",
            "subcategory":"Furniture",
            "type":"Manufacturing & Wholesale Goods"
        }
    ],
    "sg:phone":"+1 401 397 8500",
    "sg:postcode":"02822",
    "sg:province":"RI",
    "sg:tags":[
        "lawn",
        "cedar",
        "fence",
        "mfg"
    ],
    "wof:name":"Cedar Craft Fence Co",
    "wof:placetype":"venue"
},
  "geometry": {"coordinates":[-71.659521,41.565603],"type":"Point"}
}