{
  "type": "Feature",
  "properties": {
    "iso:country":"US",
    "sg:address":"342 Harrington Ave",
    "sg:city":"Warwick",
    "sg:classifiers":[
        {
            "category":"Building & Trades",
            "subcategory":"Construction",
            "type":"Services"
        }
    ],
    "sg:phone":"+1 401 461 2197",
    "sg:postcode":"02888",
    "sg:province":"RI",
    "sg:tags":[
        "house"
    ],
    "wof:name":"Miranda Builders",
    "wof:placetype":"venue"
},
  "geometry": {"coordinates":[-71.424335,41.751683],"type":"Point"}
}