{
  "type": "Feature",
  "properties": {
    "iso:country":"US",
    "sg:address":"15 Church St",
    "sg:city":"Providence",
    "sg:classifiers":[
        {
            "category":"Banks & Credit Unions",
            "subcategory":"Financial Services",
            "type":"Services"
        }
    ],
    "sg:phone":"+1 401 861 6927",
    "sg:postcode":"02904",
    "sg:province":"RI",
    "sg:tags":[
        "trust",
        "management"
    ],
    "wof:name":"Robert Klberer Living Tr 01/03",
    "wof:placetype":"venue"
},
  "geometry": {"coordinates":[-71.409634,41.83082],"type":"Point"}
}