{
  "type": "Feature",
  "properties": {
    "addr:full":"55 Amaral St Riverside RI 02915",
    "addr:postcode":"02915",
    "addr:street":"Amaral St",
    "iso:country":"US",
    "sg:address":"55 Amaral St",
    "sg:city":"Riverside",
    "sg:classifiers":[
        {
            "category":"Freight",
            "type":"Transportation"
        }
    ],
    "sg:phone":"+1 401 434 5290",
    "sg:postcode":"02915",
    "sg:province":"RI",
    "sg:tags":[
        "commercial",
        "storage"
    ],
    "wof:name":"Trailside Mini Storage",
    "wof:placetype":"venue"
},
  "geometry": {"coordinates":[-71.347724,41.79661],"type":"Point"}
}