{
  "type": "Feature",
  "properties": {
    "iso:country":"US",
    "sg:address":"380 Main St",
    "sg:city":"Wakefield",
    "sg:classifiers":[
        {
            "category":"Professional",
            "subcategory":"Lawyer & Legal Services",
            "type":"Services"
        }
    ],
    "sg:phone":"+1 401 782 8700",
    "sg:postcode":"02879",
    "sg:province":"RI",
    "sg:tags":[
        "attorney"
    ],
    "wof:name":"R J Mulholland LAW Office",
    "wof:placetype":"venue"
},
  "geometry": {"coordinates":[-71.500508,41.437526],"type":"Point"}
}