{
  "type": "Feature",
  "properties": {
    "iso:country":"US",
    "sg:address":"21 Smith Ave",
    "sg:city":"Greenville",
    "sg:classifiers":[
        {
            "category":"Restaurant",
            "type":"Food & Drink"
        }
    ],
    "sg:phone":"+1 401 949 7390",
    "sg:postcode":"02828",
    "sg:province":"RI",
    "wof:name":"Mick Frickles Eatery",
    "wof:placetype":"venue"
},
  "geometry": {"coordinates":[-71.554695,41.869474],"type":"Point"}
}