{
  "type": "Feature",
  "properties": {
    "iso:country":"US",
    "sg:address":"47 W Shore Rd",
    "sg:city":"Warwick",
    "sg:classifiers":[
        {
            "category":"Arts & Performance",
            "subcategory":"Theater",
            "type":"Entertainment"
        }
    ],
    "sg:phone":"+1 401 732 7878",
    "sg:postcode":"02889",
    "sg:province":"RI",
    "sg:tags":[
        "theatrical"
    ],
    "wof:name":"Adam Productions",
    "wof:placetype":"venue"
},
  "geometry": {"coordinates":[-71.40472800000001,41.733477],"type":"Point"}
}