{
  "type": "Feature",
  "properties": {
    "addr:full":"115 Providence Pl Providence RI 02903",
    "addr:housenumber":"115",
    "addr:postcode":"02903",
    "addr:street":"Providence Pl",
    "iso:country":"US",
    "sg:address":"115 Providence Pl",
    "sg:city":"Providence",
    "sg:classifiers":[
        {
            "category":"Personal",
            "subcategory":"Beauty Salon",
            "type":"Services"
        }
    ],
    "sg:phone":"+1 401 383 4278",
    "sg:postcode":"02903",
    "sg:province":"RI",
    "sg:tags":[
        "shop"
    ],
    "wof:name":"Pro Nail",
    "wof:placetype":"venue"
},
  "geometry": {"coordinates":[-71.418891,41.827826],"type":"Point"}
}