{
  "type": "Feature",
  "properties": {
    "iso:country":"US",
    "sg:address":"232 Oakwoods Dr",
    "sg:city":"Wakefield",
    "sg:classifiers":[
        {
            "category":"Real Estate",
            "subcategory":"Architect",
            "type":"Services"
        }
    ],
    "sg:phone":"+1 401 789 0308",
    "sg:postcode":"02879",
    "sg:province":"RI",
    "sg:tags":[
        "architectural"
    ],
    "wof:name":"Oliver C Johnson",
    "wof:placetype":"venue"
},
  "geometry": {"coordinates":[-71.49130700000001,41.456123],"type":"Point"}
}