{
  "type": "Feature",
  "properties": {
    "iso:country":"US",
    "sg:address":"631 Park Ave",
    "sg:city":"Cranston",
    "sg:classifiers":[
        {
            "category":"Building & Trades",
            "subcategory":"Plumbing",
            "type":"Services"
        }
    ],
    "sg:phone":"+1 401 383 5552",
    "sg:postcode":"02910",
    "sg:province":"RI",
    "sg:tags":[
        "mechanical",
        "contractor"
    ],
    "wof:name":"Bernard Mechanical",
    "wof:placetype":"venue"
},
  "geometry": {"coordinates":[-71.425781,41.776942],"type":"Point"}
}