{
  "type": "Feature",
  "properties": {
    "addr:full":"6 Jefferson Dr Coventry RI 02816",
    "addr:housenumber":"6",
    "addr:postcode":"02816",
    "addr:street":"Jefferson Dr",
    "iso:country":"US",
    "sg:address":"6 Jefferson Dr",
    "sg:city":"Coventry",
    "sg:classifiers":[
        {
            "category":"Wholesale",
            "subcategory":"Construction Materials",
            "type":"Manufacturing & Wholesale Goods"
        },
        {
            "category":"Home & Garden",
            "subcategory":"Building Materials",
            "type":"Retail Goods"
        }
    ],
    "sg:phone":"+1 401 821 2800",
    "sg:postcode":"02816",
    "sg:province":"RI",
    "sg:tags":[
        "other",
        "lumber"
    ],
    "wof:name":"Coventry Lumber Inc",
    "wof:placetype":"venue"
},
  "geometry": {"coordinates":[-71.57414799999999,41.677052],"type":"Point"}
}