{
  "type": "Feature",
  "properties": {
    "iso:country":"US",
    "sg:address":"70 Phillips St",
    "sg:city":"North Kingstown",
    "sg:classifiers":[
        {
            "category":"Real Estate",
            "subcategory":"Real Estate Agent",
            "type":"Services"
        }
    ],
    "sg:phone":"+1 401 295 5711",
    "sg:postcode":"02852",
    "sg:province":"RI",
    "wof:name":"Maya Realty LLC",
    "wof:placetype":"venue"
},
  "geometry": {"coordinates":[-71.454601,41.568126],"type":"Point"}
}