{
  "type": "Feature",
  "properties": {
    "iso:country":"US",
    "sg:address":"10 Moshassuck St",
    "sg:city":"Pawtucket",
    "sg:classifiers":[
        {
            "category":"Government",
            "subcategory":"Office",
            "type":"Public Place"
        }
    ],
    "sg:phone":"+1 401 726 1851",
    "sg:postcode":"02860",
    "sg:province":"RI",
    "wof:name":"Rhode Island State Of Narr Bay",
    "wof:placetype":"venue"
},
  "geometry": {"coordinates":[-71.401325,41.859695],"type":"Point"}
}