{
  "type": "Feature",
  "properties": {
    "addr:full":"298 W Exchange St Providence RI 02903",
    "addr:housenumber":"298",
    "addr:postcode":"02903",
    "addr:street":"W Exchange St",
    "iso:country":"US",
    "sg:address":"298 W Exchange St",
    "sg:city":"Providence",
    "sg:classifiers":[
        {
            "category":"Organizations",
            "subcategory":"Professional Association",
            "type":"Services"
        }
    ],
    "sg:phone":"+1 401 421 6487",
    "sg:postcode":"02903",
    "sg:province":"RI",
    "wof:name":"American Lung Assn",
    "wof:placetype":"venue"
},
  "geometry": {"coordinates":[-71.422084,41.825263],"type":"Point"}
}