{
  "type": "Feature",
  "properties": {
    "addr:full":"623 Washington St Lincoln RI 02816",
    "addr:housenumber":"623",
    "addr:postcode":"02816",
    "addr:street":"Washington St",
    "iso:country":"US",
    "sg:address":"623 Washington St",
    "sg:city":"Lincoln",
    "sg:classifiers":[
        {
            "category":"Manufacturing",
            "subcategory":"Tools & Machinery",
            "type":"Manufacturing & Wholesale Goods"
        }
    ],
    "sg:phone":"+1 401 333 4363",
    "sg:postcode":"02816",
    "sg:province":"RI",
    "sg:tags":[
        "industrial",
        "mfg"
    ],
    "wof:name":"Dynamic Converting Systems",
    "wof:placetype":"venue"
},
  "geometry": {"coordinates":[-71.546606,41.697136],"type":"Point"}
}