{
  "type": "Feature",
  "properties": {
    "iso:country":"US",
    "sg:address":"282 Bayview Ave",
    "sg:city":"Providence",
    "sg:classifiers":[
        {
            "category":"Social Services",
            "subcategory":"Child Care",
            "type":"Services"
        }
    ],
    "sg:phone":"+1 401 941 2123",
    "sg:postcode":"02905",
    "sg:province":"RI",
    "sg:tags":[
        "day"
    ],
    "wof:name":"Day One Coaching",
    "wof:placetype":"venue"
},
  "geometry": {"coordinates":[-71.400942,41.784193],"type":"Point"}
}