{
  "type": "Feature",
  "properties": {
    "iso:country":"US",
    "sg:address":"623 George Washington Hwy",
    "sg:city":"Lincoln",
    "sg:classifiers":[
        {
            "category":"Manufacturing",
            "subcategory":"Tools & Machinery",
            "type":"Manufacturing & Wholesale Goods"
        }
    ],
    "sg:phone":"+1 401 333 4363",
    "sg:postcode":"02865",
    "sg:province":"RI",
    "sg:tags":[
        "designed",
        "built"
    ],
    "wof:name":"Dynamic Converting Systems Inc",
    "wof:placetype":"venue"
},
  "geometry": {"coordinates":[-71.44749299999999,41.93491],"type":"Point"}
}