{
  "type": "Feature",
  "properties": {
    "iso:country":"US",
    "sg:address":"91 Toll Gate Rd",
    "sg:city":"Warwick",
    "sg:classifiers":[
        {
            "category":"Insurance",
            "subcategory":"Insurance Agent",
            "type":"Services"
        }
    ],
    "sg:phone":"+1 401 739 4322",
    "sg:postcode":"02886",
    "sg:province":"RI",
    "wof:name":"Provident Mutual Life Ins Co",
    "wof:placetype":"venue"
},
  "geometry": {"coordinates":[-71.465225,41.698809],"type":"Point"}
}