{
  "type": "Feature",
  "properties": {
    "iso:country":"US",
    "sg:address":"2656 Main Rd",
    "sg:city":"Tiverton",
    "sg:classifiers":[
        {
            "category":"Home & Garden",
            "subcategory":"Building Materials",
            "type":"Retail Goods"
        }
    ],
    "sg:phone":"+1 401 624 1944",
    "sg:postcode":"02878",
    "sg:province":"RI",
    "wof:name":"A Touch Of Glass",
    "wof:placetype":"venue"
},
  "geometry": {"coordinates":[-71.19292799999999,41.608409],"type":"Point"}
}