{
  "type": "Feature",
  "properties": {
    "addr:full":"74 Smith Ave Greenville RI 02828",
    "addr:housenumber":"74",
    "addr:postcode":"02828",
    "addr:street":"Smith Ave",
    "iso:country":"US",
    "sg:address":"74 Smith Ave",
    "sg:city":"Greenville",
    "sg:classifiers":[
        {
            "category":"Personal",
            "type":"Services"
        },
        {
            "category":"Professional",
            "subcategory":"Management & Consulting",
            "type":"Services"
        }
    ],
    "sg:phone":"+1 401 949 4370",
    "sg:postcode":"02828",
    "sg:province":"RI",
    "sg:tags":[
        "party",
        "planning"
    ],
    "wof:name":"Birthday Bee Co Inc",
    "wof:placetype":"venue"
},
  "geometry": {"coordinates":[-71.566261,41.864853],"type":"Point"}
}