{
  "type": "Feature",
  "properties": {
    "iso:country":"US",
    "sg:address":"15 Elbow St",
    "sg:city":"Providence",
    "sg:classifiers":[
        {
            "category":"Bars & Pubs",
            "subcategory":"Lounge",
            "type":"Food & Drink"
        },
        {
            "category":"Cafe",
            "type":"Food & Drink"
        }
    ],
    "sg:menulink":"http://www.allmenus.com/ri/providence/9451-jewel-cafe--lounge/menu/",
    "sg:phone":"+1 401 273 7300",
    "sg:postcode":"02903",
    "sg:province":"RI",
    "sg:tags":[
        "american"
    ],
    "wof:name":"Jewel Cafe & Lounge",
    "wof:placetype":"venue"
},
  "geometry": {"coordinates":[-71.40977599999999,41.818402],"type":"Point"}
}