{
  "type": "Feature",
  "properties": {
    "iso:country":"US",
    "sg:address":"60 N Main St",
    "sg:city":"Bradford",
    "sg:classifiers":[
        {
            "category":"Coffee & Tea",
            "type":"Food & Drink"
        },
        {
            "category":"Restaurant",
            "type":"Food & Drink"
        },
        {
            "category":"Food & Beverages",
            "subcategory":"Groceries & Convenience Stores",
            "type":"Retail Goods"
        }
    ],
    "sg:phone":"+1 401 315 2423",
    "sg:postcode":"02808",
    "sg:province":"RI",
    "sg:tags":[
        "shop",
        "sandwich",
        "espresso",
        "lunch",
        "brunch",
        "breakfast"
    ],
    "sg:website":"http://www.timhortons.com/",
    "wof:name":"Tim Horton's",
    "wof:placetype":"venue"
},
  "geometry": {"coordinates":[-71.748507,41.402806],"type":"Point"}
}