{
  "type": "Feature",
  "properties": {
    "iso:country":"US",
    "sg:address":"69 Laconia Rd",
    "sg:city":"Cranston",
    "sg:classifiers":[
        {
            "category":"Professional",
            "subcategory":"Art Services",
            "type":"Services"
        }
    ],
    "sg:phone":"+1 401 942 2974",
    "sg:postcode":"02920",
    "sg:province":"RI",
    "sg:tags":[
        "photography",
        "commercial"
    ],
    "wof:name":"Martha Dimeo Photography",
    "wof:placetype":"venue"
},
  "geometry": {"coordinates":[-71.47640199999999,41.777424],"type":"Point"}
}