{
  "type": "Feature",
  "properties": {
    "iso:country":"US",
    "sg:address":"625 Broad St",
    "sg:city":"Cumberland",
    "sg:classifiers":[
        {
            "category":"Autos & Motor Vehicles",
            "subcategory":"Automobile Sales",
            "type":"Retail Goods"
        }
    ],
    "sg:phone":"+1 401 475 8899",
    "sg:postcode":"02864",
    "sg:province":"RI",
    "sg:tags":[
        "car",
        "dealer"
    ],
    "wof:name":"Apollo Auto Sales Like New To",
    "wof:placetype":"venue"
},
  "geometry": {"coordinates":[-71.402565,41.916129],"type":"Point"}
}