{
  "type": "Feature",
  "properties": {
    "iso:country":"US",
    "sg:address":"184 Ave C",
    "sg:city":"Woonsocket",
    "sg:classifiers":[
        {
            "category":"Retail",
            "subcategory":"Repair Shop",
            "type":"Services"
        }
    ],
    "sg:phone":"+1 401 769 1952",
    "sg:postcode":"02895",
    "sg:province":"RI",
    "sg:tags":[
        "upholsterer"
    ],
    "wof:name":"Carriere's Upholstery Inc",
    "wof:placetype":"venue"
},
  "geometry": {"coordinates":[-71.52383,41.991269],"type":"Point"}
}