{
  "type": "Feature",
  "properties": {
    "iso:country":"US",
    "sg:address":"630 Social St",
    "sg:city":"Woonsocket",
    "sg:classifiers":[
        {
            "category":"Home & Garden",
            "subcategory":"Hardware",
            "type":"Retail Goods"
        }
    ],
    "sg:phone":"+1 401 762 2283",
    "sg:postcode":"02895",
    "sg:province":"RI",
    "wof:name":"Pinault Hardware Company",
    "wof:placetype":"venue"
},
  "geometry": {"coordinates":[-71.503649,42.008959],"type":"Point"}
}