{
  "type": "Feature",
  "properties": {
    "addr:full":"80 Public St Providence RI 02903",
    "addr:housenumber":"80",
    "addr:postcode":"02903",
    "addr:street":"Public St",
    "iso:country":"US",
    "sg:address":"80 Public St",
    "sg:city":"Providence",
    "sg:classifiers":[
        {
            "category":"Autos & Motor Vehicles",
            "subcategory":"Auto Supplies",
            "type":"Retail Goods"
        }
    ],
    "sg:phone":"+1 401 521 2240",
    "sg:postcode":"02903",
    "sg:province":"RI",
    "sg:tags":[
        "wheel",
        "tire"
    ],
    "sg:website":"http://www.petestirebarns.com",
    "wof:name":"Pete's Tire Barn",
    "wof:placetype":"venue"
},
  "geometry": {"coordinates":[-71.40346700000001,41.808261],"type":"Point"}
}