{
  "type": "Feature",
  "properties": {
    "iso:country":"US",
    "sg:address":"40 Technology Way",
    "sg:city":"West Greenwich",
    "sg:classifiers":[
        {
            "category":"Professional",
            "subcategory":"Computer Services",
            "type":"Services"
        }
    ],
    "sg:phone":"+1 401 392 3521",
    "sg:postcode":"02817",
    "sg:province":"RI",
    "sg:tags":[
        "design",
        "system"
    ],
    "wof:name":"Andover Controls Corporation",
    "wof:placetype":"venue"
},
  "geometry": {"coordinates":[-71.572036,41.658954],"type":"Point"}
}