{
  "type": "Feature",
  "properties": {
    "iso:country":"US",
    "sg:address":"105 Scenery Ln",
    "sg:city":"Johnston",
    "sg:classifiers":[
        {
            "category":"Shopping",
            "subcategory":"Jewelry",
            "type":"Retail Goods"
        }
    ],
    "sg:phone":"+1 401 233 8023",
    "sg:postcode":"02919",
    "sg:province":"RI",
    "sg:tags":[
        "precious",
        "semi-precious",
        "stone"
    ],
    "wof:name":"Hermes Jewelry",
    "wof:placetype":"venue"
},
  "geometry": {"coordinates":[-71.501037,41.865005],"type":"Point"}
}