{
  "type": "Feature",
  "properties": {
    "addr:full":"78 Leuba Rd Coventry RI 02816",
    "addr:housenumber":"78",
    "addr:postcode":"02816",
    "addr:street":"Leuba Rd",
    "iso:country":"US",
    "sg:address":"78 Leuba Rd",
    "sg:city":"Coventry",
    "sg:classifiers":[
        {
            "category":"Professional",
            "subcategory":"Management & Consulting",
            "type":"Services"
        }
    ],
    "sg:phone":"+1 401 615 0597",
    "sg:postcode":"02816",
    "sg:province":"RI",
    "wof:name":"Cdx Pro",
    "wof:placetype":"venue"
},
  "geometry": {"coordinates":[-71.583901,41.707451],"type":"Point"}
}