{
  "type": "Feature",
  "properties": {
    "iso:country":"US",
    "sg:address":"18 High St",
    "sg:city":"Westerly",
    "sg:classifiers":[
        {
            "category":"Professional",
            "subcategory":"Art Services",
            "type":"Services"
        }
    ],
    "sg:phone":"+1 401 348 9600",
    "sg:postcode":"02891",
    "sg:province":"RI",
    "sg:tags":[
        "photography",
        "commercial"
    ],
    "wof:name":"Lambrecht Photography",
    "wof:placetype":"venue"
},
  "geometry": {"coordinates":[-71.829875,41.379362],"type":"Point"}
}