{
  "type": "Feature",
  "properties": {
    "iso:country":"US",
    "sg:address":"Main",
    "sg:city":"Albion",
    "sg:classifiers":[
        {
            "category":"Autos & Motor Vehicles",
            "subcategory":"Fuel & Gas Station",
            "type":"Retail Goods"
        }
    ],
    "sg:phone":"+1 401 333 1536",
    "sg:postcode":"02802",
    "sg:province":"RI",
    "sg:website":"www.texaco.com",
    "wof:name":"Landry's Texaco Sta",
    "wof:placetype":"venue"
},
  "geometry": {"coordinates":[-71.45500199999999,41.951801],"type":"Point"}
}