{
  "type": "Feature",
  "properties": {
    "iso:country":"US",
    "sg:address":"228 High St",
    "sg:city":"Westerly",
    "sg:classifiers":[
        {
            "category":"Retail",
            "subcategory":"Auto Repair",
            "type":"Services"
        }
    ],
    "sg:phone":"+1 401 596 5370",
    "sg:postcode":"02891",
    "sg:province":"RI",
    "sg:tags":[
        "repairing",
        "automobile"
    ],
    "wof:name":"Brown Service Station",
    "wof:placetype":"venue"
},
  "geometry": {"coordinates":[-71.823341,41.391026],"type":"Point"}
}