{
  "type": "Feature",
  "properties": {
    "iso:country":"US",
    "sg:address":"122 Connell Hwy",
    "sg:city":"Newport",
    "sg:classifiers":[
        {
            "category":"Organizations",
            "subcategory":"Non-profit Organization",
            "type":"Services"
        }
    ],
    "sg:phone":"+1 401 847 4878",
    "sg:postcode":"02840",
    "sg:province":"RI",
    "wof:name":"Fleet Reserve Assn",
    "wof:placetype":"venue"
},
  "geometry": {"coordinates":[-71.317702,41.504552],"type":"Point"}
}