{
  "type": "Feature",
  "properties": {
    "iso:country":"US",
    "sg:address":"56 Elmdale Rd",
    "sg:city":"North Scituate",
    "sg:classifiers":[
        {
            "category":"Farming",
            "subcategory":"Orchard",
            "type":"Manufacturing & Wholesale Goods"
        }
    ],
    "sg:phone":"+1 401 934 1413",
    "sg:postcode":"02857",
    "sg:province":"RI",
    "sg:tags":[
        "farm",
        "fruit",
        "tree"
    ],
    "wof:name":"Barden Orchards",
    "wof:placetype":"venue"
},
  "geometry": {"coordinates":[-71.588014,41.860167],"type":"Point"}
}