{
  "type": "Feature",
  "properties": {
    "iso:country":"US",
    "sg:address":"3 Greenbrier Dr",
    "sg:city":"Barrington",
    "sg:classifiers":[
        {
            "category":"Professional",
            "subcategory":"Management & Consulting",
            "type":"Services"
        }
    ],
    "sg:phone":"+1 401 245 0383",
    "sg:postcode":"02806",
    "sg:province":"RI",
    "wof:name":"Brixton Company",
    "wof:placetype":"venue"
},
  "geometry": {"coordinates":[-71.297961,41.744455],"type":"Point"}
}