{
  "type": "Feature",
  "properties": {
    "iso:country":"US",
    "sg:address":"25 Columbine Ct",
    "sg:city":"Wakefield",
    "sg:classifiers":[
        {
            "category":"Recreation",
            "type":"Entertainment"
        }
    ],
    "sg:phone":"+1 401 789 3756",
    "sg:postcode":"02879",
    "sg:province":"RI",
    "sg:tags":[
        "charter",
        "boat"
    ],
    "wof:name":"Charterboat Mako II",
    "wof:placetype":"venue"
},
  "geometry": {"coordinates":[-71.52112099999999,41.404824],"type":"Point"}
}