{
  "type": "Feature",
  "properties": {
    "iso:country":"US",
    "sg:address":"197 Wickenden St",
    "sg:city":"Providence",
    "sg:classifiers":[
        {
            "category":"Shopping",
            "subcategory":"Used Merchandise",
            "type":"Retail Goods"
        }
    ],
    "sg:phone":"+1 401 272 3202",
    "sg:postcode":"02903",
    "sg:province":"RI",
    "sg:tags":[
        "antique"
    ],
    "wof:name":"Doyle Antique's",
    "wof:placetype":"venue"
},
  "geometry": {"coordinates":[-71.398608,41.819371],"type":"Point"}
}