{
  "type": "Feature",
  "properties": {
    "addr:full":"44 Church St Bristol RI 02809",
    "addr:housenumber":"44",
    "addr:postcode":"02809",
    "addr:street":"Church St",
    "iso:country":"US",
    "sg:address":"44 Church St",
    "sg:city":"Bristol",
    "sg:classifiers":[
        {
            "category":"Professional",
            "type":"Services"
        }
    ],
    "sg:phone":"+1 401 254 0338",
    "sg:postcode":"02809",
    "sg:province":"RI",
    "wof:name":"Bristol Tree Society",
    "wof:placetype":"venue"
},
  "geometry": {"coordinates":[-71.275384,41.668727],"type":"Point"}
}