{
  "type": "Feature",
  "properties": {
    "iso:country":"US",
    "sg:address":"2093 Harkney Hill Rd",
    "sg:city":"Coventry",
    "sg:classifiers":[
        {
            "category":"Organizations",
            "subcategory":"Community Association",
            "type":"Services"
        }
    ],
    "sg:phone":"+1 401 397 7779",
    "sg:postcode":"02816",
    "sg:province":"RI",
    "wof:name":"YMCA",
    "wof:placetype":"venue"
},
  "geometry": {"coordinates":[-71.669799,41.683161],"type":"Point"}
}