{
  "type": "Feature",
  "properties": {
    "iso:country":"US",
    "sg:address":"708 Warwick Ave",
    "sg:city":"Warwick",
    "sg:classifiers":[
        {
            "category":"Health Services",
            "subcategory":"Doctor",
            "type":"Services"
        }
    ],
    "sg:phone":"+1 401 785 2111",
    "sg:postcode":"02888",
    "sg:province":"RI",
    "wof:name":"Professional Dental Assoc",
    "wof:placetype":"venue"
},
  "geometry": {"coordinates":[-71.40443399999999,41.757274],"type":"Point"}
}