{
  "type": "Feature",
  "properties": {
    "iso:country":"US",
    "sg:address":"3093 E Main Rd",
    "sg:city":"Portsmouth",
    "sg:classifiers":[
        {
            "category":"Building & Trades",
            "subcategory":"Electrical",
            "type":"Services"
        }
    ],
    "sg:phone":"+1 401 683 9645",
    "sg:postcode":"02871",
    "sg:province":"RI",
    "sg:tags":[
        "security",
        "system",
        "install"
    ],
    "wof:name":"Aquidneck Lock & SEC Systems",
    "wof:placetype":"venue"
},
  "geometry": {"coordinates":[-71.24637800000001,41.610672],"type":"Point"}
}