{
  "type": "Feature",
  "properties": {
    "iso:country":"US",
    "sg:address":"1001 Main St",
    "sg:city":"East Greenwich",
    "sg:classifiers":[
        {
            "category":"Manufacturing",
            "subcategory":"Tools & Machinery",
            "type":"Manufacturing & Wholesale Goods"
        }
    ],
    "sg:phone":"+1 401 884 2250",
    "sg:postcode":"02818",
    "sg:province":"RI",
    "sg:tags":[
        "machine",
        "shop"
    ],
    "wof:name":"Harris Tool & Machinery Co",
    "wof:placetype":"venue"
},
  "geometry": {"coordinates":[-71.457905,41.650517],"type":"Point"}
}