{
  "type": "Feature",
  "properties": {
    "iso:country":"US",
    "sg:address":"197 Broad St",
    "sg:city":"Pawtucket",
    "sg:classifiers":[
        {
            "category":"Government",
            "subcategory":"Post Office",
            "type":"Public Place"
        }
    ],
    "sg:phone":"+1 401 725 0169",
    "sg:postcode":"02860",
    "sg:province":"RI",
    "sg:tags":[
        "postal",
        "us"
    ],
    "wof:name":"United States Postal Service",
    "wof:placetype":"venue"
},
  "geometry": {"coordinates":[-71.386551,41.881378],"type":"Point"}
}