{
  "type": "Feature",
  "properties": {
    "addr:full":"57 Carolina Ave Providence RI 02905",
    "addr:housenumber":"57",
    "addr:postcode":"02905",
    "addr:street":"Carolina Ave",
    "iso:country":"US",
    "sg:address":"57 Carolina Ave",
    "sg:city":"Providence",
    "sg:classifiers":[
        {
            "category":"Professional",
            "subcategory":"Business Services",
            "type":"Services"
        }
    ],
    "sg:phone":"+1 401 941 1660",
    "sg:postcode":"02905",
    "sg:province":"RI",
    "wof:name":"Gac Associates Inc",
    "wof:placetype":"venue"
},
  "geometry": {"coordinates":[-71.396669,41.791696],"type":"Point"}
}