{
  "type": "Feature",
  "properties": {
    "iso:country":"US",
    "sg:address":"1367 Elmwood Ave",
    "sg:city":"Cranston",
    "sg:classifiers":[
        {
            "category":"Wholesale",
            "subcategory":"Medical Equipment & Supplies",
            "type":"Manufacturing & Wholesale Goods"
        },
        {
            "category":"Health Services",
            "subcategory":"Hospital",
            "type":"Services"
        },
        {
            "category":"Shopping",
            "subcategory":"Pharmacy",
            "type":"Retail Goods"
        }
    ],
    "sg:phone":"+1 401 780 8737",
    "sg:postcode":"02910",
    "sg:province":"RI",
    "sg:tags":[
        "instrument",
        "surgical",
        "care",
        "home"
    ],
    "sg:website":"http://www.torbot.com",
    "wof:name":"Torbot Group, Inc.",
    "wof:placetype":"venue"
},
  "geometry": {"coordinates":[-71.422951,41.772556],"type":"Point"}
}