{
  "type": "Feature",
  "properties": {
    "addr:full":"17 Ferncrest Dr Johnston RI 02919",
    "addr:housenumber":"17",
    "addr:postcode":"02919",
    "addr:street":"Ferncrest Dr",
    "iso:country":"US",
    "sg:address":"17 Ferncrest Dr",
    "sg:city":"Johnston",
    "sg:classifiers":[
        {
            "category":"Manufacturing",
            "subcategory":"Printing",
            "type":"Manufacturing & Wholesale Goods"
        }
    ],
    "sg:phone":"+1 401 231 1389",
    "sg:postcode":"02919",
    "sg:province":"RI",
    "sg:tags":[
        "publishing"
    ],
    "wof:name":"Cars Realty LLC",
    "wof:placetype":"venue"
},
  "geometry": {"coordinates":[-71.483977,41.835772],"type":"Point"}
}