{
  "type": "Feature",
  "properties": {
    "iso:country":"US",
    "sg:address":"1464 Diamond Hill Rd",
    "sg:city":"Cumberland",
    "sg:classifiers":[
        {
            "category":"Health Services",
            "subcategory":"Doctor",
            "type":"Services"
        }
    ],
    "sg:phone":"+1 401 333 3810",
    "sg:postcode":"02864",
    "sg:province":"RI",
    "wof:name":"Bermon Maurice MD",
    "wof:placetype":"venue"
},
  "geometry": {"coordinates":[-71.400002,41.934898],"type":"Point"}
}