{
  "type": "Feature",
  "properties": {
    "iso:country":"US",
    "sg:address":"67 Cedar St",
    "sg:city":"Providence",
    "sg:classifiers":[
        {
            "category":"Professional",
            "subcategory":"Lawyer & Legal Services",
            "type":"Services"
        }
    ],
    "sg:phone":"+1 401 273 0200",
    "sg:postcode":"02903",
    "sg:province":"RI",
    "wof:name":"Russo Kenneth E",
    "wof:placetype":"venue"
},
  "geometry": {"coordinates":[-71.422884,41.824797],"type":"Point"}
}