{
  "type": "Feature",
  "properties": {
    "addr:full":"626 Rathbun St Blackstone RI 01504",
    "addr:housenumber":"626",
    "addr:postcode":"01504",
    "addr:street":"Rathbun St",
    "iso:country":"US",
    "sg:address":"626 Rathbun St",
    "sg:city":"Blackstone",
    "sg:classifiers":[
        {
            "category":"Professional",
            "subcategory":"Lawyer & Legal Services",
            "type":"Services"
        }
    ],
    "sg:phone":"+1 508 883 6909",
    "sg:postcode":"01504",
    "sg:province":"RI",
    "sg:tags":[
        "attorney"
    ],
    "wof:name":"R Bernard Biron",
    "wof:placetype":"venue"
},
  "geometry": {"coordinates":[-71.50166,42.018952],"type":"Point"}
}