{
  "type": "Feature",
  "properties": {
    "addr:full":"114 Granite St Westerly RI 02891",
    "addr:housenumber":"114",
    "addr:postcode":"02891",
    "addr:street":"Granite St",
    "iso:country":"US",
    "sg:address":"114 Granite St",
    "sg:city":"Westerly",
    "sg:classifiers":[
        {
            "category":"Retail",
            "subcategory":"Laundry & Dry Cleaning",
            "type":"Services"
        }
    ],
    "sg:phone":"+1 401 596 2457",
    "sg:postcode":"02891",
    "sg:province":"RI",
    "sg:tags":[
        "cleaners"
    ],
    "wof:name":"Suburban Cleaners",
    "wof:placetype":"venue"
},
  "geometry": {"coordinates":[-71.820465,41.372765],"type":"Point"}
}