{
  "type": "Feature",
  "properties": {
    "addr:full":"21 Pier Market Pl Narragansett RI 02882",
    "addr:housenumber":"21",
    "addr:postcode":"02882",
    "addr:street":"Pier Market Pl",
    "iso:country":"US",
    "sg:address":"21 Pier Market Pl",
    "sg:city":"Narragansett",
    "sg:classifiers":[
        {
            "category":"Restaurant",
            "type":"Food & Drink"
        }
    ],
    "sg:phone":"+1 401 789 9500",
    "sg:postcode":"02882",
    "sg:province":"RI",
    "wof:name":"Woodys Cafe",
    "wof:placetype":"venue"
},
  "geometry": {"coordinates":[-71.458349,41.431485],"type":"Point"}
}