{
  "type": "Feature",
  "properties": {
    "addr:full":"255 Hoxsie Ave Warwick RI 02889",
    "addr:housenumber":"255",
    "addr:postcode":"02889",
    "addr:street":"Hoxsie Ave",
    "iso:country":"US",
    "sg:address":"255 Hoxsie Ave",
    "sg:city":"Warwick",
    "sg:classifiers":[
        {
            "category":"Building & Trades",
            "subcategory":"Construction",
            "type":"Services"
        }
    ],
    "sg:phone":"+1 401 738 8514",
    "sg:postcode":"02889",
    "sg:province":"RI",
    "sg:tags":[
        "house",
        "general",
        "contractor"
    ],
    "wof:name":"Tavarozzi Brothers Inc",
    "wof:placetype":"venue"
},
  "geometry": {"coordinates":[-71.413487,41.731349],"type":"Point"}
}