{
  "type": "Feature",
  "properties": {
    "iso:country":"US",
    "sg:address":"2010 Diamond Hill Rd",
    "sg:city":"Woonsocket",
    "sg:classifiers":[
        {
            "category":"Home & Garden",
            "subcategory":"Building Materials",
            "type":"Retail Goods"
        }
    ],
    "sg:phone":"+1 401 769 0471",
    "sg:postcode":"02895",
    "sg:province":"RI",
    "sg:tags":[
        "center"
    ],
    "wof:name":"Lowe's",
    "wof:placetype":"venue"
},
  "geometry": {"coordinates":[-71.48147899999999,42.015682],"type":"Point"}
}