{
  "type": "Feature",
  "properties": {
    "addr:full":"163 Providence Pl Providence RI 02903",
    "addr:housenumber":"163",
    "addr:postcode":"02903",
    "addr:street":"Providence Pl",
    "iso:country":"US",
    "sg:address":"163 Providence Pl",
    "sg:city":"Providence",
    "sg:classifiers":[
        {
            "category":"Restaurant",
            "type":"Food & Drink"
        }
    ],
    "sg:phone":"+1 401 383 0988",
    "sg:postcode":"02903",
    "sg:province":"RI",
    "wof:name":"Surf N Turf Grille",
    "wof:placetype":"venue"
},
  "geometry": {"coordinates":[-71.420333,41.8282],"type":"Point"}
}