{
  "type": "Feature",
  "properties": {
    "iso:country":"US",
    "sg:address":"1220 Pontiac Ave",
    "sg:city":"Cranston",
    "sg:classifiers":[
        {
            "category":"Professional",
            "subcategory":"Lawyer & Legal Services",
            "type":"Services"
        }
    ],
    "sg:phone":"+1 401 944 5820",
    "sg:postcode":"02920",
    "sg:province":"RI",
    "sg:tags":[
        "attorney"
    ],
    "wof:name":"Joovelegian & Joovelegian",
    "wof:placetype":"venue"
},
  "geometry": {"coordinates":[-71.452849,41.748144],"type":"Point"}
}