{
  "type": "Feature",
  "properties": {
    "addr:full":"305 Quaker Ln West Warwick RI 02893",
    "addr:housenumber":"305",
    "addr:postcode":"02893",
    "addr:street":"Quaker Ln",
    "iso:country":"US",
    "sg:address":"305 Quaker Ln",
    "sg:city":"West Warwick",
    "sg:classifiers":[
        {
            "category":"Restaurant",
            "type":"Food & Drink"
        }
    ],
    "sg:menulink":"http://www.allmenus.com/ri/warwick/176637-kfc---kentucky-fried-chicken/menu/",
    "sg:phone":"+1 401 821 0556",
    "sg:postcode":"02893",
    "sg:province":"RI",
    "sg:tags":[
        "american",
        "chicken"
    ],
    "wof:name":"KFC - Kentucky Fried Chicken",
    "wof:placetype":"venue"
},
  "geometry": {"coordinates":[-71.501051,41.687798],"type":"Point"}
}