{
  "type": "Feature",
  "properties": {
    "addr:full":"400 Scituate Ave Cranston RI 02921",
    "addr:housenumber":"400",
    "addr:postcode":"02921",
    "addr:street":"Scituate Ave",
    "iso:country":"US",
    "sg:address":"400 Scituate Ave",
    "sg:city":"Cranston",
    "sg:classifiers":[
        {
            "category":"Building & Trades",
            "subcategory":"Construction",
            "type":"Services"
        }
    ],
    "sg:phone":"+1 401 233 0400",
    "sg:postcode":"02921",
    "sg:province":"RI",
    "sg:tags":[
        "hanging",
        "contractor"
    ],
    "wof:name":"Joseph Tavone Painting",
    "wof:placetype":"venue"
},
  "geometry": {"coordinates":[-71.48898800000001,41.778704],"type":"Point"}
}