{
  "type": "Feature",
  "properties": {
    "iso:country":"US",
    "sg:address":"25 Bath St",
    "sg:city":"Providence",
    "sg:classifiers":[
        {
            "category":"Food & Beverages",
            "subcategory":"Meat & Fish",
            "type":"Retail Goods"
        }
    ],
    "sg:phone":"+1 401 421 5668",
    "sg:postcode":"02908",
    "sg:province":"RI",
    "sg:tags":[
        "shop"
    ],
    "sg:website":"www.qualitybeefcompany.com",
    "wof:name":"Quality Beef Co Inc",
    "wof:placetype":"venue"
},
  "geometry": {"coordinates":[-71.423897,41.830601],"type":"Point"}
}