{
  "type": "Feature",
  "properties": {
    "iso:country":"US",
    "sg:address":"7595 Post Rd",
    "sg:city":"North Kingstown",
    "sg:classifiers":[
        {
            "category":"Restaurant",
            "type":"Food & Drink"
        }
    ],
    "sg:phone":"+1 401 294 4141",
    "sg:postcode":"02852",
    "sg:province":"RI",
    "wof:name":"Filippou's 2 New York System",
    "wof:placetype":"venue"
},
  "geometry": {"coordinates":[-71.456822,41.593272],"type":"Point"}
}