{
  "type": "Feature",
  "properties": {
    "iso:country":"US",
    "sg:address":"1639 Warwick Ave",
    "sg:city":"Warwick",
    "sg:classifiers":[
        {
            "category":"Sports & Exercise",
            "subcategory":"Gym",
            "type":"Entertainment"
        }
    ],
    "sg:phone":"+1 401 732 2899",
    "sg:postcode":"02889",
    "sg:province":"RI",
    "sg:tags":[
        "fitness",
        "physical",
        "facility"
    ],
    "wof:name":"Body In Action",
    "wof:placetype":"venue"
},
  "geometry": {"coordinates":[-71.406847,41.731899],"type":"Point"}
}