{
  "type": "Feature",
  "properties": {
    "addr:full":"1 Greco Ln Providence RI 02909",
    "addr:housenumber":"1",
    "addr:postcode":"02909",
    "addr:street":"Greco Ln",
    "iso:country":"US",
    "sg:address":"1 Greco Ln",
    "sg:city":"Providence",
    "sg:classifiers":[
        {
            "category":"Manufacturing",
            "subcategory":"Tools & Machinery",
            "type":"Manufacturing & Wholesale Goods"
        }
    ],
    "sg:phone":"+1 401 421 9306",
    "sg:postcode":"02909",
    "sg:province":"RI",
    "sg:tags":[
        "plating",
        "finish",
        "supply",
        "mfg",
        "metal",
        "equipment",
        "as",
        "such"
    ],
    "sg:website":"www.grecobrothers.com",
    "wof:name":"Greco Brothers Inc",
    "wof:placetype":"venue"
},
  "geometry": {"coordinates":[-71.441605,41.820437],"type":"Point"}
}