{
  "type": "Feature",
  "properties": {
    "iso:country":"US",
    "sg:address":"1775 Atwood Ave",
    "sg:city":"Johnston",
    "sg:classifiers":[
        {
            "category":"Manufacturing",
            "subcategory":"Jewelry",
            "type":"Manufacturing & Wholesale Goods"
        }
    ],
    "sg:phone":"+1 401 943 0626",
    "sg:postcode":"02919",
    "sg:province":"RI",
    "sg:tags":[
        "precious",
        "metal",
        "mfg"
    ],
    "wof:name":"Dees Mar Jewelry",
    "wof:placetype":"venue"
},
  "geometry": {"coordinates":[-71.504114,41.840954],"type":"Point"}
}