{
  "type": "Feature",
  "properties": {
    "addr:full":"206 Broad St Providence RI 02903",
    "addr:housenumber":"206",
    "addr:postcode":"02903",
    "addr:street":"Broad St",
    "iso:country":"US",
    "sg:address":"206 Broad St",
    "sg:city":"Providence",
    "sg:classifiers":[
        {
            "category":"Building & Trades",
            "subcategory":"Construction",
            "type":"Services"
        }
    ],
    "sg:phone":"+1 401 273 5131",
    "sg:postcode":"02903",
    "sg:province":"RI",
    "sg:tags":[
        "contractor"
    ],
    "wof:name":"Continental Building",
    "wof:placetype":"venue"
},
  "geometry": {"coordinates":[-71.418543,41.81665],"type":"Point"}
}