{
  "type": "Feature",
  "properties": {
    "addr:full":"889 Dexter St Central Falls RI 02863",
    "addr:housenumber":"889",
    "addr:postcode":"02863",
    "addr:street":"Dexter St",
    "iso:country":"US",
    "sg:address":"889 Dexter St",
    "sg:city":"Central Falls",
    "sg:classifiers":[
        {
            "category":"Shopping",
            "subcategory":"Gifts & Souvenirs",
            "type":"Retail Goods"
        }
    ],
    "sg:phone":"+1 401 312 0000",
    "sg:postcode":"02863",
    "sg:province":"RI",
    "wof:name":"Variedades Mil",
    "wof:placetype":"venue"
},
  "geometry": {"coordinates":[-71.39936299999999,41.889107],"type":"Point"}
}