{
  "type": "Feature",
  "properties": {
    "iso:country":"US",
    "sg:address":"86 Calla St",
    "sg:city":"Providence",
    "sg:classifiers":[
        {
            "category":"Taxi",
            "type":"Transportation"
        }
    ],
    "sg:phone":"+1 401 241 5233",
    "sg:postcode":"02905",
    "sg:province":"RI",
    "sg:tags":[
        "taxicab"
    ],
    "wof:name":"Alexander Taxi",
    "wof:placetype":"venue"
},
  "geometry": {"coordinates":[-71.40516,41.789707],"type":"Point"}
}