{
  "type": "Feature",
  "properties": {
    "iso:country":"US",
    "sg:address":"696 Douglas Pike",
    "sg:city":"Smithfield",
    "sg:classifiers":[
        {
            "category":"Real Estate",
            "subcategory":"Real Estate Agent",
            "type":"Services"
        }
    ],
    "sg:phone":"+1 401 233 1948",
    "sg:postcode":"02917",
    "sg:province":"RI",
    "wof:name":"Richard Harrington Inc",
    "wof:placetype":"venue"
},
  "geometry": {"coordinates":[-71.50707,41.904157],"type":"Point"}
}