{
  "type": "Feature",
  "properties": {
    "iso:country":"US",
    "sg:address":"123 Smith Ave",
    "sg:city":"Greenville",
    "sg:classifiers":[
        {
            "category":"Professional",
            "subcategory":"Detective & Security Services",
            "type":"Services"
        }
    ],
    "sg:phone":"+1 401 949 1397",
    "sg:postcode":"02828",
    "sg:province":"RI",
    "sg:tags":[
        "car"
    ],
    "wof:name":"Surveillance & Security Svcs",
    "wof:placetype":"venue"
},
  "geometry": {"coordinates":[-71.572512,41.864251],"type":"Point"}
}