{
  "type": "Feature",
  "properties": {
    "addr:full":"184 Burnside Ave Woonsocket RI 02895",
    "addr:housenumber":"184",
    "addr:postcode":"02895",
    "addr:street":"Burnside Ave",
    "iso:country":"US",
    "sg:address":"184 Burnside Ave",
    "sg:city":"Woonsocket",
    "sg:classifiers":[
        {
            "category":"Manufacturing",
            "subcategory":"Metals",
            "type":"Manufacturing & Wholesale Goods"
        }
    ],
    "sg:phone":"+1 401 766 8689",
    "sg:postcode":"02895",
    "sg:province":"RI",
    "sg:tags":[
        "fabricator",
        "sheet"
    ],
    "sg:website":"www.brogil.com",
    "wof:name":"Brogil Industries Inc",
    "wof:placetype":"venue"
},
  "geometry": {"coordinates":[-71.499122,42.011832],"type":"Point"}
}