{
  "type": "Feature",
  "properties": {
    "iso:country":"US",
    "sg:address":"80 Half Moon Trl",
    "sg:city":"Wakefield",
    "sg:classifiers":[
        {
            "category":"Wholesale",
            "subcategory":"Seafood",
            "type":"Manufacturing & Wholesale Goods"
        }
    ],
    "sg:phone":"+1 401 789 2371",
    "sg:postcode":"02879",
    "sg:province":"RI",
    "wof:name":"F V Wallaby",
    "wof:placetype":"venue"
},
  "geometry": {"coordinates":[-71.460489,41.483201],"type":"Point"}
}