{
  "type": "Feature",
  "properties": {
    "iso:country":"US",
    "sg:address":"128 Summit St",
    "sg:city":"Pawtucket",
    "sg:classifiers":[
        {
            "category":"Food & Beverages",
            "subcategory":"Liquor & Beverages",
            "type":"Retail Goods"
        }
    ],
    "sg:phone":"+1 401 722 9775",
    "sg:postcode":"02860",
    "sg:province":"RI",
    "sg:tags":[
        "beer",
        "wine",
        "spirit",
        "alcoholic"
    ],
    "wof:name":"Colonial Liquors",
    "wof:placetype":"venue"
},
  "geometry": {"coordinates":[-71.37840300000001,41.873798],"type":"Point"}
}