{
  "type": "Feature",
  "properties": {
    "iso:country":"US",
    "sg:address":"64 Putnam Pike",
    "sg:city":"Johnston",
    "sg:classifiers":[
        {
            "category":"Restaurant",
            "type":"Food & Drink"
        }
    ],
    "sg:phone":"+1 401 232 1940",
    "sg:postcode":"02919",
    "sg:province":"RI",
    "sg:tags":[
        "pizza"
    ],
    "wof:name":"Divozzi & Sons Bakery & Pizzaria Inc",
    "wof:placetype":"venue"
},
  "geometry": {"coordinates":[-71.49193699999999,41.861449],"type":"Point"}
}