{
  "type": "Feature",
  "properties": {
    "iso:country":"US",
    "sg:address":"789 Washington St",
    "sg:city":"Coventry",
    "sg:classifiers":[
        {
            "category":"Wholesale",
            "subcategory":"Machinery & Supplies",
            "type":"Manufacturing & Wholesale Goods"
        }
    ],
    "sg:phone":"+1 401 615 2400",
    "sg:postcode":"02816",
    "sg:province":"RI",
    "sg:tags":[
        "fire",
        "department",
        "equipment"
    ],
    "wof:name":"Northeast Emergency Equipment",
    "wof:placetype":"venue"
},
  "geometry": {"coordinates":[-71.554211,41.693775],"type":"Point"}
}