{
  "type": "Feature",
  "properties": {
    "iso:country":"US",
    "sg:address":"30 Fairview Ave",
    "sg:city":"Middletown",
    "sg:classifiers":[
        {
            "category":"Manufacturing",
            "subcategory":"Signs",
            "type":"Manufacturing & Wholesale Goods"
        }
    ],
    "sg:phone":"+1 401 841 5498",
    "sg:postcode":"02842",
    "sg:province":"RI",
    "sg:tags":[
        "advertising",
        "specialty"
    ],
    "wof:name":"Renaissance Custom Signs",
    "wof:placetype":"venue"
},
  "geometry": {"coordinates":[-71.30107599999999,41.508525],"type":"Point"}
}