{
  "type": "Feature",
  "properties": {
    "iso:country":"US",
    "sg:address":"61 Spruce St",
    "sg:city":"Westerly",
    "sg:classifiers":[
        {
            "category":"Retail",
            "subcategory":"Auto Repair",
            "type":"Services"
        }
    ],
    "sg:phone":"+1 401 596 6416",
    "sg:postcode":"02891",
    "sg:province":"RI",
    "sg:tags":[
        "repairing",
        "automobile",
        "general"
    ],
    "wof:name":"Sully's Auto Repair",
    "wof:placetype":"venue"
},
  "geometry": {"coordinates":[-71.82319200000001,41.382679],"type":"Point"}
}