{
  "type": "Feature",
  "properties": {
    "iso:country":"US",
    "sg:address":"4 Mendon Rd",
    "sg:city":"Cumberland",
    "sg:classifiers":[
        {
            "category":"Personal",
            "subcategory":"Tanning Parlor",
            "type":"Services"
        }
    ],
    "sg:phone":"+1 401 729 4826",
    "sg:postcode":"02864",
    "sg:province":"RI",
    "wof:name":"Exotic Tans",
    "wof:placetype":"venue"
},
  "geometry": {"coordinates":[-71.40335399999999,41.911895],"type":"Point"}
}