{
  "type": "Feature",
  "properties": {
    "iso:country":"US",
    "sg:address":"36 Exchange Ter",
    "sg:city":"Providence",
    "sg:classifiers":[
        {
            "category":"Professional",
            "subcategory":"Accounting & Tax Preparation",
            "type":"Services"
        }
    ],
    "sg:phone":"+1 401 273 7600",
    "sg:postcode":"02903",
    "sg:province":"RI",
    "sg:tags":[
        "accountant"
    ],
    "wof:name":"Restivo Monacelli",
    "wof:placetype":"venue"
},
  "geometry": {"coordinates":[-71.413839,41.825449],"type":"Point"}
}