{
  "type": "Feature",
  "properties": {
    "addr:full":"790 Centre of New England Blvd Coventry RI 02816",
    "addr:housenumber":"790",
    "addr:postcode":"02816",
    "addr:street":"Centre Of New;Blvd",
    "iso:country":"US",
    "sg:address":"790 Centre of New England Blvd",
    "sg:city":"Coventry",
    "sg:classifiers":[
        {
            "category":"Retail",
            "subcategory":"Auto Repair",
            "type":"Services"
        }
    ],
    "sg:phone":"+1 401 821 8500",
    "sg:postcode":"02816",
    "sg:province":"RI",
    "sg:tags":[
        "repairing",
        "automobile"
    ],
    "wof:name":"Monro Muffler Brake & Svc",
    "wof:placetype":"venue"
},
  "geometry": {"coordinates":[-71.570905,41.661915],"type":"Point"}
}