{
  "type": "Feature",
  "properties": {
    "addr:full":"215 Washington St Central Falls RI 02863",
    "addr:housenumber":"215",
    "addr:postcode":"02863",
    "addr:street":"Washington St",
    "iso:country":"US",
    "sg:address":"215 Washington St",
    "sg:city":"Central Falls",
    "sg:classifiers":[
        {
            "category":"Organizations",
            "subcategory":"Religious Organization",
            "type":"Services"
        }
    ],
    "sg:phone":"+1 401 724 0090",
    "sg:postcode":"02863",
    "sg:province":"RI",
    "sg:tags":[
        "church"
    ],
    "wof:name":"St Ephraim's Church",
    "wof:placetype":"venue"
},
  "geometry": {"coordinates":[-71.393219,41.892132],"type":"Point"}
}