{
  "type": "Feature",
  "properties": {
    "iso:country":"US",
    "sg:address":"918 Cranston St",
    "sg:city":"Cranston",
    "sg:classifiers":[
        {
            "category":"Real Estate",
            "subcategory":"Real Estate Agent",
            "type":"Services"
        }
    ],
    "sg:phone":"+1 401 942 1010",
    "sg:postcode":"02920",
    "sg:province":"RI",
    "wof:name":"Quinn Real Estate Agency",
    "wof:placetype":"venue"
},
  "geometry": {"coordinates":[-71.444687,41.80204],"type":"Point"}
}