{
  "type": "Feature",
  "properties": {
    "iso:country":"US",
    "sg:address":"674 Hope St",
    "sg:city":"Bristol",
    "sg:classifiers":[
        {
            "category":"Professional",
            "subcategory":"Lawyer & Legal Services",
            "type":"Services"
        }
    ],
    "sg:phone":"+1 401 253 0100",
    "sg:postcode":"02809",
    "sg:province":"RI",
    "sg:tags":[
        "attorney"
    ],
    "wof:name":"Jane F Howlett",
    "wof:placetype":"venue"
},
  "geometry": {"coordinates":[-71.27708699999999,41.67204],"type":"Point"}
}