{
  "type": "Feature",
  "properties": {
    "addr:full":"57 Everett St Middletown RI 02842",
    "addr:housenumber":"57",
    "addr:postcode":"02842",
    "addr:street":"Everett St",
    "iso:country":"US",
    "sg:address":"57 Everett St",
    "sg:city":"Middletown",
    "sg:classifiers":[
        {
            "category":"Retail",
            "subcategory":"Repair Shop",
            "type":"Services"
        }
    ],
    "sg:phone":"+1 401 847 2449",
    "sg:postcode":"02842",
    "sg:province":"RI",
    "wof:name":"Lyons Fmly Clg & Restorations",
    "wof:placetype":"venue"
},
  "geometry": {"coordinates":[-71.298649,41.510992],"type":"Point"}
}