{
  "type": "Feature",
  "properties": {
    "iso:country":"US",
    "sg:address":"2465 W Shore Rd",
    "sg:city":"Warwick",
    "sg:classifiers":[
        {
            "category":"Professional",
            "subcategory":"Management & Consulting",
            "type":"Services"
        },
        {
            "category":"Building & Trades",
            "subcategory":"Landscaping Services",
            "type":"Services"
        }
    ],
    "sg:phone":"+1 401 352 0222",
    "sg:postcode":"02889",
    "sg:province":"RI",
    "sg:tags":[
        "landscape",
        "contractor"
    ],
    "wof:name":"Colbalt Industries Inc",
    "wof:placetype":"venue"
},
  "geometry": {"coordinates":[-71.41215200000001,41.704183],"type":"Point"}
}