{
  "type": "Feature",
  "properties": {
    "iso:country":"US",
    "sg:address":"1184 Old Smithfield Rd",
    "sg:city":"North Smithfield",
    "sg:classifiers":[
        {
            "category":"Retail",
            "subcategory":"Auto Repair",
            "type":"Services"
        }
    ],
    "sg:phone":"+1 401 769 4327",
    "sg:postcode":"02896",
    "sg:province":"RI",
    "sg:tags":[
        "repairing",
        "automobile"
    ],
    "wof:name":"All Gears Transmissions",
    "wof:placetype":"venue"
},
  "geometry": {"coordinates":[-71.489092,41.963825],"type":"Point"}
}