{
  "type": "Feature",
  "properties": {
    "addr:full":"80 Stone Church Rd Tiverton RI 02878",
    "addr:housenumber":"80",
    "addr:postcode":"02878",
    "addr:street":"Stone Church Rd",
    "iso:country":"US",
    "sg:address":"80 Stone Church Rd",
    "sg:city":"Tiverton",
    "sg:classifiers":[
        {
            "category":"Building & Trades",
            "subcategory":"Construction",
            "type":"Services"
        }
    ],
    "sg:phone":"+1 401 683 1784",
    "sg:postcode":"02878",
    "sg:province":"RI",
    "sg:tags":[
        "general",
        "contractor"
    ],
    "wof:name":"K C Construction Inc",
    "wof:placetype":"venue"
},
  "geometry": {"coordinates":[-71.148635,41.567752],"type":"Point"}
}