{
  "type": "Feature",
  "properties": {
    "iso:country":"US",
    "sg:address":"102 Fountain St",
    "sg:city":"Providence",
    "sg:classifiers":[
        {
            "category":"Professional",
            "subcategory":"Business Services",
            "type":"Services"
        }
    ],
    "sg:phone":"+1 401 454 0790",
    "sg:postcode":"02903",
    "sg:province":"RI",
    "sg:tags":[
        "delivery",
        "courier"
    ],
    "wof:name":"Greyhound Package Express",
    "wof:placetype":"venue"
},
  "geometry": {"coordinates":[-71.416,41.823601],"type":"Point"}
}