{
  "type": "Feature",
  "properties": {
    "iso:country":"US",
    "sg:address":"64 Dewey Ave",
    "sg:city":"Warwick",
    "sg:classifiers":[
        {
            "category":"Professional",
            "subcategory":"Management & Consulting",
            "type":"Services"
        }
    ],
    "sg:phone":"+1 401 381 0300",
    "sg:postcode":"02886",
    "sg:province":"RI",
    "sg:tags":[
        "consultant",
        "automation"
    ],
    "wof:name":"Fluid Power Automation LLC",
    "wof:placetype":"venue"
},
  "geometry": {"coordinates":[-71.43217,41.732967],"type":"Point"}
}