{
  "type": "Feature",
  "properties": {
    "iso:country":"US",
    "sg:address":"1516 Newport Ave",
    "sg:city":"Pawtucket",
    "sg:classifiers":[
        {
            "category":"Food & Beverages",
            "subcategory":"Liquor & Beverages",
            "type":"Retail Goods"
        }
    ],
    "sg:phone":"+1 401 729 7400",
    "sg:postcode":"02861",
    "sg:province":"RI",
    "sg:tags":[
        "beer",
        "wine",
        "spirit",
        "alcoholic"
    ],
    "wof:name":"Borderline Liquor",
    "wof:placetype":"venue"
},
  "geometry": {"coordinates":[-71.353897,41.894199],"type":"Point"}
}