{
  "type": "Feature",
  "properties": {
    "addr:full":"199 Ausdale Rd Cranston RI 02910",
    "addr:housenumber":"199",
    "addr:postcode":"02910",
    "addr:street":"Ausdale Rd",
    "iso:country":"US",
    "sg:address":"199 Ausdale Rd",
    "sg:city":"Cranston",
    "sg:classifiers":[
        {
            "category":"Wholesale",
            "subcategory":"Medical Equipment & Supplies",
            "type":"Manufacturing & Wholesale Goods"
        }
    ],
    "sg:phone":"+1 401 946 3512",
    "sg:postcode":"02910",
    "sg:province":"RI",
    "sg:tags":[
        "dental"
    ],
    "wof:name":"Hodosh Dental Supply Co",
    "wof:placetype":"venue"
},
  "geometry": {"coordinates":[-71.45162000000001,41.781457],"type":"Point"}
}