{
  "type": "Feature",
  "properties": {
    "iso:country":"US",
    "sg:address":"685 Old Smithfield Rd",
    "sg:city":"North Smithfield",
    "sg:classifiers":[
        {
            "category":"Restaurant",
            "type":"Food & Drink"
        }
    ],
    "sg:phone":"+1 401 762 9211",
    "sg:postcode":"02896",
    "sg:province":"RI",
    "sg:tags":[
        "eating"
    ],
    "wof:name":"Kennedy's Lunch",
    "wof:placetype":"venue"
},
  "geometry": {"coordinates":[-71.501335,41.970249],"type":"Point"}
}