{
  "type": "Feature",
  "properties": {
    "iso:country":"US",
    "sg:address":"1 Reservoir Rd",
    "sg:city":"Cumberland",
    "sg:classifiers":[
        {
            "category":"Shopping",
            "subcategory":"Gifts & Souvenirs",
            "type":"Retail Goods"
        }
    ],
    "sg:phone":"+1 401 334 0447",
    "sg:postcode":"02864",
    "sg:province":"RI",
    "sg:tags":[
        "basket",
        "parcel"
    ],
    "wof:name":"Baskets In The Loft",
    "wof:placetype":"venue"
},
  "geometry": {"coordinates":[-71.411867,41.991046],"type":"Point"}
}