{
  "type": "Feature",
  "properties": {
    "iso:country":"US",
    "sg:address":"199 Amaral St",
    "sg:city":"Riverside",
    "sg:classifiers":[
        {
            "category":"Wholesale",
            "subcategory":"Chemicals & Plastics",
            "type":"Manufacturing & Wholesale Goods"
        }
    ],
    "sg:phone":"+1 401 435 8800",
    "sg:postcode":"02915",
    "sg:province":"RI",
    "wof:name":"Soluol",
    "wof:placetype":"venue"
},
  "geometry": {"coordinates":[-71.349228,41.802116],"type":"Point"}
}