{
  "type": "Feature",
  "properties": {
    "iso:country":"US",
    "sg:address":"1 Cumberland St",
    "sg:city":"Woonsocket",
    "sg:classifiers":[
        {
            "category":"Insurance",
            "subcategory":"Insurance Agent",
            "type":"Services"
        }
    ],
    "sg:phone":"+1 401 766 1742",
    "sg:postcode":"02895",
    "sg:province":"RI",
    "wof:name":"Primerica Financial Svc",
    "wof:placetype":"venue"
},
  "geometry": {"coordinates":[-71.502937,42.008072],"type":"Point"}
}