{
  "type": "Feature",
  "properties": {
    "iso:country":"US",
    "sg:address":"11 Jefferson St",
    "sg:city":"Warren",
    "sg:classifiers":[
        {
            "category":"Organizations",
            "subcategory":"Community Association",
            "type":"Services"
        }
    ],
    "sg:phone":"+1 401 245 9240",
    "sg:postcode":"02885",
    "sg:province":"RI",
    "sg:tags":[
        "military"
    ],
    "wof:name":"American Legion Post 11",
    "wof:placetype":"venue"
},
  "geometry": {"coordinates":[-71.283512,41.72919],"type":"Point"}
}