{
  "type": "Feature",
  "properties": {
    "addr:full":"1339 Smith St Providence RI 02908",
    "addr:housenumber":"1339",
    "addr:postcode":"02908",
    "addr:street":"Smith St",
    "iso:country":"US",
    "sg:address":"1339 Smith St",
    "sg:city":"Providence",
    "sg:classifiers":[
        {
            "category":"Health Services",
            "subcategory":"Doctor",
            "type":"Services"
        }
    ],
    "sg:phone":"+1 401 351 1900",
    "sg:postcode":"02908",
    "sg:province":"RI",
    "sg:tags":[
        "medicine",
        "internal"
    ],
    "wof:name":"Farina Anthony G MD",
    "wof:placetype":"venue"
},
  "geometry": {"coordinates":[-71.45589200000001,41.848122],"type":"Point"}
}