{
  "type": "Feature",
  "properties": {
    "iso:country":"US",
    "sg:address":"1160 Cranston St",
    "sg:city":"Cranston",
    "sg:classifiers":[
        {
            "category":"Manufacturing",
            "subcategory":"Metals",
            "type":"Manufacturing & Wholesale Goods"
        }
    ],
    "sg:phone":"+1 401 942 8000",
    "sg:postcode":"02920",
    "sg:province":"RI",
    "sg:tags":[
        "heat",
        "mfg"
    ],
    "sg:website":"www.taco-hvac.com",
    "wof:name":"Taco Inc",
    "wof:placetype":"venue"
},
  "geometry": {"coordinates":[-71.449844,41.794807],"type":"Point"}
}