{
  "type": "Feature",
  "properties": {
    "addr:full":"8 Zoar Ave Johnston RI 02919",
    "addr:housenumber":"8",
    "addr:postcode":"02919",
    "addr:street":"Zoar Ave",
    "iso:country":"US",
    "sg:address":"8 Zoar Ave",
    "sg:city":"Johnston",
    "sg:classifiers":[
        {
            "category":"Building & Trades",
            "subcategory":"Construction",
            "type":"Services"
        }
    ],
    "sg:phone":"+1 401 272 4741",
    "sg:postcode":"02919",
    "sg:province":"RI",
    "sg:tags":[
        "contractor"
    ],
    "wof:name":"M & J Constr Co Inc",
    "wof:placetype":"venue"
},
  "geometry": {"coordinates":[-71.474926,41.826443],"type":"Point"}
}