{
  "type": "Feature",
  "properties": {
    "addr:full":"606 Metacom Ave Warren RI 02885",
    "addr:housenumber":"606",
    "addr:postcode":"02885",
    "addr:street":"Metacom Ave",
    "iso:country":"US",
    "sg:address":"606 Metacom Ave",
    "sg:city":"Warren",
    "sg:classifiers":[
        {
            "category":"Health Services",
            "subcategory":"Chiropractor",
            "type":"Services"
        }
    ],
    "sg:phone":"+1 401 245 6294",
    "sg:postcode":"02885",
    "sg:province":"RI",
    "wof:name":"Van Amberg Family Chiropractic",
    "wof:placetype":"venue"
},
  "geometry": {"coordinates":[-71.268936,41.720062],"type":"Point"}
}