{
  "type": "Feature",
  "properties": {
    "iso:country":"US",
    "sg:address":"14 Countryside Dr",
    "sg:city":"Johnston",
    "sg:classifiers":[
        {
            "category":"Building & Trades",
            "subcategory":"Construction",
            "type":"Services"
        }
    ],
    "sg:phone":"+1 401 349 0590",
    "sg:postcode":"02919",
    "sg:province":"RI",
    "sg:tags":[
        "nonresidential",
        "electrical",
        "build",
        "contractor"
    ],
    "wof:name":"Michael Property Maintenance",
    "wof:placetype":"venue"
},
  "geometry": {"coordinates":[-71.547387,41.856936],"type":"Point"}
}