{
  "type": "Feature",
  "properties": {
    "addr:full":"1 Waterman Ave East Providence RI 02914",
    "addr:housenumber":"1",
    "addr:postcode":"02914",
    "addr:street":"Waterman Ave",
    "iso:country":"US",
    "sg:address":"1 Waterman Ave",
    "sg:city":"East Providence",
    "sg:classifiers":[
        {
            "category":"Retail",
            "subcategory":"Auto Repair",
            "type":"Services"
        }
    ],
    "sg:phone":"+1 401 434 3840",
    "sg:postcode":"02914",
    "sg:province":"RI",
    "sg:tags":[
        "repairing",
        "automobile"
    ],
    "wof:name":"Sunrise Auto Ctr",
    "wof:placetype":"venue"
},
  "geometry": {"coordinates":[-71.378395,41.826088],"type":"Point"}
}