{
  "type": "Feature",
  "properties": {
    "iso:country":"US",
    "sg:address":"685 Metacom Ave",
    "sg:city":"Bristol",
    "sg:classifiers":[
        {
            "category":"Sports & Exercise",
            "subcategory":"Gym",
            "type":"Entertainment"
        }
    ],
    "sg:phone":"+1 401 254 3900",
    "sg:postcode":"02809",
    "sg:province":"RI",
    "sg:tags":[
        "facility",
        "club",
        "gymnasium",
        "health",
        "fitness",
        "studio",
        "physical"
    ],
    "wof:name":"Bristol Total Fitness Inc",
    "wof:placetype":"venue"
},
  "geometry": {"coordinates":[-71.26544699999999,41.702212],"type":"Point"}
}