{
  "type": "Feature",
  "properties": {
    "iso:country":"US",
    "sg:address":"137 Pettaconsett Ave",
    "sg:city":"Warwick",
    "sg:classifiers":[
        {
            "category":"Organizations",
            "subcategory":"Membership Organization",
            "type":"Services"
        }
    ],
    "sg:phone":"+1 401 467 7712",
    "sg:postcode":"02888",
    "sg:province":"RI",
    "sg:tags":[
        "insurance"
    ],
    "wof:name":"Ocean State Shorthair CLU",
    "wof:placetype":"venue"
},
  "geometry": {"coordinates":[-71.430476,41.748564],"type":"Point"}
}