{
  "type": "Feature",
  "properties": {
    "addr:full":"648 Thames St Newport RI 02840",
    "addr:housenumber":"648",
    "addr:postcode":"02840",
    "addr:street":"Thames St",
    "iso:country":"US",
    "sg:address":"648 Thames St",
    "sg:city":"Newport",
    "sg:classifiers":[
        {
            "category":"Retail",
            "subcategory":"Portrait Studio",
            "type":"Services"
        }
    ],
    "sg:phone":"+1 401 848 0027",
    "sg:postcode":"02840",
    "sg:province":"RI",
    "sg:tags":[
        "photo"
    ],
    "sg:website":"www.margolisphotography.com",
    "wof:name":"Margolis Photography Studio",
    "wof:placetype":"venue"
},
  "geometry": {"coordinates":[-71.31379200000001,41.474848],"type":"Point"}
}