{
  "type": "Feature",
  "properties": {
    "iso:country":"US",
    "sg:address":"864 Old Greenwich Dr",
    "sg:city":"East Greenwich",
    "sg:classifiers":[
        {
            "category":"Recreation",
            "type":"Entertainment"
        }
    ],
    "sg:phone":"+1 401 884 6773",
    "sg:postcode":"02818",
    "sg:province":"RI",
    "sg:tags":[
        "riding",
        "academy"
    ],
    "wof:name":"Heritage Equestrian Ctr",
    "wof:placetype":"venue"
},
  "geometry": {"coordinates":[-71.478387,41.655052],"type":"Point"}
}