{
  "type": "Feature",
  "properties": {
    "addr:full":"68 Wollaston St Cranston RI 02910",
    "addr:housenumber":"68",
    "addr:postcode":"02910",
    "addr:street":"Wollaston St",
    "iso:country":"US",
    "sg:address":"68 Wollaston St",
    "sg:city":"Cranston",
    "sg:classifiers":[
        {
            "category":"Manufacturing",
            "subcategory":"Jewelry",
            "type":"Manufacturing & Wholesale Goods"
        }
    ],
    "sg:phone":"+1 401 461 4940",
    "sg:postcode":"02910",
    "sg:province":"RI",
    "wof:name":"So-Go Research Development",
    "wof:placetype":"venue"
},
  "geometry": {"coordinates":[-71.43836899999999,41.778358],"type":"Point"}
}