{
  "type": "Feature",
  "properties": {
    "iso:country":"US",
    "sg:address":"200 Wayland Ave",
    "sg:city":"Providence",
    "sg:classifiers":[
        {
            "category":"Shopping",
            "subcategory":"Clothing, Apparel, & Fashions",
            "type":"Retail Goods"
        }
    ],
    "sg:phone":"+1 401 331 8811",
    "sg:postcode":"02906",
    "sg:province":"RI",
    "sg:tags":[
        "clothing",
        "women's"
    ],
    "wof:name":"Williams Dorothy",
    "wof:placetype":"venue"
},
  "geometry": {"coordinates":[-71.38800000000001,41.829498],"type":"Point"}
}