{
  "type": "Feature",
  "properties": {
    "iso:country":"US",
    "sg:address":"130 Sanctuary Rd",
    "sg:city":"Charlestown",
    "sg:classifiers":[
        {
            "category":"Building & Trades",
            "subcategory":"Construction",
            "type":"Services"
        }
    ],
    "sg:phone":"+1 401 213 6262",
    "sg:postcode":"02813",
    "sg:province":"RI",
    "sg:tags":[
        "contractor"
    ],
    "wof:name":"Re Audette and Son",
    "wof:placetype":"venue"
},
  "geometry": {"coordinates":[-71.683312,41.376139],"type":"Point"}
}