{
  "type": "Feature",
  "properties": {
    "iso:country":"US",
    "sg:address":"55 4th Ave",
    "sg:city":"East Greenwich",
    "sg:classifiers":[
        {
            "category":"Organizations",
            "subcategory":"Religious Organization",
            "type":"Services"
        }
    ],
    "sg:phone":"+1 401 884 1618",
    "sg:postcode":"02818",
    "sg:province":"RI",
    "sg:tags":[
        "school"
    ],
    "wof:name":"Our Lady Mercy Regional School",
    "wof:placetype":"venue"
},
  "geometry": {"coordinates":[-71.456991,41.654235],"type":"Point"}
}