{
  "type": "Feature",
  "properties": {
    "addr:full":"1175 Boston Neck Rd Narragansett RI 02882",
    "addr:housenumber":"1175",
    "addr:postcode":"02882",
    "addr:street":"Boston Neck Rd",
    "iso:country":"US",
    "sg:address":"1175 Boston Neck Rd",
    "sg:city":"Narragansett",
    "sg:classifiers":[
        {
            "category":"Food & Beverages",
            "subcategory":"Specialty",
            "type":"Retail Goods"
        },
        {
            "category":"Restaurant",
            "type":"Food & Drink"
        }
    ],
    "sg:phone":"+1 401 782 9920",
    "sg:postcode":"02882",
    "sg:province":"RI",
    "sg:tags":[
        "tea",
        "coffee",
        "eating"
    ],
    "wof:name":"Coffee N' Bagel Connection",
    "wof:placetype":"venue"
},
  "geometry": {"coordinates":[-71.43808300000001,41.491545],"type":"Point"}
}