{
  "type": "Feature",
  "properties": {
    "iso:country":"US",
    "sg:address":"80 Hillside Rd",
    "sg:city":"Cranston",
    "sg:classifiers":[
        {
            "category":"Shopping",
            "subcategory":"Clothing, Apparel, & Fashions",
            "type":"Retail Goods"
        }
    ],
    "sg:phone":"+1 401 946 3100",
    "sg:postcode":"02920",
    "sg:province":"RI",
    "sg:tags":[
        "furnishing"
    ],
    "sg:website":"www.josbank.com",
    "wof:name":"Bank Joseph A Clothiers",
    "wof:placetype":"venue"
},
  "geometry": {"coordinates":[-71.458448,41.76339],"type":"Point"}
}