{
  "type": "Feature",
  "properties": {
    "iso:country":"US",
    "sg:address":"39 Sandy Bottom Rd",
    "sg:city":"Coventry",
    "sg:classifiers":[
        {
            "category":"Education",
            "subcategory":"Dance Studio",
            "type":"Public Place"
        }
    ],
    "sg:phone":"+1 401 822 4650",
    "sg:postcode":"02816",
    "sg:province":"RI",
    "wof:name":"Legein Dnce Acdemy Prfrmg Arts",
    "wof:placetype":"venue"
},
  "geometry": {"coordinates":[-71.56070800000001,41.6889],"type":"Point"}
}