{
  "type": "Feature",
  "properties": {
    "iso:country":"US",
    "sg:address":"1800 Post Rd",
    "sg:city":"Warwick",
    "sg:classifiers":[
        {
            "category":"Home & Garden",
            "subcategory":"Furniture",
            "type":"Retail Goods"
        }
    ],
    "sg:phone":"+1 401 737 0002",
    "sg:postcode":"02886",
    "sg:province":"RI",
    "wof:name":"Gilmore's Leather Showcase",
    "wof:placetype":"venue"
},
  "geometry": {"coordinates":[-71.436685,41.732505],"type":"Point"}
}