{
  "type": "Feature",
  "properties": {
    "iso:country":"US",
    "sg:address":"500 Angell St",
    "sg:city":"Providence",
    "sg:classifiers":[
        {
            "category":"Personal",
            "subcategory":"Beauty Salon",
            "type":"Services"
        }
    ],
    "sg:phone":"+1 401 457 5000",
    "sg:postcode":"02906",
    "sg:province":"RI",
    "wof:name":"Femme Fatale",
    "wof:placetype":"venue"
},
  "geometry": {"coordinates":[-71.387547,41.830255],"type":"Point"}
}