{
  "type": "Feature",
  "properties": {
    "addr:full":"80 Snow St Providence RI 02903",
    "addr:housenumber":"80",
    "addr:postcode":"02903",
    "addr:street":"Snow St",
    "iso:country":"US",
    "sg:address":"80 Snow St",
    "sg:city":"Providence",
    "sg:classifiers":[
        {
            "category":"Parking",
            "type":"Transportation"
        }
    ],
    "sg:phone":"+1 401 273 1615",
    "sg:postcode":"02903",
    "sg:province":"RI",
    "sg:tags":[
        "garage"
    ],
    "wof:name":"Intown Parking Lot",
    "wof:placetype":"venue"
},
  "geometry": {"coordinates":[-71.413888,41.821384],"type":"Point"}
}