{
  "type": "Feature",
  "properties": {
    "iso:country":"US",
    "sg:address":"379 Broadway",
    "sg:city":"Providence",
    "sg:classifiers":[
        {
            "category":"Shopping",
            "subcategory":"Gifts & Souvenirs",
            "type":"Retail Goods"
        }
    ],
    "sg:phone":"+1 401 273 8883",
    "sg:postcode":"02909",
    "sg:province":"RI",
    "sg:tags":[
        "flower"
    ],
    "sg:website":"www.relishprovidence.com",
    "wof:name":"Relish",
    "wof:placetype":"venue"
},
  "geometry": {"coordinates":[-71.430483,41.819548],"type":"Point"}
}