{
  "type": "Feature",
  "properties": {
    "addr:full":"12 Ann and Hope Way Cumberland RI 02864",
    "addr:housenumber":"12",
    "addr:postcode":"02864",
    "addr:street":"Ann And Hope Way",
    "iso:country":"US",
    "sg:address":"12 Ann and Hope Way",
    "sg:city":"Cumberland",
    "sg:classifiers":[
        {
            "category":"Retail",
            "subcategory":"Auto Repair",
            "type":"Services"
        }
    ],
    "sg:phone":"+1 401 334 0334",
    "sg:postcode":"02864",
    "sg:province":"RI",
    "sg:tags":[
        "body",
        "shop"
    ],
    "wof:name":"Blackstone Auto Sales & Body Inc",
    "wof:placetype":"venue"
},
  "geometry": {"coordinates":[-71.399597,41.913898],"type":"Point"}
}