{
  "type": "Feature",
  "properties": {
    "iso:country":"US",
    "sg:address":"128 High Meadow Ln",
    "sg:city":"Wakefield",
    "sg:classifiers":[
        {
            "category":"Wholesale",
            "subcategory":"Construction Materials",
            "type":"Manufacturing & Wholesale Goods"
        },
        {
            "category":"Manufacturing",
            "subcategory":"Leather Goods",
            "type":"Manufacturing & Wholesale Goods"
        }
    ],
    "sg:phone":"+1 401 792 7000",
    "sg:postcode":"02879",
    "sg:province":"RI",
    "sg:tags":[
        "fence",
        "mfg"
    ],
    "wof:name":"K 9 Containment Concepts",
    "wof:placetype":"venue"
},
  "geometry": {"coordinates":[-71.532633,41.466603],"type":"Point"}
}