{
  "type": "Feature",
  "properties": {
    "addr:full":"170 Royal Little Dr Providence RI 02904",
    "addr:housenumber":"170",
    "addr:postcode":"02904",
    "addr:street":"Royal Little Dr",
    "iso:country":"US",
    "sg:address":"170 Royal Little Dr",
    "sg:city":"Providence",
    "sg:classifiers":[
        {
            "category":"Bakery",
            "type":"Food & Drink"
        }
    ],
    "sg:phone":"+1 401 223 7100",
    "sg:postcode":"02904",
    "sg:province":"RI",
    "sg:tags":[
        "cake",
        "pastry",
        "wedding"
    ],
    "wof:name":"Pastry Gourmet, The",
    "wof:placetype":"venue"
},
  "geometry": {"coordinates":[-71.411304,41.851726],"type":"Point"}
}