{
  "type": "Feature",
  "properties": {
    "iso:country":"US",
    "sg:address":"44 Terrace Ave",
    "sg:city":"Pawtucket",
    "sg:classifiers":[
        {
            "category":"Building & Trades",
            "subcategory":"Construction",
            "type":"Services"
        }
    ],
    "sg:phone":"+1 401 724 4566",
    "sg:postcode":"02860",
    "sg:province":"RI",
    "sg:tags":[
        "roofing",
        "contractor"
    ],
    "wof:name":"A & J Home Exteriors",
    "wof:placetype":"venue"
},
  "geometry": {"coordinates":[-71.413337,41.866371],"type":"Point"}
}