{
  "type": "Feature",
  "properties": {
    "iso:country":"US",
    "sg:address":"15 View Ave",
    "sg:city":"Warwick",
    "sg:classifiers":[
        {
            "category":"Professional",
            "subcategory":"Management & Consulting",
            "type":"Services"
        }
    ],
    "sg:phone":"+1 401 738 8829",
    "sg:postcode":"02886",
    "sg:province":"RI",
    "sg:tags":[
        "advisory",
        "sales"
    ],
    "wof:name":"Delhagen Associates",
    "wof:placetype":"venue"
},
  "geometry": {"coordinates":[-71.448592,41.701743],"type":"Point"}
}