{
  "type": "Feature",
  "properties": {
    "iso:country":"US",
    "sg:address":"480 Valley St",
    "sg:city":"Providence",
    "sg:classifiers":[
        {
            "category":"Autos & Motor Vehicles",
            "subcategory":"Automobile Sales",
            "type":"Retail Goods"
        }
    ],
    "sg:phone":"+1 401 383 0803",
    "sg:postcode":"02908",
    "sg:province":"RI",
    "sg:tags":[
        "car",
        "dealer"
    ],
    "wof:name":"Parkway Auto Sales",
    "wof:placetype":"venue"
},
  "geometry": {"coordinates":[-71.434056,41.828524],"type":"Point"}
}