{
  "type": "Feature",
  "properties": {
    "addr:full":"56 Sprague St Providence RI 02907",
    "addr:housenumber":"56",
    "addr:postcode":"02907",
    "addr:street":"Sprague St",
    "iso:country":"US",
    "sg:address":"56 Sprague St",
    "sg:city":"Providence",
    "sg:classifiers":[
        {
            "category":"Manufacturing",
            "subcategory":"Metals",
            "type":"Manufacturing & Wholesale Goods"
        }
    ],
    "sg:phone":"+1 401 421 0840",
    "sg:postcode":"02907",
    "sg:province":"RI",
    "sg:tags":[
        "plating"
    ],
    "wof:name":"Austin Hard Chrome Plating",
    "wof:placetype":"venue"
},
  "geometry": {"coordinates":[-71.4268,41.809538],"type":"Point"}
}