{
  "type": "Feature",
  "properties": {
    "iso:country":"US",
    "sg:address":"1181 Kingstown Rd",
    "sg:city":"Wakefield",
    "sg:classifiers":[
        {
            "category":"Retail",
            "subcategory":"Repair Shop",
            "type":"Services"
        }
    ],
    "sg:phone":"+1 401 789 4455",
    "sg:postcode":"02879",
    "sg:province":"RI",
    "wof:name":"Seating Arrangement Inc",
    "wof:placetype":"venue"
},
  "geometry": {"coordinates":[-71.49851700000001,41.45112],"type":"Point"}
}