{
  "type": "Feature",
  "properties": {
    "iso:country":"US",
    "sg:address":"125 Valley St",
    "sg:city":"East Providence",
    "sg:classifiers":[
        {
            "category":"Manufacturing",
            "subcategory":"Signs",
            "type":"Manufacturing & Wholesale Goods"
        }
    ],
    "sg:phone":"+1 401 431 9191",
    "sg:postcode":"02914",
    "sg:province":"RI",
    "wof:name":"Richard Owens Assoc",
    "wof:placetype":"venue"
},
  "geometry": {"coordinates":[-71.38045200000001,41.823099],"type":"Point"}
}