{
  "type": "Feature",
  "properties": {
    "addr:full":"12 Carriage Dr Lincoln RI 02865",
    "addr:housenumber":"12",
    "addr:postcode":"02865",
    "addr:street":"Carriage Dr",
    "iso:country":"US",
    "sg:address":"12 Carriage Dr",
    "sg:city":"Lincoln",
    "sg:classifiers":[
        {
            "category":"Retail",
            "subcategory":"Laundry & Dry Cleaning",
            "type":"Services"
        }
    ],
    "sg:phone":"+1 401 728 4444",
    "sg:postcode":"02865",
    "sg:province":"RI",
    "wof:name":"Belisle's Coin Laundry",
    "wof:placetype":"venue"
},
  "geometry": {"coordinates":[-71.42432700000001,41.890068],"type":"Point"}
}