{
  "type": "Feature",
  "properties": {
    "iso:country":"US",
    "sg:address":"31 Buena Vista Dr",
    "sg:city":"North Kingstown",
    "sg:classifiers":[
        {
            "category":"Retail",
            "subcategory":"Repair Shop",
            "type":"Services"
        }
    ],
    "sg:phone":"+1 401 295 4319",
    "sg:postcode":"02852",
    "sg:province":"RI",
    "wof:name":"Hamilton Webb Clock Repair",
    "wof:placetype":"venue"
},
  "geometry": {"coordinates":[-71.42861499999999,41.555204],"type":"Point"}
}