{
  "type": "Feature",
  "properties": {
    "iso:country":"US",
    "sg:address":"149 Camp St",
    "sg:city":"Providence",
    "sg:classifiers":[
        {
            "category":"Food & Beverages",
            "subcategory":"Groceries & Convenience Stores",
            "type":"Retail Goods"
        }
    ],
    "sg:phone":"+1 401 490 6945",
    "sg:postcode":"02906",
    "sg:province":"RI",
    "wof:name":"Marks Grocery",
    "wof:placetype":"venue"
},
  "geometry": {"coordinates":[-71.402901,41.8423],"type":"Point"}
}