{
  "type": "Feature",
  "properties": {
    "addr:full":"2 Hammet Rd Jamestown RI 02816",
    "addr:housenumber":"2",
    "addr:postcode":"02816",
    "addr:street":"Hammet Rd",
    "iso:country":"US",
    "sg:address":"2 Hammet Rd",
    "sg:city":"Jamestown",
    "sg:classifiers":[
        {
            "category":"Building & Trades",
            "subcategory":"Cleaning & Sanitation",
            "type":"Services"
        }
    ],
    "sg:phone":"+1 401 423 0522",
    "sg:postcode":"02816",
    "sg:province":"RI",
    "sg:tags":[
        "maintenance"
    ],
    "wof:name":"Cover-Up Shop",
    "wof:placetype":"venue"
},
  "geometry": {"coordinates":[-71.662733,41.709911],"type":"Point"}
}