{
  "type": "Feature",
  "properties": {
    "iso:country":"US",
    "sg:address":"722 Oakland Beach Ave",
    "sg:city":"Warwick",
    "sg:classifiers":[
        {
            "category":"Organizations",
            "subcategory":"Religious Organization",
            "type":"Services"
        }
    ],
    "sg:phone":"+1 401 738 1800",
    "sg:postcode":"02889",
    "sg:province":"RI",
    "sg:tags":[
        "church"
    ],
    "wof:name":"St Rita's Church",
    "wof:placetype":"venue"
},
  "geometry": {"coordinates":[-71.398095,41.688886],"type":"Point"}
}