{
  "type": "Feature",
  "properties": {
    "addr:full":"11 Terrace Dr Bristol RI 02809",
    "addr:housenumber":"11",
    "addr:postcode":"02809",
    "addr:street":"Terrace Dr",
    "iso:country":"US",
    "sg:address":"11 Terrace Dr",
    "sg:city":"Bristol",
    "sg:classifiers":[
        {
            "category":"Retail",
            "subcategory":"Auto Repair",
            "type":"Services"
        }
    ],
    "sg:phone":"+1 401 245 5710",
    "sg:postcode":"02809",
    "sg:province":"RI",
    "sg:tags":[
        "automotive"
    ],
    "wof:name":"Ace Towing",
    "wof:placetype":"venue"
},
  "geometry": {"coordinates":[-71.278848,41.710129],"type":"Point"}
}