{
  "type": "Feature",
  "properties": {
    "iso:country":"US",
    "sg:address":"49 9th St",
    "sg:city":"East Providence",
    "sg:classifiers":[
        {
            "category":"Professional",
            "subcategory":"Computer Services",
            "type":"Services"
        }
    ],
    "sg:phone":"+1 401 434 1357",
    "sg:postcode":"02914",
    "sg:province":"RI",
    "sg:tags":[
        "datum"
    ],
    "wof:name":"JM Net Solutions",
    "wof:placetype":"venue"
},
  "geometry": {"coordinates":[-71.378795,41.813169],"type":"Point"}
}