{
  "type": "Feature",
  "properties": {
    "addr:full":"340 Burnt Hill Rd Hope RI 02831",
    "addr:housenumber":"340",
    "addr:postcode":"02831",
    "addr:street":"Burnt Hill Rd",
    "iso:country":"US",
    "sg:address":"340 Burnt Hill Rd",
    "sg:city":"Hope",
    "sg:classifiers":[
        {
            "category":"Professional",
            "subcategory":"Business Services",
            "type":"Services"
        }
    ],
    "sg:phone":"+1 401 823 5972",
    "sg:postcode":"02831",
    "sg:province":"RI",
    "wof:name":"Lutalia Enterprises LLC",
    "wof:placetype":"venue"
},
  "geometry": {"coordinates":[-71.606013,41.736955],"type":"Point"}
}