{
  "type": "Feature",
  "properties": {
    "addr:full":"261 Wickenden St Providence RI 02903",
    "addr:housenumber":"261",
    "addr:postcode":"02903",
    "addr:street":"Wickenden St",
    "iso:country":"US",
    "sg:address":"261 Wickenden St",
    "sg:city":"Providence",
    "sg:classifiers":[
        {
            "category":"Social Services",
            "type":"Services"
        }
    ],
    "sg:phone":"+1 401 272 2006",
    "sg:postcode":"02903",
    "sg:province":"RI",
    "sg:tags":[
        "counselor",
        "marriage",
        "family"
    ],
    "wof:name":"Gwendolyn Howard Dmin Licsw",
    "wof:placetype":"venue"
},
  "geometry": {"coordinates":[-71.397137,41.819462],"type":"Point"}
}