{
  "type": "Feature",
  "properties": {
    "iso:country":"US",
    "sg:address":"269 Main St",
    "sg:city":"Wakefield",
    "sg:classifiers":[
        {
            "category":"Shopping",
            "subcategory":"Optical Goods",
            "type":"Retail Goods"
        }
    ],
    "sg:phone":"+1 401 783 5089",
    "sg:postcode":"02879",
    "sg:province":"RI",
    "wof:name":"Wakefield Optical Shop",
    "wof:placetype":"venue"
},
  "geometry": {"coordinates":[-71.498142,41.439576],"type":"Point"}
}