{
  "type": "Feature",
  "properties": {
    "iso:country":"US",
    "sg:address":"149 Reservoir Ave",
    "sg:city":"Lincoln",
    "sg:classifiers":[
        {
            "category":"Retail",
            "subcategory":"Auto Repair",
            "type":"Services"
        }
    ],
    "sg:phone":"+1 401 725 8500",
    "sg:postcode":"02865",
    "sg:province":"RI",
    "sg:tags":[
        "wrecker"
    ],
    "wof:name":"Preferred Recovery",
    "wof:placetype":"venue"
},
  "geometry": {"coordinates":[-71.41417,41.879919],"type":"Point"}
}