{
  "type": "Feature",
  "properties": {
    "iso:country":"US",
    "sg:address":"54 Sutton St",
    "sg:city":"Providence",
    "sg:classifiers":[
        {
            "category":"Real Estate",
            "subcategory":"Real Estate Agent",
            "type":"Services"
        }
    ],
    "sg:phone":"+1 401 831 2073",
    "sg:postcode":"02903",
    "sg:province":"RI",
    "sg:tags":[
        "apartment"
    ],
    "wof:name":"Demco Realty",
    "wof:placetype":"venue"
},
  "geometry": {"coordinates":[-71.42910000000001,41.8232],"type":"Point"}
}