{
  "type": "Feature",
  "properties": {
    "addr:full":"300 Barton St Pawtucket RI 02860",
    "addr:housenumber":"300",
    "addr:postcode":"02860",
    "addr:street":"Barton St",
    "iso:country":"US",
    "sg:address":"300 Barton St",
    "sg:city":"Pawtucket",
    "sg:classifiers":[
        {
            "category":"Home & Garden",
            "subcategory":"Furniture",
            "type":"Retail Goods"
        }
    ],
    "sg:phone":"+1 401 728 7451",
    "sg:postcode":"02860",
    "sg:province":"RI",
    "sg:tags":[
        "store"
    ],
    "wof:name":"Pawtucket Discount Furniture",
    "wof:placetype":"venue"
},
  "geometry": {"coordinates":[-71.391391,41.87966],"type":"Point"}
}