{
  "type": "Feature",
  "properties": {
    "iso:country":"US",
    "sg:address":"1179 Mendon Rd",
    "sg:city":"Cumberland",
    "sg:classifiers":[
        {
            "category":"Shopping",
            "subcategory":"Florist",
            "type":"Retail Goods"
        }
    ],
    "sg:phone":"+1 401 334 2011",
    "sg:postcode":"02864",
    "sg:province":"RI",
    "wof:name":"Hill House Herb Gardens and Flower Shoppe",
    "wof:placetype":"venue"
},
  "geometry": {"coordinates":[-71.427002,41.933399],"type":"Point"}
}