{
  "type": "Feature",
  "properties": {
    "addr:full":"15 Courtney Ln Hope Valley RI 02832",
    "addr:housenumber":"15",
    "addr:postcode":"02832",
    "addr:street":"Courtney Ln",
    "iso:country":"US",
    "sg:address":"15 Courtney Ln",
    "sg:city":"Hope Valley",
    "sg:classifiers":[
        {
            "category":"Restaurant",
            "type":"Food & Drink"
        }
    ],
    "sg:phone":"+1 401 364 9307",
    "sg:postcode":"02832",
    "sg:province":"RI",
    "sg:tags":[
        "eating"
    ],
    "wof:name":"Westerly House of Pizza Inc",
    "wof:placetype":"venue"
},
  "geometry": {"coordinates":[-71.721143,41.446298],"type":"Point"}
}