{
  "type": "Feature",
  "properties": {
    "iso:country":"US",
    "sg:address":"346 Wood St",
    "sg:city":"Bristol",
    "sg:classifiers":[
        {
            "category":"Shopping",
            "subcategory":"Florist",
            "type":"Retail Goods"
        }
    ],
    "sg:phone":"+1 401 245 1348",
    "sg:postcode":"02809",
    "sg:province":"RI",
    "sg:website":"www.floralsymphony.com",
    "wof:name":"Floral Symphony",
    "wof:placetype":"venue"
},
  "geometry": {"coordinates":[-71.271385,41.672058],"type":"Point"}
}