{
  "type": "Feature",
  "properties": {
    "iso:country":"US",
    "sg:address":"31 Glen Rd",
    "sg:city":"Cranston",
    "sg:phone":"+1 401 467 5906",
    "sg:postcode":"02920",
    "sg:province":"RI",
    "sg:tags":[
        "product",
        "petroleum"
    ],
    "wof:name":"Linda Dicola",
    "wof:placetype":"venue"
},
  "geometry": {"coordinates":[-71.44612600000001,41.753459],"type":"Point"}
}