{
  "type": "Feature",
  "properties": {
    "iso:country":"US",
    "sg:address":"30 Martin St",
    "sg:city":"Pawtucket",
    "sg:classifiers":[
        {
            "category":"Health Services",
            "subcategory":"Doctor",
            "type":"Services"
        }
    ],
    "sg:phone":"+1 401 312 0093",
    "sg:postcode":"02861",
    "sg:province":"RI",
    "sg:tags":[
        "physician",
        "surgeon"
    ],
    "wof:name":"Rhode Island Family Care",
    "wof:placetype":"venue"
},
  "geometry": {"coordinates":[-71.36121900000001,41.871934],"type":"Point"}
}