{
  "type": "Feature",
  "properties": {
    "iso:country":"US",
    "sg:address":"745 Bullocks Point Ave",
    "sg:city":"Riverside",
    "sg:classifiers":[
        {
            "category":"Food & Beverages",
            "subcategory":"Groceries & Convenience Stores",
            "type":"Retail Goods"
        }
    ],
    "sg:phone":"+1 401 223 1299",
    "sg:postcode":"02915",
    "sg:province":"RI",
    "sg:tags":[
        "market"
    ],
    "wof:name":"Crescent Marketplace Inc",
    "wof:placetype":"venue"
},
  "geometry": {"coordinates":[-71.359962,41.758004],"type":"Point"}
}