{
  "type": "Feature",
  "properties": {
    "iso:country":"US",
    "sg:address":"1332 Smith St",
    "sg:city":"North Providence",
    "sg:classifiers":[
        {
            "category":"Health Services",
            "subcategory":"Doctor",
            "type":"Services"
        }
    ],
    "sg:phone":"+1 401 273 5277",
    "sg:postcode":"02911",
    "sg:province":"RI",
    "sg:tags":[
        "medicine",
        "internal"
    ],
    "wof:name":"Gauthier Edw J Phys",
    "wof:placetype":"venue"
},
  "geometry": {"coordinates":[-71.45610000000001,41.848],"type":"Point"}
}