{
  "type": "Feature",
  "properties": {
    "iso:country":"US",
    "sg:address":"14 Kane Rd",
    "sg:city":"Smithfield",
    "sg:classifiers":[
        {
            "category":"Manufacturing",
            "subcategory":"Tools & Machinery",
            "type":"Manufacturing & Wholesale Goods"
        }
    ],
    "sg:phone":"+1 401 231 2798",
    "sg:postcode":"02917",
    "sg:province":"RI",
    "sg:tags":[
        "industrial",
        "mfg"
    ],
    "wof:name":"Rtg Machine Tool Co Inc",
    "wof:placetype":"venue"
},
  "geometry": {"coordinates":[-71.527123,41.899498],"type":"Point"}
}