{
  "type": "Feature",
  "properties": {
    "iso:country":"US",
    "sg:address":"34 Elmcrest Ave",
    "sg:city":"Providence",
    "sg:classifiers":[
        {
            "category":"Professional",
            "subcategory":"Computer Services",
            "type":"Services"
        }
    ],
    "sg:phone":"+1 401 276 2727",
    "sg:postcode":"02908",
    "sg:province":"RI",
    "sg:tags":[
        "consultant",
        "designer"
    ],
    "wof:name":"PDA Indpections",
    "wof:placetype":"venue"
},
  "geometry": {"coordinates":[-71.456613,41.846965],"type":"Point"}
}