{
  "type": "Feature",
  "properties": {
    "iso:country":"US",
    "sg:address":"2841 PAWTUCKET AVE",
    "sg:city":"RIVERSIDE",
    "sg:classifiers":[
        {
            "category":"Home & Garden",
            "subcategory":"Household Appliances",
            "type":"Retail Goods"
        },
        {
            "category":"Communications",
            "subcategory":"Radio Station",
            "type":"Services"
        },
        {
            "category":"Shopping",
            "subcategory":"Computers & Home Electronics",
            "type":"Retail Goods"
        },
        {
            "category":"Home & Garden",
            "subcategory":"Furniture",
            "type":"Retail Goods"
        }
    ],
    "sg:phone":"+1 401 434 7444",
    "sg:postcode":"02915",
    "sg:province":"RI",
    "sg:tags":[
        "renting",
        "television",
        "leasing",
        "radio-renting",
        "equipment",
        "rental"
    ],
    "sg:website":"http://www.rentacenter.com/",
    "wof:name":"Rent-A-Center",
    "wof:placetype":"venue"
},
  "geometry": {"coordinates":[-71.36374499999999,41.797121],"type":"Point"}
}