{
  "type": "Feature",
  "properties": {
    "iso:country":"US",
    "sg:address":"207 Highpoint Ave",
    "sg:city":"Portsmouth",
    "sg:classifiers":[
        {
            "category":"Museum",
            "type":"Entertainment"
        },
        {
            "category":"Manufacturing",
            "subcategory":"Printing",
            "type":"Manufacturing & Wholesale Goods"
        }
    ],
    "sg:phone":"+1 401 683 5535",
    "sg:postcode":"02871",
    "sg:province":"RI",
    "sg:tags":[
        "wholesaler",
        "science",
        "technology",
        "retailer",
        "kit"
    ],
    "wof:name":"Thames & Kosmos LLC",
    "wof:placetype":"venue"
},
  "geometry": {"coordinates":[-71.263504,41.593481],"type":"Point"}
}