{
  "type": "Feature",
  "properties": {
    "iso:country":"US",
    "sg:address":"1300 Mineral Spring Ave",
    "sg:city":"North Providence",
    "sg:classifiers":[
        {
            "category":"Health Services",
            "subcategory":"Doctor",
            "type":"Services"
        }
    ],
    "sg:phone":"+1 401 726 2777",
    "sg:postcode":"02904",
    "sg:province":"RI",
    "wof:name":"Younes Claude Phys",
    "wof:placetype":"venue"
},
  "geometry": {"coordinates":[-71.43650100000001,41.867599],"type":"Point"}
}