{
  "type": "Feature",
  "properties": {
    "iso:country":"US",
    "sg:address":"58 Walcott St",
    "sg:city":"Pawtucket",
    "sg:classifiers":[
        {
            "category":"Arts & Performance",
            "subcategory":"Theater",
            "type":"Entertainment"
        }
    ],
    "sg:phone":"+1 401 724 6500",
    "sg:postcode":"02860",
    "sg:province":"RI",
    "sg:tags":[
        "group"
    ],
    "sg:website":"www.thegrandmanor.com",
    "wof:name":"Grand Manor",
    "wof:placetype":"venue"
},
  "geometry": {"coordinates":[-71.378433,41.876857],"type":"Point"}
}