{
  "type": "Feature",
  "properties": {
    "iso:country":"US",
    "sg:address":"995 Main St",
    "sg:city":"Hope Valley",
    "sg:classifiers":[
        {
            "category":"Food & Beverages",
            "subcategory":"Bakery",
            "type":"Retail Goods"
        }
    ],
    "sg:phone":"+1 401 539 2451",
    "sg:postcode":"02832",
    "sg:province":"RI",
    "sg:tags":[
        "baker",
        "caterer"
    ],
    "wof:name":"West's Bakery Inc",
    "wof:placetype":"venue"
},
  "geometry": {"coordinates":[-71.716122,41.507753],"type":"Point"}
}