{
  "type": "Feature",
  "properties": {
    "iso:country":"US",
    "sg:address":"22 Barnes St",
    "sg:city":"Greenville",
    "sg:classifiers":[
        {
            "category":"Wholesale",
            "subcategory":"Electrical",
            "type":"Manufacturing & Wholesale Goods"
        }
    ],
    "sg:phone":"+1 401 949 4603",
    "sg:postcode":"02828",
    "sg:province":"RI",
    "sg:tags":[
        "electronic",
        "representative"
    ],
    "wof:name":"Image A Nation Marketing",
    "wof:placetype":"venue"
},
  "geometry": {"coordinates":[-71.542984,41.873534],"type":"Point"}
}