{
  "type": "Feature",
  "properties": {
    "iso:country":"US",
    "sg:address":"88 Countryside Dr",
    "sg:city":"Cumberland",
    "sg:classifiers":[
        {
            "category":"Professional",
            "type":"Services"
        }
    ],
    "sg:phone":"+1 401 658 1155",
    "sg:postcode":"02864",
    "sg:province":"RI",
    "wof:name":"Jrsd Corp",
    "wof:placetype":"venue"
},
  "geometry": {"coordinates":[-71.44843899999999,41.976238],"type":"Point"}
}