{
  "type": "Feature",
  "properties": {
    "iso:country":"US",
    "sg:address":"41 Shannock Hill Rd",
    "sg:city":"Carolina",
    "sg:classifiers":[
        {
            "category":"Professional",
            "subcategory":"Employment Agencies",
            "type":"Services"
        }
    ],
    "sg:phone":"+1 401 213 6116",
    "sg:postcode":"02812",
    "sg:province":"RI",
    "sg:tags":[
        "opportunity"
    ],
    "wof:name":"Search Personnel Inc",
    "wof:placetype":"venue"
},
  "geometry": {"coordinates":[-71.654627,41.461706],"type":"Point"}
}