{
  "type": "Feature",
  "properties": {
    "iso:country":"US",
    "sg:address":"377 Child St",
    "sg:city":"Warren",
    "sg:classifiers":[
        {
            "category":"Professional",
            "subcategory":"Lawyer & Legal Services",
            "type":"Services"
        }
    ],
    "sg:phone":"+1 401 245 3857",
    "sg:postcode":"02885",
    "sg:province":"RI",
    "sg:tags":[
        "attorney"
    ],
    "wof:name":"John G Hellew",
    "wof:placetype":"venue"
},
  "geometry": {"coordinates":[-71.269294,41.729132],"type":"Point"}
}