{
  "type": "Feature",
  "properties": {
    "addr:full":"27 Strawberry Field Rd Warwick RI 02886",
    "addr:housenumber":"27",
    "addr:postcode":"02886",
    "addr:street":"Strawberry Field Rd",
    "iso:country":"US",
    "sg:address":"27 Strawberry Field Rd",
    "sg:city":"Warwick",
    "sg:classifiers":[
        {
            "category":"Banks & Credit Unions",
            "subcategory":"Bank",
            "type":"Services"
        }
    ],
    "sg:phone":"+1 401 737 4700",
    "sg:postcode":"02886",
    "sg:province":"RI",
    "sg:tags":[
        "state",
        "commercial"
    ],
    "wof:name":"Citizens Bank",
    "wof:placetype":"venue"
},
  "geometry": {"coordinates":[-71.417872,41.70607],"type":"Point"}
}