{
  "type": "Feature",
  "properties": {
    "addr:full":"802 Hope St Providence RI 02906",
    "addr:housenumber":"802",
    "addr:postcode":"02906",
    "addr:street":"Hope St",
    "iso:country":"US",
    "sg:address":"802 Hope St",
    "sg:city":"Providence",
    "sg:classifiers":[
        {
            "category":"Shopping",
            "subcategory":"Used Merchandise",
            "type":"Retail Goods"
        }
    ],
    "sg:phone":"+1 401 274 2223",
    "sg:postcode":"02906",
    "sg:province":"RI",
    "sg:tags":[
        "vintage",
        "clothing",
        "secondhand",
        "consignment"
    ],
    "wof:name":"Act II",
    "wof:placetype":"venue"
},
  "geometry": {"coordinates":[-71.394997,41.848801],"type":"Point"}
}