{
  "type": "Feature",
  "properties": {
    "iso:country":"US",
    "sg:address":"800 Clinton St",
    "sg:city":"Woonsocket",
    "sg:classifiers":[
        {
            "category":"Professional",
            "type":"Services"
        }
    ],
    "sg:phone":"+1 401 765 5553",
    "sg:postcode":"02895",
    "sg:province":"RI",
    "sg:tags":[
        "establishment"
    ],
    "wof:name":"David E Morgan Inc",
    "wof:placetype":"venue"
},
  "geometry": {"coordinates":[-71.503567,42.007846],"type":"Point"}
}