{
  "type": "Feature",
  "properties": {
    "iso:country":"US",
    "sg:address":"1264 Stafford Rd",
    "sg:city":"Tiverton",
    "sg:classifiers":[
        {
            "category":"Professional",
            "type":"Services"
        },
        {
            "category":"Organizations",
            "subcategory":"Religious Organization",
            "type":"Services"
        }
    ],
    "sg:phone":"+1 401 624 4113",
    "sg:postcode":"02878",
    "sg:province":"RI",
    "sg:tags":[
        "establishment"
    ],
    "wof:name":"Bliss Four Corner Congregation",
    "wof:placetype":"venue"
},
  "geometry": {"coordinates":[-71.14633600000001,41.627736],"type":"Point"}
}