{
  "type": "Feature",
  "properties": {
    "iso:country":"US",
    "sg:address":"105 Smithfield Rd",
    "sg:city":"Providence",
    "sg:classifiers":[
        {
            "category":"Building & Trades",
            "subcategory":"Landscaping Services",
            "type":"Services"
        }
    ],
    "sg:phone":"+1 401 354 8392",
    "sg:postcode":"02904",
    "sg:province":"RI",
    "sg:tags":[
        "contractor",
        "cutting",
        "shrub",
        "landscape",
        "doe"
    ],
    "wof:name":"Zars Landscape",
    "wof:placetype":"venue"
},
  "geometry": {"coordinates":[-71.450322,41.856262],"type":"Point"}
}