{
  "type": "Feature",
  "properties": {
    "iso:country":"US",
    "sg:address":"70 Curson St",
    "sg:city":"West Warwick",
    "sg:classifiers":[
        {
            "category":"Building & Trades",
            "subcategory":"Construction",
            "type":"Services"
        }
    ],
    "sg:phone":"+1 401 487 5062",
    "sg:postcode":"02893",
    "sg:province":"RI",
    "sg:tags":[
        "house"
    ],
    "wof:name":"J Graf Construction",
    "wof:placetype":"venue"
},
  "geometry": {"coordinates":[-71.52875400000001,41.705785],"type":"Point"}
}