{
  "type": "Feature",
  "properties": {
    "iso:country":"US",
    "sg:address":"87 Hallville Rd",
    "sg:city":"Exeter",
    "sg:classifiers":[
        {
            "category":"Home & Garden",
            "subcategory":"Garden Supply",
            "type":"Retail Goods"
        }
    ],
    "sg:phone":"+1 401 295 2065",
    "sg:postcode":"02822",
    "sg:province":"RI",
    "sg:tags":[
        "landscaping",
        "equipment"
    ],
    "wof:name":"USA Hydro LLC",
    "wof:placetype":"venue"
},
  "geometry": {"coordinates":[-71.571989,41.573245],"type":"Point"}
}