{
  "type": "Feature",
  "properties": {
    "iso:country":"US",
    "sg:address":"5 Nancy Ct",
    "sg:city":"Coventry",
    "sg:classifiers":[
        {
            "category":"Building & Trades",
            "subcategory":"Construction",
            "type":"Services"
        }
    ],
    "sg:phone":"+1 401 828 6450",
    "sg:postcode":"02816",
    "sg:province":"RI",
    "sg:tags":[
        "hanging",
        "contractor"
    ],
    "wof:name":"R J Vermette Painting",
    "wof:placetype":"venue"
},
  "geometry": {"coordinates":[-71.543271,41.702176],"type":"Point"}
}