{
  "type": "Feature",
  "properties": {
    "addr:full":"1291 Narragansett Blvd Cranston RI 02905",
    "addr:housenumber":"1291",
    "addr:postcode":"02905",
    "addr:street":"Narragansett Blvd",
    "iso:country":"US",
    "sg:address":"1291 Narragansett Blvd",
    "sg:city":"Cranston",
    "sg:classifiers":[
        {
            "category":"Professional",
            "subcategory":"Management & Consulting",
            "type":"Services"
        }
    ],
    "sg:phone":"+1 401 461 3500",
    "sg:postcode":"02905",
    "sg:province":"RI",
    "sg:tags":[
        "consultant",
        "business"
    ],
    "wof:name":"Odyssues Group",
    "wof:placetype":"venue"
},
  "geometry": {"coordinates":[-71.391747,41.776005],"type":"Point"}
}