{
  "type": "Feature",
  "properties": {
    "iso:country":"US",
    "sg:address":"1145 Main St",
    "sg:city":"Pawtucket",
    "sg:classifiers":[
        {
            "category":"Health Services",
            "subcategory":"Health Practitioner",
            "type":"Services"
        }
    ],
    "sg:phone":"+1 401 365 1370",
    "sg:postcode":"02860",
    "sg:province":"RI",
    "sg:tags":[
        "therapy",
        "physical"
    ],
    "wof:name":"Specialized Orthopedic Physical Therapy Inc",
    "wof:placetype":"venue"
},
  "geometry": {"coordinates":[-71.3991,41.858537],"type":"Point"}
}