{
  "type": "Feature",
  "properties": {
    "iso:country":"US",
    "sg:address":"54 Barnes St",
    "sg:city":"Providence",
    "sg:classifiers":[
        {
            "category":"Professional",
            "subcategory":"Management & Consulting",
            "type":"Services"
        }
    ],
    "sg:phone":"+1 401 272 8208",
    "sg:postcode":"02906",
    "sg:province":"RI",
    "sg:tags":[
        "consultant",
        "business"
    ],
    "sg:website":"www.synthesispartnership.com",
    "wof:name":"Synthesis",
    "wof:placetype":"venue"
},
  "geometry": {"coordinates":[-71.401939,41.832998],"type":"Point"}
}