{
  "type": "Feature",
  "properties": {
    "addr:full":"110 Waterman Ave Cranston RI 02910",
    "addr:housenumber":"110",
    "addr:postcode":"02910",
    "addr:street":"Waterman Ave",
    "iso:country":"US",
    "sg:address":"110 Waterman Ave",
    "sg:city":"Cranston",
    "sg:classifiers":[
        {
            "category":"Restaurant",
            "type":"Food & Drink"
        }
    ],
    "sg:phone":"+1 401 331 5282",
    "sg:postcode":"02910",
    "sg:province":"RI",
    "sg:tags":[
        "cafe"
    ],
    "wof:name":"Ocean Coffee Roasters",
    "wof:placetype":"venue"
},
  "geometry": {"coordinates":[-71.44302,41.773649],"type":"Point"}
}