{
  "type": "Feature",
  "properties": {
    "addr:full":"3 India Pt Westerly RI 02891",
    "addr:housenumber":"3",
    "addr:postcode":"02891",
    "addr:street":"India Pt",
    "iso:country":"US",
    "sg:address":"3 India Pt",
    "sg:city":"Westerly",
    "sg:classifiers":[
        {
            "category":"Professional",
            "type":"Services"
        }
    ],
    "sg:phone":"+1 401 596 7807",
    "sg:postcode":"02891",
    "sg:province":"RI",
    "sg:tags":[
        "establishment"
    ],
    "wof:name":"Watch Hill Docks",
    "wof:placetype":"venue"
},
  "geometry": {"coordinates":[-71.834384,41.335199],"type":"Point"}
}