{
  "type": "Feature",
  "properties": {
    "iso:country":"US",
    "sg:address":"1092 Post Rd",
    "sg:city":"Warwick",
    "sg:classifiers":[
        {
            "category":"Shopping",
            "subcategory":"Discount & Variety Stores",
            "type":"Retail Goods"
        },
        {
            "category":"Shopping",
            "subcategory":"Department Store",
            "type":"Retail Goods"
        }
    ],
    "sg:phone":"+1 401 785 0242",
    "sg:postcode":"02888",
    "sg:province":"RI",
    "wof:name":"Family Dollar Stores",
    "wof:placetype":"venue"
},
  "geometry": {"coordinates":[-71.42262100000001,41.748471],"type":"Point"}
}