{
  "type": "Feature",
  "properties": {
    "iso:country":"US",
    "sg:address":"125 New London Tpke",
    "sg:city":"Wyoming",
    "sg:classifiers":[
        {
            "category":"Building & Trades",
            "subcategory":"Construction",
            "type":"Services"
        }
    ],
    "sg:phone":"+1 401 539 0588",
    "sg:postcode":"02898",
    "sg:province":"RI",
    "sg:tags":[
        "concrete",
        "contractor"
    ],
    "wof:name":"New England Driveway Design",
    "wof:placetype":"venue"
},
  "geometry": {"coordinates":[-71.66002899999999,41.547067],"type":"Point"}
}