{
  "type": "Feature",
  "properties": {
    "addr:full":"472 Smith St Providence RI 02908",
    "addr:housenumber":"472",
    "addr:postcode":"02908",
    "addr:street":"Smith St",
    "iso:country":"US",
    "sg:address":"472 Smith St",
    "sg:city":"Providence",
    "sg:classifiers":[
        {
            "category":"Professional",
            "subcategory":"Testing Lab",
            "type":"Services"
        }
    ],
    "sg:phone":"+1 401 454 3400",
    "sg:postcode":"02908",
    "sg:province":"RI",
    "sg:tags":[
        "environmental",
        "laboratory"
    ],
    "wof:name":"Northeast Envmtl Tstg Laborato",
    "wof:placetype":"venue"
},
  "geometry": {"coordinates":[-71.42583500000001,41.835166],"type":"Point"}
}