{
  "type": "Feature",
  "properties": {
    "iso:country":"US",
    "sg:address":"396 Elmwood Ave",
    "sg:city":"Providence",
    "sg:classifiers":[
        {
            "category":"Autos & Motor Vehicles",
            "subcategory":"Fuel & Gas Station",
            "type":"Retail Goods"
        }
    ],
    "sg:phone":"+1 401 941 9454",
    "sg:postcode":"02907",
    "sg:province":"RI",
    "sg:tags":[
        "station",
        "gasoline"
    ],
    "wof:name":"Amerada Hess Corporation",
    "wof:placetype":"venue"
},
  "geometry": {"coordinates":[-71.42631799999999,41.801408],"type":"Point"}
}