{
  "type": "Feature",
  "properties": {
    "iso:country":"US",
    "sg:address":"1120 Toll Gate Rd",
    "sg:city":"Warwick",
    "sg:classifiers":[
        {
            "category":"Health Services",
            "subcategory":"Doctor",
            "type":"Services"
        }
    ],
    "sg:phone":"+1 401 823 1313",
    "sg:postcode":"02886",
    "sg:province":"RI",
    "sg:tags":[
        "dentist"
    ],
    "wof:name":"Estelita A Santiago DDS",
    "wof:placetype":"venue"
},
  "geometry": {"coordinates":[-71.495705,41.710757],"type":"Point"}
}