{
  "type": "Feature",
  "properties": {
    "iso:country":"US",
    "sg:address":"18 Robin Dr",
    "sg:city":"Exeter",
    "sg:classifiers":[
        {
            "category":"Building & Trades",
            "subcategory":"Plumbing",
            "type":"Services"
        }
    ],
    "sg:phone":"+1 401 294 1039",
    "sg:postcode":"02822",
    "sg:province":"RI",
    "sg:tags":[
        "contractor"
    ],
    "wof:name":"Economy Air Inc",
    "wof:placetype":"venue"
},
  "geometry": {"coordinates":[-71.538695,41.566713],"type":"Point"}
}