{
  "type": "Feature",
  "properties": {
    "iso:country":"US",
    "sg:address":"91 Friendship St Ste 4",
    "sg:city":"Providence",
    "sg:classifiers":[
        {
            "category":"Professional",
            "subcategory":"Lawyer & Legal Services",
            "type":"Services"
        }
    ],
    "sg:phone":"+1 401 861 5393",
    "sg:postcode":"02903",
    "sg:province":"RI",
    "wof:name":"Rallis John G Esquire",
    "wof:placetype":"venue"
},
  "geometry": {"coordinates":[-71.4105,41.8209],"type":"Point"}
}