{
  "type": "Feature",
  "properties": {
    "iso:country":"US",
    "sg:address":"1121 Centerville Rd",
    "sg:city":"Warwick",
    "sg:classifiers":[
        {
            "category":"Professional",
            "subcategory":"Computer Services",
            "type":"Services"
        }
    ],
    "sg:phone":"+1 401 826 8889",
    "sg:postcode":"02886",
    "sg:province":"RI",
    "sg:tags":[
        "consultant",
        "designer"
    ],
    "wof:name":"Digital Dental Systems",
    "wof:placetype":"venue"
},
  "geometry": {"coordinates":[-71.497878,41.69675],"type":"Point"}
}