{
  "type": "Feature",
  "properties": {
    "iso:country":"US",
    "sg:address":"115 Reservoir Rd",
    "sg:city":"Coventry",
    "sg:classifiers":[
        {
            "category":"Manufacturing",
            "subcategory":"Lumber",
            "type":"Manufacturing & Wholesale Goods"
        }
    ],
    "sg:phone":"+1 401 822 1621",
    "sg:postcode":"02816",
    "sg:province":"RI",
    "sg:tags":[
        "logging"
    ],
    "wof:name":"Stanley Logging Inc",
    "wof:placetype":"venue"
},
  "geometry": {"coordinates":[-71.590462,41.690025],"type":"Point"}
}