{
  "type": "Feature",
  "properties": {
    "iso:country":"US",
    "sg:address":"30 Meeting St",
    "sg:city":"Cumberland",
    "sg:classifiers":[
        {
            "category":"Manufacturing",
            "subcategory":"Textiles",
            "type":"Manufacturing & Wholesale Goods"
        }
    ],
    "sg:phone":"+1 401 722 3220",
    "sg:postcode":"02864",
    "sg:province":"RI",
    "sg:tags":[
        "mills"
    ],
    "wof:name":"Cadillac Mills Corp",
    "wof:placetype":"venue"
},
  "geometry": {"coordinates":[-71.39291299999999,41.899207],"type":"Point"}
}