{
  "type": "Feature",
  "properties": {
    "addr:full":"73 Division St Newport RI 02840",
    "addr:housenumber":"73",
    "addr:postcode":"02840",
    "addr:street":"Division St",
    "iso:country":"US",
    "sg:address":"73 Division St",
    "sg:city":"Newport",
    "sg:classifiers":[
        {
            "category":"Professional",
            "subcategory":"Business Services",
            "type":"Services"
        }
    ],
    "sg:phone":"+1 401 849 3779",
    "sg:postcode":"02840",
    "sg:province":"RI",
    "sg:tags":[
        "conservation",
        "art"
    ],
    "wof:name":"Artcare Resources",
    "wof:placetype":"venue"
},
  "geometry": {"coordinates":[-71.312285,41.486794],"type":"Point"}
}