{
  "type": "Feature",
  "properties": {
    "iso:country":"US",
    "sg:address":"674 Centre of New England Blvd",
    "sg:city":"Coventry",
    "sg:classifiers":[
        {
            "category":"Restaurant",
            "type":"Food & Drink"
        }
    ],
    "sg:menulink":"http://www.allmenus.com/ri/coventry/153535-salad-creations/menu/",
    "sg:phone":"+1 401 821 8080",
    "sg:postcode":"02816",
    "sg:province":"RI",
    "sg:tags":[
        "soup",
        "american",
        "salad"
    ],
    "wof:name":"Salad Creations",
    "wof:placetype":"venue"
},
  "geometry": {"coordinates":[-71.566118,41.664232],"type":"Point"}
}