{
  "type": "Feature",
  "properties": {
    "iso:country":"US",
    "sg:address":"84 Camp St",
    "sg:city":"Providence",
    "sg:classifiers":[
        {
            "category":"Retail",
            "subcategory":"Funeral Services",
            "type":"Services"
        }
    ],
    "sg:phone":"+1 401 331 1334",
    "sg:postcode":"02906",
    "sg:province":"RI",
    "sg:tags":[
        "director"
    ],
    "wof:name":"Bailey Albert L Funrl Home",
    "wof:placetype":"venue"
},
  "geometry": {"coordinates":[-71.40422,41.838937],"type":"Point"}
}