{
  "type": "Feature",
  "properties": {
    "iso:country":"US",
    "sg:address":"41 Paine Rd",
    "sg:city":"Foster",
    "sg:classifiers":[
        {
            "category":"Professional",
            "type":"Services"
        }
    ],
    "sg:phone":"+1 401 647 0518",
    "sg:postcode":"02825",
    "sg:province":"RI",
    "wof:name":"B J Wiley",
    "wof:placetype":"venue"
},
  "geometry": {"coordinates":[-71.750055,41.816965],"type":"Point"}
}