{
  "type": "Feature",
  "properties": {
    "addr:full":"610 Hope St Bristol RI 02809",
    "addr:housenumber":"610",
    "addr:postcode":"02809",
    "addr:street":"Hope St",
    "iso:country":"US",
    "sg:address":"610 Hope St",
    "sg:city":"Bristol",
    "sg:classifiers":[
        {
            "category":"Travel",
            "subcategory":"Hotels & Motels",
            "type":"Entertainment"
        }
    ],
    "sg:phone":"+1 401 253 0040",
    "sg:postcode":"02809",
    "sg:province":"RI",
    "sg:tags":[
        "breakfast",
        "accommodation",
        "bed"
    ],
    "wof:name":"Rockwell House Inn B & B",
    "wof:placetype":"venue"
},
  "geometry": {"coordinates":[-71.277479,41.673064],"type":"Point"}
}