{
  "type": "Feature",
  "properties": {
    "iso:country":"US",
    "sg:address":"472 Central Ave",
    "sg:city":"Johnston",
    "sg:classifiers":[
        {
            "category":"Real Estate",
            "subcategory":"Real Estate Agent",
            "type":"Services"
        }
    ],
    "sg:phone":"+1 401 943 1766",
    "sg:postcode":"02919",
    "sg:province":"RI",
    "wof:name":"Chris Belair & Co",
    "wof:placetype":"venue"
},
  "geometry": {"coordinates":[-71.500079,41.807623],"type":"Point"}
}