{
  "type": "Feature",
  "properties": {
    "iso:country":"US",
    "sg:address":"22 Lark Industrial Dr",
    "sg:city":"Greenville",
    "sg:classifiers":[
        {
            "category":"Wholesale",
            "subcategory":"Furniture",
            "type":"Manufacturing & Wholesale Goods"
        }
    ],
    "sg:phone":"+1 401 949 6800",
    "sg:postcode":"02828",
    "sg:province":"RI",
    "wof:name":"Sunshine Distributors",
    "wof:placetype":"venue"
},
  "geometry": {"coordinates":[-71.53524400000001,41.86811],"type":"Point"}
}