{
  "type": "Feature",
  "properties": {
    "iso:country":"US",
    "sg:address":"129 Ferris St",
    "sg:city":"Pawtucket",
    "sg:classifiers":[
        {
            "category":"Organizations",
            "subcategory":"Religious Organization",
            "type":"Services"
        }
    ],
    "sg:phone":"+1 401 725 7874",
    "sg:postcode":"02861",
    "sg:province":"RI",
    "sg:tags":[
        "monastery",
        "convent"
    ],
    "wof:name":"Sisters Of Mercy",
    "wof:placetype":"venue"
},
  "geometry": {"coordinates":[-71.360799,41.872391],"type":"Point"}
}