{
  "type": "Feature",
  "properties": {
    "iso:country":"US",
    "sg:address":"2 Overlook Dr",
    "sg:city":"Ashaway",
    "sg:classifiers":[
        {
            "category":"Banks & Credit Unions",
            "subcategory":"Financial Services",
            "type":"Services"
        }
    ],
    "sg:phone":"+1 401 377 2777",
    "sg:postcode":"02804",
    "sg:province":"RI",
    "sg:tags":[
        "company",
        "holding"
    ],
    "wof:name":"132 Oak Street Holding LLC",
    "wof:placetype":"venue"
},
  "geometry": {"coordinates":[-71.75385199999999,41.438839],"type":"Point"}
}