{
  "type": "Feature",
  "properties": {
    "iso:country":"US",
    "sg:address":"718 Plainfield St",
    "sg:city":"Providence",
    "sg:classifiers":[
        {
            "category":"Restaurant",
            "type":"Food & Drink"
        }
    ],
    "sg:phone":"+1 401 942 2260",
    "sg:postcode":"02909",
    "sg:province":"RI",
    "wof:name":"Fusion Catering",
    "wof:placetype":"venue"
},
  "geometry": {"coordinates":[-71.461794,41.811741],"type":"Point"}
}