{
  "type": "Feature",
  "properties": {
    "iso:country":"US",
    "sg:address":"32 Green Meadow Ln",
    "sg:city":"Cumberland",
    "sg:classifiers":[
        {
            "category":"Building & Trades",
            "subcategory":"Landscaping Services",
            "type":"Services"
        }
    ],
    "sg:phone":"+1 401 333 9034",
    "sg:postcode":"02864",
    "sg:province":"RI",
    "sg:tags":[
        "consultant",
        "designer",
        "landscape"
    ],
    "wof:name":"Green Meadow Landscape Designs",
    "wof:placetype":"venue"
},
  "geometry": {"coordinates":[-71.418037,41.98737],"type":"Point"}
}