{
  "type": "Feature",
  "properties": {
    "iso:country":"US",
    "sg:address":"1070 Central Ave",
    "sg:city":"Pawtucket",
    "sg:classifiers":[
        {
            "category":"Building & Trades",
            "subcategory":"Plumbing",
            "type":"Services"
        }
    ],
    "sg:phone":"+1 401 724 5656",
    "sg:postcode":"02861",
    "sg:province":"RI",
    "wof:name":"Geiselman Ralph E Plumbing & Heating",
    "wof:placetype":"venue"
},
  "geometry": {"coordinates":[-71.34339900000001,41.890301],"type":"Point"}
}