{
  "type": "Feature",
  "properties": {
    "addr:full":"325 Water St Warren RI 02885",
    "addr:housenumber":"325",
    "addr:postcode":"02885",
    "addr:street":"Water St",
    "iso:country":"US",
    "sg:address":"325 Water St",
    "sg:city":"Warren",
    "sg:classifiers":[
        {
            "category":"Wholesale",
            "subcategory":"Seafood",
            "type":"Manufacturing & Wholesale Goods"
        }
    ],
    "sg:phone":"+1 401 245 0054",
    "sg:postcode":"02885",
    "sg:province":"RI",
    "wof:name":"Best In The Bay Seafood",
    "wof:placetype":"venue"
},
  "geometry": {"coordinates":[-71.285065,41.727862],"type":"Point"}
}