{
  "type": "Feature",
  "properties": {
    "addr:full":"39 Dexter St Cumberland RI 02864",
    "addr:housenumber":"39",
    "addr:postcode":"02864",
    "addr:street":"Dexter St",
    "iso:country":"US",
    "sg:address":"39 Dexter St",
    "sg:city":"Cumberland",
    "sg:classifiers":[
        {
            "category":"Home & Garden",
            "subcategory":"Household Appliances",
            "type":"Retail Goods"
        }
    ],
    "sg:phone":"+1 401 723 2361",
    "sg:postcode":"02864",
    "sg:province":"RI",
    "wof:name":"Stan's Appliance Sales & Svc",
    "wof:placetype":"venue"
},
  "geometry": {"coordinates":[-71.393199,41.912484],"type":"Point"}
}