{
  "type": "Feature",
  "properties": {
    "iso:country":"US",
    "sg:address":"156 Maplewood Ave",
    "sg:city":"Cranston",
    "sg:classifiers":[
        {
            "category":"Building & Trades",
            "subcategory":"Construction",
            "type":"Services"
        }
    ],
    "sg:phone":"+1 401 270 5930",
    "sg:postcode":"02920",
    "sg:province":"RI",
    "sg:tags":[
        "house"
    ],
    "wof:name":"Richards Home Improvements LLC",
    "wof:placetype":"venue"
},
  "geometry": {"coordinates":[-71.451358,41.803535],"type":"Point"}
}