{
  "type": "Feature",
  "properties": {
    "iso:country":"US",
    "sg:address":"87 Stedman Ave",
    "sg:city":"Pawtucket",
    "sg:classifiers":[
        {
            "category":"Personal",
            "type":"Services"
        }
    ],
    "sg:phone":"+1 401 722 0849",
    "sg:postcode":"02860",
    "sg:province":"RI",
    "wof:name":"Siternet USA",
    "wof:placetype":"venue"
},
  "geometry": {"coordinates":[-71.41970600000001,41.871543],"type":"Point"}
}