{
  "type": "Feature",
  "properties": {
    "addr:full":"530 Greenwich Ave Warwick RI 02886",
    "addr:housenumber":"530",
    "addr:postcode":"02886",
    "addr:street":"Greenwich Ave",
    "iso:country":"US",
    "sg:address":"530 Greenwich Ave",
    "sg:city":"Warwick",
    "sg:classifiers":[
        {
            "category":"Insurance",
            "subcategory":"Insurance Agent",
            "type":"Services"
        }
    ],
    "sg:phone":"+1 401 739 8417",
    "sg:postcode":"02886",
    "sg:province":"RI",
    "wof:name":"Met Life",
    "wof:placetype":"venue"
},
  "geometry": {"coordinates":[-71.464294,41.719347],"type":"Point"}
}