{
  "type": "Feature",
  "properties": {
    "iso:country":"US",
    "sg:address":"654 Metacom Ave",
    "sg:city":"Warren",
    "sg:classifiers":[
        {
            "category":"Recreation",
            "type":"Entertainment"
        }
    ],
    "sg:phone":"+1 401 864 8307",
    "sg:postcode":"02885",
    "sg:province":"RI",
    "sg:tags":[
        "psychic",
        "medium"
    ],
    "wof:name":"Afterlife Readings-Lynn Kent",
    "wof:placetype":"venue"
},
  "geometry": {"coordinates":[-71.26778299999999,41.714236],"type":"Point"}
}