{
  "type": "Feature",
  "properties": {
    "iso:country":"US",
    "sg:address":"2370 Diamond Hill Rd",
    "sg:city":"Cumberland",
    "sg:classifiers":[
        {
            "category":"Real Estate",
            "subcategory":"Real Estate Services",
            "type":"Services"
        }
    ],
    "sg:phone":"+1 401 333 9333",
    "sg:postcode":"02864",
    "sg:province":"RI",
    "sg:website":"www.residentialproperties.com",
    "wof:name":"Residential Properties Ltd",
    "wof:placetype":"venue"
},
  "geometry": {"coordinates":[-71.40173900000001,41.954505],"type":"Point"}
}