{
  "type": "Feature",
  "properties": {
    "iso:country":"US",
    "sg:address":"2572 E Main Rd",
    "sg:city":"Portsmouth",
    "sg:classifiers":[
        {
            "category":"Real Estate",
            "subcategory":"Real Estate Operator",
            "type":"Services"
        }
    ],
    "sg:phone":"+1 401 683 3222",
    "sg:postcode":"02871",
    "sg:province":"RI",
    "sg:tags":[
        "apartment"
    ],
    "wof:name":"Samuels Realty Co Inc",
    "wof:placetype":"venue"
},
  "geometry": {"coordinates":[-71.250607,41.599216],"type":"Point"}
}