{
  "type": "Feature",
  "properties": {
    "addr:full":"178 Touisset Rd Warren RI 02885",
    "addr:housenumber":"178",
    "addr:postcode":"02885",
    "addr:street":"Touisset Rd",
    "iso:country":"US",
    "sg:address":"178 Touisset Rd",
    "sg:city":"Warren",
    "sg:classifiers":[
        {
            "category":"Recreation",
            "type":"Entertainment"
        }
    ],
    "sg:phone":"+1 401 245 0499",
    "sg:postcode":"02885",
    "sg:province":"RI",
    "sg:tags":[
        "stable"
    ],
    "wof:name":"Blackhorse Farm",
    "wof:placetype":"venue"
},
  "geometry": {"coordinates":[-71.237376,41.721135],"type":"Point"}
}