{
  "type": "Feature",
  "properties": {
    "iso:country":"US",
    "sg:address":"India Street Next to Community Boating Center",
    "sg:city":"Providence",
    "sg:classifiers":[
        {
            "category":"Park",
            "type":"Public Place"
        }
    ],
    "sg:postcode":"02903",
    "sg:province":"RI",
    "sg:website":"www.friendsofindiapointpark.com",
    "wof:name":"India Point Park",
    "wof:placetype":"venue"
},
  "geometry": {"coordinates":[-71.39446599999999,41.818315],"type":"Point"}
}