{
  "type": "Feature",
  "properties": {
    "iso:country":"US",
    "sg:address":"8 Larch St",
    "sg:city":"Smithfield",
    "sg:classifiers":[
        {
            "category":"Retail",
            "subcategory":"Auto Repair",
            "type":"Services"
        }
    ],
    "sg:phone":"+1 401 231 2130",
    "sg:postcode":"02917",
    "sg:province":"RI",
    "sg:tags":[
        "repairing",
        "automobile"
    ],
    "wof:name":"Cars Automotive Inc",
    "wof:placetype":"venue"
},
  "geometry": {"coordinates":[-71.507993,41.86728],"type":"Point"}
}