{
  "type": "Feature",
  "properties": {
    "iso:country":"US",
    "sg:address":"218 Benefit St",
    "sg:city":"Pawtucket",
    "sg:classifiers":[
        {
            "category":"Shopping",
            "subcategory":"Florist",
            "type":"Retail Goods"
        }
    ],
    "sg:phone":"+1 401 724 3747",
    "sg:postcode":"02861",
    "sg:province":"RI",
    "wof:name":"Picture & Floral Place",
    "wof:placetype":"venue"
},
  "geometry": {"coordinates":[-71.361423,41.892585],"type":"Point"}
}