{
  "type": "Feature",
  "properties": {
    "iso:country":"US",
    "sg:address":"723 Quaker Ln",
    "sg:city":"West Warwick",
    "sg:classifiers":[
        {
            "category":"Professional",
            "type":"Services"
        }
    ],
    "sg:phone":"+1 401 821 2839",
    "sg:postcode":"02893",
    "sg:province":"RI",
    "sg:tags":[
        "establishment"
    ],
    "wof:name":"NECDS",
    "wof:placetype":"venue"
},
  "geometry": {"coordinates":[-71.500117,41.676541],"type":"Point"}
}