{
  "type": "Feature",
  "properties": {
    "iso:country":"US",
    "sg:address":"721 Mendon Rd",
    "sg:city":"Cumberland",
    "sg:classifiers":[
        {
            "category":"Retail",
            "subcategory":"Auto Repair",
            "type":"Services"
        }
    ],
    "sg:phone":"+1 401 334 4787",
    "sg:postcode":"02864",
    "sg:province":"RI",
    "wof:name":"L & J Auto Inc",
    "wof:placetype":"venue"
},
  "geometry": {"coordinates":[-71.41680100000001,41.925999],"type":"Point"}
}