{
  "type": "Feature",
  "properties": {
    "iso:country":"US",
    "sg:address":"710 Boston Neck Rd",
    "sg:city":"North Kingstown",
    "sg:classifiers":[
        {
            "category":"Retail",
            "subcategory":"Auto Repair",
            "type":"Services"
        }
    ],
    "sg:phone":"+1 401 294 2988",
    "sg:postcode":"02852",
    "sg:province":"RI",
    "sg:tags":[
        "wrecker"
    ],
    "wof:name":"Wheelock's Auto Ctr Inc",
    "wof:placetype":"venue"
},
  "geometry": {"coordinates":[-71.440907,41.550492],"type":"Point"}
}