{
  "type": "Feature",
  "properties": {
    "addr:full":"11 10th St East Providence RI 02914",
    "addr:housenumber":"11",
    "addr:postcode":"02914",
    "addr:street":"10Th St",
    "iso:country":"US",
    "sg:address":"11 10th St",
    "sg:city":"East Providence",
    "sg:classifiers":[
        {
            "category":"Manufacturing",
            "subcategory":"Jewelry",
            "type":"Manufacturing & Wholesale Goods"
        }
    ],
    "sg:phone":"+1 401 435 4982",
    "sg:postcode":"02914",
    "sg:province":"RI",
    "sg:tags":[
        "precious",
        "metal",
        "mfg"
    ],
    "wof:name":"Elizabeth Sterling",
    "wof:placetype":"venue"
},
  "geometry": {"coordinates":[-71.377009,41.814504],"type":"Point"}
}