{
  "type": "Feature",
  "properties": {
    "addr:full":"356 Washington Hwy Smithfield RI 02917",
    "addr:housenumber":"356",
    "addr:postcode":"02917",
    "addr:street":"Washington Hwy",
    "iso:country":"US",
    "sg:address":"356 Washington Hwy",
    "sg:city":"Smithfield",
    "sg:classifiers":[
        {
            "category":"Freight",
            "type":"Transportation"
        }
    ],
    "sg:phone":"+1 401 232 1444",
    "sg:postcode":"02917",
    "sg:province":"RI",
    "sg:tags":[
        "trucking"
    ],
    "wof:name":"Northeast Transportation Corp",
    "wof:placetype":"venue"
},
  "geometry": {"coordinates":[-71.512883,41.921175],"type":"Point"}
}