{
  "type": "Feature",
  "properties": {
    "addr:full":"955 Post Rd Warwick RI 02888",
    "addr:housenumber":"955",
    "addr:postcode":"02888",
    "addr:street":"Post Rd",
    "iso:country":"US",
    "sg:address":"955 Post Rd",
    "sg:city":"Warwick",
    "sg:classifiers":[
        {
            "category":"Health Services",
            "subcategory":"Clinic",
            "type":"Services"
        }
    ],
    "sg:phone":"+1 401 781 8018",
    "sg:postcode":"02888",
    "sg:province":"RI",
    "sg:tags":[
        "home",
        "care"
    ],
    "wof:name":"Cranberry Pond Apartments",
    "wof:placetype":"venue"
},
  "geometry": {"coordinates":[-71.41799,41.751246],"type":"Point"}
}