{
  "type": "Feature",
  "properties": {
    "iso:country":"US",
    "sg:address":"9 Atlantic Dr",
    "sg:city":"Little Compton",
    "sg:classifiers":[
        {
            "category":"Organizations",
            "subcategory":"Community Association",
            "type":"Services"
        }
    ],
    "sg:phone":"+1 401 635 8053",
    "sg:postcode":"02837",
    "sg:province":"RI",
    "sg:tags":[
        "club"
    ],
    "wof:name":"Warrens Beach Club Inc",
    "wof:placetype":"venue"
},
  "geometry": {"coordinates":[-71.171736,41.462272],"type":"Point"}
}