{
  "type": "Feature",
  "properties": {
    "iso:country":"US",
    "sg:address":"89 Neptune St",
    "sg:city":"Jamestown",
    "sg:classifiers":[
        {
            "category":"Real Estate",
            "subcategory":"Architect",
            "type":"Services"
        }
    ],
    "sg:phone":"+1 401 423 3900",
    "sg:postcode":"02835",
    "sg:province":"RI",
    "sg:tags":[
        "home",
        "planning",
        "design"
    ],
    "wof:name":"J Bryer Designs",
    "wof:placetype":"venue"
},
  "geometry": {"coordinates":[-71.389376,41.52816],"type":"Point"}
}