{
  "type": "Feature",
  "properties": {
    "iso:country":"US",
    "sg:address":"2074 Smith St",
    "sg:city":"North Providence",
    "sg:classifiers":[
        {
            "category":"Social Services",
            "subcategory":"Adult Care",
            "type":"Services"
        }
    ],
    "sg:phone":"+1 401 232 3770",
    "sg:postcode":"02911",
    "sg:province":"RI",
    "sg:tags":[
        "home",
        "residential"
    ],
    "wof:name":"Centredale Manor",
    "wof:placetype":"venue"
},
  "geometry": {"coordinates":[-71.486862,41.858822],"type":"Point"}
}