{
  "type": "Feature",
  "properties": {
    "iso:country":"US",
    "sg:address":"42 Victor St",
    "sg:city":"Providence",
    "sg:classifiers":[
        {
            "category":"Organizations",
            "subcategory":"Non-profit Organization",
            "type":"Services"
        }
    ],
    "sg:phone":"+1 401 276 4130",
    "sg:postcode":"02908",
    "sg:province":"RI",
    "wof:name":"Providence Center",
    "wof:placetype":"venue"
},
  "geometry": {"coordinates":[-71.41839899999999,41.836993],"type":"Point"}
}