{
  "type": "Feature",
  "properties": {
    "iso:country":"US",
    "sg:address":"47 Atwells Ave",
    "sg:city":"Johnston",
    "sg:classifiers":[
        {
            "category":"Professional",
            "subcategory":"Management & Consulting",
            "type":"Services"
        }
    ],
    "sg:phone":"+1 401 231 3580",
    "sg:postcode":"02919",
    "sg:province":"RI",
    "sg:tags":[
        "specializing",
        "marketing",
        "business"
    ],
    "wof:name":"Continental Sales Development",
    "wof:placetype":"venue"
},
  "geometry": {"coordinates":[-71.488133,41.835148],"type":"Point"}
}