{
  "type": "Feature",
  "properties": {
    "iso:country":"US",
    "sg:address":"26 Hill Ave",
    "sg:city":"North Scituate",
    "sg:classifiers":[
        {
            "category":"Manufacturing",
            "subcategory":"Printing",
            "type":"Manufacturing & Wholesale Goods"
        }
    ],
    "sg:phone":"+1 401 647 0440",
    "sg:postcode":"02857",
    "sg:province":"RI",
    "sg:tags":[
        "book",
        "publishing"
    ],
    "wof:name":"Secret Passage Press",
    "wof:placetype":"venue"
},
  "geometry": {"coordinates":[-71.57374900000001,41.830398],"type":"Point"}
}