{
  "type": "Feature",
  "properties": {
    "addr:full":"102 Farnum Pike Smithfield RI 02917",
    "addr:housenumber":"102",
    "addr:postcode":"02917",
    "addr:street":"Farnum Pike",
    "iso:country":"US",
    "sg:address":"102 Farnum Pike",
    "sg:city":"Smithfield",
    "sg:classifiers":[
        {
            "category":"Building & Trades",
            "subcategory":"Cleaning & Sanitation",
            "type":"Services"
        }
    ],
    "sg:phone":"+1 401 233 0291",
    "sg:postcode":"02917",
    "sg:province":"RI",
    "sg:tags":[
        "janitor"
    ],
    "wof:name":"White Magic Cleaning Svc",
    "wof:placetype":"venue"
},
  "geometry": {"coordinates":[-71.515027,41.890437],"type":"Point"}
}