{
  "type": "Feature",
  "properties": {
    "addr:full":"15 Leatherleaf Rd Narragansett RI 02882",
    "addr:housenumber":"15",
    "addr:postcode":"02882",
    "addr:street":"Leatherleaf Rd",
    "iso:country":"US",
    "sg:address":"15 Leatherleaf Rd",
    "sg:city":"Narragansett",
    "sg:classifiers":[
        {
            "category":"Professional",
            "subcategory":"Computer Services",
            "type":"Services"
        }
    ],
    "sg:phone":"+1 401 783 3924",
    "sg:postcode":"02882",
    "sg:province":"RI",
    "sg:tags":[
        "related"
    ],
    "wof:name":"Integrated Data Solutions Inc",
    "wof:placetype":"venue"
},
  "geometry": {"coordinates":[-71.43915200000001,41.475479],"type":"Point"}
}