{
  "type": "Feature",
  "properties": {
    "addr:full":"1 Ann and Hope Way Cumberland RI 02864",
    "addr:housenumber":"1",
    "addr:postcode":"02864",
    "addr:street":"Ann And Hope Way",
    "iso:country":"US",
    "sg:address":"1 Ann and Hope Way",
    "sg:city":"Cumberland",
    "sg:classifiers":[
        {
            "category":"Shopping",
            "subcategory":"Optician",
            "type":"Retail Goods"
        }
    ],
    "sg:phone":"+1 401 726 5930",
    "sg:postcode":"02864",
    "sg:province":"RI",
    "sg:tags":[
        "eyewear"
    ],
    "wof:name":"Ann & Hope Store Jewelers Outlet # 610",
    "wof:placetype":"venue"
},
  "geometry": {"coordinates":[-71.399101,41.914101],"type":"Point"}
}