{
  "type": "Feature",
  "properties": {
    "iso:country":"US",
    "sg:address":"218 Chalkstone Ave",
    "sg:city":"Providence",
    "sg:classifiers":[
        {
            "category":"Wholesale",
            "subcategory":"Scrap",
            "type":"Manufacturing & Wholesale Goods"
        }
    ],
    "sg:phone":"+1 401 351 3830",
    "sg:postcode":"02908",
    "sg:province":"RI",
    "sg:tags":[
        "material",
        "metal",
        "center",
        "iron"
    ],
    "wof:name":"Charles Scrap Metal",
    "wof:placetype":"venue"
},
  "geometry": {"coordinates":[-71.416679,41.836529],"type":"Point"}
}