{
  "type": "Feature",
  "properties": {
    "addr:full":"84 Pawtuxet Ave Cranston RI 02905",
    "addr:housenumber":"84",
    "addr:postcode":"02905",
    "addr:street":"Pawtuxet Ave",
    "iso:country":"US",
    "sg:address":"84 Pawtuxet Ave",
    "sg:city":"Cranston",
    "sg:classifiers":[
        {
            "category":"Manufacturing",
            "subcategory":"Metals",
            "type":"Manufacturing & Wholesale Goods"
        },
        {
            "category":"Building & Trades",
            "subcategory":"Construction",
            "type":"Services"
        }
    ],
    "sg:phone":"+1 401 781 5644",
    "sg:postcode":"02905",
    "sg:province":"RI",
    "sg:tags":[
        "fence",
        "contractor"
    ],
    "wof:name":"Victor Fence Company",
    "wof:placetype":"venue"
},
  "geometry": {"coordinates":[-71.397755,41.783756],"type":"Point"}
}