{
  "type": "Feature",
  "properties": {
    "addr:full":"395 Front St Woonsocket RI 02895",
    "addr:housenumber":"395",
    "addr:postcode":"02895",
    "addr:street":"Front St",
    "iso:country":"US",
    "sg:address":"395 Front St",
    "sg:city":"Woonsocket",
    "sg:classifiers":[
        {
            "category":"Food & Beverages",
            "subcategory":"Meat & Fish",
            "type":"Retail Goods"
        },
        {
            "category":"Wholesale",
            "subcategory":"Seafood",
            "type":"Manufacturing & Wholesale Goods"
        }
    ],
    "sg:phone":"+1 401 762 4800",
    "sg:postcode":"02895",
    "sg:province":"RI",
    "sg:tags":[
        "lobster"
    ],
    "wof:name":"Ray's Super Sea Food Inc",
    "wof:placetype":"venue"
},
  "geometry": {"coordinates":[-71.51266800000001,41.999431],"type":"Point"}
}