{
  "type": "Feature",
  "properties": {
    "addr:full":"165 Pitman Street Providence RI 02906",
    "addr:housenumber":"165",
    "addr:postcode":"02906",
    "addr:street":"Pitman Street",
    "iso:country":"US",
    "sg:address":"165 Pitman Street",
    "sg:city":"Providence",
    "sg:classifiers":[
        {
            "category":"Insurance",
            "subcategory":"Health Insurance",
            "type":"Services"
        },
        {
            "category":"Wholesale",
            "subcategory":"Fruits & Vegetables",
            "type":"Manufacturing & Wholesale Goods"
        },
        {
            "category":"Food & Beverages",
            "subcategory":"Meat & Fish",
            "type":"Retail Goods"
        }
    ],
    "sg:phone":"+1 401 831 5370",
    "sg:postcode":"02906",
    "sg:province":"RI",
    "sg:tags":[
        "shop",
        "seafood",
        "veggie",
        "market"
    ],
    "wof:name":"Eastside Marketplace",
    "wof:placetype":"venue"
},
  "geometry": {"coordinates":[-71.388402,41.826728],"type":"Point"}
}