{
  "type": "Feature",
  "properties": {
    "addr:full":"116 Randall Ave Warwick RI 02889",
    "addr:housenumber":"116",
    "addr:postcode":"02889",
    "addr:street":"Randall Ave",
    "iso:country":"US",
    "sg:address":"116 Randall Ave",
    "sg:city":"Warwick",
    "sg:classifiers":[
        {
            "category":"Shopping",
            "subcategory":"Gifts & Souvenirs",
            "type":"Retail Goods"
        }
    ],
    "sg:phone":"+1 401 739 8808",
    "sg:postcode":"02889",
    "sg:province":"RI",
    "wof:name":"Far East Jade",
    "wof:placetype":"venue"
},
  "geometry": {"coordinates":[-71.37998899999999,41.686067],"type":"Point"}
}