{
  "type": "Feature",
  "properties": {
    "iso:country":"US",
    "sg:address":"347 Waterman Ave",
    "sg:city":"Smithfield",
    "sg:classifiers":[
        {
            "category":"Restaurant",
            "type":"Food & Drink"
        }
    ],
    "sg:phone":"+1 401 233 0440",
    "sg:postcode":"02917",
    "sg:province":"RI",
    "sg:tags":[
        "eating"
    ],
    "wof:name":"Karen's Kitchen",
    "wof:placetype":"venue"
},
  "geometry": {"coordinates":[-71.49593299999999,41.874001],"type":"Point"}
}