{
  "type": "Feature",
  "properties": {
    "addr:full":"633 Metacom Ave Warren RI 02885",
    "addr:housenumber":"633",
    "addr:postcode":"02885",
    "addr:street":"Metacom Ave",
    "iso:country":"US",
    "sg:address":"633 Metacom Ave",
    "sg:city":"Warren",
    "sg:classifiers":[
        {
            "category":"Health Services",
            "subcategory":"Clinic",
            "type":"Services"
        },
        {
            "category":"Professional",
            "subcategory":"Employment Agencies",
            "type":"Services"
        }
    ],
    "sg:phone":"+1 401 245 0795",
    "sg:postcode":"02885",
    "sg:province":"RI",
    "sg:tags":[
        "home",
        "assistant",
        "physician"
    ],
    "sg:website":"http://www.preferredhealthcare.net",
    "wof:name":"Preferred Health Care Services",
    "wof:placetype":"venue"
},
  "geometry": {"coordinates":[-71.268261,41.716326],"type":"Point"}
}