{
  "type": "Feature",
  "properties": {
    "iso:country":"US",
    "sg:address":"5 Catamore Blvd",
    "sg:city":"East Providence",
    "sg:classifiers":[
        {
            "category":"Banks & Credit Unions",
            "subcategory":"Bank",
            "type":"Services"
        }
    ],
    "sg:phone":"+1 401 223 0555",
    "sg:postcode":"02914",
    "sg:province":"RI",
    "sg:tags":[
        "broker",
        "mortgage"
    ],
    "sg:website":"www.pmcoa.com",
    "wof:name":"Professional Mortgage Corp",
    "wof:placetype":"venue"
},
  "geometry": {"coordinates":[-71.343906,41.801195],"type":"Point"}
}