{
  "type": "Feature",
  "properties": {
    "addr:full":"338 Broad St Providence RI 02907",
    "addr:housenumber":"338",
    "addr:postcode":"02907",
    "addr:street":"Broad St",
    "iso:country":"US",
    "sg:address":"338 Broad St",
    "sg:city":"Providence",
    "sg:classifiers":[
        {
            "category":"Shopping",
            "subcategory":"Computers & Home Electronics",
            "type":"Retail Goods"
        }
    ],
    "sg:phone":"+1 401 277 4263",
    "sg:postcode":"02907",
    "sg:province":"RI",
    "sg:tags":[
        "game",
        "video"
    ],
    "wof:name":"Game World",
    "wof:placetype":"venue"
},
  "geometry": {"coordinates":[-71.42132700000001,41.813971],"type":"Point"}
}