{
  "type": "Feature",
  "properties": {
    "iso:country":"US",
    "sg:address":"555 Thames St",
    "sg:city":"Newport",
    "sg:classifiers":[
        {
            "category":"Professional",
            "subcategory":"Management & Consulting",
            "type":"Services"
        }
    ],
    "sg:phone":"+1 401 849 3387",
    "sg:postcode":"02840",
    "sg:province":"RI",
    "sg:tags":[
        "consultant",
        "marine"
    ],
    "wof:name":"Marine Construction Management",
    "wof:placetype":"venue"
},
  "geometry": {"coordinates":[-71.314196,41.477945],"type":"Point"}
}