{
  "type": "Feature",
  "properties": {
    "iso:country":"US",
    "sg:address":"725 Branch Ave",
    "sg:city":"Providence",
    "sg:classifiers":[
        {
            "category":"Professional",
            "subcategory":"Employment Agencies",
            "type":"Services"
        }
    ],
    "sg:phone":"+1 401 714 0505",
    "sg:postcode":"02904",
    "sg:province":"RI",
    "sg:tags":[
        "opportunity"
    ],
    "wof:name":"BHP Global Solutions",
    "wof:placetype":"venue"
},
  "geometry": {"coordinates":[-71.42877900000001,41.853739],"type":"Point"}
}