{
  "type": "Feature",
  "properties": {
    "addr:full":"18 Maple Ave Barrington RI 02806",
    "addr:housenumber":"18",
    "addr:postcode":"02806",
    "addr:street":"Maple Ave",
    "iso:country":"US",
    "sg:address":"18 Maple Ave",
    "sg:city":"Barrington",
    "sg:classifiers":[
        {
            "category":"Professional",
            "subcategory":"Computer Services",
            "type":"Services"
        }
    ],
    "sg:phone":"+1 401 245 9626",
    "sg:postcode":"02806",
    "sg:province":"RI",
    "sg:tags":[
        "consultant",
        "designer"
    ],
    "wof:name":"Info Tech",
    "wof:placetype":"venue"
},
  "geometry": {"coordinates":[-71.31031,41.739453],"type":"Point"}
}