{
  "type": "Feature",
  "properties": {
    "iso:country":"US",
    "sg:address":"182 Front St",
    "sg:city":"Lincoln",
    "sg:classifiers":[
        {
            "category":"Food & Beverages",
            "subcategory":"Liquor & Beverages",
            "type":"Retail Goods"
        }
    ],
    "sg:phone":"+1 401 475 6665",
    "sg:postcode":"02865",
    "sg:province":"RI",
    "sg:tags":[
        "shopping",
        "center",
        "alcoholic"
    ],
    "sg:website":"www.lincolnliquors.com",
    "wof:name":"Lincoln Liquors LLC",
    "wof:placetype":"venue"
},
  "geometry": {"coordinates":[-71.40816599999999,41.904501],"type":"Point"}
}