{
  "type": "Feature",
  "properties": {
    "iso:country":"US",
    "sg:address":"170 Thames St",
    "sg:city":"Newport",
    "sg:classifiers":[
        {
            "category":"Manufacturing",
            "subcategory":"Retail Goods",
            "type":"Manufacturing & Wholesale Goods"
        }
    ],
    "sg:phone":"+1 401 849 4430",
    "sg:postcode":"02840",
    "sg:province":"RI",
    "sg:tags":[
        "basket",
        "mfg",
        "supply"
    ],
    "wof:name":"New Port Trading",
    "wof:placetype":"venue"
},
  "geometry": {"coordinates":[-71.31513099999999,41.489755],"type":"Point"}
}