{
  "type": "Feature",
  "properties": {
    "addr:full":"11 Clarke St Newport RI 02840",
    "addr:housenumber":"11",
    "addr:postcode":"02840",
    "addr:street":"Clarke St",
    "iso:country":"US",
    "sg:address":"11 Clarke St",
    "sg:city":"Newport",
    "sg:classifiers":[
        {
            "category":"Communications",
            "subcategory":"Film & Video Production",
            "type":"Services"
        }
    ],
    "sg:phone":"+1 401 846 8890",
    "sg:postcode":"02840",
    "sg:province":"RI",
    "sg:tags":[
        "audio"
    ],
    "wof:name":"Pike Productions Inc",
    "wof:placetype":"venue"
},
  "geometry": {"coordinates":[-71.313524,41.488669],"type":"Point"}
}