{
  "type": "Feature",
  "properties": {
    "iso:country":"US",
    "sg:address":"84 Cutler St",
    "sg:city":"Warren",
    "sg:classifiers":[
        {
            "category":"Wholesale",
            "subcategory":"Home Furnishings",
            "type":"Manufacturing & Wholesale Goods"
        },
        {
            "category":"Wholesale",
            "subcategory":"Non-durable Goods",
            "type":"Manufacturing & Wholesale Goods"
        }
    ],
    "sg:phone":"+1 401 247 7710",
    "sg:postcode":"02885",
    "sg:province":"RI",
    "sg:tags":[
        "album",
        "photo",
        "frame",
        "advertising"
    ],
    "sg:website":"www.distinctivebrands.com",
    "wof:name":"Distinctive Brands Limited",
    "wof:placetype":"venue"
},
  "geometry": {"coordinates":[-71.27819,41.727393],"type":"Point"}
}