{
  "type": "Feature",
  "properties": {
    "iso:country":"US",
    "sg:address":"37 Waterman Dr",
    "sg:city":"North Scituate",
    "sg:classifiers":[
        {
            "category":"Building & Trades",
            "subcategory":"Electrical",
            "type":"Services"
        },
        {
            "category":"Professional",
            "subcategory":"Computer Services",
            "type":"Services"
        }
    ],
    "sg:phone":"+1 401 647 2240",
    "sg:postcode":"02857",
    "sg:province":"RI",
    "sg:tags":[
        "wiring",
        "electrical",
        "contractor"
    ],
    "wof:name":"Luther Electric Co",
    "wof:placetype":"venue"
},
  "geometry": {"coordinates":[-71.580809,41.791895],"type":"Point"}
}