{
  "type": "Feature",
  "properties": {
    "addr:full":"440 Buttonwoods Ave Warwick RI 02886",
    "addr:housenumber":"440",
    "addr:postcode":"02886",
    "addr:street":"Buttonwoods Ave",
    "iso:country":"US",
    "sg:address":"440 Buttonwoods Ave",
    "sg:city":"Warwick",
    "sg:classifiers":[
        {
            "category":"Personal",
            "subcategory":"Beauty Salon",
            "type":"Services"
        }
    ],
    "sg:phone":"+1 401 737 9650",
    "sg:postcode":"02886",
    "sg:province":"RI",
    "wof:name":"Hair Dimensions",
    "wof:placetype":"venue"
},
  "geometry": {"coordinates":[-71.42701599999999,41.694437],"type":"Point"}
}