{
  "type": "Feature",
  "properties": {
    "iso:country":"US",
    "sg:address":"21 Van Zandt Ave",
    "sg:city":"Warwick",
    "sg:classifiers":[
        {
            "category":"Professional",
            "subcategory":"Business Services",
            "type":"Services"
        }
    ],
    "sg:phone":"+1 401 732 1294",
    "sg:postcode":"02889",
    "sg:province":"RI",
    "wof:name":"Jac Oil Svc Inc",
    "wof:placetype":"venue"
},
  "geometry": {"coordinates":[-71.367193,41.706912],"type":"Point"}
}