{
  "type": "Feature",
  "properties": {
    "iso:country":"US",
    "sg:address":"309 Greenwich Ave",
    "sg:city":"Warwick",
    "sg:classifiers":[
        {
            "category":"Manufacturing",
            "subcategory":"Retail Goods",
            "type":"Manufacturing & Wholesale Goods"
        }
    ],
    "sg:phone":"+1 401 738 7173",
    "sg:postcode":"02886",
    "sg:province":"RI",
    "sg:tags":[
        "product",
        "mfg"
    ],
    "wof:name":"Balian Industries Intl Co",
    "wof:placetype":"venue"
},
  "geometry": {"coordinates":[-71.47314900000001,41.725797],"type":"Point"}
}