{
  "type": "Feature",
  "properties": {
    "iso:country":"US",
    "sg:address":"5 Windward Dr",
    "sg:city":"Barrington",
    "sg:classifiers":[
        {
            "category":"Health Services",
            "subcategory":"Doctor",
            "type":"Services"
        }
    ],
    "sg:phone":"+1 401 245 8758",
    "sg:postcode":"02806",
    "sg:province":"RI",
    "sg:tags":[
        "medical"
    ],
    "wof:name":"Georges Peter",
    "wof:placetype":"venue"
},
  "geometry": {"coordinates":[-71.296312,41.72695],"type":"Point"}
}