{
  "type": "Feature",
  "properties": {
    "addr:full":"51 Callendar Ave Newport RI 02840",
    "addr:housenumber":"51",
    "addr:postcode":"02840",
    "addr:street":"Callendar Ave",
    "iso:country":"US",
    "sg:address":"51 Callendar Ave",
    "sg:city":"Newport",
    "sg:classifiers":[
        {
            "category":"Building & Trades",
            "subcategory":"Construction",
            "type":"Services"
        }
    ],
    "sg:phone":"+1 401 845 0966",
    "sg:postcode":"02840",
    "sg:province":"RI",
    "sg:tags":[
        "contractor"
    ],
    "wof:name":"Napolitano Builders",
    "wof:placetype":"venue"
},
  "geometry": {"coordinates":[-71.312861,41.494829],"type":"Point"}
}