{
  "type": "Feature",
  "properties": {
    "addr:full":"361 Beacon Dr North Kingstown RI 02852",
    "addr:housenumber":"361",
    "addr:postcode":"02852",
    "addr:street":"Beacon Dr",
    "iso:country":"US",
    "sg:address":"361 Beacon Dr",
    "sg:city":"North Kingstown",
    "sg:classifiers":[
        {
            "category":"Banks & Credit Unions",
            "subcategory":"Financial Services",
            "type":"Services"
        }
    ],
    "sg:phone":"+1 401 295 5161",
    "sg:postcode":"02852",
    "sg:province":"RI",
    "sg:tags":[
        "investor"
    ],
    "wof:name":"Global Investments LLC",
    "wof:placetype":"venue"
},
  "geometry": {"coordinates":[-71.504818,41.572282],"type":"Point"}
}