{
  "type": "Feature",
  "properties": {
    "iso:country":"US",
    "sg:address":"1499 Newport Ave",
    "sg:city":"Pawtucket",
    "sg:classifiers":[
        {
            "category":"Insurance",
            "subcategory":"Insurance Agent",
            "type":"Services"
        },
        {
            "category":"Insurance",
            "subcategory":"Hazard Insurance",
            "type":"Services"
        },
        {
            "category":"Insurance",
            "subcategory":"Title Insurance",
            "type":"Services"
        }
    ],
    "sg:phone":"+1 401 722 1442",
    "sg:postcode":"02861",
    "sg:province":"RI",
    "sg:tags":[
        "auto",
        "commercial",
        "business",
        "homeowner"
    ],
    "sg:website":"http://metlife.findlocalagent.net/car-insurance-in-Providence-Fall-River-Warwick-RI_18",
    "wof:name":"MetLife Auto & Home Agent: Erik Kugel",
    "wof:placetype":"venue"
},
  "geometry": {"coordinates":[-71.354035,41.893783],"type":"Point"}
}