{
  "type": "Feature",
  "properties": {
    "addr:full":"4 Circle Dr North Smithfield RI 02896",
    "addr:housenumber":"4",
    "addr:postcode":"02896",
    "addr:street":"Circle Dr",
    "iso:country":"US",
    "sg:address":"4 Circle Dr",
    "sg:city":"North Smithfield",
    "sg:classifiers":[
        {
            "category":"Professional",
            "subcategory":"Computer Services",
            "type":"Services"
        }
    ],
    "sg:phone":"+1 401 765 3100",
    "sg:postcode":"02896",
    "sg:province":"RI",
    "sg:tags":[
        "consultant",
        "designer",
        "programing",
        "custom"
    ],
    "wof:name":"Edco Computer Consultants Inc",
    "wof:placetype":"venue"
},
  "geometry": {"coordinates":[-71.568634,41.987938],"type":"Point"}
}