{
  "type": "Feature",
  "properties": {
    "iso:country":"US",
    "sg:address":"52 High St",
    "sg:city":"Westerly",
    "sg:classifiers":[
        {
            "category":"Building & Trades",
            "subcategory":"Landscaping Services",
            "type":"Services"
        }
    ],
    "sg:phone":"+1 401 348 1841",
    "sg:postcode":"02891",
    "sg:province":"RI",
    "wof:name":"Heritage Tree Care",
    "wof:placetype":"venue"
},
  "geometry": {"coordinates":[-71.83040800000001,41.378201],"type":"Point"}
}