{
  "type": "Feature",
  "properties": {
    "iso:country":"US",
    "sg:address":"593 Eddy St",
    "sg:city":"Providence",
    "sg:classifiers":[
        {
            "category":"Health Services",
            "subcategory":"Hospital",
            "type":"Services"
        }
    ],
    "sg:phone":"+1 401 444 5391",
    "sg:postcode":"02903",
    "sg:province":"RI",
    "sg:tags":[
        "sleep",
        "treatment",
        "disorders-information"
    ],
    "wof:name":"Louis A Leone",
    "wof:placetype":"venue"
},
  "geometry": {"coordinates":[-71.407089,41.811668],"type":"Point"}
}