{
  "type": "Feature",
  "properties": {
    "iso:country":"US",
    "sg:address":"145 Main St",
    "sg:city":"East Greenwich",
    "sg:classifiers":[
        {
            "category":"Restaurant",
            "type":"Food & Drink"
        }
    ],
    "sg:menulink":"http://www.allmenus.com/ri/east-greenwich/58789-jiggers-diner/menu/",
    "sg:phone":"+1 401 884 5388",
    "sg:postcode":"02818",
    "sg:province":"RI",
    "sg:tags":[
        "american",
        "diner"
    ],
    "wof:name":"Jiggers Diner",
    "wof:placetype":"venue"
},
  "geometry": {"coordinates":[-71.450019,41.661935],"type":"Point"}
}