{
  "type": "Feature",
  "properties": {
    "addr:full":"1099 Mendon Rd Cumberland RI 02864",
    "addr:housenumber":"1099",
    "addr:postcode":"02864",
    "addr:street":"Mendon Rd",
    "iso:country":"US",
    "sg:address":"1099 Mendon Rd",
    "sg:city":"Cumberland",
    "sg:classifiers":[
        {
            "category":"Retail",
            "subcategory":"Repair Shop",
            "type":"Services"
        }
    ],
    "sg:phone":"+1 401 333 8224",
    "sg:postcode":"02864",
    "sg:province":"RI",
    "sg:tags":[
        "used",
        "refinishing",
        "merchandise",
        "furniture"
    ],
    "wof:name":"Cro's Nest",
    "wof:placetype":"venue"
},
  "geometry": {"coordinates":[-71.422089,41.92968],"type":"Point"}
}