{
  "type": "Feature",
  "properties": {
    "iso:country":"US",
    "sg:address":"33 College Hill Rd",
    "sg:city":"Warwick",
    "sg:classifiers":[
        {
            "category":"Professional",
            "subcategory":"Accounting & Tax Preparation",
            "type":"Services"
        }
    ],
    "sg:phone":"+1 401 828 0700",
    "sg:postcode":"02886",
    "sg:province":"RI",
    "sg:tags":[
        "accountant"
    ],
    "wof:name":"Richard F Saccoccia CPA",
    "wof:placetype":"venue"
},
  "geometry": {"coordinates":[-71.485619,41.713349],"type":"Point"}
}