{
  "type": "Feature",
  "properties": {
    "iso:country":"US",
    "sg:address":"9 Taylor Rd",
    "sg:city":"Johnston",
    "sg:classifiers":[
        {
            "category":"Retail",
            "subcategory":"Laundry & Dry Cleaning",
            "type":"Services"
        }
    ],
    "sg:phone":"+1 401 464 8937",
    "sg:postcode":"02919",
    "sg:province":"RI",
    "sg:tags":[
        "cleaners",
        "rug",
        "carpet"
    ],
    "wof:name":"Lynch's Cleaning Svc",
    "wof:placetype":"venue"
},
  "geometry": {"coordinates":[-71.520658,41.790931],"type":"Point"}
}