{
  "type": "Feature",
  "properties": {
    "addr:full":"231 Old Tower Hill Rd Wakefield RI 02879",
    "addr:housenumber":"231",
    "addr:postcode":"02879",
    "addr:street":"Old Tower Hill Rd",
    "iso:country":"US",
    "sg:address":"231 Old Tower Hill Rd",
    "sg:city":"Wakefield",
    "sg:classifiers":[
        {
            "category":"Banks & Credit Unions",
            "subcategory":"Bank",
            "type":"Services"
        }
    ],
    "sg:phone":"+1 401 782 6000",
    "sg:postcode":"02879",
    "sg:province":"RI",
    "sg:tags":[
        "company",
        "mortgage"
    ],
    "wof:name":"Wells Fargo",
    "wof:placetype":"venue"
},
  "geometry": {"coordinates":[-71.480346,41.442402],"type":"Point"}
}