{
  "type": "Feature",
  "properties": {
    "addr:full":"3 Frank Dr Portsmouth RI 02878",
    "addr:housenumber":"3",
    "addr:postcode":"02878",
    "addr:street":"Frank Dr",
    "iso:country":"US",
    "sg:address":"3 Frank Dr",
    "sg:city":"Portsmouth",
    "sg:classifiers":[
        {
            "category":"Restaurant",
            "type":"Food & Drink"
        }
    ],
    "sg:phone":"+1 401 683 4177",
    "sg:postcode":"02878",
    "sg:province":"RI",
    "sg:tags":[
        "personal",
        "eating"
    ],
    "sg:website":"www.glenmanorhouse.com",
    "wof:name":"Glen Manor House",
    "wof:placetype":"venue"
},
  "geometry": {"coordinates":[-71.18884300000001,41.655283],"type":"Point"}
}