{
  "type": "Feature",
  "properties": {
    "iso:country":"US",
    "sg:address":"1325 Sherman Farm Rd",
    "sg:city":"Harrisville",
    "sg:classifiers":[
        {
            "category":"Retail",
            "subcategory":"Auto Repair",
            "type":"Services"
        }
    ],
    "sg:phone":"+1 401 567 0838",
    "sg:postcode":"02830",
    "sg:province":"RI",
    "sg:tags":[
        "body"
    ],
    "wof:name":"Collision Tools Inc",
    "wof:placetype":"venue"
},
  "geometry": {"coordinates":[-71.678562,42.005869],"type":"Point"}
}