{
  "type": "Feature",
  "properties": {
    "iso:country":"US",
    "sg:address":"4 Dolly Dr",
    "sg:city":"Bristol",
    "sg:classifiers":[
        {
            "category":"Restaurant",
            "type":"Food & Drink"
        }
    ],
    "sg:phone":"+1 401 254 2333",
    "sg:postcode":"02809",
    "sg:province":"RI",
    "sg:tags":[
        "eating"
    ],
    "wof:name":"Greg Doyle Canteen Ltd",
    "wof:placetype":"venue"
},
  "geometry": {"coordinates":[-71.28031799999999,41.705089],"type":"Point"}
}