{
  "type": "Feature",
  "properties": {
    "iso:country":"US",
    "sg:address":"527 Thames St",
    "sg:city":"Newport",
    "sg:classifiers":[
        {
            "category":"Restaurant",
            "type":"Food & Drink"
        }
    ],
    "sg:phone":"+1 401 847 2000",
    "sg:postcode":"02840",
    "sg:province":"RI",
    "sg:tags":[
        "eating"
    ],
    "wof:name":"Upscales",
    "wof:placetype":"venue"
},
  "geometry": {"coordinates":[-71.31424,41.478339],"type":"Point"}
}