{
  "type": "Feature",
  "properties": {
    "addr:full":"43 Stony Acre Dr Cranston RI 02920",
    "addr:housenumber":"43",
    "addr:postcode":"02920",
    "addr:street":"Stony Acre Dr",
    "iso:country":"US",
    "sg:address":"43 Stony Acre Dr",
    "sg:city":"Cranston",
    "sg:classifiers":[
        {
            "category":"Manufacturing",
            "subcategory":"Glass & Minerals",
            "type":"Manufacturing & Wholesale Goods"
        }
    ],
    "sg:phone":"+1 401 823 5527",
    "sg:postcode":"02920",
    "sg:province":"RI",
    "sg:tags":[
        "product",
        "nonmetallic",
        "mfg"
    ],
    "wof:name":"Joanne Delomba Studios",
    "wof:placetype":"venue"
},
  "geometry": {"coordinates":[-71.48815500000001,41.792022],"type":"Point"}
}