{
  "type": "Feature",
  "properties": {
    "addr:full":"82 Broadway Newport RI 02840",
    "addr:housenumber":"82",
    "addr:postcode":"02840",
    "addr:street":"Broadway",
    "iso:country":"US",
    "sg:address":"82 Broadway",
    "sg:city":"Newport",
    "sg:classifiers":[
        {
            "category":"Restaurant",
            "type":"Food & Drink"
        }
    ],
    "sg:phone":"+1 401 846 2100",
    "sg:postcode":"02840",
    "sg:province":"RI",
    "wof:name":"Kio's Asian Stir",
    "wof:placetype":"venue"
},
  "geometry": {"coordinates":[-71.31125299999999,41.492288],"type":"Point"}
}