{
  "type": "Feature",
  "properties": {
    "addr:full":"359 Stafford Rd Tiverton RI 02878",
    "addr:housenumber":"359",
    "addr:postcode":"02878",
    "addr:street":"Stafford Rd",
    "iso:country":"US",
    "sg:address":"359 Stafford Rd",
    "sg:city":"Tiverton",
    "sg:classifiers":[
        {
            "category":"Personal",
            "subcategory":"Beauty Salon",
            "type":"Services"
        }
    ],
    "sg:phone":"+1 401 625 5363",
    "sg:postcode":"02878",
    "sg:province":"RI",
    "sg:tags":[
        "shop"
    ],
    "wof:name":"Marie's Beauty Salon",
    "wof:placetype":"venue"
},
  "geometry": {"coordinates":[-71.150508,41.65206],"type":"Point"}
}