{
  "type": "Feature",
  "properties": {
    "iso:country":"US",
    "sg:address":"461 Main St",
    "sg:city":"East Greenwich",
    "sg:classifiers":[
        {
            "category":"Shopping",
            "subcategory":"Florist",
            "type":"Retail Goods"
        }
    ],
    "sg:phone":"+1 401 884 8800",
    "sg:postcode":"02818",
    "sg:province":"RI",
    "wof:name":"Botanica",
    "wof:placetype":"venue"
},
  "geometry": {"coordinates":[-71.451842,41.657524],"type":"Point"}
}