{
  "type": "Feature",
  "properties": {
    "iso:country":"US",
    "sg:address":"1985 Broad St",
    "sg:city":"Cranston",
    "sg:classifiers":[
        {
            "category":"Home & Garden",
            "subcategory":"Building Materials",
            "type":"Retail Goods"
        },
        {
            "category":"Manufacturing",
            "subcategory":"Tools & Machinery",
            "type":"Manufacturing & Wholesale Goods"
        }
    ],
    "sg:phone":"+1 401 461 4635",
    "sg:postcode":"02905",
    "sg:province":"RI",
    "sg:tags":[
        "door",
        "mfg",
        "devices",
        "operating",
        "gate",
        "electrical"
    ],
    "wof:name":"Edge Wood Door Company",
    "wof:placetype":"venue"
},
  "geometry": {"coordinates":[-71.39481600000001,41.771451],"type":"Point"}
}