{
  "type": "Feature",
  "properties": {
    "iso:country":"US",
    "sg:address":"5 Briarwood Rd",
    "sg:city":"North Scituate",
    "sg:classifiers":[
        {
            "category":"Freight",
            "type":"Transportation"
        }
    ],
    "sg:phone":"+1 401 323 0009",
    "sg:postcode":"02857",
    "sg:province":"RI",
    "sg:tags":[
        "automobile",
        "transport"
    ],
    "wof:name":"Skyline Auto Transport Inc",
    "wof:placetype":"venue"
},
  "geometry": {"coordinates":[-71.61451700000001,41.874381],"type":"Point"}
}