{
  "type": "Feature",
  "properties": {
    "iso:country":"US",
    "sg:address":"64 Eagle St",
    "sg:city":"Providence",
    "sg:classifiers":[
        {
            "category":"Shopping",
            "subcategory":"Discount & Variety Stores",
            "type":"Retail Goods"
        }
    ],
    "sg:phone":"+1 401 272 6909",
    "sg:postcode":"02919",
    "sg:province":"RI",
    "sg:tags":[
        "merchandise",
        "general"
    ],
    "wof:name":"Tamco Sales Inc",
    "wof:placetype":"venue"
},
  "geometry": {"coordinates":[-71.486448,41.830214],"type":"Point"}
}