{
  "type": "Feature",
  "properties": {
    "iso:country":"US",
    "sg:address":"763 Atwood Ave",
    "sg:city":"Cranston",
    "sg:classifiers":[
        {
            "category":"Arts & Performance",
            "subcategory":"Theater",
            "type":"Entertainment"
        }
    ],
    "sg:phone":"+1 401 944 8000",
    "sg:postcode":"02920",
    "sg:province":"RI",
    "wof:name":"Fantasy Sounds Unlimited Inc",
    "wof:placetype":"venue"
},
  "geometry": {"coordinates":[-71.47827700000001,41.794055],"type":"Point"}
}