{
  "type": "Feature",
  "properties": {
    "addr:full":"16 Mount Vernon St Newport RI 02840",
    "addr:housenumber":"16",
    "addr:postcode":"02840",
    "addr:street":"Mount Vernon St",
    "iso:country":"US",
    "sg:address":"16 Mount Vernon St",
    "sg:city":"Newport",
    "sg:classifiers":[
        {
            "category":"Professional",
            "subcategory":"Business Services",
            "type":"Services"
        }
    ],
    "sg:phone":"+1 401 849 0718",
    "sg:postcode":"02840",
    "sg:province":"RI",
    "sg:tags":[
        "consulting",
        "maritime"
    ],
    "wof:name":"David Wood",
    "wof:placetype":"venue"
},
  "geometry": {"coordinates":[-71.310732,41.48915],"type":"Point"}
}