{
  "type": "Feature",
  "properties": {
    "iso:country":"US",
    "sg:address":"147 Garden City Dr",
    "sg:city":"Cranston",
    "sg:classifiers":[
        {
            "category":"Banks & Credit Unions",
            "subcategory":"Financial Services",
            "type":"Services"
        }
    ],
    "sg:phone":"+1 401 946 7311",
    "sg:postcode":"02920",
    "sg:province":"RI",
    "sg:tags":[
        "trust",
        "investment",
        "real estate"
    ],
    "wof:name":"Joan Romano",
    "wof:placetype":"venue"
},
  "geometry": {"coordinates":[-71.45350999999999,41.763877],"type":"Point"}
}