{
  "type": "Feature",
  "properties": {
    "addr:full":"1680 Cranston St Cranston RI 02920",
    "addr:housenumber":"1680",
    "addr:postcode":"02920",
    "addr:street":"Cranston St",
    "iso:country":"US",
    "sg:address":"1680 Cranston St",
    "sg:city":"Cranston",
    "sg:classifiers":[
        {
            "category":"Retail",
            "subcategory":"Repair Shop",
            "type":"Services"
        }
    ],
    "sg:phone":"+1 401 946 2108",
    "sg:postcode":"02920",
    "sg:province":"RI",
    "wof:name":"Loskoutov Vladimar Watch Repr",
    "wof:placetype":"venue"
},
  "geometry": {"coordinates":[-71.464496,41.783864],"type":"Point"}
}