{
  "type": "Feature",
  "properties": {
    "iso:country":"US",
    "sg:address":"40 Stevens St",
    "sg:city":"North Providence",
    "sg:classifiers":[
        {
            "category":"Building & Trades",
            "subcategory":"Electrical",
            "type":"Services"
        }
    ],
    "sg:phone":"+1 401 232 1204",
    "sg:postcode":"02911",
    "sg:province":"RI",
    "sg:tags":[
        "work",
        "electrical"
    ],
    "wof:name":"Jack S Electric",
    "wof:placetype":"venue"
},
  "geometry": {"coordinates":[-71.482406,41.854761],"type":"Point"}
}