{
  "type": "Feature",
  "properties": {
    "addr:full":"2563 Post Rd Warwick RI 02886",
    "addr:housenumber":"2563",
    "addr:postcode":"02886",
    "addr:street":"Post Rd",
    "iso:country":"US",
    "sg:address":"2563 Post Rd",
    "sg:city":"Warwick",
    "sg:classifiers":[
        {
            "category":"Home & Garden",
            "subcategory":"Building Materials",
            "type":"Retail Goods"
        }
    ],
    "sg:phone":"+1 401 732 9794",
    "sg:postcode":"02886",
    "sg:province":"RI",
    "sg:tags":[
        "glass",
        "window",
        "plate"
    ],
    "wof:name":"Safelite Auto Glass",
    "wof:placetype":"venue"
},
  "geometry": {"coordinates":[-71.44712699999999,41.711579],"type":"Point"}
}