{
  "type": "Feature",
  "properties": {
    "iso:country":"US",
    "sg:address":"1563 Plainfield Pike",
    "sg:city":"Johnston",
    "sg:classifiers":[
        {
            "category":"Education",
            "subcategory":"Special Training",
            "type":"Public Place"
        }
    ],
    "sg:phone":"+1 401 944 2895",
    "sg:postcode":"02919",
    "sg:province":"RI",
    "wof:name":"Accordion Conservatory",
    "wof:placetype":"venue"
},
  "geometry": {"coordinates":[-71.490758,41.791439],"type":"Point"}
}