{
  "type": "Feature",
  "properties": {
    "iso:country":"US",
    "sg:address":"344 3rd Ave",
    "sg:city":"Newport",
    "sg:classifiers":[
        {
            "category":"Government",
            "subcategory":"Office",
            "type":"Public Place"
        }
    ],
    "sg:phone":"+1 401 841 2241",
    "sg:postcode":"02895",
    "sg:province":"RI",
    "sg:tags":[
        "federal",
        "security"
    ],
    "sg:website":"www.ncis.navy.mil",
    "wof:name":"US Naval Investigative Svc",
    "wof:placetype":"venue"
},
  "geometry": {"coordinates":[-71.528077,42.001792],"type":"Point"}
}