{
  "type": "Feature",
  "properties": {
    "addr:full":"32 Toll Gate Rd Warwick RI 02886",
    "addr:housenumber":"32",
    "addr:postcode":"02886",
    "addr:street":"Toll Gate Rd",
    "iso:country":"US",
    "sg:address":"32 Toll Gate Rd",
    "sg:city":"Warwick",
    "sg:classifiers":[
        {
            "category":"Deli",
            "type":"Food & Drink"
        }
    ],
    "sg:menulink":"http://www.allmenus.com/ri/warwick/53314-the-bagel-factory/menu/",
    "sg:phone":"+1 401 737 0109",
    "sg:postcode":"02886",
    "sg:province":"RI",
    "sg:tags":[
        "american"
    ],
    "wof:name":"The Bagel Factory",
    "wof:placetype":"venue"
},
  "geometry": {"coordinates":[-71.464788,41.698461],"type":"Point"}
}