{
  "type": "Feature",
  "properties": {
    "iso:country":"US",
    "sg:address":"4 Wampanoag Dr",
    "sg:city":"Portsmouth",
    "sg:classifiers":[
        {
            "category":"Social Services",
            "type":"Services"
        }
    ],
    "sg:phone":"+1 401 683 5386",
    "sg:postcode":"02871",
    "sg:province":"RI",
    "sg:tags":[
        "counselor",
        "marriage",
        "family"
    ],
    "wof:name":"Betsy Madden-Echols Licsw",
    "wof:placetype":"venue"
},
  "geometry": {"coordinates":[-71.245615,41.573417],"type":"Point"}
}