{
  "type": "Feature",
  "properties": {
    "iso:country":"US",
    "sg:address":"778 Charles St",
    "sg:city":"Providence",
    "sg:classifiers":[
        {
            "category":"Autos & Motor Vehicles",
            "subcategory":"Fuel & Gas Station",
            "type":"Retail Goods"
        },
        {
            "category":"Retail",
            "subcategory":"Auto Repair",
            "type":"Services"
        }
    ],
    "sg:phone":"+1 401 831 9128",
    "sg:postcode":"02904",
    "sg:province":"RI",
    "sg:tags":[
        "repairing",
        "automobile",
        "gasoline"
    ],
    "wof:name":"Richard's Service Station",
    "wof:placetype":"venue"
},
  "geometry": {"coordinates":[-71.421097,41.8577],"type":"Point"}
}