{
  "type": "Feature",
  "properties": {
    "iso:country":"US",
    "sg:address":"146 Admiral St",
    "sg:city":"Providence",
    "sg:classifiers":[
        {
            "category":"Manufacturing",
            "subcategory":"Jewelry",
            "type":"Manufacturing & Wholesale Goods"
        }
    ],
    "sg:phone":"+1 401 272 3888",
    "sg:postcode":"02908",
    "sg:province":"RI",
    "wof:name":"Look",
    "wof:placetype":"venue"
},
  "geometry": {"coordinates":[-71.421859,41.8424],"type":"Point"}
}