{
  "type": "Feature",
  "properties": {
    "iso:country":"US",
    "sg:address":"47 Chandler St",
    "sg:city":"Newport",
    "sg:classifiers":[
        {
            "category":"Government",
            "subcategory":"Office",
            "type":"Public Place"
        }
    ],
    "sg:phone":"+1 401 841 4212",
    "sg:postcode":"02865",
    "sg:province":"RI",
    "sg:tags":[
        "national",
        "security"
    ],
    "wof:name":"Naval Education & Training Ctr",
    "wof:placetype":"venue"
},
  "geometry": {"coordinates":[-71.47869799999999,41.850845],"type":"Point"}
}