{
  "type": "Feature",
  "properties": {
    "iso:country":"US",
    "sg:address":"1670 Hartford Ave",
    "sg:city":"Johnston",
    "sg:classifiers":[
        {
            "category":"Government",
            "subcategory":"Office",
            "type":"Public Place"
        }
    ],
    "sg:phone":"+1 401 222 2291",
    "sg:postcode":"02919",
    "sg:province":"RI",
    "sg:tags":[
        "computer",
        "center"
    ],
    "wof:name":"RI State Computer Center",
    "wof:placetype":"venue"
},
  "geometry": {"coordinates":[-71.507689,41.825736],"type":"Point"}
}