{
  "type": "Feature",
  "properties": {
    "addr:full":"911 Broad St Providence RI 02907",
    "addr:housenumber":"911",
    "addr:postcode":"02907",
    "addr:street":"Broad St",
    "iso:country":"US",
    "sg:address":"911 Broad St",
    "sg:city":"Providence",
    "sg:classifiers":[
        {
            "category":"Retail",
            "subcategory":"Auto Repair",
            "type":"Services"
        }
    ],
    "sg:phone":"+1 401 781 5557",
    "sg:postcode":"02907",
    "sg:province":"RI",
    "sg:tags":[
        "repairing",
        "automobile"
    ],
    "wof:name":"Stanley's Auto Svc",
    "wof:placetype":"venue"
},
  "geometry": {"coordinates":[-71.415612,41.79889],"type":"Point"}
}