{
  "type": "Feature",
  "properties": {
    "addr:full":"1447 Wampanoag Trl Riverside RI 02915",
    "addr:housenumber":"1447",
    "addr:postcode":"02915",
    "addr:street":"Wampanoag Trl",
    "iso:country":"US",
    "sg:address":"1447 Wampanoag Trl",
    "sg:city":"Riverside",
    "sg:classifiers":[
        {
            "category":"Home & Garden",
            "subcategory":"Home Furnishings",
            "type":"Retail Goods"
        }
    ],
    "sg:phone":"+1 401 433 0500",
    "sg:postcode":"02915",
    "sg:province":"RI",
    "sg:tags":[
        "lamp",
        "shades"
    ],
    "wof:name":"Breeze Hill Lamp & Shade Shop",
    "wof:placetype":"venue"
},
  "geometry": {"coordinates":[-71.330671,41.778147],"type":"Point"}
}