{
  "type": "Feature",
  "properties": {
    "iso:country":"US",
    "sg:address":"801 Elmwood Ave",
    "sg:city":"Providence",
    "sg:classifiers":[
        {
            "category":"Food & Beverages",
            "subcategory":"Liquor & Beverages",
            "type":"Retail Goods"
        }
    ],
    "sg:phone":"+1 401 785 3944",
    "sg:postcode":"02907",
    "sg:province":"RI",
    "sg:tags":[
        "alcoholic"
    ],
    "wof:name":"Mundial Liquors",
    "wof:placetype":"venue"
},
  "geometry": {"coordinates":[-71.422111,41.790421],"type":"Point"}
}