{
  "type": "Feature",
  "properties": {
    "addr:full":"958 Centerville Rd Warwick RI 02886",
    "addr:housenumber":"958",
    "addr:postcode":"02886",
    "addr:street":"Centerville Rd",
    "iso:country":"US",
    "sg:address":"958 Centerville Rd",
    "sg:city":"Warwick",
    "sg:classifiers":[
        {
            "category":"Professional",
            "type":"Services"
        }
    ],
    "sg:phone":"+1 401 821 2319",
    "sg:postcode":"02886",
    "sg:province":"RI",
    "wof:name":"Herb Bianchi Co",
    "wof:placetype":"venue"
},
  "geometry": {"coordinates":[-71.493302,41.696794],"type":"Point"}
}