{
  "type": "Feature",
  "properties": {
    "iso:country":"US",
    "sg:address":"1467 Atwood Ave",
    "sg:city":"Johnston",
    "sg:classifiers":[
        {
            "category":"Wholesale",
            "subcategory":"Jewelry",
            "type":"Manufacturing & Wholesale Goods"
        }
    ],
    "sg:phone":"+1 401 272 6777",
    "sg:postcode":"02919",
    "sg:province":"RI",
    "sg:tags":[
        "jeweler",
        "findings",
        "supply"
    ],
    "wof:name":"Waliga Imports & Sales Inc",
    "wof:placetype":"venue"
},
  "geometry": {"coordinates":[-71.49804,41.820835],"type":"Point"}
}