{
  "type": "Feature",
  "properties": {
    "addr:full":"291 High St Woonsocket RI 02895",
    "addr:housenumber":"291",
    "addr:postcode":"02895",
    "addr:street":"High St",
    "iso:country":"US",
    "sg:address":"291 High St",
    "sg:city":"Woonsocket",
    "sg:classifiers":[
        {
            "category":"Shopping",
            "subcategory":"Used Merchandise",
            "type":"Retail Goods"
        }
    ],
    "sg:phone":"+1 401 762 9661",
    "sg:postcode":"02895",
    "sg:province":"RI",
    "sg:tags":[
        "antique"
    ],
    "wof:name":"Antique Toys & Collectables",
    "wof:placetype":"venue"
},
  "geometry": {"coordinates":[-71.518146,42.003248],"type":"Point"}
}