{
  "type": "Feature",
  "properties": {
    "iso:country":"US",
    "sg:address":"4365 Post Rd",
    "sg:city":"East Greenwich",
    "sg:classifiers":[
        {
            "category":"Restaurant",
            "type":"Food & Drink"
        }
    ],
    "sg:phone":"+1 401 885 4034",
    "sg:postcode":"02818",
    "sg:province":"RI",
    "sg:tags":[
        "eating"
    ],
    "wof:name":"Fu Wong Restaurant Inc",
    "wof:placetype":"venue"
},
  "geometry": {"coordinates":[-71.44808999999999,41.672145],"type":"Point"}
}