{
  "type": "Feature",
  "properties": {
    "addr:full":"39 Greenville Ave Johnston RI 02919",
    "addr:housenumber":"39",
    "addr:postcode":"02919",
    "addr:street":"Greenville",
    "iso:country":"US",
    "sg:address":"39 Greenville Ave",
    "sg:city":"Johnston",
    "sg:classifiers":[
        {
            "category":"Professional",
            "type":"Services"
        }
    ],
    "sg:phone":"+1 401 453 4731",
    "sg:postcode":"02919",
    "sg:province":"RI",
    "sg:tags":[
        "establishment"
    ],
    "wof:name":"Del's Lemonade Of Johnston",
    "wof:placetype":"venue"
},
  "geometry": {"coordinates":[-71.47332299999999,41.83316],"type":"Point"}
}