{
  "type": "Feature",
  "properties": {
    "addr:full":"21 Katama Rd Pawtucket RI 02861",
    "addr:housenumber":"21",
    "addr:postcode":"02861",
    "addr:street":"Katama Rd",
    "iso:country":"US",
    "sg:address":"21 Katama Rd",
    "sg:city":"Pawtucket",
    "sg:classifiers":[
        {
            "category":"Building & Trades",
            "subcategory":"Landscaping Services",
            "type":"Services"
        }
    ],
    "sg:phone":"+1 401 722 5912",
    "sg:postcode":"02861",
    "sg:province":"RI",
    "sg:tags":[
        "landscape",
        "contractor"
    ],
    "wof:name":"D M Bruzzi Landscape Co",
    "wof:placetype":"venue"
},
  "geometry": {"coordinates":[-71.340417,41.867393],"type":"Point"}
}