{
  "type": "Feature",
  "properties": {
    "iso:country":"US",
    "sg:address":"285 Gravelly Hill Rd",
    "sg:city":"Wakefield",
    "sg:classifiers":[
        {
            "category":"Professional",
            "subcategory":"Management & Consulting",
            "type":"Services"
        }
    ],
    "sg:phone":"+1 401 783 0560",
    "sg:postcode":"02879",
    "sg:province":"RI",
    "sg:tags":[
        "consultant",
        "training"
    ],
    "wof:name":"Lovett Assoc",
    "wof:placetype":"venue"
},
  "geometry": {"coordinates":[-71.592405,41.40766],"type":"Point"}
}