{
  "type": "Feature",
  "properties": {
    "iso:country":"US",
    "sg:address":"179 Front St",
    "sg:city":"Lincoln",
    "sg:classifiers":[
        {
            "category":"Home & Garden",
            "subcategory":"Building Materials",
            "type":"Retail Goods"
        },
        {
            "category":"Home & Garden",
            "subcategory":"Carpets & Floor Coverings",
            "type":"Retail Goods"
        }
    ],
    "sg:phone":"+1 401 723 3038",
    "sg:postcode":"02865",
    "sg:province":"RI",
    "sg:tags":[
        "wallpaper",
        "rug",
        "carpeting"
    ],
    "wof:name":"Bessette W R Co Inc",
    "wof:placetype":"venue"
},
  "geometry": {"coordinates":[-71.40830200000001,41.904598],"type":"Point"}
}