{
  "type": "Feature",
  "properties": {
    "iso:country":"US",
    "sg:address":"14 Industrial Dr",
    "sg:city":"Westerly",
    "sg:classifiers":[
        {
            "category":"Shopping",
            "subcategory":"Computers & Home Electronics",
            "type":"Retail Goods"
        }
    ],
    "sg:phone":"+1 401 596 0166",
    "sg:postcode":"02891",
    "sg:province":"RI",
    "sg:tags":[
        "television",
        "appliance"
    ],
    "wof:name":"Major Brands Outlet",
    "wof:placetype":"venue"
},
  "geometry": {"coordinates":[-71.830365,41.383972],"type":"Point"}
}