{
  "type": "Feature",
  "properties": {
    "addr:full":"685 East Ave Warwick RI 02886",
    "addr:housenumber":"685",
    "addr:postcode":"02886",
    "addr:street":"East Ave",
    "iso:country":"US",
    "sg:address":"685 East Ave",
    "sg:city":"Warwick",
    "sg:classifiers":[
        {
            "category":"Personal",
            "subcategory":"Barber",
            "type":"Services"
        }
    ],
    "sg:phone":"+1 401 823 0060",
    "sg:postcode":"02886",
    "sg:province":"RI",
    "wof:name":"Gq Barber Salon",
    "wof:placetype":"venue"
},
  "geometry": {"coordinates":[-71.486557,41.719842],"type":"Point"}
}