{
  "type": "Feature",
  "properties": {
    "iso:country":"US",
    "sg:address":"57 Minerva St",
    "sg:city":"Woonsocket",
    "sg:classifiers":[
        {
            "category":"Building & Trades",
            "subcategory":"Construction",
            "type":"Services"
        }
    ],
    "sg:phone":"+1 401 766 4993",
    "sg:postcode":"02895",
    "sg:province":"RI",
    "sg:tags":[
        "floor",
        "laying",
        "contractor"
    ],
    "wof:name":"Flooring Unlimited Ltd",
    "wof:placetype":"venue"
},
  "geometry": {"coordinates":[-71.51802000000001,41.989509],"type":"Point"}
}