{
  "type": "Feature",
  "properties": {
    "iso:country":"US",
    "sg:address":"37 Sandy Bottom Rd",
    "sg:city":"Coventry",
    "sg:classifiers":[
        {
            "category":"Personal",
            "subcategory":"Beauty Salon",
            "type":"Services"
        }
    ],
    "sg:phone":"+1 401 223 3597",
    "sg:postcode":"02816",
    "sg:province":"RI",
    "sg:tags":[
        "manicuring"
    ],
    "wof:name":"Air Nails",
    "wof:placetype":"venue"
},
  "geometry": {"coordinates":[-71.560686,41.688989],"type":"Point"}
}