{
  "type": "Feature",
  "properties": {
    "addr:full":"16 Industrial Dr Westerly RI 02891",
    "addr:housenumber":"16",
    "addr:postcode":"02891",
    "addr:street":"Industrial Dr",
    "iso:country":"US",
    "sg:address":"16 Industrial Dr",
    "sg:city":"Westerly",
    "sg:classifiers":[
        {
            "category":"Retail",
            "subcategory":"Auto Repair",
            "type":"Services"
        }
    ],
    "sg:phone":"+1 401 348 2886",
    "sg:postcode":"02891",
    "sg:province":"RI",
    "sg:tags":[
        "repairing",
        "automobile"
    ],
    "wof:name":"J Fish Auto Svc LLC",
    "wof:placetype":"venue"
},
  "geometry": {"coordinates":[-71.830359,41.3839],"type":"Point"}
}