{
  "type": "Feature",
  "properties": {
    "iso:country":"US",
    "sg:address":"51 Wisteria Dr",
    "sg:city":"Coventry",
    "sg:classifiers":[
        {
            "category":"Wholesale",
            "subcategory":"Machinery & Supplies",
            "type":"Manufacturing & Wholesale Goods"
        }
    ],
    "sg:phone":"+1 401 821 8532",
    "sg:postcode":"02816",
    "sg:province":"RI",
    "sg:tags":[
        "equipment",
        "industrial"
    ],
    "wof:name":"Menzel Inc",
    "wof:placetype":"venue"
},
  "geometry": {"coordinates":[-71.597793,41.676455],"type":"Point"}
}