{
  "type": "Feature",
  "properties": {
    "addr:full":"300 Niantic Ave Providence RI 02907",
    "addr:housenumber":"300",
    "addr:postcode":"02907",
    "addr:street":"Niantic Ave",
    "iso:country":"US",
    "sg:address":"300 Niantic Ave",
    "sg:city":"Providence",
    "sg:classifiers":[
        {
            "category":"Manufacturing",
            "subcategory":"Metals",
            "type":"Manufacturing & Wholesale Goods"
        }
    ],
    "sg:phone":"+1 401 943 1400",
    "sg:postcode":"02907",
    "sg:province":"RI",
    "sg:tags":[
        "gd",
        "mfg",
        "personal",
        "leather",
        "paper",
        "fab"
    ],
    "wof:name":"Jewel Case Corporation",
    "wof:placetype":"venue"
},
  "geometry": {"coordinates":[-71.438597,41.794898],"type":"Point"}
}