{
  "type": "Feature",
  "properties": {
    "addr:full":"27 Jefferson Park Rd Warwick RI 02888",
    "addr:housenumber":"27",
    "addr:postcode":"02888",
    "addr:street":"Jefferson Park Rd",
    "iso:country":"US",
    "sg:address":"27 Jefferson Park Rd",
    "sg:city":"Warwick",
    "sg:classifiers":[
        {
            "category":"Bakery",
            "type":"Food & Drink"
        },
        {
            "category":"Coffee & Tea",
            "type":"Food & Drink"
        },
        {
            "category":"Bagels",
            "type":"Food & Drink"
        },
        {
            "category":"Donuts",
            "type":"Food & Drink"
        }
    ],
    "sg:menulink":"http://www.allmenus.com/ri/warwick/138916-dunkin-donuts/menu/",
    "sg:phone":"+1 401 941 0310",
    "sg:postcode":"02888",
    "sg:province":"RI",
    "sg:tags":[
        "american",
        "pastry"
    ],
    "wof:name":"Dunkin' Donuts",
    "wof:placetype":"venue"
},
  "geometry": {"coordinates":[-71.43377599999999,41.75458],"type":"Point"}
}