{
  "type": "Feature",
  "properties": {
    "iso:country":"US",
    "sg:address":"258 Kenyon Ave",
    "sg:city":"Pawtucket",
    "sg:classifiers":[
        {
            "category":"Professional",
            "type":"Services"
        }
    ],
    "sg:phone":"+1 401 335 3888",
    "sg:postcode":"02861",
    "sg:province":"RI",
    "sg:tags":[
        "caterer"
    ],
    "wof:name":"Cabral's Catering Inc",
    "wof:placetype":"venue"
},
  "geometry": {"coordinates":[-71.364144,41.892983],"type":"Point"}
}