{
  "type": "Feature",
  "properties": {
    "iso:country":"US",
    "sg:address":"236 Benefit St",
    "sg:city":"Providence",
    "sg:classifiers":[
        {
            "category":"Education",
            "subcategory":"Library",
            "type":"Public Place"
        }
    ],
    "sg:phone":"+1 401 454 6365",
    "sg:postcode":"02903",
    "sg:province":"RI",
    "sg:website":"www.risdboston.org",
    "wof:name":"Rhode Island Schl-Design Libr",
    "wof:placetype":"venue"
},
  "geometry": {"coordinates":[-71.40733299999999,41.827002],"type":"Point"}
}