{
  "type": "Feature",
  "properties": {
    "iso:country":"US",
    "sg:address":"30 Quaker Ln",
    "sg:city":"Warwick",
    "sg:classifiers":[
        {
            "category":"Government",
            "subcategory":"Office",
            "type":"Public Place"
        }
    ],
    "sg:phone":"+1 401 822 1463",
    "sg:postcode":"02886",
    "sg:province":"RI",
    "sg:tags":[
        "federal",
        "human"
    ],
    "wof:name":"US Social Security Admin",
    "wof:placetype":"venue"
},
  "geometry": {"coordinates":[-71.501526,41.695778],"type":"Point"}
}