{
  "type": "Feature",
  "properties": {
    "iso:country":"US",
    "sg:address":"58 Main St",
    "sg:city":"Ashaway",
    "sg:classifiers":[
        {
            "category":"Building & Trades",
            "subcategory":"Construction",
            "type":"Services"
        }
    ],
    "sg:phone":"+1 401 377 2115",
    "sg:postcode":"02804",
    "sg:province":"RI",
    "sg:tags":[
        "house"
    ],
    "wof:name":"Peloquin Builders Inc",
    "wof:placetype":"venue"
},
  "geometry": {"coordinates":[-71.799469,41.399973],"type":"Point"}
}