{
  "type": "Feature",
  "properties": {
    "iso:country":"US",
    "sg:address":"20 Dovetail Ln",
    "sg:city":"Wakefield",
    "sg:classifiers":[
        {
            "category":"Real Estate",
            "subcategory":"Architect",
            "type":"Services"
        }
    ],
    "sg:phone":"+1 401 782 4604",
    "sg:postcode":"02879",
    "sg:province":"RI",
    "wof:name":"Frank Karpowicz Architects Inc",
    "wof:placetype":"venue"
},
  "geometry": {"coordinates":[-71.53255299999999,41.464793],"type":"Point"}
}