{
  "type": "Feature",
  "properties": {
    "iso:country":"US",
    "sg:address":"220 Cranston St",
    "sg:city":"Providence",
    "sg:classifiers":[
        {
            "category":"Shopping",
            "subcategory":"Discount & Variety Stores",
            "type":"Retail Goods"
        }
    ],
    "sg:phone":"+1 401 331 0415",
    "sg:postcode":"02907",
    "sg:province":"RI",
    "wof:name":"Costa Trading Co",
    "wof:placetype":"venue"
},
  "geometry": {"coordinates":[-71.427483,41.81361],"type":"Point"}
}