{
  "type": "Feature",
  "properties": {
    "addr:full":"1512 Mendon Rd Cumberland RI 02864",
    "addr:housenumber":"1512",
    "addr:postcode":"02864",
    "addr:street":"Mendon Rd",
    "iso:country":"US",
    "sg:address":"1512 Mendon Rd",
    "sg:city":"Cumberland",
    "sg:classifiers":[
        {
            "category":"Health Services",
            "subcategory":"Clinic",
            "type":"Services"
        }
    ],
    "sg:phone":"+1 401 334 3090",
    "sg:postcode":"02864",
    "sg:province":"RI",
    "sg:tags":[
        "organization",
        "religious"
    ],
    "wof:name":"Town of Cumberland Ems",
    "wof:placetype":"venue"
},
  "geometry": {"coordinates":[-71.432776,41.939969],"type":"Point"}
}