{
  "type": "Feature",
  "properties": {
    "iso:country":"US",
    "sg:address":"85 Gooding Ave",
    "sg:city":"Bristol",
    "sg:classifiers":[
        {
            "category":"Building & Trades",
            "subcategory":"Construction",
            "type":"Services"
        }
    ],
    "sg:phone":"+1 401 254 0377",
    "sg:postcode":"02809",
    "sg:province":"RI",
    "sg:tags":[
        "general",
        "contractor"
    ],
    "wof:name":"Raynham Avenue Development",
    "wof:placetype":"venue"
},
  "geometry": {"coordinates":[-71.267955,41.693963],"type":"Point"}
}