{
  "type": "Feature",
  "properties": {
    "iso:country":"US",
    "sg:address":"107 Parkview Dr",
    "sg:city":"Pawtucket",
    "sg:classifiers":[
        {
            "category":"Building & Trades",
            "subcategory":"Construction",
            "type":"Services"
        }
    ],
    "sg:phone":"+1 401 722 7790",
    "sg:postcode":"02861",
    "sg:province":"RI",
    "sg:tags":[
        "paving",
        "contractor"
    ],
    "wof:name":"Hanley Paving Inc",
    "wof:placetype":"venue"
},
  "geometry": {"coordinates":[-71.34977600000001,41.864925],"type":"Point"}
}