{
  "type": "Feature",
  "properties": {
    "iso:country":"US",
    "sg:address":"749 Main St",
    "sg:city":"West Warwick",
    "sg:classifiers":[
        {
            "category":"Professional",
            "subcategory":"Computer Services",
            "type":"Services"
        }
    ],
    "sg:phone":"+1 401 822 3237",
    "sg:postcode":"02893",
    "sg:province":"RI",
    "sg:tags":[
        "consultant",
        "designer"
    ],
    "wof:name":"Systematic Information Control",
    "wof:placetype":"venue"
},
  "geometry": {"coordinates":[-71.532259,41.721283],"type":"Point"}
}