{
  "type": "Feature",
  "properties": {
    "addr:full":"75 Peck Ave Bristol RI 02809",
    "addr:housenumber":"75",
    "addr:postcode":"02809",
    "addr:street":"Peck Ave",
    "iso:country":"US",
    "sg:address":"75 Peck Ave",
    "sg:city":"Bristol",
    "sg:classifiers":[
        {
            "category":"Home & Garden",
            "subcategory":"Building Materials",
            "type":"Retail Goods"
        }
    ],
    "sg:phone":"+1 401 253 4090",
    "sg:postcode":"02809",
    "sg:province":"RI",
    "wof:name":"T McGinn & Son Inc",
    "wof:placetype":"venue"
},
  "geometry": {"coordinates":[-71.28527200000001,41.700765],"type":"Point"}
}