{
  "type": "Feature",
  "properties": {
    "iso:country":"US",
    "sg:address":"30 Martin St",
    "sg:city":"Cumberland",
    "sg:classifiers":[
        {
            "category":"Manufacturing",
            "subcategory":"Electronics",
            "type":"Manufacturing & Wholesale Goods"
        }
    ],
    "sg:phone":"+1 401 333 8580",
    "sg:postcode":"02864",
    "sg:province":"RI",
    "sg:tags":[
        "equipment",
        "electronic",
        "supply"
    ],
    "sg:website":"www.aoi-corp.com",
    "wof:name":"Alpha Omega Instruments Corp",
    "wof:placetype":"venue"
},
  "geometry": {"coordinates":[-71.42940900000001,41.927045],"type":"Point"}
}