{
  "type": "Feature",
  "properties": {
    "addr:full":"12 Stanley Ave Barrington RI 02806",
    "addr:housenumber":"12",
    "addr:postcode":"02806",
    "addr:street":"Stanley Ave",
    "iso:country":"US",
    "sg:address":"12 Stanley Ave",
    "sg:city":"Barrington",
    "sg:classifiers":[
        {
            "category":"Manufacturing",
            "subcategory":"Printing",
            "type":"Manufacturing & Wholesale Goods"
        }
    ],
    "sg:phone":"+1 401 245 5599",
    "sg:postcode":"02806",
    "sg:province":"RI",
    "sg:tags":[
        "typesetting"
    ],
    "wof:name":"Creative Approach Typesetting",
    "wof:placetype":"venue"
},
  "geometry": {"coordinates":[-71.292182,41.747314],"type":"Point"}
}