{
  "type": "Feature",
  "properties": {
    "iso:country":"US",
    "sg:address":"47 Indian Trl",
    "sg:city":"Coventry",
    "sg:classifiers":[
        {
            "category":"Building & Trades",
            "subcategory":"Construction",
            "type":"Services"
        }
    ],
    "sg:phone":"+1 401 397 9995",
    "sg:postcode":"02816",
    "sg:province":"RI",
    "sg:tags":[
        "contractor",
        "grading"
    ],
    "wof:name":"Jws Enterprises Inc",
    "wof:placetype":"venue"
},
  "geometry": {"coordinates":[-71.627808,41.706039],"type":"Point"}
}