{
  "type": "Feature",
  "properties": {
    "iso:country":"US",
    "sg:address":"321 High St",
    "sg:city":"Bristol",
    "sg:classifiers":[
        {
            "category":"Building & Trades",
            "subcategory":"Construction",
            "type":"Services"
        }
    ],
    "sg:phone":"+1 401 254 1602",
    "sg:postcode":"02809",
    "sg:province":"RI",
    "sg:tags":[
        "carpentry",
        "contractor"
    ],
    "wof:name":"Bc Woodworking",
    "wof:placetype":"venue"
},
  "geometry": {"coordinates":[-71.27475099999999,41.672823],"type":"Point"}
}