{
  "type": "Feature",
  "properties": {
    "iso:country":"US",
    "sg:address":"130 Gold Mine Rd",
    "sg:city":"Chepachet",
    "sg:classifiers":[
        {
            "category":"Professional",
            "type":"Services"
        }
    ],
    "sg:phone":"+1 401 567 0526",
    "sg:postcode":"02814",
    "sg:province":"RI",
    "sg:tags":[
        "educational"
    ],
    "wof:name":"Andrew Bostom",
    "wof:placetype":"venue"
},
  "geometry": {"coordinates":[-71.749172,41.883924],"type":"Point"}
}