{
  "type": "Feature",
  "properties": {
    "iso:country":"US",
    "sg:address":"62 Magnolia St",
    "sg:city":"Cranston",
    "sg:classifiers":[
        {
            "category":"Shopping",
            "subcategory":"Gifts & Souvenirs",
            "type":"Retail Goods"
        }
    ],
    "sg:phone":"+1 401 270 7624",
    "sg:postcode":"02910",
    "sg:province":"RI",
    "sg:tags":[
        "shop"
    ],
    "wof:name":"Unique Gifts",
    "wof:placetype":"venue"
},
  "geometry": {"coordinates":[-71.42877799999999,41.7791],"type":"Point"}
}