{
  "type": "Feature",
  "properties": {
    "addr:full":"296 Chad Brown St Providence RI 02908",
    "addr:housenumber":"296",
    "addr:postcode":"02908",
    "addr:street":"Chad Brown St",
    "iso:country":"US",
    "sg:address":"296 Chad Brown St",
    "sg:city":"Providence",
    "sg:classifiers":[
        {
            "category":"Organizations",
            "subcategory":"Religious Organization",
            "type":"Services"
        }
    ],
    "sg:phone":"+1 401 351 0863",
    "sg:postcode":"02908",
    "sg:province":"RI",
    "sg:tags":[
        "church"
    ],
    "wof:name":"Trumpet-Faith Pentecostal",
    "wof:placetype":"venue"
},
  "geometry": {"coordinates":[-71.42167999999999,41.84197],"type":"Point"}
}