{
  "type": "Feature",
  "properties": {
    "iso:country":"US",
    "sg:address":"158 Old Plainfield Pike",
    "sg:city":"Foster",
    "sg:classifiers":[
        {
            "category":"Shopping",
            "subcategory":"Clothing, Apparel, & Fashions",
            "type":"Retail Goods"
        }
    ],
    "sg:phone":"+1 401 397 8694",
    "sg:postcode":"02825",
    "sg:province":"RI",
    "wof:name":"Sunset Novelties Net",
    "wof:placetype":"venue"
},
  "geometry": {"coordinates":[-71.690727,41.744934],"type":"Point"}
}