{
  "type": "Feature",
  "properties": {
    "iso:country":"US",
    "sg:address":"800 Boston Neck Rd",
    "sg:city":"North Kingstown",
    "sg:classifiers":[
        {
            "category":"Travel",
            "subcategory":"Hotels & Motels",
            "type":"Entertainment"
        }
    ],
    "sg:phone":"+1 401 294 6168",
    "sg:postcode":"02852",
    "sg:province":"RI",
    "sg:tags":[
        "operation"
    ],
    "wof:name":"Crosswinds Little Farm B&B",
    "wof:placetype":"venue"
},
  "geometry": {"coordinates":[-71.440872,41.550819],"type":"Point"}
}