{
  "type": "Feature",
  "properties": {
    "iso:country":"US",
    "sg:address":"253 Arlington Ave",
    "sg:city":"Warwick",
    "sg:classifiers":[
        {
            "category":"Professional",
            "subcategory":"Secretarial Services",
            "type":"Services"
        }
    ],
    "sg:phone":"+1 401 738 4448",
    "sg:postcode":"02889",
    "sg:province":"RI",
    "sg:tags":[
        "court",
        "reporter"
    ],
    "wof:name":"Donna Allen",
    "wof:placetype":"venue"
},
  "geometry": {"coordinates":[-71.37481200000001,41.700835],"type":"Point"}
}