{
  "type": "Feature",
  "properties": {
    "addr:full":"617 Hartford Ave Providence RI 02909",
    "addr:housenumber":"617",
    "addr:postcode":"02909",
    "addr:street":"Hartford Ave",
    "iso:country":"US",
    "sg:address":"617 Hartford Ave",
    "sg:city":"Providence",
    "sg:classifiers":[
        {
            "category":"Real Estate",
            "subcategory":"Real Estate Agent",
            "type":"Services"
        }
    ],
    "sg:phone":"+1 401 521 3399",
    "sg:postcode":"02909",
    "sg:province":"RI",
    "wof:name":"Voyage Realty Group Inc",
    "wof:placetype":"venue"
},
  "geometry": {"coordinates":[-71.465523,41.819615],"type":"Point"}
}