{
  "type": "Feature",
  "properties": {
    "iso:country":"US",
    "sg:address":"171 Danielson Pike",
    "sg:city":"North Scituate",
    "sg:classifiers":[
        {
            "category":"Shopping",
            "subcategory":"Florist",
            "type":"Retail Goods"
        }
    ],
    "sg:phone":"+1 401 647 3335",
    "sg:postcode":"02857",
    "sg:province":"RI",
    "wof:name":"Magnolia's & Memories",
    "wof:placetype":"venue"
},
  "geometry": {"coordinates":[-71.590271,41.832527],"type":"Point"}
}