{
  "type": "Feature",
  "properties": {
    "iso:country":"US",
    "sg:address":"345 Blackstone Blvd Ste 1",
    "sg:city":"Providence",
    "sg:classifiers":[
        {
            "category":"Health Services",
            "subcategory":"Doctor",
            "type":"Services"
        }
    ],
    "sg:phone":"+1 401 524 3076",
    "sg:postcode":"02906",
    "sg:province":"RI",
    "sg:tags":[
        "psychiatrist"
    ],
    "wof:name":"American Academy of Addiction and Psychiatry",
    "wof:placetype":"venue"
},
  "geometry": {"coordinates":[-71.38659699999999,41.846281],"type":"Point"}
}