{
  "type": "Feature",
  "properties": {
    "addr:full":"1301 Bald Hill Rd Warwick RI 02886",
    "addr:housenumber":"1301",
    "addr:postcode":"02886",
    "addr:street":"Bald Hill Rd",
    "iso:country":"US",
    "sg:address":"1301 Bald Hill Rd",
    "sg:city":"Warwick",
    "sg:classifiers":[
        {
            "category":"Manufacturing",
            "subcategory":"Printing",
            "type":"Manufacturing & Wholesale Goods"
        }
    ],
    "sg:phone":"+1 401 828 5749",
    "sg:postcode":"02886",
    "sg:province":"RI",
    "sg:tags":[
        "multimedia"
    ],
    "wof:name":"Media Systems",
    "wof:placetype":"venue"
},
  "geometry": {"coordinates":[-71.496948,41.698246],"type":"Point"}
}