{
  "type": "Feature",
  "properties": {
    "iso:country":"US",
    "sg:address":"89 Hopkins Hill Rd",
    "sg:city":"Coventry",
    "sg:classifiers":[
        {
            "category":"Manufacturing",
            "subcategory":"Textiles",
            "type":"Manufacturing & Wholesale Goods"
        }
    ],
    "sg:phone":"+1 401 392 1110",
    "sg:postcode":"02816",
    "sg:province":"RI",
    "wof:name":"Conneaut Industries Inc",
    "wof:placetype":"venue"
},
  "geometry": {"coordinates":[-71.567194,41.678336],"type":"Point"}
}