{
  "type": "Feature",
  "properties": {
    "addr:full":"19 Bayside Ave Newport RI 02840",
    "addr:housenumber":"19",
    "addr:postcode":"02840",
    "addr:street":"Bayside Ave",
    "iso:country":"US",
    "sg:address":"19 Bayside Ave",
    "sg:city":"Newport",
    "sg:classifiers":[
        {
            "category":"Organizations",
            "subcategory":"Community Association",
            "type":"Services"
        }
    ],
    "sg:phone":"+1 401 848 2945",
    "sg:postcode":"02840",
    "sg:province":"RI",
    "wof:name":"Friends of Van Zandt Pier Inc",
    "wof:placetype":"venue"
},
  "geometry": {"coordinates":[-71.321243,41.499392],"type":"Point"}
}