{
  "type": "Feature",
  "properties": {
    "addr:full":"36 Hood Ave Rumford RI 02916",
    "addr:housenumber":"36",
    "addr:postcode":"02916",
    "addr:street":"Hood Ave",
    "iso:country":"US",
    "sg:address":"36 Hood Ave",
    "sg:city":"Rumford",
    "sg:classifiers":[
        {
            "category":"Professional",
            "subcategory":"Business Services",
            "type":"Services"
        }
    ],
    "sg:phone":"+1 401 438 5240",
    "sg:postcode":"02916",
    "sg:province":"RI",
    "wof:name":"East Providence Hockey Blues",
    "wof:placetype":"venue"
},
  "geometry": {"coordinates":[-71.34627399999999,41.834499],"type":"Point"}
}