{
  "type": "Feature",
  "properties": {
    "addr:full":"8 Mendon Ave Pawtucket RI 02861",
    "addr:housenumber":"8",
    "addr:postcode":"02861",
    "addr:street":"Mendon Ave",
    "iso:country":"US",
    "sg:address":"8 Mendon Ave",
    "sg:city":"Pawtucket",
    "sg:classifiers":[
        {
            "category":"Personal",
            "subcategory":"Barber",
            "type":"Services"
        }
    ],
    "sg:phone":"+1 401 722 9710",
    "sg:postcode":"02861",
    "sg:province":"RI",
    "sg:website":"www.supercuts.com",
    "wof:name":"Supercuts",
    "wof:placetype":"venue"
},
  "geometry": {"coordinates":[-71.36438699999999,41.880928],"type":"Point"}
}