{
  "type": "Feature",
  "properties": {
    "addr:full":"2014 Mendon Rd Cumberland RI 02864",
    "addr:housenumber":"2014",
    "addr:postcode":"02864",
    "addr:street":"Mendon Rd",
    "iso:country":"US",
    "sg:address":"2014 Mendon Rd",
    "sg:city":"Cumberland",
    "sg:classifiers":[
        {
            "category":"Personal",
            "subcategory":"Tanning Parlor",
            "type":"Services"
        }
    ],
    "sg:phone":"+1 401 334 3330",
    "sg:postcode":"02864",
    "sg:province":"RI",
    "wof:name":"Ultimate Bronze & Body Salon Inc the",
    "wof:placetype":"venue"
},
  "geometry": {"coordinates":[-71.403702,41.945999],"type":"Point"}
}