{
  "type": "Feature",
  "properties": {
    "iso:country":"US",
    "sg:address":"176 Union Ave",
    "sg:city":"Providence",
    "sg:classifiers":[
        {
            "category":"Wholesale",
            "subcategory":"Hardware",
            "type":"Manufacturing & Wholesale Goods"
        }
    ],
    "sg:phone":"+1 401 944 0200",
    "sg:postcode":"02909",
    "sg:province":"RI",
    "sg:tags":[
        "equipment",
        "heating",
        "system"
    ],
    "wof:name":"Bell/Simon Co-Sydney Supply",
    "wof:placetype":"venue"
},
  "geometry": {"coordinates":[-71.44234,41.808126],"type":"Point"}
}