{
  "type": "Feature",
  "properties": {
    "iso:country":"US",
    "sg:address":"774 Metacom Ave",
    "sg:city":"Bristol",
    "sg:classifiers":[
        {
            "category":"Building & Trades",
            "subcategory":"Construction",
            "type":"Services"
        }
    ],
    "sg:phone":"+1 401 253 2435",
    "sg:postcode":"02809",
    "sg:province":"RI",
    "sg:tags":[
        "house"
    ],
    "wof:name":"Oliveira Construction",
    "wof:placetype":"venue"
},
  "geometry": {"coordinates":[-71.267162,41.711677],"type":"Point"}
}