{
  "type": "Feature",
  "properties": {
    "iso:country":"US",
    "sg:address":"150 Morris Ave",
    "sg:city":"Providence",
    "sg:classifiers":[
        {
            "category":"Building & Trades",
            "subcategory":"Construction",
            "type":"Services"
        }
    ],
    "sg:phone":"+1 401 523 5356",
    "sg:postcode":"02906",
    "sg:province":"RI",
    "sg:tags":[
        "hanging",
        "contractor"
    ],
    "wof:name":"Double Dennco Inc",
    "wof:placetype":"venue"
},
  "geometry": {"coordinates":[-71.39798399999999,41.837576],"type":"Point"}
}