{
  "type": "Feature",
  "properties": {
    "iso:country":"US",
    "sg:address":"776 Greenville Ave",
    "sg:city":"Johnston",
    "sg:classifiers":[
        {
            "category":"Home & Garden",
            "subcategory":"Building Materials",
            "type":"Retail Goods"
        }
    ],
    "sg:phone":"+1 401 231 1585",
    "sg:postcode":"02919",
    "sg:province":"RI",
    "sg:tags":[
        "center"
    ],
    "wof:name":"East Coast Home & Garden",
    "wof:placetype":"venue"
},
  "geometry": {"coordinates":[-71.527973,41.858439],"type":"Point"}
}