{
  "type": "Feature",
  "properties": {
    "iso:country":"US",
    "sg:address":"4259 Old Post Rd",
    "sg:city":"Charlestown",
    "sg:classifiers":[
        {
            "category":"Retail",
            "subcategory":"Veterinary Services",
            "type":"Services"
        }
    ],
    "sg:phone":"+1 401 364 6630",
    "sg:postcode":"02813",
    "sg:province":"RI",
    "sg:tags":[
        "veterinarian"
    ],
    "wof:name":"Johnson Lewis E",
    "wof:placetype":"venue"
},
  "geometry": {"coordinates":[-71.63446500000001,41.382475],"type":"Point"}
}