{
  "type": "Feature",
  "properties": {
    "addr:full":"2175 Broad St Providence RI 02905",
    "addr:housenumber":"2175",
    "addr:postcode":"02905",
    "addr:street":"Broad St",
    "iso:country":"US",
    "sg:address":"2175 Broad St",
    "sg:city":"Providence",
    "sg:classifiers":[
        {
            "category":"Autos & Motor Vehicles",
            "subcategory":"Fuel & Gas Station",
            "type":"Retail Goods"
        }
    ],
    "sg:phone":"+1 401 467 9210",
    "sg:postcode":"02905",
    "sg:province":"RI",
    "sg:tags":[
        "station",
        "gasoline"
    ],
    "wof:name":"P J Grogan",
    "wof:placetype":"venue"
},
  "geometry": {"coordinates":[-71.390896,41.765588],"type":"Point"}
}