{
  "type": "Feature",
  "properties": {
    "iso:country":"US",
    "sg:address":"787 Charles St",
    "sg:city":"Providence",
    "sg:classifiers":[
        {
            "category":"Food & Beverages",
            "subcategory":"Groceries & Convenience Stores",
            "type":"Retail Goods"
        }
    ],
    "sg:phone":"+1 401 521 7378",
    "sg:postcode":"02904",
    "sg:province":"RI",
    "sg:tags":[
        "market"
    ],
    "wof:name":"Graziano Sausage",
    "wof:placetype":"venue"
},
  "geometry": {"coordinates":[-71.42150100000001,41.857899],"type":"Point"}
}