{
  "type": "Feature",
  "properties": {
    "iso:country":"US",
    "sg:address":"2323 Warwick Ave",
    "sg:city":"Warwick",
    "sg:classifiers":[
        {
            "category":"Shopping",
            "subcategory":"Jewelry",
            "type":"Retail Goods"
        }
    ],
    "sg:phone":"+1 401 732 3453",
    "sg:postcode":"02889",
    "sg:province":"RI",
    "sg:tags":[
        "jeweler"
    ],
    "wof:name":"Stencel Jewelers",
    "wof:placetype":"venue"
},
  "geometry": {"coordinates":[-71.399344,41.714273],"type":"Point"}
}