{
  "type": "Feature",
  "properties": {
    "addr:full":"220 Weybosset St Providence RI 02903",
    "addr:housenumber":"220",
    "addr:postcode":"02903",
    "addr:street":"Weybosset St",
    "iso:country":"US",
    "sg:address":"220 Weybosset St",
    "sg:city":"Providence",
    "sg:classifiers":[
        {
            "category":"Restaurant",
            "type":"Food & Drink"
        }
    ],
    "sg:phone":"+1 401 331 5100",
    "sg:postcode":"02903",
    "sg:province":"RI",
    "wof:name":"Intermezzo Bistro",
    "wof:placetype":"venue"
},
  "geometry": {"coordinates":[-71.412459,41.821382],"type":"Point"}
}