{
  "type": "Feature",
  "properties": {
    "iso:country":"US",
    "sg:address":"1 Veazie St",
    "sg:city":"Johnston",
    "sg:classifiers":[
        {
            "category":"Restaurant",
            "type":"Food & Drink"
        }
    ],
    "sg:phone":"+1 401 944 4530",
    "sg:postcode":"02908",
    "sg:province":"RI",
    "sg:tags":[
        "eating"
    ],
    "wof:name":"George Restaurant",
    "wof:placetype":"venue"
},
  "geometry": {"coordinates":[-71.430931,41.847111],"type":"Point"}
}