{
  "type": "Feature",
  "properties": {
    "addr:full":"840 Tiogue Ave Coventry RI 02816",
    "addr:housenumber":"840",
    "addr:postcode":"02816",
    "addr:street":"Tiogue Ave",
    "iso:country":"US",
    "sg:address":"840 Tiogue Ave",
    "sg:city":"Coventry",
    "sg:classifiers":[
        {
            "category":"Sports & Exercise",
            "subcategory":"Gym",
            "type":"Entertainment"
        }
    ],
    "sg:phone":"+1 401 586 6333",
    "sg:postcode":"02816",
    "sg:province":"RI",
    "sg:tags":[
        "club",
        "health",
        "studio",
        "gymnasium"
    ],
    "wof:name":"Curves For Women",
    "wof:placetype":"venue"
},
  "geometry": {"coordinates":[-71.56822099999999,41.680766],"type":"Point"}
}