{
  "type": "Feature",
  "properties": {
    "iso:country":"US",
    "sg:address":"638 Charles St",
    "sg:city":"Providence",
    "sg:classifiers":[
        {
            "category":"Food & Beverages",
            "subcategory":"Groceries & Convenience Stores",
            "type":"Retail Goods"
        }
    ],
    "sg:phone":"+1 401 751 1180",
    "sg:postcode":"02904",
    "sg:province":"RI",
    "wof:name":"Foodland Farm",
    "wof:placetype":"venue"
},
  "geometry": {"coordinates":[-71.420502,41.854401],"type":"Point"}
}