{
  "type": "Feature",
  "properties": {
    "addr:full":"9 Franklin Rd East Greenwich RI 02818",
    "addr:housenumber":"9",
    "addr:postcode":"02818",
    "addr:street":"Franklin Rd",
    "iso:country":"US",
    "sg:address":"9 Franklin Rd",
    "sg:city":"East Greenwich",
    "sg:classifiers":[
        {
            "category":"Retail",
            "subcategory":"Repair Shop",
            "type":"Services"
        }
    ],
    "sg:phone":"+1 401 737 2323",
    "sg:postcode":"02818",
    "sg:province":"RI",
    "sg:tags":[
        "lock",
        "locksmith"
    ],
    "wof:name":"Lock Shop",
    "wof:placetype":"venue"
},
  "geometry": {"coordinates":[-71.468242,41.635481],"type":"Point"}
}