{
  "type": "Feature",
  "properties": {
    "iso:country":"US",
    "sg:address":"101 Pleasant St",
    "sg:city":"North Kingstown",
    "sg:classifiers":[
        {
            "category":"Professional",
            "type":"Services"
        }
    ],
    "sg:phone":"+1 401 884 3424",
    "sg:postcode":"02852",
    "sg:province":"RI",
    "wof:name":"Vivian Eisner Hess Co Inc",
    "wof:placetype":"venue"
},
  "geometry": {"coordinates":[-71.447422,41.574487],"type":"Point"}
}