{
  "type": "Feature",
  "properties": {
    "iso:country":"US",
    "sg:address":"180 Sayles Ave",
    "sg:city":"Pascoag",
    "sg:classifiers":[
        {
            "category":"Education",
            "subcategory":"School",
            "type":"Public Place"
        }
    ],
    "sg:phone":"+1 401 568 4589",
    "sg:postcode":"02859",
    "sg:province":"RI",
    "sg:tags":[
        "religious"
    ],
    "wof:name":"Father Holland School",
    "wof:placetype":"venue"
},
  "geometry": {"coordinates":[-71.704391,41.96049],"type":"Point"}
}