{
  "type": "Feature",
  "properties": {
    "addr:full":"200 Sargent St Warwick RI 02888",
    "addr:housenumber":"200",
    "addr:postcode":"02888",
    "addr:street":"Sargent St",
    "iso:country":"US",
    "sg:address":"200 Sargent St",
    "sg:city":"Warwick",
    "sg:classifiers":[
        {
            "category":"Professional",
            "subcategory":"Art Services",
            "type":"Services"
        }
    ],
    "sg:phone":"+1 401 461 1435",
    "sg:postcode":"02888",
    "sg:province":"RI",
    "sg:tags":[
        "photographer"
    ],
    "wof:name":"Marty Doyle Photography",
    "wof:placetype":"venue"
},
  "geometry": {"coordinates":[-71.43527,41.749451],"type":"Point"}
}