{
  "type": "Feature",
  "properties": {
    "iso:country":"US",
    "sg:address":"44 Dunedin St",
    "sg:city":"Cranston",
    "sg:classifiers":[
        {
            "category":"Utilities",
            "subcategory":"Mobile Phone",
            "type":"Services"
        }
    ],
    "sg:phone":"+1 401 946 7346",
    "sg:postcode":"02920",
    "sg:province":"RI",
    "sg:tags":[
        "communication",
        "radiotelephone"
    ],
    "wof:name":"Novos Corner Store",
    "wof:placetype":"venue"
},
  "geometry": {"coordinates":[-71.451764,41.802161],"type":"Point"}
}