{
  "type": "Feature",
  "properties": {
    "iso:country":"US",
    "sg:address":"50 Sims Ave",
    "sg:city":"Providence",
    "sg:classifiers":[
        {
            "category":"Building & Trades",
            "subcategory":"Construction",
            "type":"Services"
        }
    ],
    "sg:phone":"+1 401 383 3490",
    "sg:postcode":"02909",
    "sg:province":"RI",
    "sg:tags":[
        "fabricator",
        "metal"
    ],
    "wof:name":"Oster Pewter",
    "wof:placetype":"venue"
},
  "geometry": {"coordinates":[-71.433516,41.826663],"type":"Point"}
}