{
  "type": "Feature",
  "properties": {
    "iso:country":"US",
    "sg:address":"55 Beach St",
    "sg:city":"Westerly",
    "sg:classifiers":[
        {
            "category":"Restaurant",
            "type":"Food & Drink"
        }
    ],
    "sg:phone":"+1 401 596 5709",
    "sg:postcode":"02891",
    "sg:province":"RI",
    "wof:name":"Rafters",
    "wof:placetype":"venue"
},
  "geometry": {"coordinates":[-71.829882,41.364994],"type":"Point"}
}