{
  "type": "Feature",
  "properties": {
    "addr:full":"1 Hilton St Providence RI 02905",
    "addr:housenumber":"1",
    "addr:postcode":"02905",
    "addr:street":"Hilton St",
    "iso:country":"US",
    "sg:address":"1 Hilton St",
    "sg:city":"Providence",
    "sg:classifiers":[
        {
            "category":"Government",
            "subcategory":"Office",
            "type":"Public Place"
        }
    ],
    "sg:phone":"+1 401 455 6028",
    "sg:postcode":"02905",
    "sg:province":"RI",
    "sg:tags":[
        "government-united",
        "program",
        "administrative",
        "state",
        "educational"
    ],
    "sg:website":"http://www.ridoe.com",
    "wof:name":"Educational Opportunity Ctr",
    "wof:placetype":"venue"
},
  "geometry": {"coordinates":[-71.41368900000001,41.807301],"type":"Point"}
}