{
  "type": "Feature",
  "properties": {
    "iso:country":"US",
    "sg:address":"5 Marin St",
    "sg:city":"Newport",
    "sg:classifiers":[
        {
            "category":"Autos & Motor Vehicles",
            "subcategory":"Boat Sales",
            "type":"Retail Goods"
        }
    ],
    "sg:phone":"+1 401 848 5500",
    "sg:postcode":"02840",
    "sg:province":"RI",
    "sg:tags":[
        "yacht",
        "broker"
    ],
    "sg:website":"www.nandj.com",
    "wof:name":"Northrop & Johnson Inc",
    "wof:placetype":"venue"
},
  "geometry": {"coordinates":[-71.30888400000001,41.490716],"type":"Point"}
}