{
  "type": "Feature",
  "properties": {
    "addr:full":"310 Atwells Ave Providence RI 02903",
    "addr:housenumber":"310",
    "addr:postcode":"02903",
    "addr:street":"Atwells Ave",
    "iso:country":"US",
    "sg:address":"310 Atwells Ave",
    "sg:city":"Providence",
    "sg:classifiers":[
        {
            "category":"Restaurant",
            "type":"Food & Drink"
        }
    ],
    "sg:phone":"+1 401 919 5700",
    "sg:postcode":"02903",
    "sg:province":"RI",
    "sg:tags":[
        "italian"
    ],
    "wof:name":"Trattoria Difiori",
    "wof:placetype":"venue"
},
  "geometry": {"coordinates":[-71.428229,41.823563],"type":"Point"}
}