{
  "type": "Feature",
  "properties": {
    "iso:country":"US",
    "sg:address":"2719 E Main Rd",
    "sg:city":"Portsmouth",
    "sg:classifiers":[
        {
            "category":"Insurance",
            "subcategory":"Insurance Agent",
            "type":"Services"
        }
    ],
    "sg:phone":"+1 401 683 9100",
    "sg:postcode":"02871",
    "sg:province":"RI",
    "wof:name":"Trend Insurance Inc",
    "wof:placetype":"venue"
},
  "geometry": {"coordinates":[-71.247985,41.602153],"type":"Point"}
}