{
  "type": "Feature",
  "properties": {
    "addr:full":"485 Prospect St Pawtucket RI 02860",
    "addr:housenumber":"485",
    "addr:postcode":"02860",
    "addr:street":"Prospect St",
    "iso:country":"US",
    "sg:address":"485 Prospect St",
    "sg:city":"Pawtucket",
    "sg:classifiers":[
        {
            "category":"Freight",
            "type":"Transportation"
        }
    ],
    "sg:phone":"+1 401 723 2162",
    "sg:postcode":"02860",
    "sg:province":"RI",
    "wof:name":"Kellaway Transportation",
    "wof:placetype":"venue"
},
  "geometry": {"coordinates":[-71.372184,41.864252],"type":"Point"}
}