{
  "type": "Feature",
  "properties": {
    "addr:full":"622 Killingly St Ste A Johnston RI 02919",
    "addr:housenumber":"622",
    "addr:postcode":"02919",
    "addr:street":"Killingly St Ste A",
    "iso:country":"US",
    "sg:address":"622 Killingly St Ste A",
    "sg:city":"Johnston",
    "sg:classifiers":[
        {
            "category":"Personal",
            "subcategory":"Day Spa",
            "type":"Services"
        }
    ],
    "sg:phone":"+1 401 861 5548",
    "sg:postcode":"02919",
    "sg:province":"RI",
    "wof:name":"Kim's Nails",
    "wof:placetype":"venue"
},
  "geometry": {"coordinates":[-71.47287900000001,41.828679],"type":"Point"}
}