{
  "type": "Feature",
  "properties": {
    "addr:full":"2975 W Shore Rd Warwick RI 02886",
    "addr:housenumber":"2975",
    "addr:postcode":"02886",
    "addr:street":"W Shore Rd",
    "iso:country":"US",
    "sg:address":"2975 W Shore Rd",
    "sg:city":"Warwick",
    "sg:classifiers":[
        {
            "category":"Banks & Credit Unions",
            "subcategory":"Bank",
            "type":"Services"
        }
    ],
    "sg:phone":"+1 401 732 4045",
    "sg:postcode":"02886",
    "sg:province":"RI",
    "sg:tags":[
        "state",
        "commercial"
    ],
    "sg:website":"www.bankri.com",
    "wof:name":"Bank Rhode Island",
    "wof:placetype":"venue"
},
  "geometry": {"coordinates":[-71.429591,41.702343],"type":"Point"}
}