{
  "type": "Feature",
  "properties": {
    "iso:country":"US",
    "sg:address":"476 Central Ave",
    "sg:city":"Pawtucket",
    "sg:classifiers":[
        {
            "category":"Personal",
            "subcategory":"Beauty Salon",
            "type":"Services"
        }
    ],
    "sg:phone":"+1 401 724 8843",
    "sg:postcode":"02861",
    "sg:province":"RI",
    "wof:name":"Capri Salon",
    "wof:placetype":"venue"
},
  "geometry": {"coordinates":[-71.36344800000001,41.885767],"type":"Point"}
}