{
  "type": "Feature",
  "properties": {
    "iso:country":"US",
    "sg:address":"6 Brae St",
    "sg:city":"North Providence",
    "sg:classifiers":[
        {
            "category":"Building & Trades",
            "subcategory":"Construction",
            "type":"Services"
        }
    ],
    "sg:phone":"+1 401 523 0883",
    "sg:postcode":"02911",
    "sg:province":"RI",
    "sg:tags":[
        "concrete",
        "contractor"
    ],
    "wof:name":"Diamond Concrete Construction",
    "wof:placetype":"venue"
},
  "geometry": {"coordinates":[-71.47434,41.850442],"type":"Point"}
}