{
  "type": "Feature",
  "properties": {
    "iso:country":"US",
    "sg:address":"30 Risho Ave",
    "sg:city":"East Providence",
    "sg:classifiers":[
        {
            "category":"Manufacturing",
            "subcategory":"Printing",
            "type":"Manufacturing & Wholesale Goods"
        }
    ],
    "sg:phone":"+1 401 435 4477",
    "sg:postcode":"02914",
    "sg:province":"RI",
    "wof:name":"B C T",
    "wof:placetype":"venue"
},
  "geometry": {"coordinates":[-71.344488,41.801077],"type":"Point"}
}