{
  "type": "Feature",
  "properties": {
    "addr:full":"895 Elmwood Ave Providence RI 02907",
    "addr:housenumber":"895",
    "addr:postcode":"02907",
    "addr:street":"Elmwood Ave",
    "iso:country":"US",
    "sg:address":"895 Elmwood Ave",
    "sg:city":"Providence",
    "sg:classifiers":[
        {
            "category":"Professional",
            "type":"Services"
        }
    ],
    "sg:phone":"+1 401 461 2548",
    "sg:postcode":"02907",
    "sg:province":"RI",
    "sg:tags":[
        "establishment"
    ],
    "wof:name":"Trucklease Corp",
    "wof:placetype":"venue"
},
  "geometry": {"coordinates":[-71.42088200000001,41.788273],"type":"Point"}
}