{
  "type": "Feature",
  "properties": {
    "iso:country":"US",
    "sg:address":"405 N Broadway",
    "sg:city":"Rumford",
    "sg:classifiers":[
        {
            "category":"Retail",
            "subcategory":"Auto Repair",
            "type":"Services"
        }
    ],
    "sg:phone":"+1 401 437 6566",
    "sg:postcode":"02916",
    "sg:province":"RI",
    "wof:name":"Vally Auto Service",
    "wof:placetype":"venue"
},
  "geometry": {"coordinates":[-71.361898,41.831301],"type":"Point"}
}