{
  "type": "Feature",
  "properties": {
    "addr:full":"15 Juniper St Barrington RI 02806",
    "addr:housenumber":"15",
    "addr:postcode":"02806",
    "addr:street":"Juniper St",
    "iso:country":"US",
    "sg:address":"15 Juniper St",
    "sg:city":"Barrington",
    "sg:classifiers":[
        {
            "category":"Recreation",
            "type":"Entertainment"
        }
    ],
    "sg:phone":"+1 401 247 9369",
    "sg:postcode":"02806",
    "sg:province":"RI",
    "wof:name":"Astrology Institute",
    "wof:placetype":"venue"
},
  "geometry": {"coordinates":[-71.31656,41.752771],"type":"Point"}
}