{
  "type": "Feature",
  "properties": {
    "addr:full":"1 2nd St East Providence RI 02914",
    "addr:housenumber":"1",
    "addr:postcode":"02914",
    "addr:street":"2Nd St",
    "iso:country":"US",
    "sg:address":"1 2nd St",
    "sg:city":"East Providence",
    "sg:classifiers":[
        {
            "category":"Professional",
            "subcategory":"Computer Services",
            "type":"Services"
        }
    ],
    "sg:phone":"+1 401 431 5233",
    "sg:postcode":"02914",
    "sg:province":"RI",
    "sg:tags":[
        "repair"
    ],
    "sg:website":"www.nelaserofne.com",
    "wof:name":"Northeast Laser Image",
    "wof:placetype":"venue"
},
  "geometry": {"coordinates":[-71.384468,41.814823],"type":"Point"}
}