{
  "type": "Feature",
  "properties": {
    "iso:country":"US",
    "sg:address":"3852 Main Rd",
    "sg:city":"Tiverton",
    "sg:classifiers":[
        {
            "category":"Professional",
            "type":"Services"
        }
    ],
    "sg:phone":"+1 401 624 2600",
    "sg:postcode":"02878",
    "sg:province":"RI",
    "wof:name":"Tiverton Four Cornrs Cntr Arts",
    "wof:placetype":"venue"
},
  "geometry": {"coordinates":[-71.189019,41.575032],"type":"Point"}
}