{
  "type": "Feature",
  "properties": {
    "addr:full":"164 Rockwood Ave Cranston RI 02920",
    "addr:housenumber":"164",
    "addr:postcode":"02920",
    "addr:street":"Rockwood Ave",
    "iso:country":"US",
    "sg:address":"164 Rockwood Ave",
    "sg:city":"Cranston",
    "sg:classifiers":[
        {
            "category":"Building & Trades",
            "subcategory":"Landscaping Services",
            "type":"Services"
        }
    ],
    "sg:phone":"+1 401 942 2576",
    "sg:postcode":"02920",
    "sg:province":"RI",
    "wof:name":"J De Marco Landscaping Inc",
    "wof:placetype":"venue"
},
  "geometry": {"coordinates":[-71.480797,41.790638],"type":"Point"}
}