{
  "type": "Feature",
  "properties": {
    "iso:country":"US",
    "sg:address":"38 Sanderson Rd",
    "sg:city":"Smithfield",
    "sg:classifiers":[
        {
            "category":"Retail",
            "subcategory":"Auto Repair",
            "type":"Services"
        }
    ],
    "sg:phone":"+1 401 949 4383",
    "sg:postcode":"02917",
    "sg:province":"RI",
    "sg:tags":[
        "body",
        "shop",
        "top",
        "paint"
    ],
    "wof:name":"Rt 5 Auto Repair",
    "wof:placetype":"venue"
},
  "geometry": {"coordinates":[-71.531441,41.864716],"type":"Point"}
}