{
  "type": "Feature",
  "properties": {
    "addr:full":"126 Mail Rd Exeter RI 02822",
    "addr:housenumber":"126",
    "addr:postcode":"02822",
    "addr:street":"Mail Rd",
    "iso:country":"US",
    "sg:address":"126 Mail Rd",
    "sg:city":"Exeter",
    "sg:classifiers":[
        {
            "category":"Building & Trades",
            "subcategory":"Construction",
            "type":"Services"
        }
    ],
    "sg:phone":"+1 401 294 3297",
    "sg:postcode":"02822",
    "sg:province":"RI",
    "sg:tags":[
        "contractor"
    ],
    "wof:name":"Taylor Fence",
    "wof:placetype":"venue"
},
  "geometry": {"coordinates":[-71.56373499999999,41.53712],"type":"Point"}
}