{
  "type": "Feature",
  "properties": {
    "iso:country":"US",
    "sg:address":"28 Columbia St",
    "sg:city":"Wakefield",
    "sg:classifiers":[
        {
            "category":"Retail",
            "subcategory":"Funeral Services",
            "type":"Services"
        }
    ],
    "sg:phone":"+1 401 789 6550",
    "sg:postcode":"02879",
    "sg:province":"RI",
    "sg:tags":[
        "director"
    ],
    "wof:name":"Forbes Funeral Home",
    "wof:placetype":"venue"
},
  "geometry": {"coordinates":[-71.49570799999999,41.441663],"type":"Point"}
}