{
  "type": "Feature",
  "properties": {
    "addr:full":"958 Manton Ave Providence RI 02909",
    "addr:housenumber":"958",
    "addr:postcode":"02909",
    "addr:street":"Manton Ave",
    "iso:country":"US",
    "sg:address":"958 Manton Ave",
    "sg:city":"Providence",
    "sg:classifiers":[
        {
            "category":"Wholesale",
            "subcategory":"Home Furnishings",
            "type":"Manufacturing & Wholesale Goods"
        }
    ],
    "sg:phone":"+1 401 831 8500",
    "sg:postcode":"02909",
    "sg:province":"RI",
    "sg:tags":[
        "floor",
        "covering"
    ],
    "wof:name":"New England Carpet Consultants",
    "wof:placetype":"venue"
},
  "geometry": {"coordinates":[-71.46894399999999,41.833532],"type":"Point"}
}