{
  "type": "Feature",
  "properties": {
    "iso:country":"US",
    "sg:address":"1372 Main St",
    "sg:city":"Coventry",
    "sg:classifiers":[
        {
            "category":"Recreation",
            "type":"Entertainment"
        }
    ],
    "sg:phone":"+1 401 827 5900",
    "sg:postcode":"02816",
    "sg:province":"RI",
    "sg:tags":[
        "lottery",
        "agent"
    ],
    "sg:website":"www.gtech.com",
    "wof:name":"Gtech Corp",
    "wof:placetype":"venue"
},
  "geometry": {"coordinates":[-71.57096900000001,41.691736],"type":"Point"}
}