{
  "type": "Feature",
  "properties": {
    "iso:country":"US",
    "sg:address":"1009 Waterman Ave",
    "sg:city":"East Providence",
    "sg:classifiers":[
        {
            "category":"Insurance",
            "subcategory":"Insurance Agent",
            "type":"Services"
        }
    ],
    "sg:phone":"+1 401 434 7222",
    "sg:postcode":"02914",
    "sg:province":"RI",
    "wof:name":"Anderton Insurance",
    "wof:placetype":"venue"
},
  "geometry": {"coordinates":[-71.341835,41.80902],"type":"Point"}
}