{
  "type": "Feature",
  "properties": {
    "addr:full":"450 Klondike Rd Charlestown RI 02813",
    "addr:housenumber":"450",
    "addr:postcode":"02813",
    "addr:street":"Klondike Rd",
    "iso:country":"US",
    "sg:address":"450 Klondike Rd",
    "sg:city":"Charlestown",
    "sg:classifiers":[
        {
            "category":"Building & Trades",
            "subcategory":"Construction",
            "type":"Services"
        }
    ],
    "sg:phone":"+1 401 322 1407",
    "sg:postcode":"02813",
    "sg:province":"RI",
    "sg:tags":[
        "hanging",
        "contractor"
    ],
    "wof:name":"Boyd Painting",
    "wof:placetype":"venue"
},
  "geometry": {"coordinates":[-71.72241,41.382651],"type":"Point"}
}