{
  "type": "Feature",
  "properties": {
    "iso:country":"US",
    "sg:address":"514 Main St",
    "sg:city":"Warren",
    "sg:classifiers":[
        {
            "category":"Government",
            "subcategory":"Office",
            "type":"Public Place"
        }
    ],
    "sg:phone":"+1 401 245 7360",
    "sg:postcode":"02885",
    "sg:province":"RI",
    "sg:tags":[
        "city",
        "planning",
        "dev"
    ],
    "wof:name":"Warren Community Development",
    "wof:placetype":"venue"
},
  "geometry": {"coordinates":[-71.28233299999999,41.729383],"type":"Point"}
}