{
  "type": "Feature",
  "properties": {
    "iso:country":"US",
    "sg:address":"242 Allens Ave",
    "sg:city":"Providence",
    "sg:classifiers":[
        {
            "category":"Recreation",
            "subcategory":"Marina",
            "type":"Entertainment"
        }
    ],
    "sg:phone":"+1 401 467 3730",
    "sg:postcode":"02905",
    "sg:province":"RI",
    "sg:tags":[
        "repair",
        "marine"
    ],
    "sg:website":"www.prometmarineservices.com",
    "wof:name":"Promet Marine Svc Corp",
    "wof:placetype":"venue"
},
  "geometry": {"coordinates":[-71.403137,41.806937],"type":"Point"}
}