{
  "type": "Feature",
  "properties": {
    "iso:country":"US",
    "sg:address":"3879 Main Rd",
    "sg:city":"Tiverton",
    "sg:classifiers":[
        {
            "category":"Home & Garden",
            "subcategory":"Home Furnishings",
            "type":"Retail Goods"
        }
    ],
    "sg:phone":"+1 401 625 1599",
    "sg:postcode":"02878",
    "sg:province":"RI",
    "sg:tags":[
        "pottery"
    ],
    "wof:name":"Stone Bridge Dishes",
    "wof:placetype":"venue"
},
  "geometry": {"coordinates":[-71.187968,41.571932],"type":"Point"}
}