{
  "type": "Feature",
  "properties": {
    "addr:full":"555 Broad St Central Falls RI 02863",
    "addr:housenumber":"555",
    "addr:postcode":"02863",
    "addr:street":"Broad St",
    "iso:country":"US",
    "sg:address":"555 Broad St",
    "sg:city":"Central Falls",
    "sg:classifiers":[
        {
            "category":"Shopping",
            "subcategory":"Computers & Home Electronics",
            "type":"Retail Goods"
        }
    ],
    "sg:phone":"+1 401 434 3377",
    "sg:postcode":"02863",
    "sg:province":"RI",
    "wof:name":"Media Depot",
    "wof:placetype":"venue"
},
  "geometry": {"coordinates":[-71.386976,41.887231],"type":"Point"}
}