{
  "type": "Feature",
  "properties": {
    "iso:country":"US",
    "sg:address":"980 Eddie Dowling Hwy",
    "sg:city":"North Smithfield",
    "sg:classifiers":[
        {
            "category":"Professional",
            "subcategory":"Lawyer & Legal Services",
            "type":"Services"
        }
    ],
    "sg:phone":"+1 401 769 9400",
    "sg:postcode":"02896",
    "sg:province":"RI",
    "wof:name":"Heroux Keith Atty",
    "wof:placetype":"venue"
},
  "geometry": {"coordinates":[-71.494598,41.961102],"type":"Point"}
}