{
  "type": "Feature",
  "properties": {
    "iso:country":"US",
    "sg:address":"2094 Diamond Hill Rd",
    "sg:city":"Cumberland",
    "sg:classifiers":[
        {
            "category":"Home & Garden",
            "subcategory":"Building Materials",
            "type":"Retail Goods"
        }
    ],
    "sg:phone":"+1 401 725 6096",
    "sg:postcode":"02864",
    "sg:province":"RI",
    "sg:tags":[
        "paint"
    ],
    "wof:name":"Hanna's Color Ctr",
    "wof:placetype":"venue"
},
  "geometry": {"coordinates":[-71.402733,41.943073],"type":"Point"}
}