{
  "type": "Feature",
  "properties": {
    "iso:country":"US",
    "sg:address":"55 Veil Ct",
    "sg:city":"North Kingstown",
    "sg:classifiers":[
        {
            "category":"Building & Trades",
            "subcategory":"Construction",
            "type":"Services"
        }
    ],
    "sg:phone":"+1 401 295 7721",
    "sg:postcode":"02852",
    "sg:province":"RI",
    "sg:tags":[
        "designer",
        "dealer",
        "pool",
        "swimming"
    ],
    "wof:name":"Signature Pool & Spas",
    "wof:placetype":"venue"
},
  "geometry": {"coordinates":[-71.45607,41.557195],"type":"Point"}
}