{
  "type": "Feature",
  "properties": {
    "addr:full":"34 Alder Ct East Greenwich RI 02818",
    "addr:housenumber":"34",
    "addr:postcode":"02818",
    "addr:street":"Alder Ct",
    "iso:country":"US",
    "sg:address":"34 Alder Ct",
    "sg:city":"East Greenwich",
    "sg:classifiers":[
        {
            "category":"Professional",
            "subcategory":"Management & Consulting",
            "type":"Services"
        }
    ],
    "sg:phone":"+1 401 398 0223",
    "sg:postcode":"02818",
    "sg:province":"RI",
    "sg:tags":[
        "consultant"
    ],
    "wof:name":"Wickford Consulting LLC",
    "wof:placetype":"venue"
},
  "geometry": {"coordinates":[-71.471796,41.653628],"type":"Point"}
}