{
  "type": "Feature",
  "properties": {
    "iso:country":"US",
    "sg:address":"145 Westminster St",
    "sg:city":"Providence",
    "sg:classifiers":[
        {
            "category":"Real Estate",
            "subcategory":"Real Estate Services",
            "type":"Services"
        }
    ],
    "sg:phone":"+1 401 861 4300",
    "sg:postcode":"02903",
    "sg:province":"RI",
    "sg:tags":[
        "management",
        "property"
    ],
    "wof:name":"Kennedy Property Management",
    "wof:placetype":"venue"
},
  "geometry": {"coordinates":[-71.411162,41.824049],"type":"Point"}
}