{
  "type": "Feature",
  "properties": {
    "addr:full":"400 Highland Ave Cumberland RI 02864",
    "addr:housenumber":"400",
    "addr:postcode":"02864",
    "addr:street":"Highland Ave",
    "iso:country":"US",
    "sg:address":"400 Highland Ave",
    "sg:city":"Cumberland",
    "sg:classifiers":[
        {
            "category":"Wholesale",
            "subcategory":"Drugs",
            "type":"Manufacturing & Wholesale Goods"
        }
    ],
    "sg:phone":"+1 401 762 2000",
    "sg:postcode":"02864",
    "sg:province":"RI",
    "sg:tags":[
        "pharmaceutical"
    ],
    "wof:name":"Collegium Pharmaceutical",
    "wof:placetype":"venue"
},
  "geometry": {"coordinates":[-71.387235,41.919931],"type":"Point"}
}