{
  "type": "Feature",
  "properties": {
    "addr:full":"11 King Charles Dr Portsmouth RI 02871",
    "addr:housenumber":"11",
    "addr:postcode":"02871",
    "addr:street":"King Charles Dr",
    "iso:country":"US",
    "sg:address":"11 King Charles Dr",
    "sg:city":"Portsmouth",
    "sg:classifiers":[
        {
            "category":"Health Services",
            "subcategory":"Chiropractor",
            "type":"Services"
        }
    ],
    "sg:phone":"+1 401 683 1941",
    "sg:postcode":"02871",
    "sg:province":"RI",
    "wof:name":"Ronald P Marsh DC",
    "wof:placetype":"venue"
},
  "geometry": {"coordinates":[-71.26828500000001,41.591781],"type":"Point"}
}