{
  "type": "Feature",
  "properties": {
    "addr:full":"80 Fountain St Pawtucket RI 02860",
    "addr:housenumber":"80",
    "addr:postcode":"02860",
    "addr:street":"Fountain St",
    "iso:country":"US",
    "sg:address":"80 Fountain St",
    "sg:city":"Pawtucket",
    "sg:classifiers":[
        {
            "category":"Professional",
            "subcategory":"Art Services",
            "type":"Services"
        }
    ],
    "sg:phone":"+1 401 721 2240",
    "sg:postcode":"02860",
    "sg:province":"RI",
    "sg:tags":[
        "silk",
        "screening",
        "pop",
        "display"
    ],
    "sg:website":"www.classicdisplay.com",
    "wof:name":"Classic Display Inc",
    "wof:placetype":"venue"
},
  "geometry": {"coordinates":[-71.37825599999999,41.882886],"type":"Point"}
}