{
  "type": "Feature",
  "properties": {
    "iso:country":"US",
    "sg:address":"1710 Cranston St",
    "sg:city":"Cranston",
    "sg:classifiers":[
        {
            "category":"Restaurant",
            "type":"Food & Drink"
        }
    ],
    "sg:phone":"+1 401 943 1932",
    "sg:postcode":"02920",
    "sg:province":"RI",
    "sg:tags":[
        "eating"
    ],
    "wof:name":"Antonio's Restaurant",
    "wof:placetype":"venue"
},
  "geometry": {"coordinates":[-71.464668,41.783346],"type":"Point"}
}