{
  "type": "Feature",
  "properties": {
    "iso:country":"US",
    "sg:address":"79 Chestnut St",
    "sg:city":"Central Falls",
    "sg:classifiers":[
        {
            "category":"Wholesale",
            "subcategory":"Home Furnishings",
            "type":"Manufacturing & Wholesale Goods"
        }
    ],
    "sg:phone":"+1 401 726 8786",
    "sg:postcode":"02863",
    "sg:province":"RI",
    "sg:tags":[
        "picture",
        "frame"
    ],
    "wof:name":"Motyka Art Frame",
    "wof:placetype":"venue"
},
  "geometry": {"coordinates":[-71.38768,41.892838],"type":"Point"}
}