{
  "type": "Feature",
  "properties": {
    "iso:country":"US",
    "sg:address":"1643 Kingstown Rd",
    "sg:city":"Wakefield",
    "sg:classifiers":[
        {
            "category":"Building & Trades",
            "subcategory":"Construction",
            "type":"Services"
        }
    ],
    "sg:phone":"+1 401 782 3450",
    "sg:postcode":"02879",
    "sg:province":"RI",
    "sg:tags":[
        "general",
        "contractor"
    ],
    "wof:name":"South County Construction",
    "wof:placetype":"venue"
},
  "geometry": {"coordinates":[-71.508325,41.4567],"type":"Point"}
}