{
  "type": "Feature",
  "properties": {
    "iso:country":"US",
    "sg:address":"14 Clarke St",
    "sg:city":"Newport",
    "sg:classifiers":[
        {
            "category":"Health Services",
            "subcategory":"Nursing And Care Facility",
            "type":"Services"
        }
    ],
    "sg:phone":"+1 401 847 0841",
    "sg:postcode":"02840",
    "sg:province":"RI",
    "sg:tags":[
        "home",
        "convalescent"
    ],
    "wof:name":"Henderson Home",
    "wof:placetype":"venue"
},
  "geometry": {"coordinates":[-71.31337499999999,41.488694],"type":"Point"}
}