{
  "type": "Feature",
  "properties": {
    "iso:country":"US",
    "sg:address":"67 Old Greenwich Dr",
    "sg:city":"East Greenwich",
    "sg:classifiers":[
        {
            "category":"Manufacturing",
            "subcategory":"Printing",
            "type":"Manufacturing & Wholesale Goods"
        }
    ],
    "sg:phone":"+1 401 885 2147",
    "sg:postcode":"02818",
    "sg:province":"RI",
    "sg:tags":[
        "commercial",
        "offset"
    ],
    "wof:name":"Narragansett Bay Press Inc",
    "wof:placetype":"venue"
},
  "geometry": {"coordinates":[-71.47848999999999,41.654817],"type":"Point"}
}