{
  "type": "Feature",
  "properties": {
    "iso:country":"US",
    "sg:address":"2 Commerce Way",
    "sg:city":"Johnston",
    "sg:classifiers":[
        {
            "category":"Professional",
            "type":"Services"
        }
    ],
    "sg:phone":"+1 401 943 1360",
    "sg:postcode":"02919",
    "sg:province":"RI",
    "sg:tags":[
        "establishment"
    ],
    "wof:name":"John Paul Co",
    "wof:placetype":"venue"
},
  "geometry": {"coordinates":[-71.498673,41.820406],"type":"Point"}
}