{
  "type": "Feature",
  "properties": {
    "iso:country":"US",
    "sg:address":"1119 Chalkstone Ave",
    "sg:city":"Providence",
    "sg:classifiers":[
        {
            "category":"Professional",
            "subcategory":"Lawyer & Legal Services",
            "type":"Services"
        }
    ],
    "sg:phone":"+1 401 331 7200",
    "sg:postcode":"02908",
    "sg:province":"RI",
    "wof:name":"Gentile & Gentile",
    "wof:placetype":"venue"
},
  "geometry": {"coordinates":[-71.445297,41.8325],"type":"Point"}
}