{
  "type": "Feature",
  "properties": {
    "addr:full":"50 Kennedy Plz Providence RI 02903",
    "addr:housenumber":"50",
    "addr:postcode":"02903",
    "addr:street":"Kennedy Plz",
    "iso:country":"US",
    "sg:address":"50 Kennedy Plz",
    "sg:city":"Providence",
    "sg:classifiers":[
        {
            "category":"Manufacturing",
            "subcategory":"Building Materials",
            "type":"Manufacturing & Wholesale Goods"
        },
        {
            "category":"Manufacturing",
            "subcategory":"Tools & Machinery",
            "type":"Manufacturing & Wholesale Goods"
        }
    ],
    "sg:phone":"+1 401 751 1600",
    "sg:postcode":"02903",
    "sg:province":"RI",
    "sg:tags":[
        "residential",
        "product",
        "air",
        "conditioning",
        "mfg"
    ],
    "sg:website":"www.nortek-inc.com",
    "wof:name":"Nortek Holdings Inc",
    "wof:placetype":"venue"
},
  "geometry": {"coordinates":[-71.410875,41.825182],"type":"Point"}
}