{
  "type": "Feature",
  "properties": {
    "iso:country":"US",
    "sg:address":"6 Blackstone Valley Pl",
    "sg:city":"Lincoln",
    "sg:classifiers":[
        {
            "category":"Professional",
            "type":"Services"
        },
        {
            "category":"Professional",
            "subcategory":"Research",
            "type":"Services"
        }
    ],
    "sg:phone":"+1 401 333 3880",
    "sg:postcode":"02865",
    "sg:province":"RI",
    "sg:tags":[
        "establishment",
        "commercial"
    ],
    "wof:name":"Neurotech USA Inc",
    "wof:placetype":"venue"
},
  "geometry": {"coordinates":[-71.45736599999999,41.937798],"type":"Point"}
}