{
  "type": "Feature",
  "properties": {
    "addr:full":"1725 Mendon Rd Ste 105 Cumberland RI 02864",
    "addr:housenumber":"1725",
    "addr:postcode":"02864",
    "addr:street":"Mendon Rd Ste 105",
    "iso:country":"US",
    "sg:address":"1725 Mendon Rd Ste 105",
    "sg:city":"Cumberland",
    "sg:classifiers":[
        {
            "category":"Education",
            "subcategory":"Special Training",
            "type":"Public Place"
        }
    ],
    "sg:phone":"+1 401 334 9309",
    "sg:postcode":"02864",
    "sg:province":"RI",
    "sg:tags":[
        "tutoring"
    ],
    "sg:website":"www.sylvanlearning.com/cumberland",
    "wof:name":"Sylvan Learning Center",
    "wof:placetype":"venue"
},
  "geometry": {"coordinates":[-71.434674,41.942384],"type":"Point"}
}