{
  "type": "Feature",
  "properties": {
    "addr:full":"400 Metacom Ave Bristol RI 02809",
    "addr:housenumber":"400",
    "addr:postcode":"02809",
    "addr:street":"Metacom Ave",
    "iso:country":"US",
    "sg:address":"400 Metacom Ave",
    "sg:city":"Bristol",
    "sg:classifiers":[
        {
            "category":"Organizations",
            "subcategory":"Professional Association",
            "type":"Services"
        }
    ],
    "sg:phone":"+1 401 253 7282",
    "sg:postcode":"02809",
    "sg:province":"RI",
    "wof:name":"Pokanoket Tribal Acknwldgmnt",
    "wof:placetype":"venue"
},
  "geometry": {"coordinates":[-71.26050499999999,41.680326],"type":"Point"}
}