{
  "type": "Feature",
  "properties": {
    "iso:country":"US",
    "sg:address":"80 Hopkins Ave",
    "sg:city":"Johnston",
    "sg:classifiers":[
        {
            "category":"Wholesale",
            "subcategory":"Books, Periodicals, & Newspapers",
            "type":"Manufacturing & Wholesale Goods"
        }
    ],
    "sg:phone":"+1 401 934 2149",
    "sg:postcode":"02919",
    "sg:province":"RI",
    "wof:name":"Dowry Collection Inc",
    "wof:placetype":"venue"
},
  "geometry": {"coordinates":[-71.566329,41.8449],"type":"Point"}
}