{
  "type": "Feature",
  "properties": {
    "iso:country":"US",
    "sg:address":"320 Shermantown Rd",
    "sg:city":"Saunderstown",
    "sg:classifiers":[
        {
            "category":"Farming",
            "subcategory":"Berry Farm",
            "type":"Manufacturing & Wholesale Goods"
        },
        {
            "category":"Farming",
            "subcategory":"Farm",
            "type":"Manufacturing & Wholesale Goods"
        }
    ],
    "sg:phone":"+1 401 295 7669",
    "sg:postcode":"02874",
    "sg:province":"RI",
    "wof:name":"Smith's Berry Farm",
    "wof:placetype":"venue"
},
  "geometry": {"coordinates":[-71.470792,41.521189],"type":"Point"}
}