{
  "type": "Feature",
  "properties": {
    "iso:country":"US",
    "sg:address":"50 Rutland St",
    "sg:city":"Manville",
    "sg:classifiers":[
        {
            "category":"Real Estate",
            "subcategory":"Real Estate Agent",
            "type":"Services"
        }
    ],
    "sg:phone":"+1 401 767 2248",
    "sg:postcode":"02838",
    "sg:province":"RI",
    "wof:name":"Mpm",
    "wof:placetype":"venue"
},
  "geometry": {"coordinates":[-71.47419499999999,41.965202],"type":"Point"}
}