{
  "type": "Feature",
  "properties": {
    "iso:country":"US",
    "sg:address":"15 Benefit St",
    "sg:city":"Providence",
    "sg:classifiers":[
        {
            "category":"Health Services",
            "subcategory":"Doctor",
            "type":"Services"
        }
    ],
    "sg:phone":"+1 401 273 4050",
    "sg:postcode":"02904",
    "sg:province":"RI",
    "sg:tags":[
        "physician",
        "surgeon",
        "psychiatrist"
    ],
    "wof:name":"Golinger Ronald C MD",
    "wof:placetype":"venue"
},
  "geometry": {"coordinates":[-71.40969800000001,41.834202],"type":"Point"}
}