{
  "type": "Feature",
  "properties": {
    "addr:full":"1 Champlin Pl Newport RI 02840",
    "addr:housenumber":"1",
    "addr:postcode":"02840",
    "addr:street":"Champlin Pl",
    "iso:country":"US",
    "sg:address":"1 Champlin Pl",
    "sg:city":"Newport",
    "sg:classifiers":[
        {
            "category":"Social Services",
            "type":"Services"
        }
    ],
    "sg:phone":"+1 401 847 8040",
    "sg:postcode":"02840",
    "sg:province":"RI",
    "sg:tags":[
        "counselor",
        "marriage",
        "family"
    ],
    "wof:name":"Michael Castaldi",
    "wof:placetype":"venue"
},
  "geometry": {"coordinates":[-71.300354,41.492408],"type":"Point"}
}