{
  "type": "Feature",
  "properties": {
    "addr:full":"556 W Main Rd Middletown RI 02842",
    "addr:housenumber":"556",
    "addr:postcode":"02842",
    "addr:street":"W Main Rd",
    "iso:country":"US",
    "sg:address":"556 W Main Rd",
    "sg:city":"Middletown",
    "sg:classifiers":[
        {
            "category":"Personal",
            "subcategory":"Barber",
            "type":"Services"
        }
    ],
    "sg:phone":"+1 401 849 1840",
    "sg:postcode":"02842",
    "sg:province":"RI",
    "sg:tags":[
        "shop"
    ],
    "wof:name":"Jason's II Barber Stylist",
    "wof:placetype":"venue"
},
  "geometry": {"coordinates":[-71.30026700000001,41.518247],"type":"Point"}
}