{
  "type": "Feature",
  "properties": {
    "addr:full":"210 Willett Ave Riverside RI 02915",
    "addr:housenumber":"210",
    "addr:postcode":"02915",
    "addr:street":"Willett Ave",
    "iso:country":"US",
    "sg:address":"210 Willett Ave",
    "sg:city":"Riverside",
    "sg:classifiers":[
        {
            "category":"Shopping",
            "type":"Retail Goods"
        }
    ],
    "sg:phone":"+1 401 383 6035",
    "sg:postcode":"02915",
    "sg:province":"RI",
    "sg:tags":[
        "pet",
        "shop"
    ],
    "wof:name":"J L Breeders Reptile Spec",
    "wof:placetype":"venue"
},
  "geometry": {"coordinates":[-71.35687799999999,41.775158],"type":"Point"}
}