{
  "type": "Feature",
  "properties": {
    "addr:full":"812 Branch Ave Providence RI 02904",
    "addr:housenumber":"812",
    "addr:postcode":"02904",
    "addr:street":"Branch Ave",
    "iso:country":"US",
    "sg:address":"812 Branch Ave",
    "sg:city":"Providence",
    "sg:classifiers":[
        {
            "category":"Wholesale",
            "subcategory":"Metals & Minerals",
            "type":"Manufacturing & Wholesale Goods"
        }
    ],
    "sg:phone":"+1 401 331 8660",
    "sg:postcode":"02904",
    "sg:province":"RI",
    "sg:tags":[
        "die",
        "casting"
    ],
    "wof:name":"Jadco",
    "wof:placetype":"venue"
},
  "geometry": {"coordinates":[-71.43467699999999,41.854721],"type":"Point"}
}