{
  "type": "Feature",
  "properties": {
    "iso:country":"US",
    "sg:address":"50 Kennedy Plz",
    "sg:city":"Providence",
    "sg:classifiers":[
        {
            "category":"Banks & Credit Unions",
            "subcategory":"Investment Brokerage",
            "type":"Services"
        }
    ],
    "sg:phone":"+1 401 274 3130",
    "sg:postcode":"02903",
    "sg:province":"RI",
    "sg:tags":[
        "security"
    ],
    "sg:website":"www.wachovia.com",
    "wof:name":"Wachovia Securities",
    "wof:placetype":"venue"
},
  "geometry": {"coordinates":[-71.410875,41.825182],"type":"Point"}
}