{
  "type": "Feature",
  "properties": {
    "addr:full":"27 Hamilton Ave Warwick RI 02886",
    "addr:housenumber":"27",
    "addr:postcode":"02886",
    "addr:street":"Hamilton Ave",
    "iso:country":"US",
    "sg:address":"27 Hamilton Ave",
    "sg:city":"Warwick",
    "sg:classifiers":[
        {
            "category":"Manufacturing",
            "subcategory":"Printing",
            "type":"Manufacturing & Wholesale Goods"
        }
    ],
    "sg:phone":"+1 401 739 9882",
    "sg:postcode":"02886",
    "sg:province":"RI",
    "sg:tags":[
        "lithographic",
        "commercial"
    ],
    "wof:name":"Quest Printing",
    "wof:placetype":"venue"
},
  "geometry": {"coordinates":[-71.419366,41.710413],"type":"Point"}
}