{
  "type": "Feature",
  "properties": {
    "iso:country":"US",
    "sg:address":"75 Ophelia St",
    "sg:city":"Providence",
    "sg:classifiers":[
        {
            "category":"Building & Trades",
            "subcategory":"Construction",
            "type":"Services"
        }
    ],
    "sg:phone":"+1 401 351 0030",
    "sg:postcode":"02909",
    "sg:province":"RI",
    "sg:tags":[
        "contractor"
    ],
    "wof:name":"Decesare Bldg Co Inc",
    "wof:placetype":"venue"
},
  "geometry": {"coordinates":[-71.46410400000001,41.818001],"type":"Point"}
}