{
  "type": "Feature",
  "properties": {
    "iso:country":"US",
    "sg:address":"31 Bridge St",
    "sg:city":"Newport",
    "sg:classifiers":[
        {
            "category":"Health Services",
            "subcategory":"Clinic",
            "type":"Services"
        }
    ],
    "sg:phone":"+1 401 849 3275",
    "sg:postcode":"02840",
    "sg:province":"RI",
    "wof:name":"ATC Healthcare Svc",
    "wof:placetype":"venue"
},
  "geometry": {"coordinates":[-71.315467,41.492405],"type":"Point"}
}