{
  "type": "Feature",
  "properties": {
    "iso:country":"US",
    "sg:address":"199 Austin Farm Rd",
    "sg:city":"Exeter",
    "sg:classifiers":[
        {
            "category":"Recreation",
            "type":"Entertainment"
        }
    ],
    "sg:phone":"+1 401 392 0212",
    "sg:postcode":"02822",
    "sg:province":"RI",
    "wof:name":"Bishops Castle",
    "wof:placetype":"venue"
},
  "geometry": {"coordinates":[-71.667396,41.593368],"type":"Point"}
}