{
  "type": "Feature",
  "properties": {
    "iso:country":"US",
    "sg:address":"97 Main St",
    "sg:city":"Blackstone",
    "sg:classifiers":[
        {
            "category":"Retail",
            "subcategory":"Self-service Laundry",
            "type":"Services"
        }
    ],
    "sg:phone":"+1 508 876 8095",
    "sg:postcode":"01504",
    "sg:province":"RI",
    "wof:name":"Clothesline Laundry",
    "wof:placetype":"venue"
},
  "geometry": {"coordinates":[-71.53753399999999,42.018587],"type":"Point"}
}