{
  "type": "Feature",
  "properties": {
    "iso:country":"US",
    "sg:address":"67 Indian Trl",
    "sg:city":"Chepachet",
    "sg:classifiers":[
        {
            "category":"Organizations",
            "subcategory":"Religious Organization",
            "type":"Services"
        }
    ],
    "sg:phone":"+1 401 568 0060",
    "sg:postcode":"02814",
    "sg:province":"RI",
    "sg:tags":[
        "church"
    ],
    "wof:name":"Glad Tidings Assembly Of God",
    "wof:placetype":"venue"
},
  "geometry": {"coordinates":[-71.69938,41.881429],"type":"Point"}
}