{
  "type": "Feature",
  "properties": {
    "iso:country":"US",
    "sg:address":"193 Division St",
    "sg:city":"Pawtucket",
    "sg:classifiers":[
        {
            "category":"Food & Beverages",
            "subcategory":"Groceries & Convenience Stores",
            "type":"Retail Goods"
        }
    ],
    "sg:phone":"+1 401 727 3214",
    "sg:postcode":"02860",
    "sg:province":"RI",
    "sg:website":"www.cumberlandfarms.com",
    "wof:name":"Cumberland Farms Inc",
    "wof:placetype":"venue"
},
  "geometry": {"coordinates":[-71.376999,41.8736],"type":"Point"}
}