{
  "type": "Feature",
  "properties": {
    "iso:country":"US",
    "sg:address":"25 Fernwood Dr",
    "sg:city":"Cranston",
    "sg:classifiers":[
        {
            "category":"Retail",
            "subcategory":"Funeral Services",
            "type":"Services"
        }
    ],
    "sg:phone":"+1 401 463 6458",
    "sg:postcode":"02920",
    "sg:province":"RI",
    "wof:name":"Lamphar John",
    "wof:placetype":"venue"
},
  "geometry": {"coordinates":[-71.46535,41.734008],"type":"Point"}
}