{
  "type": "Feature",
  "properties": {
    "iso:country":"US",
    "sg:address":"718 Plainfield St",
    "sg:city":"Providence",
    "sg:classifiers":[
        {
            "category":"Home & Garden",
            "subcategory":"Carpets & Floor Coverings",
            "type":"Retail Goods"
        }
    ],
    "sg:phone":"+1 401 943 2600",
    "sg:postcode":"02909",
    "sg:province":"RI",
    "sg:tags":[
        "dealer",
        "laying",
        "rug",
        "contractor"
    ],
    "wof:name":"Branch Floor Covering Inc",
    "wof:placetype":"venue"
},
  "geometry": {"coordinates":[-71.461794,41.811741],"type":"Point"}
}