{
  "type": "Feature",
  "properties": {
    "addr:full":"121 Longwood Ave Providence RI 02908",
    "addr:housenumber":"121",
    "addr:postcode":"02908",
    "addr:street":"Longwood Ave",
    "iso:country":"US",
    "sg:address":"121 Longwood Ave",
    "sg:city":"Providence",
    "sg:classifiers":[
        {
            "category":"Autos & Motor Vehicles",
            "subcategory":"Automobile Sales",
            "type":"Retail Goods"
        }
    ],
    "sg:phone":"+1 401 996 8787",
    "sg:postcode":"02908",
    "sg:province":"RI",
    "sg:tags":[
        "used"
    ],
    "wof:name":"Destiny Auto Sales",
    "wof:placetype":"venue"
},
  "geometry": {"coordinates":[-71.45160799999999,41.849734],"type":"Point"}
}