{
  "type": "Feature",
  "properties": {
    "iso:country":"US",
    "sg:address":"170 Compton View Dr",
    "sg:city":"Middletown",
    "sg:classifiers":[
        {
            "category":"Local Transit",
            "type":"Transportation"
        }
    ],
    "sg:phone":"+1 401 847 4883",
    "sg:postcode":"02842",
    "sg:province":"RI",
    "sg:tags":[
        "airport"
    ],
    "sg:website":"www.landsendlimo.com",
    "wof:name":"Lands End Limousine Inc",
    "wof:placetype":"venue"
},
  "geometry": {"coordinates":[-71.27436299999999,41.507178],"type":"Point"}
}