{
  "type": "Feature",
  "properties": {
    "iso:country":"US",
    "sg:address":"180 Pine Street",
    "sg:city":"Providence",
    "sg:classifiers":[
        {
            "category":"Recreation",
            "subcategory":"Dance Hall",
            "type":"Entertainment"
        }
    ],
    "sg:postcode":"02903",
    "sg:province":"RI",
    "sg:tags":[
        "club"
    ],
    "sg:website":"colosseumri.com",
    "wof:name":"Colosseum",
    "wof:placetype":"venue"
},
  "geometry": {"coordinates":[-71.412087,41.820173],"type":"Point"}
}