{
  "type": "Feature",
  "properties": {
    "addr:full":"1210 Mendon Rd Woonsocket RI 02895",
    "addr:postcode":"1210;02895",
    "addr:street":"Mendon Rd",
    "iso:country":"US",
    "sg:address":"1210 Mendon Rd",
    "sg:city":"Woonsocket",
    "sg:classifiers":[
        {
            "category":"Education",
            "subcategory":"School",
            "type":"Public Place"
        }
    ],
    "sg:phone":"+1 401 767 5907",
    "sg:postcode":"02895",
    "sg:province":"RI",
    "sg:tags":[
        "religious"
    ],
    "sg:website":"www.gwcrs.org",
    "wof:name":"Good Shepherd Catholic School",
    "wof:placetype":"venue"
},
  "geometry": {"coordinates":[-71.480315,42.002397],"type":"Point"}
}