{
  "type": "Feature",
  "properties": {
    "addr:full":"280 Victory Hwy West Greenwich RI 02817",
    "addr:housenumber":"280",
    "addr:postcode":"02817",
    "addr:street":"Victory Hwy",
    "iso:country":"US",
    "sg:address":"280 Victory Hwy",
    "sg:city":"West Greenwich",
    "sg:classifiers":[
        {
            "category":"Government",
            "subcategory":"Office",
            "type":"Public Place"
        },
        {
            "category":"Government",
            "subcategory":"Court House",
            "type":"Public Place"
        }
    ],
    "sg:phone":"+1 401 397 5016",
    "sg:postcode":"02817",
    "sg:province":"RI",
    "sg:tags":[
        "city",
        "state",
        "system"
    ],
    "wof:name":"West Greenwich Town Clerk",
    "wof:placetype":"venue"
},
  "geometry": {"coordinates":[-71.685942,41.634991],"type":"Point"}
}