{
  "type": "Feature",
  "properties": {
    "iso:country":"US",
    "sg:address":"582 Newport Ave",
    "sg:city":"Pawtucket",
    "sg:classifiers":[
        {
            "category":"Personal",
            "subcategory":"Beauty Salon",
            "type":"Services"
        }
    ],
    "sg:phone":"+1 401 722 0820",
    "sg:postcode":"02861",
    "sg:province":"RI",
    "sg:tags":[
        "shop"
    ],
    "wof:name":"Total Creations Salon",
    "wof:placetype":"venue"
},
  "geometry": {"coordinates":[-71.354406,41.872464],"type":"Point"}
}