{
  "type": "Feature",
  "properties": {
    "iso:country":"US",
    "sg:address":"950 N Quidnessett Rd",
    "sg:city":"North Kingstown",
    "sg:classifiers":[
        {
            "category":"Recreation",
            "type":"Entertainment"
        }
    ],
    "sg:phone":"+1 401 884 9755",
    "sg:postcode":"02852",
    "sg:province":"RI",
    "sg:tags":[
        "course",
        "golf"
    ],
    "sg:website":"www.quidnessett.com",
    "wof:name":"Quidnessett Country Club",
    "wof:placetype":"venue"
},
  "geometry": {"coordinates":[-71.422066,41.640388],"type":"Point"}
}