{
  "type": "Feature",
  "properties": {
    "iso:country":"US",
    "sg:address":"1705 Main St",
    "sg:city":"West Warwick",
    "sg:classifiers":[
        {
            "category":"Retail",
            "subcategory":"Self-service Laundry",
            "type":"Services"
        }
    ],
    "sg:phone":"+1 401 823 1890",
    "sg:postcode":"02893",
    "sg:province":"RI",
    "sg:tags":[
        "coin"
    ],
    "wof:name":"Laundry Basket",
    "wof:placetype":"venue"
},
  "geometry": {"coordinates":[-71.52372699999999,41.68441],"type":"Point"}
}