{
  "type": "Feature",
  "properties": {
    "addr:full":"4 Franklin St Bristol RI 02809",
    "addr:housenumber":"4",
    "addr:postcode":"02809",
    "addr:street":"Franklin St",
    "iso:country":"US",
    "sg:address":"4 Franklin St",
    "sg:city":"Bristol",
    "sg:classifiers":[
        {
            "category":"Shopping",
            "subcategory":"Used Merchandise",
            "type":"Retail Goods"
        }
    ],
    "sg:phone":"+1 401 253 3443",
    "sg:postcode":"02809",
    "sg:province":"RI",
    "sg:tags":[
        "antique"
    ],
    "wof:name":"Print Gallery LTD",
    "wof:placetype":"venue"
},
  "geometry": {"coordinates":[-71.277777,41.673556],"type":"Point"}
}