{
  "type": "Feature",
  "properties": {
    "iso:country":"US",
    "sg:address":"45 Acorn St",
    "sg:city":"Providence",
    "sg:classifiers":[
        {
            "category":"Manufacturing",
            "subcategory":"Jewelry",
            "type":"Manufacturing & Wholesale Goods"
        }
    ],
    "sg:phone":"+1 401 331 1522",
    "sg:postcode":"02903",
    "sg:province":"RI",
    "sg:tags":[
        "precious",
        "metal",
        "mfg"
    ],
    "wof:name":"M & J Jewelry",
    "wof:placetype":"venue"
},
  "geometry": {"coordinates":[-71.428518,41.828181],"type":"Point"}
}