{
  "type": "Feature",
  "properties": {
    "iso:country":"US",
    "sg:address":"769 Hope St Ste 1",
    "sg:city":"Providence",
    "sg:classifiers":[
        {
            "category":"Shopping",
            "subcategory":"Hobbies, Toys, & Games",
            "type":"Retail Goods"
        }
    ],
    "sg:phone":"+1 401 861 7640",
    "sg:postcode":"02906",
    "sg:province":"RI",
    "sg:tags":[
        "shop",
        "hobby",
        "model",
        "coin",
        "supply"
    ],
    "wof:name":"Podrat Coin Exchange Inc",
    "wof:placetype":"venue"
},
  "geometry": {"coordinates":[-71.39559199999999,41.847847],"type":"Point"}
}