{
  "type": "Feature",
  "properties": {
    "addr:full":"199 Mishnock Rd West Greenwich RI 02817",
    "addr:housenumber":"199",
    "addr:postcode":"02817",
    "addr:street":"Mishnock Rd",
    "iso:country":"US",
    "sg:address":"199 Mishnock Rd",
    "sg:city":"West Greenwich",
    "sg:classifiers":[
        {
            "category":"Building & Trades",
            "subcategory":"Construction",
            "type":"Services"
        }
    ],
    "sg:phone":"+1 401 269 9349",
    "sg:postcode":"02817",
    "sg:province":"RI",
    "sg:tags":[
        "residential"
    ],
    "wof:name":"Final Home Improvement",
    "wof:placetype":"venue"
},
  "geometry": {"coordinates":[-71.58604,41.655753],"type":"Point"}
}