{
  "type": "Feature",
  "properties": {
    "addr:full":"21 Atwells Ave Providence RI 02903",
    "addr:housenumber":"21",
    "addr:postcode":"02903",
    "addr:street":"Atwells Ave",
    "iso:country":"US",
    "sg:address":"21 Atwells Ave",
    "sg:city":"Providence",
    "sg:classifiers":[
        {
            "category":"Restaurant",
            "type":"Food & Drink"
        }
    ],
    "sg:phone":"+1 401 709 0347",
    "sg:postcode":"02903",
    "sg:province":"RI",
    "sg:tags":[
        "steakhouse"
    ],
    "sg:website":"www.donshula.com",
    "wof:name":"Shula's 347 Grill",
    "wof:placetype":"venue"
},
  "geometry": {"coordinates":[-71.418857,41.82274],"type":"Point"}
}