{
  "type": "Feature",
  "properties": {
    "iso:country":"US",
    "sg:address":"10 Memorial Blvd",
    "sg:city":"Providence",
    "sg:classifiers":[
        {
            "category":"Restaurant",
            "type":"Food & Drink"
        }
    ],
    "sg:phone":"+1 401 272 2271",
    "sg:postcode":"02903",
    "sg:province":"RI",
    "sg:tags":[
        "steakhouse"
    ],
    "sg:website":"www.ruthschris.com",
    "wof:name":"Ruth's Chris Steak House",
    "wof:placetype":"venue"
},
  "geometry": {"coordinates":[-71.41429599999999,41.826224],"type":"Point"}
}