{
  "type": "Feature",
  "properties": {
    "iso:country":"US",
    "sg:address":"8 Autumn Ave",
    "sg:city":"Smithfield",
    "sg:classifiers":[
        {
            "category":"Building & Trades",
            "subcategory":"Cleaning & Sanitation",
            "type":"Services"
        }
    ],
    "sg:phone":"+1 401 233 0160",
    "sg:postcode":"02917",
    "sg:province":"RI",
    "sg:tags":[
        "maintenance"
    ],
    "wof:name":"Diamond Window Cleaning",
    "wof:placetype":"venue"
},
  "geometry": {"coordinates":[-71.49135,41.869739],"type":"Point"}
}