{
  "type": "Feature",
  "properties": {
    "iso:country":"US",
    "sg:address":"6 Alto St",
    "sg:city":"Warwick",
    "sg:classifiers":[
        {
            "category":"Professional",
            "subcategory":"Accounting & Tax Preparation",
            "type":"Services"
        }
    ],
    "sg:phone":"+1 401 732 0065",
    "sg:postcode":"02886",
    "sg:province":"RI",
    "wof:name":"Bookkeepng Svc Unltd",
    "wof:placetype":"venue"
},
  "geometry": {"coordinates":[-71.433914,41.699028],"type":"Point"}
}