{
  "type": "Feature",
  "properties": {
    "iso:country":"US",
    "sg:address":"2485 Post Rd",
    "sg:city":"Wakefield",
    "sg:classifiers":[
        {
            "category":"Building & Trades",
            "subcategory":"Landscaping Services",
            "type":"Services"
        }
    ],
    "sg:phone":"+1 401 788 9971",
    "sg:postcode":"02879",
    "sg:province":"RI",
    "wof:name":"Total Lawn Care LLC",
    "wof:placetype":"venue"
},
  "geometry": {"coordinates":[-71.571223,41.400624],"type":"Point"}
}