{
  "type": "Feature",
  "properties": {
    "addr:full":"911 Pontiac Ave Cranston RI 02920",
    "addr:housenumber":"911",
    "addr:postcode":"02920",
    "addr:street":"Pontiac Ave",
    "iso:country":"US",
    "sg:address":"911 Pontiac Ave",
    "sg:city":"Cranston",
    "sg:classifiers":[
        {
            "category":"Personal",
            "subcategory":"Beauty Salon",
            "type":"Services"
        }
    ],
    "sg:phone":"+1 401 941 9788",
    "sg:postcode":"02920",
    "sg:province":"RI",
    "sg:tags":[
        "shop"
    ],
    "wof:name":"Gazebo Hair Salon",
    "wof:placetype":"venue"
},
  "geometry": {"coordinates":[-71.443477,41.759751],"type":"Point"}
}