{
  "type": "Feature",
  "properties": {
    "iso:country":"US",
    "sg:address":"39 East Ave",
    "sg:city":"Westerly",
    "sg:classifiers":[
        {
            "category":"Health Services",
            "subcategory":"Doctor",
            "type":"Services"
        }
    ],
    "sg:phone":"+1 401 596 6800",
    "sg:postcode":"02891",
    "sg:province":"RI",
    "sg:tags":[
        "medical"
    ],
    "wof:name":"Kevin Maguire MD",
    "wof:placetype":"venue"
},
  "geometry": {"coordinates":[-71.819594,41.364249],"type":"Point"}
}