{
  "type": "Feature",
  "properties": {
    "iso:country":"US",
    "sg:address":"183 Washington Rd",
    "sg:city":"Barrington",
    "sg:classifiers":[
        {
            "category":"Personal",
            "subcategory":"Beauty Salon",
            "type":"Services"
        }
    ],
    "sg:phone":"+1 401 246 0456",
    "sg:postcode":"02806",
    "sg:province":"RI",
    "wof:name":"Blue Moon Hair Studio",
    "wof:placetype":"venue"
},
  "geometry": {"coordinates":[-71.341212,41.747979],"type":"Point"}
}