{
  "type": "Feature",
  "properties": {
    "addr:full":"1098 Diamond Hill Rd Woonsocket RI 02895",
    "addr:housenumber":"1098",
    "addr:postcode":"02895",
    "addr:street":"Diamond Hill Rd",
    "iso:country":"US",
    "sg:address":"1098 Diamond Hill Rd",
    "sg:city":"Woonsocket",
    "sg:classifiers":[
        {
            "category":"Shopping",
            "subcategory":"Florist",
            "type":"Retail Goods"
        }
    ],
    "sg:phone":"+1 401 769 0462",
    "sg:postcode":"02895",
    "sg:province":"RI",
    "wof:name":"Fontana's Flowers/Greenhouses",
    "wof:placetype":"venue"
},
  "geometry": {"coordinates":[-71.483785,42.015808],"type":"Point"}
}