{
  "type": "Feature",
  "properties": {
    "addr:full":"56 Rockland St Narragansett RI 02882",
    "addr:housenumber":"56",
    "addr:postcode":"02882",
    "addr:street":"Rockland St",
    "iso:country":"US",
    "sg:address":"56 Rockland St",
    "sg:city":"Narragansett",
    "sg:classifiers":[
        {
            "category":"Professional",
            "subcategory":"Business Services",
            "type":"Services"
        }
    ],
    "sg:phone":"+1 401 792 0151",
    "sg:postcode":"02882",
    "sg:province":"RI",
    "sg:tags":[
        "communication"
    ],
    "wof:name":"KIMO Communications Inc",
    "wof:placetype":"venue"
},
  "geometry": {"coordinates":[-71.462169,41.428991],"type":"Point"}
}