{
  "type": "Feature",
  "properties": {
    "iso:country":"US",
    "sg:address":"700 Centre of New England Blvd",
    "sg:city":"Coventry",
    "sg:classifiers":[
        {
            "category":"Professional",
            "type":"Services"
        }
    ],
    "sg:phone":"+1 401 822 8211",
    "sg:postcode":"02816",
    "sg:province":"RI",
    "sg:tags":[
        "establishment"
    ],
    "wof:name":"R L Spencer Inc",
    "wof:placetype":"venue"
},
  "geometry": {"coordinates":[-71.570655,41.661921],"type":"Point"}
}