{
  "type": "Feature",
  "properties": {
    "addr:full":"943 Old Hartford Pike North Scituate RI 02857",
    "addr:housenumber":"943",
    "addr:postcode":"02857",
    "addr:street":"Old Hartford Pike",
    "iso:country":"US",
    "sg:address":"943 Old Hartford Pike",
    "sg:city":"North Scituate",
    "sg:phone":"+1 401 934 3173",
    "sg:postcode":"02857",
    "sg:province":"RI",
    "sg:tags":[
        "farm",
        "field",
        "crop"
    ],
    "wof:name":"Carriage House Farm",
    "wof:placetype":"venue"
},
  "geometry": {"coordinates":[-71.64739400000001,41.839561],"type":"Point"}
}