{
  "type": "Feature",
  "properties": {
    "iso:country":"US",
    "sg:address":"16 Miller St",
    "sg:city":"Warren",
    "sg:classifiers":[
        {
            "category":"Social Services",
            "subcategory":"Child Care",
            "type":"Services"
        }
    ],
    "sg:phone":"+1 401 245 2204",
    "sg:postcode":"02885",
    "sg:province":"RI",
    "wof:name":"Carousel Nursery",
    "wof:placetype":"venue"
},
  "geometry": {"coordinates":[-71.283743,41.730987],"type":"Point"}
}