{
  "type": "Feature",
  "properties": {
    "addr:full":"101 N Main St Providence RI 02903",
    "addr:housenumber":"101",
    "addr:postcode":"02903",
    "addr:street":"N Main St",
    "iso:country":"US",
    "sg:address":"101 N Main St",
    "sg:city":"Providence",
    "sg:classifiers":[
        {
            "category":"Restaurant",
            "type":"Food & Drink"
        }
    ],
    "sg:phone":"+1 401 272 3331",
    "sg:postcode":"02903",
    "sg:province":"RI",
    "sg:tags":[
        "seafood"
    ],
    "sg:website":"www.millstavernrestaurant.com/",
    "wof:name":"Mills Tavern",
    "wof:placetype":"venue"
},
  "geometry": {"coordinates":[-71.40920300000001,41.827801],"type":"Point"}
}