{
  "type": "Feature",
  "properties": {
    "iso:country":"US",
    "sg:address":"180 Allens Ave",
    "sg:city":"Providence",
    "sg:classifiers":[
        {
            "category":"Professional",
            "subcategory":"Lawyer & Legal Services",
            "type":"Services"
        }
    ],
    "sg:phone":"+1 401 274 1787",
    "sg:postcode":"02903",
    "sg:province":"RI",
    "sg:tags":[
        "attorney"
    ],
    "wof:name":"Ri State Pier Properties LLC",
    "wof:placetype":"venue"
},
  "geometry": {"coordinates":[-71.403845,41.808879],"type":"Point"}
}