{
  "type": "Feature",
  "properties": {
    "iso:country":"US",
    "sg:address":"358 Newport Ave",
    "sg:city":"Pawtucket",
    "sg:classifiers":[
        {
            "category":"Organizations",
            "subcategory":"Religious Organization",
            "type":"Services"
        }
    ],
    "sg:phone":"+1 401 722 4470",
    "sg:postcode":"02861",
    "sg:province":"RI",
    "wof:name":"Saint Teresa Of Child Jesus",
    "wof:placetype":"venue"
},
  "geometry": {"coordinates":[-71.354395,41.867558],"type":"Point"}
}