{
  "type": "Feature",
  "properties": {
    "iso:country":"US",
    "sg:address":"242 Ives St",
    "sg:city":"Providence",
    "sg:classifiers":[
        {
            "category":"Insurance",
            "subcategory":"Insurance Agent",
            "type":"Services"
        }
    ],
    "sg:phone":"+1 401 421 8794",
    "sg:postcode":"02906",
    "sg:province":"RI",
    "wof:name":"Joels Insurance",
    "wof:placetype":"venue"
},
  "geometry": {"coordinates":[-71.392526,41.824444],"type":"Point"}
}