{
  "type": "Feature",
  "properties": {
    "iso:country":"US",
    "sg:address":"6946 Post Rd",
    "sg:city":"North Kingstown",
    "sg:classifiers":[
        {
            "category":"Real Estate",
            "subcategory":"Real Estate Services",
            "type":"Services"
        }
    ],
    "sg:phone":"+1 401 885 9410",
    "sg:postcode":"02852",
    "sg:province":"RI",
    "sg:tags":[
        "company",
        "title"
    ],
    "wof:name":"Landmark Title & Escrow",
    "wof:placetype":"venue"
},
  "geometry": {"coordinates":[-71.456459,41.609367],"type":"Point"}
}