{
  "type": "Feature",
  "properties": {
    "iso:country":"US",
    "sg:address":"433 1/2 Benefit St",
    "sg:city":"Pawtucket",
    "sg:classifiers":[
        {
            "category":"Bars & Pubs",
            "subcategory":"Nightclub",
            "type":"Food & Drink"
        }
    ],
    "sg:phone":"+1 401 725 9614",
    "sg:postcode":"02861",
    "sg:province":"RI",
    "sg:tags":[
        "nightlife"
    ],
    "wof:name":"Benefit St Pub",
    "wof:placetype":"venue"
},
  "geometry": {"coordinates":[-71.353692,41.892023],"type":"Point"}
}