{
  "type": "Feature",
  "properties": {
    "addr:full":"4 Franklin St Bristol RI 02809",
    "addr:housenumber":"4",
    "addr:postcode":"02809",
    "addr:street":"Franklin St",
    "iso:country":"US",
    "sg:address":"4 Franklin St",
    "sg:city":"Bristol",
    "sg:classifiers":[
        {
            "category":"Retail",
            "subcategory":"Portrait Studio",
            "type":"Services"
        }
    ],
    "sg:phone":"+1 401 253 2351",
    "sg:postcode":"02809",
    "sg:province":"RI",
    "sg:tags":[
        "photography"
    ],
    "sg:website":"www.brigidi-bwphoto.com",
    "wof:name":"Bristol Workshops In Photo",
    "wof:placetype":"venue"
},
  "geometry": {"coordinates":[-71.277777,41.673556],"type":"Point"}
}