{
  "type": "Feature",
  "properties": {
    "iso:country":"US",
    "sg:address":"536 E Main Rd",
    "sg:city":"Middletown",
    "sg:classifiers":[
        {
            "category":"Bakery",
            "type":"Food & Drink"
        },
        {
            "category":"Coffee & Tea",
            "type":"Food & Drink"
        },
        {
            "category":"Bagels",
            "type":"Food & Drink"
        },
        {
            "category":"Donuts",
            "type":"Food & Drink"
        }
    ],
    "sg:menulink":"http://www.allmenus.com/ri/middletown/138841-dunkin-donuts/menu/",
    "sg:phone":"+1 401 849 4516",
    "sg:postcode":"02842",
    "sg:province":"RI",
    "sg:tags":[
        "american",
        "pastry"
    ],
    "wof:name":"Dunkin' Donuts",
    "wof:placetype":"venue"
},
  "geometry": {"coordinates":[-71.282455,41.522165],"type":"Point"}
}