{
  "type": "Feature",
  "properties": {
    "iso:country":"US",
    "sg:address":"170 George Allen Rd",
    "sg:city":"Chepachet",
    "sg:classifiers":[
        {
            "category":"Building & Trades",
            "subcategory":"Construction",
            "type":"Services"
        }
    ],
    "sg:phone":"+1 401 568 2662",
    "sg:postcode":"02814",
    "sg:province":"RI",
    "sg:tags":[
        "house"
    ],
    "wof:name":"St Pierre Home Improvement",
    "wof:placetype":"venue"
},
  "geometry": {"coordinates":[-71.748908,41.875355],"type":"Point"}
}