{
  "type": "Feature",
  "properties": {
    "iso:country":"US",
    "sg:address":"864 Central Ave",
    "sg:city":"Pawtucket",
    "sg:classifiers":[
        {
            "category":"Insurance",
            "subcategory":"Insurance Agent",
            "type":"Services"
        }
    ],
    "sg:phone":"+1 401 725 0763",
    "sg:postcode":"02861",
    "sg:province":"RI",
    "wof:name":"Blanchette Insurance",
    "wof:placetype":"venue"
},
  "geometry": {"coordinates":[-71.35008999999999,41.88896],"type":"Point"}
}