{
  "type": "Feature",
  "properties": {
    "addr:full":"16 Milk St Blackstone RI 01504",
    "addr:housenumber":"16",
    "addr:postcode":"01504",
    "addr:street":"Milk St",
    "iso:country":"US",
    "sg:address":"16 Milk St",
    "sg:city":"Blackstone",
    "sg:classifiers":[
        {
            "category":"Real Estate",
            "subcategory":"Real Estate Agent",
            "type":"Services"
        }
    ],
    "sg:phone":"+1 508 883 2270",
    "sg:postcode":"01504",
    "sg:province":"RI",
    "sg:tags":[
        "management"
    ],
    "wof:name":"Gladu Realty Mgmt",
    "wof:placetype":"venue"
},
  "geometry": {"coordinates":[-71.53652700000001,42.046558],"type":"Point"}
}