{
  "type": "Feature",
  "properties": {
    "iso:country":"US",
    "sg:address":"330 Camp St",
    "sg:city":"Providence",
    "sg:classifiers":[
        {
            "category":"Government",
            "subcategory":"Office",
            "type":"Public Place"
        }
    ],
    "sg:phone":"+1 401 275 4200",
    "sg:postcode":"02906",
    "sg:province":"RI",
    "wof:name":"US Property & Fiscal Officer",
    "wof:placetype":"venue"
},
  "geometry": {"coordinates":[-71.40088299999999,41.848859],"type":"Point"}
}