{
  "type": "Feature",
  "properties": {
    "iso:country":"US",
    "sg:address":"2224 Flat River Rd",
    "sg:city":"Coventry",
    "sg:classifiers":[
        {
            "category":"Retail",
            "subcategory":"Auto Repair",
            "type":"Services"
        }
    ],
    "sg:phone":"+1 401 397 3946",
    "sg:postcode":"02816",
    "sg:province":"RI",
    "sg:tags":[
        "repairing",
        "automobile"
    ],
    "wof:name":"Wayne's Garage",
    "wof:placetype":"venue"
},
  "geometry": {"coordinates":[-71.614994,41.70457],"type":"Point"}
}