{
  "type": "Feature",
  "properties": {
    "iso:country":"US",
    "sg:address":"1 Fair St",
    "sg:city":"Providence",
    "sg:classifiers":[
        {
            "category":"Government",
            "subcategory":"Office",
            "type":"Public Place"
        }
    ],
    "sg:phone":"+1 401 222 2271",
    "sg:postcode":"02908",
    "sg:province":"RI",
    "sg:tags":[
        "state",
        "taxation"
    ],
    "wof:name":"Accounts & Control Office",
    "wof:placetype":"venue"
},
  "geometry": {"coordinates":[-71.440659,41.851807],"type":"Point"}
}