{
  "type": "Feature",
  "properties": {
    "addr:full":"55 Huguenot Dr East Greenwich RI 02818",
    "addr:housenumber":"55",
    "addr:postcode":"02818",
    "addr:street":"Huguenot Dr",
    "iso:country":"US",
    "sg:address":"55 Huguenot Dr",
    "sg:city":"East Greenwich",
    "sg:classifiers":[
        {
            "category":"Professional",
            "subcategory":"Business Services",
            "type":"Services"
        }
    ],
    "sg:phone":"+1 401 885 3109",
    "sg:postcode":"02818",
    "sg:province":"RI",
    "wof:name":"Richard A Genga Jr",
    "wof:placetype":"venue"
},
  "geometry": {"coordinates":[-71.503013,41.629136],"type":"Point"}
}