{
  "type": "Feature",
  "properties": {
    "addr:full":"50 Okeefe Ln Warwick RI 02888",
    "addr:housenumber":"50",
    "addr:postcode":"02888",
    "addr:street":"Okeefe Ln",
    "iso:country":"US",
    "sg:address":"50 Okeefe Ln",
    "sg:city":"Warwick",
    "sg:classifiers":[
        {
            "category":"Freight",
            "type":"Transportation"
        }
    ],
    "sg:phone":"+1 401 785 9550",
    "sg:postcode":"02888",
    "sg:province":"RI",
    "sg:tags":[
        "general"
    ],
    "wof:name":"EZ Mini Storage",
    "wof:placetype":"venue"
},
  "geometry": {"coordinates":[-71.436026,41.757846],"type":"Point"}
}