{
  "type": "Feature",
  "properties": {
    "iso:country":"US",
    "sg:address":"9 Champlin Ter",
    "sg:city":"Middletown",
    "sg:classifiers":[
        {
            "category":"Retail",
            "subcategory":"Repair Shop",
            "type":"Services"
        }
    ],
    "sg:phone":"+1 401 849 6659",
    "sg:postcode":"02842",
    "sg:province":"RI",
    "wof:name":"Clean Cut Sharpening Services",
    "wof:placetype":"venue"
},
  "geometry": {"coordinates":[-71.289559,41.530572],"type":"Point"}
}