{
  "type": "Feature",
  "properties": {
    "iso:country":"US",
    "sg:address":"11 Comstock Pkwy",
    "sg:city":"Cranston",
    "sg:classifiers":[
        {
            "category":"Manufacturing",
            "subcategory":"Jewelry",
            "type":"Manufacturing & Wholesale Goods"
        }
    ],
    "sg:phone":"+1 401 944 9230",
    "sg:postcode":"02921",
    "sg:province":"RI",
    "sg:tags":[
        "mfg",
        "novelty",
        "except",
        "costume"
    ],
    "wof:name":"Modern Jewelry",
    "wof:placetype":"venue"
},
  "geometry": {"coordinates":[-71.51609999999999,41.787395],"type":"Point"}
}