{
  "type": "Feature",
  "properties": {
    "iso:country":"US",
    "sg:address":"3 N View Ter",
    "sg:city":"North Providence",
    "sg:classifiers":[
        {
            "category":"Restaurant",
            "type":"Food & Drink"
        }
    ],
    "sg:phone":"+1 401 233 0733",
    "sg:postcode":"02911",
    "sg:province":"RI",
    "sg:tags":[
        "eating"
    ],
    "wof:name":"Fire House Diner",
    "wof:placetype":"venue"
},
  "geometry": {"coordinates":[-71.478414,41.861318],"type":"Point"}
}