{
  "type": "Feature",
  "properties": {
    "iso:country":"US",
    "sg:address":"725 Reservoir Ave",
    "sg:city":"Cranston",
    "sg:classifiers":[
        {
            "category":"Health Services",
            "subcategory":"Doctor",
            "type":"Services"
        }
    ],
    "sg:phone":"+1 401 944 1052",
    "sg:postcode":"02910",
    "sg:province":"RI",
    "sg:tags":[
        "physician",
        "surgeon"
    ],
    "wof:name":"Mohammed Abiri Inc",
    "wof:placetype":"venue"
},
  "geometry": {"coordinates":[-71.442457,41.780326],"type":"Point"}
}