{
  "type": "Feature",
  "properties": {
    "iso:country":"US",
    "sg:address":"45 Prospect St",
    "sg:city":"Providence",
    "sg:classifiers":[
        {
            "category":"Education",
            "subcategory":"University",
            "type":"Public Place"
        }
    ],
    "sg:phone":"+1 401 831 0260",
    "sg:postcode":"02912",
    "sg:province":"RI",
    "sg:tags":[
        "college"
    ],
    "wof:name":"Brown University",
    "wof:placetype":"venue"
},
  "geometry": {"coordinates":[-71.404743,41.827509],"type":"Point"}
}