{
  "type": "Feature",
  "properties": {
    "addr:full":"363 Broad St Cumberland RI 02864",
    "addr:housenumber":"363",
    "addr:postcode":"02864",
    "addr:street":"Broad St",
    "iso:country":"US",
    "sg:address":"363 Broad St",
    "sg:city":"Cumberland",
    "sg:classifiers":[
        {
            "category":"Personal",
            "subcategory":"Barber",
            "type":"Services"
        }
    ],
    "sg:phone":"+1 401 728 5838",
    "sg:postcode":"02864",
    "sg:province":"RI",
    "wof:name":"Hillside Barber Shop",
    "wof:placetype":"venue"
},
  "geometry": {"coordinates":[-71.39476500000001,41.910004],"type":"Point"}
}