{
  "type": "Feature",
  "properties": {
    "iso:country":"US",
    "sg:address":"10 Redwood Dr",
    "sg:city":"North Providence",
    "sg:classifiers":[
        {
            "category":"Shopping",
            "subcategory":"Bicycles & Sporting Goods",
            "type":"Retail Goods"
        }
    ],
    "sg:phone":"+1 401 232 9949",
    "sg:postcode":"02911",
    "sg:province":"RI",
    "wof:name":"Audino Enterprises Inc",
    "wof:placetype":"venue"
},
  "geometry": {"coordinates":[-71.454199,41.852221],"type":"Point"}
}