{
  "type": "Feature",
  "properties": {
    "iso:country":"US",
    "sg:address":"35 High St",
    "sg:city":"Westerly",
    "sg:classifiers":[
        {
            "category":"Arts & Performance",
            "subcategory":"Theater",
            "type":"Entertainment"
        }
    ],
    "sg:phone":"+1 401 596 4600",
    "sg:postcode":"02891",
    "sg:province":"RI",
    "sg:tags":[
        "musician"
    ],
    "wof:name":"Musica Dolce Chamber Orchestra",
    "wof:placetype":"venue"
},
  "geometry": {"coordinates":[-71.829992,41.378732],"type":"Point"}
}