{
  "type": "Feature",
  "properties": {
    "iso:country":"US",
    "sg:address":"529 Switch Rd",
    "sg:city":"Wood River Jct",
    "sg:classifiers":[
        {
            "category":"School Buses",
            "type":"Transportation"
        }
    ],
    "sg:phone":"+1 401 364 3702",
    "sg:postcode":"02894",
    "sg:province":"RI",
    "wof:name":"Laidlaw Education Svc",
    "wof:placetype":"venue"
},
  "geometry": {"coordinates":[-71.694113,41.440014],"type":"Point"}
}