{
  "type": "Feature",
  "properties": {
    "addr:full":"53 Bittersweet Ln Wakefield RI 02879",
    "addr:housenumber":"53",
    "addr:postcode":"02879",
    "addr:street":"Bittersweet Ln",
    "iso:country":"US",
    "sg:address":"53 Bittersweet Ln",
    "sg:city":"Wakefield",
    "sg:classifiers":[
        {
            "category":"Professional",
            "subcategory":"Lawyer & Legal Services",
            "type":"Services"
        }
    ],
    "sg:phone":"+1 401 792 2285",
    "sg:postcode":"02879",
    "sg:province":"RI",
    "sg:tags":[
        "attorney"
    ],
    "wof:name":"Kirshenbaum & Kirshenbaum",
    "wof:placetype":"venue"
},
  "geometry": {"coordinates":[-71.523231,41.453171],"type":"Point"}
}