{
  "type": "Feature",
  "properties": {
    "iso:country":"US",
    "sg:address":"501 Main St",
    "sg:city":"Warren",
    "sg:classifiers":[
        {
            "category":"Restaurant",
            "type":"Food & Drink"
        }
    ],
    "sg:phone":"+1 401 247 9890",
    "sg:postcode":"02885",
    "sg:province":"RI",
    "sg:tags":[
        "eating"
    ],
    "wof:name":"Red Cap Investments",
    "wof:placetype":"venue"
},
  "geometry": {"coordinates":[-71.28237799999999,41.729328],"type":"Point"}
}