{
  "type": "Feature",
  "properties": {
    "iso:country":"US",
    "sg:address":"190 Newport Ave",
    "sg:city":"Rumford",
    "sg:classifiers":[
        {
            "category":"Shopping",
            "subcategory":"Mobile Phones",
            "type":"Retail Goods"
        }
    ],
    "sg:phone":"+1 401 383 1902",
    "sg:postcode":"02916",
    "sg:province":"RI",
    "wof:name":"Metro Wireless",
    "wof:placetype":"venue"
},
  "geometry": {"coordinates":[-71.354193,41.854642],"type":"Point"}
}