{
  "type": "Feature",
  "properties": {
    "addr:full":"33 Greenwich St Providence RI 02907",
    "addr:housenumber":"33",
    "addr:postcode":"02907",
    "addr:street":"Greenwich St",
    "iso:country":"US",
    "sg:address":"33 Greenwich St",
    "sg:city":"Providence",
    "sg:classifiers":[
        {
            "category":"Real Estate",
            "subcategory":"Real Estate Agent",
            "type":"Services"
        }
    ],
    "sg:phone":"+1 401 228 8088",
    "sg:postcode":"02907",
    "sg:province":"RI",
    "wof:name":"Gammons Realty",
    "wof:placetype":"venue"
},
  "geometry": {"coordinates":[-71.426868,41.802428],"type":"Point"}
}