{
  "type": "Feature",
  "properties": {
    "iso:country":"US",
    "sg:address":"171 Jenckes Hill Rd",
    "sg:city":"Lincoln",
    "sg:classifiers":[
        {
            "category":"Organizations",
            "subcategory":"Professional Association",
            "type":"Services"
        }
    ],
    "sg:phone":"+1 401 333 1492",
    "sg:postcode":"02865",
    "sg:province":"RI",
    "wof:name":"Columbus Club Of Lincoln Inc",
    "wof:placetype":"venue"
},
  "geometry": {"coordinates":[-71.472167,41.910789],"type":"Point"}
}