{
  "type": "Feature",
  "properties": {
    "iso:country":"US",
    "sg:address":"27 Douglas St",
    "sg:city":"Jamestown",
    "sg:classifiers":[
        {
            "category":"Professional",
            "subcategory":"Management & Consulting",
            "type":"Services"
        }
    ],
    "sg:phone":"+1 401 423 1155",
    "sg:postcode":"02835",
    "sg:province":"RI",
    "sg:tags":[
        "consultant",
        "business"
    ],
    "wof:name":"Action Associates",
    "wof:placetype":"venue"
},
  "geometry": {"coordinates":[-71.373757,41.498157],"type":"Point"}
}