{
  "type": "Feature",
  "properties": {
    "addr:full":"33 Maple St North Providence RI 02911",
    "addr:housenumber":"33",
    "addr:postcode":"02911",
    "addr:street":"Maple St",
    "iso:country":"US",
    "sg:address":"33 Maple St",
    "sg:city":"North Providence",
    "sg:classifiers":[
        {
            "category":"Social Services",
            "subcategory":"Child Care",
            "type":"Services"
        }
    ],
    "sg:phone":"+1 401 444 0769",
    "sg:postcode":"02911",
    "sg:province":"RI",
    "sg:tags":[
        "day"
    ],
    "wof:name":"Early Years Learning Centers",
    "wof:placetype":"venue"
},
  "geometry": {"coordinates":[-71.479799,41.848004],"type":"Point"}
}