{
  "type": "Feature",
  "properties": {
    "addr:full":"12 Hopkins Hill Rd Coventry RI 02816",
    "addr:housenumber":"12",
    "addr:postcode":"02816",
    "addr:street":"Hopkins Hill Rd",
    "iso:country":"US",
    "sg:address":"12 Hopkins Hill Rd",
    "sg:city":"Coventry",
    "sg:classifiers":[
        {
            "category":"Manufacturing",
            "subcategory":"Jewelry",
            "type":"Manufacturing & Wholesale Goods"
        }
    ],
    "sg:phone":"+1 401 823 7163",
    "sg:postcode":"02816",
    "sg:province":"RI",
    "sg:tags":[
        "costume",
        "mfg"
    ],
    "wof:name":"A-Ok Industries",
    "wof:placetype":"venue"
},
  "geometry": {"coordinates":[-71.568191,41.680935],"type":"Point"}
}