{
  "type": "Feature",
  "properties": {
    "addr:full":"9 Lake Ct Ashaway RI 02804",
    "addr:housenumber":"9",
    "addr:postcode":"02804",
    "addr:street":"Lake Ct",
    "iso:country":"US",
    "sg:address":"9 Lake Ct",
    "sg:city":"Ashaway",
    "sg:classifiers":[
        {
            "category":"Building & Trades",
            "subcategory":"Electrical",
            "type":"Services"
        }
    ],
    "sg:phone":"+1 401 377 2910",
    "sg:postcode":"02804",
    "sg:province":"RI",
    "sg:tags":[
        "electrical",
        "contractor"
    ],
    "wof:name":"Bruce Kenyon Electrical C",
    "wof:placetype":"venue"
},
  "geometry": {"coordinates":[-71.79149099999999,41.423903],"type":"Point"}
}