{
  "type": "Feature",
  "properties": {
    "iso:country":"US",
    "sg:address":"222 Richmond St",
    "sg:city":"Providence",
    "sg:classifiers":[
        {
            "category":"Professional",
            "subcategory":"Employment Agencies",
            "type":"Services"
        }
    ],
    "sg:phone":"+1 401 421 0488",
    "sg:postcode":"02903",
    "sg:province":"RI",
    "sg:tags":[
        "opportunity"
    ],
    "wof:name":"Talent Tree",
    "wof:placetype":"venue"
},
  "geometry": {"coordinates":[-71.40886999999999,41.818986],"type":"Point"}
}