{
  "type": "Feature",
  "properties": {
    "iso:country":"US",
    "sg:address":"19 Luther Ave",
    "sg:city":"Warwick",
    "sg:classifiers":[
        {
            "category":"Communications",
            "subcategory":"Radio Station",
            "type":"Services"
        }
    ],
    "sg:phone":"+1 401 737 0700",
    "sg:postcode":"02886",
    "sg:province":"RI",
    "sg:tags":[
        "broadcast",
        "organization",
        "religious"
    ],
    "sg:website":"www.warv.net",
    "wof:name":"WARV",
    "wof:placetype":"venue"
},
  "geometry": {"coordinates":[-71.45975,41.701554],"type":"Point"}
}