{
  "type": "Feature",
  "properties": {
    "addr:full":"1778 Mineral Spring Ave North Providence RI 02904",
    "addr:housenumber":"1778",
    "addr:postcode":"02904",
    "addr:street":"Mineral Spring Ave",
    "iso:country":"US",
    "sg:address":"1778 Mineral Spring Ave",
    "sg:city":"North Providence",
    "sg:classifiers":[
        {
            "category":"Restaurant",
            "type":"Food & Drink"
        }
    ],
    "sg:phone":"+1 401 353 5560",
    "sg:postcode":"02904",
    "sg:province":"RI",
    "sg:tags":[
        "pizza"
    ],
    "wof:name":"Pizza Hut",
    "wof:placetype":"venue"
},
  "geometry": {"coordinates":[-71.457328,41.862326],"type":"Point"}
}