{
  "type": "Feature",
  "properties": {
    "iso:country":"US",
    "sg:address":"76 Jerry Ln",
    "sg:city":"North Kingstown",
    "sg:classifiers":[
        {
            "category":"Building & Trades",
            "subcategory":"Construction",
            "type":"Services"
        }
    ],
    "sg:phone":"+1 401 884 0692",
    "sg:postcode":"02852",
    "sg:province":"RI",
    "sg:tags":[
        "painter"
    ],
    "wof:name":"Allstate Sandblasting Corp",
    "wof:placetype":"venue"
},
  "geometry": {"coordinates":[-71.442177,41.612594],"type":"Point"}
}