{
  "type": "Feature",
  "properties": {
    "iso:country":"US",
    "sg:address":"3 Indigo Farm Rd",
    "sg:city":"Harrisville",
    "sg:classifiers":[
        {
            "category":"Professional",
            "subcategory":"Management & Consulting",
            "type":"Services"
        }
    ],
    "sg:phone":"+1 401 769 4248",
    "sg:postcode":"02830",
    "sg:province":"RI",
    "sg:tags":[
        "marketing"
    ],
    "wof:name":"Extreme Sales and Mktg LLC",
    "wof:placetype":"venue"
},
  "geometry": {"coordinates":[-71.589455,41.939156],"type":"Point"}
}