{
  "type": "Feature",
  "properties": {
    "addr:full":"1088 Bald Hill Rd Warwick RI 02886",
    "addr:housenumber":"1088",
    "addr:postcode":"02886",
    "addr:street":"Bald Hill Rd",
    "iso:country":"US",
    "sg:address":"1088 Bald Hill Rd",
    "sg:city":"Warwick",
    "sg:classifiers":[
        {
            "category":"Personal",
            "subcategory":"Beauty Salon",
            "type":"Services"
        }
    ],
    "sg:phone":"+1 401 828 2199",
    "sg:postcode":"02886",
    "sg:province":"RI",
    "sg:tags":[
        "manicuring"
    ],
    "wof:name":"Hollywood Nails",
    "wof:placetype":"venue"
},
  "geometry": {"coordinates":[-71.493236,41.704536],"type":"Point"}
}