{
  "type": "Feature",
  "properties": {
    "iso:country":"US",
    "sg:address":"716 S County Trl",
    "sg:city":"Exeter",
    "sg:classifiers":[
        {
            "category":"Home & Garden",
            "subcategory":"Building Materials",
            "type":"Retail Goods"
        }
    ],
    "sg:phone":"+1 401 295 2770",
    "sg:postcode":"02822",
    "sg:province":"RI",
    "sg:tags":[
        "center"
    ],
    "wof:name":"Gillette's Home & Garden",
    "wof:placetype":"venue"
},
  "geometry": {"coordinates":[-71.55486399999999,41.517404],"type":"Point"}
}