{
  "type": "Feature",
  "properties": {
    "iso:country":"US",
    "sg:address":"35 Airport Rd",
    "sg:city":"Warwick",
    "sg:classifiers":[
        {
            "category":"Education",
            "subcategory":"Dance Studio",
            "type":"Public Place"
        }
    ],
    "sg:phone":"+1 401 732 0439",
    "sg:postcode":"02889",
    "sg:province":"RI",
    "sg:tags":[
        "instruction",
        "dancing"
    ],
    "wof:name":"Damhsa Irish Dance Studio",
    "wof:placetype":"venue"
},
  "geometry": {"coordinates":[-71.408828,41.733459],"type":"Point"}
}