{
  "type": "Feature",
  "properties": {
    "addr:full":"750 Aquidneck Ave Middletown RI 02842",
    "addr:housenumber":"750",
    "addr:postcode":"02842",
    "addr:street":"Aquidneck Ave",
    "iso:country":"US",
    "sg:address":"750 Aquidneck Ave",
    "sg:city":"Middletown",
    "sg:classifiers":[
        {
            "category":"Retail",
            "subcategory":"Laundry & Dry Cleaning",
            "type":"Services"
        }
    ],
    "sg:phone":"+1 401 847 0500",
    "sg:postcode":"02842",
    "sg:province":"RI",
    "wof:name":"Sams Plaza Cleaner",
    "wof:placetype":"venue"
},
  "geometry": {"coordinates":[-71.28258599999999,41.508925],"type":"Point"}
}