{
  "type": "Feature",
  "properties": {
    "iso:country":"US",
    "sg:address":"1228 Main St",
    "sg:city":"West Warwick",
    "sg:classifiers":[
        {
            "category":"Real Estate",
            "subcategory":"Real Estate Agent",
            "type":"Services"
        }
    ],
    "sg:phone":"+1 401 828 1333",
    "sg:postcode":"02893",
    "sg:province":"RI",
    "wof:name":"Rustic Realty",
    "wof:placetype":"venue"
},
  "geometry": {"coordinates":[-71.524157,41.704378],"type":"Point"}
}