{
  "type": "Feature",
  "properties": {
    "addr:full":"2 Alves St Bristol RI 02809",
    "addr:housenumber":"2",
    "addr:postcode":"02809",
    "addr:street":"Alves St",
    "iso:country":"US",
    "sg:address":"2 Alves St",
    "sg:city":"Bristol",
    "sg:classifiers":[
        {
            "category":"Retail",
            "subcategory":"Repair Shop",
            "type":"Services"
        }
    ],
    "sg:phone":"+1 401 253 5797",
    "sg:postcode":"02809",
    "sg:province":"RI",
    "sg:tags":[
        "related"
    ],
    "wof:name":"All Kinds Of Repairs",
    "wof:placetype":"venue"
},
  "geometry": {"coordinates":[-71.25442200000001,41.680138],"type":"Point"}
}