{
  "type": "Feature",
  "properties": {
    "addr:full":"38 Selkirk Rd Providence RI 02905",
    "addr:housenumber":"38",
    "addr:postcode":"02905",
    "addr:street":"Selkirk Rd",
    "iso:country":"US",
    "sg:address":"38 Selkirk Rd",
    "sg:city":"Providence",
    "sg:classifiers":[
        {
            "category":"Professional",
            "subcategory":"Business Services",
            "type":"Services"
        }
    ],
    "sg:phone":"+1 401 941 5628",
    "sg:postcode":"02905",
    "sg:province":"RI",
    "sg:tags":[
        "interior",
        "company",
        "design",
        "holding",
        "for"
    ],
    "wof:name":"Canterbury Partners Inc",
    "wof:placetype":"venue"
},
  "geometry": {"coordinates":[-71.39060600000001,41.768561],"type":"Point"}
}