{
  "type": "Feature",
  "properties": {
    "iso:country":"US",
    "sg:address":"146 Water St",
    "sg:city":"Warren",
    "sg:classifiers":[
        {
            "category":"Personal",
            "subcategory":"Beauty Salon",
            "type":"Services"
        }
    ],
    "sg:phone":"+1 401 245 0640",
    "sg:postcode":"02885",
    "sg:province":"RI",
    "wof:name":"Scott's Studio",
    "wof:placetype":"venue"
},
  "geometry": {"coordinates":[-71.285229,41.732667],"type":"Point"}
}