{
  "type": "Feature",
  "properties": {
    "iso:country":"US",
    "sg:address":"59 Pinecrest Dr",
    "sg:city":"Pawtucket",
    "sg:classifiers":[
        {
            "category":"Building & Trades",
            "subcategory":"Construction",
            "type":"Services"
        }
    ],
    "sg:phone":"+1 401 726 4520",
    "sg:postcode":"02861",
    "sg:province":"RI",
    "sg:tags":[
        "floral",
        "instruction",
        "design"
    ],
    "wof:name":"Handcrafts And Sweet Toot",
    "wof:placetype":"venue"
},
  "geometry": {"coordinates":[-71.34143,41.892517],"type":"Point"}
}