{
  "type": "Feature",
  "properties": {
    "addr:full":"78 Mawney St East Greenwich RI 02818",
    "addr:housenumber":"78",
    "addr:postcode":"02818",
    "addr:street":"Mawney St",
    "iso:country":"US",
    "sg:address":"78 Mawney St",
    "sg:city":"East Greenwich",
    "sg:classifiers":[
        {
            "category":"Building & Trades",
            "subcategory":"Construction",
            "type":"Services"
        }
    ],
    "sg:phone":"+1 401 884 3058",
    "sg:postcode":"02818",
    "sg:province":"RI",
    "sg:tags":[
        "hanging",
        "contractor"
    ],
    "wof:name":"Professional Painters of RI",
    "wof:placetype":"venue"
},
  "geometry": {"coordinates":[-71.45465799999999,41.660351],"type":"Point"}
}