{
  "type": "Feature",
  "properties": {
    "iso:country":"US",
    "sg:address":"104 School St",
    "sg:city":"North Kingstown",
    "sg:classifiers":[
        {
            "category":"Travel",
            "subcategory":"Hotels & Motels",
            "type":"Entertainment"
        }
    ],
    "sg:phone":"+1 401 885 1712",
    "sg:postcode":"02852",
    "sg:province":"RI",
    "sg:tags":[
        "breakfast",
        "accommodation",
        "bed"
    ],
    "wof:name":"Mrs B's Bed & Breakfast",
    "wof:placetype":"venue"
},
  "geometry": {"coordinates":[-71.462377,41.621747],"type":"Point"}
}