{
  "type": "Feature",
  "properties": {
    "iso:country":"US",
    "sg:address":"52 Fieldview Dr",
    "sg:city":"Warwick",
    "sg:classifiers":[
        {
            "category":"Building & Trades",
            "subcategory":"Pest Control",
            "type":"Services"
        }
    ],
    "sg:phone":"+1 401 732 4518",
    "sg:postcode":"02886",
    "sg:province":"RI",
    "wof:name":"Atlantic Pest Control",
    "wof:placetype":"venue"
},
  "geometry": {"coordinates":[-71.438799,41.716863],"type":"Point"}
}