{
  "type": "Feature",
  "properties": {
    "iso:country":"US",
    "sg:address":"1150 Pontiac Ave",
    "sg:city":"Cranston",
    "sg:classifiers":[
        {
            "category":"Organizations",
            "subcategory":"Professional Association",
            "type":"Services"
        }
    ],
    "sg:phone":"+1 401 943 8888",
    "sg:postcode":"02920",
    "sg:province":"RI",
    "sg:website":"www.leukemia.org",
    "wof:name":"Leukemia & Lymphoma Society",
    "wof:placetype":"venue"
},
  "geometry": {"coordinates":[-71.450374,41.752869],"type":"Point"}
}