{
  "type": "Feature",
  "properties": {
    "iso:country":"US",
    "sg:address":"328 Atwells Ave",
    "sg:city":"Providence",
    "sg:classifiers":[
        {
            "category":"Shopping",
            "subcategory":"Optician",
            "type":"Retail Goods"
        }
    ],
    "sg:phone":"+1 401 273 2586",
    "sg:postcode":"02909",
    "sg:province":"RI",
    "sg:tags":[
        "eyewear"
    ],
    "sg:website":"westsideeyewear.com",
    "wof:name":"Westside Eyewear Boutique",
    "wof:placetype":"venue"
},
  "geometry": {"coordinates":[-71.428551,41.823563],"type":"Point"}
}