{
  "type": "Feature",
  "properties": {
    "addr:full":"50 Pietila Rd Charlestown RI 02813",
    "addr:housenumber":"50",
    "addr:postcode":"02813",
    "addr:street":"Pietila Rd",
    "iso:country":"US",
    "sg:address":"50 Pietila Rd",
    "sg:city":"Charlestown",
    "sg:classifiers":[
        {
            "category":"Real Estate",
            "subcategory":"Developer",
            "type":"Services"
        }
    ],
    "sg:phone":"+1 401 364 6210",
    "sg:postcode":"02813",
    "sg:province":"RI",
    "wof:name":"Beechwood Enterprises",
    "wof:placetype":"venue"
},
  "geometry": {"coordinates":[-71.634063,41.423975],"type":"Point"}
}