{
  "type": "Feature",
  "properties": {
    "iso:country":"US",
    "sg:address":"977 Mineral Spring Ave",
    "sg:city":"North Providence",
    "sg:classifiers":[
        {
            "category":"Personal",
            "subcategory":"Nail Salon",
            "type":"Services"
        }
    ],
    "sg:phone":"+1 401 723 6570",
    "sg:postcode":"02904",
    "sg:province":"RI",
    "wof:name":"Get Nailed Hair",
    "wof:placetype":"venue"
},
  "geometry": {"coordinates":[-71.421718,41.869496],"type":"Point"}
}