{
  "type": "Feature",
  "properties": {
    "iso:country":"US",
    "sg:address":"11 Spring St",
    "sg:city":"West Warwick",
    "sg:classifiers":[
        {
            "category":"Building & Trades",
            "subcategory":"Construction",
            "type":"Services"
        }
    ],
    "sg:phone":"+1 401 821 9914",
    "sg:postcode":"02893",
    "sg:province":"RI",
    "sg:tags":[
        "masonry",
        "contractor"
    ],
    "wof:name":"East Coast Masonary Contrs",
    "wof:placetype":"venue"
},
  "geometry": {"coordinates":[-71.521587,41.685673],"type":"Point"}
}