{
  "type": "Feature",
  "properties": {
    "addr:full":"24 Addy Dr Bristol RI 02809",
    "addr:housenumber":"24",
    "addr:postcode":"02809",
    "addr:street":"Addy Dr",
    "iso:country":"US",
    "sg:address":"24 Addy Dr",
    "sg:city":"Bristol",
    "sg:classifiers":[
        {
            "category":"Professional",
            "subcategory":"Art Services",
            "type":"Services"
        }
    ],
    "sg:phone":"+1 401 253 3755",
    "sg:postcode":"02809",
    "sg:province":"RI",
    "sg:tags":[
        "photography",
        "commercial"
    ],
    "wof:name":"Picture This",
    "wof:placetype":"venue"
},
  "geometry": {"coordinates":[-71.258279,41.692361],"type":"Point"}
}