{
  "type": "Feature",
  "properties": {
    "iso:country":"US",
    "sg:address":"99 Burnt Hill Rd",
    "sg:city":"Hope",
    "sg:classifiers":[
        {
            "category":"Farming",
            "subcategory":"Orchard",
            "type":"Manufacturing & Wholesale Goods"
        }
    ],
    "sg:phone":"+1 401 821 6561",
    "sg:postcode":"02831",
    "sg:province":"RI",
    "wof:name":"Hazard Brothers Orchard",
    "wof:placetype":"venue"
},
  "geometry": {"coordinates":[-71.59678099999999,41.741579],"type":"Point"}
}