{
  "type": "Feature",
  "properties": {
    "addr:full":"171 Frenchtown Rd North Kingstown RI 02852",
    "addr:housenumber":"171",
    "addr:postcode":"02852",
    "addr:street":"Frenchtown Rd",
    "iso:country":"US",
    "sg:address":"171 Frenchtown Rd",
    "sg:city":"North Kingstown",
    "sg:classifiers":[
        {
            "category":"Autos & Motor Vehicles",
            "subcategory":"Automobile Sales",
            "type":"Retail Goods"
        }
    ],
    "sg:phone":"+1 401 885 4448",
    "sg:postcode":"02852",
    "sg:province":"RI",
    "sg:tags":[
        "car",
        "dealer"
    ],
    "wof:name":"Frenchtown Auto Sales & Lsng",
    "wof:placetype":"venue"
},
  "geometry": {"coordinates":[-71.46818500000001,41.632813],"type":"Point"}
}