{
  "type": "Feature",
  "properties": {
    "addr:full":"1500 Diamond Hill Rd Ste 2 Woonsocket RI 02895",
    "addr:housenumber":"1500",
    "addr:postcode":"02895",
    "addr:street":"Diamond Hill Rd Ste 2",
    "iso:country":"US",
    "sg:address":"1500 Diamond Hill Rd Ste 2",
    "sg:city":"Woonsocket",
    "sg:classifiers":[
        {
            "category":"Banks & Credit Unions",
            "subcategory":"Financial Services",
            "type":"Services"
        }
    ],
    "sg:phone":"+1 401 767 2155",
    "sg:postcode":"02895",
    "sg:province":"RI",
    "sg:tags":[
        "financing",
        "cashing",
        "money",
        "loan",
        "check",
        "payday",
        "order"
    ],
    "sg:website":"http://ad.doubleclick.net/clk;225053199;48888911;w?http://www.checkngo.com?source=yellowpages&cat=TLs&AfsCampaignId=642",
    "wof:name":"Check 'n Go",
    "wof:placetype":"venue"
},
  "geometry": {"coordinates":[-71.481313,42.0158],"type":"Point"}
}