{
  "type": "Feature",
  "properties": {
    "iso:country":"US",
    "sg:address":"27 Ricks Rd",
    "sg:city":"Charlestown",
    "sg:classifiers":[
        {
            "category":"Shopping",
            "subcategory":"Gifts & Souvenirs",
            "type":"Retail Goods"
        }
    ],
    "sg:phone":"+1 401 364 9314",
    "sg:postcode":"02813",
    "sg:province":"RI",
    "wof:name":"T&D Trading Post",
    "wof:placetype":"venue"
},
  "geometry": {"coordinates":[-71.67740499999999,41.383469],"type":"Point"}
}