{
  "type": "Feature",
  "properties": {
    "addr:full":"475 Old Mill Rd Charlestown RI 02813",
    "addr:housenumber":"475",
    "addr:postcode":"02813",
    "addr:street":"Old Mill Rd",
    "iso:country":"US",
    "sg:address":"475 Old Mill Rd",
    "sg:city":"Charlestown",
    "sg:classifiers":[
        {
            "category":"Building & Trades",
            "subcategory":"Construction",
            "type":"Services"
        }
    ],
    "sg:phone":"+1 401 364 1620",
    "sg:postcode":"02813",
    "sg:province":"RI",
    "sg:tags":[
        "contractor"
    ],
    "wof:name":"Simmons Masonry Inc",
    "wof:placetype":"venue"
},
  "geometry": {"coordinates":[-71.662614,41.433604],"type":"Point"}
}