{
  "type": "Feature",
  "properties": {
    "iso:country":"US",
    "sg:address":"329 Broadway",
    "sg:city":"Providence",
    "sg:classifiers":[
        {
            "category":"Professional",
            "subcategory":"Business Services",
            "type":"Services"
        }
    ],
    "sg:phone":"+1 401 861 6093",
    "sg:postcode":"02909",
    "sg:province":"RI",
    "wof:name":"Richardson Design Inc",
    "wof:placetype":"venue"
},
  "geometry": {"coordinates":[-71.42903099999999,41.819981],"type":"Point"}
}