{
  "type": "Feature",
  "properties": {
    "iso:country":"US",
    "sg:address":"116 Hartford Ave",
    "sg:city":"Providence",
    "sg:classifiers":[
        {
            "category":"Retail",
            "subcategory":"Auto Repair",
            "type":"Services"
        }
    ],
    "sg:phone":"+1 401 831 4800",
    "sg:postcode":"02909",
    "sg:province":"RI",
    "wof:name":"Grasso's Service",
    "wof:placetype":"venue"
},
  "geometry": {"coordinates":[-71.44596,41.816778],"type":"Point"}
}