{
  "type": "Feature",
  "properties": {
    "addr:full":"57 Sweet Fern Ln Wakefield RI 02879",
    "addr:housenumber":"57",
    "addr:postcode":"02879",
    "addr:street":"Sweet Fern Ln",
    "iso:country":"US",
    "sg:address":"57 Sweet Fern Ln",
    "sg:city":"Wakefield",
    "sg:classifiers":[
        {
            "category":"Building & Trades",
            "subcategory":"Electrical",
            "type":"Services"
        }
    ],
    "sg:phone":"+1 401 789 3883",
    "sg:postcode":"02879",
    "sg:province":"RI",
    "sg:tags":[
        "electric",
        "contractor"
    ],
    "wof:name":"Jedi Enterprises",
    "wof:placetype":"venue"
},
  "geometry": {"coordinates":[-71.504036,41.451862],"type":"Point"}
}