{
  "type": "Feature",
  "properties": {
    "iso:country":"US",
    "sg:address":"365 Eddy St",
    "sg:city":"Providence",
    "sg:classifiers":[
        {
            "category":"Wholesale",
            "subcategory":"Medical Equipment & Supplies",
            "type":"Manufacturing & Wholesale Goods"
        },
        {
            "category":"Wholesale",
            "subcategory":"Drugs",
            "type":"Manufacturing & Wholesale Goods"
        }
    ],
    "sg:phone":"+1 401 831 8030",
    "sg:postcode":"02903",
    "sg:province":"RI",
    "sg:tags":[
        "physician",
        "surgeon",
        "surgical",
        "pharmaceutical"
    ],
    "wof:name":"New England Medical Supply Co",
    "wof:placetype":"venue"
},
  "geometry": {"coordinates":[-71.407235,41.817809],"type":"Point"}
}