{
  "type": "Feature",
  "properties": {
    "addr:full":"150 Curran Rd Cumberland RI 02864",
    "addr:housenumber":"150",
    "addr:postcode":"02864",
    "addr:street":"Curran Rd",
    "iso:country":"US",
    "sg:address":"150 Curran Rd",
    "sg:city":"Cumberland",
    "sg:classifiers":[
        {
            "category":"Professional",
            "subcategory":"Business Services",
            "type":"Services"
        }
    ],
    "sg:phone":"+1 401 728 6544",
    "sg:postcode":"02864",
    "sg:province":"RI",
    "wof:name":"GKS Custom Interiors",
    "wof:placetype":"venue"
},
  "geometry": {"coordinates":[-71.38609599999999,41.917148],"type":"Point"}
}