{
  "type": "Feature",
  "properties": {
    "iso:country":"US",
    "sg:address":"4080 S County Trl",
    "sg:city":"Charlestown",
    "sg:classifiers":[
        {
            "category":"Professional",
            "subcategory":"Lawyer & Legal Services",
            "type":"Services"
        }
    ],
    "sg:phone":"+1 401 364 8001",
    "sg:postcode":"02813",
    "sg:province":"RI",
    "wof:name":"Law Offices of K Erik Wallin",
    "wof:placetype":"venue"
},
  "geometry": {"coordinates":[-71.63227999999999,41.441756],"type":"Point"}
}