{
  "type": "Feature",
  "properties": {
    "addr:full":"739 Hartford Ave Johnston RI 02919",
    "addr:housenumber":"739",
    "addr:postcode":"02919",
    "addr:street":"Hartford Ave",
    "iso:country":"US",
    "sg:address":"739 Hartford Ave",
    "sg:city":"Johnston",
    "sg:classifiers":[
        {
            "category":"Shopping",
            "subcategory":"Florist",
            "type":"Retail Goods"
        }
    ],
    "sg:phone":"+1 401 946 3503",
    "sg:postcode":"02919",
    "sg:province":"RI",
    "sg:website":"www.whiteorchidflowers.net",
    "wof:name":"White Orchid",
    "wof:placetype":"venue"
},
  "geometry": {"coordinates":[-71.471283,41.819655],"type":"Point"}
}