{
  "type": "Feature",
  "properties": {
    "addr:full":"677 Central Ave Pawtucket RI 02861",
    "addr:housenumber":"677",
    "addr:postcode":"02861",
    "addr:street":"Central Ave",
    "iso:country":"US",
    "sg:address":"677 Central Ave",
    "sg:city":"Pawtucket",
    "sg:classifiers":[
        {
            "category":"Personal",
            "subcategory":"Beauty Salon",
            "type":"Services"
        }
    ],
    "sg:phone":"+1 401 722 0788",
    "sg:postcode":"02861",
    "sg:province":"RI",
    "sg:tags":[
        "nail",
        "shop"
    ],
    "wof:name":"Hair Illusions",
    "wof:placetype":"venue"
},
  "geometry": {"coordinates":[-71.356697,41.887402],"type":"Point"}
}