{
  "type": "Feature",
  "properties": {
    "iso:country":"US",
    "sg:address":"2332 Post Rd",
    "sg:city":"Warwick",
    "sg:classifiers":[
        {
            "category":"Professional",
            "subcategory":"Accounting & Tax Preparation",
            "type":"Services"
        }
    ],
    "sg:phone":"+1 401 732 5574",
    "sg:postcode":"02886",
    "sg:province":"RI",
    "sg:tags":[
        "supp",
        "bookkeeping",
        "retail"
    ],
    "wof:name":"Accurate Business Services",
    "wof:placetype":"venue"
},
  "geometry": {"coordinates":[-71.443444,41.718524],"type":"Point"}
}