{
  "type": "Feature",
  "properties": {
    "iso:country":"US",
    "sg:address":"144 Danielson Pike",
    "sg:city":"North Scituate",
    "sg:classifiers":[
        {
            "category":"Organizations",
            "subcategory":"Religious Organization",
            "type":"Services"
        }
    ],
    "sg:phone":"+1 401 647 2255",
    "sg:postcode":"02857",
    "sg:province":"RI",
    "sg:tags":[
        "church"
    ],
    "wof:name":"St Joseph's Church",
    "wof:placetype":"venue"
},
  "geometry": {"coordinates":[-71.587492,41.831849],"type":"Point"}
}