{
  "type": "Feature",
  "properties": {
    "iso:country":"US",
    "sg:address":"4 Westwood Ln",
    "sg:city":"Barrington",
    "sg:classifiers":[
        {
            "category":"Health Services",
            "subcategory":"Doctor",
            "type":"Services"
        }
    ],
    "sg:phone":"+1 401 245 5634",
    "sg:postcode":"02806",
    "sg:province":"RI",
    "sg:tags":[
        "medical"
    ],
    "wof:name":"Greenburg A Gerson MD PHD",
    "wof:placetype":"venue"
},
  "geometry": {"coordinates":[-71.305458,41.756764],"type":"Point"}
}