{
  "type": "Feature",
  "properties": {
    "iso:country":"US",
    "sg:address":"67 Jefferson Blvd",
    "sg:city":"Warwick",
    "sg:classifiers":[
        {
            "category":"Professional",
            "subcategory":"Accounting & Tax Preparation",
            "type":"Services"
        }
    ],
    "sg:phone":"+1 401 781 6300",
    "sg:postcode":"02888",
    "sg:province":"RI",
    "wof:name":"Salvatore C Santilli",
    "wof:placetype":"venue"
},
  "geometry": {"coordinates":[-71.43619099999999,41.747916],"type":"Point"}
}