{
  "type": "Feature",
  "properties": {
    "iso:country":"US",
    "sg:address":"27 North Rd",
    "sg:city":"Wakefield",
    "sg:classifiers":[
        {
            "category":"Recreation",
            "type":"Entertainment"
        }
    ],
    "sg:phone":"+1 401 789 4625",
    "sg:postcode":"02879",
    "sg:province":"RI",
    "sg:tags":[
        "center"
    ],
    "sg:website":"www.greenway.org",
    "wof:name":"East Coast Greenway Alliance",
    "wof:placetype":"venue"
},
  "geometry": {"coordinates":[-71.496629,41.452071],"type":"Point"}
}