{
  "type": "Feature",
  "properties": {
    "iso:country":"US",
    "sg:address":"464 Hope St",
    "sg:city":"Bristol",
    "sg:classifiers":[
        {
            "category":"Banks & Credit Unions",
            "subcategory":"Bank",
            "type":"Services"
        }
    ],
    "sg:phone":"+1 401 253 2385",
    "sg:postcode":"02809",
    "sg:province":"RI",
    "wof:name":"Citizens Bank",
    "wof:placetype":"venue"
},
  "geometry": {"coordinates":[-71.276174,41.669541],"type":"Point"}
}