{
  "type": "Feature",
  "properties": {
    "iso:country":"US",
    "sg:address":"911 Pontiac Ave",
    "sg:city":"Cranston",
    "sg:classifiers":[
        {
            "category":"Health Services",
            "subcategory":"Doctor",
            "type":"Services"
        }
    ],
    "sg:phone":"+1 401 941 1888",
    "sg:postcode":"02920",
    "sg:province":"RI",
    "wof:name":"Contour Dental Laboratory",
    "wof:placetype":"venue"
},
  "geometry": {"coordinates":[-71.443477,41.759751],"type":"Point"}
}