{
  "type": "Feature",
  "properties": {
    "iso:country":"US",
    "sg:address":"286 Maple Ave",
    "sg:city":"Barrington",
    "sg:classifiers":[
        {
            "category":"Education",
            "subcategory":"Dance Studio",
            "type":"Public Place"
        }
    ],
    "sg:phone":"+1 401 245 0094",
    "sg:postcode":"02806",
    "sg:province":"RI",
    "sg:tags":[
        "instruction",
        "dancing"
    ],
    "wof:name":"Grooves Theatrical Dance",
    "wof:placetype":"venue"
},
  "geometry": {"coordinates":[-71.31588000000001,41.73894],"type":"Point"}
}