{
  "type": "Feature",
  "properties": {
    "iso:country":"US",
    "sg:address":"21 Suburban Pkwy",
    "sg:city":"Warwick",
    "sg:classifiers":[
        {
            "category":"Recreation",
            "subcategory":"Marina",
            "type":"Entertainment"
        }
    ],
    "sg:phone":"+1 401 737 2729",
    "sg:postcode":"02889",
    "sg:province":"RI",
    "sg:tags":[
        "operation"
    ],
    "wof:name":"Aqua Vista Marina Inc",
    "wof:placetype":"venue"
},
  "geometry": {"coordinates":[-71.394026,41.686939],"type":"Point"}
}