{
  "type": "Feature",
  "properties": {
    "iso:country":"US",
    "sg:address":"59 Pocasset Ave",
    "sg:city":"Providence",
    "sg:classifiers":[
        {
            "category":"Retail",
            "subcategory":"Auto Repair",
            "type":"Services"
        }
    ],
    "sg:phone":"+1 401 751 4140",
    "sg:postcode":"02909",
    "sg:province":"RI",
    "sg:tags":[
        "repairing",
        "automobile",
        "general"
    ],
    "wof:name":"Matarese's Auto Repair",
    "wof:placetype":"venue"
},
  "geometry": {"coordinates":[-71.449394,41.812473],"type":"Point"}
}