{
  "type": "Feature",
  "properties": {
    "iso:country":"US",
    "sg:address":"15 Glendale Ave",
    "sg:city":"Riverside",
    "sg:classifiers":[
        {
            "category":"Building & Trades",
            "subcategory":"Construction",
            "type":"Services"
        }
    ],
    "sg:phone":"+1 401 632 4911",
    "sg:postcode":"02915",
    "sg:province":"RI",
    "sg:tags":[
        "downspouts",
        "gutter"
    ],
    "wof:name":"Gutter Works",
    "wof:placetype":"venue"
},
  "geometry": {"coordinates":[-71.36208999999999,41.793981],"type":"Point"}
}