{
  "type": "Feature",
  "properties": {
    "addr:full":"119 Mount View Rd Narragansett RI 02882",
    "addr:housenumber":"119",
    "addr:postcode":"02882",
    "addr:street":"Mount View Rd",
    "iso:country":"US",
    "sg:address":"119 Mount View Rd",
    "sg:city":"Narragansett",
    "sg:classifiers":[
        {
            "category":"Professional",
            "type":"Services"
        }
    ],
    "sg:phone":"+1 401 789 7683",
    "sg:postcode":"02882",
    "sg:province":"RI",
    "wof:name":"Bassen Dib",
    "wof:placetype":"venue"
},
  "geometry": {"coordinates":[-71.443668,41.482843],"type":"Point"}
}