{
  "type": "Feature",
  "properties": {
    "addr:full":"99 Poppasquash Rd Bristol RI 02809",
    "addr:housenumber":"99",
    "addr:postcode":"02809",
    "addr:street":"Poppasquash Rd",
    "iso:country":"US",
    "sg:address":"99 Poppasquash Rd",
    "sg:city":"Bristol",
    "sg:classifiers":[
        {
            "category":"Banks & Credit Unions",
            "subcategory":"Bank",
            "type":"Services"
        }
    ],
    "sg:phone":"+1 401 253 8210",
    "sg:postcode":"02809",
    "sg:province":"RI",
    "sg:tags":[
        "loan",
        "real estate"
    ],
    "wof:name":"Countrywide Home Loans",
    "wof:placetype":"venue"
},
  "geometry": {"coordinates":[-71.288111,41.681518],"type":"Point"}
}