{
  "type": "Feature",
  "properties": {
    "iso:country":"US",
    "sg:address":"19 Radcliffe Ave",
    "sg:city":"Providence",
    "sg:classifiers":[
        {
            "category":"Freight",
            "type":"Transportation"
        }
    ],
    "sg:phone":"+1 401 941 2408",
    "sg:postcode":"02908",
    "sg:province":"RI",
    "sg:tags":[
        "operator",
        "local",
        "trucking"
    ],
    "wof:name":"Bencosme Enterprise Inc",
    "wof:placetype":"venue"
},
  "geometry": {"coordinates":[-71.4312,41.838779],"type":"Point"}
}