{
  "type": "Feature",
  "properties": {
    "iso:country":"US",
    "sg:address":"2 Thurber Blvd",
    "sg:city":"Smithfield",
    "sg:classifiers":[
        {
            "category":"Professional",
            "type":"Services"
        },
        {
            "category":"Building & Trades",
            "subcategory":"Equipment Rental",
            "type":"Services"
        }
    ],
    "sg:phone":"+1 401 233 6400",
    "sg:postcode":"02917",
    "sg:province":"RI",
    "sg:tags":[
        "medical",
        "establishment"
    ],
    "wof:name":"Clinical Data Inc",
    "wof:placetype":"venue"
},
  "geometry": {"coordinates":[-71.516167,41.9126],"type":"Point"}
}