{
  "type": "Feature",
  "properties": {
    "iso:country":"US",
    "sg:address":"45 Wells St",
    "sg:city":"Westerly",
    "sg:classifiers":[
        {
            "category":"Health Services",
            "subcategory":"Doctor",
            "type":"Services"
        }
    ],
    "sg:phone":"+1 401 596 0259",
    "sg:postcode":"02891",
    "sg:province":"RI",
    "sg:tags":[
        "medical"
    ],
    "wof:name":"Daniel Gaccione MD",
    "wof:placetype":"venue"
},
  "geometry": {"coordinates":[-71.823785,41.363097],"type":"Point"}
}