{
  "type": "Feature",
  "properties": {
    "addr:full":"32 Broad St Warren RI 02885",
    "addr:housenumber":"32",
    "addr:postcode":"02885",
    "addr:street":"Broad St",
    "iso:country":"US",
    "sg:address":"32 Broad St",
    "sg:city":"Warren",
    "sg:classifiers":[
        {
            "category":"Manufacturing",
            "subcategory":"Printing",
            "type":"Manufacturing & Wholesale Goods"
        }
    ],
    "sg:phone":"+1 401 289 0756",
    "sg:postcode":"02885",
    "sg:province":"RI",
    "sg:tags":[
        "screen"
    ],
    "wof:name":"Interior Sourcing Concepts",
    "wof:placetype":"venue"
},
  "geometry": {"coordinates":[-71.284857,41.727182],"type":"Point"}
}