{
  "type": "Feature",
  "properties": {
    "iso:country":"US",
    "sg:address":"112 Log Rd",
    "sg:city":"Smithfield",
    "sg:classifiers":[
        {
            "category":"Building & Trades",
            "subcategory":"Construction",
            "type":"Services"
        }
    ],
    "sg:phone":"+1 401 231 4380",
    "sg:postcode":"02917",
    "sg:province":"RI",
    "sg:tags":[
        "contractor"
    ],
    "wof:name":"W C Mc Cann Construction Inc",
    "wof:placetype":"venue"
},
  "geometry": {"coordinates":[-71.550686,41.908496],"type":"Point"}
}