{
  "type": "Feature",
  "properties": {
    "iso:country":"US",
    "sg:address":"2145 Broad St",
    "sg:city":"Cranston",
    "sg:classifiers":[
        {
            "category":"Shopping",
            "subcategory":"Used Merchandise",
            "type":"Retail Goods"
        }
    ],
    "sg:phone":"+1 401 781 5226",
    "sg:postcode":"02905",
    "sg:province":"RI",
    "sg:tags":[
        "antique"
    ],
    "wof:name":"Village Art & Antiques",
    "wof:placetype":"venue"
},
  "geometry": {"coordinates":[-71.391186,41.766315],"type":"Point"}
}