{
  "type": "Feature",
  "properties": {
    "addr:full":"248 Shawomet Ave Warwick RI 02889",
    "addr:housenumber":"248",
    "addr:postcode":"02889",
    "addr:street":"Shawomet Ave",
    "iso:country":"US",
    "sg:address":"248 Shawomet Ave",
    "sg:city":"Warwick",
    "sg:classifiers":[
        {
            "category":"Restaurant",
            "type":"Food & Drink"
        }
    ],
    "sg:phone":"+1 401 738 1538",
    "sg:postcode":"02889",
    "sg:province":"RI",
    "sg:tags":[
        "bakery"
    ],
    "wof:name":"Ddeluise Corp",
    "wof:placetype":"venue"
},
  "geometry": {"coordinates":[-71.36565400000001,41.717169],"type":"Point"}
}