{
  "type": "Feature",
  "properties": {
    "iso:country":"US",
    "sg:address":"71 Fairway Dr",
    "sg:city":"Cranston",
    "sg:classifiers":[
        {
            "category":"Freight",
            "type":"Transportation"
        }
    ],
    "sg:phone":"+1 401 461 6200",
    "sg:postcode":"02920",
    "sg:province":"RI",
    "sg:tags":[
        "commercial",
        "storage"
    ],
    "sg:website":"www.publicstorage.com",
    "wof:name":"Public Storage Inc",
    "wof:placetype":"venue"
},
  "geometry": {"coordinates":[-71.480648,41.740088],"type":"Point"}
}