{
  "type": "Feature",
  "properties": {
    "addr:full":"182 Arnold Rd Coventry RI 02816",
    "addr:housenumber":"182",
    "addr:postcode":"02816",
    "addr:street":"Arnold Rd",
    "iso:country":"US",
    "sg:address":"182 Arnold Rd",
    "sg:city":"Coventry",
    "sg:classifiers":[
        {
            "category":"Food & Beverages",
            "subcategory":"Groceries & Convenience Stores",
            "type":"Retail Goods"
        }
    ],
    "sg:phone":"+1 401 821 9674",
    "sg:postcode":"02816",
    "sg:province":"RI",
    "sg:tags":[
        "market"
    ],
    "wof:name":"Veteran's Market",
    "wof:placetype":"venue"
},
  "geometry": {"coordinates":[-71.55538199999999,41.675452],"type":"Point"}
}