{
  "type": "Feature",
  "properties": {
    "iso:country":"US",
    "sg:address":"22 Stockton Dr",
    "sg:city":"Middletown",
    "sg:classifiers":[
        {
            "category":"Building & Trades",
            "subcategory":"Landscaping Services",
            "type":"Services"
        }
    ],
    "sg:phone":"+1 401 849 7268",
    "sg:postcode":"02842",
    "sg:province":"RI",
    "wof:name":"DSM Landscaping",
    "wof:placetype":"venue"
},
  "geometry": {"coordinates":[-71.304419,41.510675],"type":"Point"}
}