{
  "type": "Feature",
  "properties": {
    "addr:full":"10 Appian Way Smithfield RI 02917",
    "addr:housenumber":"10",
    "addr:postcode":"02917",
    "addr:street":"Appian Way",
    "iso:country":"US",
    "sg:address":"10 Appian Way",
    "sg:city":"Smithfield",
    "sg:classifiers":[
        {
            "category":"Professional",
            "type":"Services"
        }
    ],
    "sg:phone":"+1 401 231 2009",
    "sg:postcode":"02917",
    "sg:province":"RI",
    "sg:tags":[
        "establishment"
    ],
    "wof:name":"Sound Move Productions",
    "wof:placetype":"venue"
},
  "geometry": {"coordinates":[-71.53071,41.910522],"type":"Point"}
}