{
  "type": "Feature",
  "properties": {
    "iso:country":"US",
    "sg:address":"441 Prospect St",
    "sg:city":"Pawtucket",
    "sg:classifiers":[
        {
            "category":"Local Transit",
            "type":"Transportation"
        }
    ],
    "sg:phone":"+1 401 725 4660",
    "sg:postcode":"02860",
    "sg:province":"RI",
    "sg:tags":[
        "passenger"
    ],
    "wof:name":"Al Casmire Limosine Services",
    "wof:placetype":"venue"
},
  "geometry": {"coordinates":[-71.37178299999999,41.86387],"type":"Point"}
}