{
  "type": "Feature",
  "properties": {
    "iso:country":"US",
    "sg:address":"288 Scituate Ave",
    "sg:city":"Johnston",
    "sg:classifiers":[
        {
            "category":"Wholesale",
            "subcategory":"Home Furnishings",
            "type":"Manufacturing & Wholesale Goods"
        }
    ],
    "sg:phone":"+1 401 943 5524",
    "sg:postcode":"02919",
    "sg:province":"RI",
    "sg:tags":[
        "mat",
        "matting"
    ],
    "wof:name":"ADF Inc",
    "wof:placetype":"venue"
},
  "geometry": {"coordinates":[-71.527135,41.81124],"type":"Point"}
}