{
  "type": "Feature",
  "properties": {
    "iso:country":"US",
    "sg:address":"935 Park Ave",
    "sg:city":"Cranston",
    "sg:classifiers":[
        {
            "category":"Professional",
            "subcategory":"Lawyer & Legal Services",
            "type":"Services"
        }
    ],
    "sg:phone":"+1 401 943 1987",
    "sg:postcode":"02910",
    "sg:province":"RI",
    "sg:tags":[
        "attorney"
    ],
    "wof:name":"Stephen P Ashukian",
    "wof:placetype":"venue"
},
  "geometry": {"coordinates":[-71.439729,41.78085],"type":"Point"}
}