{
  "type": "Feature",
  "properties": {
    "addr:full":"11 Redberry Dr Wakefield RI 02879",
    "addr:housenumber":"11",
    "addr:postcode":"02879",
    "addr:street":"Redberry Dr",
    "iso:country":"US",
    "sg:address":"11 Redberry Dr",
    "sg:city":"Wakefield",
    "sg:classifiers":[
        {
            "category":"Travel",
            "subcategory":"Hotels & Motels",
            "type":"Entertainment"
        }
    ],
    "sg:phone":"+1 401 783 4002",
    "sg:postcode":"02879",
    "sg:province":"RI",
    "sg:tags":[
        "membership",
        "lodging"
    ],
    "wof:name":"Alpha Delta Kappa Sororit",
    "wof:placetype":"venue"
},
  "geometry": {"coordinates":[-71.52696299999999,41.452016],"type":"Point"}
}