{
  "type": "Feature",
  "properties": {
    "addr:full":"177 Greenwood Ave Rumford RI 02916",
    "addr:housenumber":"177",
    "addr:postcode":"02916",
    "addr:street":"Greenwood Ave",
    "iso:country":"US",
    "sg:address":"177 Greenwood Ave",
    "sg:city":"Rumford",
    "sg:classifiers":[
        {
            "category":"Retail",
            "subcategory":"Auto Repair",
            "type":"Services"
        }
    ],
    "sg:phone":"+1 401 435 6862",
    "sg:postcode":"02916",
    "sg:province":"RI",
    "sg:tags":[
        "wrecker"
    ],
    "wof:name":"Coastal Collision & Towing",
    "wof:placetype":"venue"
},
  "geometry": {"coordinates":[-71.352238,41.837442],"type":"Point"}
}