{
  "type": "Feature",
  "properties": {
    "iso:country":"US",
    "sg:address":"14 Rock Ave",
    "sg:city":"Pascoag",
    "sg:classifiers":[
        {
            "category":"Professional",
            "type":"Services"
        }
    ],
    "sg:phone":"+1 401 568 2885",
    "sg:postcode":"02859",
    "sg:province":"RI",
    "sg:tags":[
        "establishment"
    ],
    "wof:name":"Intap",
    "wof:placetype":"venue"
},
  "geometry": {"coordinates":[-71.70610499999999,41.954638],"type":"Point"}
}