{
  "type": "Feature",
  "properties": {
    "addr:full":"48 Ledge St Providence RI 02904",
    "addr:housenumber":"48",
    "addr:postcode":"02904",
    "addr:street":"Ledge St",
    "iso:country":"US",
    "sg:address":"48 Ledge St",
    "sg:city":"Providence",
    "sg:classifiers":[
        {
            "category":"Building & Trades",
            "subcategory":"Construction",
            "type":"Services"
        }
    ],
    "sg:phone":"+1 401 351 5657",
    "sg:postcode":"02904",
    "sg:province":"RI",
    "sg:tags":[
        "plastering",
        "contractor"
    ],
    "wof:name":"Joseph Garganese & Son Plaster",
    "wof:placetype":"venue"
},
  "geometry": {"coordinates":[-71.419663,41.853345],"type":"Point"}
}