{
  "type": "Feature",
  "properties": {
    "iso:country":"US",
    "sg:address":"25 Humphreys Rd",
    "sg:city":"Barrington",
    "sg:classifiers":[
        {
            "category":"Professional",
            "subcategory":"Business Services",
            "type":"Services"
        }
    ],
    "sg:phone":"+1 401 433 0214",
    "sg:postcode":"02806",
    "sg:province":"RI",
    "sg:tags":[
        "interior",
        "decorator"
    ],
    "wof:name":"Morse Janet C Interiors",
    "wof:placetype":"venue"
},
  "geometry": {"coordinates":[-71.34173800000001,41.753845],"type":"Point"}
}