{
  "type": "Feature",
  "properties": {
    "iso:country":"US",
    "sg:address":"7661 Post Rd",
    "sg:city":"North Kingstown",
    "sg:classifiers":[
        {
            "category":"Organizations",
            "subcategory":"Religious Organization",
            "type":"Services"
        }
    ],
    "sg:phone":"+1 401 294 8788",
    "sg:postcode":"02852",
    "sg:province":"RI",
    "sg:tags":[
        "church"
    ],
    "wof:name":"Living Truth A Christian",
    "wof:placetype":"venue"
},
  "geometry": {"coordinates":[-71.457803,41.589297],"type":"Point"}
}