{
  "type": "Feature",
  "properties": {
    "iso:country":"US",
    "sg:address":"33 Cobble Hill Rd",
    "sg:city":"Lincoln",
    "sg:classifiers":[
        {
            "category":"Professional",
            "subcategory":"Engineering",
            "type":"Services"
        }
    ],
    "sg:phone":"+1 401 726 7871",
    "sg:postcode":"02865",
    "sg:province":"RI",
    "sg:tags":[
        "engineer"
    ],
    "wof:name":"Tri State Engineering & Assoc",
    "wof:placetype":"venue"
},
  "geometry": {"coordinates":[-71.41891099999999,41.879599],"type":"Point"}
}