{
  "type": "Feature",
  "properties": {
    "addr:full":"16 River Run East Greenwich RI 02818",
    "addr:housenumber":"16",
    "addr:postcode":"02818",
    "addr:street":"River Run",
    "iso:country":"US",
    "sg:address":"16 River Run",
    "sg:city":"East Greenwich",
    "sg:classifiers":[
        {
            "category":"Professional",
            "type":"Services"
        }
    ],
    "sg:phone":"+1 401 885 6449",
    "sg:postcode":"02818",
    "sg:province":"RI",
    "sg:tags":[
        "lecturing"
    ],
    "wof:name":"Michael J Lysaght",
    "wof:placetype":"venue"
},
  "geometry": {"coordinates":[-71.51844,41.635172],"type":"Point"}
}