{
  "type": "Feature",
  "properties": {
    "addr:full":"1003 Anthony Rd Portsmouth RI 02871",
    "addr:housenumber":"1003",
    "addr:postcode":"02871",
    "addr:street":"Anthony Rd",
    "iso:country":"US",
    "sg:address":"1003 Anthony Rd",
    "sg:city":"Portsmouth",
    "sg:classifiers":[
        {
            "category":"Professional",
            "subcategory":"Art Services",
            "type":"Services"
        }
    ],
    "sg:phone":"+1 401 683 0546",
    "sg:postcode":"02871",
    "sg:province":"RI",
    "sg:tags":[
        "commercial",
        "design"
    ],
    "wof:name":"Bde T Designs",
    "wof:placetype":"venue"
},
  "geometry": {"coordinates":[-71.222481,41.645549],"type":"Point"}
}