{
  "type": "Feature",
  "properties": {
    "addr:full":"31 de Arruda Ter Portsmouth RI 02871",
    "addr:postcode":"02871",
    "addr:street":"31 De Arruda Ter",
    "iso:country":"US",
    "sg:address":"31 de Arruda Ter",
    "sg:city":"Portsmouth",
    "sg:classifiers":[
        {
            "category":"Professional",
            "subcategory":"Management & Consulting",
            "type":"Services"
        }
    ],
    "sg:phone":"+1 401 683 0235",
    "sg:postcode":"02871",
    "sg:province":"RI",
    "sg:tags":[
        "construction"
    ],
    "wof:name":"Sepol Industries Consulting",
    "wof:placetype":"venue"
},
  "geometry": {"coordinates":[-71.257842,41.578728],"type":"Point"}
}