{
  "type": "Feature",
  "properties": {
    "iso:country":"US",
    "sg:address":"833 Hope St",
    "sg:city":"Providence",
    "sg:classifiers":[
        {
            "category":"Restaurant",
            "type":"Food & Drink"
        }
    ],
    "sg:phone":"+1 401 831 1150",
    "sg:postcode":"02906",
    "sg:province":"RI",
    "sg:tags":[
        "pakistani",
        "indian"
    ],
    "wof:name":"Not Just Snacks",
    "wof:placetype":"venue"
},
  "geometry": {"coordinates":[-71.394383,41.849755],"type":"Point"}
}