{
  "type": "Feature",
  "properties": {
    "addr:full":"724 Elder Ballou Mtg House Rd Woonsocket RI 02895",
    "addr:housenumber":"724",
    "addr:postcode":"02895",
    "addr:street":"Elder;House Rd",
    "iso:country":"US",
    "sg:address":"724 Elder Ballou Mtg House Rd",
    "sg:city":"Woonsocket",
    "sg:classifiers":[
        {
            "category":"Freight",
            "type":"Transportation"
        }
    ],
    "sg:phone":"+1 401 766 9531",
    "sg:postcode":"02895",
    "sg:province":"RI",
    "sg:tags":[
        "operator",
        "local",
        "trucking"
    ],
    "wof:name":"Mds",
    "wof:placetype":"venue"
},
  "geometry": {"coordinates":[-71.46111399999999,42.008037],"type":"Point"}
}