{
  "type": "Feature",
  "properties": {
    "addr:full":"12 Bradford Rd Cranston RI 02910",
    "addr:housenumber":"12",
    "addr:postcode":"02910",
    "addr:street":"Bradford Rd",
    "iso:country":"US",
    "sg:address":"12 Bradford Rd",
    "sg:city":"Cranston",
    "sg:classifiers":[
        {
            "category":"Manufacturing",
            "subcategory":"Printing",
            "type":"Manufacturing & Wholesale Goods"
        }
    ],
    "sg:phone":"+1 401 467 7446",
    "sg:postcode":"02910",
    "sg:province":"RI",
    "sg:tags":[
        "marketing",
        "consulting",
        "retail",
        "sign"
    ],
    "wof:name":"Pro Graphics",
    "wof:placetype":"venue"
},
  "geometry": {"coordinates":[-71.43767,41.767166],"type":"Point"}
}