{
  "type": "Feature",
  "properties": {
    "addr:full":"617 W Greenville Rd North Scituate RI 02857",
    "addr:housenumber":"617",
    "addr:postcode":"02857",
    "addr:street":"W Greenville Rd",
    "iso:country":"US",
    "sg:address":"617 W Greenville Rd",
    "sg:city":"North Scituate",
    "sg:classifiers":[
        {
            "category":"Shopping",
            "subcategory":"Florist",
            "type":"Retail Goods"
        },
        {
            "category":"Farming",
            "subcategory":"Nursery",
            "type":"Manufacturing & Wholesale Goods"
        }
    ],
    "sg:phone":"+1 401 647 2208",
    "sg:postcode":"02857",
    "sg:province":"RI",
    "sg:tags":[
        "ornamental"
    ],
    "wof:name":"Country Gardeners",
    "wof:placetype":"venue"
},
  "geometry": {"coordinates":[-71.58384,41.839772],"type":"Point"}
}