{
  "type": "Feature",
  "properties": {
    "addr:full":"162 Peirce St East Greenwich RI 02818",
    "addr:housenumber":"162",
    "addr:postcode":"02818",
    "addr:street":"Peirce St",
    "iso:country":"US",
    "sg:address":"162 Peirce St",
    "sg:city":"East Greenwich",
    "sg:classifiers":[
        {
            "category":"Travel",
            "subcategory":"Hotels & Motels",
            "type":"Entertainment"
        }
    ],
    "sg:phone":"+1 401 884 9955",
    "sg:postcode":"02818",
    "sg:province":"RI",
    "sg:tags":[
        "breakfast",
        "accommodation",
        "bed"
    ],
    "wof:name":"1873 House",
    "wof:placetype":"venue"
},
  "geometry": {"coordinates":[-71.45056599999999,41.658843],"type":"Point"}
}