{
  "type": "Feature",
  "properties": {
    "iso:country":"US",
    "sg:address":"21 Brayton Ave",
    "sg:city":"Warwick",
    "sg:classifiers":[
        {
            "category":"Manufacturing",
            "subcategory":"Furniture",
            "type":"Manufacturing & Wholesale Goods"
        }
    ],
    "sg:phone":"+1 401 821 9800",
    "sg:postcode":"02886",
    "sg:province":"RI",
    "sg:tags":[
        "household",
        "wood",
        "mfg"
    ],
    "wof:name":"Wood N Things",
    "wof:placetype":"venue"
},
  "geometry": {"coordinates":[-71.494927,41.713079],"type":"Point"}
}