{
  "type": "Feature",
  "properties": {
    "addr:full":"58 Waterman Ave North Providence RI 02911",
    "addr:housenumber":"58",
    "addr:postcode":"02911",
    "addr:street":"Waterman Ave",
    "iso:country":"US",
    "sg:address":"58 Waterman Ave",
    "sg:city":"North Providence",
    "sg:classifiers":[
        {
            "category":"Taxi",
            "type":"Transportation"
        }
    ],
    "sg:phone":"+1 401 231 2228",
    "sg:postcode":"02911",
    "sg:province":"RI",
    "sg:tags":[
        "taxicab"
    ],
    "wof:name":"Corporate Taxi",
    "wof:placetype":"venue"
},
  "geometry": {"coordinates":[-71.485708,41.858395],"type":"Point"}
}