{
  "type": "Feature",
  "properties": {
    "iso:country":"US",
    "sg:address":"40 Janna Ct",
    "sg:city":"North Kingstown",
    "sg:phone":"+1 401 294 9547",
    "sg:postcode":"02852",
    "sg:province":"RI",
    "sg:tags":[
        "gas"
    ],
    "wof:name":"Star Gas Svc",
    "wof:placetype":"venue"
},
  "geometry": {"coordinates":[-71.50526000000001,41.593493],"type":"Point"}
}