{
  "type": "Feature",
  "properties": {
    "iso:country":"US",
    "sg:address":"14 Port Ave",
    "sg:city":"Wakefield",
    "sg:classifiers":[
        {
            "category":"Building & Trades",
            "subcategory":"Cleaning & Sanitation",
            "type":"Services"
        }
    ],
    "sg:phone":"+1 401 782 2849",
    "sg:postcode":"02879",
    "sg:province":"RI",
    "sg:tags":[
        "fireplace",
        "chimney"
    ],
    "wof:name":"Bishop's Chimney Svc",
    "wof:placetype":"venue"
},
  "geometry": {"coordinates":[-71.52166099999999,41.390568],"type":"Point"}
}