{
  "type": "Feature",
  "properties": {
    "iso:country":"US",
    "sg:address":"33 Grove Ave",
    "sg:city":"Cranston",
    "sg:classifiers":[
        {
            "category":"Building & Trades",
            "subcategory":"Electrical",
            "type":"Services"
        }
    ],
    "sg:phone":"+1 401 781 9627",
    "sg:postcode":"02910",
    "sg:province":"RI",
    "sg:tags":[
        "electrical",
        "contractor"
    ],
    "wof:name":"A Dibiase Electric Co Inc",
    "wof:placetype":"venue"
},
  "geometry": {"coordinates":[-71.43642199999999,41.764535],"type":"Point"}
}