{
  "type": "Feature",
  "properties": {
    "iso:country":"US",
    "sg:address":"400 Warwick Ave",
    "sg:city":"Warwick",
    "sg:classifiers":[
        {
            "category":"Restaurant",
            "type":"Food & Drink"
        }
    ],
    "sg:menulink":"http://www.allmenus.com/ri/warwick/56706-tong-chinese-restaurant/menu/",
    "sg:phone":"+1 401 941 3880",
    "sg:postcode":"02888",
    "sg:province":"RI",
    "sg:tags":[
        "asian",
        "chinese"
    ],
    "wof:name":"Tong Chinese Restaurant",
    "wof:placetype":"venue"
},
  "geometry": {"coordinates":[-71.405,41.764381],"type":"Point"}
}