{
  "type": "Feature",
  "properties": {
    "iso:country":"US",
    "sg:address":"205 Hallene Rd",
    "sg:city":"Warwick",
    "sg:classifiers":[
        {
            "category":"Building & Trades",
            "subcategory":"Construction",
            "type":"Services"
        }
    ],
    "sg:phone":"+1 401 739 6700",
    "sg:postcode":"02886",
    "sg:province":"RI",
    "sg:tags":[
        "home",
        "builder"
    ],
    "wof:name":"Pulte Homes Corp",
    "wof:placetype":"venue"
},
  "geometry": {"coordinates":[-71.429091,41.733618],"type":"Point"}
}