{
  "type": "Feature",
  "properties": {
    "addr:full":"150 Higginson Ave Lincoln RI 02865",
    "addr:housenumber":"150",
    "addr:postcode":"02865",
    "addr:street":"Higginson Ave",
    "iso:country":"US",
    "sg:address":"150 Higginson Ave",
    "sg:city":"Lincoln",
    "sg:classifiers":[
        {
            "category":"Wholesale",
            "subcategory":"Construction Materials",
            "type":"Manufacturing & Wholesale Goods"
        }
    ],
    "sg:phone":"+1 401 723 7100",
    "sg:postcode":"02865",
    "sg:province":"RI",
    "sg:tags":[
        "concrete",
        "product"
    ],
    "sg:website":"www.durastonecorporation.com",
    "wof:name":"Durastone Corp",
    "wof:placetype":"venue"
},
  "geometry": {"coordinates":[-71.408736,41.885163],"type":"Point"}
}