{
  "type": "Feature",
  "properties": {
    "iso:country":"US",
    "sg:address":"11 Glen Ave",
    "sg:city":"North Smithfield",
    "sg:classifiers":[
        {
            "category":"Home & Garden",
            "subcategory":"Hardware",
            "type":"Retail Goods"
        }
    ],
    "sg:phone":"+1 401 769 9793",
    "sg:postcode":"02896",
    "sg:province":"RI",
    "sg:tags":[
        "windows",
        "repair",
        "screen",
        "rental",
        "store"
    ],
    "wof:name":"Mulveys True Value",
    "wof:placetype":"venue"
},
  "geometry": {"coordinates":[-71.519543,41.983318],"type":"Point"}
}