{
  "type": "Feature",
  "properties": {
    "iso:country":"US",
    "sg:address":"1 Randall St",
    "sg:city":"Providence",
    "sg:classifiers":[
        {
            "category":"Health Services",
            "subcategory":"Medical Lab",
            "type":"Services"
        }
    ],
    "sg:phone":"+1 401 456 0558",
    "sg:postcode":"02904",
    "sg:province":"RI",
    "sg:tags":[
        "laboratory"
    ],
    "wof:name":"Quest Diagnostics Inc",
    "wof:placetype":"venue"
},
  "geometry": {"coordinates":[-71.41170700000001,41.836504],"type":"Point"}
}