{
  "type": "Feature",
  "properties": {
    "iso:country":"US",
    "sg:address":"2 New Industrial Way",
    "sg:city":"Warren",
    "sg:classifiers":[
        {
            "category":"Manufacturing",
            "subcategory":"Motor Vehicles & Parts",
            "type":"Manufacturing & Wholesale Goods"
        },
        {
            "category":"Wholesale",
            "subcategory":"Auto Parts",
            "type":"Manufacturing & Wholesale Goods"
        },
        {
            "category":"Retail",
            "subcategory":"Auto Repair",
            "type":"Services"
        }
    ],
    "sg:phone":"+1 401 245 0213",
    "sg:postcode":"02885",
    "sg:province":"RI",
    "sg:tags":[
        "body",
        "repairing",
        "shop",
        "supply",
        "automobile",
        "supply-wholesale",
        "equipment",
        "service-equipment",
        "painting",
        "manufacturer"
    ],
    "wof:name":"Choice Collision Center",
    "wof:placetype":"venue"
},
  "geometry": {"coordinates":[-71.272369,41.750204],"type":"Point"}
}