{
  "type": "Feature",
  "properties": {
    "iso:country":"US",
    "sg:address":"26 Church Ln",
    "sg:city":"Portsmouth",
    "sg:classifiers":[
        {
            "category":"Organizations",
            "subcategory":"Membership Organization",
            "type":"Services"
        }
    ],
    "sg:phone":"+1 401 683 5528",
    "sg:postcode":"02871",
    "sg:province":"RI",
    "wof:name":"United States Power Squad",
    "wof:placetype":"venue"
},
  "geometry": {"coordinates":[-71.247575,41.602285],"type":"Point"}
}