{
  "type": "Feature",
  "properties": {
    "addr:full":"861 Victory Hwy West Greenwich RI 02817",
    "addr:housenumber":"861",
    "addr:postcode":"02817",
    "addr:street":"Victory Hwy",
    "iso:country":"US",
    "sg:address":"861 Victory Hwy",
    "sg:city":"West Greenwich",
    "sg:classifiers":[
        {
            "category":"Wholesale",
            "subcategory":"Machinery & Supplies",
            "type":"Manufacturing & Wholesale Goods"
        }
    ],
    "sg:phone":"+1 401 397 2323",
    "sg:postcode":"02817",
    "sg:province":"RI",
    "sg:tags":[
        "equipment",
        "material",
        "handling"
    ],
    "wof:name":"Adams Equipment Co",
    "wof:placetype":"venue"
},
  "geometry": {"coordinates":[-71.662758,41.60865],"type":"Point"}
}