{
  "type": "Feature",
  "properties": {
    "iso:country":"US",
    "sg:address":"311 Gorton Lake Blvd",
    "sg:city":"Warwick",
    "sg:classifiers":[
        {
            "category":"Shopping",
            "subcategory":"Clothing, Apparel, & Fashions",
            "type":"Retail Goods"
        }
    ],
    "sg:phone":"+1 401 739 7859",
    "sg:postcode":"02886",
    "sg:province":"RI",
    "sg:tags":[
        "wig",
        "toupee",
        "hairpiece"
    ],
    "wof:name":"Deezines In Hair",
    "wof:placetype":"venue"
},
  "geometry": {"coordinates":[-71.460548,41.708633],"type":"Point"}
}