{
  "type": "Feature",
  "properties": {
    "iso:country":"US",
    "sg:address":"173 Knight St",
    "sg:city":"Woonsocket",
    "sg:classifiers":[
        {
            "category":"Shopping",
            "subcategory":"Bicycles & Sporting Goods",
            "type":"Retail Goods"
        }
    ],
    "sg:phone":"+1 401 884 3535",
    "sg:postcode":"02895",
    "sg:province":"RI",
    "sg:tags":[
        "equipment",
        "golf",
        "supply"
    ],
    "wof:name":"Clones Golf",
    "wof:placetype":"venue"
},
  "geometry": {"coordinates":[-71.510363,41.992749],"type":"Point"}
}