{
  "type": "Feature",
  "properties": {
    "iso:country":"US",
    "sg:address":"31 King Charles Dr",
    "sg:city":"Portsmouth",
    "sg:classifiers":[
        {
            "category":"Health Services",
            "subcategory":"Doctor",
            "type":"Services"
        }
    ],
    "sg:phone":"+1 401 683 9002",
    "sg:postcode":"02871",
    "sg:province":"RI",
    "sg:tags":[
        "physician",
        "surgeon"
    ],
    "wof:name":"Aquidneck Neurology",
    "wof:placetype":"venue"
},
  "geometry": {"coordinates":[-71.267402,41.591445],"type":"Point"}
}