{
  "type": "Feature",
  "properties": {
    "iso:country":"US",
    "sg:address":"50 Ann Mary St",
    "sg:city":"Pawtucket",
    "sg:classifiers":[
        {
            "category":"Personal",
            "subcategory":"Beauty Salon",
            "type":"Services"
        }
    ],
    "sg:phone":"+1 401 726 5357",
    "sg:postcode":"02860",
    "sg:province":"RI",
    "sg:tags":[
        "cosmetic",
        "supply"
    ],
    "wof:name":"Beauty Works",
    "wof:placetype":"venue"
},
  "geometry": {"coordinates":[-71.40149700000001,41.8577],"type":"Point"}
}