{
  "type": "Feature",
  "properties": {
    "iso:country":"US",
    "sg:address":"212 Greenwich Ave",
    "sg:city":"Warwick",
    "sg:classifiers":[
        {
            "category":"Professional",
            "subcategory":"Lawyer & Legal Services",
            "type":"Services"
        }
    ],
    "sg:phone":"+1 401 384 8080",
    "sg:postcode":"02886",
    "sg:province":"RI",
    "wof:name":"Michael Hagopian Atty At Law",
    "wof:placetype":"venue"
},
  "geometry": {"coordinates":[-71.473719,41.726991],"type":"Point"}
}