{
  "type": "Feature",
  "properties": {
    "iso:country":"US",
    "sg:address":"32 Selkirk St",
    "sg:city":"Pawtucket",
    "sg:classifiers":[
        {
            "category":"Building & Trades",
            "subcategory":"Construction",
            "type":"Services"
        }
    ],
    "sg:phone":"+1 401 725 9750",
    "sg:postcode":"02860",
    "sg:province":"RI",
    "sg:tags":[
        "contractor"
    ],
    "wof:name":"Landmark Building Corp",
    "wof:placetype":"venue"
},
  "geometry": {"coordinates":[-71.410004,41.8573],"type":"Point"}
}