{
  "type": "Feature",
  "properties": {
    "iso:country":"US",
    "sg:address":"34 Sawyer St",
    "sg:city":"Providence",
    "sg:classifiers":[
        {
            "category":"Building & Trades",
            "subcategory":"Landscaping Services",
            "type":"Services"
        }
    ],
    "sg:phone":"+1 401 781 5935",
    "sg:postcode":"02907",
    "sg:province":"RI",
    "sg:tags":[
        "landscape"
    ],
    "wof:name":"Classic Tree Lands",
    "wof:placetype":"venue"
},
  "geometry": {"coordinates":[-71.419678,41.778365],"type":"Point"}
}