{
  "type": "Feature",
  "properties": {
    "iso:country":"US",
    "sg:address":"6 Lewis St",
    "sg:city":"Central Falls",
    "sg:classifiers":[
        {
            "category":"Professional",
            "subcategory":"Business Services",
            "type":"Services"
        }
    ],
    "sg:phone":"+1 401 729 9502",
    "sg:postcode":"02863",
    "sg:province":"RI",
    "wof:name":"World Show Business Inc",
    "wof:placetype":"venue"
},
  "geometry": {"coordinates":[-71.391901,41.896009],"type":"Point"}
}