{
  "type": "Feature",
  "properties": {
    "addr:full":"38 Acorn Ave Warwick RI 02888",
    "addr:housenumber":"38",
    "addr:postcode":"02888",
    "addr:street":"Acorn Ave",
    "iso:country":"US",
    "sg:address":"38 Acorn Ave",
    "sg:city":"Warwick",
    "sg:classifiers":[
        {
            "category":"Real Estate",
            "subcategory":"Real Estate Agent",
            "type":"Services"
        }
    ],
    "sg:phone":"+1 401 781 4538",
    "sg:postcode":"02888",
    "sg:province":"RI",
    "wof:name":"KUG Realty Co",
    "wof:placetype":"venue"
},
  "geometry": {"coordinates":[-71.430982,41.755889],"type":"Point"}
}