{
  "type": "Feature",
  "properties": {
    "iso:country":"US",
    "sg:address":"15 Quoquonset Ln",
    "sg:city":"Little Compton",
    "sg:classifiers":[
        {
            "category":"Sports & Exercise",
            "subcategory":"Gym",
            "type":"Entertainment"
        }
    ],
    "sg:phone":"+1 401 635 4462",
    "sg:postcode":"02837",
    "sg:province":"RI",
    "sg:tags":[
        "fitness",
        "physical",
        "facility"
    ],
    "wof:name":"Solutions Inc",
    "wof:placetype":"venue"
},
  "geometry": {"coordinates":[-71.173123,41.480994],"type":"Point"}
}