{
  "type": "Feature",
  "properties": {
    "iso:country":"US",
    "sg:address":"88 Rolfe Sq",
    "sg:city":"Cranston",
    "sg:classifiers":[
        {
            "category":"Restaurant",
            "type":"Food & Drink"
        }
    ],
    "sg:phone":"+1 401 467 6286",
    "sg:postcode":"02910",
    "sg:province":"RI",
    "sg:tags":[
        "delicatessen"
    ],
    "wof:name":"Dj's Deli 7 More",
    "wof:placetype":"venue"
},
  "geometry": {"coordinates":[-71.437155,41.774604],"type":"Point"}
}