{
  "type": "Feature",
  "properties": {
    "iso:country":"US",
    "sg:address":"20 Bosworth St",
    "sg:city":"Barrington",
    "sg:classifiers":[
        {
            "category":"Health Services",
            "subcategory":"Chiropractor",
            "type":"Services"
        }
    ],
    "sg:phone":"+1 401 247 2991",
    "sg:postcode":"02806",
    "sg:province":"RI",
    "sg:tags":[
        "chiropractic"
    ],
    "wof:name":"Casalino Family Chiropractic Inc",
    "wof:placetype":"venue"
},
  "geometry": {"coordinates":[-71.304799,41.73635],"type":"Point"}
}