{
  "type": "Feature",
  "properties": {
    "addr:full":"747 Aquidneck Ave Middletown RI 02842",
    "addr:housenumber":"747",
    "addr:postcode":"02842",
    "addr:street":"Aquidneck Ave",
    "iso:country":"US",
    "sg:address":"747 Aquidneck Ave",
    "sg:city":"Middletown",
    "sg:classifiers":[
        {
            "category":"Shopping",
            "subcategory":"Crafts & Fabrics",
            "type":"Retail Goods"
        }
    ],
    "sg:phone":"+1 401 846 2127",
    "sg:postcode":"02842",
    "sg:province":"RI",
    "sg:tags":[
        "material",
        "quilting",
        "supply"
    ],
    "wof:name":"Quilt Artisan",
    "wof:placetype":"venue"
},
  "geometry": {"coordinates":[-71.282437,41.508907],"type":"Point"}
}