{
  "type": "Feature",
  "properties": {
    "addr:full":"380 Atwood Ave Cranston RI 02920",
    "addr:housenumber":"380",
    "addr:postcode":"02920",
    "addr:street":"Atwood Ave",
    "iso:country":"US",
    "sg:address":"380 Atwood Ave",
    "sg:city":"Cranston",
    "sg:classifiers":[
        {
            "category":"Retail",
            "subcategory":"Auto Repair",
            "type":"Services"
        }
    ],
    "sg:phone":"+1 401 946 6888",
    "sg:postcode":"02920",
    "sg:province":"RI",
    "sg:tags":[
        "repairing",
        "automobile"
    ],
    "sg:website":"www.speedeecorp.com",
    "wof:name":"Speedee Oil Change & Tune Up",
    "wof:placetype":"venue"
},
  "geometry": {"coordinates":[-71.472824,41.785511],"type":"Point"}
}