{
  "type": "Feature",
  "properties": {
    "iso:country":"US",
    "sg:address":"58 High St",
    "sg:city":"Westerly",
    "sg:classifiers":[
        {
            "category":"Social Services",
            "type":"Services"
        }
    ],
    "sg:phone":"+1 401 596 3399",
    "sg:postcode":"02891",
    "sg:province":"RI",
    "sg:tags":[
        "worker"
    ],
    "wof:name":"Michael N Derosa Social Worker",
    "wof:placetype":"venue"
},
  "geometry": {"coordinates":[-71.83047500000001,41.377985],"type":"Point"}
}