{
  "type": "Feature",
  "properties": {
    "addr:full":"290 W Main Rd Little Compton RI 02837",
    "addr:housenumber":"290",
    "addr:postcode":"02837",
    "addr:street":"W Main Rd",
    "iso:country":"US",
    "sg:address":"290 W Main Rd",
    "sg:city":"Little Compton",
    "sg:classifiers":[
        {
            "category":"Building & Trades",
            "subcategory":"Construction",
            "type":"Services"
        }
    ],
    "sg:phone":"+1 401 635 8348",
    "sg:postcode":"02837",
    "sg:province":"RI",
    "sg:tags":[
        "carpentry",
        "contractor"
    ],
    "wof:name":"P M Thurston & Sons",
    "wof:placetype":"venue"
},
  "geometry": {"coordinates":[-71.193603,41.518204],"type":"Point"}
}