{
  "type": "Feature",
  "properties": {
    "iso:country":"US",
    "sg:address":"37 Howard St",
    "sg:city":"Newport",
    "sg:classifiers":[
        {
            "category":"Building & Trades",
            "subcategory":"Construction",
            "type":"Services"
        }
    ],
    "sg:phone":"+1 401 846 0683",
    "sg:postcode":"02840",
    "sg:province":"RI",
    "sg:tags":[
        "residential",
        "general",
        "nonresidential",
        "contractor"
    ],
    "wof:name":"George Hull Construction Co",
    "wof:placetype":"venue"
},
  "geometry": {"coordinates":[-71.313759,41.481054],"type":"Point"}
}