{
  "type": "Feature",
  "properties": {
    "addr:full":"30 Budlong Rd Cranston RI 02920",
    "addr:housenumber":"30",
    "addr:postcode":"02920",
    "addr:street":"Budlong Rd",
    "iso:country":"US",
    "sg:address":"30 Budlong Rd",
    "sg:city":"Cranston",
    "sg:classifiers":[
        {
            "category":"Manufacturing",
            "subcategory":"Glass & Minerals",
            "type":"Manufacturing & Wholesale Goods"
        }
    ],
    "sg:phone":"+1 401 942 4800",
    "sg:postcode":"02920",
    "sg:province":"RI",
    "sg:tags":[
        "concrete",
        "product",
        "mfg"
    ],
    "wof:name":"Park Ave Cement Block Co Inc",
    "wof:placetype":"venue"
},
  "geometry": {"coordinates":[-71.45732599999999,41.782564],"type":"Point"}
}