{
  "type": "Feature",
  "properties": {
    "iso:country":"US",
    "sg:address":"951 Hope St",
    "sg:city":"Providence",
    "sg:classifiers":[
        {
            "category":"Home & Garden",
            "subcategory":"Home Furnishings",
            "type":"Retail Goods"
        },
        {
            "category":"Building & Trades",
            "subcategory":"Construction",
            "type":"Services"
        },
        {
            "category":"Home & Garden",
            "subcategory":"Furniture",
            "type":"Retail Goods"
        }
    ],
    "sg:phone":"+1 401 383 7105",
    "sg:postcode":"02906",
    "sg:province":"RI",
    "sg:tags":[
        "equipment-household",
        "refacing",
        "resurfacing",
        "cabinet",
        "maker",
        "cabinets-refinishing",
        "kitchen"
    ],
    "wof:name":"The Art Of The Kitchen Ltd",
    "wof:placetype":"venue"
},
  "geometry": {"coordinates":[-71.393062,41.852977],"type":"Point"}
}