{
  "type": "Feature",
  "properties": {
    "addr:full":"1 Custom House St Providence RI 02903",
    "addr:housenumber":"1",
    "addr:postcode":"02903",
    "addr:street":"Custom House St",
    "iso:country":"US",
    "sg:address":"1 Custom House St",
    "sg:city":"Providence",
    "sg:classifiers":[
        {
            "category":"Banks & Credit Unions",
            "subcategory":"Bank",
            "type":"Services"
        }
    ],
    "sg:phone":"+1 401 351 0800",
    "sg:postcode":"02903",
    "sg:province":"RI",
    "sg:tags":[
        "loan",
        "real estate"
    ],
    "wof:name":"Cityview Mortgage Corp",
    "wof:placetype":"venue"
},
  "geometry": {"coordinates":[-71.408627,41.824219],"type":"Point"}
}