{
  "type": "Feature",
  "properties": {
    "addr:full":"160 Franklin St Warren RI 02885",
    "addr:housenumber":"160",
    "addr:postcode":"02885",
    "addr:street":"Franklin St",
    "iso:country":"US",
    "sg:address":"160 Franklin St",
    "sg:city":"Warren",
    "sg:classifiers":[
        {
            "category":"Building & Trades",
            "subcategory":"Construction",
            "type":"Services"
        }
    ],
    "sg:phone":"+1 401 253 8500",
    "sg:postcode":"02885",
    "sg:province":"RI",
    "sg:tags":[
        "bathroom",
        "remodeling"
    ],
    "sg:website":"www.bathfitter.com",
    "wof:name":"Bath Fitter",
    "wof:placetype":"venue"
},
  "geometry": {"coordinates":[-71.275794,41.725746],"type":"Point"}
}