{
  "type": "Feature",
  "properties": {
    "addr:full":"2741 Hartford Ave Johnston RI 02919",
    "addr:housenumber":"2741",
    "addr:postcode":"02919",
    "addr:street":"Hartford Ave",
    "iso:country":"US",
    "sg:address":"2741 Hartford Ave",
    "sg:city":"Johnston",
    "sg:classifiers":[
        {
            "category":"Retail",
            "subcategory":"Auto Repair",
            "type":"Services"
        }
    ],
    "sg:phone":"+1 401 934 3338",
    "sg:postcode":"02919",
    "sg:province":"RI",
    "sg:tags":[
        "body",
        "automobile",
        "painting"
    ],
    "wof:name":"Casale Auto Sales",
    "wof:placetype":"venue"
},
  "geometry": {"coordinates":[-71.559957,41.833639],"type":"Point"}
}