{
  "type": "Feature",
  "properties": {
    "addr:full":"8 Marine Ave Warwick RI 02888",
    "addr:housenumber":"8",
    "addr:postcode":"02888",
    "addr:street":"Marine Ave",
    "iso:country":"US",
    "sg:address":"8 Marine Ave",
    "sg:city":"Warwick",
    "sg:classifiers":[
        {
            "category":"Social Services",
            "subcategory":"Job Training",
            "type":"Services"
        }
    ],
    "sg:phone":"+1 401 785 0036",
    "sg:postcode":"02888",
    "sg:province":"RI",
    "wof:name":"Career Quest",
    "wof:placetype":"venue"
},
  "geometry": {"coordinates":[-71.38773999999999,41.754362],"type":"Point"}
}