{
  "type": "Feature",
  "properties": {
    "iso:country":"US",
    "sg:address":"7 Ninigret Ave",
    "sg:city":"Providence",
    "sg:classifiers":[
        {
            "category":"Manufacturing",
            "subcategory":"Metals",
            "type":"Manufacturing & Wholesale Goods"
        }
    ],
    "sg:phone":"+1 401 781 6800",
    "sg:postcode":"02907",
    "sg:province":"RI",
    "sg:tags":[
        "on",
        "etching"
    ],
    "wof:name":"International Etching Inc",
    "wof:placetype":"venue"
},
  "geometry": {"coordinates":[-71.43699100000001,41.803903],"type":"Point"}
}