{
  "type": "Feature",
  "properties": {
    "iso:country":"US",
    "sg:address":"107 Fletcher Ave",
    "sg:city":"Cranston",
    "sg:classifiers":[
        {
            "category":"Retail",
            "subcategory":"Auto Repair",
            "type":"Services"
        }
    ],
    "sg:phone":"+1 401 464 8630",
    "sg:postcode":"02920",
    "sg:province":"RI",
    "sg:tags":[
        "general"
    ],
    "wof:name":"Rodriguez Jamie Costello",
    "wof:placetype":"venue"
},
  "geometry": {"coordinates":[-71.47556899999999,41.794851],"type":"Point"}
}