{
  "type": "Feature",
  "properties": {
    "addr:full":"20 Randall St Providence RI 02904",
    "addr:housenumber":"20",
    "addr:postcode":"02904",
    "addr:street":"Randall St",
    "iso:country":"US",
    "sg:address":"20 Randall St",
    "sg:city":"Providence",
    "sg:classifiers":[
        {
            "category":"Organizations",
            "subcategory":"Religious Organization",
            "type":"Services"
        }
    ],
    "sg:phone":"+1 401 781 3382",
    "sg:postcode":"02904",
    "sg:province":"RI",
    "sg:tags":[
        "church"
    ],
    "wof:name":"Cambodians For Jesus Pntcstl",
    "wof:placetype":"venue"
},
  "geometry": {"coordinates":[-71.411143,41.836953],"type":"Point"}
}