{
  "type": "Feature",
  "properties": {
    "addr:full":"42 Weybosset St Providence RI 02903",
    "addr:housenumber":"42",
    "addr:postcode":"02903",
    "addr:street":"Weybosset St",
    "iso:country":"US",
    "sg:address":"42 Weybosset St",
    "sg:city":"Providence",
    "sg:classifiers":[
        {
            "category":"Building & Trades",
            "subcategory":"Construction",
            "type":"Services"
        }
    ],
    "sg:phone":"+1 401 861 4900",
    "sg:postcode":"02903",
    "sg:province":"RI",
    "sg:tags":[
        "interior",
        "design"
    ],
    "wof:name":"Barricelli Janice Interior Design",
    "wof:placetype":"venue"
},
  "geometry": {"coordinates":[-71.40949000000001,41.824158],"type":"Point"}
}