{
  "type": "Feature",
  "properties": {
    "addr:full":"17 Ashton St Pawtucket RI 02860",
    "addr:housenumber":"17",
    "addr:postcode":"02860",
    "addr:street":"Ashton St",
    "iso:country":"US",
    "sg:address":"17 Ashton St",
    "sg:city":"Pawtucket",
    "sg:classifiers":[
        {
            "category":"Freight",
            "type":"Transportation"
        }
    ],
    "sg:phone":"+1 401 475 7115",
    "sg:postcode":"02860",
    "sg:province":"RI",
    "sg:tags":[
        "delivery"
    ],
    "wof:name":"Eastern Connection",
    "wof:placetype":"venue"
},
  "geometry": {"coordinates":[-71.370801,41.87916],"type":"Point"}
}