{
  "type": "Feature",
  "properties": {
    "addr:full":"600 Plainfield St Providence RI 02909",
    "addr:housenumber":"600",
    "addr:postcode":"02909",
    "addr:street":"Plainfield St",
    "iso:country":"US",
    "sg:address":"600 Plainfield St",
    "sg:city":"Providence",
    "sg:classifiers":[
        {
            "category":"Food & Beverages",
            "subcategory":"Groceries & Convenience Stores",
            "type":"Retail Goods"
        }
    ],
    "sg:phone":"+1 401 944 4646",
    "sg:postcode":"02909",
    "sg:province":"RI",
    "sg:tags":[
        "market"
    ],
    "wof:name":"Anthony's Super Market",
    "wof:placetype":"venue"
},
  "geometry": {"coordinates":[-71.457848,41.812858],"type":"Point"}
}