{
  "type": "Feature",
  "properties": {
    "iso:country":"US",
    "sg:address":"136 Rhode Island Ave",
    "sg:city":"Newport",
    "sg:classifiers":[
        {
            "category":"Health Services",
            "subcategory":"Doctor",
            "type":"Services"
        }
    ],
    "sg:phone":"+1 401 849 6446",
    "sg:postcode":"02840",
    "sg:province":"RI",
    "sg:tags":[
        "physician",
        "surgeon"
    ],
    "wof:name":"Elie Cohen Inc",
    "wof:placetype":"venue"
},
  "geometry": {"coordinates":[-71.302949,41.48887],"type":"Point"}
}