{
  "type": "Feature",
  "properties": {
    "addr:full":"39 Villa Ave Providence RI 02904",
    "addr:housenumber":"39",
    "addr:postcode":"02904",
    "addr:street":"Villa Ave",
    "iso:country":"US",
    "sg:address":"39 Villa Ave",
    "sg:city":"Providence",
    "sg:classifiers":[
        {
            "category":"Retail",
            "subcategory":"Repair Shop",
            "type":"Services"
        }
    ],
    "sg:phone":"+1 401 353 6117",
    "sg:postcode":"02904",
    "sg:province":"RI",
    "sg:tags":[
        "electrical"
    ],
    "wof:name":"Larrys Appliance Service Inc",
    "wof:placetype":"venue"
},
  "geometry": {"coordinates":[-71.442256,41.861037],"type":"Point"}
}