{
  "type": "Feature",
  "properties": {
    "addr:full":"30 Jefferson Park Rd Warwick RI 02888",
    "addr:housenumber":"30",
    "addr:postcode":"02888",
    "addr:street":"Jefferson Park Rd",
    "iso:country":"US",
    "sg:address":"30 Jefferson Park Rd",
    "sg:city":"Warwick",
    "sg:classifiers":[
        {
            "category":"Manufacturing",
            "subcategory":"Tools & Machinery",
            "type":"Manufacturing & Wholesale Goods"
        }
    ],
    "sg:phone":"+1 401 736 9600",
    "sg:postcode":"02888",
    "sg:province":"RI",
    "sg:tags":[
        "optical"
    ],
    "sg:website":"www.oraclelens.com",
    "wof:name":"Oracle Lens Mfg Corp",
    "wof:placetype":"venue"
},
  "geometry": {"coordinates":[-71.43373200000001,41.754035],"type":"Point"}
}