{
  "type": "Feature",
  "properties": {
    "iso:country":"US",
    "sg:address":"603 Old Smithfield Rd",
    "sg:city":"North Smithfield",
    "sg:classifiers":[
        {
            "category":"Manufacturing",
            "subcategory":"Chemicals & Compounds",
            "type":"Manufacturing & Wholesale Goods"
        }
    ],
    "sg:phone":"+1 401 766 5909",
    "sg:postcode":"02896",
    "sg:province":"RI",
    "sg:tags":[
        "fertilizer",
        "mixing",
        "only"
    ],
    "wof:name":"Homestead Co",
    "wof:placetype":"venue"
},
  "geometry": {"coordinates":[-71.5063,41.970996],"type":"Point"}
}