{
  "type": "Feature",
  "properties": {
    "iso:country":"US",
    "sg:address":"79 Coolridge Rd",
    "sg:city":"Greenville",
    "sg:classifiers":[
        {
            "category":"Professional",
            "type":"Services"
        }
    ],
    "sg:phone":"+1 401 949 2094",
    "sg:postcode":"02828",
    "sg:province":"RI",
    "wof:name":"Suburban Land Co",
    "wof:placetype":"venue"
},
  "geometry": {"coordinates":[-71.558729,41.865352],"type":"Point"}
}