{
  "type": "Feature",
  "properties": {
    "addr:full":"154 Smithfield Ave Pawtucket RI 02860",
    "addr:housenumber":"154",
    "addr:postcode":"02860",
    "addr:street":"Smithfield Ave",
    "iso:country":"US",
    "sg:address":"154 Smithfield Ave",
    "sg:city":"Pawtucket",
    "sg:classifiers":[
        {
            "category":"Sports & Exercise",
            "subcategory":"Gym",
            "type":"Entertainment"
        }
    ],
    "sg:phone":"+1 401 305 5585",
    "sg:postcode":"02860",
    "sg:province":"RI",
    "sg:website":"crosstrainersri.com",
    "wof:name":"Cross Trainers Health and Fitness",
    "wof:placetype":"venue"
},
  "geometry": {"coordinates":[-71.412166,41.86326],"type":"Point"}
}