{
  "type": "Feature",
  "properties": {
    "addr:full":"200 Manville Hill Rd Cumberland RI 02864",
    "addr:housenumber":"200",
    "addr:postcode":"02864",
    "addr:street":"Manville Hill Rd",
    "iso:country":"US",
    "sg:address":"200 Manville Hill Rd",
    "sg:city":"Cumberland",
    "sg:classifiers":[
        {
            "category":"Building & Trades",
            "subcategory":"Cleaning & Sanitation",
            "type":"Services"
        }
    ],
    "sg:phone":"+1 401 744 2359",
    "sg:postcode":"02864",
    "sg:province":"RI",
    "sg:tags":[
        "residential",
        "commercial",
        "janitorial"
    ],
    "wof:name":"Sunrise Cleaning Company Inc",
    "wof:placetype":"venue"
},
  "geometry": {"coordinates":[-71.459419,41.976786],"type":"Point"}
}