{
  "type": "Feature",
  "properties": {
    "iso:country":"US",
    "sg:address":"2732 E Main Rd",
    "sg:city":"Portsmouth",
    "sg:classifiers":[
        {
            "category":"Organizations",
            "subcategory":"Religious Organization",
            "type":"Services"
        }
    ],
    "sg:phone":"+1 401 683 4005",
    "sg:postcode":"02871",
    "sg:province":"RI",
    "sg:tags":[
        "church"
    ],
    "wof:name":"Portsmouth United Methodist",
    "wof:placetype":"venue"
},
  "geometry": {"coordinates":[-71.247665,41.602483],"type":"Point"}
}