{
  "type": "Feature",
  "properties": {
    "addr:full":"151 Douglas Pike North Smithfield RI 02896",
    "addr:housenumber":"151",
    "addr:postcode":"02896",
    "addr:street":"Douglas Pike",
    "iso:country":"US",
    "sg:address":"151 Douglas Pike",
    "sg:city":"North Smithfield",
    "sg:classifiers":[
        {
            "category":"Personal",
            "subcategory":"Tanning Parlor",
            "type":"Services"
        }
    ],
    "sg:phone":"+1 401 349 4551",
    "sg:postcode":"02896",
    "sg:province":"RI",
    "sg:tags":[
        "salon"
    ],
    "wof:name":"Sunset Tans",
    "wof:placetype":"venue"
},
  "geometry": {"coordinates":[-71.583853,41.961125],"type":"Point"}
}