{
  "type": "Feature",
  "properties": {
    "iso:country":"US",
    "sg:address":"34 Narragansett Ave",
    "sg:city":"Jamestown",
    "sg:classifiers":[
        {
            "category":"Restaurant",
            "type":"Food & Drink"
        }
    ],
    "sg:phone":"+1 401 423 0907",
    "sg:postcode":"02835",
    "sg:province":"RI",
    "sg:tags":[
        "eating"
    ],
    "wof:name":"Theatre Family Restaurant",
    "wof:placetype":"venue"
},
  "geometry": {"coordinates":[-71.369727,41.496331],"type":"Point"}
}