{
  "type": "Feature",
  "properties": {
    "iso:country":"US",
    "sg:address":"8 Rock St",
    "sg:city":"Tiverton",
    "sg:classifiers":[
        {
            "category":"Professional",
            "type":"Services"
        }
    ],
    "sg:phone":"+1 401 624 2290",
    "sg:postcode":"02878",
    "sg:province":"RI",
    "wof:name":"North Tiverton Sportsmens Club",
    "wof:placetype":"venue"
},
  "geometry": {"coordinates":[-71.18325,41.672633],"type":"Point"}
}