{
  "type": "Feature",
  "properties": {
    "addr:full":"110 High St Ashaway RI 02804",
    "addr:housenumber":"110",
    "addr:postcode":"02804",
    "addr:street":"High St",
    "iso:country":"US",
    "sg:address":"110 High St",
    "sg:city":"Ashaway",
    "sg:classifiers":[
        {
            "category":"Organizations",
            "subcategory":"Religious Organization",
            "type":"Services"
        }
    ],
    "sg:phone":"+1 401 377 4340",
    "sg:postcode":"02804",
    "sg:province":"RI",
    "sg:tags":[
        "church"
    ],
    "sg:website":"www.trinityashaway.org",
    "wof:name":"Trinity Lutheran Church",
    "wof:placetype":"venue"
},
  "geometry": {"coordinates":[-71.795768,41.435899],"type":"Point"}
}