{
  "type": "Feature",
  "properties": {
    "iso:country":"US",
    "sg:address":"239 Harris Ave",
    "sg:city":"Providence",
    "sg:classifiers":[
        {
            "category":"Communications",
            "type":"Services"
        }
    ],
    "sg:phone":"+1 401 351 2248",
    "sg:postcode":"02903",
    "sg:province":"RI",
    "sg:tags":[
        "web",
        "design"
    ],
    "wof:name":"White Whale Web Services",
    "wof:placetype":"venue"
},
  "geometry": {"coordinates":[-71.42765199999999,41.826484],"type":"Point"}
}