{
  "type": "Feature",
  "properties": {
    "iso:country":"US",
    "sg:address":"14 Vallette St",
    "sg:city":"Cranston",
    "sg:classifiers":[
        {
            "category":"Building & Trades",
            "subcategory":"Plumbing",
            "type":"Services"
        }
    ],
    "sg:phone":"+1 401 490 7081",
    "sg:postcode":"02920",
    "sg:province":"RI",
    "sg:tags":[
        "sheet",
        "work",
        "metal",
        "contractor"
    ],
    "wof:name":"Narragansett Sheet Metal",
    "wof:placetype":"venue"
},
  "geometry": {"coordinates":[-71.464079,41.778565],"type":"Point"}
}