{
  "type": "Feature",
  "properties": {
    "iso:country":"US",
    "sg:address":"807 Broad St",
    "sg:city":"Providence",
    "sg:classifiers":[
        {
            "category":"Shopping",
            "subcategory":"Computers & Home Electronics",
            "type":"Retail Goods"
        }
    ],
    "sg:phone":"+1 401 383 9444",
    "sg:postcode":"02907",
    "sg:province":"RI",
    "sg:tags":[
        "equipment",
        "satellite",
        "system"
    ],
    "wof:name":"TV Mas",
    "wof:placetype":"venue"
},
  "geometry": {"coordinates":[-71.418442,41.801655],"type":"Point"}
}