{
  "type": "Feature",
  "properties": {
    "iso:country":"US",
    "sg:address":"6 Riidam Way",
    "sg:city":"Charlestown",
    "sg:classifiers":[
        {
            "category":"Building & Trades",
            "subcategory":"Construction",
            "type":"Services"
        }
    ],
    "sg:phone":"+1 401 377 7700",
    "sg:postcode":"02813",
    "sg:province":"RI",
    "sg:tags":[
        "carpentry",
        "contractor"
    ],
    "wof:name":"Closet Creations",
    "wof:placetype":"venue"
},
  "geometry": {"coordinates":[-71.721243,41.392607],"type":"Point"}
}