{
  "type": "Feature",
  "properties": {
    "iso:country":"US",
    "sg:address":"125 S Main St",
    "sg:city":"Woonsocket",
    "sg:classifiers":[
        {
            "category":"Wholesale",
            "subcategory":"Machinery & Supplies",
            "type":"Manufacturing & Wholesale Goods"
        }
    ],
    "sg:phone":"+1 401 769 0200",
    "sg:postcode":"02895",
    "sg:province":"RI",
    "sg:tags":[
        "equipment",
        "welding"
    ],
    "wof:name":"Woonsocket Supply Co",
    "wof:placetype":"venue"
},
  "geometry": {"coordinates":[-71.518287,41.99893],"type":"Point"}
}