{
  "type": "Feature",
  "properties": {
    "iso:country":"US",
    "sg:address":"936 Smithfield Ave",
    "sg:city":"Lincoln",
    "sg:classifiers":[
        {
            "category":"Professional",
            "subcategory":"Lawyer & Legal Services",
            "type":"Services"
        }
    ],
    "sg:phone":"+1 401 724 2400",
    "sg:postcode":"02865",
    "sg:province":"RI",
    "sg:tags":[
        "firm",
        "law"
    ],
    "wof:name":"Oster Law Office",
    "wof:placetype":"venue"
},
  "geometry": {"coordinates":[-71.414383,41.88451],"type":"Point"}
}