{
  "type": "Feature",
  "properties": {
    "iso:country":"US",
    "sg:address":"595 Potter Rd",
    "sg:city":"North Kingstown",
    "sg:classifiers":[
        {
            "category":"Health Services",
            "subcategory":"Doctor",
            "type":"Services"
        }
    ],
    "sg:phone":"+1 401 884 5292",
    "sg:postcode":"02852",
    "sg:province":"RI",
    "wof:name":"Mirmirani Consultant",
    "wof:placetype":"venue"
},
  "geometry": {"coordinates":[-71.436718,41.617488],"type":"Point"}
}