{
  "type": "Feature",
  "properties": {
    "iso:country":"US",
    "sg:address":"400 Bald Hill Rd Ste F6",
    "sg:city":"Warwick",
    "sg:phone":"+1 401 732 5672",
    "sg:postcode":"02886",
    "sg:province":"RI",
    "wof:name":"Tilt",
    "wof:placetype":"venue"
},
  "geometry": {"coordinates":[-71.479958,41.726528],"type":"Point"}
}