{
  "type": "Feature",
  "properties": {
    "iso:country":"US",
    "sg:address":"1222 Smith St",
    "sg:city":"Providence",
    "sg:classifiers":[
        {
            "category":"Food & Beverages",
            "subcategory":"Groceries & Convenience Stores",
            "type":"Retail Goods"
        }
    ],
    "sg:phone":"+1 401 490 0330",
    "sg:postcode":"02908",
    "sg:province":"RI",
    "wof:name":"Sunrise Market",
    "wof:placetype":"venue"
},
  "geometry": {"coordinates":[-71.45169799999999,41.8461],"type":"Point"}
}