{
  "type": "Feature",
  "properties": {
    "addr:full":"166 Valley St # 10 Providence RI 02909",
    "addr:housenumber":"166;10",
    "addr:postcode":"02909",
    "addr:street":"Valley St #",
    "iso:country":"US",
    "sg:address":"166 Valley St # 10",
    "sg:city":"Providence",
    "sg:classifiers":[
        {
            "category":"Food & Beverages",
            "subcategory":"Bakery",
            "type":"Retail Goods"
        }
    ],
    "sg:phone":"+1 401 861 4266",
    "sg:postcode":"02909",
    "sg:province":"RI",
    "sg:tags":[
        "sandwich"
    ],
    "wof:name":"Icon Cafe",
    "wof:placetype":"venue"
},
  "geometry": {"coordinates":[-71.44096399999999,41.821021],"type":"Point"}
}