{
  "type": "Feature",
  "properties": {
    "iso:country":"US",
    "sg:address":"34 Nooseneck Hill Rd",
    "sg:city":"West Greenwich",
    "sg:classifiers":[
        {
            "category":"Shopping",
            "subcategory":"Books",
            "type":"Retail Goods"
        }
    ],
    "sg:phone":"+1 401 397 5500",
    "sg:postcode":"02817",
    "sg:province":"RI",
    "sg:tags":[
        "dealer"
    ],
    "wof:name":"All Booked Up",
    "wof:placetype":"venue"
},
  "geometry": {"coordinates":[-71.604309,41.656071],"type":"Point"}
}