{
  "type": "Feature",
  "properties": {
    "addr:full":"10 Christies Lndg Newport RI 02840",
    "addr:housenumber":"10",
    "addr:postcode":"02840",
    "addr:street":"Christies Lndg",
    "iso:country":"US",
    "sg:address":"10 Christies Lndg",
    "sg:city":"Newport",
    "sg:classifiers":[
        {
            "category":"Travel",
            "subcategory":"Hotels & Motels",
            "type":"Entertainment"
        }
    ],
    "sg:phone":"+1 401 849 2676",
    "sg:postcode":"02840",
    "sg:province":"RI",
    "sg:tags":[
        "operation"
    ],
    "wof:name":"Beach Bums Inc",
    "wof:placetype":"venue"
},
  "geometry": {"coordinates":[-71.316327,41.483709],"type":"Point"}
}