{
  "type": "Feature",
  "properties": {
    "iso:country":"US",
    "sg:address":"76 Payton Ave",
    "sg:city":"Warwick",
    "sg:classifiers":[
        {
            "category":"Building & Trades",
            "subcategory":"Construction",
            "type":"Services"
        }
    ],
    "sg:phone":"+1 401 736 0610",
    "sg:postcode":"02889",
    "sg:province":"RI",
    "sg:tags":[
        "house"
    ],
    "wof:name":"Gil Remodeling Inc",
    "wof:placetype":"venue"
},
  "geometry": {"coordinates":[-71.37005600000001,41.704007],"type":"Point"}
}