{
  "type": "Feature",
  "properties": {
    "iso:country":"US",
    "sg:address":"1085 Cranston St",
    "sg:city":"Cranston",
    "sg:classifiers":[
        {
            "category":"Retail",
            "subcategory":"Auto Repair",
            "type":"Services"
        }
    ],
    "sg:phone":"+1 401 942 9700",
    "sg:postcode":"02920",
    "sg:province":"RI",
    "sg:tags":[
        "body"
    ],
    "sg:website":"www.gershkoff.com",
    "wof:name":"Gershkoff Auto Body",
    "wof:placetype":"venue"
},
  "geometry": {"coordinates":[-71.44888400000001,41.796899],"type":"Point"}
}