{
  "type": "Feature",
  "properties": {
    "addr:full":"700 Maple Ave Barrington RI 02806",
    "addr:housenumber":"700",
    "addr:postcode":"02806",
    "addr:street":"Maple Ave",
    "iso:country":"US",
    "sg:address":"700 Maple Ave",
    "sg:city":"Barrington",
    "sg:classifiers":[
        {
            "category":"Professional",
            "subcategory":"Lawyer & Legal Services",
            "type":"Services"
        }
    ],
    "sg:phone":"+1 401 247 7976",
    "sg:postcode":"02806",
    "sg:province":"RI",
    "sg:tags":[
        "attorney"
    ],
    "wof:name":"Joseph M Codega",
    "wof:placetype":"venue"
},
  "geometry": {"coordinates":[-71.327656,41.738737],"type":"Point"}
}