{
  "type": "Feature",
  "properties": {
    "addr:full":"690 Warren Ave East Providence RI 02914",
    "addr:housenumber":"690",
    "addr:postcode":"02914",
    "addr:street":"Warren Ave",
    "iso:country":"US",
    "sg:address":"690 Warren Ave",
    "sg:city":"East Providence",
    "sg:classifiers":[
        {
            "category":"Insurance",
            "subcategory":"Insurance Agent",
            "type":"Services"
        }
    ],
    "sg:phone":"+1 401 431 6205",
    "sg:postcode":"02914",
    "sg:province":"RI",
    "sg:tags":[
        "consultant"
    ],
    "wof:name":"EPS Settlements Group",
    "wof:placetype":"venue"
},
  "geometry": {"coordinates":[-71.354973,41.810241],"type":"Point"}
}