{
  "type": "Feature",
  "properties": {
    "addr:full":"59 Stilson Rd Wyoming RI 02898",
    "addr:housenumber":"59",
    "addr:postcode":"02898",
    "addr:street":"Stilson Rd",
    "iso:country":"US",
    "sg:address":"59 Stilson Rd",
    "sg:city":"Wyoming",
    "sg:classifiers":[
        {
            "category":"Building & Trades",
            "subcategory":"Construction",
            "type":"Services"
        }
    ],
    "sg:phone":"+1 401 539 4215",
    "sg:postcode":"02898",
    "sg:province":"RI",
    "sg:tags":[
        "paint",
        "varnish",
        "removal"
    ],
    "wof:name":"Safety Marking Inc",
    "wof:placetype":"venue"
},
  "geometry": {"coordinates":[-71.687251,41.513094],"type":"Point"}
}