{
  "type": "Feature",
  "properties": {
    "addr:full":"92 Dean Ave Smithfield RI 02917",
    "addr:housenumber":"92",
    "addr:postcode":"02917",
    "addr:street":"Dean Ave",
    "iso:country":"US",
    "sg:address":"92 Dean Ave",
    "sg:city":"Smithfield",
    "sg:classifiers":[
        {
            "category":"Manufacturing",
            "subcategory":"Retail Goods",
            "type":"Manufacturing & Wholesale Goods"
        },
        {
            "category":"Wholesale",
            "subcategory":"Non-durable Goods",
            "type":"Manufacturing & Wholesale Goods"
        }
    ],
    "sg:phone":"+1 401 232 3836",
    "sg:postcode":"02917",
    "sg:province":"RI",
    "sg:tags":[
        "stamp"
    ],
    "wof:name":"Anjil International Inc",
    "wof:placetype":"venue"
},
  "geometry": {"coordinates":[-71.500984,41.870594],"type":"Point"}
}