{
  "type": "Feature",
  "properties": {
    "iso:country":"US",
    "sg:address":"10 Davol Sq Ste 305",
    "sg:city":"Providence",
    "sg:classifiers":[
        {
            "category":"Personal",
            "subcategory":"Day Spa",
            "type":"Services"
        }
    ],
    "sg:phone":"+1 401 351 5250",
    "sg:postcode":"02903",
    "sg:province":"RI",
    "wof:name":"Chestnuts Salon & Day Spa",
    "wof:placetype":"venue"
},
  "geometry": {"coordinates":[-71.408798,41.8148],"type":"Point"}
}