{
  "type": "Feature",
  "properties": {
    "addr:full":"333 Adelaide Ave Providence RI 02907",
    "addr:housenumber":"333",
    "addr:postcode":"02907",
    "addr:street":"Adelaide Ave",
    "iso:country":"US",
    "sg:address":"333 Adelaide Ave",
    "sg:city":"Providence",
    "sg:classifiers":[
        {
            "category":"Banks & Credit Unions",
            "subcategory":"Bank",
            "type":"Services"
        }
    ],
    "sg:phone":"+1 401 467 0017",
    "sg:postcode":"02907",
    "sg:province":"RI",
    "wof:name":"Citizens Bank",
    "wof:placetype":"venue"
},
  "geometry": {"coordinates":[-71.42980799999999,41.794519],"type":"Point"}
}