{
  "type": "Feature",
  "properties": {
    "iso:country":"US",
    "sg:address":"693 Broad St",
    "sg:city":"Providence",
    "sg:classifiers":[
        {
            "category":"Landmark",
            "subcategory":"Historic",
            "type":"Public Place"
        },
        {
            "category":"Professional",
            "subcategory":"Employment Agencies",
            "type":"Services"
        }
    ],
    "sg:phone":"+1 401 273 2330",
    "sg:postcode":"02907",
    "sg:province":"RI",
    "sg:tags":[
        "historical",
        "employer"
    ],
    "wof:name":"Elmwood Foundation for Architectural & Historic Preservation",
    "wof:placetype":"venue"
},
  "geometry": {"coordinates":[-71.419612,41.805233],"type":"Point"}
}