{
  "type": "Feature",
  "properties": {
    "iso:country":"US",
    "sg:address":"52 Lynde St",
    "sg:city":"Providence",
    "sg:classifiers":[
        {
            "category":"Real Estate",
            "subcategory":"Real Estate Services",
            "type":"Services"
        }
    ],
    "sg:phone":"+1 401 351 4023",
    "sg:postcode":"02908",
    "sg:province":"RI",
    "sg:tags":[
        "home",
        "inspector"
    ],
    "wof:name":"A-One Pest Control Co",
    "wof:placetype":"venue"
},
  "geometry": {"coordinates":[-71.451358,41.847997],"type":"Point"}
}