{
  "type": "Feature",
  "properties": {
    "iso:country":"US",
    "sg:address":"549 Branch Ave",
    "sg:city":"Providence",
    "sg:classifiers":[
        {
            "category":"Real Estate",
            "subcategory":"Real Estate Agent",
            "type":"Services"
        }
    ],
    "sg:phone":"+1 401 331 8277",
    "sg:postcode":"02904",
    "sg:province":"RI",
    "wof:name":"Cd Puleo Prudential Realty",
    "wof:placetype":"venue"
},
  "geometry": {"coordinates":[-71.424352,41.852234],"type":"Point"}
}