{
  "type": "Feature",
  "properties": {
    "iso:country":"US",
    "sg:address":"435 Sawmill Rd",
    "sg:city":"North Scituate",
    "sg:classifiers":[
        {
            "category":"Building & Trades",
            "subcategory":"Electrical",
            "type":"Services"
        }
    ],
    "sg:phone":"+1 401 934 7663",
    "sg:postcode":"02857",
    "sg:province":"RI",
    "sg:tags":[
        "electrical",
        "contractor"
    ],
    "sg:website":"www.applevalleyalarms.com",
    "wof:name":"Apple Valley Alarms LLC",
    "wof:placetype":"venue"
},
  "geometry": {"coordinates":[-71.60449,41.860537],"type":"Point"}
}