{
  "type": "Feature",
  "properties": {
    "addr:full":"142 Long Wharf Newport RI 02840",
    "addr:housenumber":"142",
    "addr:postcode":"02840",
    "addr:street":"Long Wharf",
    "iso:country":"US",
    "sg:address":"142 Long Wharf",
    "sg:city":"Newport",
    "sg:classifiers":[
        {
            "category":"Travel",
            "subcategory":"Hotels & Motels",
            "type":"Entertainment"
        }
    ],
    "sg:phone":"+1 401 845 0100",
    "sg:postcode":"02840",
    "sg:province":"RI",
    "sg:tags":[
        "resort"
    ],
    "wof:name":"Long Wharf Resort",
    "wof:placetype":"venue"
},
  "geometry": {"coordinates":[-71.31849200000001,41.489517],"type":"Point"}
}