{
  "type": "Feature",
  "properties": {
    "iso:country":"US",
    "sg:address":"31 Buck Hill Rd",
    "sg:city":"Johnston",
    "sg:classifiers":[
        {
            "category":"Retail",
            "subcategory":"Auto Repair",
            "type":"Services"
        }
    ],
    "sg:phone":"+1 401 464 4499",
    "sg:postcode":"02919",
    "sg:province":"RI",
    "sg:tags":[
        "general"
    ],
    "wof:name":"Atomic Motor Sport",
    "wof:placetype":"venue"
},
  "geometry": {"coordinates":[-71.529021,41.79643],"type":"Point"}
}