{
  "type": "Feature",
  "properties": {
    "addr:full":"11 Scott Ln Bristol RI 02809",
    "addr:housenumber":"11",
    "addr:postcode":"02809",
    "addr:street":"Scott Ln",
    "iso:country":"US",
    "sg:address":"11 Scott Ln",
    "sg:city":"Bristol",
    "sg:classifiers":[
        {
            "category":"Building & Trades",
            "subcategory":"Landscaping Services",
            "type":"Services"
        },
        {
            "category":"Home & Garden",
            "subcategory":"Garden Supply",
            "type":"Retail Goods"
        },
        {
            "category":"Building & Trades",
            "subcategory":"Construction",
            "type":"Services"
        }
    ],
    "sg:phone":"+1 401 323 3489",
    "sg:postcode":"02809",
    "sg:province":"RI",
    "sg:tags":[
        "lawn",
        "designer",
        "excavation",
        "consultant",
        "mulch",
        "contractor",
        "maintenance",
        "landscape"
    ],
    "wof:name":"M & D Landscaping",
    "wof:placetype":"venue"
},
  "geometry": {"coordinates":[-71.260262,41.690508],"type":"Point"}
}