{
  "type": "Feature",
  "properties": {
    "iso:country":"US",
    "sg:address":"1572 Lonsdale Ave",
    "sg:city":"Lincoln",
    "sg:classifiers":[
        {
            "category":"Education",
            "subcategory":"Dance Studio",
            "type":"Public Place"
        },
        {
            "category":"Education",
            "subcategory":"School",
            "type":"Public Place"
        }
    ],
    "sg:phone":"+1 401 723 5850",
    "sg:postcode":"02865",
    "sg:province":"RI",
    "wof:name":"Ann Carr Dance Studio",
    "wof:placetype":"venue"
},
  "geometry": {"coordinates":[-71.404197,41.904418],"type":"Point"}
}