{
  "type": "Feature",
  "properties": {
    "iso:country":"US",
    "sg:address":"126 Hedley Ave",
    "sg:city":"Johnston",
    "sg:classifiers":[
        {
            "category":"Shopping",
            "subcategory":"Jewelry",
            "type":"Retail Goods"
        }
    ],
    "sg:phone":"+1 401 942 3269",
    "sg:postcode":"02919",
    "sg:province":"RI",
    "wof:name":"Jewelry Jobbers",
    "wof:placetype":"venue"
},
  "geometry": {"coordinates":[-71.46718199999999,41.830406],"type":"Point"}
}