{
  "type": "Feature",
  "properties": {
    "iso:country":"US",
    "sg:address":"1 Richmond St",
    "sg:city":"Providence",
    "sg:classifiers":[
        {
            "category":"Wholesale",
            "subcategory":"Medical Equipment & Supplies",
            "type":"Manufacturing & Wholesale Goods"
        }
    ],
    "sg:phone":"+1 401 751 7313",
    "sg:postcode":"02903",
    "sg:province":"RI",
    "sg:tags":[
        "hospital"
    ],
    "wof:name":"United Med Worldwide",
    "wof:placetype":"venue"
},
  "geometry": {"coordinates":[-71.41185900000001,41.820628],"type":"Point"}
}