{
  "type": "Feature",
  "properties": {
    "addr:full":"1000 Smith St Providence RI 02908",
    "addr:housenumber":"1000",
    "addr:postcode":"02908",
    "addr:street":"Smith St",
    "iso:country":"US",
    "sg:address":"1000 Smith St",
    "sg:city":"Providence",
    "sg:classifiers":[
        {
            "category":"Professional",
            "subcategory":"Lawyer & Legal Services",
            "type":"Services"
        }
    ],
    "sg:phone":"+1 401 454 1200",
    "sg:postcode":"02908",
    "sg:province":"RI",
    "wof:name":"Spinella David M Atty",
    "wof:placetype":"venue"
},
  "geometry": {"coordinates":[-71.44450399999999,41.8423],"type":"Point"}
}