{
  "type": "Feature",
  "properties": {
    "iso:country":"US",
    "sg:address":"256 East St",
    "sg:city":"Cranston",
    "sg:classifiers":[
        {
            "category":"Personal",
            "subcategory":"Beauty Salon",
            "type":"Services"
        }
    ],
    "sg:phone":"+1 401 463 7706",
    "sg:postcode":"02920",
    "sg:province":"RI",
    "sg:tags":[
        "shop"
    ],
    "wof:name":"Van Dyke Hair Salon",
    "wof:placetype":"venue"
},
  "geometry": {"coordinates":[-71.468192,41.733584],"type":"Point"}
}