{
  "type": "Feature",
  "properties": {
    "iso:country":"US",
    "sg:address":"1 Barden Ln",
    "sg:city":"Warren",
    "sg:classifiers":[
        {
            "category":"Health Services",
            "subcategory":"Medical Lab",
            "type":"Services"
        }
    ],
    "sg:phone":"+1 401 245 6488",
    "sg:postcode":"02885",
    "sg:province":"RI",
    "sg:tags":[
        "laboratory"
    ],
    "wof:name":"Poly Load Laboratories Inc",
    "wof:placetype":"venue"
},
  "geometry": {"coordinates":[-71.27284899999999,41.721435],"type":"Point"}
}