{
  "type": "Feature",
  "properties": {
    "iso:country":"US",
    "sg:address":"101 Pleasant View Ave",
    "sg:city":"Smithfield",
    "sg:classifiers":[
        {
            "category":"Autos & Motor Vehicles",
            "subcategory":"Fuel & Gas Station",
            "type":"Retail Goods"
        }
    ],
    "sg:phone":"+1 401 231 0390",
    "sg:postcode":"02917",
    "sg:province":"RI",
    "sg:tags":[
        "station"
    ],
    "wof:name":"Sunoco",
    "wof:placetype":"venue"
},
  "geometry": {"coordinates":[-71.54188499999999,41.887806],"type":"Point"}
}