{
  "type": "Feature",
  "properties": {
    "iso:country":"US",
    "sg:address":"6 Davison Ave",
    "sg:city":"Woonsocket",
    "sg:classifiers":[
        {
            "category":"Manufacturing",
            "subcategory":"Tools & Machinery",
            "type":"Manufacturing & Wholesale Goods"
        }
    ],
    "sg:phone":"+1 401 769 2233",
    "sg:postcode":"02895",
    "sg:province":"RI",
    "sg:tags":[
        "control",
        "mfg"
    ],
    "wof:name":"Cole Hersee Company",
    "wof:placetype":"venue"
},
  "geometry": {"coordinates":[-71.49915799999999,42.002876],"type":"Point"}
}