{
  "type": "Feature",
  "properties": {
    "addr:full":"730 York Ave Pawtucket RI 02861",
    "addr:housenumber":"730",
    "addr:postcode":"02861",
    "addr:street":"York Ave",
    "iso:country":"US",
    "sg:address":"730 York Ave",
    "sg:city":"Pawtucket",
    "sg:classifiers":[
        {
            "category":"Manufacturing",
            "subcategory":"Paper Products",
            "type":"Manufacturing & Wholesale Goods"
        }
    ],
    "sg:phone":"+1 401 725 9700",
    "sg:postcode":"02861",
    "sg:province":"RI",
    "sg:tags":[
        "converted",
        "coated",
        "prod",
        "laminated"
    ],
    "sg:website":"www.ecofibers.com",
    "wof:name":"Narragansett Coated Paper Corp",
    "wof:placetype":"venue"
},
  "geometry": {"coordinates":[-71.362762,41.877583],"type":"Point"}
}