{
  "type": "Feature",
  "properties": {
    "iso:country":"US",
    "sg:address":"400 Franklin St",
    "sg:city":"Bristol",
    "sg:classifiers":[
        {
            "category":"Manufacturing",
            "subcategory":"Tools & Machinery",
            "type":"Manufacturing & Wholesale Goods"
        }
    ],
    "sg:phone":"+1 401 253 1240",
    "sg:postcode":"02809",
    "sg:province":"RI",
    "sg:tags":[
        "machine",
        "shop"
    ],
    "wof:name":"Accu-Tek Inc",
    "wof:placetype":"venue"
},
  "geometry": {"coordinates":[-71.266983,41.675835],"type":"Point"}
}