{
  "type": "Feature",
  "properties": {
    "addr:full":"131 Asa Pond Rd South Kingstown RI 02879",
    "addr:housenumber":"131",
    "addr:postcode":"02879",
    "addr:street":"Asa Pond Rd",
    "iso:country":"US",
    "sg:address":"131 Asa Pond Rd",
    "sg:city":"South Kingstown",
    "sg:classifiers":[
        {
            "category":"Government",
            "subcategory":"Fire Station",
            "type":"Public Place"
        }
    ],
    "sg:phone":"+1 401 789 8354",
    "sg:postcode":"02879",
    "sg:province":"RI",
    "sg:tags":[
        "department"
    ],
    "wof:name":"Union Fire Dist Of S Kingstown",
    "wof:placetype":"venue"
},
  "geometry": {"coordinates":[-71.51490800000001,41.455982],"type":"Point"}
}