{
  "type": "Feature",
  "properties": {
    "iso:country":"US",
    "sg:address":"107 Danielson Pike",
    "sg:city":"North Scituate",
    "sg:classifiers":[
        {
            "category":"Professional",
            "subcategory":"Research",
            "type":"Services"
        }
    ],
    "sg:phone":"+1 401 647 7881",
    "sg:postcode":"02857",
    "sg:province":"RI",
    "sg:tags":[
        "researching"
    ],
    "wof:name":"McGuire Research Associates",
    "wof:placetype":"venue"
},
  "geometry": {"coordinates":[-71.583792,41.831839],"type":"Point"}
}