{
  "type": "Feature",
  "properties": {
    "addr:full":"1515 Smith St North Providence RI 02911",
    "addr:housenumber":"1515",
    "addr:postcode":"02911",
    "addr:street":"Smith St",
    "iso:country":"US",
    "sg:address":"1515 Smith St",
    "sg:city":"North Providence",
    "sg:classifiers":[
        {
            "category":"Health Services",
            "subcategory":"Doctor",
            "type":"Services"
        }
    ],
    "sg:phone":"+1 401 354 4384",
    "sg:postcode":"02911",
    "sg:province":"RI",
    "sg:tags":[
        "medicine",
        "internal"
    ],
    "wof:name":"Paolella Robert A MD",
    "wof:placetype":"venue"
},
  "geometry": {"coordinates":[-71.460701,41.8498],"type":"Point"}
}