{
  "type": "Feature",
  "properties": {
    "iso:country":"US",
    "sg:address":"1 Ann St",
    "sg:city":"Newport",
    "sg:classifiers":[
        {
            "category":"Organizations",
            "subcategory":"Religious Organization",
            "type":"Services"
        }
    ],
    "sg:phone":"+1 401 846 0660",
    "sg:postcode":"02840",
    "sg:province":"RI",
    "sg:tags":[
        "church"
    ],
    "sg:website":"www.trinitynewport.org",
    "wof:name":"Trinity Church",
    "wof:placetype":"venue"
},
  "geometry": {"coordinates":[-71.31289599999999,41.483443],"type":"Point"}
}