{
  "type": "Feature",
  "properties": {
    "iso:country":"US",
    "sg:address":"51 Silver Spring St",
    "sg:city":"Providence",
    "sg:classifiers":[
        {
            "category":"Personal",
            "subcategory":"Nail Salon",
            "type":"Services"
        }
    ],
    "sg:phone":"+1 401 272 0469",
    "sg:postcode":"02904",
    "sg:province":"RI",
    "wof:name":"Regal Nail Salon Spa",
    "wof:placetype":"venue"
},
  "geometry": {"coordinates":[-71.41748,41.845537],"type":"Point"}
}