{
  "type": "Feature",
  "properties": {
    "iso:country":"US",
    "sg:address":"99 Wayland Ave",
    "sg:city":"Providence",
    "sg:classifiers":[
        {
            "category":"Professional",
            "subcategory":"Lawyer & Legal Services",
            "type":"Services"
        }
    ],
    "sg:phone":"+1 401 351 3666",
    "sg:postcode":"02906",
    "sg:province":"RI",
    "wof:name":"Norman Bolotow Atty",
    "wof:placetype":"venue"
},
  "geometry": {"coordinates":[-71.388362,41.826217],"type":"Point"}
}