{
  "type": "Feature",
  "properties": {
    "iso:country":"US",
    "sg:address":"1249 Main St",
    "sg:city":"West Warwick",
    "sg:classifiers":[
        {
            "category":"Wholesale",
            "subcategory":"Electrical",
            "type":"Manufacturing & Wholesale Goods"
        }
    ],
    "sg:phone":"+1 401 821 0278",
    "sg:postcode":"02893",
    "sg:province":"RI",
    "sg:tags":[
        "equipment",
        "electric",
        "supply"
    ],
    "wof:name":"Mastro Electric Supply Co Inc",
    "wof:placetype":"venue"
},
  "geometry": {"coordinates":[-71.52400900000001,41.704959],"type":"Point"}
}