{
  "type": "Feature",
  "properties": {
    "iso:country":"US",
    "sg:address":"1360 W Main Rd",
    "sg:city":"Middletown",
    "sg:classifiers":[
        {
            "category":"Banks & Credit Unions",
            "subcategory":"Bank",
            "type":"Services"
        }
    ],
    "sg:phone":"+1 401 849 7556",
    "sg:postcode":"02842",
    "sg:province":"RI",
    "wof:name":"Citizens Bank",
    "wof:placetype":"venue"
},
  "geometry": {"coordinates":[-71.293204,41.532922],"type":"Point"}
}