{
  "type": "Feature",
  "properties": {
    "iso:country":"US",
    "sg:address":"1560 Hartford Ave",
    "sg:city":"Johnston",
    "sg:classifiers":[
        {
            "category":"Building & Trades",
            "subcategory":"Construction",
            "type":"Services"
        }
    ],
    "sg:phone":"+1 401 432 4110",
    "sg:postcode":"02919",
    "sg:province":"RI",
    "sg:tags":[
        "shed",
        "utility"
    ],
    "wof:name":"Rosewood Structures",
    "wof:placetype":"venue"
},
  "geometry": {"coordinates":[-71.50533,41.825169],"type":"Point"}
}