{
  "type": "Feature",
  "properties": {
    "iso:country":"US",
    "sg:address":"50 Birch St",
    "sg:city":"Cranston",
    "sg:classifiers":[
        {
            "category":"Government",
            "subcategory":"Office",
            "type":"Public Place"
        }
    ],
    "sg:phone":"+1 401 944 7210",
    "sg:postcode":"02920",
    "sg:province":"RI",
    "sg:tags":[
        "housing",
        "program"
    ],
    "wof:name":"Cranston Housing Authority",
    "wof:placetype":"venue"
},
  "geometry": {"coordinates":[-71.4485,41.80051],"type":"Point"}
}