{
  "type": "Feature",
  "properties": {
    "iso:country":"US",
    "sg:address":"99 Cumberland St",
    "sg:city":"Woonsocket",
    "sg:classifiers":[
        {
            "category":"Insurance",
            "subcategory":"Hazard Insurance",
            "type":"Services"
        }
    ],
    "sg:phone":"+1 401 765 5040",
    "sg:postcode":"02895",
    "sg:province":"RI",
    "sg:tags":[
        "commercial",
        "business"
    ],
    "wof:name":"F & F Insurance Agency Inc",
    "wof:placetype":"venue"
},
  "geometry": {"coordinates":[-71.502432,42.00775],"type":"Point"}
}