{
  "type": "Feature",
  "properties": {
    "iso:country":"US",
    "sg:address":"28 White Ln",
    "sg:city":"Hope",
    "sg:classifiers":[
        {
            "category":"Arts & Performance",
            "subcategory":"Theater",
            "type":"Entertainment"
        }
    ],
    "sg:phone":"+1 401 826 2263",
    "sg:postcode":"02831",
    "sg:province":"RI",
    "sg:tags":[
        "group"
    ],
    "wof:name":"Stanley Enterpeise Svc & Sls",
    "wof:placetype":"venue"
},
  "geometry": {"coordinates":[-71.562989,41.7381],"type":"Point"}
}