{
  "type": "Feature",
  "properties": {
    "iso:country":"US",
    "sg:address":"263 Academy Ave",
    "sg:city":"Providence",
    "sg:classifiers":[
        {
            "category":"Home & Garden",
            "subcategory":"Household Appliances",
            "type":"Retail Goods"
        }
    ],
    "sg:phone":"+1 401 351 0510",
    "sg:postcode":"02908",
    "sg:province":"RI",
    "sg:tags":[
        "repair",
        "electrical"
    ],
    "wof:name":"Danny's Appliance Sales",
    "wof:placetype":"venue"
},
  "geometry": {"coordinates":[-71.444603,41.831902],"type":"Point"}
}