{
  "type": "Feature",
  "properties": {
    "addr:full":"1509 Mendon Rd Cumberland RI 02864",
    "addr:housenumber":"1509",
    "addr:postcode":"02864",
    "addr:street":"Mendon Rd",
    "iso:country":"US",
    "sg:address":"1509 Mendon Rd",
    "sg:city":"Cumberland",
    "sg:classifiers":[
        {
            "category":"Social Services",
            "subcategory":"Child Care",
            "type":"Services"
        }
    ],
    "sg:phone":"+1 401 333 6558",
    "sg:postcode":"02864",
    "sg:province":"RI",
    "wof:name":"Highlands Child Care Ctr",
    "wof:placetype":"venue"
},
  "geometry": {"coordinates":[-71.43281399999999,41.940005],"type":"Point"}
}