{
  "type": "Feature",
  "properties": {
    "iso:country":"US",
    "sg:address":"139 Broad St",
    "sg:city":"Pawtucket",
    "sg:classifiers":[
        {
            "category":"Communications",
            "subcategory":"Radio Station",
            "type":"Services"
        }
    ],
    "sg:phone":"+1 401 722 3900",
    "sg:postcode":"02860",
    "sg:province":"RI",
    "sg:tags":[
        "company",
        "broadcasting"
    ],
    "wof:name":"Mac's Radio & Television Co",
    "wof:placetype":"venue"
},
  "geometry": {"coordinates":[-71.386449,41.88099],"type":"Point"}
}