{
  "type": "Feature",
  "properties": {
    "addr:full":"14 Stevens Rd Cranston RI 02910",
    "addr:housenumber":"14",
    "addr:postcode":"02910",
    "addr:street":"Stevens Rd",
    "iso:country":"US",
    "sg:address":"14 Stevens Rd",
    "sg:city":"Cranston",
    "sg:classifiers":[
        {
            "category":"Arena",
            "subcategory":"Sports Club",
            "type":"Entertainment"
        }
    ],
    "sg:phone":"+1 401 943 4269",
    "sg:postcode":"02910",
    "sg:province":"RI",
    "sg:tags":[
        "representation",
        "athlete"
    ],
    "wof:name":"Nexstar Sports Agency",
    "wof:placetype":"venue"
},
  "geometry": {"coordinates":[-71.445162,41.778544],"type":"Point"}
}