{
  "type": "Feature",
  "properties": {
    "addr:full":"23 Lucas Ave Newport RI 02840",
    "addr:housenumber":"23",
    "addr:postcode":"02840",
    "addr:street":"Lucas Ave",
    "iso:country":"US",
    "sg:address":"23 Lucas Ave",
    "sg:city":"Newport",
    "sg:classifiers":[
        {
            "category":"Building & Trades",
            "subcategory":"Landscaping Services",
            "type":"Services"
        }
    ],
    "sg:phone":"+1 401 847 2081",
    "sg:postcode":"02840",
    "sg:province":"RI",
    "sg:tags":[
        "landscape",
        "contractor"
    ],
    "wof:name":"T J Brown Inc",
    "wof:placetype":"venue"
},
  "geometry": {"coordinates":[-71.313751,41.473635],"type":"Point"}
}