{
  "type": "Feature",
  "properties": {
    "iso:country":"US",
    "sg:address":"29 Lark Industrial Dr",
    "sg:city":"Greenville",
    "sg:classifiers":[
        {
            "category":"Wholesale",
            "subcategory":"Non-durable Goods",
            "type":"Manufacturing & Wholesale Goods"
        }
    ],
    "sg:phone":"+1 401 349 4940",
    "sg:postcode":"02828",
    "sg:province":"RI",
    "sg:tags":[
        "advertising"
    ],
    "wof:name":"Coast To Coast Promotional Prd",
    "wof:placetype":"venue"
},
  "geometry": {"coordinates":[-71.535031,41.86847],"type":"Point"}
}