{
  "type": "Feature",
  "properties": {
    "addr:full":"5 Blacksmith Rd Cumberland RI 02864",
    "addr:housenumber":"5",
    "addr:postcode":"02864",
    "addr:street":"Blacksmith Rd",
    "iso:country":"US",
    "sg:address":"5 Blacksmith Rd",
    "sg:city":"Cumberland",
    "sg:classifiers":[
        {
            "category":"Professional",
            "type":"Services"
        }
    ],
    "sg:phone":"+1 401 334 3519",
    "sg:postcode":"02864",
    "sg:province":"RI",
    "sg:tags":[
        "establishment"
    ],
    "wof:name":"Fluoro Ware",
    "wof:placetype":"venue"
},
  "geometry": {"coordinates":[-71.38751999999999,41.946498],"type":"Point"}
}