{
  "type": "Feature",
  "properties": {
    "addr:full":"171 Mattity Rd North Smithfield RI 02896",
    "addr:housenumber":"171",
    "addr:postcode":"02896",
    "addr:street":"Mattity Rd",
    "iso:country":"US",
    "sg:address":"171 Mattity Rd",
    "sg:city":"North Smithfield",
    "sg:classifiers":[
        {
            "category":"Building & Trades",
            "subcategory":"Cleaning & Sanitation",
            "type":"Services"
        }
    ],
    "sg:phone":"+1 401 766 8811",
    "sg:postcode":"02896",
    "sg:province":"RI",
    "sg:tags":[
        "maintenance"
    ],
    "wof:name":"Delta Maintenance Co Inc",
    "wof:placetype":"venue"
},
  "geometry": {"coordinates":[-71.57865,41.959081],"type":"Point"}
}