{
  "type": "Feature",
  "properties": {
    "iso:country":"US",
    "sg:address":"14 Grant Ln",
    "sg:city":"Cumberland",
    "sg:classifiers":[
        {
            "category":"Professional",
            "subcategory":"Computer Services",
            "type":"Services"
        }
    ],
    "sg:phone":"+1 401 334 9013",
    "sg:postcode":"02864",
    "sg:province":"RI",
    "sg:tags":[
        "datum"
    ],
    "wof:name":"Corporate Data Services Inc",
    "wof:placetype":"venue"
},
  "geometry": {"coordinates":[-71.386207,41.968068],"type":"Point"}
}