{
  "type": "Feature",
  "properties": {
    "iso:country":"US",
    "sg:address":"21 Powder Hill Rd",
    "sg:city":"Lincoln",
    "sg:classifiers":[
        {
            "category":"Professional",
            "subcategory":"Computer Services",
            "type":"Services"
        }
    ],
    "sg:phone":"+1 401 334 4602",
    "sg:postcode":"02865",
    "sg:province":"RI",
    "sg:tags":[
        "consultant",
        "designer"
    ],
    "wof:name":"Design Net Inc",
    "wof:placetype":"venue"
},
  "geometry": {"coordinates":[-71.480379,41.921222],"type":"Point"}
}