{
  "type": "Feature",
  "properties": {
    "addr:full":"39 Parker St Woonsocket RI 02895",
    "addr:housenumber":"39",
    "addr:postcode":"02895",
    "addr:street":"Parker St",
    "iso:country":"US",
    "sg:address":"39 Parker St",
    "sg:city":"Woonsocket",
    "sg:classifiers":[
        {
            "category":"Retail",
            "subcategory":"Auto Repair",
            "type":"Services"
        }
    ],
    "sg:phone":"+1 401 762 3636",
    "sg:postcode":"02895",
    "sg:province":"RI",
    "sg:tags":[
        "body",
        "automobile",
        "used",
        "painting"
    ],
    "wof:name":"Plante's Auto Body & Sales",
    "wof:placetype":"venue"
},
  "geometry": {"coordinates":[-71.51979900000001,41.996926],"type":"Point"}
}