{
  "type": "Feature",
  "properties": {
    "iso:country":"US",
    "sg:address":"232 Waseca Ave",
    "sg:city":"Barrington",
    "sg:classifiers":[
        {
            "category":"Sports & Exercise",
            "subcategory":"Gym",
            "type":"Entertainment"
        }
    ],
    "sg:phone":"+1 401 247 0025",
    "sg:postcode":"02806",
    "sg:province":"RI",
    "sg:tags":[
        "club",
        "health",
        "studio",
        "gymnasium"
    ],
    "wof:name":"Balance Fitness For Women",
    "wof:placetype":"venue"
},
  "geometry": {"coordinates":[-71.311108,41.737969],"type":"Point"}
}