{
  "type": "Feature",
  "properties": {
    "iso:country":"US",
    "sg:address":"101 Comstock Pkwy",
    "sg:city":"Cranston",
    "sg:classifiers":[
        {
            "category":"Shopping",
            "subcategory":"Jewelry",
            "type":"Retail Goods"
        },
        {
            "category":"Wholesale",
            "subcategory":"Jewelry",
            "type":"Manufacturing & Wholesale Goods"
        }
    ],
    "sg:phone":"+1 401 943 7330",
    "sg:postcode":"02921",
    "sg:province":"RI",
    "sg:tags":[
        "findings"
    ],
    "wof:name":"Spinco Inc",
    "wof:placetype":"venue"
},
  "geometry": {"coordinates":[-71.51538499999999,41.782412],"type":"Point"}
}