{
  "type": "Feature",
  "properties": {
    "iso:country":"US",
    "sg:address":"30 Bedson Rd",
    "sg:city":"Cranston",
    "sg:classifiers":[
        {
            "category":"Freight",
            "type":"Transportation"
        }
    ],
    "sg:phone":"+1 401 781 8715",
    "sg:postcode":"02910",
    "sg:province":"RI",
    "sg:website":"www.lily.com",
    "wof:name":"Lily Transportation",
    "wof:placetype":"venue"
},
  "geometry": {"coordinates":[-71.42677500000001,41.766024],"type":"Point"}
}