{
  "type": "Feature",
  "properties": {
    "iso:country":"US",
    "sg:address":"3 Coventry Dr",
    "sg:city":"Coventry",
    "sg:classifiers":[
        {
            "category":"Professional",
            "type":"Services"
        }
    ],
    "sg:phone":"+1 401 823 5425",
    "sg:postcode":"02816",
    "sg:province":"RI",
    "sg:tags":[
        "establishment"
    ],
    "wof:name":"Nick Cerio's Kenpo Karate",
    "wof:placetype":"venue"
},
  "geometry": {"coordinates":[-71.565727,41.68131],"type":"Point"}
}