{
  "type": "Feature",
  "properties": {
    "iso:country":"US",
    "sg:address":"1160 Pawtucket Ave",
    "sg:city":"Rumford",
    "sg:classifiers":[
        {
            "category":"Autos & Motor Vehicles",
            "subcategory":"Automobile Sales",
            "type":"Retail Goods"
        }
    ],
    "sg:phone":"+1 401 435 5466",
    "sg:postcode":"02916",
    "sg:province":"RI",
    "sg:tags":[
        "limo"
    ],
    "wof:name":"Starlight Limosine Service",
    "wof:placetype":"venue"
},
  "geometry": {"coordinates":[-71.35011,41.842194],"type":"Point"}
}