{
  "type": "Feature",
  "properties": {
    "addr:full":"125 Central Pike Foster RI 02825",
    "addr:housenumber":"125",
    "addr:postcode":"02825",
    "addr:street":"Central Pike",
    "iso:country":"US",
    "sg:address":"125 Central Pike",
    "sg:city":"Foster",
    "sg:classifiers":[
        {
            "category":"Professional",
            "type":"Services"
        }
    ],
    "sg:phone":"+1 401 647 7326",
    "sg:postcode":"02825",
    "sg:province":"RI",
    "wof:name":"Machinex Corp",
    "wof:placetype":"venue"
},
  "geometry": {"coordinates":[-71.730794,41.799171],"type":"Point"}
}