{
  "type": "Feature",
  "properties": {
    "addr:full":"188 Mathewson St Providence RI 02903",
    "addr:housenumber":"188",
    "addr:postcode":"02903",
    "addr:street":"Mathewson St",
    "iso:country":"US",
    "sg:address":"188 Mathewson St",
    "sg:city":"Providence",
    "sg:classifiers":[
        {
            "category":"Shopping",
            "subcategory":"Clothing, Apparel, & Fashions",
            "type":"Retail Goods"
        },
        {
            "category":"Shopping",
            "subcategory":"Shoes",
            "type":"Retail Goods"
        }
    ],
    "sg:phone":"+1 401 331 2562",
    "sg:postcode":"02903",
    "sg:province":"RI",
    "sg:tags":[
        "clothing",
        "women's"
    ],
    "sg:website":"parksplaza.com/home",
    "wof:name":"Park's Plaza",
    "wof:placetype":"venue"
},
  "geometry": {"coordinates":[-71.412903,41.821499],"type":"Point"}
}