{
  "type": "Feature",
  "properties": {
    "iso:country":"US",
    "sg:address":"231 Providence St",
    "sg:city":"Woonsocket",
    "sg:classifiers":[
        {
            "category":"Retail",
            "subcategory":"Auto Repair",
            "type":"Services"
        }
    ],
    "sg:phone":"+1 401 767 2886",
    "sg:postcode":"02895",
    "sg:province":"RI",
    "sg:tags":[
        "repairing",
        "automobile"
    ],
    "wof:name":"Broad Street Garage",
    "wof:placetype":"venue"
},
  "geometry": {"coordinates":[-71.521253,41.993412],"type":"Point"}
}