{
  "type": "Feature",
  "properties": {
    "addr:full":"3 Carol Dr Lincoln RI 02865",
    "addr:housenumber":"3",
    "addr:postcode":"02865",
    "addr:street":"Carol Dr",
    "iso:country":"US",
    "sg:address":"3 Carol Dr",
    "sg:city":"Lincoln",
    "sg:classifiers":[
        {
            "category":"Building & Trades",
            "subcategory":"Electrical",
            "type":"Services"
        }
    ],
    "sg:phone":"+1 401 333 4848",
    "sg:postcode":"02865",
    "sg:province":"RI",
    "sg:tags":[
        "wire",
        "products-wholesale",
        "manufacturer"
    ],
    "sg:website":"http://www.generalcable.com",
    "wof:name":"Lincoln, Ri Plant",
    "wof:placetype":"venue"
},
  "geometry": {"coordinates":[-71.480836,41.922869],"type":"Point"}
}