{
  "type": "Feature",
  "properties": {
    "addr:full":"7 Bay St Westerly RI 02891",
    "addr:housenumber":"7",
    "addr:postcode":"02891",
    "addr:street":"Bay St",
    "iso:country":"US",
    "sg:address":"7 Bay St",
    "sg:city":"Westerly",
    "sg:classifiers":[
        {
            "category":"Shopping",
            "subcategory":"Books",
            "type":"Retail Goods"
        }
    ],
    "sg:phone":"+1 401 315 3633",
    "sg:postcode":"02891",
    "sg:province":"RI",
    "sg:tags":[
        "dealer"
    ],
    "wof:name":"Book & Tackle",
    "wof:placetype":"venue"
},
  "geometry": {"coordinates":[-71.85699,41.311476],"type":"Point"}
}