{
  "type": "Feature",
  "properties": {
    "iso:country":"US",
    "sg:address":"36 Elmhurst St",
    "sg:city":"Warwick",
    "sg:classifiers":[
        {
            "category":"Professional",
            "subcategory":"Art Services",
            "type":"Services"
        }
    ],
    "sg:phone":"+1 401 738 9840",
    "sg:postcode":"02889",
    "sg:province":"RI",
    "sg:tags":[
        "commercial",
        "design"
    ],
    "wof:name":"Perfect Graphics Plus",
    "wof:placetype":"venue"
},
  "geometry": {"coordinates":[-71.410827,41.734374],"type":"Point"}
}