{
  "type": "Feature",
  "properties": {
    "addr:full":"1 Social St Woonsocket RI 02895",
    "addr:postcode":"02895",
    "addr:street":"Social St",
    "iso:country":"US",
    "sg:address":"1 Social St",
    "sg:city":"Woonsocket",
    "sg:classifiers":[
        {
            "category":"Professional",
            "subcategory":"Lawyer & Legal Services",
            "type":"Services"
        }
    ],
    "sg:phone":"+1 401 769 0737",
    "sg:postcode":"02895",
    "sg:province":"RI",
    "sg:tags":[
        "attorney"
    ],
    "wof:name":"Pierre G Rondeau",
    "wof:placetype":"venue"
},
  "geometry": {"coordinates":[-71.511948,42.00597],"type":"Point"}
}