{
  "type": "Feature",
  "properties": {
    "iso:country":"US",
    "sg:address":"189 Canal St",
    "sg:city":"Providence",
    "sg:classifiers":[
        {
            "category":"Real Estate",
            "subcategory":"Real Estate Operator",
            "type":"Services"
        }
    ],
    "sg:phone":"+1 401 751 4700",
    "sg:postcode":"02903",
    "sg:province":"RI",
    "sg:tags":[
        "owner",
        "residential",
        "commercial"
    ],
    "wof:name":"Shawomet Holding Associates",
    "wof:placetype":"venue"
},
  "geometry": {"coordinates":[-71.41029399999999,41.827746],"type":"Point"}
}